Workbook
Name Appendix_1_Range: 'APPENDIX 1'!$B$3:$R$51
Name Appendix_10_Range: 'APPENDIX 10'!$B$3:$Q$37
Name Appendix_11_Range: 'APPENDIX 11'!$B$3:$Q$37
Name Appendix_12_Range: 'APPENDIX 12'!$B$3:$Q$37
Name Appendix_13_Range: 'APPENDIX 13'!$B$3:$Q$37
Name Appendix_14_Range: 'APPENDIX 14'!$B$3:$Q$37
Name Appendix_15_Range: 'APPENDIX 15'!$B$3:$R$50
Name Appendix_16_Range: 'APPENDIX 16'!$B$3:$Q$50
Name Appendix_17_Range: 'APPENDIX 17'!$B$3:$Q$50
Name Appendix_18_Range: 'APPENDIX 18'!$B$3:$Q$50
Name Appendix_19_Range: 'APPENDIX 19'!$B$3:$Q$50
Name Appendix_2_Range: 'APPENDIX 2'!$B$3:$R$38
Name Appendix_20_Range: 'APPENDIX 20'!$B$3:$Q$50
Name Appendix_21_Range: 'APPENDIX 21'!$B$3:$Q$50
Name Appendix_22_Range: 'APPENDIX 22'!$B$3:$G$24
Name Appendix_23_Range: 'APPENDIX 23Micro'!$B$3:$F$13
Name Appendix_24_Range: 'APPENDIX 24Micro'!$B$3:$F$13
Name Appendix_25_Range: 'APPENDIX 25Micro'!$B$3:$F$13
Name Appendix_26_Range: 'APPENDIX 26Micro'!$B$3:$F$13
Name Appendix_27_Range: 'APPENDIX 27Micro'!$B$3:$F$13
Name Appendix_28_Range: 'APPENDIX 23'!$B$3:$Q$13
Name Appendix_29i_Range: 'APPENDIX 24 i'!$B$4:$L$44
Name Appendix_29ii_Range: 'APPENDIX 24 ii'!$B$3:$L$44
Name Appendix_29iii_Range: 'APPENDIX 24 iii'!$B$3:$K$44
Name Appendix_3_Range: 'APPENDIX 3'!$B$3:$R$12
Name Appendix_30i_Range: 'APPENDIX 25 i'!$B$4:$L$42
Name Appendix_30ii_Range: 'APPENDIX 25 ii'!$B$3:$L$42
Name Appendix_30iii_Range: 'APPENDIX 25 iii'!$B$3:$L$42
Name Appendix_30iv_Range: 'APPENDIX 25 iv'!$B$3:$N$42
Name Appendix_31i_Range: 'APPENDIX 26 i'!$B$4:$I$42
Name Appendix_4_Range: 'APPENDIX 4'!$B$3:$L$37
Name Appendix_5_Range: 'APPENDIX 5'!$B$3:$K$37
Name Appendix_6_Range: 'APPENDIX 6'!$B$3:$Q$37
Name Appendix_7_Range: 'APPENDIX 7'!$B$3:$Q$37
Name Appendix_8_Range: 'APPENDIX 8'!$B$3:$Q$37
Name Appendix_9_Range: 'APPENDIX 9'!$B$3:$Q$37
Name Details_Range: Details!$C$2:$J$21

Sheet Details
E6: INSURANCE REGULATORY AUTHORITY
E11: TYPE OF INDUSTRY STATISTICS | F11: Quarterly (Unaudited)
E13: QUARTER | F13: 1
E15: YEAR | F15: 2025
E18: PERIOD ENDED | F18: 31.03.2025

Sheet Reliance & Limitations
B3: RELIANCE AND LIMITATIONS
B4: The insurance information contained in this workbook has been extracted from the quarterly unaudited returns submitted to the Authority in line with Section 54 of the Insurance Act. No adjustments have been made to the returns’ data except where necessary in consultation with the affected insurer(s) or reinsurer(s). The publication of any summary of the returns in this report does not necessarily mean that the returns so summarized have satisfied all the requirements of the Insurance Act, or that the Commissioner of Insurance approves the accuracy or the contents of the returns Where necessary, figures have been adjusted to eliminate errors in totals due to rounding off, and are given in thousands Kenya shillings (‘000’ KES) except where otherwise stated. The report incorporates data from all insurers and reinsurers except for Jubilee Allianz General Insurance Limited, Invesco Assurance Company and Corporate Insurance Company Limited-Life due to non-submission of 2024 Q2 unaudited returns.

Sheet Table of Contents
B3: INSURANCE REGULATORY AUTHORITY
B5: 2025 QUARTER ONE STATISTICS
B6: TABLE OF CONTENTS
B7: Link | C7: Description
B8: APPENDIX 1 | C8: =_xlfn.CONCAT("SUMMARY OF GENERAL INSURANCE BUSINESS PROFIT & LOSS ACCOUNTS FOR THE PERIOD ENDED"," ",Details!F18) -> SUMMARY OF GENERAL INSURANCE BUSINESS PROFIT & LOSS ACCOUNTS FOR THE PERIOD ENDED 31.03.2025
B9: APPENDIX 2 | C9: =_xlfn.CONCAT("SUMMARY OF LONG TERM INSURANCE BUSINESS PROFIT & LOSS ACCOUNTS FOR THE PERIOD ENDED"," ",Details!$F$18) -> SUMMARY OF LONG TERM INSURANCE BUSINESS PROFIT & LOSS ACCOUNTS FOR THE PERIOD ENDED 31.03.2025
B10: APPENDIX 3 | C10: =_xlfn.CONCAT("SUMMARY OF MICRO INSURANCE BUSINESS PROFIT & LOSS ACCOUNTS FOR THE PERIOD ENDED"," ",Details!$F$18) -> SUMMARY OF MICRO INSURANCE BUSINESS PROFIT & LOSS ACCOUNTS FOR THE PERIOD ENDED 31.03.2025
B11: APPENDIX 4 | C11: =_xlfn.CONCAT("SUMMARY OF LONG TERM INSURANCE BUSINESS GROSS PREMIUM INCOME FOR THE PERIOD ENDED"," ",Details!F18) -> SUMMARY OF LONG TERM INSURANCE BUSINESS GROSS PREMIUM INCOME FOR THE PERIOD ENDED 31.03.2025
B12: APPENDIX 5 | C12: =_xlfn.CONCAT("SUMMARY OF LONG TERM INSURANCE BUSINESS MARKET SHARE PER CLASS FOR THE PERIOD ENDED"," ",Details!F18) -> SUMMARY OF LONG TERM INSURANCE BUSINESS MARKET SHARE PER CLASS FOR THE PERIOD ENDED 31.03.2025
B13: APPENDIX 6 | C13: =_xlfn.CONCAT("SUMMARY OF LIFE ASSURANCE BUSINESS REVENUE ACCOUNTS FOR THE PERIOD ENDED"," ",Details!F18) -> SUMMARY OF LIFE ASSURANCE BUSINESS REVENUE ACCOUNTS FOR THE PERIOD ENDED 31.03.2025
B14: APPENDIX 7 | C14: =_xlfn.CONCAT("SUMMARY OF ANNUITIES BUSINESS REVENUE ACCOUNTS FOR THE PERIOD ENDED"," ",Details!F18) -> SUMMARY OF ANNUITIES BUSINESS REVENUE ACCOUNTS FOR THE PERIOD ENDED 31.03.2025
B15: APPENDIX 8 | C15: =_xlfn.CONCAT("SUMMARY OF GROUP LIFE BUSINESS REVENUE ACCOUNTS FOR THE PERIOD ENDED"," ",Details!F18) -> SUMMARY OF GROUP LIFE BUSINESS REVENUE ACCOUNTS FOR THE PERIOD ENDED 31.03.2025
B16: APPENDIX 9 | C16: =_xlfn.CONCAT("SUMMARY OF GROUP CREDIT BUSINESS REVENUE ACCOUNTS FOR THE PERIOD ENDED"," ",Details!F18) -> SUMMARY OF GROUP CREDIT BUSINESS REVENUE ACCOUNTS FOR THE PERIOD ENDED 31.03.2025
B17: APPENDIX 10 | C17: =_xlfn.CONCAT("SUMMARY OF INVESTMENTS BUSINESS REVENUE ACCOUNTS FOR THE PERIOD ENDED"," ",Details!F18) -> SUMMARY OF INVESTMENTS BUSINESS REVENUE ACCOUNTS FOR THE PERIOD ENDED 31.03.2025
B18: APPENDIX 11 | C18: =_xlfn.CONCAT("SUMMARY OF PERMANENT HEALTH BUSINESS REVENUE ACCOUNTS FOR THE PERIOD ENDED"," ",Details!F18) -> SUMMARY OF PERMANENT HEALTH BUSINESS REVENUE ACCOUNTS FOR THE PERIOD ENDED 31.03.2025
B19: APPENDIX 12 | C19: =_xlfn.CONCAT("SUMMARY OF PERSONAL PENSIONS BUSINESS REVENUE ACCOUNTS FOR THE PERIOD ENDED"," ",Details!F18) -> SUMMARY OF PERSONAL PENSIONS BUSINESS REVENUE ACCOUNTS FOR THE PERIOD ENDED 31.03.2025
B20: APPENDIX 13 | C20: =_xlfn.CONCAT("SUMMARY OF DEPOSIT ADMINISTRATION BUSINESS REVENUE ACCOUNTS FOR THE PERIOD ENDED"," ",Details!F18) -> SUMMARY OF DEPOSIT ADMINISTRATION BUSINESS REVENUE ACCOUNTS FOR THE PERIOD ENDED 31.03.2025
B21: APPENDIX 14 | C21: =_xlfn.CONCAT("SUMMARY OF COMBINED LONG TERM BUSINESS REVENUE ACCOUNTS FOR THE PERIOD ENDED"," ",Details!F18) -> SUMMARY OF COMBINED LONG TERM BUSINESS REVENUE ACCOUNTS FOR THE PERIOD ENDED 31.03.2025
B22: APPENDIX 15 | C22: =_xlfn.CONCAT("SUMMARY OF GROSS PREMIUM INCOME UNDER GENERAL INSURANCE BUSINESS FOR THE PERIOD ENDED"," ",Details!$F$18) -> SUMMARY OF GROSS PREMIUM INCOME UNDER GENERAL INSURANCE BUSINESS FOR THE PERIOD ENDED 31.03.2025
B23: APPENDIX 16 | C23: =_xlfn.CONCAT("SUMMARY OF GENERAL INSURANCE BUSINESS MARKET SHARE PER CLASS FOR THE PERIOD ENDED"," ",Details!$F$18) -> SUMMARY OF GENERAL INSURANCE BUSINESS MARKET SHARE PER CLASS FOR THE PERIOD ENDED 31.03.2025
B24: APPENDIX 17 | C24: =_xlfn.CONCAT("SUMMARY OF CLAIMS PAID UNDER GENERAL INSURANCE BUSINESS FOR THE PERIOD ENDED"," ",Details!$F$18) -> SUMMARY OF CLAIMS PAID UNDER GENERAL INSURANCE BUSINESS FOR THE PERIOD ENDED 31.03.2025
B25: APPENDIX 18 | C25: =_xlfn.CONCAT("SUMMARY OF CLAIMS INCURRED UNDER GENERAL INSURANCE BUSINESS FOR THE PERIOD ENDED"," ",Details!$F$18) -> SUMMARY OF CLAIMS INCURRED UNDER GENERAL INSURANCE BUSINESS FOR THE PERIOD ENDED 31.03.2025
B26: APPENDIX 19 | C26: =_xlfn.CONCAT("SUMMARY OF INCURRED CLAIMS RATIOS UNDER GENERAL INSURANCE BUSINESS FOR THE PERIOD ENDED"," ",Details!$F$18) -> SUMMARY OF INCURRED CLAIMS RATIOS UNDER GENERAL INSURANCE BUSINESS FOR THE PERIOD ENDED 31.03.2025
B27: APPENDIX 20 | C27: =_xlfn.CONCAT("SUMMARY OF UNDERWRITING PROFITS UNDER GENERAL INSURANCE BUSINESS FOR THE PERIOD ENDED"," ",Details!$F$18) -> SUMMARY OF UNDERWRITING PROFITS UNDER GENERAL INSURANCE BUSINESS FOR THE PERIOD ENDED 31.03.2025
B28: APPENDIX 21 | C28: =_xlfn.CONCAT("SUMMARY OF GENERAL INSURANCE BUSINESS REVENUE ACCOUNTS FOR THE PERIOD ENDED"," ",Details!$F$18) -> SUMMARY OF GENERAL INSURANCE BUSINESS REVENUE ACCOUNTS FOR THE PERIOD ENDED 31.03.2025
B29: APPENDIX 22 | C29: =_xlfn.CONCAT("SUMMARY OF MICRO INSURANCE BUSINESS REVENUE ACCOUNT RESULTS FOR THE PERIOD ENDED"," ",Details!$F$18) -> SUMMARY OF MICRO INSURANCE BUSINESS REVENUE ACCOUNT RESULTS FOR THE PERIOD ENDED 31.03.2025
B30: APPENDIX 23Micro | C30: =_xlfn.CONCAT("SUMMARY OF MICRO INSURANCE BUSINESS MARKET SHARE PER CLASS FOR THE PERIOD ENDED"," ",Details!$F$18) -> SUMMARY OF MICRO INSURANCE BUSINESS MARKET SHARE PER CLASS FOR THE PERIOD ENDED 31.03.2025
B31: APPENDIX 24Micro | C31: =_xlfn.CONCAT("SUMMARY OF CLAIMS PAID UNDER MICRO INSURANCE BUSINESS FOR THE PERIOD ENDED"," ",Details!$F$18) -> SUMMARY OF CLAIMS PAID UNDER MICRO INSURANCE BUSINESS FOR THE PERIOD ENDED 31.03.2025
B32: APPENDIX 25Micro | C32: =_xlfn.CONCAT("SUMMARY OF CLAIMS INCURRED UNDER MICRO INSURANCE BUSINESS FOR THE PERIOD ENDED"," ",Details!$F$18) -> SUMMARY OF CLAIMS INCURRED UNDER MICRO INSURANCE BUSINESS FOR THE PERIOD ENDED 31.03.2025
B33: APPENDIX 26Micro | C33: =_xlfn.CONCAT("SUMMARY OF INCURRED CLAIMS RATIOS UNDER MICRO INSURANCE BUSINESS FOR THE PERIOD ENDED"," ",Details!$F$18) -> SUMMARY OF INCURRED CLAIMS RATIOS UNDER MICRO INSURANCE BUSINESS FOR THE PERIOD ENDED 31.03.2025
B34: APPENDIX 27Micro | C34: =_xlfn.CONCAT("SUMMARY OF UNDERWRITING PROFITS UNDER MICRO INSURANCE BUSINESS FOR THE PERIOD ENDED"," ",Details!$F$18) -> SUMMARY OF UNDERWRITING PROFITS UNDER MICRO INSURANCE BUSINESS FOR THE PERIOD ENDED 31.03.2025
B35: APPENDIX 23 | C35: =_xlfn.CONCAT("SUMMARY OF COMBINED MICRO INSURANCE BUSINESS REVENUE ACCOUNTS FOR THE PERIOD ENDED"," ",Details!F18) -> SUMMARY OF COMBINED MICRO INSURANCE BUSINESS REVENUE ACCOUNTS FOR THE PERIOD ENDED 31.03.2025
B36: APPENDIX 24 i | C36: =_xlfn.CONCAT("SUMMARY OF LONG TERM INSURANCE BUSINESS BALANCE SHEETS AS AT"," ",Details!F18) -> SUMMARY OF LONG TERM INSURANCE BUSINESS BALANCE SHEETS AS AT 31.03.2025
B37: APPENDIX 24 ii | C37: =_xlfn.CONCAT("SUMMARY OF LONG TERM INSURANCE BUSINESS BALANCE SHEETS AS AT"," ",Details!F18) -> SUMMARY OF LONG TERM INSURANCE BUSINESS BALANCE SHEETS AS AT 31.03.2025
B38: APPENDIX 24 iii | C38: =_xlfn.CONCAT("SUMMARY OF LONG TERM INSURANCE BUSINESS BALANCE SHEETS AS AT"," ",Details!F18) -> SUMMARY OF LONG TERM INSURANCE BUSINESS BALANCE SHEETS AS AT 31.03.2025
B39: APPENDIX 25 i | C39: =_xlfn.CONCAT("SUMMARY OF GENERAL INSURANCE BUSINESS BALANCE SHEETS AS AT"," ",Details!F18) -> SUMMARY OF GENERAL INSURANCE BUSINESS BALANCE SHEETS AS AT 31.03.2025
B40: APPENDIX 25 ii | C40: =_xlfn.CONCAT("SUMMARY OF GENERAL INSURANCE BUSINESS BALANCE SHEETS AS AT"," ",Details!F18) -> SUMMARY OF GENERAL INSURANCE BUSINESS BALANCE SHEETS AS AT 31.03.2025
B41: APPENDIX 25 iii | C41: =_xlfn.CONCAT("SUMMARY OF GENERAL INSURANCE BUSINESS BALANCE SHEETS AS AT"," ",Details!F18) -> SUMMARY OF GENERAL INSURANCE BUSINESS BALANCE SHEETS AS AT 31.03.2025
B42: APPENDIX 25 iv | C42: =_xlfn.CONCAT("SUMMARY OF GENERAL INSURANCE BUSINESS BALANCE SHEETS AS AT"," ",Details!F18) -> SUMMARY OF GENERAL INSURANCE BUSINESS BALANCE SHEETS AS AT 31.03.2025
B43: APPENDIX 26 i | C43: =_xlfn.CONCAT("SUMMARY OF MICRO INSURANCE BUSINESS BALANCE SHEETS AS AT"," ",Details!F18) -> SUMMARY OF MICRO INSURANCE BUSINESS BALANCE SHEETS AS AT 31.03.2025

Sheet APPENDIX 1
B3: =_xlfn.CONCAT('Table of Contents'!B8,": ",'Table of Contents'!C8) -> APPENDIX 1: SUMMARY OF GENERAL INSURANCE BUSINESS PROFIT & LOSS ACCOUNTS FOR THE PERIOD ENDED 31.03.2025
B4: Company | C4: Insurance Revenue | D4: Insurance Service Expense | E4: Net expenses from reinsurance contracts held | F4: Insurance Service Result | G4: Net Investment Income | H4: Finance expenses from insurance contracts | I4: Finance income from reinsurance contracts | J4: Net Financial Result | K4: Asset management services revenue | L4: Other Income | M4: Other finance costs | N4: Other operating expenses | O4: Share of profit of associates and joint ventures accounted for using the equity method | P4: Profit before income tax | Q4: Income tax expense | R4: Profit for the year
B5: INSURERS
B6: AAR INSURANCE KENYA | C6: 2767250 | D6: 2590990.5 | E6: 46409.727 | F6: 129849.81 | G6: 202123.65 | H6: 0 | I6: 0 | J6: 202123.65 | K6: 0 | L6: -1758.9654 | M6: 8583.0165 | N6: 148456.18 | O6: 0 | P6: 173175.3 | Q6: 0 | R6: 173175.3
B7: AFRICAN MERCHANT ASSURANCE | C7: 1079878.6 | D7: 869225.06 | E7: -11322.627 | F7: 221976.21 | G7: 31980 | H7: 62997.283 | I7: 7811.7527 | J7: -23205.53 | K7: 0 | L7: 0 | M7: 0 | N7: 130182.43 | O7: 0 | P7: 68588.254 | Q7: 0 | R7: 68588.254
B8: APA INSURANCE COMPANY | C8: 4372412.9 | D8: 3692799.7 | E8: 485219.7 | F8: 194393.48 | G8: 479526.05 | H8: 531144.71 | I8: 289726.87 | J8: 238108.21 | K8: 0 | L8: 0 | M8: 7261.4703 | N8: 88669.94 | O8: 0 | P8: 336570.29 | Q8: -17596.639 | R8: 354166.92
B9: BRITAM GENERAL INSURANCE | C9: 3951116.3 | D9: 3033554.2 | E9: 814691.46 | F9: 102870.7 | G9: 508908.73 | H9: 445718.98 | I9: 219527.93 | J9: 282717.67 | K9: 0 | L9: 8308.3264 | M9: 8704.1132 | N9: 93579.844 | O9: 0 | P9: 291612.74 | Q9: 0 | R9: 291612.74
B10: CANNON GENERAL INSURANCE (K) LIMITED | C10: 514448.92 | D10: 484901.3 | E10: 41414.308 | F10: -11866.687 | G10: 26549.271 | H10: 111612.1 | I10: 66305.029 | J10: -18757.803 | K10: 0 | L10: 0 | M10: 0 | N10: 47179.337 | O10: 0 | P10: -77803.827 | Q10: 0 | R10: -77803.827
B11: CIC GENERAL INSURANCE COMPANY | C11: 4394571.9 | D11: 3823921.2 | E11: 506033.61 | F11: 64617.114 | G11: 280735.3 | H11: 201066.73 | I11: 53258.674 | J11: 132927.25 | K11: 0 | L11: 64678.522 | M11: 0 | N11: 91658.724 | O11: 0 | P11: 170564.16 | Q11: 51169.249 | R11: 119394.91
B12: CORPORATE INSURANCE COMPANY | C12: 42952.314 | D12: -33854.017 | E12: 16177.318 | F12: 60629.013 | G12: 5746.453 | H12: 76899.083 | I12: 27687.468 | J12: -43465.162 | K12: 0 | L12: 0 | M12: 0 | N12: 25755.381 | O12: 0 | P12: -8591.5299 | Q12: 0 | R12: -8591.5299
B13: DEFINITE ASSURANCE COMPANY | C13: 25256.267 | D13: 21152.995 | E13: 477.41787 | F13: 3625.8544 | G13: 0 | H13: 0 | I13: 0 | J13: 0 | K13: 0 | L13: 0 | M13: 0 | N13: 0 | O13: 0 | P13: 3625.8544 | Q13: 0 | R13: 3625.8544
B14: DIRECTLINE ASSURANCE COMPANY | C14: 717147.63 | D14: 761039.08 | E14: 15745.425 | F14: -59636.87 | G14: 71430.841 | H14: 762416.41 | I14: 0 | J14: -690985.57 | K14: 0 | L14: 0 | M14: 0 | N14: 7500.808 | O14: 0 | P14: -758123.24 | Q14: 0 | R14: -758123.24
B15: EQUITY GENERAL INSURANCE LIMITED | C15: 280504.69 | D15: 319216.16 | E15: 19295.15 | F15: -58006.614 | G15: 29819.8 | H15: 0 | I15: 0 | J15: 29819.8 | K15: 0 | L15: 0 | M15: 0 | N15: 0 | O15: 0 | P15: -28186.814 | Q15: -8456.0442 | R15: -19730.77
B16: FIDELITY SHIELD INSURANCE | C16: 1074606.7 | D16: 929812.61 | E16: 193359.03 | F16: -48564.917 | G16: 128890.2 | H16: 46838.872 | I16: 8079.5037 | J16: 90130.836 | K16: 0 | L16: 14707.181 | M16: 0 | N16: 46489.123 | O16: 0 | P16: 9783.9779 | Q16: 0 | R16: 9783.9779
B17: FIRST ASSURANCE COMPANY | C17: 1679272.8 | D17: 1558410.2 | E17: 107490.29 | F17: 13372.4 | G17: 89512.957 | H17: -89215.97 | I17: -35054.097 | J17: 143674.83 | K17: 0 | L17: 0 | M17: 0 | N17: 87023.79 | O17: 0 | P17: 70023.439 | Q17: 21216 | R17: 48807.439
... B41: TRIDENT INSURANCE COMPANY | C41: 0 | D41: 0 | E41: 0 | F41: 0 | G41: 0 | H41: 0 | I41: 0 | J41: 0 | K41: 0 | L41: 0 | M41: 0 | N41: 0 | O41: 0 | P41: 0 | Q41: 0 | R41: 0
B42: TOTAL | C42: =SUM(C6:C41) -> 51594233 | D42: =SUM(D6:D41) -> 42921946 | E42: =SUM(E6:E41) -> 5987188.9 | F42: =SUM(F6:F41) -> 2685098.1 | G42: =SUM(G6:G41) -> 4579029.8 | H42: =SUM(H6:H41) -> 4214617.6 | I42: =SUM(I6:I41) -> 1277381.2 | J42: =SUM(J6:J41) -> 1641793.5 | ... R42: =SUM(R6:R41) -> 1810141.2
B43: REINSURERS
B44: CONTINENTAL REINSURANCE | C44: 1498541 | D44: 1460000.5 | E44: -80030.113 | F44: 118570.66 | G44: 61370.513 | H44: 155208.27 | I44: 62790.039 | J44: -31047.721 | K44: 0 | L44: 11022.149 | M44: 810.181 | N44: 6633.212 | O44: 0 | P44: 91101.699 | Q44: 27330.509 | R44: 63771.19
B45: EAST AFRICA REINSURANCE | C45: 1513009.7 | D45: 1297891.5 | E45: 123540.01 | F45: 91578.181 | G45: 169797.46 | H45: 42543.38 | I45: 8144.1956 | J45: 135398.27 | K45: 0 | L45: 0 | M45: 0 | N45: 3488.565 | O45: 0 | P45: 223487.89 | Q45: 55871.971 | R45: 167615.92
B46: GHANA REINSURANCE COMPANY | C46: 915568.14 | D46: 798999.17 | E46: 73348.869 | F46: 43220.1 | G46: 59297.68 | H46: 44096.781 | I46: 9334.2695 | J46: 24535.168 | K46: 0 | L46: 0 | M46: -6444.1883 | N46: 51366.221 | O46: 0 | P46: 22833.235 | Q46: 0 | R46: 22833.235
B47: KENYA REINSURANCE CORPORATION | C47: 2634223.2 | D47: 2837322.2 | E47: 173645.88 | F47: -376744.86 | G47: 1133012.2 | H47: -82747.898 | I47: 12356.061 | J47: 1228116.1 | K47: 0 | L47: 9605.024 | M47: -1895.489 | N47: 403490.64 | O47: 0 | P47: 459381.16 | Q47: 137814.35 | R47: 321566.81
B48: WAICA REINSURANCE KENYA LIMITED | C48: 1635403.3 | D48: 1008390 | E48: 271727.44 | F48: 355285.84 | G48: 89004.18 | H48: 122950.7 | I48: 13091.25 | J48: -20855.268 | K48: 0 | L48: 2070.5998 | M48: 0 | N48: 154865.24 | O48: 0 | P48: 181635.93 | Q48: 54490.779 | R48: 127145.15
B49: TOTAL | C49: =SUM(C44:C48) -> 8196745.4 | D49: =SUM(D44:D48) -> 7402603.4 | E49: =SUM(E44:E48) -> 562232.09 | F49: =SUM(F44:F48) -> 231909.93 | G49: =SUM(G44:G48) -> 1512482 | H49: =SUM(H44:H48) -> 282051.23 | I49: =SUM(I44:I48) -> 105715.81 | J49: =SUM(J44:J48) -> 1336146.6 | ... R49: =SUM(R44:R48) -> 702932.3
B50: GRAND TOTAL | C50: =C42+C49 -> 59790978 | D50: =D42+D49 -> 50324549 | E50: =E42+E49 -> 6549421 | F50: =F42+F49 -> 2917008.1 | G50: =G42+G49 -> 6091511.9 | H50: =H42+H49 -> 4496668.8 | I50: =I42+I49 -> 1383097 | J50: =J42+J49 -> 2977940 | ... R50: =R42+R49 -> 2513073.5
B51: Amounts in Thousand Shillings

Sheet APPENDIX 2
B3: =_xlfn.CONCAT('Table of Contents'!B9,": ",'Table of Contents'!C9) -> APPENDIX 2: SUMMARY OF LONG TERM INSURANCE BUSINESS PROFIT & LOSS ACCOUNTS FOR THE PERIOD ENDED 31.03.2025
B4: Company | C4: Insurance Revenue | D4: Insurance Service Expense | E4: Net expenses from reinsurance contracts held | F4: Insurance Service Result | G4: Net Investment Income | H4: Finance expenses from insurance contracts | I4: Finance income from reinsurance contracts | J4: Net Financial Result | K4: Asset management services revenue | L4: Other Income | M4: Other finance costs | N4: Other operating expenses | O4: Share of profit of associates and joint ventures accounted for using the equity method | P4: Profit before income tax | Q4: Income tax expense | R4: Profit for the year
B5: INSURERS
B6: ABSA LIFE ASSURANCE | C6: 2086213.3 | D6: 1665485.3 | E6: 119654.65 | F6: 301073.31 | G6: 459692.37 | H6: 1162010.6 | I6: 14883.6 | J6: -687434.66 | K6: 0 | L6: 0 | M6: 0 | N6: 44993.901 | O6: 0 | P6: -431355.24 | Q6: 45466.182 | R6: -476821.43
B7: APA LIFE ASSURANCE COMPANY | C7: 1345408.7 | D7: 868201.33 | E7: 476738.86 | F7: 468.54316 | G7: 596632.61 | H7: 476681.92 | I7: 5473.9033 | J7: 125424.6 | K7: 0 | L7: 0 | M7: 7388.641 | N7: 25123.075 | O7: 0 | P7: 93381.423 | Q7: 19511.08 | R7: 73870.343
B8: BRITAM LIFE ASSURANCE | C8: 3480058 | D8: 2554301.8 | E8: 201473.48 | F8: 724282.71 | G8: 9804614.4 | H8: 9955073.9 | I8: 38503.529 | J8: -111956.01 | K8: 0 | L8: -15078.871 | M8: 10471.147 | N8: 128343.45 | O8: 149927.78 | P8: 608361.01 | Q8: 182508.3 | R8: 425852.71
B9: CANNON LIFE ASSURANCE (K) LIMITED | C9: 121787.11 | D9: 147480.24 | E9: 5100.417 | F9: -30793.546 | G9: 40307.388 | H9: 32676.434 | I9: 755.22343 | J9: 8386.1773 | K9: 0 | L9: 3743.4 | M9: 0 | N9: 1885.3023 | O9: 0 | P9: -20549.271 | Q9: 1806.882 | R9: -22356.153
B10: CAPEX LIFE ASSURANCE COMPANY | C10: 398941.75 | D10: 408018.18 | E10: -8977.387 | F10: -99.043759 | G10: 13332.822 | H10: 11087.15 | I10: 8161.032 | J10: 10406.704 | K10: 0 | L10: 0 | M10: 0 | N10: 5100.12 | O10: 0 | P10: 5207.5402 | Q10: 0 | R10: 5207.5402
B11: CIC LIFE ASSURANCE COMPANY | C11: 1592770.2 | D11: 1517857 | E11: 90103.488 | F11: -15190.305 | G11: 501325.41 | H11: 464442.56 | I11: 20488.986 | J11: 57371.835 | K11: 0 | L11: 146827.75 | M11: 0 | N11: 60543.563 | O11: 0 | P11: 128465.72 | Q11: 38539.716 | R11: 89926.004
B12: CORPORATE INSURANCE COMPANY | C12: 59706.503 | D12: 54129.934 | E12: 4750.5172 | F12: 826.05232 | G12: 4813.398 | H12: 35647.354 | I12: 0 | J12: -30833.956 | K12: 0 | L12: 0 | M12: 0 | N12: 190.07583 | O12: 0 | P12: -30197.979 | Q12: 0 | R12: -30197.979
B13: EQUITY LIFE ASSURANCE | C13: 448608.63 | D13: 366370.22 | E13: -75098.176 | F13: 157336.59 | G13: 767664.74 | H13: 474933.83 | I13: 15980.041 | J13: 308710.95 | K13: 0 | L13: 47172.976 | M13: 0 | N13: 70550.568 | O13: 0 | P13: 442669.95 | Q13: 132800.99 | R13: 309868.97
B14: GA LIFE ASSURANCE COMPANY | C14: 22123.436 | D14: 9977.4012 | E14: -6663.914 | F14: 18809.949 | G14: 1615731.9 | H14: 0 | I14: 0 | J14: 1615731.9 | K14: 0 | L14: 331877.67 | M14: 0 | N14: 67946.851 | O14: 0 | P14: 1898472.7 | Q14: 5248.199 | R14: 1893224.5
B15: GEMINIA LIFE INSURANCE COMPANY | C15: 310433.83 | D15: 147421.11 | E15: 5642.784 | F15: 157369.93 | G15: 6146.895 | H15: 0 | I15: 0 | J15: 6146.895 | K15: 0 | L15: 0 | M15: 0 | N15: 29267.578 | O15: 0 | P15: 134249.25 | Q15: 0 | R15: 134249.25
B16: ICEA LION LIFE ASSURANCE | C16: 1389953.9 | D16: 1179225.3 | E16: -96901.208 | F16: 307629.77 | G16: 7974626.6 | H16: 7862984.7 | I16: 0 | J16: 111641.97 | K16: 0 | L16: 63249.497 | M16: 0 | N16: 275626.67 | O16: 0 | P16: 206894.57 | Q16: 46564.349 | R16: 160330.22
B17: JUBILEE LIFE INSURANCE | C17: 1097635.6 | D17: 999433.19 | E17: 177540.61 | F17: -79338.179 | G17: 6223309.3 | H17: 5534370.5 | I17: 0 | J17: 688938.75 | K17: 0 | L17: 0 | M17: 0 | N17: 259888.09 | O17: 15332.819 | P17: 365045.3 | Q17: 86090.688 | R17: 278954.61
... B30: THE MONARCH INSURANCE | C30: 0 | D30: 0 | E30: 0 | F30: 0 | G30: 0 | H30: 0 | I30: 0 | J30: 0 | K30: 0 | L30: 0 | M30: 0 | N30: 0 | O30: 0 | P30: 0 | Q30: 0 | R30: 0
B31: TOTAL | C31: =SUM(C6:C30) -> 18361442 | D31: =SUM(D6:D30) -> 16131998 | E31: =SUM(E6:E30) -> 1203450.7 | F31: =SUM(F6:F30) -> 1025993.1 | G31: =SUM(G6:G30) -> 36975973 | H31: =SUM(H6:H30) -> 34156545 | I31: =SUM(I6:I30) -> 107049.1 | J31: =SUM(J6:J30) -> 2926476.6 | ... R31: =SUM(R6:R30) -> 3127551.6
B32: REINSURERS
B33: CONTINENTAL REINSURANCE | C33: 22961.78 | D33: 24268.422 | E33: 31.049 | F33: -1337.6906 | G33: 16974.278 | H33: 1324.463 | I33: 74 | J33: 15723.815 | K33: 0 | L33: 0 | M33: 43.998 | N33: 677 | O33: 0 | P33: 13753.052 | Q33: -4125.916 | R33: 9627.1364
B34: EAST AFRICA REINSURANCE | C34: 361178.95 | D34: 252517.47 | E34: 51013.29 | F34: 57648.186 | G34: 65895.28 | H34: 7098.455 | I34: 1468.1674 | J34: 60264.992 | K34: 0 | L34: 0 | M34: 0 | N34: 4741 | O34: 0 | P34: 113171.7 | Q34: -33951.511 | R34: 79220.192
B35: KENYA REINSURANCE CORPORATION | C35: 688924.38 | D35: 840979.3 | E35: 8998.1368 | F35: -161053.05 | G35: 205888.07 | H35: 94599.293 | I35: 952.43524 | J35: 112241.21 | K35: 0 | L35: 0 | M35: 0 | N35: 131088 | O35: 0 | P35: -179900.02 | Q35: 53970.006 | R35: -125930.01
B36: TOTAL | C36: =SUM(C33:C35) -> 1073065.1 | D36: =SUM(D33:D35) -> 1117765.2 | E36: =SUM(E33:E35) -> 60042.476 | F36: =SUM(F33:F35) -> -104742.56 | G36: =SUM(G33:G35) -> 288757.63 | H36: =SUM(H33:H35) -> 103022.21 | I36: =SUM(I33:I35) -> 2494.6026 | J36: =SUM(J33:J35) -> 188230.02 | ... R36: =SUM(R33:R35) -> -37082.686
B37: GRAND TOTAL | C37: =C36+C31 -> 19434507 | D37: =D36+D31 -> 17249763 | E37: =E36+E31 -> 1263493.2 | F37: =F36+F31 -> 921250.57 | G37: =G36+G31 -> 37264730 | H37: =H36+H31 -> 34259567 | I37: =I36+I31 -> 109543.7 | J37: =J36+J31 -> 3114706.7 | ... R37: =R36+R31 -> 3090468.9
B38: Amounts in Thousand Shillings

Sheet APPENDIX 3
B3: =_xlfn.CONCAT('Table of Contents'!B10,": ",'Table of Contents'!C10) -> APPENDIX 3: SUMMARY OF MICRO INSURANCE BUSINESS PROFIT & LOSS ACCOUNTS FOR THE PERIOD ENDED 31.03.2025
B4: Company | C4: Insurance Revenue | D4: Insurance Service Expense | E4: Net expenses from reinsurance contracts held | F4: Insurance Service Result | G4: Net Investment Income | H4: Finance expenses from insurance contracts | I4: Finance income from reinsurance contracts | J4: Net Financial Result | K4: Asset management services revenue | L4: Other Income | M4: Other finance costs | N4: Other operating expenses | O4: Share of profit of associates and joint ventures accounted for using the equity method | P4: Profit before income tax | Q4: Income tax expense | R4: Profit for the year
B5: INSURERS
B6: APA MICRO INSURANCE | C6: 0 | D6: 0 | E6: 0 | F6: 0 | G6: 0 | H6: 0 | I6: 0 | J6: 0 | K6: 0 | L6: 0 | M6: 0 | N6: 0 | O6: 0 | P6: 0 | Q6: 0 | R6: 0
B7: BIRDVIEW MICRO INSURANCE | C7: 0 | D7: 0 | E7: 0 | F7: 0 | G7: 0 | H7: 0 | I7: 0 | J7: 0 | K7: 0 | L7: 0 | M7: 0 | N7: 0 | O7: 0 | P7: 0 | Q7: 0 | R7: 0
B8: BRITAM MICRO INSURANCE | C8: 151301.27 | D8: 137594.63 | E8: 17581.794 | F8: -3875.1561 | G8: 11352.201 | H8: 3904.0245 | I8: 28.893163 | J8: 7477.0702 | K8: 0 | L8: 246.72707 | M8: 1295.7948 | N8: 5099.7644 | O8: 0 | P8: -2546.918 | Q8: 0 | R8: -2546.918
B9: CIC MICRO INSURANCE | C9: 0 | D9: 0 | E9: 0 | F9: 0 | G9: 0 | H9: 0 | I9: 0 | J9: 0 | K9: 0 | L9: 0 | M9: 0 | N9: 0 | O9: 0 | P9: 0 | Q9: 0 | R9: 0
B10: STAR DISCOVER MICRO INSURANCE | C10: 23728.542 | D10: 30528.194 | E10: 10240.628 | F10: -17040.279 | G10: 0 | H10: 214.64969 | I10: 122.15404 | J10: -92.495651 | K10: 0 | L10: 272.554 | M10: 0 | N10: 0 | O10: 0 | P10: -16860.221 | Q10: 0 | R10: -16860.221
B11: TURACO MICRO INSURANCE | C11: 98546.435 | D11: 87976.48 | E11: 7905.9752 | F11: 2663.9803 | G11: 1052.0548 | H11: 39.096737 | I11: 7.2545134 | J11: 1020.2126 | K11: 0 | L11: 0 | M11: 0 | N11: 0 | O11: 0 | P11: 3684.1929 | Q11: 1105.2579 | R11: 2578.935
B12: TOTAL | C12: =SUM(C6:C11) -> 273576.25 | D12: =SUM(D6:D11) -> 256099.3 | E12: =SUM(E6:E11) -> 35728.397 | F12: =SUM(F6:F11) -> -18251.455 | G12: =SUM(G6:G11) -> 12404.256 | H12: =SUM(H6:H11) -> 4157.7709 | I12: =SUM(I6:I11) -> 158.30172 | J12: =SUM(J6:J11) -> 8404.7871 | ... R12: =SUM(R6:R11) -> -16828.204
B13: Amounts in Thousand Shillings

Sheet APPENDIX 4
B3: =_xlfn.CONCAT('Table of Contents'!B11,": ",'Table of Contents'!C11) -> APPENDIX 4: SUMMARY OF LONG TERM INSURANCE BUSINESS GROSS PREMIUM INCOME FOR THE PERIOD ENDED 31.03.2025
B4: Company | C4: Life Assurances | D4: Annuities | E4: Personal Pensions | F4: Deposit Administration | G4: Group Life | H4: Group Credit | I4: Permanent Health | J4: Investments | K4: Total | L4: Market Share (%)
B5: INSURERS
B6: ='APPENDIX 6'!B6 -> ABSA LIFE ASSURANCE | C6: ='APPENDIX 6'!D6 -> 1419720.3 | D6: ='APPENDIX 7'!D6 -> 0 | E6: ='APPENDIX 12'!D6 -> 0 | F6: ='APPENDIX 13'!D6 -> 0 | G6: ='APPENDIX 8'!D6 -> 1397419.6 | H6: ='APPENDIX 9'!D6 -> 155932.11 | I6: ='APPENDIX 11'!D6 -> 0 | J6: ='APPENDIX 10'!D6 -> 0 | K6: =SUM(C6:J6) -> 2973072 | L6: =IFERROR(K6/$K$31,0)*100 -> 5.5632577
B7: ='APPENDIX 6'!B7 -> APA LIFE ASSURANCE COMPANY | C7: ='APPENDIX 6'!D7 -> 140563.62 | D7: ='APPENDIX 7'!D7 -> 18694.998 | E7: ='APPENDIX 12'!D7 -> 51601.347 | F7: ='APPENDIX 13'!D7 -> 253912.34 | G7: ='APPENDIX 8'!D7 -> 750660.01 | H7: ='APPENDIX 9'!D7 -> 190625.79 | I7: ='APPENDIX 11'!D7 -> 0 | J7: ='APPENDIX 10'!D7 -> 1093378.7 | K7: =SUM(C7:J7) -> 2499436.8 | L7: =IFERROR(K7/$K$31,0)*100 -> 4.6769842
B8: ='APPENDIX 6'!B8 -> BRITAM LIFE ASSURANCE | C8: ='APPENDIX 6'!D8 -> 2845011 | D8: ='APPENDIX 7'!D8 -> 1516175.6 | E8: ='APPENDIX 12'!D8 -> 979427.72 | F8: ='APPENDIX 13'!D8 -> 1291968 | G8: ='APPENDIX 8'!D8 -> 500832.27 | H8: ='APPENDIX 9'!D8 -> 120684.12 | I8: ='APPENDIX 11'!D8 -> 0 | J8: ='APPENDIX 10'!D8 -> 2404280 | K8: =SUM(C8:J8) -> 9658378.7 | L8: =IFERROR(K8/$K$31,0)*100 -> 18.072905
B9: ='APPENDIX 6'!B9 -> CANNON LIFE ASSURANCE (K) LIMITED | C9: ='APPENDIX 6'!D9 -> 6556.598 | D9: ='APPENDIX 7'!D9 -> 0 | E9: ='APPENDIX 12'!D9 -> 0 | F9: ='APPENDIX 13'!D9 -> 0 | G9: ='APPENDIX 8'!D9 -> 226335.44 | H9: ='APPENDIX 9'!D9 -> 4106.174 | I9: ='APPENDIX 11'!D9 -> 0 | J9: ='APPENDIX 10'!D9 -> 0 | K9: =SUM(C9:J9) -> 236998.21 | L9: =IFERROR(K9/$K$31,0)*100 -> 0.44347467
B10: ='APPENDIX 6'!B10 -> CAPEX LIFE ASSURANCE COMPANY | C10: ='APPENDIX 6'!D10 -> 7679.969 | D10: ='APPENDIX 7'!D10 -> 127646.8 | E10: ='APPENDIX 12'!D10 -> 0 | F10: ='APPENDIX 13'!D10 -> 0 | G10: ='APPENDIX 8'!D10 -> 200062.22 | H10: ='APPENDIX 9'!D10 -> 43060.997 | I10: ='APPENDIX 11'!D10 -> 0 | J10: ='APPENDIX 10'!D10 -> 0 | K10: =SUM(C10:J10) -> 378449.98 | L10: =IFERROR(K10/$K$31,0)*100 -> 0.70816137
B11: ='APPENDIX 6'!B11 -> CIC LIFE ASSURANCE COMPANY | C11: ='APPENDIX 6'!D11 -> 325786.32 | D11: ='APPENDIX 7'!D11 -> 119075.01 | E11: ='APPENDIX 12'!D11 -> 0 | F11: ='APPENDIX 13'!D11 -> 863483.16 | G11: ='APPENDIX 8'!D11 -> 388787.88 | H11: ='APPENDIX 9'!D11 -> 2352717.4 | I11: ='APPENDIX 11'!D11 -> 0 | J11: ='APPENDIX 10'!D11 -> 0 | K11: =SUM(C11:J11) -> 4049849.8 | L11: =IFERROR(K11/$K$31,0)*100 -> 7.5781407
B12: ='APPENDIX 6'!B12 -> CORPORATE INSURANCE COMPANY | C12: ='APPENDIX 6'!D12 -> 8452.4385 | D12: ='APPENDIX 7'!D12 -> 0 | E12: ='APPENDIX 12'!D12 -> 0 | F12: ='APPENDIX 13'!D12 -> 0 | G12: ='APPENDIX 8'!D12 -> 0 | H12: ='APPENDIX 9'!D12 -> 0 | I12: ='APPENDIX 11'!D12 -> 0 | J12: ='APPENDIX 10'!D12 -> 0 | K12: =SUM(C12:J12) -> 8452.4385 | L12: =IFERROR(K12/$K$31,0)*100 -> 0.015816332
B13: ='APPENDIX 6'!B13 -> EQUITY LIFE ASSURANCE | C13: ='APPENDIX 6'!D13 -> 0 | D13: ='APPENDIX 7'!D13 -> 0 | E13: ='APPENDIX 12'!D13 -> 59723.999 | F13: ='APPENDIX 13'!D13 -> 633735.15 | G13: ='APPENDIX 8'!D13 -> 574687.98 | H13: ='APPENDIX 9'!D13 -> 652617.51 | I13: ='APPENDIX 11'!D13 -> 0 | J13: ='APPENDIX 10'!D13 -> 155652.82 | K13: =SUM(C13:J13) -> 2076417.5 | L13: =IFERROR(K13/$K$31,0)*100 -> 3.885424
B14: ='APPENDIX 6'!B14 -> GA LIFE ASSURANCE COMPANY | C14: ='APPENDIX 6'!D14 -> 18244.757 | D14: ='APPENDIX 7'!D14 -> 0 | E14: ='APPENDIX 12'!D14 -> 310066.09 | F14: ='APPENDIX 13'!D14 -> 5040249 | G14: ='APPENDIX 8'!D14 -> 34320.526 | H14: ='APPENDIX 9'!D14 -> 896.95848 | I14: ='APPENDIX 11'!D14 -> 0 | J14: ='APPENDIX 10'!D14 -> 0 | K14: =SUM(C14:J14) -> 5403777.4 | L14: =IFERROR(K14/$K$31,0)*100 -> 10.111631
B15: ='APPENDIX 6'!B15 -> GEMINIA LIFE INSURANCE COMPANY | C15: ='APPENDIX 6'!D15 -> 17232.776 | D15: ='APPENDIX 7'!D15 -> 0 | E15: ='APPENDIX 12'!D15 -> 164999.69 | F15: ='APPENDIX 13'!D15 -> 598310.41 | G15: ='APPENDIX 8'!D15 -> 122624.96 | H15: ='APPENDIX 9'!D15 -> 80579.255 | I15: ='APPENDIX 11'!D15 -> 0 | J15: ='APPENDIX 10'!D15 -> 168430.38 | K15: =SUM(C15:J15) -> 1152177.5 | L15: =IFERROR(K15/$K$31,0)*100 -> 2.1559721
B16: ='APPENDIX 6'!B16 -> ICEA LION LIFE ASSURANCE | C16: ='APPENDIX 6'!D16 -> 1863890.6 | D16: ='APPENDIX 7'!D16 -> 518127.29 | E16: ='APPENDIX 12'!D16 -> 1903461.8 | F16: ='APPENDIX 13'!D16 -> 2474247.9 | G16: ='APPENDIX 8'!D16 -> 186560.47 | H16: ='APPENDIX 9'!D16 -> 35161.351 | I16: ='APPENDIX 11'!D16 -> 0 | J16: ='APPENDIX 10'!D16 -> 1312.6909 | K16: =SUM(C16:J16) -> 6982762.2 | L16: =IFERROR(K16/$K$31,0)*100 -> 13.066251
B17: ='APPENDIX 6'!B17 -> JUBILEE LIFE INSURANCE | C17: ='APPENDIX 6'!D17 -> 1698033.3 | D17: ='APPENDIX 7'!D17 -> 577366.4 | E17: ='APPENDIX 12'!D17 -> 670804.03 | F17: ='APPENDIX 13'!D17 -> 3614808.5 | G17: ='APPENDIX 8'!D17 -> 420477.76 | H17: ='APPENDIX 9'!D17 -> 93087.809 | I17: ='APPENDIX 11'!D17 -> 0 | J17: ='APPENDIX 10'!D17 -> 0 | K17: =SUM(C17:J17) -> 7074577.8 | L17: =IFERROR(K17/$K$31,0)*100 -> 13.238058
... B30: ='APPENDIX 6'!B30 -> THE MONARCH INSURANCE | C30: ='APPENDIX 6'!D30 -> 0 | D30: ='APPENDIX 7'!D30 -> 0 | E30: ='APPENDIX 12'!D30 -> 0 | F30: ='APPENDIX 13'!D30 -> 0 | G30: ='APPENDIX 8'!D30 -> 0 | H30: ='APPENDIX 9'!D30 -> 0 | I30: ='APPENDIX 11'!D30 -> 0 | J30: ='APPENDIX 10'!D30 -> 0 | K30: =SUM(C30:J30) -> 0 | L30: =IFERROR(K30/$K$31,0)*100 -> 0
B31: TOTAL | C31: =SUM(C6:C30) -> 11796272 | D31: =SUM(D6:D30) -> 3292672.4 | E31: =SUM(E6:E30) -> 5043446.6 | F31: =SUM(F6:F30) -> 16490309 | G31: =SUM(G6:G30) -> 7163503.3 | H31: =SUM(H6:H30) -> 5548840.9 | I31: =SUM(I6:I30) -> 0 | J31: =SUM(J6:J30) -> 4106161.7 | ... L31: =SUM(L6:L30) -> 100
B32: REINSURERS
B33: ='APPENDIX 6'!B33 -> CONTINENTAL REINSURANCE | C33: ='APPENDIX 6'!D33 -> 0 | D33: ='APPENDIX 7'!D33 -> 0 | E33: ='APPENDIX 12'!D33 -> 0 | F33: ='APPENDIX 13'!F33 -> 0 | G33: ='APPENDIX 8'!D33 -> 22961.78 | H33: ='APPENDIX 9'!D33 -> 0 | I33: ='APPENDIX 11'!D33 -> 0 | J33: ='APPENDIX 10'!D33 -> 0 | K33: =SUM(C33:J33) -> 22961.78 | L33: =IFERROR(K33/$K$36,0)*100 -> 1.9511532
B34: ='APPENDIX 6'!B34 -> EAST AFRICA REINSURANCE | C34: ='APPENDIX 6'!D34 -> 34147.043 | D34: ='APPENDIX 7'!D34 -> 0 | E34: ='APPENDIX 12'!D34 -> 0 | F34: ='APPENDIX 13'!F34 -> 0 | G34: ='APPENDIX 8'!D34 -> 327031.9 | H34: ='APPENDIX 9'!D34 -> 0 | I34: ='APPENDIX 11'!D34 -> 0 | J34: ='APPENDIX 10'!D34 -> 0 | K34: =SUM(C34:J34) -> 361178.95 | L34: =IFERROR(K34/$K$36,0)*100 -> 30.690803
B35: ='APPENDIX 6'!B35 -> KENYA REINSURANCE CORPORATION | C35: ='APPENDIX 6'!D35 -> 36014.078 | D35: ='APPENDIX 7'!D35 -> 0 | E35: ='APPENDIX 12'!D35 -> 0 | F35: ='APPENDIX 13'!F35 -> 0 | G35: ='APPENDIX 8'!D35 -> 756676.39 | H35: ='APPENDIX 9'!D35 -> 0 | I35: ='APPENDIX 11'!D35 -> 0 | J35: ='APPENDIX 10'!D35 -> 0 | K35: =SUM(C35:J35) -> 792690.47 | L35: =IFERROR(K35/$K$36,0)*100 -> 67.358044
B36: TOTAL | C36: =SUM(C33:C35) -> 70161.121 | D36: =SUM(D33:D35) -> 0 | E36: =SUM(E33:E35) -> 0 | F36: =SUM(F33:F35) -> 0 | G36: =SUM(G33:G35) -> 1106670.1 | H36: =SUM(H33:H35) -> 0 | I36: =SUM(I33:I35) -> 0 | J36: =SUM(J33:J35) -> 0 | ... L36: =SUM(L33:L35) -> 100
B37: Amounts in Thousand Shillings

Sheet APPENDIX 5
B3: =_xlfn.CONCAT('Table of Contents'!B12,": ",'Table of Contents'!C12) -> APPENDIX 5: SUMMARY OF LONG TERM INSURANCE BUSINESS MARKET SHARE PER CLASS FOR THE PERIOD ENDED 31.03.2025
B4: Company | C4: Life Assurances | D4: Annuities | E4: Pensions | F4: Deposit Administration | G4: Group Life | H4: Group Credit | I4: Permanent Health | J4: Investments | K4: Total
B5: INSURERS
B6: ='APPENDIX 6'!B6 -> ABSA LIFE ASSURANCE | C6: =IFERROR(('APPENDIX 4'!C6/'APPENDIX 4'!C$31)*100,0) -> 12.03533 | D6: =IFERROR(('APPENDIX 4'!D6/'APPENDIX 4'!D$31)*100,0) -> 0 | E6: =IFERROR(('APPENDIX 4'!E6/'APPENDIX 4'!E$31)*100,0) -> 0 | F6: =IFERROR(('APPENDIX 4'!F6/'APPENDIX 4'!F$31)*100,0) -> 0 | G6: =IFERROR(('APPENDIX 4'!G6/'APPENDIX 4'!G$31)*100,0) -> 19.507489 | H6: =IFERROR(('APPENDIX 4'!H6/'APPENDIX 4'!H$31)*100,0) -> 2.8101745 | I6: =IFERROR(('APPENDIX 4'!I6/'APPENDIX 4'!I$31)*100,0) -> 0 | J6: =IFERROR(('APPENDIX 4'!J6/'APPENDIX 4'!J$31)*100,0) -> 0 | K6: =IFERROR(('APPENDIX 4'!K6/'APPENDIX 4'!K$31)*100,0) -> 5.5632577 | L6: =RANK(K6,$K$6:$K$30) -> 6 | M6: =COUNTIF(K6:K30,">5") -> 6
B7: ='APPENDIX 6'!B7 -> APA LIFE ASSURANCE COMPANY | C7: =IFERROR(('APPENDIX 4'!C7/'APPENDIX 4'!C$31)*100,0) -> 1.1915936 | D7: =IFERROR(('APPENDIX 4'!D7/'APPENDIX 4'!D$31)*100,0) -> 0.56777584 | E7: =IFERROR(('APPENDIX 4'!E7/'APPENDIX 4'!E$31)*100,0) -> 1.0231366 | F7: =IFERROR(('APPENDIX 4'!F7/'APPENDIX 4'!F$31)*100,0) -> 1.539767 | G7: =IFERROR(('APPENDIX 4'!G7/'APPENDIX 4'!G$31)*100,0) -> 10.478951 | H7: =IFERROR(('APPENDIX 4'!H7/'APPENDIX 4'!H$31)*100,0) -> 3.4354165 | I7: =IFERROR(('APPENDIX 4'!I7/'APPENDIX 4'!I$31)*100,0) -> 0 | J7: =IFERROR(('APPENDIX 4'!J7/'APPENDIX 4'!J$31)*100,0) -> 26.627754 | K7: =IFERROR(('APPENDIX 4'!K7/'APPENDIX 4'!K$31)*100,0) -> 4.6769842 | L7: =RANK(K7,$K$6:$K$30) -> 7
B8: ='APPENDIX 6'!B8 -> BRITAM LIFE ASSURANCE | C8: =IFERROR(('APPENDIX 4'!C8/'APPENDIX 4'!C$31)*100,0) -> 24.117881 | D8: =IFERROR(('APPENDIX 4'!D8/'APPENDIX 4'!D$31)*100,0) -> 46.046962 | E8: =IFERROR(('APPENDIX 4'!E8/'APPENDIX 4'!E$31)*100,0) -> 19.419809 | F8: =IFERROR(('APPENDIX 4'!F8/'APPENDIX 4'!F$31)*100,0) -> 7.8347109 | G8: =IFERROR(('APPENDIX 4'!G8/'APPENDIX 4'!G$31)*100,0) -> 6.9914432 | H8: =IFERROR(('APPENDIX 4'!H8/'APPENDIX 4'!H$31)*100,0) -> 2.1749429 | I8: =IFERROR(('APPENDIX 4'!I8/'APPENDIX 4'!I$31)*100,0) -> 0 | J8: =IFERROR(('APPENDIX 4'!J8/'APPENDIX 4'!J$31)*100,0) -> 58.552977 | K8: =IFERROR(('APPENDIX 4'!K8/'APPENDIX 4'!K$31)*100,0) -> 18.072905 | L8: =RANK(K8,$K$6:$K$30) -> 1
B9: ='APPENDIX 6'!B9 -> CANNON LIFE ASSURANCE (K) LIMITED | C9: =IFERROR(('APPENDIX 4'!C9/'APPENDIX 4'!C$31)*100,0) -> 0.055581948 | D9: =IFERROR(('APPENDIX 4'!D9/'APPENDIX 4'!D$31)*100,0) -> 0 | E9: =IFERROR(('APPENDIX 4'!E9/'APPENDIX 4'!E$31)*100,0) -> 0 | F9: =IFERROR(('APPENDIX 4'!F9/'APPENDIX 4'!F$31)*100,0) -> 0 | G9: =IFERROR(('APPENDIX 4'!G9/'APPENDIX 4'!G$31)*100,0) -> 3.1595635 | H9: =IFERROR(('APPENDIX 4'!H9/'APPENDIX 4'!H$31)*100,0) -> 0.074000572 | I9: =IFERROR(('APPENDIX 4'!I9/'APPENDIX 4'!I$31)*100,0) -> 0 | J9: =IFERROR(('APPENDIX 4'!J9/'APPENDIX 4'!J$31)*100,0) -> 0 | K9: =IFERROR(('APPENDIX 4'!K9/'APPENDIX 4'!K$31)*100,0) -> 0.44347467 | L9: =RANK(K9,$K$6:$K$30) -> 20
B10: ='APPENDIX 6'!B10 -> CAPEX LIFE ASSURANCE COMPANY | C10: =IFERROR(('APPENDIX 4'!C10/'APPENDIX 4'!C$31)*100,0) -> 0.065105049 | D10: =IFERROR(('APPENDIX 4'!D10/'APPENDIX 4'!D$31)*100,0) -> 3.876693 | E10: =IFERROR(('APPENDIX 4'!E10/'APPENDIX 4'!E$31)*100,0) -> 0 | F10: =IFERROR(('APPENDIX 4'!F10/'APPENDIX 4'!F$31)*100,0) -> 0 | G10: =IFERROR(('APPENDIX 4'!G10/'APPENDIX 4'!G$31)*100,0) -> 2.7927985 | H10: =IFERROR(('APPENDIX 4'!H10/'APPENDIX 4'!H$31)*100,0) -> 0.77603589 | I10: =IFERROR(('APPENDIX 4'!I10/'APPENDIX 4'!I$31)*100,0) -> 0 | J10: =IFERROR(('APPENDIX 4'!J10/'APPENDIX 4'!J$31)*100,0) -> 0 | K10: =IFERROR(('APPENDIX 4'!K10/'APPENDIX 4'!K$31)*100,0) -> 0.70816137 | L10: =RANK(K10,$K$6:$K$30) -> 18
B11: ='APPENDIX 6'!B11 -> CIC LIFE ASSURANCE COMPANY | C11: =IFERROR(('APPENDIX 4'!C11/'APPENDIX 4'!C$31)*100,0) -> 2.7617734 | D11: =IFERROR(('APPENDIX 4'!D11/'APPENDIX 4'!D$31)*100,0) -> 3.6163638 | E11: =IFERROR(('APPENDIX 4'!E11/'APPENDIX 4'!E$31)*100,0) -> 0 | F11: =IFERROR(('APPENDIX 4'!F11/'APPENDIX 4'!F$31)*100,0) -> 5.2363067 | G11: =IFERROR(('APPENDIX 4'!G11/'APPENDIX 4'!G$31)*100,0) -> 5.4273428 | H11: =IFERROR(('APPENDIX 4'!H11/'APPENDIX 4'!H$31)*100,0) -> 42.40016 | I11: =IFERROR(('APPENDIX 4'!I11/'APPENDIX 4'!I$31)*100,0) -> 0 | J11: =IFERROR(('APPENDIX 4'!J11/'APPENDIX 4'!J$31)*100,0) -> 0 | K11: =IFERROR(('APPENDIX 4'!K11/'APPENDIX 4'!K$31)*100,0) -> 7.5781407 | L11: =RANK(K11,$K$6:$K$30) -> 5
B12: ='APPENDIX 6'!B12 -> CORPORATE INSURANCE COMPANY | C12: =IFERROR(('APPENDIX 4'!C12/'APPENDIX 4'!C$31)*100,0) -> 0.07165347 | D12: =IFERROR(('APPENDIX 4'!D12/'APPENDIX 4'!D$31)*100,0) -> 0 | E12: =IFERROR(('APPENDIX 4'!E12/'APPENDIX 4'!E$31)*100,0) -> 0 | F12: =IFERROR(('APPENDIX 4'!F12/'APPENDIX 4'!F$31)*100,0) -> 0 | G12: =IFERROR(('APPENDIX 4'!G12/'APPENDIX 4'!G$31)*100,0) -> 0 | H12: =IFERROR(('APPENDIX 4'!H12/'APPENDIX 4'!H$31)*100,0) -> 0 | I12: =IFERROR(('APPENDIX 4'!I12/'APPENDIX 4'!I$31)*100,0) -> 0 | J12: =IFERROR(('APPENDIX 4'!J12/'APPENDIX 4'!J$31)*100,0) -> 0 | K12: =IFERROR(('APPENDIX 4'!K12/'APPENDIX 4'!K$31)*100,0) -> 0.015816332 | L12: =RANK(K12,$K$6:$K$30) -> 23
B13: ='APPENDIX 6'!B13 -> EQUITY LIFE ASSURANCE | C13: =IFERROR(('APPENDIX 4'!C13/'APPENDIX 4'!C$31)*100,0) -> 0 | D13: =IFERROR(('APPENDIX 4'!D13/'APPENDIX 4'!D$31)*100,0) -> 0 | E13: =IFERROR(('APPENDIX 4'!E13/'APPENDIX 4'!E$31)*100,0) -> 1.1841902 | F13: =IFERROR(('APPENDIX 4'!F13/'APPENDIX 4'!F$31)*100,0) -> 3.8430763 | G13: =IFERROR(('APPENDIX 4'!G13/'APPENDIX 4'!G$31)*100,0) -> 8.0224431 | H13: =IFERROR(('APPENDIX 4'!H13/'APPENDIX 4'!H$31)*100,0) -> 11.76133 | I13: =IFERROR(('APPENDIX 4'!I13/'APPENDIX 4'!I$31)*100,0) -> 0 | J13: =IFERROR(('APPENDIX 4'!J13/'APPENDIX 4'!J$31)*100,0) -> 3.7907133 | K13: =IFERROR(('APPENDIX 4'!K13/'APPENDIX 4'!K$31)*100,0) -> 3.885424 | L13: =RANK(K13,$K$6:$K$30) -> 8
B14: ='APPENDIX 6'!B14 -> GA LIFE ASSURANCE COMPANY | C14: =IFERROR(('APPENDIX 4'!C14/'APPENDIX 4'!C$31)*100,0) -> 0.15466544 | D14: =IFERROR(('APPENDIX 4'!D14/'APPENDIX 4'!D$31)*100,0) -> 0 | E14: =IFERROR(('APPENDIX 4'!E14/'APPENDIX 4'!E$31)*100,0) -> 6.1479008 | F14: =IFERROR(('APPENDIX 4'!F14/'APPENDIX 4'!F$31)*100,0) -> 30.564916 | G14: =IFERROR(('APPENDIX 4'!G14/'APPENDIX 4'!G$31)*100,0) -> 0.47910253 | H14: =IFERROR(('APPENDIX 4'!H14/'APPENDIX 4'!H$31)*100,0) -> 0.01616479 | I14: =IFERROR(('APPENDIX 4'!I14/'APPENDIX 4'!I$31)*100,0) -> 0 | J14: =IFERROR(('APPENDIX 4'!J14/'APPENDIX 4'!J$31)*100,0) -> 0 | K14: =IFERROR(('APPENDIX 4'!K14/'APPENDIX 4'!K$31)*100,0) -> 10.111631 | L14: =RANK(K14,$K$6:$K$30) -> 4
B15: ='APPENDIX 6'!B15 -> GEMINIA LIFE INSURANCE COMPANY | C15: =IFERROR(('APPENDIX 4'!C15/'APPENDIX 4'!C$31)*100,0) -> 0.14608663 | D15: =IFERROR(('APPENDIX 4'!D15/'APPENDIX 4'!D$31)*100,0) -> 0 | E15: =IFERROR(('APPENDIX 4'!E15/'APPENDIX 4'!E$31)*100,0) -> 3.2715661 | F15: =IFERROR(('APPENDIX 4'!F15/'APPENDIX 4'!F$31)*100,0) -> 3.6282547 | G15: =IFERROR(('APPENDIX 4'!G15/'APPENDIX 4'!G$31)*100,0) -> 1.7118016 | H15: =IFERROR(('APPENDIX 4'!H15/'APPENDIX 4'!H$31)*100,0) -> 1.4521818 | I15: =IFERROR(('APPENDIX 4'!I15/'APPENDIX 4'!I$31)*100,0) -> 0 | J15: =IFERROR(('APPENDIX 4'!J15/'APPENDIX 4'!J$31)*100,0) -> 4.1018935 | K15: =IFERROR(('APPENDIX 4'!K15/'APPENDIX 4'!K$31)*100,0) -> 2.1559721 | L15: =RANK(K15,$K$6:$K$30) -> 14
B16: ='APPENDIX 6'!B16 -> ICEA LION LIFE ASSURANCE | C16: =IFERROR(('APPENDIX 4'!C16/'APPENDIX 4'!C$31)*100,0) -> 15.800675 | D16: =IFERROR(('APPENDIX 4'!D16/'APPENDIX 4'!D$31)*100,0) -> 15.735768 | E16: =IFERROR(('APPENDIX 4'!E16/'APPENDIX 4'!E$31)*100,0) -> 37.74129 | F16: =IFERROR(('APPENDIX 4'!F16/'APPENDIX 4'!F$31)*100,0) -> 15.004255 | G16: =IFERROR(('APPENDIX 4'!G16/'APPENDIX 4'!G$31)*100,0) -> 2.6043188 | H16: =IFERROR(('APPENDIX 4'!H16/'APPENDIX 4'!H$31)*100,0) -> 0.63367019 | I16: =IFERROR(('APPENDIX 4'!I16/'APPENDIX 4'!I$31)*100,0) -> 0 | J16: =IFERROR(('APPENDIX 4'!J16/'APPENDIX 4'!J$31)*100,0) -> 0.031968807 | K16: =IFERROR(('APPENDIX 4'!K16/'APPENDIX 4'!K$31)*100,0) -> 13.066251 | L16: =RANK(K16,$K$6:$K$30) -> 3
B17: ='APPENDIX 6'!B17 -> JUBILEE LIFE INSURANCE | C17: =IFERROR(('APPENDIX 4'!C17/'APPENDIX 4'!C$31)*100,0) -> 14.39466 | D17: =IFERROR(('APPENDIX 4'!D17/'APPENDIX 4'!D$31)*100,0) -> 17.534888 | E17: =IFERROR(('APPENDIX 4'!E17/'APPENDIX 4'!E$31)*100,0) -> 13.300508 | F17: =IFERROR(('APPENDIX 4'!F17/'APPENDIX 4'!F$31)*100,0) -> 21.920805 | G17: =IFERROR(('APPENDIX 4'!G17/'APPENDIX 4'!G$31)*100,0) -> 5.8697224 | H17: =IFERROR(('APPENDIX 4'!H17/'APPENDIX 4'!H$31)*100,0) -> 1.6776082 | I17: =IFERROR(('APPENDIX 4'!I17/'APPENDIX 4'!I$31)*100,0) -> 0 | J17: =IFERROR(('APPENDIX 4'!J17/'APPENDIX 4'!J$31)*100,0) -> 0 | K17: =IFERROR(('APPENDIX 4'!K17/'APPENDIX 4'!K$31)*100,0) -> 13.238058 | L17: =RANK(K17,$K$6:$K$30) -> 2
B18: ='APPENDIX 6'!B18 -> KENINDIA ASSURANCE COMPANY | C18: =IFERROR(('APPENDIX 4'!C18/'APPENDIX 4'!C$31)*100,0) -> 5.7681031 | D18: =IFERROR(('APPENDIX 4'!D18/'APPENDIX 4'!D$31)*100,0) -> 2.9471525 | E18: =IFERROR(('APPENDIX 4'!E18/'APPENDIX 4'!E$31)*100,0) -> 6.6907025 | F18: =IFERROR(('APPENDIX 4'!F18/'APPENDIX 4'!F$31)*100,0) -> 4.8124161 | G18: =IFERROR(('APPENDIX 4'!G18/'APPENDIX 4'!G$31)*100,0) -> 0.33936433 | H18: =IFERROR(('APPENDIX 4'!H18/'APPENDIX 4'!H$31)*100,0) -> 0.00054470836 | I18: =IFERROR(('APPENDIX 4'!I18/'APPENDIX 4'!I$31)*100,0) -> 0 | J18: =IFERROR(('APPENDIX 4'!J18/'APPENDIX 4'!J$31)*100,0) -> 0 | K18: =IFERROR(('APPENDIX 4'!K18/'APPENDIX 4'!K$31)*100,0) -> 3.6167337 | L18: =RANK(K18,$K$6:$K$30) -> 9
... B30: ='APPENDIX 6'!B30 -> THE MONARCH INSURANCE | C30: =IFERROR(('APPENDIX 4'!C30/'APPENDIX 4'!C$31)*100,0) -> 0 | D30: =IFERROR(('APPENDIX 4'!D30/'APPENDIX 4'!D$31)*100,0) -> 0 | E30: =IFERROR(('APPENDIX 4'!E30/'APPENDIX 4'!E$31)*100,0) -> 0 | F30: =IFERROR(('APPENDIX 4'!F30/'APPENDIX 4'!F$31)*100,0) -> 0 | G30: =IFERROR(('APPENDIX 4'!G30/'APPENDIX 4'!G$31)*100,0) -> 0 | H30: =IFERROR(('APPENDIX 4'!H30/'APPENDIX 4'!H$31)*100,0) -> 0 | I30: =IFERROR(('APPENDIX 4'!I30/'APPENDIX 4'!I$31)*100,0) -> 0 | J30: =IFERROR(('APPENDIX 4'!J30/'APPENDIX 4'!J$31)*100,0) -> 0 | K30: =IFERROR(('APPENDIX 4'!K30/'APPENDIX 4'!K$31)*100,0) -> 0 | L30: =RANK(K30,$K$6:$K$30) -> 25
B31: TOTAL | C31: =SUM(C6:C30) -> 100 | D31: =SUM(D6:D30) -> 100 | E31: =SUM(E6:E30) -> 100 | F31: =SUM(F6:F30) -> 100 | G31: =SUM(G6:G30) -> 100 | H31: =SUM(H6:H30) -> 100 | I31: =SUM(I6:I30) -> 0 | J31: =SUM(J6:J30) -> 100 | K31: =SUM(K6:K30) -> 100
B32: REINSURERS
B33: ='APPENDIX 6'!B33 -> CONTINENTAL REINSURANCE | C33: =IFERROR(('APPENDIX 4'!C33/'APPENDIX 4'!C$36)*100,0) -> 0 | D33: =IFERROR(('APPENDIX 4'!D33/'APPENDIX 4'!D$36)*100,0) -> 0 | E33: =IFERROR(('APPENDIX 4'!E33/'APPENDIX 4'!E$36)*100,0) -> 0 | F33: =IFERROR(('APPENDIX 4'!F33/'APPENDIX 4'!F$36)*100,0) -> 0 | G33: =IFERROR(('APPENDIX 4'!G33/'APPENDIX 4'!G$36)*100,0) -> 2.0748532 | H33: =IFERROR(('APPENDIX 4'!H33/'APPENDIX 4'!H$36)*100,0) -> 0 | I33: =IFERROR(('APPENDIX 4'!I33/'APPENDIX 4'!I$36)*100,0) -> 0 | J33: =IFERROR(('APPENDIX 4'!J33/'APPENDIX 4'!J$36)*100,0) -> 0 | K33: =IFERROR(('APPENDIX 4'!K33/'APPENDIX 4'!K$36)*100,0) -> 1.9511532
B34: ='APPENDIX 6'!B34 -> EAST AFRICA REINSURANCE | C34: =IFERROR(('APPENDIX 4'!C34/'APPENDIX 4'!C$36)*100,0) -> 48.669466 | D34: =IFERROR(('APPENDIX 4'!D34/'APPENDIX 4'!D$36)*100,0) -> 0 | E34: =IFERROR(('APPENDIX 4'!E34/'APPENDIX 4'!E$36)*100,0) -> 0 | F34: =IFERROR(('APPENDIX 4'!F34/'APPENDIX 4'!F$36)*100,0) -> 0 | G34: =IFERROR(('APPENDIX 4'!G34/'APPENDIX 4'!G$36)*100,0) -> 29.550985 | H34: =IFERROR(('APPENDIX 4'!H34/'APPENDIX 4'!H$36)*100,0) -> 0 | I34: =IFERROR(('APPENDIX 4'!I34/'APPENDIX 4'!I$36)*100,0) -> 0 | J34: =IFERROR(('APPENDIX 4'!J34/'APPENDIX 4'!J$36)*100,0) -> 0 | K34: =IFERROR(('APPENDIX 4'!K34/'APPENDIX 4'!K$36)*100,0) -> 30.690803
B35: ='APPENDIX 6'!B35 -> KENYA REINSURANCE CORPORATION | C35: =IFERROR(('APPENDIX 4'!C35/'APPENDIX 4'!C$36)*100,0) -> 51.330534 | D35: =IFERROR(('APPENDIX 4'!D35/'APPENDIX 4'!D$36)*100,0) -> 0 | E35: =IFERROR(('APPENDIX 4'!E35/'APPENDIX 4'!E$36)*100,0) -> 0 | F35: =IFERROR(('APPENDIX 4'!F35/'APPENDIX 4'!F$36)*100,0) -> 0 | G35: =IFERROR(('APPENDIX 4'!G35/'APPENDIX 4'!G$36)*100,0) -> 68.374162 | H35: =IFERROR(('APPENDIX 4'!H35/'APPENDIX 4'!H$36)*100,0) -> 0 | I35: =IFERROR(('APPENDIX 4'!I35/'APPENDIX 4'!I$36)*100,0) -> 0 | J35: =IFERROR(('APPENDIX 4'!J35/'APPENDIX 4'!J$36)*100,0) -> 0 | K35: =IFERROR(('APPENDIX 4'!K35/'APPENDIX 4'!K$36)*100,0) -> 67.358044
B36: TOTAL | C36: =SUM(C33:C35) -> 100 | D36: =SUM(D33:D35) -> 0 | E36: =SUM(E33:E35) -> 0 | F36: =SUM(F33:F35) -> 0 | G36: =SUM(G33:G35) -> 100 | H36: =SUM(H33:H35) -> 0 | I36: =SUM(I33:I35) -> 0 | J36: =SUM(J33:J35) -> 0 | K36: =SUM(K33:K35) -> 100
B37: Figures in %

Sheet APPENDIX 6
B3: =_xlfn.CONCAT('Table of Contents'!B13,": ",'Table of Contents'!C13) -> APPENDIX 6: SUMMARY OF LIFE ASSURANCE BUSINESS REVENUE ACCOUNTS FOR THE PERIOD ENDED 31.03.2025
B4: Company | C4: Life Fund BF | D4: Gross Premium | E4: Net Premium | F4: Other (Fee) Income | G4: Total Benefits | H4: Claims | I4: Surrenders_x000D_ | J4: Bonuses Paid | K4: Annuities Paid | L4: Net Commisions | M4: Expense of Management | N4: Investment Income | O4: Investment Expenses | P4: Transfer To (From) P & L | Q4: Life Fund CF
B5: INSURERS
B6: ABSA LIFE ASSURANCE | C6: 10636609 | D6: 1419720.3 | E6: 1409541.5 | F6: 0 | G6: 451168.12 | H6: 451168.12 | I6: 0 | J6: 0 | K6: 0 | L6: 204810.99 | M6: 87691.463 | N6: 381924.46 | O6: 0 | P6: 0 | Q6: 11684404
B7: APA LIFE ASSURANCE COMPANY | C7: 995078.63 | D7: 140563.62 | E7: 137275.5 | F7: 0 | G7: 49906.008 | H7: 49906.008 | I7: 0 | J7: 0 | K7: 0 | L7: 14935.125 | M7: 32405.377 | N7: 32414.031 | O7: 320.89121 | P7: 0 | Q7: 1067200.8
B8: BRITAM LIFE ASSURANCE | C8: 43886184 | D8: 2845011 | E8: 2843523.8 | F8: -15078.871 | G8: 2025235.4 | H8: 2025235.4 | I8: 0 | J8: 0 | K8: 0 | L8: 377857.62 | M8: 577779.63 | N8: 2646290.5 | O8: 35659.441 | P8: 108220.34 | Q8: 46236167
B9: CANNON LIFE ASSURANCE (K) LIMITED | C9: 527806.79 | D9: 6556.598 | E9: 6398.732 | F9: 0 | G9: 19258.763 | H9: 19258.763 | I9: 0 | J9: 0 | K9: 0 | L9: -328.957 | M9: 15355.272 | N9: 11144.338 | O9: 0 | P9: 0 | Q9: 511064.78
B10: CAPEX LIFE ASSURANCE COMPANY | C10: 33226.715 | D10: 7679.969 | E10: 7679.969 | F10: 0 | G10: 1174.0861 | H10: 1174.0861 | I10: 0 | J10: 0 | K10: 0 | L10: 414.18722 | M10: 2069.9568 | N10: 270.56587 | O10: 0 | P10: 0 | Q10: 37519.02
B11: CIC LIFE ASSURANCE COMPANY | C11: 5139412.2 | D11: 325786.32 | E11: 304364.72 | F11: 0 | G11: 211040.38 | H11: 211040.38 | I11: 0 | J11: 0 | K11: 0 | L11: 42444.646 | M11: 76054.005 | N11: 113755.69 | O11: 0 | P11: 0 | Q11: 5227993.6
B12: CORPORATE INSURANCE COMPANY | C12: 73832.62 | D12: 8452.4385 | E12: 8452.4385 | F12: 0 | G12: 51459.937 | H12: 51459.937 | I12: 0 | J12: 0 | K12: 0 | L12: 0 | M12: 1795.0758 | N12: 0 | O12: 0 | P12: 0 | Q12: 29030.046
B13: EQUITY LIFE ASSURANCE | C13: 0 | D13: 0 | E13: 0 | F13: 0 | G13: 0 | H13: 0 | I13: 0 | J13: 0 | K13: 0 | L13: 0 | M13: 0 | N13: 0 | O13: 0 | P13: 0 | Q13: 0
B14: GA LIFE ASSURANCE COMPANY | C14: 4094574 | D14: 18244.757 | E14: 18244.757 | F14: 0 | G14: 16018.311 | H14: 16018.311 | I14: 0 | J14: 0 | K14: 0 | L14: 258 | M14: 75.1867 | N14: 314280.72 | O14: 0 | P14: 0 | Q14: 4410747.9
B15: GEMINIA LIFE INSURANCE COMPANY | C15: 423624.61 | D15: 17232.776 | E15: 17232.776 | F15: 0 | G15: 17219.716 | H15: 17219.716 | I15: 0 | J15: 0 | K15: 0 | L15: 2452.1477 | M15: 7178.0856 | N15: 6146.895 | O15: 0 | P15: 0 | Q15: 420154.33
B16: ICEA LION LIFE ASSURANCE | C16: 22398339 | D16: 1863890.6 | E16: 1844086.3 | F16: 0 | G16: 950476.66 | H16: 766843.57 | I16: 183633.09 | J16: 0 | K16: 0 | L16: 361276.98 | M16: 341572.81 | N16: 777397.74 | O16: 0 | P16: 0 | Q16: 23366497
B17: JUBILEE LIFE INSURANCE | C17: 13044508 | D17: 1698033.3 | E17: 1693593.4 | F17: 0 | G17: 1194266.8 | H17: 1194266.8 | I17: 0 | J17: 0 | K17: 0 | L17: 213878.19 | M17: 183235.76 | N17: 1091820.5 | O17: 3952.5977 | P17: 0 | Q17: 14234588
... B30: THE MONARCH INSURANCE | C30: 0 | D30: 0 | E30: 0 | F30: 0 | G30: 0 | H30: 0 | I30: 0 | J30: 0 | K30: 0 | L30: 0 | M30: 0 | N30: 0 | O30: 0 | P30: 0 | Q30: 0
B31: TOTAL | C31: =SUM(C6:C30) -> 1.5416208e+08 | D31: =SUM(D6:D30) -> 11796272 | E31: =SUM(E6:E30) -> 11668238 | F31: =SUM(F6:F30) -> 51704.138 | G31: =SUM(G6:G30) -> 7413025.3 | H31: =SUM(H6:H30) -> 7246710.9 | I31: =SUM(I6:I30) -> 183633.09 | J31: =SUM(J6:J30) -> -17318.718 | ... Q31: =SUM(Q6:Q30) -> 1.6105419e+08
B32: REINSURERS
B33: CONTINENTAL REINSURANCE | C33: 0 | D33: 0 | E33: 0 | F33: 0 | G33: 0 | H33: 0 | I33: 0 | J33: 0 | K33: 0 | L33: 0 | M33: 0 | N33: 0 | O33: 0 | P33: 0 | Q33: 0
B34: EAST AFRICA REINSURANCE | C34: 139860.33 | D34: 34147.043 | E34: 28491.054 | F34: 0 | G34: 7061.0911 | H34: 7061.0911 | I34: 0 | J34: 0 | K34: 0 | L34: 7359.1425 | M34: 1989.7898 | N34: 6229.956 | O34: 279.72185 | P34: 0 | Q34: 157891.6
B35: KENYA REINSURANCE CORPORATION | C35: 430383.33 | D35: 36014.078 | E35: 36014.078 | F35: 0 | G35: 607.114 | H35: 607.114 | I35: 0 | J35: 0 | K35: 0 | L35: 17610.706 | M35: 13108.819 | N35: 9357.049 | O35: 0 | P35: 0 | Q35: 444427.82
B36: TOTAL | C36: =SUM(C33:C35) -> 570243.66 | D36: =SUM(D33:D35) -> 70161.121 | E36: =SUM(E33:E35) -> 64505.132 | F36: =SUM(F33:F35) -> 0 | G36: =SUM(G33:G35) -> 7668.2051 | H36: =SUM(H33:H35) -> 7668.2051 | I36: =SUM(I33:I35) -> 0 | J36: =SUM(J33:J35) -> 0 | ... Q36: =SUM(Q33:Q35) -> 602319.42
B37: Amounts in Thousand Shillings
C38: =C36+C31 -> 1.5473232e+08 | D38: =D36+D31 -> 11866434 | E38: =E36+E31 -> 11732743 | F38: =F36+F31 -> 51704.138 | G38: =G36+G31 -> 7420693.5 | H38: =H36+H31 -> 7254379.1 | I38: =I36+I31 -> 183633.09 | J38: =J36+J31 -> -17318.718 | ... Q38: =Q36+Q31 -> 1.6165651e+08

Sheet APPENDIX 7
B3: =_xlfn.CONCAT('Table of Contents'!B14,": ",'Table of Contents'!C14) -> APPENDIX 7: SUMMARY OF ANNUITIES BUSINESS REVENUE ACCOUNTS FOR THE PERIOD ENDED 31.03.2025
B4: Company | C4: Life Fund BF | D4: Gross Premium | E4: Net Premium | F4: Other (Fee) Income | G4: Total Benefits | H4: Claims | I4: Surrenders_x000D_ | J4: Bonuses Paid | K4: Annuities Paid | L4: Net Commisions | M4: Expense of Management | N4: Investment Income | O4: Investment Expenses | P4: Transfer To (From) P & L | Q4: Life Fund CF
B5: INSURERS
B6: ABSA LIFE ASSURANCE | C6: 0 | D6: 0 | E6: 0 | F6: 0 | G6: 0 | H6: 0 | I6: 0 | J6: 0 | K6: 0 | L6: 0 | M6: 0 | N6: 0 | O6: 0 | P6: 0 | Q6: 0
B7: APA LIFE ASSURANCE COMPANY | C7: 1015040.1 | D7: 18694.998 | E7: 18694.998 | F7: 0 | G7: 40603.681 | H7: 40603.681 | I7: 0 | J7: 0 | K7: 0 | L7: 0 | M7: 2218.2519 | N7: 14052.191 | O7: 55.754074 | P7: 0 | Q7: 1004909.6
B8: BRITAM LIFE ASSURANCE | C8: 24059616 | D8: 1516175.6 | E8: 1516175.6 | F8: 0 | G8: 787650.57 | H8: 787650.57 | I8: 0 | J8: 0 | K8: 0 | L8: 30046.709 | M8: 20486.333 | N8: 2987463.3 | O8: 9066.6004 | P8: 22856.322 | Q8: 27693149
B9: CANNON LIFE ASSURANCE (K) LIMITED | C9: 11532.723 | D9: 0 | E9: 0 | F9: 0 | G9: 327.37725 | H9: 327.37725 | I9: 0 | J9: 0 | K9: 0 | L9: 0 | M9: 0 | N9: 0 | O9: 0 | P9: 0 | Q9: 11205.346
B10: CAPEX LIFE ASSURANCE COMPANY | C10: 862965.63 | D10: 127646.8 | E10: 127646.8 | F10: 0 | G10: 106748.06 | H10: 106748.06 | I10: 0 | J10: 0 | K10: 0 | L10: 6400.2924 | M10: 34404.227 | N10: 4497.0066 | O10: 0 | P10: 0 | Q10: 847556.85
B11: CIC LIFE ASSURANCE COMPANY | C11: 1829277.5 | D11: 119075.01 | E11: 119075.01 | F11: 0 | G11: 85608.618 | H11: 85608.618 | I11: 0 | J11: 0 | K11: 0 | L11: 2115.121 | M11: 5963.6513 | N11: 69925.733 | O11: 0 | P11: 0 | Q11: 1924590.9
B12: CORPORATE INSURANCE COMPANY | C12: 0 | D12: 0 | E12: 0 | F12: 0 | G12: 0 | H12: 0 | I12: 0 | J12: 0 | K12: 0 | L12: 0 | M12: 0 | N12: 0 | O12: 0 | P12: 0 | Q12: 0
B13: EQUITY LIFE ASSURANCE | C13: 0 | D13: 0 | E13: 0 | F13: 0 | G13: 0 | H13: 0 | I13: 0 | J13: 0 | K13: 0 | L13: 0 | M13: 0 | N13: 0 | O13: 0 | P13: 0 | Q13: 0
B14: GA LIFE ASSURANCE COMPANY | C14: 0 | D14: 0 | E14: 0 | F14: 0 | G14: 0 | H14: 0 | I14: 0 | J14: 0 | K14: 0 | L14: 0 | M14: 0 | N14: 0 | O14: 0 | P14: 0 | Q14: 0
B15: GEMINIA LIFE INSURANCE COMPANY | C15: 0 | D15: 0 | E15: 0 | F15: 0 | G15: 0 | H15: 0 | I15: 0 | J15: 0 | K15: 0 | L15: 0 | M15: 0 | N15: 0 | O15: 0 | P15: 0 | Q15: 0
B16: ICEA LION LIFE ASSURANCE | C16: 22651302 | D16: 518127.29 | E16: 518127.29 | F16: 0 | G16: 644708.92 | H16: 20312.706 | I16: 0 | J16: 0 | K16: 624396.22 | L16: 8225.4073 | M16: 11418.054 | N16: 2275980.1 | O16: 0 | P16: 0 | Q16: 24781057
B17: JUBILEE LIFE INSURANCE | C17: 12997600 | D17: 577366.4 | E17: 577366.4 | F17: 0 | G17: 414386.22 | H17: 414386.22 | I17: 0 | J17: 0 | K17: 0 | L17: 9784.612 | M17: 2854.494 | N17: 1327119.4 | O17: 3646.73 | P17: 0 | Q17: 14471414
... B30: THE MONARCH INSURANCE | C30: 0 | D30: 0 | E30: 0 | F30: 0 | G30: 0 | H30: 0 | I30: 0 | J30: 0 | K30: 0 | L30: 0 | M30: 0 | N30: 0 | O30: 0 | P30: 0 | Q30: 0
B31: TOTAL | C31: =SUM(C6:C30) -> 95757120 | D31: =SUM(D6:D30) -> 3292672.4 | E31: =SUM(E6:E30) -> 3292672.4 | F31: =SUM(F6:F30) -> 0 | G31: =SUM(G6:G30) -> 3157213.5 | H31: =SUM(H6:H30) -> 2526072.5 | I31: =SUM(I6:I30) -> 0 | J31: =SUM(J6:J30) -> 6744.7092 | ... Q31: =SUM(Q6:Q30) -> 1.0464428e+08
B32: REINSURERS
B33: CONTINENTAL REINSURANCE | C33: 0 | D33: 0 | E33: 0 | F33: 0 | G33: 0 | H33: 0 | I33: 0 | J33: 0 | K33: 0 | L33: 0 | M33: 0 | N33: 0 | O33: 0 | P33: 0 | Q33: 0
B34: EAST AFRICA REINSURANCE | C34: 0 | D34: 0 | E34: 0 | F34: 0 | G34: 0 | H34: 0 | I34: 0 | J34: 0 | K34: 0 | L34: 0 | M34: 0 | N34: 0 | O34: 0 | P34: 0 | Q34: 0
B35: KENYA REINSURANCE CORPORATION | C35: 0 | D35: 0 | E35: 0 | F35: 0 | G35: 0 | H35: 0 | I35: 0 | J35: 0 | K35: 0 | L35: 0 | M35: 0 | N35: 0 | O35: 0 | P35: 0 | Q35: 0
B36: TOTAL | C36: =SUM(C33:C35) -> 0 | D36: =SUM(D33:D35) -> 0 | E36: =SUM(E33:E35) -> 0 | F36: =SUM(F33:F35) -> 0 | G36: =SUM(G33:G35) -> 0 | H36: =SUM(H33:H35) -> 0 | I36: =SUM(I33:I35) -> 0 | J36: =SUM(J33:J35) -> 0 | ... Q36: =SUM(Q33:Q35) -> 0
B37: Amounts in Thousand Shillings

Sheet APPENDIX 8
B3: =_xlfn.CONCAT('Table of Contents'!B15,": ",'Table of Contents'!C15) -> APPENDIX 8: SUMMARY OF GROUP LIFE BUSINESS REVENUE ACCOUNTS FOR THE PERIOD ENDED 31.03.2025
B4: Company | C4: Life Fund BF | D4: Gross Premium | E4: Net Premium | F4: Other (Fee) Income | G4: Total Benefits | H4: Claims | I4: Surrenders_x000D_ | J4: Bonuses Paid | K4: Annuities Paid | L4: Net Commisions | M4: Expense of Management | N4: Investment Income | O4: Investment Expenses | P4: Transfer To (From) P & L | Q4: Life Fund CF
B5: INSURERS
B6: ABSA LIFE ASSURANCE | C6: 454028.71 | D6: 1397419.6 | E6: 645621.89 | F6: 0 | G6: 665879.69 | H6: 665879.69 | I6: 0 | J6: 0 | K6: 0 | L6: 32555.169 | M6: 106292.68 | N6: 12669.187 | O6: 0 | P6: 0 | Q6: 307592.25
B7: APA LIFE ASSURANCE COMPANY | C7: 639163.48 | D7: 750660.01 | E7: 213990.34 | F7: 0 | G7: 92797.424 | H7: 92797.424 | I7: 0 | J7: 0 | K7: 0 | L7: -59731.331 | M7: 54607.722 | N7: 60340.593 | O7: 2238.6926 | P7: 0 | Q7: 823581.91
B8: BRITAM LIFE ASSURANCE | C8: 2772767 | D8: 500832.27 | E8: 288136.79 | F8: 0 | G8: 118450.09 | H8: 118450.09 | I8: 0 | J8: 0 | K8: 0 | L8: -73739.994 | M8: 83358.407 | N8: 144439.08 | O8: -80.92076 | P8: 137101.29 | Q8: 2940254
B9: CANNON LIFE ASSURANCE (K) LIMITED | C9: 168205.61 | D9: 226335.44 | E9: 162537.25 | F9: 0 | G9: 23117.277 | H9: 23117.277 | I9: 0 | J9: 0 | K9: 0 | L9: 16799.638 | M9: 28804.936 | N9: 20905.648 | O9: 0 | P9: 0 | Q9: 282926.66
B10: CAPEX LIFE ASSURANCE COMPANY | C10: 335333.11 | D10: 200062.22 | E10: 140222.29 | F10: 0 | G10: 96013.963 | H10: 96013.963 | I10: 0 | J10: 0 | K10: 0 | L10: 57444.104 | M10: 53922.119 | N10: 7048.2073 | O10: 0 | P10: 0 | Q10: 275223.42
B11: CIC LIFE ASSURANCE COMPANY | C11: 1654152.2 | D11: 388787.88 | E11: 1322650 | F11: 0 | G11: 147787.29 | H11: 147787.29 | I11: 0 | J11: 0 | K11: 0 | L11: -180283.35 | M11: 103732.13 | N11: 297004.79 | O11: 0 | P11: 0 | Q11: 3202571
B12: CORPORATE INSURANCE COMPANY | C12: 0 | D12: 0 | E12: 0 | F12: 0 | G12: 0 | H12: 0 | I12: 0 | J12: 0 | K12: 0 | L12: 0 | M12: 0 | N12: 0 | O12: 0 | P12: 0 | Q12: 0
B13: EQUITY LIFE ASSURANCE | C13: 587628.71 | D13: 574687.98 | E13: 193862.11 | F13: 0 | G13: 21004.975 | H13: 21004.975 | I13: 0 | J13: 0 | K13: 0 | L13: -82823.103 | M13: 13439.96 | N13: 81534.865 | O13: 0 | P13: 0 | Q13: 911403.86
B14: GA LIFE ASSURANCE COMPANY | C14: 27060.958 | D14: 34320.526 | E14: 1976.779 | F14: 0 | G14: 1481.6327 | H14: 1481.6327 | I14: 0 | J14: 0 | K14: 0 | L14: -24583.933 | M14: 6319.5804 | N14: 959.23479 | O14: 0 | P14: 0 | Q14: 46779.692
B15: GEMINIA LIFE INSURANCE COMPANY | C15: 1007272.1 | D15: 122624.96 | E15: 90886.962 | F15: 0 | G15: 131199.95 | H15: 131199.95 | I15: 0 | J15: 0 | K15: 0 | L15: 13773.206 | M15: 46331.28 | N15: 0 | O15: 0 | P15: 0 | Q15: 906854.67
B16: ICEA LION LIFE ASSURANCE | C16: 433367.02 | D16: 186560.47 | E16: 100977.86 | F16: 0 | G16: 35627.835 | H16: 35627.835 | I16: 0 | J16: 0 | K16: 0 | L16: -7528.4667 | M16: 38974.28 | N16: 13069.638 | O16: 0 | P16: 0 | Q16: 480340.87
B17: JUBILEE LIFE INSURANCE | C17: 747633.55 | D17: 420477.76 | E17: 185931.17 | F17: 0 | G17: 119419.83 | H17: 119419.83 | I17: 0 | J17: 0 | K17: 0 | L17: -8395.651 | M17: 34178.713 | N17: 41870.618 | O17: 348.57769 | P17: 0 | Q17: 829883.86
... B30: THE MONARCH INSURANCE | C30: 0 | D30: 0 | E30: 0 | F30: 0 | G30: 0 | H30: 0 | I30: 0 | J30: 0 | K30: 0 | L30: 0 | M30: 0 | N30: 0 | O30: 0 | P30: 0 | Q30: 0
B31: TOTAL | C31: =SUM(C6:C30) -> 15381348 | D31: =SUM(D6:D30) -> 7163503.3 | E31: =SUM(E6:E30) -> 4925860 | F31: =SUM(F6:F30) -> -211950.23 | G31: =SUM(G6:G30) -> 2305916.8 | H31: =SUM(H6:H30) -> 2146998.9 | I31: =SUM(I6:I30) -> 0 | J31: =SUM(J6:J30) -> 158917.94 | ... Q31: =SUM(Q6:Q30) -> 18178817
B32: REINSURERS
B33: CONTINENTAL REINSURANCE | C33: 0 | D33: 22961.78 | E33: 22961.78 | F33: 0 | G33: 16283.717 | H33: 16283.717 | I33: 0 | J33: 0 | K33: 0 | L33: 7104.372 | M33: 1924.579 | N33: 16974.278 | O33: 0 | P33: 0 | Q33: 14623.39
B34: EAST AFRICA REINSURANCE | C34: 1039475.6 | D34: 327031.9 | E34: 272863.56 | F34: 0 | G34: 142805.84 | H34: 142805.84 | I34: 0 | J34: 0 | K34: 0 | L34: 70479.731 | M34: 19056.548 | N34: 59665.324 | O34: 2678.9427 | P34: 0 | Q34: 1136983.4
B35: KENYA REINSURANCE CORPORATION | C35: 7951511.7 | D35: 756676.39 | E35: 756676.39 | F35: 0 | G35: 407146.77 | H35: 407146.77 | I35: 0 | J35: 0 | K35: 0 | L35: 322380.52 | M35: 117979.36 | N35: 196531.02 | O35: 0 | P35: 0 | Q35: 8057212.4
B36: TOTAL | C36: =SUM(C33:C35) -> 8990987.3 | D36: =SUM(D33:D35) -> 1106670.1 | E36: =SUM(E33:E35) -> 1052501.7 | F36: =SUM(F33:F35) -> 0 | G36: =SUM(G33:G35) -> 566236.33 | H36: =SUM(H33:H35) -> 566236.33 | I36: =SUM(I33:I35) -> 0 | J36: =SUM(J33:J35) -> 0 | ... Q36: =SUM(Q33:Q35) -> 9208819.2
B37: Amounts in Thousand Shillings
C38: =C31+C36 -> 24372335 | D38: =D31+D36 -> 8270173.4 | E38: =E31+E36 -> 5978361.7 | F38: =F31+F36 -> -211950.23 | G38: =G31+G36 -> 2872153.1 | H38: =H31+H36 -> 2713235.2 | I38: =I31+I36 -> 0 | J38: =J31+J36 -> 158917.94 | ... Q38: =Q31+Q36 -> 27387636

Sheet APPENDIX 9
B3: =_xlfn.CONCAT('Table of Contents'!B16,": ",'Table of Contents'!C16) -> APPENDIX 9: SUMMARY OF GROUP CREDIT BUSINESS REVENUE ACCOUNTS FOR THE PERIOD ENDED 31.03.2025
B4: Company | C4: Life Fund BF | D4: Gross Premium | E4: Net Premium | F4: Other (Fee) Income | G4: Total Benefits | H4: Claims | I4: Surrenders_x000D_ | J4: Bonuses Paid | K4: Annuities Paid | L4: Net Commisions | M4: Expense of Management | N4: Investment Income | O4: Investment Expenses | P4: Transfer To (From) P & L | Q4: Life Fund CF
B5: INSURERS
B6: ABSA LIFE ASSURANCE | C6: 1902798.6 | D6: 155932.11 | E6: 144810.46 | F6: 0 | G6: 84024.795 | H6: 84024.795 | I6: 0 | J6: 0 | K6: 0 | L6: 89695.531 | M6: 71747.561 | N6: 65098.718 | O6: 0 | P6: 0 | Q6: 1867239.9
B7: APA LIFE ASSURANCE COMPANY | C7: 1019232.3 | D7: 190625.79 | E7: 180999.75 | F7: 0 | G7: 184317.28 | H7: 184317.28 | I7: 0 | J7: 0 | K7: 0 | L7: 95051.295 | M7: 2411.848 | N7: 15323.147 | O7: 568.50311 | P7: 0 | Q7: 933206.27
B8: BRITAM LIFE ASSURANCE | C8: -415879.34 | D8: 120684.12 | E8: 120784.99 | F8: 0 | G8: 74465.91 | H8: 74465.91 | I8: 0 | J8: 0 | K8: 0 | L8: 17427.138 | M8: 49958.328 | N8: 84436.799 | O8: 581.08516 | P8: 108777.62 | Q8: -461867.63
B9: CANNON LIFE ASSURANCE (K) LIMITED | C9: -4966.8409 | D9: 4106.174 | E9: 3812.5215 | F9: 0 | G9: 1495.72 | H9: 1495.72 | I9: 0 | J9: 0 | K9: 0 | L9: -83.690959 | M9: 4310.865 | N9: 3128.679 | O9: 0 | P9: 0 | Q9: -3748.5344
B10: CAPEX LIFE ASSURANCE COMPANY | C10: 28980.046 | D10: 43060.997 | E10: 37696.122 | F10: 0 | G10: 8952.1892 | H10: 8952.1892 | I10: 0 | J10: 0 | K10: 0 | L10: -1448.5163 | M10: 11606.091 | N10: 1517.0423 | O10: 0 | P10: 0 | Q10: 49083.447
B11: CIC LIFE ASSURANCE COMPANY | C11: 6623757.7 | D11: 2352717.4 | E11: 2352717.4 | F11: 0 | G11: 572911.27 | H11: 572911.27 | I11: 0 | J11: 0 | K11: 0 | L11: 0 | M11: 322731.41 | N11: 0 | O11: 0 | P11: 0 | Q11: 8080832.4
B12: CORPORATE INSURANCE COMPANY | C12: 0 | D12: 0 | E12: 0 | F12: 0 | G12: 0 | H12: 0 | I12: 0 | J12: 0 | K12: 0 | L12: 0 | M12: 0 | N12: 0 | O12: 0 | P12: 0 | Q12: 0
B13: EQUITY LIFE ASSURANCE | C13: 6283361 | D13: 652617.51 | E13: 703178.52 | F13: 0 | G13: 65409.645 | H13: 65409.645 | I13: 0 | J13: 0 | K13: 0 | L13: 48996.095 | M13: 134349.97 | N13: 178179.94 | O13: 0 | P13: 0 | Q13: 6915963.8
B14: GA LIFE ASSURANCE COMPANY | C14: 1843.319 | D14: 896.95848 | E14: 15.611479 | F14: 0 | G14: -13.914 | H14: -13.914 | I14: 0 | J14: 0 | K14: 0 | L14: -181.4086 | M14: 160.48429 | N14: 24.359609 | O14: 0 | P14: 0 | Q14: 1918.1284
B15: GEMINIA LIFE INSURANCE COMPANY | C15: 384576.65 | D15: 80579.255 | E15: 80579.255 | F15: 0 | G15: 6585.036 | H15: 6585.036 | I15: 0 | J15: 0 | K15: 0 | L15: 12560.999 | M15: 10440.852 | N15: 0 | O15: 0 | P15: 0 | Q15: 435569.02
B16: ICEA LION LIFE ASSURANCE | C16: 125908.65 | D16: 35161.351 | E16: 22511.696 | F16: 0 | G16: 61767.115 | H16: 61767.115 | I16: 0 | J16: 0 | K16: 0 | L16: -369.91438 | M16: 31751.262 | N16: 6120.631 | O16: 0 | P16: 0 | Q16: 61392.516
B17: JUBILEE LIFE INSURANCE | C17: 304867.38 | D17: 93087.809 | E17: 89388.394 | F17: 0 | G17: 4156.173 | H17: 4156.173 | I17: 0 | J17: 0 | K17: 0 | L17: 15855.882 | M17: 8807.4519 | N17: 9583.7053 | O17: 77.574821 | P17: 0 | Q17: 374942.39
... B30: THE MONARCH INSURANCE | C30: 0 | D30: 0 | E30: 0 | F30: 0 | G30: 0 | H30: 0 | I30: 0 | J30: 0 | K30: 0 | L30: 0 | M30: 0 | N30: 0 | O30: 0 | P30: 0 | Q30: 0
B31: TOTAL | C31: =SUM(C6:C30) -> 21767359 | D31: =SUM(D6:D30) -> 5548840.9 | E31: =SUM(E6:E30) -> 5259069.1 | F31: =SUM(F6:F30) -> -103747.88 | G31: =SUM(G6:G30) -> 1863974.9 | H31: =SUM(H6:H30) -> 1863974.9 | I31: =SUM(I6:I30) -> 0 | J31: =SUM(J6:J30) -> 0 | ... Q31: =SUM(Q6:Q30) -> 24023195
B32: REINSURERS
B33: CONTINENTAL REINSURANCE | C33: 0 | D33: 0 | E33: 0 | F33: 0 | G33: 0 | H33: 0 | I33: 0 | J33: 0 | K33: 0 | L33: 0 | M33: 0 | N33: 0 | O33: 0 | P33: 0 | Q33: 0
B34: EAST AFRICA REINSURANCE | C34: 0 | D34: 0 | E34: 0 | F34: 0 | G34: 0 | H34: 0 | I34: 0 | J34: 0 | K34: 0 | L34: 0 | M34: 0 | N34: 0 | O34: 0 | P34: 0 | Q34: 0
B35: KENYA REINSURANCE CORPORATION | C35: 0 | D35: 0 | E35: 0 | F35: 0 | G35: 0 | H35: 0 | I35: 0 | J35: 0 | K35: 0 | L35: 0 | M35: 0 | N35: 0 | O35: 0 | P35: 0 | Q35: 0
B36: TOTAL | C36: =SUM(C33:C35) -> 0 | D36: =SUM(D33:D35) -> 0 | E36: =SUM(E33:E35) -> 0 | F36: =SUM(F33:F35) -> 0 | G36: =SUM(G33:G35) -> 0 | H36: =SUM(H33:H35) -> 0 | I36: =SUM(I33:I35) -> 0 | J36: =SUM(J33:J35) -> 0 | ... Q36: =SUM(Q33:Q35) -> 0
B37: Amounts in Thousand Shillings

Sheet APPENDIX 10
B3: =_xlfn.CONCAT('Table of Contents'!B17,": ",'Table of Contents'!C17) -> APPENDIX 10: SUMMARY OF INVESTMENTS BUSINESS REVENUE ACCOUNTS FOR THE PERIOD ENDED 31.03.2025
B4: Company | C4: Life Fund BF | D4: Gross Premium | E4: Net Premium | F4: Other (Fee) Income | G4: Total Benefits | H4: Claims | I4: Surrenders_x000D_ | J4: Bonuses Paid | K4: Annuities Paid | L4: Net Commisions | M4: Expense of Management | N4: Investment Income | O4: Investment Expenses | P4: Transfer To (From) P & L | Q4: Life Fund CF
B5: INSURERS
B6: =LINKED!B6 -> ABSA LIFE ASSURANCE | C6: =+LINKED!C6+'NON-LINKED'!C6 -> 0 | D6: =+LINKED!D6+'NON-LINKED'!D6 -> 0 | E6: =+LINKED!E6+'NON-LINKED'!E6 -> 0 | F6: =+LINKED!F6+'NON-LINKED'!F6 -> 0 | G6: =+LINKED!G6+'NON-LINKED'!G6 -> 0 | H6: =+LINKED!H6+'NON-LINKED'!H6 -> 0 | I6: =+LINKED!I6+'NON-LINKED'!I6 -> 0 | J6: =+LINKED!J6+'NON-LINKED'!J6 -> 0 | ... Q6: =+LINKED!Q6+'NON-LINKED'!Q6 -> 0
B7: =LINKED!B7 -> APA LIFE ASSURANCE COMPANY | C7: =+LINKED!C7+'NON-LINKED'!C7 -> 1808290.5 | D7: =+LINKED!D7+'NON-LINKED'!D7 -> 1093378.7 | E7: =+LINKED!E7+'NON-LINKED'!E7 -> 1093378.7 | F7: =+LINKED!F7+'NON-LINKED'!F7 -> 0 | G7: =+LINKED!G7+'NON-LINKED'!G7 -> 3786.073 | H7: =+LINKED!H7+'NON-LINKED'!H7 -> 3786.073 | I7: =+LINKED!I7+'NON-LINKED'!I7 -> 0 | J7: =+LINKED!J7+'NON-LINKED'!J7 -> 0 | ... Q7: =+LINKED!Q7+'NON-LINKED'!Q7 -> 2944560.6
B8: =LINKED!B8 -> BRITAM LIFE ASSURANCE | C8: =+LINKED!C8+'NON-LINKED'!C8 -> 7519675.8 | D8: =+LINKED!D8+'NON-LINKED'!D8 -> 2404280 | E8: =+LINKED!E8+'NON-LINKED'!E8 -> 2404280 | F8: =+LINKED!F8+'NON-LINKED'!F8 -> 0 | G8: =+LINKED!G8+'NON-LINKED'!G8 -> 1031631.2 | H8: =+LINKED!H8+'NON-LINKED'!H8 -> 1031631.2 | I8: =+LINKED!I8+'NON-LINKED'!I8 -> 0 | J8: =+LINKED!J8+'NON-LINKED'!J8 -> 0 | ... Q8: =+LINKED!Q8+'NON-LINKED'!Q8 -> 9142076.3
B9: =LINKED!B9 -> CANNON LIFE ASSURANCE (K) LIMITED | C9: =+LINKED!C9+'NON-LINKED'!C9 -> 118268.31 | D9: =+LINKED!D9+'NON-LINKED'!D9 -> 0 | E9: =+LINKED!E9+'NON-LINKED'!E9 -> 0 | F9: =+LINKED!F9+'NON-LINKED'!F9 -> 0 | G9: =+LINKED!G9+'NON-LINKED'!G9 -> 0 | H9: =+LINKED!H9+'NON-LINKED'!H9 -> 0 | I9: =+LINKED!I9+'NON-LINKED'!I9 -> 0 | J9: =+LINKED!J9+'NON-LINKED'!J9 -> 0 | ... Q9: =+LINKED!Q9+'NON-LINKED'!Q9 -> 115628.31
B10: =LINKED!B10 -> CAPEX LIFE ASSURANCE COMPANY | C10: =+LINKED!C10+'NON-LINKED'!C10 -> 0 | D10: =+LINKED!D10+'NON-LINKED'!D10 -> 0 | E10: =+LINKED!E10+'NON-LINKED'!E10 -> 0 | F10: =+LINKED!F10+'NON-LINKED'!F10 -> 0 | G10: =+LINKED!G10+'NON-LINKED'!G10 -> 0 | H10: =+LINKED!H10+'NON-LINKED'!H10 -> 0 | I10: =+LINKED!I10+'NON-LINKED'!I10 -> 0 | J10: =+LINKED!J10+'NON-LINKED'!J10 -> 0 | ... P10: =+LINKED!P10+'NON-LINKED'!P10 -> 0 | Q10: =+LINKED!Q20+'NON-LINKED'!Q20 -> 0
B11: =LINKED!B11 -> CIC LIFE ASSURANCE COMPANY | C11: =+LINKED!C11+'NON-LINKED'!C11 -> 0 | D11: =+LINKED!D11+'NON-LINKED'!D11 -> 0 | E11: =+LINKED!E11+'NON-LINKED'!E11 -> 0 | F11: =+LINKED!F11+'NON-LINKED'!F11 -> 0 | G11: =+LINKED!G11+'NON-LINKED'!G11 -> 0 | H11: =+LINKED!H11+'NON-LINKED'!H11 -> 0 | I11: =+LINKED!I11+'NON-LINKED'!I11 -> 0 | J11: =+LINKED!J11+'NON-LINKED'!J11 -> 0 | ... P11: =+LINKED!P11+'NON-LINKED'!P11 -> 0 | Q11: =+LINKED!Q21+'NON-LINKED'!Q21 -> 3413544.2
B12: =LINKED!B12 -> CORPORATE INSURANCE COMPANY | C12: =+LINKED!C12+'NON-LINKED'!C12 -> 0
B13: =LINKED!B13 -> EQUITY LIFE ASSURANCE | C13: =+LINKED!C13+'NON-LINKED'!C13 -> 317288.83 | D13: =+LINKED!D13+'NON-LINKED'!D13 -> 155652.82 | E13: =+LINKED!E13+'NON-LINKED'!E13 -> 155652.82 | F13: =+LINKED!F13+'NON-LINKED'!F13 -> 0 | G13: =+LINKED!G13+'NON-LINKED'!G13 -> 0 | H13: =+LINKED!H13+'NON-LINKED'!H13 -> 0 | I13: =+LINKED!I13+'NON-LINKED'!I13 -> 0 | J13: =+LINKED!J13+'NON-LINKED'!J13 -> 0 | ... P13: =+LINKED!P13+'NON-LINKED'!P13 -> 0 | Q13: =+LINKED!Q23+'NON-LINKED'!Q23 -> 3173986.2
B14: =LINKED!B14 -> GA LIFE ASSURANCE COMPANY | C14: =+LINKED!C14+'NON-LINKED'!C14 -> 0 | D14: =+LINKED!D14+'NON-LINKED'!D14 -> 0 | E14: =+LINKED!E14+'NON-LINKED'!E14 -> 0 | F14: =+LINKED!F14+'NON-LINKED'!F14 -> 0 | G14: =+LINKED!G14+'NON-LINKED'!G14 -> 0 | H14: =+LINKED!H14+'NON-LINKED'!H14 -> 0 | I14: =+LINKED!I14+'NON-LINKED'!I14 -> 0 | J14: =+LINKED!J14+'NON-LINKED'!J14 -> 0 | ... P14: =+LINKED!P14+'NON-LINKED'!P14 -> 0 | Q14: =+LINKED!Q24+'NON-LINKED'!Q24 -> 406116.77
B15: =LINKED!B15 -> GEMINIA LIFE INSURANCE COMPANY | C15: =+LINKED!C15+'NON-LINKED'!C15 -> 90519.786 | D15: =+LINKED!D15+'NON-LINKED'!D15 -> 168430.38 | E15: =+LINKED!E15+'NON-LINKED'!E15 -> 168430.38 | F15: =+LINKED!F15+'NON-LINKED'!F15 -> 0 | G15: =+LINKED!G15+'NON-LINKED'!G15 -> 0 | H15: =+LINKED!H15+'NON-LINKED'!H15 -> 0 | I15: =+LINKED!I15+'NON-LINKED'!I15 -> 0 | J15: =+LINKED!J15+'NON-LINKED'!J15 -> 0 | ... P15: =+LINKED!P15+'NON-LINKED'!P15 -> 0 | Q15: =+LINKED!Q25+'NON-LINKED'!Q25 -> 354785.25
B16: =LINKED!B16 -> ICEA LION LIFE ASSURANCE | C16: =+LINKED!C16+'NON-LINKED'!C16 -> 440263.48 | D16: =+LINKED!D16+'NON-LINKED'!D16 -> 1312.6909 | E16: =+LINKED!E16+'NON-LINKED'!E16 -> 1312.6909 | F16: =+LINKED!F16+'NON-LINKED'!F16 -> 0 | G16: =+LINKED!G16+'NON-LINKED'!G16 -> 10273.265 | H16: =+LINKED!H16+'NON-LINKED'!H16 -> 10204.793 | I16: =+LINKED!I16+'NON-LINKED'!I16 -> 68.472 | J16: =+LINKED!J16+'NON-LINKED'!J16 -> 0 | ... P16: =+LINKED!P16+'NON-LINKED'!P16 -> 0 | Q16: =+LINKED!Q26+'NON-LINKED'!Q26 -> 0
B17: =LINKED!B17 -> JUBILEE LIFE INSURANCE | C17: =+LINKED!C17+'NON-LINKED'!C17 -> 70346.668 | D17: =+LINKED!D17+'NON-LINKED'!D17 -> 0 | E17: =+LINKED!E17+'NON-LINKED'!E17 -> 0 | F17: =+LINKED!F17+'NON-LINKED'!F17 -> 0 | G17: =+LINKED!G17+'NON-LINKED'!G17 -> 0 | H17: =+LINKED!H17+'NON-LINKED'!H17 -> 0 | I17: =+LINKED!I17+'NON-LINKED'!I17 -> 0 | J17: =+LINKED!J17+'NON-LINKED'!J17 -> 0 | ... P17: =+LINKED!P17+'NON-LINKED'!P17 -> 0 | Q17: =+LINKED!Q27+'NON-LINKED'!Q27 -> 1169195.8
B18: =LINKED!B18 -> KENINDIA ASSURANCE COMPANY | C18: =+LINKED!C18+'NON-LINKED'!C18 -> 0 | D18: =+LINKED!D18+'NON-LINKED'!D18 -> 0 | E18: =+LINKED!E18+'NON-LINKED'!E18 -> 0 | F18: =+LINKED!F18+'NON-LINKED'!F18 -> 0 | G18: =+LINKED!G18+'NON-LINKED'!G18 -> 0 | H18: =+LINKED!H18+'NON-LINKED'!H18 -> 0 | I18: =+LINKED!I18+'NON-LINKED'!I18 -> 0 | J18: =+LINKED!J18+'NON-LINKED'!J18 -> 0 | ... P18: =+LINKED!P18+'NON-LINKED'!P18 -> 0 | Q18: =+LINKED!Q28+'NON-LINKED'!Q28 -> 0
B19: =LINKED!B19 -> KENYA ORIENT LIFE ASSURANCE | C19: =+LINKED!C19+'NON-LINKED'!C19 -> 0 | D19: =+LINKED!D19+'NON-LINKED'!D19 -> 0 | E19: =+LINKED!E19+'NON-LINKED'!E19 -> 0 | F19: =+LINKED!F19+'NON-LINKED'!F19 -> 0 | G19: =+LINKED!G19+'NON-LINKED'!G19 -> 0 | H19: =+LINKED!H19+'NON-LINKED'!H19 -> 0 | I19: =+LINKED!I19+'NON-LINKED'!I19 -> 0 | J19: =+LINKED!J19+'NON-LINKED'!J19 -> 0 | ... P19: =+LINKED!P19+'NON-LINKED'!P19 -> 0 | Q19: =+LINKED!Q29+'NON-LINKED'!Q29 -> 64438.778
B20: =LINKED!B20 -> KUSCCO MUTUAL ASSURANCE LIMITED | C20: =+LINKED!C20+'NON-LINKED'!C20 -> 0 | D20: =+LINKED!D20+'NON-LINKED'!D20 -> 0 | E20: =+LINKED!E20+'NON-LINKED'!E20 -> 0 | F20: =+LINKED!F20+'NON-LINKED'!F20 -> 0 | G20: =+LINKED!G20+'NON-LINKED'!G20 -> 0 | H20: =+LINKED!H20+'NON-LINKED'!H20 -> 0 | I20: =+LINKED!I20+'NON-LINKED'!I20 -> 0 | J20: =+LINKED!J20+'NON-LINKED'!J20 -> 0 | ... Q20: =+LINKED!Q20+'NON-LINKED'!Q20 -> 0
B21: =LINKED!B21 -> LIBERTY LIFE ASSURANCE COMPANY | C21: =+LINKED!C21+'NON-LINKED'!C21 -> 3343805 | D21: =+LINKED!D21+'NON-LINKED'!D21 -> 148581.3 | E21: =+LINKED!E21+'NON-LINKED'!E21 -> 148506.34 | F21: =+LINKED!F21+'NON-LINKED'!F21 -> 0 | G21: =+LINKED!G21+'NON-LINKED'!G21 -> 214036.08 | H21: =+LINKED!H21+'NON-LINKED'!H21 -> 214036.08 | I21: =+LINKED!I21+'NON-LINKED'!I21 -> 0 | J21: =+LINKED!J21+'NON-LINKED'!J21 -> 0 | ... Q21: =+LINKED!Q21+'NON-LINKED'!Q21 -> 3413544.2
B22: =LINKED!B22 -> MADISON INSURANCE COMPANY | C22: =+LINKED!C22+'NON-LINKED'!C22 -> -15507.071 | D22: =+LINKED!D22+'NON-LINKED'!D22 -> 246 | E22: =+LINKED!E22+'NON-LINKED'!E22 -> 246 | F22: =+LINKED!F22+'NON-LINKED'!F22 -> 0 | G22: =+LINKED!G22+'NON-LINKED'!G22 -> 707 | H22: =+LINKED!H22+'NON-LINKED'!H22 -> 707 | I22: =+LINKED!I22+'NON-LINKED'!I22 -> 0 | J22: =+LINKED!J22+'NON-LINKED'!J22 -> 0 | ... Q22: =+LINKED!Q22+'NON-LINKED'!Q22 -> -17527.211
B23: =LINKED!B23 -> OLD MUTUAL ASSURANCE COMPANY | C23: =+LINKED!C23+'NON-LINKED'!C23 -> 3305497.7 | D23: =+LINKED!D23+'NON-LINKED'!D23 -> 52833.338 | E23: =+LINKED!E23+'NON-LINKED'!E23 -> 52833.338 | F23: =+LINKED!F23+'NON-LINKED'!F23 -> 0 | G23: =+LINKED!G23+'NON-LINKED'!G23 -> 333579.94 | H23: =+LINKED!H23+'NON-LINKED'!H23 -> 333579.94 | I23: =+LINKED!I23+'NON-LINKED'!I23 -> 0 | J23: =+LINKED!J23+'NON-LINKED'!J23 -> 0 | ... Q23: =+LINKED!Q23+'NON-LINKED'!Q23 -> 3173986.2
B24: =LINKED!B24 -> OLD MUTUAL LIFE ASSURANCE KENYA | C24: =+LINKED!C24+'NON-LINKED'!C24 -> 405997.86 | D24: =+LINKED!D24+'NON-LINKED'!D24 -> 2579.651 | E24: =+LINKED!E24+'NON-LINKED'!E24 -> 2579.651 | F24: =+LINKED!F24+'NON-LINKED'!F24 -> 0 | G24: =+LINKED!G24+'NON-LINKED'!G24 -> 27821.628 | H24: =+LINKED!H24+'NON-LINKED'!H24 -> 27821.628 | I24: =+LINKED!I24+'NON-LINKED'!I24 -> 0 | J24: =+LINKED!J24+'NON-LINKED'!J24 -> 0 | ... Q24: =+LINKED!Q24+'NON-LINKED'!Q24 -> 406116.77
B25: =LINKED!B25 -> PIONEER ASSURANCE COMPANY | C25: =+LINKED!C25+'NON-LINKED'!C25 -> 346386.6 | D25: =+LINKED!D25+'NON-LINKED'!D25 -> 36966.691 | E25: =+LINKED!E25+'NON-LINKED'!E25 -> 36966.691 | F25: =+LINKED!F25+'NON-LINKED'!F25 -> 0 | G25: =+LINKED!G25+'NON-LINKED'!G25 -> 28568.036 | H25: =+LINKED!H25+'NON-LINKED'!H25 -> 28568.036 | I25: =+LINKED!I25+'NON-LINKED'!I25 -> 0 | J25: =+LINKED!J25+'NON-LINKED'!J25 -> 0 | ... Q25: =+LINKED!Q25+'NON-LINKED'!Q25 -> 354785.25
B26: =LINKED!B26 -> PRUDENTIAL LIFE ASSURANCE | C26: =+LINKED!C26+'NON-LINKED'!C26 -> 0 | D26: =+LINKED!D26+'NON-LINKED'!D26 -> 0 | E26: =+LINKED!E26+'NON-LINKED'!E26 -> 0 | F26: =+LINKED!F26+'NON-LINKED'!F26 -> 0 | G26: =+LINKED!G26+'NON-LINKED'!G26 -> 0 | H26: =+LINKED!H26+'NON-LINKED'!H26 -> 0 | I26: =+LINKED!I26+'NON-LINKED'!I26 -> 0 | J26: =+LINKED!J26+'NON-LINKED'!J26 -> 0 | ... Q26: =+LINKED!Q26+'NON-LINKED'!Q26 -> 0
B27: =LINKED!B27 -> SANLAM LIFE ASSURANCE | C27: =+LINKED!C27+'NON-LINKED'!C27 -> 1223094.3 | D27: =+LINKED!D27+'NON-LINKED'!D27 -> 40503.539 | E27: =+LINKED!E27+'NON-LINKED'!E27 -> 40503.539 | F27: =+LINKED!F27+'NON-LINKED'!F27 -> 0 | G27: =+LINKED!G27+'NON-LINKED'!G27 -> 248093.96 | H27: =+LINKED!H27+'NON-LINKED'!H27 -> 248093.96 | I27: =+LINKED!I27+'NON-LINKED'!I27 -> 0 | J27: =+LINKED!J27+'NON-LINKED'!J27 -> 0 | ... Q27: =+LINKED!Q27+'NON-LINKED'!Q27 -> 1169195.8
B28: =LINKED!B28 -> STAR DISCOVER LIFE INSURANCE | C28: =LINKED!C28+'NON-LINKED'!C28 -> 0 | D28: =LINKED!D28+'NON-LINKED'!D28 -> 0 | E28: =LINKED!E28+'NON-LINKED'!E28 -> 0 | F28: =LINKED!F28+'NON-LINKED'!F28 -> 0 | G28: =LINKED!G28+'NON-LINKED'!G28 -> 0 | H28: =LINKED!H28+'NON-LINKED'!H28 -> 0 | I28: =LINKED!I28+'NON-LINKED'!I28 -> 0 | J28: =LINKED!J28+'NON-LINKED'!J28 -> 0 | ... Q28: =LINKED!Q28+'NON-LINKED'!Q28 -> 0
B29: =LINKED!B29 -> THE KENYAN ALLIANCE INSURANCE | C29: =+LINKED!C29+'NON-LINKED'!C29 -> 100080.33 | D29: =+LINKED!D29+'NON-LINKED'!D29 -> 1396.7185 | E29: =+LINKED!E29+'NON-LINKED'!E29 -> 1396.7185 | F29: =+LINKED!F29+'NON-LINKED'!F29 -> 0 | G29: =+LINKED!G29+'NON-LINKED'!G29 -> 37076.576 | H29: =+LINKED!H29+'NON-LINKED'!H29 -> 6268.637 | I29: =+LINKED!I29+'NON-LINKED'!I29 -> 0 | J29: =+LINKED!J29+'NON-LINKED'!J29 -> 30807.939 | ... Q29: =+LINKED!Q29+'NON-LINKED'!Q29 -> 64438.778
B30: =LINKED!B30 -> THE MONARCH INSURANCE | C30: =+LINKED!C30+'NON-LINKED'!C30 -> 0 | D30: =+LINKED!D30+'NON-LINKED'!D30 -> 0 | E30: =+LINKED!E30+'NON-LINKED'!E30 -> 0 | F30: =+LINKED!F30+'NON-LINKED'!F30 -> 0 | G30: =+LINKED!G30+'NON-LINKED'!G30 -> 0 | H30: =+LINKED!H30+'NON-LINKED'!H30 -> 0 | I30: =+LINKED!I30+'NON-LINKED'!I30 -> 0 | J30: =+LINKED!J30+'NON-LINKED'!J30 -> 0 | ... Q30: =+LINKED!Q30+'NON-LINKED'!Q30 -> 0
B31: TOTAL | C31: =SUM(C6:C30) -> 19074008 | D31: =SUM(D6:D30) -> 4106161.7 | E31: =SUM(E6:E30) -> 4106086.8 | F31: =SUM(F6:F30) -> 0 | G31: =SUM(G6:G30) -> 1935573.8 | H31: =SUM(H6:H30) -> 1904697.4 | I31: =SUM(I6:I30) -> 68.472 | J31: =SUM(J6:J30) -> 30807.939 | ... Q31: =SUM(Q6:Q30) -> 29348872
B32: REINSURERS
B33: =LINKED!B33 -> CONTINENTAL REINSURANCE | C33: =+LINKED!C33+'NON-LINKED'!C33 -> 0 | D33: =+LINKED!D33+'NON-LINKED'!D33 -> 0 | E33: =+LINKED!E33+'NON-LINKED'!E33 -> 0 | F33: =+LINKED!F33+'NON-LINKED'!F33 -> 0 | G33: =+LINKED!G33+'NON-LINKED'!G33 -> 0 | H33: =+LINKED!H33+'NON-LINKED'!H33 -> 0 | I33: =+LINKED!I33+'NON-LINKED'!I33 -> 0 | J33: =+LINKED!J33+'NON-LINKED'!J33 -> 0 | ... Q33: =+LINKED!Q33+'NON-LINKED'!Q33 -> 0
B34: =LINKED!B34 -> EAST AFRICA REINSURANCE | C34: =+LINKED!C34+'NON-LINKED'!C34 -> 0 | D34: =+LINKED!D34+'NON-LINKED'!D34 -> 0 | E34: =+LINKED!E34+'NON-LINKED'!E34 -> 0 | F34: =+LINKED!F34+'NON-LINKED'!F34 -> 0 | G34: =+LINKED!G34+'NON-LINKED'!G34 -> 0 | H34: =+LINKED!H34+'NON-LINKED'!H34 -> 0 | I34: =+LINKED!I34+'NON-LINKED'!I34 -> 0 | J34: =+LINKED!J34+'NON-LINKED'!J34 -> 0 | ... Q34: =+LINKED!Q34+'NON-LINKED'!Q34 -> 0
B35: =LINKED!B35 -> KENYA REINSURANCE CORPORATION | C35: =+LINKED!C35+'NON-LINKED'!C35 -> 0 | D35: =+LINKED!D35+'NON-LINKED'!D35 -> 0 | E35: =+LINKED!E35+'NON-LINKED'!E35 -> 0 | F35: =+LINKED!F35+'NON-LINKED'!F35 -> 0 | G35: =+LINKED!G35+'NON-LINKED'!G35 -> 0 | H35: =+LINKED!H35+'NON-LINKED'!H35 -> 0 | I35: =+LINKED!I35+'NON-LINKED'!I35 -> 0 | J35: =+LINKED!J35+'NON-LINKED'!J35 -> 0 | ... Q35: =+LINKED!Q35+'NON-LINKED'!Q35 -> 0
B36: TOTAL | C36: =SUM(C33:C35) -> 0 | D36: =SUM(D33:D35) -> 0 | E36: =SUM(E33:E35) -> 0 | F36: =SUM(F33:F35) -> 0 | G36: =SUM(G33:G35) -> 0 | H36: =SUM(H33:H35) -> 0 | I36: =SUM(I33:I35) -> 0 | J36: =SUM(J33:J35) -> 0 | ... Q36: =SUM(Q33:Q35) -> 0
B37: Amounts in Thousand Shillings

Sheet LINKED
B3: =_xlfn.CONCAT("LINKED INVESTMENTS"," ",Details!F18) -> LINKED INVESTMENTS 31.03.2025
B4: Company | C4: Life Fund BF | D4: Gross Premium | E4: Net Premium | F4: Other (Fee) Income | G4: Total Benefits | H4: Claims | I4: Surrenders_x000D_ | J4: Bonuses Paid | K4: Annuities Paid | L4: Net Commisions | M4: Expense of Management | N4: Investment Income | O4: Investment Expenses | P4: Transfer To (From) P & L | Q4: Life Fund CF
B5: INSURERS
B6: ABSA LIFE ASSURANCE | C6: 0 | D6: 0 | E6: 0 | F6: 0 | G6: 0 | H6: 0 | I6: 0 | J6: 0 | K6: 0 | L6: 0 | M6: 0 | N6: 0 | O6: 0 | P6: 0 | Q6: 0
B7: APA LIFE ASSURANCE COMPANY | C7: 0 | D7: 111.25 | E7: 111.25 | F7: 0 | G7: 0 | H7: 0 | I7: 0 | J7: 0 | K7: 0 | L7: 0 | M7: 3600.5975 | N7: 0 | O7: 0 | P7: 0 | Q7: -3489.3475
B8: BRITAM LIFE ASSURANCE | C8: 7519675.8 | D8: 2404280 | E8: 2404280 | F8: 0 | G8: 1031631.2 | H8: 1031631.2 | I8: 0 | J8: 0 | K8: 0 | L8: 5917.6228 | M8: 30409.455 | N8: 373280.39 | O8: 3854.2576 | P8: 83347.368 | Q8: 9142076.3
B9: CANNON LIFE ASSURANCE (K) LIMITED | C9: 118268.31 | D9: 0 | E9: 0 | F9: 0 | G9: 0 | H9: 0 | I9: 0 | J9: 0 | K9: 0 | L9: 0 | M9: 9626.82 | N9: 6986.821 | O9: 0 | P9: 0 | Q9: 115628.31
B10: CAPEX LIFE ASSURANCE COMPANY | C10: 0 | D10: 0 | E10: 0 | F10: 0 | G10: 0 | H10: 0 | I10: 0 | J10: 0 | K10: 0 | L10: 0 | M10: 0 | N10: 0 | O10: 0 | P10: 0 | Q10: 0
B11: CIC LIFE ASSURANCE COMPANY | C11: 0 | D11: 0 | E11: 0 | F11: 0 | G11: 0 | H11: 0 | I11: 0 | J11: 0 | K11: 0 | L11: 0 | M11: 0 | N11: 0 | O11: 0 | P11: 0 | Q11: 0
B12: CORPORATE INSURANCE COMPANY | C12: 0 | D12: 0 | E12: 0 | F12: 0 | G12: 0 | H12: 0 | I12: 0 | J12: 0 | K12: 0 | L12: 0 | M12: 0 | N12: 0 | O12: 0 | P12: 0 | Q12: 0
B13: EQUITY LIFE ASSURANCE | C13: 0 | D13: 0 | E13: 0 | F13: 0 | G13: 0 | H13: 0 | I13: 0 | J13: 0 | K13: 0 | L13: 0 | M13: 0 | N13: 0 | O13: 0 | P13: 0 | Q13: 0
B14: GA LIFE ASSURANCE COMPANY | C14: 0 | D14: 0 | E14: 0 | F14: 0 | G14: 0 | H14: 0 | I14: 0 | J14: 0 | K14: 0 | L14: 0 | M14: 0 | N14: 0 | O14: 0 | P14: 0 | Q14: 0
B15: GEMINIA LIFE INSURANCE COMPANY | C15: 0 | D15: 0 | E15: 0 | F15: 0 | G15: 0 | H15: 0 | I15: 0 | J15: 0 | K15: 0 | L15: 0 | M15: 0 | N15: 0 | O15: 0 | P15: 0 | Q15: 0
B16: ICEA LION LIFE ASSURANCE | C16: 440263.48 | D16: 1312.6909 | E16: 1312.6909 | F16: 0 | G16: 10273.265 | H16: 10204.793 | I16: 68.472 | J16: 0 | K16: 0 | L16: 0 | M16: 13.126909 | N16: 11581.978 | O16: 0 | P16: 0 | Q16: 442871.76
B17: JUBILEE LIFE INSURANCE | C17: 70346.668 | D17: 0 | E17: 0 | F17: 0 | G17: 0 | H17: 0 | I17: 0 | J17: 0 | K17: 0 | L17: 0 | M17: 1635.3114 | N17: 0 | O17: 0 | P17: 0 | Q17: 68711.357
... B30: THE MONARCH INSURANCE | C30: 0 | D30: 0 | E30: 0 | F30: 0 | G30: 0 | H30: 0 | I30: 0 | J30: 0 | K30: 0 | L30: 0 | M30: 0 | N30: 0 | O30: 0 | P30: 0 | Q30: 0
B31: TOTAL | C31: =SUM(C6:C30) -> 15720233 | D31: =SUM(D6:D30) -> 2653523.9 | E31: =SUM(E6:E30) -> 2653448.9 | F31: =SUM(F6:F30) -> 0 | G31: =SUM(G6:G30) -> 1868520.3 | H31: =SUM(H6:H30) -> 1868451.9 | I31: =SUM(I6:I30) -> 68.472 | J31: =SUM(J6:J30) -> 0 | ... Q31: =SUM(Q6:Q30) -> 17117421
B32: REINSURERS
B33: CONTINENTAL REINSURANCE | C33: 0 | D33: 0 | E33: 0 | F33: 0 | G33: 0 | H33: 0 | I33: 0 | J33: 0 | K33: 0 | L33: 0 | M33: 0 | N33: 0 | O33: 0 | P33: 0 | Q33: 0
B34: EAST AFRICA REINSURANCE | C34: 0 | D34: 0 | E34: 0 | F34: 0 | G34: 0 | H34: 0 | I34: 0 | J34: 0 | K34: 0 | L34: 0 | M34: 0 | N34: 0 | O34: 0 | P34: 0 | Q34: 0
B35: KENYA REINSURANCE CORPORATION | C35: 0 | D35: 0 | E35: 0 | F35: 0 | G35: 0 | H35: 0 | I35: 0 | J35: 0 | K35: 0 | L35: 0 | M35: 0 | N35: 0 | O35: 0 | P35: 0 | Q35: 0
B36: TOTAL | C36: 0 | D36: 0 | E36: 0 | F36: 0 | G36: 0 | H36: 0 | I36: 0 | J36: 0 | K36: 0 | L36: 0 | M36: 0 | N36: 0 | O36: 0 | P36: 0 | Q36: 0
B37: Amounts in Thousand Shillings

Sheet NON-LINKED
B3: =_xlfn.CONCAT("NON-LINKED INVESTMENTS"," ",Details!F18) -> NON-LINKED INVESTMENTS 31.03.2025
B4: Company | C4: Life Fund BF | D4: Gross Premium | E4: Net Premium | F4: Other (Fee) Income | G4: Total Benefits | H4: Claims | I4: Surrenders_x000D_ | J4: Bonuses Paid | K4: Annuities Paid | L4: Net Commisions | M4: Expense of Management | N4: Investment Income | O4: Investment Expenses | P4: Transfer To (From) P & L | Q4: Life Fund CF
B5: INSURERS
B6: ABSA LIFE ASSURANCE | C6: 0 | D6: 0 | E6: 0 | F6: 0 | G6: 0 | H6: 0 | I6: 0 | J6: 0 | K6: 0 | L6: 0 | M6: 0 | N6: 0 | O6: 0 | P6: 0 | Q6: 0
B7: APA LIFE ASSURANCE COMPANY | C7: 1808290.5 | D7: 1093267.4 | E7: 1093267.4 | F7: 0 | G7: 3786.073 | H7: 3786.073 | I7: 0 | J7: 0 | K7: 0 | L7: 54702.12 | M7: 0 | N7: 107489.7 | O7: 2509.4275 | P7: 0 | Q7: 2948049.9
B8: BRITAM LIFE ASSURANCE | C8: 0 | D8: 0 | E8: 0 | F8: 0 | G8: 0 | H8: 0 | I8: 0 | J8: 0 | K8: 0 | L8: 0 | M8: 0 | N8: 0 | O8: 0 | P8: 0 | Q8: 0
B9: CANNON LIFE ASSURANCE (K) LIMITED | C9: 0 | D9: 0 | E9: 0 | F9: 0 | G9: 0 | H9: 0 | I9: 0 | J9: 0 | K9: 0 | L9: 0 | M9: 0 | N9: 0 | O9: 0 | P9: 0 | Q9: 0
B10: CAPEX LIFE ASSURANCE COMPANY | C10: 0 | D10: 0 | E10: 0 | F10: 0 | G10: 0 | H10: 0 | I10: 0 | J10: 0 | K10: 0 | L10: 0 | M10: 0 | N10: 0 | O10: 0 | P10: 0 | Q10: 0
B11: CIC LIFE ASSURANCE COMPANY | C11: 0 | D11: 0 | E11: 0 | F11: 0 | G11: 0 | H11: 0 | I11: 0 | J11: 0 | K11: 0 | L11: 0 | M11: 0 | N11: 0 | O11: 0 | P11: 0 | Q11: 0
B12: CORPORATE INSURANCE COMPANY | C12: 0 | D12: 0 | E12: 0 | F12: 0 | G12: 0 | H12: 0 | I12: 0 | J12: 0 | K12: 0 | L12: 0 | M12: 0 | N12: 0 | O12: 0 | P12: 0 | Q12: 0
B13: EQUITY LIFE ASSURANCE | C13: 317288.83 | D13: 155652.82 | E13: 155652.82 | F13: 0 | G13: 0 | H13: 0 | I13: 0 | J13: 0 | K13: 0 | L13: 0 | M13: 0 | N13: 0 | O13: 0 | P13: 0 | Q13: 472941.65
B14: GA LIFE ASSURANCE COMPANY | C14: 0 | D14: 0 | E14: 0 | F14: 0 | G14: 0 | H14: 0 | I14: 0 | J14: 0 | K14: 0 | L14: 0 | M14: 0 | N14: 0 | O14: 0 | P14: 0 | Q14: 0
B15: GEMINIA LIFE INSURANCE COMPANY | C15: 90519.786 | D15: 168430.38 | E15: 168430.38 | F15: 0 | G15: 0 | H15: 0 | I15: 0 | J15: 0 | K15: 0 | L15: 0 | M15: 1305.1065 | N15: 0 | O15: 0 | P15: 0 | Q15: 257645.06
B16: ICEA LION LIFE ASSURANCE | C16: 0 | D16: 0 | E16: 0 | F16: 0 | G16: 0 | H16: 0 | I16: 0 | J16: 0 | K16: 0 | L16: 0 | M16: 0 | N16: 0 | O16: 0 | P16: 0 | Q16: 0
B17: JUBILEE LIFE INSURANCE | C17: 0 | D17: 0 | E17: 0 | F17: 0 | G17: 0 | H17: 0 | I17: 0 | J17: 0 | K17: 0 | L17: 0 | M17: 0 | N17: 0 | O17: 0 | P17: 0 | Q17: 0
... B30: THE MONARCH INSURANCE | C30: 0 | D30: 0 | E30: 0 | F30: 0 | G30: 0 | H30: 0 | I30: 0 | J30: 0 | K30: 0 | L30: 0 | M30: 0 | N30: 0 | O30: 0 | P30: 0 | Q30: 0
B31: TOTAL | C31: =SUM(C6:C30) -> 3353774.6 | D31: =SUM(D6:D30) -> 1452637.9 | E31: =SUM(E6:E30) -> 1452637.9 | F31: =SUM(F6:F30) -> 0 | G31: =SUM(G6:G30) -> 67053.433 | H31: =SUM(H6:H30) -> 36245.494 | I31: =SUM(I6:I30) -> 0 | J31: =SUM(J6:J30) -> 30807.939 | ... Q31: =SUM(Q6:Q30) -> 4891553.8
B32: REINSURERS
B33: CONTINENTAL REINSURANCE | C33: 0 | D33: 0 | E33: 0 | F33: 0 | G33: 0 | H33: 0 | I33: 0 | J33: 0 | K33: 0 | L33: 0 | M33: 0 | N33: 0 | O33: 0 | P33: 0 | Q33: 0
B34: EAST AFRICA REINSURANCE | C34: 0 | D34: 0 | E34: 0 | F34: 0 | G34: 0 | H34: 0 | I34: 0 | J34: 0 | K34: 0 | L34: 0 | M34: 0 | N34: 0 | O34: 0 | P34: 0 | Q34: 0
B35: KENYA REINSURANCE CORPORATION | C35: 0 | D35: 0 | E35: 0 | F35: 0 | G35: 0 | H35: 0 | I35: 0 | J35: 0 | K35: 0 | L35: 0 | M35: 0 | N35: 0 | O35: 0 | P35: 0 | Q35: 0
B36: TOTAL | C36: =SUM(C33:C35) -> 0 | D36: =SUM(D33:D35) -> 0 | E36: =SUM(E33:E35) -> 0 | F36: =SUM(F33:F35) -> 0 | G36: =SUM(G33:G35) -> 0 | H36: =SUM(H33:H35) -> 0 | I36: =SUM(I33:I35) -> 0 | J36: =SUM(J33:J35) -> 0 | ... Q36: =SUM(Q33:Q35) -> 0
B37: Amounts in Thousand Shillings

Sheet APPENDIX 11
B3: =_xlfn.CONCAT('Table of Contents'!B18,": ",'Table of Contents'!C18) -> APPENDIX 11: SUMMARY OF PERMANENT HEALTH BUSINESS REVENUE ACCOUNTS FOR THE PERIOD ENDED 31.03.2025
B4: Company | C4: Life Fund BF | D4: Gross Premium | E4: Net Premium | F4: Other (Fee) Income | G4: Total Benefits | H4: Claims | I4: Surrenders_x000D_ | J4: Bonuses Paid | K4: Annuities Paid | L4: Net Commisions | M4: Expense of Management | N4: Investment Income | O4: Investment Expenses | P4: Transfer To (From) P & L | Q4: Life Fund CF
B5: INSURERS
B6: ABSA LIFE ASSURANCE | C6: 0 | D6: 0 | E6: 0 | F6: 0 | G6: 0 | H6: 0 | I6: 0 | J6: 0 | K6: 0 | L6: 0 | M6: 0 | N6: 0 | O6: 0 | P6: 0 | Q6: 0
B7: APA LIFE ASSURANCE COMPANY | C7: 0 | D7: 0 | E7: 0 | F7: 0 | G7: 0 | H7: 0 | I7: 0 | J7: 0 | K7: 0 | L7: 0 | M7: 0 | N7: 0 | O7: 0 | P7: 0 | Q7: 0
B8: BRITAM LIFE ASSURANCE | C8: 0 | D8: 0 | E8: 0 | F8: 0 | G8: 0 | H8: 0 | I8: 0 | J8: 0 | K8: 0 | L8: 0 | M8: 0 | N8: 0 | O8: 0 | P8: 0 | Q8: 0
B9: CANNON LIFE ASSURANCE (K) LIMITED | C9: 0 | D9: 0 | E9: 0 | F9: 0 | G9: 0 | H9: 0 | I9: 0 | J9: 0 | K9: 0 | L9: 0 | M9: 0 | N9: 0 | O9: 0 | P9: 0 | Q9: 0
B10: CAPEX LIFE ASSURANCE COMPANY | C10: 0 | D10: 0 | E10: 0 | F10: 0 | G10: 0 | H10: 0 | I10: 0 | J10: 0 | K10: 0 | L10: 0 | M10: 0 | N10: 0 | O10: 0 | P10: 0 | Q10: 0
B11: CIC LIFE ASSURANCE COMPANY | C11: 0 | D11: 0 | E11: 0 | F11: 0 | G11: 0 | H11: 0 | I11: 0 | J11: 0 | K11: 0 | L11: 0 | M11: 0 | N11: 0 | O11: 0 | P11: 0 | Q11: 0
B12: CORPORATE INSURANCE COMPANY | C12: 0 | D12: 0 | E12: 0 | F12: 0 | G12: 0 | H12: 0 | I12: 0 | J12: 0 | K12: 0 | L12: 0 | M12: 0 | N12: 0 | O12: 0 | P12: 0 | Q12: 0
B13: EQUITY LIFE ASSURANCE | C13: 0 | D13: 0 | E13: 0 | F13: 0 | G13: 0 | H13: 0 | I13: 0 | J13: 0 | K13: 0 | L13: 0 | M13: 0 | N13: 0 | O13: 0 | P13: 0 | Q13: 0
B14: GA LIFE ASSURANCE COMPANY | C14: 0 | D14: 0 | E14: 0 | F14: 0 | G14: 0 | H14: 0 | I14: 0 | J14: 0 | K14: 0 | L14: 0 | M14: 0 | N14: 0 | O14: 0 | P14: 0 | Q14: 0
B15: GEMINIA LIFE INSURANCE COMPANY | C15: 0 | D15: 0 | E15: 0 | F15: 0 | G15: 0 | H15: 0 | I15: 0 | J15: 0 | K15: 0 | L15: 0 | M15: 0 | N15: 0 | O15: 0 | P15: 0 | Q15: 0
B16: ICEA LION LIFE ASSURANCE | C16: 0 | D16: 0 | E16: 0 | F16: 0 | G16: 0 | H16: 0 | I16: 0 | J16: 0 | K16: 0 | L16: 0 | M16: 0 | N16: 0 | O16: 0 | P16: 0 | Q16: 0
B17: JUBILEE LIFE INSURANCE | C17: 0 | D17: 0 | E17: 0 | F17: 0 | G17: 0 | H17: 0 | I17: 0 | J17: 0 | K17: 0 | L17: 0 | M17: 0 | N17: 0 | O17: 0 | P17: 0 | Q17: 0
... B30: THE MONARCH INSURANCE | C30: 0 | D30: 0 | E30: 0 | F30: 0 | G30: 0 | H30: 0 | I30: 0 | J30: 0 | K30: 0 | L30: 0 | M30: 0 | N30: 0 | O30: 0 | P30: 0 | Q30: 0
B31: TOTAL | C31: =SUM(C6:C30) -> 0 | D31: =SUM(D6:D30) -> 0 | E31: =SUM(E6:E30) -> 0 | F31: =SUM(F6:F30) -> 0 | G31: =SUM(G6:G30) -> 0 | H31: =SUM(H6:H30) -> 0 | I31: =SUM(I6:I30) -> 0 | J31: =SUM(J6:J30) -> 0 | ... Q31: =SUM(Q6:Q30) -> 0
B32: REINSURERS
B33: CONTINENTAL REINSURANCE | C33: 0 | D33: 0 | E33: 0 | F33: 0 | G33: 0 | H33: 0 | I33: 0 | J33: 0 | K33: 0 | L33: 0 | M33: 0 | N33: 0 | O33: 0 | P33: 0 | Q33: 0
B34: EAST AFRICA REINSURANCE | C34: 0 | D34: 0 | E34: 0 | F34: 0 | G34: 0 | H34: 0 | I34: 0 | J34: 0 | K34: 0 | L34: 0 | M34: 0 | N34: 0 | O34: 0 | P34: 0 | Q34: 0
B35: KENYA REINSURANCE CORPORATION | C35: 0 | D35: 0 | E35: 0 | F35: 0 | G35: 0 | H35: 0 | I35: 0 | J35: 0 | K35: 0 | L35: 0 | M35: 0 | N35: 0 | O35: 0 | P35: 0 | Q35: 0
B36: TOTAL | C36: =SUM(C33:C35) -> 0 | D36: =SUM(D33:D35) -> 0 | E36: =SUM(E33:E35) -> 0 | F36: =SUM(F33:F35) -> 0 | G36: =SUM(G33:G35) -> 0 | H36: =SUM(H33:H35) -> 0 | I36: =SUM(I33:I35) -> 0 | J36: =SUM(J33:J35) -> 0 | ... Q36: =SUM(Q33:Q35) -> 0
B37: Amounts in Thousand Shillings

Sheet PENSIONS
B3: =_xlfn.CONCAT("SUMMARY OF PENSIONS BUSINESS REVENUE ACCOUNTS FOR THE PERIOD ENDED"," ",Details!F18) -> SUMMARY OF PENSIONS BUSINESS REVENUE ACCOUNTS FOR THE PERIOD ENDED 31.03.2025
B4: Company | C4: Life Fund BF | D4: Gross Premium | E4: Net Premium | F4: Other (Fee) Income | G4: Total Benefits | H4: Claims | I4: Surrenders_x000D_ | J4: Bonuses Paid | K4: Annuities Paid | L4: Net Commisions | M4: Expense of Management | N4: Investment Income | O4: Investment Expenses | P4: Transfer To (From) P & L | Q4: Life Fund CF
B5: INSURERS
B6: ABSA LIFE ASSURANCE | C6: =+'APPENDIX 12'!C6+'APPENDIX 13'!C6 -> 0 | D6: =+'APPENDIX 12'!D6+'APPENDIX 13'!D6 -> 0 | E6: =+'APPENDIX 12'!E6+'APPENDIX 13'!E6 -> 0 | F6: =+'APPENDIX 12'!F6+'APPENDIX 13'!F6 -> 0 | G6: =+'APPENDIX 12'!G6+'APPENDIX 13'!G6 -> 0 | H6: =+'APPENDIX 12'!H6+'APPENDIX 13'!H6 -> 0 | I6: =+'APPENDIX 12'!I6+'APPENDIX 13'!I6 -> 0 | J6: =+'APPENDIX 12'!J6+'APPENDIX 13'!J6 -> 0 | ... Q6: =+'APPENDIX 12'!Q6+'APPENDIX 13'!Q6 -> 0
B7: APA LIFE ASSURANCE COMPANY | C7: =+'APPENDIX 12'!C7+'APPENDIX 13'!C7 -> 9733226.8 | D7: =+'APPENDIX 12'!D7+'APPENDIX 13'!D7 -> 305513.69 | E7: =+'APPENDIX 12'!E7+'APPENDIX 13'!E7 -> 305513.69 | F7: =+'APPENDIX 12'!F7+'APPENDIX 13'!F7 -> 0 | G7: =+'APPENDIX 12'!G7+'APPENDIX 13'!G7 -> 207628.18 | H7: =+'APPENDIX 12'!H7+'APPENDIX 13'!H7 -> 207628.18 | I7: =+'APPENDIX 12'!I7+'APPENDIX 13'!I7 -> 0 | J7: =+'APPENDIX 12'!J7+'APPENDIX 13'!J7 -> 0 | ... Q7: =+'APPENDIX 12'!Q7+'APPENDIX 13'!Q7 -> 10169258
B8: BRITAM LIFE ASSURANCE | C8: =+'APPENDIX 12'!C8+'APPENDIX 13'!C8 -> 77630272 | D8: =+'APPENDIX 12'!D8+'APPENDIX 13'!D8 -> 2271395.7 | E8: =+'APPENDIX 12'!E8+'APPENDIX 13'!E8 -> 2271395.7 | F8: =+'APPENDIX 12'!F8+'APPENDIX 13'!F8 -> 0 | G8: =+'APPENDIX 12'!G8+'APPENDIX 13'!G8 -> 4359755.4 | H8: =+'APPENDIX 12'!H8+'APPENDIX 13'!H8 -> 4359755.4 | I8: =+'APPENDIX 12'!I8+'APPENDIX 13'!I8 -> 0 | J8: =+'APPENDIX 12'!J8+'APPENDIX 13'!J8 -> 0 | ... Q8: =+'APPENDIX 12'!Q8+'APPENDIX 13'!Q8 -> 78742003
B9: CANNON LIFE ASSURANCE (K) LIMITED | C9: =+'APPENDIX 12'!C9+'APPENDIX 13'!C9 -> 0 | D9: =+'APPENDIX 12'!D9+'APPENDIX 13'!D9 -> 0 | E9: =+'APPENDIX 12'!E9+'APPENDIX 13'!E9 -> 0 | F9: =+'APPENDIX 12'!F9+'APPENDIX 13'!F9 -> 0 | G9: =+'APPENDIX 12'!G9+'APPENDIX 13'!G9 -> 0 | H9: =+'APPENDIX 12'!H9+'APPENDIX 13'!H9 -> 0 | I9: =+'APPENDIX 12'!I9+'APPENDIX 13'!I9 -> 0 | J9: =+'APPENDIX 12'!J9+'APPENDIX 13'!J9 -> 0 | ... Q9: =+'APPENDIX 12'!Q9+'APPENDIX 13'!Q9 -> 0
B10: CAPEX LIFE ASSURANCE COMPANY | C10: =+'APPENDIX 12'!C10+'APPENDIX 13'!C10 -> 0 | D10: =+'APPENDIX 12'!D10+'APPENDIX 13'!D10 -> 0 | E10: =+'APPENDIX 12'!E10+'APPENDIX 13'!E10 -> 0 | F10: =+'APPENDIX 12'!F10+'APPENDIX 13'!F10 -> 0 | G10: =+'APPENDIX 12'!G10+'APPENDIX 13'!G10 -> 0 | H10: =+'APPENDIX 12'!H10+'APPENDIX 13'!H10 -> 0 | I10: =+'APPENDIX 12'!I10+'APPENDIX 13'!I10 -> 0 | J10: =+'APPENDIX 12'!J10+'APPENDIX 13'!J10 -> 0 | ... Q10: =+'APPENDIX 12'!Q10+'APPENDIX 13'!Q10 -> 0
B11: CIC LIFE ASSURANCE COMPANY | C11: =+'APPENDIX 12'!C11+'APPENDIX 13'!C11 -> 13492770 | D11: =+'APPENDIX 12'!D11+'APPENDIX 13'!D11 -> 863483.16 | E11: =+'APPENDIX 12'!E11+'APPENDIX 13'!E11 -> 863483.16 | F11: =+'APPENDIX 12'!F11+'APPENDIX 13'!F11 -> 0 | G11: =+'APPENDIX 12'!G11+'APPENDIX 13'!G11 -> 363697.99 | H11: =+'APPENDIX 12'!H11+'APPENDIX 13'!H11 -> 363697.99 | I11: =+'APPENDIX 12'!I11+'APPENDIX 13'!I11 -> 0 | J11: =+'APPENDIX 12'!J11+'APPENDIX 13'!J11 -> 0 | ... Q11: =+'APPENDIX 12'!Q11+'APPENDIX 13'!Q11 -> 13949390
B12: CORPORATE INSURANCE COMPANY | C12: =+'APPENDIX 12'!C12+'APPENDIX 13'!C12 -> 0 | D12: =+'APPENDIX 12'!D12+'APPENDIX 13'!D12 -> 0 | E12: =+'APPENDIX 12'!E12+'APPENDIX 13'!E12 -> 0 | F12: =+'APPENDIX 12'!F12+'APPENDIX 13'!F12 -> 0 | G12: =+'APPENDIX 12'!G12+'APPENDIX 13'!G12 -> 0 | H12: =+'APPENDIX 12'!H12+'APPENDIX 13'!H12 -> 0 | I12: =+'APPENDIX 12'!I12+'APPENDIX 13'!I12 -> 0 | J12: =+'APPENDIX 12'!J12+'APPENDIX 13'!J12 -> 0 | ... Q12: =+'APPENDIX 12'!Q12+'APPENDIX 13'!Q12 -> 0
B13: EQUITY LIFE ASSURANCE | C13: =+'APPENDIX 12'!C13+'APPENDIX 13'!C13 -> 13828977 | D13: =+'APPENDIX 12'!D13+'APPENDIX 13'!D13 -> 693459.15 | E13: =+'APPENDIX 12'!E13+'APPENDIX 13'!E13 -> 693459.15 | F13: =+'APPENDIX 12'!F13+'APPENDIX 13'!F13 -> 0 | G13: =+'APPENDIX 12'!G13+'APPENDIX 13'!G13 -> 0 | H13: =+'APPENDIX 12'!H13+'APPENDIX 13'!H13 -> 0 | I13: =+'APPENDIX 12'!I13+'APPENDIX 13'!I13 -> 0 | J13: =+'APPENDIX 12'!J13+'APPENDIX 13'!J13 -> 0 | ... Q13: =+'APPENDIX 12'!Q13+'APPENDIX 13'!Q13 -> 14571738
B14: GA LIFE ASSURANCE COMPANY | C14: =+'APPENDIX 12'!C14+'APPENDIX 13'!C14 -> 41439749 | D14: =+'APPENDIX 12'!D14+'APPENDIX 13'!D14 -> 5350315.1 | E14: =+'APPENDIX 12'!E14+'APPENDIX 13'!E14 -> 5350315.1 | F14: =+'APPENDIX 12'!F14+'APPENDIX 13'!F14 -> 0 | G14: =+'APPENDIX 12'!G14+'APPENDIX 13'!G14 -> 800588.19 | H14: =+'APPENDIX 12'!H14+'APPENDIX 13'!H14 -> 800588.19 | I14: =+'APPENDIX 12'!I14+'APPENDIX 13'!I14 -> 0 | J14: =+'APPENDIX 12'!J14+'APPENDIX 13'!J14 -> 0 | ... Q14: =+'APPENDIX 12'!Q14+'APPENDIX 13'!Q14 -> 47537530
B15: GEMINIA LIFE INSURANCE COMPANY | C15: =+'APPENDIX 12'!C15+'APPENDIX 13'!C15 -> 872653.45 | D15: =+'APPENDIX 12'!D15+'APPENDIX 13'!D15 -> 763310.1 | E15: =+'APPENDIX 12'!E15+'APPENDIX 13'!E15 -> 763310.1 | F15: =+'APPENDIX 12'!F15+'APPENDIX 13'!F15 -> 0 | G15: =+'APPENDIX 12'!G15+'APPENDIX 13'!G15 -> 0 | H15: =+'APPENDIX 12'!H15+'APPENDIX 13'!H15 -> 0 | I15: =+'APPENDIX 12'!I15+'APPENDIX 13'!I15 -> 0 | J15: =+'APPENDIX 12'!J15+'APPENDIX 13'!J15 -> 0 | ... Q15: =+'APPENDIX 12'!Q15+'APPENDIX 13'!Q15 -> 763309.64
B16: ICEA LION LIFE ASSURANCE | C16: =+'APPENDIX 12'!C16+'APPENDIX 13'!C16 -> 1.2949237e+08 | D16: =+'APPENDIX 12'!D16+'APPENDIX 13'!D16 -> 4377709.7 | E16: =+'APPENDIX 12'!E16+'APPENDIX 13'!E16 -> 4377709.7 | F16: =+'APPENDIX 12'!F16+'APPENDIX 13'!F16 -> 0 | G16: =+'APPENDIX 12'!G16+'APPENDIX 13'!G16 -> 3670957.9 | H16: =+'APPENDIX 12'!H16+'APPENDIX 13'!H16 -> 3670957.9 | I16: =+'APPENDIX 12'!I16+'APPENDIX 13'!I16 -> 0 | J16: =+'APPENDIX 12'!J16+'APPENDIX 13'!J16 -> 0 | ... Q16: =+'APPENDIX 12'!Q16+'APPENDIX 13'!Q16 -> 1.3485379e+08
B17: JUBILEE INSURANCE COMPANY | C17: =+'APPENDIX 12'!C17+'APPENDIX 13'!C17 -> 1.0828204e+08 | D17: =+'APPENDIX 12'!D17+'APPENDIX 13'!D17 -> 4285612.5 | E17: =+'APPENDIX 12'!E17+'APPENDIX 13'!E17 -> 4285612.5 | F17: =+'APPENDIX 12'!F17+'APPENDIX 13'!F17 -> 0 | G17: =+'APPENDIX 12'!G17+'APPENDIX 13'!G17 -> 2155899.3 | H17: =+'APPENDIX 12'!H17+'APPENDIX 13'!H17 -> 2155899.3 | I17: =+'APPENDIX 12'!I17+'APPENDIX 13'!I17 -> 0 | J17: =+'APPENDIX 12'!J17+'APPENDIX 13'!J17 -> 0 | ... Q17: =+'APPENDIX 12'!Q17+'APPENDIX 13'!Q17 -> 1.1383867e+08
... B22: MADISON INSURANCE COMPANY | C22: =+'APPENDIX 12'!C22+'APPENDIX 13'!C22 -> 5193614.2 | D22: =+'APPENDIX 12'!D22+'APPENDIX 13'!D22 -> 159122 | E22: =+'APPENDIX 12'!E22+'APPENDIX 13'!E22 -> 159122 | F22: =+'APPENDIX 12'!F22+'APPENDIX 13'!F22 -> 0 | G22: =+'APPENDIX 12'!G22+'APPENDIX 13'!G22 -> 164319 | H22: =+'APPENDIX 12'!H22+'APPENDIX 13'!H22 -> 164319 | I22: =+'APPENDIX 12'!I22+'APPENDIX 13'!I22 -> 0 | J22: =+'APPENDIX 12'!J22+'APPENDIX 13'!J22 -> 0 | ... Q22: =+'APPENDIX 12'!Q22+'APPENDIX 13'!Q22 -> 5234023.1
B23: OLD MUTUAL ASSURANCE COMPANY | C23: ='APPENDIX 12'!C23+'APPENDIX 13'!C23 -> 0 | D23: ='APPENDIX 12'!D23+'APPENDIX 13'!D23 -> 0 | E23: ='APPENDIX 12'!E23+'APPENDIX 13'!E23 -> 0 | F23: ='APPENDIX 12'!F23+'APPENDIX 13'!F23 -> 0 | G23: ='APPENDIX 12'!G23+'APPENDIX 13'!G23 -> 0 | H23: ='APPENDIX 12'!H23+'APPENDIX 13'!H23 -> 0 | I23: ='APPENDIX 12'!I23+'APPENDIX 13'!I23 -> 0 | J23: ='APPENDIX 12'!J23+'APPENDIX 13'!J23 -> 0 | ... Q23: ='APPENDIX 12'!Q23+'APPENDIX 13'!Q23 -> 0
B24: OLD MUTUAL LIFE ASSURANCE KENYA | C24: =+'APPENDIX 12'!C24+'APPENDIX 13'!C24 -> 6401678.3 | D24: =+'APPENDIX 12'!D24+'APPENDIX 13'!D24 -> 134244.37 | E24: =+'APPENDIX 12'!E24+'APPENDIX 13'!E24 -> 134244.37 | F24: =+'APPENDIX 12'!F24+'APPENDIX 13'!F24 -> 0 | G24: =+'APPENDIX 12'!G24+'APPENDIX 13'!G24 -> 271146.65 | H24: =+'APPENDIX 12'!H24+'APPENDIX 13'!H24 -> 271146.65 | I24: =+'APPENDIX 12'!I24+'APPENDIX 13'!I24 -> 0 | J24: =+'APPENDIX 12'!J24+'APPENDIX 13'!J24 -> 0 | ... Q24: =+'APPENDIX 12'!Q24+'APPENDIX 13'!Q24 -> 6699456.1
B25: PIONEER ASSURANCE COMPANY | C25: =+'APPENDIX 12'!C25+'APPENDIX 13'!C25 -> 7489190.3 | D25: =+'APPENDIX 12'!D25+'APPENDIX 13'!D25 -> 164687.16 | E25: =+'APPENDIX 12'!E25+'APPENDIX 13'!E25 -> 164687.16 | F25: =+'APPENDIX 12'!F25+'APPENDIX 13'!F25 -> 0 | G25: =+'APPENDIX 12'!G25+'APPENDIX 13'!G25 -> 126737.68 | H25: =+'APPENDIX 12'!H25+'APPENDIX 13'!H25 -> 126737.68 | I25: =+'APPENDIX 12'!I25+'APPENDIX 13'!I25 -> 0 | J25: =+'APPENDIX 12'!J25+'APPENDIX 13'!J25 -> 0 | ... Q25: =+'APPENDIX 12'!Q25+'APPENDIX 13'!Q25 -> 7527139.7
B26: PRUDENTIAL LIFE ASSURANCE | C26: =+'APPENDIX 12'!C26+'APPENDIX 13'!C26 -> 2556426.2 | D26: =+'APPENDIX 12'!D26+'APPENDIX 13'!D26 -> 348446.77 | E26: =+'APPENDIX 12'!E26+'APPENDIX 13'!E26 -> 348446.77 | F26: =+'APPENDIX 12'!F26+'APPENDIX 13'!F26 -> 0 | G26: =+'APPENDIX 12'!G26+'APPENDIX 13'!G26 -> 50268.119 | H26: =+'APPENDIX 12'!H26+'APPENDIX 13'!H26 -> 50268.119 | I26: =+'APPENDIX 12'!I26+'APPENDIX 13'!I26 -> 0 | J26: =+'APPENDIX 12'!J26+'APPENDIX 13'!J26 -> 0 | ... Q26: =+'APPENDIX 12'!Q26+'APPENDIX 13'!Q26 -> 2942715.5
B27: SANLAM LIFE ASSURANCE | C27: =+'APPENDIX 12'!C27+'APPENDIX 13'!C27 -> 3935282.1 | D27: =+'APPENDIX 12'!D27+'APPENDIX 13'!D27 -> 111428.96 | E27: =+'APPENDIX 12'!E27+'APPENDIX 13'!E27 -> 111428.96 | F27: =+'APPENDIX 12'!F27+'APPENDIX 13'!F27 -> 0 | G27: =+'APPENDIX 12'!G27+'APPENDIX 13'!G27 -> 258509.76 | H27: =+'APPENDIX 12'!H27+'APPENDIX 13'!H27 -> 258509.76 | I27: =+'APPENDIX 12'!I27+'APPENDIX 13'!I27 -> 0 | J27: =+'APPENDIX 12'!J27+'APPENDIX 13'!J27 -> 0 | ... Q27: =+'APPENDIX 12'!Q27+'APPENDIX 13'!Q27 -> 4154628.3
B28: STAR DISCOVER LIFE INSURANCE | C28: =+'APPENDIX 12'!C28+'APPENDIX 13'!C28 -> 0 | D28: =+'APPENDIX 12'!D28+'APPENDIX 13'!D28 -> 0 | E28: =+'APPENDIX 12'!E28+'APPENDIX 13'!E28 -> 0 | F28: =+'APPENDIX 12'!F28+'APPENDIX 13'!F28 -> 0 | G28: =+'APPENDIX 12'!G28+'APPENDIX 13'!G28 -> 0 | H28: =+'APPENDIX 12'!H28+'APPENDIX 13'!H28 -> 0 | I28: =+'APPENDIX 12'!I28+'APPENDIX 13'!I28 -> 0 | J28: =+'APPENDIX 12'!J28+'APPENDIX 13'!J28 -> 0 | ... Q28: =+'APPENDIX 12'!Q28+'APPENDIX 13'!Q28 -> 0
B29: THE KENYAN ALLIANCE INSURANCE | C29: =+'APPENDIX 12'!C29+'APPENDIX 13'!C29 -> 4357115.7 | D29: =+'APPENDIX 12'!D29+'APPENDIX 13'!D29 -> 152296.02 | E29: =+'APPENDIX 12'!E29+'APPENDIX 13'!E29 -> 152296.02 | F29: =+'APPENDIX 12'!F29+'APPENDIX 13'!F29 -> 0 | G29: =+'APPENDIX 12'!G29+'APPENDIX 13'!G29 -> 39778.789 | H29: =+'APPENDIX 12'!H29+'APPENDIX 13'!H29 -> 106385.02 | I29: =+'APPENDIX 12'!I29+'APPENDIX 13'!I29 -> 0 | J29: =+'APPENDIX 12'!J29+'APPENDIX 13'!J29 -> -66606.23 | ... Q29: =+'APPENDIX 12'!Q29+'APPENDIX 13'!Q29 -> 4473809.7
B30: THE MONARCH INSURANCE | C30: =+'APPENDIX 12'!C30+'APPENDIX 13'!C30 -> 0 | D30: =+'APPENDIX 12'!D30+'APPENDIX 13'!D30 -> 0 | E30: =+'APPENDIX 12'!E30+'APPENDIX 13'!E30 -> 0 | F30: =+'APPENDIX 12'!F30+'APPENDIX 13'!F30 -> 0 | G30: =+'APPENDIX 12'!G30+'APPENDIX 13'!G30 -> 0 | H30: =+'APPENDIX 12'!H30+'APPENDIX 13'!H30 -> 0 | I30: =+'APPENDIX 12'!I30+'APPENDIX 13'!I30 -> 0 | J30: =+'APPENDIX 12'!J30+'APPENDIX 13'!J30 -> 0 | ... Q30: =+'APPENDIX 12'!Q30+'APPENDIX 13'!Q30 -> 0
B31: TOTAL | C31: =SUM(C6:C30) -> 5.0064076e+08 | D31: =SUM(D6:D30) -> 21533756 | E31: =SUM(E6:E30) -> 21533756 | F31: =SUM(F6:F30) -> 0 | G31: =SUM(G6:G30) -> 14239871 | H31: =SUM(H6:H30) -> 14306478 | I31: =SUM(I6:I30) -> 0 | J31: =SUM(J6:J30) -> -66606.23 | ... Q31: =SUM(Q6:Q30) -> 5.2395562e+08
B32: REINSURERS
B33: CONTINENTAL REINSURANCE | C33: =+'APPENDIX 12'!C33+'APPENDIX 13'!C33 -> 0 | D33: =+'APPENDIX 12'!D33+'APPENDIX 13'!D33 -> 0 | E33: =+'APPENDIX 12'!E33+'APPENDIX 13'!E33 -> 0 | F33: =+'APPENDIX 12'!F33+'APPENDIX 13'!F33 -> 0 | G33: =+'APPENDIX 12'!G33+'APPENDIX 13'!G33 -> 0 | H33: =+'APPENDIX 12'!H33+'APPENDIX 13'!H33 -> 0 | I33: =+'APPENDIX 12'!I33+'APPENDIX 13'!I33 -> 0 | J33: =+'APPENDIX 12'!J33+'APPENDIX 13'!J33 -> 0 | ... Q33: =+'APPENDIX 12'!Q33+'APPENDIX 13'!Q33 -> 0
B34: EAST AFRICA REINSURANCE | C34: =+'APPENDIX 12'!C34+'APPENDIX 13'!C34 -> 0 | D34: =+'APPENDIX 12'!D34+'APPENDIX 13'!D34 -> 0 | E34: =+'APPENDIX 12'!E34+'APPENDIX 13'!E34 -> 0 | F34: =+'APPENDIX 12'!F34+'APPENDIX 13'!F34 -> 0 | G34: =+'APPENDIX 12'!G34+'APPENDIX 13'!G34 -> 0 | H34: =+'APPENDIX 12'!H34+'APPENDIX 13'!H34 -> 0 | I34: =+'APPENDIX 12'!I34+'APPENDIX 13'!I34 -> 0 | J34: =+'APPENDIX 12'!J34+'APPENDIX 13'!J34 -> 0 | ... Q34: =+'APPENDIX 12'!Q34+'APPENDIX 13'!Q34 -> 0
B35: KENYA REINSURANCE CORPORATION | C35: =+'APPENDIX 12'!C35+'APPENDIX 13'!C35 -> 0 | D35: =+'APPENDIX 12'!D35+'APPENDIX 13'!D35 -> 0 | E35: =+'APPENDIX 12'!E35+'APPENDIX 13'!E35 -> 0 | F35: =+'APPENDIX 12'!F35+'APPENDIX 13'!F35 -> 0 | G35: =+'APPENDIX 12'!G35+'APPENDIX 13'!G35 -> 0 | H35: =+'APPENDIX 12'!H35+'APPENDIX 13'!H35 -> 0 | I35: =+'APPENDIX 12'!I35+'APPENDIX 13'!I35 -> 0 | J35: =+'APPENDIX 12'!J35+'APPENDIX 13'!J35 -> 0 | ... Q35: =+'APPENDIX 12'!Q35+'APPENDIX 13'!Q35 -> 0
B36: TOTAL | C36: =SUM(C33:C35) -> 0 | D36: =SUM(D33:D35) -> 0 | E36: =SUM(E33:E35) -> 0 | F36: =SUM(F33:F35) -> 0 | G36: =SUM(G33:G35) -> 0 | H36: =SUM(H33:H35) -> 0 | I36: =SUM(I33:I35) -> 0 | J36: =SUM(J33:J35) -> 0 | ... Q36: =SUM(Q33:Q35) -> 0
B37: Amounts in Thousand Shillings

Sheet APPENDIX 12
B3: =_xlfn.CONCAT('Table of Contents'!B19,": ",'Table of Contents'!C19) -> APPENDIX 12: SUMMARY OF PERSONAL PENSIONS BUSINESS REVENUE ACCOUNTS FOR THE PERIOD ENDED 31.03.2025
B4: Company | C4: Life Fund BF | D4: Gross Premium | E4: Net Premium | F4: Other (Fee) Income | G4: Total Benefits | H4: Claims | I4: Surrenders_x000D_ | J4: Bonuses Paid | K4: Annuities Paid | L4: Net Commisions | M4: Expense of Management | N4: Investment Income | O4: Investment Expenses | P4: Transfer To (From) P & L | Q4: Life Fund CF
B5: INSURERS
B6: ABSA LIFE ASSURANCE | C6: 0 | D6: 0 | E6: 0 | F6: 0 | G6: 0 | H6: 0 | I6: 0 | J6: 0 | K6: 0 | L6: 0 | M6: 0 | N6: 0 | O6: 0 | P6: 0 | Q6: 0
B7: APA LIFE ASSURANCE COMPANY | C7: 0 | D7: 51601.347 | E7: 51601.347 | F7: 0 | G7: 17677.848 | H7: 17677.848 | I7: 0 | J7: 0 | K7: 0 | L7: 1032.027 | M7: 0 | N7: 59889.421 | O7: 1090.9047 | P7: 0 | Q7: 91689.988
B8: BRITAM LIFE ASSURANCE | C8: 33293702 | D8: 979427.72 | E8: 979427.72 | F8: 0 | G8: 1266424.2 | H8: 1266424.2 | I8: 0 | J8: 0 | K8: 0 | L8: 8648.8567 | M8: 81558.989 | N8: 1532303.6 | O8: 2608.555 | P8: 150124.27 | Q8: 34296068
B9: CANNON LIFE ASSURANCE (K) LIMITED | C9: 0 | D9: 0 | E9: 0 | F9: 0 | G9: 0 | H9: 0 | I9: 0 | J9: 0 | K9: 0 | L9: 0 | M9: 0 | N9: 0 | O9: 0 | P9: 0 | Q9: 0
B10: CAPEX LIFE ASSURANCE COMPANY | C10: 0 | D10: 0 | E10: 0 | F10: 0 | G10: 0 | H10: 0 | I10: 0 | J10: 0 | K10: 0 | L10: 0 | M10: 0 | N10: 0 | O10: 0 | P10: 0 | Q10: 0
B11: CIC LIFE ASSURANCE COMPANY | C11: 0 | D11: 0 | E11: 0 | F11: 0 | G11: 0 | H11: 0 | I11: 0 | J11: 0 | K11: 0 | L11: 0 | M11: 0 | N11: 0 | O11: 0 | P11: 0 | Q11: 0
B12: CORPORATE INSURANCE COMPANY | C12: 0 | D12: 0 | E12: 0 | F12: 0 | G12: 0 | H12: 0 | I12: 0 | J12: 0 | K12: 0 | L12: 0 | M12: 0 | N12: 0 | O12: 0 | P12: 0 | Q12: 0
B13: EQUITY LIFE ASSURANCE | C13: 374887.39 | D13: 59723.999 | E13: 59723.999 | F13: 0 | G13: 0 | H13: 0 | I13: 0 | J13: 0 | K13: 0 | L13: 0 | M13: 0 | N13: 0 | O13: 0 | P13: 0 | Q13: 434611.38
B14: GA LIFE ASSURANCE COMPANY | C14: 5859870.8 | D14: 310066.09 | E14: 310066.09 | F14: 0 | G14: 148078.6 | H14: 148078.6 | I14: 0 | J14: 0 | K14: 0 | L14: 1293.355 | M14: 7766.6931 | N14: 229471.33 | O14: 0 | P14: 0 | Q14: 6242269.5
B15: GEMINIA LIFE INSURANCE COMPANY | C15: 129029.75 | D15: 164999.69 | E15: 164999.69 | F15: 0 | G15: 0 | H15: 0 | I15: 0 | J15: 0 | K15: 0 | L15: -960.018 | M15: 0 | N15: 0 | O15: 0 | P15: 129989.93 | Q15: 164999.53
B16: ICEA LION LIFE ASSURANCE | C16: 48450961 | D16: 1903461.8 | E16: 1903461.8 | F16: 0 | G16: 1265009.4 | H16: 1265009.4 | I16: 0 | J16: 0 | K16: 0 | L16: 9384.337 | M16: 72858.323 | N16: 1835821.8 | O16: 0 | P16: 0 | Q16: 50842993
B17: JUBILEE LIFE INSURANCE | C17: 10414912 | D17: 670804.03 | E17: 670804.03 | F17: 0 | G17: 524497.57 | H17: 524497.57 | I17: 0 | J17: 0 | K17: 0 | L17: 0 | M17: 14298.68 | N17: 74031.883 | O17: 856.359 | P17: 0 | Q17: 10620095
... B30: THE MONARCH INSURANCE | C30: 0 | D30: 0 | E30: 0 | F30: 0 | G30: 0 | H30: 0 | I30: 0 | J30: 0 | K30: 0 | L30: 0 | M30: 0 | N30: 0 | O30: 0 | P30: 0 | Q30: 0
B31: TOTAL | C31: =SUM(C6:C30) -> 1.0392195e+08 | D31: =SUM(D6:D30) -> 5043446.6 | E31: =SUM(E6:E30) -> 5043446.6 | F31: =SUM(F6:F30) -> 0 | G31: =SUM(G6:G30) -> 3619494.4 | H31: =SUM(H6:H30) -> 3619494.4 | I31: =SUM(I6:I30) -> 0 | J31: =SUM(J6:J30) -> 0 | ... Q31: =SUM(Q6:Q30) -> 1.0909377e+08
B32: REINSURERS
B33: CONTINENTAL REINSURANCE | C33: 0 | D33: 0 | E33: 0 | F33: 0 | G33: 0 | H33: 0 | I33: 0 | J33: 0 | K33: 0 | L33: 0 | M33: 0 | N33: 0 | O33: 0 | P33: 0 | Q33: 0
B34: EAST AFRICA REINSURANCE | C34: 0 | D34: 0 | E34: 0 | F34: 0 | G34: 0 | H34: 0 | I34: 0 | J34: 0 | K34: 0 | L34: 0 | M34: 0 | N34: 0 | O34: 0 | P34: 0 | Q34: 0
B35: KENYA REINSURANCE CORPORATION | C35: 0 | D35: 0 | E35: 0 | F35: 0 | G35: 0 | H35: 0 | I35: 0 | J35: 0 | K35: 0 | L35: 0 | M35: 0 | N35: 0 | O35: 0 | P35: 0 | Q35: 0
B36: TOTAL | C36: =SUM(C33:C35) -> 0 | D36: =SUM(D33:D35) -> 0 | E36: =SUM(E33:E35) -> 0 | F36: =SUM(F33:F35) -> 0 | G36: =SUM(G33:G35) -> 0 | H36: =SUM(H33:H35) -> 0 | I36: =SUM(I33:I35) -> 0 | J36: =SUM(J33:J35) -> 0 | ... Q36: =SUM(Q33:Q35) -> 0
B37: Amounts in Thousand Shillings

Sheet APPENDIX 13
B3: =_xlfn.CONCAT('Table of Contents'!B20,": ",'Table of Contents'!C20) -> APPENDIX 13: SUMMARY OF DEPOSIT ADMINISTRATION BUSINESS REVENUE ACCOUNTS FOR THE PERIOD ENDED 31.03.2025
B4: Company | C4: Life Fund BF | D4: Gross Premium | E4: Net Premium | F4: Other (Fee) Income | G4: Total Benefits | H4: Claims | I4: Surrenders_x000D_ | J4: Bonuses Paid | K4: Annuities Paid | L4: Net Commisions | M4: Expense of Management | N4: Investment Income | O4: Investment Expenses | P4: Transfer To (From) P & L | Q4: Life Fund CF
B5: INSURERS
B6: ABSA LIFE ASSURANCE | C6: 0 | D6: 0 | E6: 0 | F6: 0 | G6: 0 | H6: 0 | I6: 0 | J6: 0 | K6: 0 | L6: 0 | M6: 0 | N6: 0 | O6: 0 | P6: 0 | Q6: 0
B7: APA LIFE ASSURANCE COMPANY | C7: 9733226.8 | D7: 253912.34 | E7: 253912.34 | F7: 0 | G7: 189950.33 | H7: 189950.33 | I7: 0 | J7: 0 | K7: 0 | L7: 27827.802 | M7: 10297.572 | N7: 323440.33 | O7: 4935.931 | P7: 0 | Q7: 10077568
B8: BRITAM LIFE ASSURANCE | C8: 44336570 | D8: 1291968 | E8: 1291968 | F8: 0 | G8: 3093331.2 | H8: 3093331.2 | I8: 0 | J8: 0 | K8: 0 | L8: 11410.225 | M8: 117849.33 | N8: 2241833.9 | O8: 3816.442 | P8: 198029.68 | Q8: 44445935
B9: CANNON LIFE ASSURANCE (K) LIMITED | C9: 0 | D9: 0 | E9: 0 | F9: 0 | G9: 0 | H9: 0 | I9: 0 | J9: 0 | K9: 0 | L9: 0 | M9: 0 | N9: 0 | O9: 0 | P9: 0 | Q9: 0
B10: CAPEX LIFE ASSURANCE COMPANY | C10: 0 | D10: 0 | E10: 0 | F10: 0 | G10: 0 | H10: 0 | I10: 0 | J10: 0 | K10: 0 | L10: 0 | M10: 0 | N10: 0 | O10: 0 | P10: 0 | Q10: 0
B11: CIC LIFE ASSURANCE COMPANY | C11: 13492770 | D11: 863483.16 | E11: 863483.16 | F11: 0 | G11: 363697.99 | H11: 363697.99 | I11: 0 | J11: 0 | K11: 0 | L11: 13216.589 | M11: 29948.266 | N11: 0 | O11: 0 | P11: 0 | Q11: 13949390
B12: CORPORATE INSURANCE COMPANY | C12: 0 | D12: 0 | E12: 0 | F12: 0 | G12: 0 | H12: 0 | I12: 0 | J12: 0 | K12: 0 | L12: 0 | M12: 0 | N12: 0 | O12: 0 | P12: 0 | Q12: 0
B13: EQUITY LIFE ASSURANCE | C13: 13454089 | D13: 633735.15 | E13: 633735.15 | F13: 0 | G13: 0 | H13: 0 | I13: 0 | J13: 0 | K13: 0 | L13: 0 | M13: 1492.8275 | N13: 507949.94 | O13: 457154.94 | P13: 0 | Q13: 14137127
B14: GA LIFE ASSURANCE COMPANY | C14: 35579878 | D14: 5040249 | E14: 5040249 | F14: 0 | G14: 652509.59 | H14: 652509.59 | I14: 0 | J14: 0 | K14: 0 | L14: 10747.902 | M14: 46886.124 | N14: 1385277 | O14: 0 | P14: 0 | Q14: 41295261
B15: GEMINIA LIFE INSURANCE COMPANY | C15: 743623.7 | D15: 598310.41 | E15: 598310.41 | F15: 0 | G15: 0 | H15: 0 | I15: 0 | J15: 0 | K15: 0 | L15: 0 | M15: 56.3946 | N15: 0 | O15: 0 | P15: 743567.6 | Q15: 598310.11
B16: ICEA LION LIFE ASSURANCE | C16: 81041405 | D16: 2474247.9 | E16: 2474247.9 | F16: 0 | G16: 2405948.5 | H16: 2405948.5 | I16: 0 | J16: 0 | K16: 0 | L16: 49464.475 | M16: 115681.13 | N16: 3066236.8 | O16: 0 | P16: 0 | Q16: 84010796
B17: JUBILEE LIFE INSURANCE | C17: 97867123 | D17: 3614808.5 | E17: 3614808.5 | F17: 0 | G17: 1631401.7 | H17: 1631401.7 | I17: 0 | J17: 0 | K17: 0 | L17: 48820.039 | M17: 105936.52 | N17: 3549826.2 | O17: 27022.407 | P17: 0 | Q17: 1.0321858e+08
... B30: THE MONARCH INSURANCE | C30: 0 | D30: 0 | E30: 0 | F30: 0 | G30: 0 | H30: 0 | I30: 0 | J30: 0 | K30: 0 | L30: 0 | M30: 0 | N30: 0 | O30: 0 | P30: 0 | Q30: 0
B31: TOTAL | C31: =SUM(C6:C30) -> 3.9671881e+08 | D31: =SUM(D6:D30) -> 16490309 | E31: =SUM(E6:E30) -> 16490309 | F31: =SUM(F6:F30) -> 0 | G31: =SUM(G6:G30) -> 10620377 | H31: =SUM(H6:H30) -> 10686983 | I31: =SUM(I6:I30) -> 0 | J31: =SUM(J6:J30) -> -66606.23 | ... Q31: =SUM(Q6:Q30) -> 4.1486185e+08
B32: REINSURERS
B33: CONTINENTAL REINSURANCE | C33: 0 | D33: 0 | E33: 0 | F33: 0 | G33: 0 | H33: 0 | I33: 0 | J33: 0 | K33: 0 | L33: 0 | M33: 0 | N33: 0 | O33: 0 | P33: 0 | Q33: 0
B34: EAST AFRICA REINSURANCE | C34: 0 | D34: 0 | E34: 0 | F34: 0 | G34: 0 | H34: 0 | I34: 0 | J34: 0 | K34: 0 | L34: 0 | M34: 0 | N34: 0 | O34: 0 | P34: 0 | Q34: 0
B35: KENYA REINSURANCE CORPORATION | C35: 0 | D35: 0 | E35: 0 | F35: 0 | G35: 0 | H35: 0 | I35: 0 | J35: 0 | K35: 0 | L35: 0 | M35: 0 | N35: 0 | O35: 0 | P35: 0 | Q35: 0
B36: TOTAL | C36: =SUM(C33:C35) -> 0 | D36: =SUM(D33:D35) -> 0 | E36: =SUM(E33:E35) -> 0 | F36: =SUM(F33:F35) -> 0 | G36: =SUM(G33:G35) -> 0 | H36: =SUM(H33:H35) -> 0 | I36: =SUM(I33:I35) -> 0 | J36: =SUM(J33:J35) -> 0 | ... Q36: =SUM(Q33:Q35) -> 0
B37: Amounts in Thousand Shillings

Sheet APPENDIX 14
B3: =_xlfn.CONCAT('Table of Contents'!B21,": ",'Table of Contents'!C21) -> APPENDIX 14: SUMMARY OF COMBINED LONG TERM BUSINESS REVENUE ACCOUNTS FOR THE PERIOD ENDED 31.03.2025
B4: Company | C4: Life Fund BF | D4: Gross Premium | E4: Net Premium | F4: Other (Fee) Income | G4: Total Benefits | H4: Claims | I4: Surrenders_x000D_ | J4: Bonuses Paid | K4: Annuities Paid | L4: Net Commisions | M4: Expense of Management | N4: Investment Income | O4: Investment Expenses | P4: Transfer To (From) P & L | Q4: Life Fund CF
B5: INSURERS
B6: ='APPENDIX 13'!B6 -> ABSA LIFE ASSURANCE | C6: ='APPENDIX 6'!C6+'APPENDIX 7'!C6+'APPENDIX 8'!C6+'APPENDIX 9'!C6+'APPENDIX 10'!C6+'APPENDIX 11'!C6+PENSIONS!C6 -> 12993436 | D6: ='APPENDIX 6'!D6+'APPENDIX 7'!D6+'APPENDIX 8'!D6+'APPENDIX 9'!D6+'APPENDIX 10'!D6+'APPENDIX 11'!D6+PENSIONS!D6 -> 2973072 | E6: ='APPENDIX 6'!E6+'APPENDIX 7'!E6+'APPENDIX 8'!E6+'APPENDIX 9'!E6+'APPENDIX 10'!E6+'APPENDIX 11'!E6+PENSIONS!E6 -> 2199973.8 | F6: ='APPENDIX 6'!F6+'APPENDIX 7'!F6+'APPENDIX 8'!F6+'APPENDIX 9'!F6+'APPENDIX 10'!F6+'APPENDIX 11'!F6+PENSIONS!F6 -> 0 | G6: ='APPENDIX 6'!G6+'APPENDIX 7'!G6+'APPENDIX 8'!G6+'APPENDIX 9'!G6+'APPENDIX 10'!G6+'APPENDIX 11'!G6+PENSIONS!G6 -> 1201072.6 | H6: ='APPENDIX 6'!H6+'APPENDIX 7'!H6+'APPENDIX 8'!H6+'APPENDIX 9'!H6+'APPENDIX 10'!H6+'APPENDIX 11'!H6+PENSIONS!H6 -> 1201072.6 | I6: ='APPENDIX 6'!I6+'APPENDIX 7'!I6+'APPENDIX 8'!I6+'APPENDIX 9'!I6+'APPENDIX 10'!I6+'APPENDIX 11'!I6+PENSIONS!I6 -> 0 | J6: ='APPENDIX 6'!J6+'APPENDIX 7'!J6+'APPENDIX 8'!J6+'APPENDIX 9'!J6+'APPENDIX 10'!J6+'APPENDIX 11'!J6+PENSIONS!J6 -> 0 | ... Q6: ='APPENDIX 6'!Q6+'APPENDIX 7'!Q6+'APPENDIX 8'!Q6+'APPENDIX 9'!Q6+'APPENDIX 10'!Q6+'APPENDIX 11'!Q6+PENSIONS!Q6 -> 13859237
B7: ='APPENDIX 13'!B7 -> APA LIFE ASSURANCE COMPANY | C7: ='APPENDIX 6'!C7+'APPENDIX 7'!C7+'APPENDIX 8'!C7+'APPENDIX 9'!C7+'APPENDIX 10'!C7+'APPENDIX 11'!C7+PENSIONS!C7 -> 15210032 | D7: ='APPENDIX 6'!D7+'APPENDIX 7'!D7+'APPENDIX 8'!D7+'APPENDIX 9'!D7+'APPENDIX 10'!D7+'APPENDIX 11'!D7+PENSIONS!D7 -> 2499436.8 | E7: ='APPENDIX 6'!E7+'APPENDIX 7'!E7+'APPENDIX 8'!E7+'APPENDIX 9'!E7+'APPENDIX 10'!E7+'APPENDIX 11'!E7+PENSIONS!E7 -> 1949852.9 | F7: ='APPENDIX 6'!F7+'APPENDIX 7'!F7+'APPENDIX 8'!F7+'APPENDIX 9'!F7+'APPENDIX 10'!F7+'APPENDIX 11'!F7+PENSIONS!F7 -> 0 | G7: ='APPENDIX 6'!G7+'APPENDIX 7'!G7+'APPENDIX 8'!G7+'APPENDIX 9'!G7+'APPENDIX 10'!G7+'APPENDIX 11'!G7+PENSIONS!G7 -> 579038.65 | H7: ='APPENDIX 6'!H7+'APPENDIX 7'!H7+'APPENDIX 8'!H7+'APPENDIX 9'!H7+'APPENDIX 10'!H7+'APPENDIX 11'!H7+PENSIONS!H7 -> 579038.65 | I7: ='APPENDIX 6'!I7+'APPENDIX 7'!I7+'APPENDIX 8'!I7+'APPENDIX 9'!I7+'APPENDIX 10'!I7+'APPENDIX 11'!I7+PENSIONS!I7 -> 0 | J7: ='APPENDIX 6'!J7+'APPENDIX 7'!J7+'APPENDIX 8'!J7+'APPENDIX 9'!J7+'APPENDIX 10'!J7+'APPENDIX 11'!J7+PENSIONS!J7 -> 0 | ... Q7: ='APPENDIX 6'!Q7+'APPENDIX 7'!Q7+'APPENDIX 8'!Q7+'APPENDIX 9'!Q7+'APPENDIX 10'!Q7+'APPENDIX 11'!Q7+PENSIONS!Q7 -> 16942717
B8: ='APPENDIX 13'!B8 -> BRITAM LIFE ASSURANCE | C8: ='APPENDIX 6'!C8+'APPENDIX 7'!C8+'APPENDIX 8'!C8+'APPENDIX 9'!C8+'APPENDIX 10'!C8+'APPENDIX 11'!C8+PENSIONS!C8 -> 1.5545264e+08 | D8: ='APPENDIX 6'!D8+'APPENDIX 7'!D8+'APPENDIX 8'!D8+'APPENDIX 9'!D8+'APPENDIX 10'!D8+'APPENDIX 11'!D8+PENSIONS!D8 -> 9658378.7 | E8: ='APPENDIX 6'!E8+'APPENDIX 7'!E8+'APPENDIX 8'!E8+'APPENDIX 9'!E8+'APPENDIX 10'!E8+'APPENDIX 11'!E8+PENSIONS!E8 -> 9444296.9 | F8: ='APPENDIX 6'!F8+'APPENDIX 7'!F8+'APPENDIX 8'!F8+'APPENDIX 9'!F8+'APPENDIX 10'!F8+'APPENDIX 11'!F8+PENSIONS!F8 -> -15078.871 | G8: ='APPENDIX 6'!G8+'APPENDIX 7'!G8+'APPENDIX 8'!G8+'APPENDIX 9'!G8+'APPENDIX 10'!G8+'APPENDIX 11'!G8+PENSIONS!G8 -> 8397188.5 | H8: ='APPENDIX 6'!H8+'APPENDIX 7'!H8+'APPENDIX 8'!H8+'APPENDIX 9'!H8+'APPENDIX 10'!H8+'APPENDIX 11'!H8+PENSIONS!H8 -> 8397188.5 | I8: ='APPENDIX 6'!I8+'APPENDIX 7'!I8+'APPENDIX 8'!I8+'APPENDIX 9'!I8+'APPENDIX 10'!I8+'APPENDIX 11'!I8+PENSIONS!I8 -> 0 | J8: ='APPENDIX 6'!J8+'APPENDIX 7'!J8+'APPENDIX 8'!J8+'APPENDIX 9'!J8+'APPENDIX 10'!J8+'APPENDIX 11'!J8+PENSIONS!J8 -> 0 | ... Q8: ='APPENDIX 6'!Q8+'APPENDIX 7'!Q8+'APPENDIX 8'!Q8+'APPENDIX 9'!Q8+'APPENDIX 10'!Q8+'APPENDIX 11'!Q8+PENSIONS!Q8 -> 1.6429178e+08
B9: ='APPENDIX 13'!B9 -> CANNON LIFE ASSURANCE (K) LIMITED | C9: ='APPENDIX 6'!C9+'APPENDIX 7'!C9+'APPENDIX 8'!C9+'APPENDIX 9'!C9+'APPENDIX 10'!C9+'APPENDIX 11'!C9+PENSIONS!C9 -> 820846.59 | D9: ='APPENDIX 6'!D9+'APPENDIX 7'!D9+'APPENDIX 8'!D9+'APPENDIX 9'!D9+'APPENDIX 10'!D9+'APPENDIX 11'!D9+PENSIONS!D9 -> 236998.21 | E9: ='APPENDIX 6'!E9+'APPENDIX 7'!E9+'APPENDIX 8'!E9+'APPENDIX 9'!E9+'APPENDIX 10'!E9+'APPENDIX 11'!E9+PENSIONS!E9 -> 172748.51 | F9: ='APPENDIX 6'!F9+'APPENDIX 7'!F9+'APPENDIX 8'!F9+'APPENDIX 9'!F9+'APPENDIX 10'!F9+'APPENDIX 11'!F9+PENSIONS!F9 -> 0 | G9: ='APPENDIX 6'!G9+'APPENDIX 7'!G9+'APPENDIX 8'!G9+'APPENDIX 9'!G9+'APPENDIX 10'!G9+'APPENDIX 11'!G9+PENSIONS!G9 -> 44199.138 | H9: ='APPENDIX 6'!H9+'APPENDIX 7'!H9+'APPENDIX 8'!H9+'APPENDIX 9'!H9+'APPENDIX 10'!H9+'APPENDIX 11'!H9+PENSIONS!H9 -> 44199.138 | I9: ='APPENDIX 6'!I9+'APPENDIX 7'!I9+'APPENDIX 8'!I9+'APPENDIX 9'!I9+'APPENDIX 10'!I9+'APPENDIX 11'!I9+PENSIONS!I9 -> 0 | J9: ='APPENDIX 6'!J9+'APPENDIX 7'!J9+'APPENDIX 8'!J9+'APPENDIX 9'!J9+'APPENDIX 10'!J9+'APPENDIX 11'!J9+PENSIONS!J9 -> 0 | ... Q9: ='APPENDIX 6'!Q9+'APPENDIX 7'!Q9+'APPENDIX 8'!Q9+'APPENDIX 9'!Q9+'APPENDIX 10'!Q9+'APPENDIX 11'!Q9+PENSIONS!Q9 -> 917076.56
B10: ='APPENDIX 13'!B10 -> CAPEX LIFE ASSURANCE COMPANY | C10: ='APPENDIX 6'!C10+'APPENDIX 7'!C10+'APPENDIX 8'!C10+'APPENDIX 9'!C10+'APPENDIX 10'!C10+'APPENDIX 11'!C10+PENSIONS!C10 -> 1260505.5 | D10: ='APPENDIX 6'!D10+'APPENDIX 7'!D10+'APPENDIX 8'!D10+'APPENDIX 9'!D10+'APPENDIX 10'!D10+'APPENDIX 11'!D10+PENSIONS!D10 -> 378449.98 | E10: ='APPENDIX 6'!E10+'APPENDIX 7'!E10+'APPENDIX 8'!E10+'APPENDIX 9'!E10+'APPENDIX 10'!E10+'APPENDIX 11'!E10+PENSIONS!E10 -> 313245.18 | F10: ='APPENDIX 6'!F10+'APPENDIX 7'!F10+'APPENDIX 8'!F10+'APPENDIX 9'!F10+'APPENDIX 10'!F10+'APPENDIX 11'!F10+PENSIONS!F10 -> 0 | G10: ='APPENDIX 6'!G10+'APPENDIX 7'!G10+'APPENDIX 8'!G10+'APPENDIX 9'!G10+'APPENDIX 10'!G10+'APPENDIX 11'!G10+PENSIONS!G10 -> 212888.3 | H10: ='APPENDIX 6'!H10+'APPENDIX 7'!H10+'APPENDIX 8'!H10+'APPENDIX 9'!H10+'APPENDIX 10'!H10+'APPENDIX 11'!H10+PENSIONS!H10 -> 212888.3 | I10: ='APPENDIX 6'!I10+'APPENDIX 7'!I10+'APPENDIX 8'!I10+'APPENDIX 9'!I10+'APPENDIX 10'!I10+'APPENDIX 11'!I10+PENSIONS!I10 -> 0 | J10: ='APPENDIX 6'!J10+'APPENDIX 7'!J10+'APPENDIX 8'!J10+'APPENDIX 9'!J10+'APPENDIX 10'!J10+'APPENDIX 11'!J10+PENSIONS!J10 -> 0 | ... P10: ='APPENDIX 6'!P10+'APPENDIX 7'!P10+'APPENDIX 8'!P10+'APPENDIX 9'!P10+'APPENDIX 10'!P10+'APPENDIX 11'!P10+PENSIONS!P10 -> 0 | Q10: ='APPENDIX 6'!Q20+'APPENDIX 7'!Q20+'APPENDIX 8'!Q20+'APPENDIX 9'!Q20+'APPENDIX 10'!Q20+'APPENDIX 11'!Q20+PENSIONS!Q20 -> 201471.66
B11: ='APPENDIX 13'!B11 -> CIC LIFE ASSURANCE COMPANY | C11: ='APPENDIX 6'!C11+'APPENDIX 7'!C11+'APPENDIX 8'!C11+'APPENDIX 9'!C11+'APPENDIX 10'!C11+'APPENDIX 11'!C11+PENSIONS!C11 -> 28739369 | D11: ='APPENDIX 6'!D11+'APPENDIX 7'!D11+'APPENDIX 8'!D11+'APPENDIX 9'!D11+'APPENDIX 10'!D11+'APPENDIX 11'!D11+PENSIONS!D11 -> 4049849.8 | E11: ='APPENDIX 6'!E11+'APPENDIX 7'!E11+'APPENDIX 8'!E11+'APPENDIX 9'!E11+'APPENDIX 10'!E11+'APPENDIX 11'!E11+PENSIONS!E11 -> 4962290.4 | F11: ='APPENDIX 6'!F11+'APPENDIX 7'!F11+'APPENDIX 8'!F11+'APPENDIX 9'!F11+'APPENDIX 10'!F11+'APPENDIX 11'!F11+PENSIONS!F11 -> 0 | G11: ='APPENDIX 6'!G11+'APPENDIX 7'!G11+'APPENDIX 8'!G11+'APPENDIX 9'!G11+'APPENDIX 10'!G11+'APPENDIX 11'!G11+PENSIONS!G11 -> 1381045.6 | H11: ='APPENDIX 6'!H11+'APPENDIX 7'!H11+'APPENDIX 8'!H11+'APPENDIX 9'!H11+'APPENDIX 10'!H11+'APPENDIX 11'!H11+PENSIONS!H11 -> 1381045.6 | I11: ='APPENDIX 6'!I11+'APPENDIX 7'!I11+'APPENDIX 8'!I11+'APPENDIX 9'!I11+'APPENDIX 10'!I11+'APPENDIX 11'!I11+PENSIONS!I11 -> 0 | J11: ='APPENDIX 6'!J11+'APPENDIX 7'!J11+'APPENDIX 8'!J11+'APPENDIX 9'!J11+'APPENDIX 10'!J11+'APPENDIX 11'!J11+PENSIONS!J11 -> 0 | ... P11: ='APPENDIX 6'!P11+'APPENDIX 7'!P11+'APPENDIX 8'!P11+'APPENDIX 9'!P11+'APPENDIX 10'!P11+'APPENDIX 11'!P11+PENSIONS!P11 -> 0 | Q11: ='APPENDIX 6'!Q21+'APPENDIX 7'!Q21+'APPENDIX 8'!Q21+'APPENDIX 9'!Q21+'APPENDIX 10'!Q21+'APPENDIX 11'!Q21+PENSIONS!Q21 -> 26864198
B12: ='APPENDIX 13'!B12 -> CORPORATE INSURANCE COMPANY | C12: ='APPENDIX 6'!C12+'APPENDIX 7'!C12+'APPENDIX 8'!C12+'APPENDIX 9'!C12+'APPENDIX 10'!C12+'APPENDIX 11'!C12+PENSIONS!C12 -> 73832.62 | D12: ='APPENDIX 6'!D12+'APPENDIX 7'!D12+'APPENDIX 8'!D12+'APPENDIX 9'!D12+'APPENDIX 10'!D12+'APPENDIX 11'!D12+PENSIONS!D12 -> 8452.4385 | E12: ='APPENDIX 6'!E12+'APPENDIX 7'!E12+'APPENDIX 8'!E12+'APPENDIX 9'!E12+'APPENDIX 10'!E12+'APPENDIX 11'!E12+PENSIONS!E12 -> 8452.4385 | F12: ='APPENDIX 6'!F12+'APPENDIX 7'!F12+'APPENDIX 8'!F12+'APPENDIX 9'!F12+'APPENDIX 10'!F12+'APPENDIX 11'!F12+PENSIONS!F12 -> 0 | G12: ='APPENDIX 6'!G12+'APPENDIX 7'!G12+'APPENDIX 8'!G12+'APPENDIX 9'!G12+'APPENDIX 10'!G12+'APPENDIX 11'!G12+PENSIONS!G12 -> 51459.937 | H12: ='APPENDIX 6'!H12+'APPENDIX 7'!H12+'APPENDIX 8'!H12+'APPENDIX 9'!H12+'APPENDIX 10'!H12+'APPENDIX 11'!H12+PENSIONS!H12 -> 51459.937 | I12: ='APPENDIX 6'!I12+'APPENDIX 7'!I12+'APPENDIX 8'!I12+'APPENDIX 9'!I12+'APPENDIX 10'!I12+'APPENDIX 11'!I12+PENSIONS!I12 -> 0 | J12: ='APPENDIX 6'!J12+'APPENDIX 7'!J12+'APPENDIX 8'!J12+'APPENDIX 9'!J12+'APPENDIX 10'!J12+'APPENDIX 11'!J12+PENSIONS!J12 -> 0 | ... P12: ='APPENDIX 6'!P12+'APPENDIX 7'!P12+'APPENDIX 8'!P12+'APPENDIX 9'!P12+'APPENDIX 10'!P12+'APPENDIX 11'!P12+PENSIONS!P12 -> 0 | Q12: ='APPENDIX 6'!Q22+'APPENDIX 7'!Q22+'APPENDIX 8'!Q22+'APPENDIX 9'!Q22+'APPENDIX 10'!Q22+'APPENDIX 11'!Q22+PENSIONS!Q22 -> 15034582
B13: ='APPENDIX 13'!B13 -> EQUITY LIFE ASSURANCE | C13: ='APPENDIX 6'!C13+'APPENDIX 7'!C13+'APPENDIX 8'!C13+'APPENDIX 9'!C13+'APPENDIX 10'!C13+'APPENDIX 11'!C13+PENSIONS!C13 -> 21017255 | D13: ='APPENDIX 6'!D13+'APPENDIX 7'!D13+'APPENDIX 8'!D13+'APPENDIX 9'!D13+'APPENDIX 10'!D13+'APPENDIX 11'!D13+PENSIONS!D13 -> 2076417.5 | E13: ='APPENDIX 6'!E13+'APPENDIX 7'!E13+'APPENDIX 8'!E13+'APPENDIX 9'!E13+'APPENDIX 10'!E13+'APPENDIX 11'!E13+PENSIONS!E13 -> 1746152.6 | F13: ='APPENDIX 6'!F13+'APPENDIX 7'!F13+'APPENDIX 8'!F13+'APPENDIX 9'!F13+'APPENDIX 10'!F13+'APPENDIX 11'!F13+PENSIONS!F13 -> 0 | G13: ='APPENDIX 6'!G13+'APPENDIX 7'!G13+'APPENDIX 8'!G13+'APPENDIX 9'!G13+'APPENDIX 10'!G13+'APPENDIX 11'!G13+PENSIONS!G13 -> 86414.62 | H13: ='APPENDIX 6'!H13+'APPENDIX 7'!H13+'APPENDIX 8'!H13+'APPENDIX 9'!H13+'APPENDIX 10'!H13+'APPENDIX 11'!H13+PENSIONS!H13 -> 86414.62 | I13: ='APPENDIX 6'!I13+'APPENDIX 7'!I13+'APPENDIX 8'!I13+'APPENDIX 9'!I13+'APPENDIX 10'!I13+'APPENDIX 11'!I13+PENSIONS!I13 -> 0 | J13: ='APPENDIX 6'!J13+'APPENDIX 7'!J13+'APPENDIX 8'!J13+'APPENDIX 9'!J13+'APPENDIX 10'!J13+'APPENDIX 11'!J13+PENSIONS!J13 -> 0 | ... P13: ='APPENDIX 6'!P13+'APPENDIX 7'!P13+'APPENDIX 8'!P13+'APPENDIX 9'!P13+'APPENDIX 10'!P13+'APPENDIX 11'!P13+PENSIONS!P13 -> 0 | Q13: ='APPENDIX 6'!Q23+'APPENDIX 7'!Q23+'APPENDIX 8'!Q23+'APPENDIX 9'!Q23+'APPENDIX 10'!Q23+'APPENDIX 11'!Q23+PENSIONS!Q23 -> 10131139
B14: ='APPENDIX 13'!B14 -> GA LIFE ASSURANCE COMPANY | C14: ='APPENDIX 6'!C14+'APPENDIX 7'!C14+'APPENDIX 8'!C14+'APPENDIX 9'!C14+'APPENDIX 10'!C14+'APPENDIX 11'!C14+PENSIONS!C14 -> 45563227 | D14: ='APPENDIX 6'!D14+'APPENDIX 7'!D14+'APPENDIX 8'!D14+'APPENDIX 9'!D14+'APPENDIX 10'!D14+'APPENDIX 11'!D14+PENSIONS!D14 -> 5403777.4 | E14: ='APPENDIX 6'!E14+'APPENDIX 7'!E14+'APPENDIX 8'!E14+'APPENDIX 9'!E14+'APPENDIX 10'!E14+'APPENDIX 11'!E14+PENSIONS!E14 -> 5370552.3 | F14: ='APPENDIX 6'!F14+'APPENDIX 7'!F14+'APPENDIX 8'!F14+'APPENDIX 9'!F14+'APPENDIX 10'!F14+'APPENDIX 11'!F14+PENSIONS!F14 -> 0 | G14: ='APPENDIX 6'!G14+'APPENDIX 7'!G14+'APPENDIX 8'!G14+'APPENDIX 9'!G14+'APPENDIX 10'!G14+'APPENDIX 11'!G14+PENSIONS!G14 -> 818074.22 | H14: ='APPENDIX 6'!H14+'APPENDIX 7'!H14+'APPENDIX 8'!H14+'APPENDIX 9'!H14+'APPENDIX 10'!H14+'APPENDIX 11'!H14+PENSIONS!H14 -> 818074.22 | I14: ='APPENDIX 6'!I14+'APPENDIX 7'!I14+'APPENDIX 8'!I14+'APPENDIX 9'!I14+'APPENDIX 10'!I14+'APPENDIX 11'!I14+PENSIONS!I14 -> 0 | J14: ='APPENDIX 6'!J14+'APPENDIX 7'!J14+'APPENDIX 8'!J14+'APPENDIX 9'!J14+'APPENDIX 10'!J14+'APPENDIX 11'!J14+PENSIONS!J14 -> 0 | ... P14: ='APPENDIX 6'!P14+'APPENDIX 7'!P14+'APPENDIX 8'!P14+'APPENDIX 9'!P14+'APPENDIX 10'!P14+'APPENDIX 11'!P14+PENSIONS!P14 -> 0 | Q14: ='APPENDIX 6'!Q24+'APPENDIX 7'!Q24+'APPENDIX 8'!Q24+'APPENDIX 9'!Q24+'APPENDIX 10'!Q24+'APPENDIX 11'!Q24+PENSIONS!Q24 -> 14562561
B15: ='APPENDIX 13'!B15 -> GEMINIA LIFE INSURANCE COMPANY | C15: ='APPENDIX 6'!C15+'APPENDIX 7'!C15+'APPENDIX 8'!C15+'APPENDIX 9'!C15+'APPENDIX 10'!C15+'APPENDIX 11'!C15+PENSIONS!C15 -> 2778646.6 | D15: ='APPENDIX 6'!D15+'APPENDIX 7'!D15+'APPENDIX 8'!D15+'APPENDIX 9'!D15+'APPENDIX 10'!D15+'APPENDIX 11'!D15+PENSIONS!D15 -> 1152177.5 | E15: ='APPENDIX 6'!E15+'APPENDIX 7'!E15+'APPENDIX 8'!E15+'APPENDIX 9'!E15+'APPENDIX 10'!E15+'APPENDIX 11'!E15+PENSIONS!E15 -> 1120439.5 | F15: ='APPENDIX 6'!F15+'APPENDIX 7'!F15+'APPENDIX 8'!F15+'APPENDIX 9'!F15+'APPENDIX 10'!F15+'APPENDIX 11'!F15+PENSIONS!F15 -> 0 | G15: ='APPENDIX 6'!G15+'APPENDIX 7'!G15+'APPENDIX 8'!G15+'APPENDIX 9'!G15+'APPENDIX 10'!G15+'APPENDIX 11'!G15+PENSIONS!G15 -> 155004.7 | H15: ='APPENDIX 6'!H15+'APPENDIX 7'!H15+'APPENDIX 8'!H15+'APPENDIX 9'!H15+'APPENDIX 10'!H15+'APPENDIX 11'!H15+PENSIONS!H15 -> 155004.7 | I15: ='APPENDIX 6'!I15+'APPENDIX 7'!I15+'APPENDIX 8'!I15+'APPENDIX 9'!I15+'APPENDIX 10'!I15+'APPENDIX 11'!I15+PENSIONS!I15 -> 0 | J15: ='APPENDIX 6'!J15+'APPENDIX 7'!J15+'APPENDIX 8'!J15+'APPENDIX 9'!J15+'APPENDIX 10'!J15+'APPENDIX 11'!J15+PENSIONS!J15 -> 0 | ... P15: ='APPENDIX 6'!P15+'APPENDIX 7'!P15+'APPENDIX 8'!P15+'APPENDIX 9'!P15+'APPENDIX 10'!P15+'APPENDIX 11'!P15+PENSIONS!P15 -> 873557.53 | Q15: ='APPENDIX 6'!Q25+'APPENDIX 7'!Q25+'APPENDIX 8'!Q25+'APPENDIX 9'!Q25+'APPENDIX 10'!Q25+'APPENDIX 11'!Q25+PENSIONS!Q25 -> 11825302
B16: ='APPENDIX 13'!B16 -> ICEA LION LIFE ASSURANCE | C16: ='APPENDIX 6'!C16+'APPENDIX 7'!C16+'APPENDIX 8'!C16+'APPENDIX 9'!C16+'APPENDIX 10'!C16+'APPENDIX 11'!C16+PENSIONS!C16 -> 1.7554155e+08 | D16: ='APPENDIX 6'!D16+'APPENDIX 7'!D16+'APPENDIX 8'!D16+'APPENDIX 9'!D16+'APPENDIX 10'!D16+'APPENDIX 11'!D16+PENSIONS!D16 -> 6982762.2 | E16: ='APPENDIX 6'!E16+'APPENDIX 7'!E16+'APPENDIX 8'!E16+'APPENDIX 9'!E16+'APPENDIX 10'!E16+'APPENDIX 11'!E16+PENSIONS!E16 -> 6864725.6 | F16: ='APPENDIX 6'!F16+'APPENDIX 7'!F16+'APPENDIX 8'!F16+'APPENDIX 9'!F16+'APPENDIX 10'!F16+'APPENDIX 11'!F16+PENSIONS!F16 -> 0 | G16: ='APPENDIX 6'!G16+'APPENDIX 7'!G16+'APPENDIX 8'!G16+'APPENDIX 9'!G16+'APPENDIX 10'!G16+'APPENDIX 11'!G16+PENSIONS!G16 -> 5373811.7 | H16: ='APPENDIX 6'!H16+'APPENDIX 7'!H16+'APPENDIX 8'!H16+'APPENDIX 9'!H16+'APPENDIX 10'!H16+'APPENDIX 11'!H16+PENSIONS!H16 -> 4565714 | I16: ='APPENDIX 6'!I16+'APPENDIX 7'!I16+'APPENDIX 8'!I16+'APPENDIX 9'!I16+'APPENDIX 10'!I16+'APPENDIX 11'!I16+PENSIONS!I16 -> 183701.56 | J16: ='APPENDIX 6'!J16+'APPENDIX 7'!J16+'APPENDIX 8'!J16+'APPENDIX 9'!J16+'APPENDIX 10'!J16+'APPENDIX 11'!J16+PENSIONS!J16 -> 0 | ... P16: ='APPENDIX 6'!P16+'APPENDIX 7'!P16+'APPENDIX 8'!P16+'APPENDIX 9'!P16+'APPENDIX 10'!P16+'APPENDIX 11'!P16+PENSIONS!P16 -> 0 | Q16: ='APPENDIX 6'!Q26+'APPENDIX 7'!Q26+'APPENDIX 8'!Q26+'APPENDIX 9'!Q26+'APPENDIX 10'!Q26+'APPENDIX 11'!Q26+PENSIONS!Q26 -> 4706068.5
B17: ='APPENDIX 13'!B17 -> JUBILEE LIFE INSURANCE | C17: ='APPENDIX 6'!C17+'APPENDIX 7'!C17+'APPENDIX 8'!C17+'APPENDIX 9'!C17+'APPENDIX 10'!C17+'APPENDIX 11'!C17+PENSIONS!C17 -> 1.3544699e+08 | D17: ='APPENDIX 6'!D17+'APPENDIX 7'!D17+'APPENDIX 8'!D17+'APPENDIX 9'!D17+'APPENDIX 10'!D17+'APPENDIX 11'!D17+PENSIONS!D17 -> 7074577.8 | E17: ='APPENDIX 6'!E17+'APPENDIX 7'!E17+'APPENDIX 8'!E17+'APPENDIX 9'!E17+'APPENDIX 10'!E17+'APPENDIX 11'!E17+PENSIONS!E17 -> 6831891.9 | F17: ='APPENDIX 6'!F17+'APPENDIX 7'!F17+'APPENDIX 8'!F17+'APPENDIX 9'!F17+'APPENDIX 10'!F17+'APPENDIX 11'!F17+PENSIONS!F17 -> 0 | G17: ='APPENDIX 6'!G17+'APPENDIX 7'!G17+'APPENDIX 8'!G17+'APPENDIX 9'!G17+'APPENDIX 10'!G17+'APPENDIX 11'!G17+PENSIONS!G17 -> 3888128.3 | H17: ='APPENDIX 6'!H17+'APPENDIX 7'!H17+'APPENDIX 8'!H17+'APPENDIX 9'!H17+'APPENDIX 10'!H17+'APPENDIX 11'!H17+PENSIONS!H17 -> 3888128.3 | I17: ='APPENDIX 6'!I17+'APPENDIX 7'!I17+'APPENDIX 8'!I17+'APPENDIX 9'!I17+'APPENDIX 10'!I17+'APPENDIX 11'!I17+PENSIONS!I17 -> 0 | J17: ='APPENDIX 6'!J17+'APPENDIX 7'!J17+'APPENDIX 8'!J17+'APPENDIX 9'!J17+'APPENDIX 10'!J17+'APPENDIX 11'!J17+PENSIONS!J17 -> 0 | ... P17: ='APPENDIX 6'!P17+'APPENDIX 7'!P17+'APPENDIX 8'!P17+'APPENDIX 9'!P17+'APPENDIX 10'!P17+'APPENDIX 11'!P17+PENSIONS!P17 -> 0 | Q17: ='APPENDIX 6'!Q27+'APPENDIX 7'!Q27+'APPENDIX 8'!Q27+'APPENDIX 9'!Q27+'APPENDIX 10'!Q27+'APPENDIX 11'!Q27+PENSIONS!Q27 -> 32700494
B18: ='APPENDIX 13'!B18 -> KENINDIA ASSURANCE COMPANY | C18: ='APPENDIX 6'!C18+'APPENDIX 7'!C18+'APPENDIX 8'!C18+'APPENDIX 9'!C18+'APPENDIX 10'!C18+'APPENDIX 11'!C18+PENSIONS!C18 -> 89269516 | D18: ='APPENDIX 6'!D18+'APPENDIX 7'!D18+'APPENDIX 8'!D18+'APPENDIX 9'!D18+'APPENDIX 10'!D18+'APPENDIX 11'!D18+PENSIONS!D18 -> 1932826.1 | E18: ='APPENDIX 6'!E18+'APPENDIX 7'!E18+'APPENDIX 8'!E18+'APPENDIX 9'!E18+'APPENDIX 10'!E18+'APPENDIX 11'!E18+PENSIONS!E18 -> 1899263.8 | F18: ='APPENDIX 6'!F18+'APPENDIX 7'!F18+'APPENDIX 8'!F18+'APPENDIX 9'!F18+'APPENDIX 10'!F18+'APPENDIX 11'!F18+PENSIONS!F18 -> 0 | G18: ='APPENDIX 6'!G18+'APPENDIX 7'!G18+'APPENDIX 8'!G18+'APPENDIX 9'!G18+'APPENDIX 10'!G18+'APPENDIX 11'!G18+PENSIONS!G18 -> 2034084.8 | H18: ='APPENDIX 6'!H18+'APPENDIX 7'!H18+'APPENDIX 8'!H18+'APPENDIX 9'!H18+'APPENDIX 10'!H18+'APPENDIX 11'!H18+PENSIONS!H18 -> 2034084.8 | I18: ='APPENDIX 6'!I18+'APPENDIX 7'!I18+'APPENDIX 8'!I18+'APPENDIX 9'!I18+'APPENDIX 10'!I18+'APPENDIX 11'!I18+PENSIONS!I18 -> 0 | J18: ='APPENDIX 6'!J18+'APPENDIX 7'!J18+'APPENDIX 8'!J18+'APPENDIX 9'!J18+'APPENDIX 10'!J18+'APPENDIX 11'!J18+PENSIONS!J18 -> 0 | ... P18: ='APPENDIX 6'!P18+'APPENDIX 7'!P18+'APPENDIX 8'!P18+'APPENDIX 9'!P18+'APPENDIX 10'!P18+'APPENDIX 11'!P18+PENSIONS!P18 -> 163250 | Q18: ='APPENDIX 6'!Q28+'APPENDIX 7'!Q28+'APPENDIX 8'!Q28+'APPENDIX 9'!Q28+'APPENDIX 10'!Q28+'APPENDIX 11'!Q28+PENSIONS!Q28 -> 522454.22
B19: ='APPENDIX 13'!B19 -> KENYA ORIENT LIFE ASSURANCE | C19: ='APPENDIX 6'!C19+'APPENDIX 7'!C19+'APPENDIX 8'!C19+'APPENDIX 9'!C19+'APPENDIX 10'!C19+'APPENDIX 11'!C19+PENSIONS!C19 -> 4391298 | D19: ='APPENDIX 6'!D19+'APPENDIX 7'!D19+'APPENDIX 8'!D19+'APPENDIX 9'!D19+'APPENDIX 10'!D19+'APPENDIX 11'!D19+PENSIONS!D19 -> 365287.85 | E19: ='APPENDIX 6'!E19+'APPENDIX 7'!E19+'APPENDIX 8'!E19+'APPENDIX 9'!E19+'APPENDIX 10'!E19+'APPENDIX 11'!E19+PENSIONS!E19 -> 342329.25 | F19: ='APPENDIX 6'!F19+'APPENDIX 7'!F19+'APPENDIX 8'!F19+'APPENDIX 9'!F19+'APPENDIX 10'!F19+'APPENDIX 11'!F19+PENSIONS!F19 -> 0 | G19: ='APPENDIX 6'!G19+'APPENDIX 7'!G19+'APPENDIX 8'!G19+'APPENDIX 9'!G19+'APPENDIX 10'!G19+'APPENDIX 11'!G19+PENSIONS!G19 -> 117122.86 | H19: ='APPENDIX 6'!H19+'APPENDIX 7'!H19+'APPENDIX 8'!H19+'APPENDIX 9'!H19+'APPENDIX 10'!H19+'APPENDIX 11'!H19+PENSIONS!H19 -> 117122.86 | I19: ='APPENDIX 6'!I19+'APPENDIX 7'!I19+'APPENDIX 8'!I19+'APPENDIX 9'!I19+'APPENDIX 10'!I19+'APPENDIX 11'!I19+PENSIONS!I19 -> 0 | J19: ='APPENDIX 6'!J19+'APPENDIX 7'!J19+'APPENDIX 8'!J19+'APPENDIX 9'!J19+'APPENDIX 10'!J19+'APPENDIX 11'!J19+PENSIONS!J19 -> 0 | ... P19: ='APPENDIX 6'!P19+'APPENDIX 7'!P19+'APPENDIX 8'!P19+'APPENDIX 9'!P19+'APPENDIX 10'!P19+'APPENDIX 11'!P19+PENSIONS!P19 -> 0 | Q19: ='APPENDIX 6'!Q29+'APPENDIX 7'!Q29+'APPENDIX 8'!Q29+'APPENDIX 9'!Q29+'APPENDIX 10'!Q29+'APPENDIX 11'!Q29+PENSIONS!Q29 -> 5610906.4
B20: ='APPENDIX 13'!B20 -> KUSCCO MUTUAL ASSURANCE LIMITED | C20: ='APPENDIX 6'!C20+'APPENDIX 7'!C20+'APPENDIX 8'!C20+'APPENDIX 9'!C20+'APPENDIX 10'!C20+'APPENDIX 11'!C20+PENSIONS!C20 -> 529729.8 | D20: ='APPENDIX 6'!D20+'APPENDIX 7'!D20+'APPENDIX 8'!D20+'APPENDIX 9'!D20+'APPENDIX 10'!D20+'APPENDIX 11'!D20+PENSIONS!D20 -> 436999.96 | E20: ='APPENDIX 6'!E20+'APPENDIX 7'!E20+'APPENDIX 8'!E20+'APPENDIX 9'!E20+'APPENDIX 10'!E20+'APPENDIX 11'!E20+PENSIONS!E20 -> 343222.26 | F20: ='APPENDIX 6'!F20+'APPENDIX 7'!F20+'APPENDIX 8'!F20+'APPENDIX 9'!F20+'APPENDIX 10'!F20+'APPENDIX 11'!F20+PENSIONS!F20 -> 0 | G20: ='APPENDIX 6'!G20+'APPENDIX 7'!G20+'APPENDIX 8'!G20+'APPENDIX 9'!G20+'APPENDIX 10'!G20+'APPENDIX 11'!G20+PENSIONS!G20 -> 505637.18 | H20: ='APPENDIX 6'!H20+'APPENDIX 7'!H20+'APPENDIX 8'!H20+'APPENDIX 9'!H20+'APPENDIX 10'!H20+'APPENDIX 11'!H20+PENSIONS!H20 -> 505637.18 | I20: ='APPENDIX 6'!I20+'APPENDIX 7'!I20+'APPENDIX 8'!I20+'APPENDIX 9'!I20+'APPENDIX 10'!I20+'APPENDIX 11'!I20+PENSIONS!I20 -> 0 | J20: ='APPENDIX 6'!J20+'APPENDIX 7'!J20+'APPENDIX 8'!J20+'APPENDIX 9'!J20+'APPENDIX 10'!J20+'APPENDIX 11'!J20+PENSIONS!J20 -> 0 | ... Q20: ='APPENDIX 6'!Q20+'APPENDIX 7'!Q20+'APPENDIX 8'!Q20+'APPENDIX 9'!Q20+'APPENDIX 10'!Q20+'APPENDIX 11'!Q20+PENSIONS!Q20 -> 201471.66
B21: ='APPENDIX 13'!B21 -> LIBERTY LIFE ASSURANCE COMPANY | C21: ='APPENDIX 6'!C21+'APPENDIX 7'!C21+'APPENDIX 8'!C21+'APPENDIX 9'!C21+'APPENDIX 10'!C21+'APPENDIX 11'!C21+PENSIONS!C21 -> 25879671 | D21: ='APPENDIX 6'!D21+'APPENDIX 7'!D21+'APPENDIX 8'!D21+'APPENDIX 9'!D21+'APPENDIX 10'!D21+'APPENDIX 11'!D21+PENSIONS!D21 -> 1442556.5 | E21: ='APPENDIX 6'!E21+'APPENDIX 7'!E21+'APPENDIX 8'!E21+'APPENDIX 9'!E21+'APPENDIX 10'!E21+'APPENDIX 11'!E21+PENSIONS!E21 -> 1321036.4 | F21: ='APPENDIX 6'!F21+'APPENDIX 7'!F21+'APPENDIX 8'!F21+'APPENDIX 9'!F21+'APPENDIX 10'!F21+'APPENDIX 11'!F21+PENSIONS!F21 -> 0 | G21: ='APPENDIX 6'!G21+'APPENDIX 7'!G21+'APPENDIX 8'!G21+'APPENDIX 9'!G21+'APPENDIX 10'!G21+'APPENDIX 11'!G21+PENSIONS!G21 -> 1212410.1 | H21: ='APPENDIX 6'!H21+'APPENDIX 7'!H21+'APPENDIX 8'!H21+'APPENDIX 9'!H21+'APPENDIX 10'!H21+'APPENDIX 11'!H21+PENSIONS!H21 -> 1212410.1 | I21: ='APPENDIX 6'!I21+'APPENDIX 7'!I21+'APPENDIX 8'!I21+'APPENDIX 9'!I21+'APPENDIX 10'!I21+'APPENDIX 11'!I21+PENSIONS!I21 -> 0 | J21: ='APPENDIX 6'!J21+'APPENDIX 7'!J21+'APPENDIX 8'!J21+'APPENDIX 9'!J21+'APPENDIX 10'!J21+'APPENDIX 11'!J21+PENSIONS!J21 -> 0 | ... Q21: ='APPENDIX 6'!Q21+'APPENDIX 7'!Q21+'APPENDIX 8'!Q21+'APPENDIX 9'!Q21+'APPENDIX 10'!Q21+'APPENDIX 11'!Q21+PENSIONS!Q21 -> 26864198
B22: ='APPENDIX 13'!B22 -> MADISON INSURANCE COMPANY | C22: ='APPENDIX 6'!C22+'APPENDIX 7'!C22+'APPENDIX 8'!C22+'APPENDIX 9'!C22+'APPENDIX 10'!C22+'APPENDIX 11'!C22+PENSIONS!C22 -> 15136526 | D22: ='APPENDIX 6'!D22+'APPENDIX 7'!D22+'APPENDIX 8'!D22+'APPENDIX 9'!D22+'APPENDIX 10'!D22+'APPENDIX 11'!D22+PENSIONS!D22 -> 1279940 | E22: ='APPENDIX 6'!E22+'APPENDIX 7'!E22+'APPENDIX 8'!E22+'APPENDIX 9'!E22+'APPENDIX 10'!E22+'APPENDIX 11'!E22+PENSIONS!E22 -> 1146577 | F22: ='APPENDIX 6'!F22+'APPENDIX 7'!F22+'APPENDIX 8'!F22+'APPENDIX 9'!F22+'APPENDIX 10'!F22+'APPENDIX 11'!F22+PENSIONS!F22 -> 0 | G22: ='APPENDIX 6'!G22+'APPENDIX 7'!G22+'APPENDIX 8'!G22+'APPENDIX 9'!G22+'APPENDIX 10'!G22+'APPENDIX 11'!G22+PENSIONS!G22 -> 1020412 | H22: ='APPENDIX 6'!H22+'APPENDIX 7'!H22+'APPENDIX 8'!H22+'APPENDIX 9'!H22+'APPENDIX 10'!H22+'APPENDIX 11'!H22+PENSIONS!H22 -> 1020412 | I22: ='APPENDIX 6'!I22+'APPENDIX 7'!I22+'APPENDIX 8'!I22+'APPENDIX 9'!I22+'APPENDIX 10'!I22+'APPENDIX 11'!I22+PENSIONS!I22 -> 0 | J22: ='APPENDIX 6'!J22+'APPENDIX 7'!J22+'APPENDIX 8'!J22+'APPENDIX 9'!J22+'APPENDIX 10'!J22+'APPENDIX 11'!J22+PENSIONS!J22 -> 0 | ... Q22: ='APPENDIX 6'!Q22+'APPENDIX 7'!Q22+'APPENDIX 8'!Q22+'APPENDIX 9'!Q22+'APPENDIX 10'!Q22+'APPENDIX 11'!Q22+PENSIONS!Q22 -> 15034582
B23: ='APPENDIX 13'!B23 -> OLD MUTUAL ASSURANCE COMPANY | C23: ='APPENDIX 6'!C23+'APPENDIX 7'!C23+'APPENDIX 8'!C23+'APPENDIX 9'!C23+'APPENDIX 10'!C23+'APPENDIX 11'!C23+PENSIONS!C23 -> 9933649.6 | D23: ='APPENDIX 6'!D23+'APPENDIX 7'!D23+'APPENDIX 8'!D23+'APPENDIX 9'!D23+'APPENDIX 10'!D23+'APPENDIX 11'!D23+PENSIONS!D23 -> 229915.14 | E23: ='APPENDIX 6'!E23+'APPENDIX 7'!E23+'APPENDIX 8'!E23+'APPENDIX 9'!E23+'APPENDIX 10'!E23+'APPENDIX 11'!E23+PENSIONS!E23 -> 211929.57 | F23: ='APPENDIX 6'!F23+'APPENDIX 7'!F23+'APPENDIX 8'!F23+'APPENDIX 9'!F23+'APPENDIX 10'!F23+'APPENDIX 11'!F23+PENSIONS!F23 -> 66783.009 | G23: ='APPENDIX 6'!G23+'APPENDIX 7'!G23+'APPENDIX 8'!G23+'APPENDIX 9'!G23+'APPENDIX 10'!G23+'APPENDIX 11'!G23+PENSIONS!G23 -> 555084.01 | H23: ='APPENDIX 6'!H23+'APPENDIX 7'!H23+'APPENDIX 8'!H23+'APPENDIX 9'!H23+'APPENDIX 10'!H23+'APPENDIX 11'!H23+PENSIONS!H23 -> 555084.01 | I23: ='APPENDIX 6'!I23+'APPENDIX 7'!I23+'APPENDIX 8'!I23+'APPENDIX 9'!I23+'APPENDIX 10'!I23+'APPENDIX 11'!I23+PENSIONS!I23 -> 0 | J23: ='APPENDIX 6'!J23+'APPENDIX 7'!J23+'APPENDIX 8'!J23+'APPENDIX 9'!J23+'APPENDIX 10'!J23+'APPENDIX 11'!J23+PENSIONS!J23 -> 0 | ... Q23: ='APPENDIX 6'!Q23+'APPENDIX 7'!Q23+'APPENDIX 8'!Q23+'APPENDIX 9'!Q23+'APPENDIX 10'!Q23+'APPENDIX 11'!Q23+PENSIONS!Q23 -> 10131139
B24: ='APPENDIX 13'!B24 -> OLD MUTUAL LIFE ASSURANCE KENYA | C24: ='APPENDIX 6'!C24+'APPENDIX 7'!C24+'APPENDIX 8'!C24+'APPENDIX 9'!C24+'APPENDIX 10'!C24+'APPENDIX 11'!C24+PENSIONS!C24 -> 13951331 | D24: ='APPENDIX 6'!D24+'APPENDIX 7'!D24+'APPENDIX 8'!D24+'APPENDIX 9'!D24+'APPENDIX 10'!D24+'APPENDIX 11'!D24+PENSIONS!D24 -> 1546331.5 | E24: ='APPENDIX 6'!E24+'APPENDIX 7'!E24+'APPENDIX 8'!E24+'APPENDIX 9'!E24+'APPENDIX 10'!E24+'APPENDIX 11'!E24+PENSIONS!E24 -> 1212825.9 | F24: ='APPENDIX 6'!F24+'APPENDIX 7'!F24+'APPENDIX 8'!F24+'APPENDIX 9'!F24+'APPENDIX 10'!F24+'APPENDIX 11'!F24+PENSIONS!F24 -> -315698.11 | G24: ='APPENDIX 6'!G24+'APPENDIX 7'!G24+'APPENDIX 8'!G24+'APPENDIX 9'!G24+'APPENDIX 10'!G24+'APPENDIX 11'!G24+PENSIONS!G24 -> 933092.02 | H24: ='APPENDIX 6'!H24+'APPENDIX 7'!H24+'APPENDIX 8'!H24+'APPENDIX 9'!H24+'APPENDIX 10'!H24+'APPENDIX 11'!H24+PENSIONS!H24 -> 933092.02 | I24: ='APPENDIX 6'!I24+'APPENDIX 7'!I24+'APPENDIX 8'!I24+'APPENDIX 9'!I24+'APPENDIX 10'!I24+'APPENDIX 11'!I24+PENSIONS!I24 -> 0 | J24: ='APPENDIX 6'!J24+'APPENDIX 7'!J24+'APPENDIX 8'!J24+'APPENDIX 9'!J24+'APPENDIX 10'!J24+'APPENDIX 11'!J24+PENSIONS!J24 -> 0 | ... Q24: ='APPENDIX 6'!Q24+'APPENDIX 7'!Q24+'APPENDIX 8'!Q24+'APPENDIX 9'!Q24+'APPENDIX 10'!Q24+'APPENDIX 11'!Q24+PENSIONS!Q24 -> 14562561
B25: ='APPENDIX 13'!B25 -> PIONEER ASSURANCE COMPANY | C25: ='APPENDIX 6'!C25+'APPENDIX 7'!C25+'APPENDIX 8'!C25+'APPENDIX 9'!C25+'APPENDIX 10'!C25+'APPENDIX 11'!C25+PENSIONS!C25 -> 11240259 | D25: ='APPENDIX 6'!D25+'APPENDIX 7'!D25+'APPENDIX 8'!D25+'APPENDIX 9'!D25+'APPENDIX 10'!D25+'APPENDIX 11'!D25+PENSIONS!D25 -> 833917.51 | E25: ='APPENDIX 6'!E25+'APPENDIX 7'!E25+'APPENDIX 8'!E25+'APPENDIX 9'!E25+'APPENDIX 10'!E25+'APPENDIX 11'!E25+PENSIONS!E25 -> 779621.8 | F25: ='APPENDIX 6'!F25+'APPENDIX 7'!F25+'APPENDIX 8'!F25+'APPENDIX 9'!F25+'APPENDIX 10'!F25+'APPENDIX 11'!F25+PENSIONS!F25 -> 0 | G25: ='APPENDIX 6'!G25+'APPENDIX 7'!G25+'APPENDIX 8'!G25+'APPENDIX 9'!G25+'APPENDIX 10'!G25+'APPENDIX 11'!G25+PENSIONS!G25 -> 429062.52 | H25: ='APPENDIX 6'!H25+'APPENDIX 7'!H25+'APPENDIX 8'!H25+'APPENDIX 9'!H25+'APPENDIX 10'!H25+'APPENDIX 11'!H25+PENSIONS!H25 -> 429062.52 | I25: ='APPENDIX 6'!I25+'APPENDIX 7'!I25+'APPENDIX 8'!I25+'APPENDIX 9'!I25+'APPENDIX 10'!I25+'APPENDIX 11'!I25+PENSIONS!I25 -> 0 | J25: ='APPENDIX 6'!J25+'APPENDIX 7'!J25+'APPENDIX 8'!J25+'APPENDIX 9'!J25+'APPENDIX 10'!J25+'APPENDIX 11'!J25+PENSIONS!J25 -> 0 | ... Q25: ='APPENDIX 6'!Q25+'APPENDIX 7'!Q25+'APPENDIX 8'!Q25+'APPENDIX 9'!Q25+'APPENDIX 10'!Q25+'APPENDIX 11'!Q25+PENSIONS!Q25 -> 11825302
B26: ='APPENDIX 13'!B26 -> PRUDENTIAL LIFE ASSURANCE | C26: ='APPENDIX 6'!C26+'APPENDIX 7'!C26+'APPENDIX 8'!C26+'APPENDIX 9'!C26+'APPENDIX 10'!C26+'APPENDIX 11'!C26+PENSIONS!C26 -> 3919507.5 | D26: ='APPENDIX 6'!D26+'APPENDIX 7'!D26+'APPENDIX 8'!D26+'APPENDIX 9'!D26+'APPENDIX 10'!D26+'APPENDIX 11'!D26+PENSIONS!D26 -> 1092660.9 | E26: ='APPENDIX 6'!E26+'APPENDIX 7'!E26+'APPENDIX 8'!E26+'APPENDIX 9'!E26+'APPENDIX 10'!E26+'APPENDIX 11'!E26+PENSIONS!E26 -> 1017505.9 | F26: ='APPENDIX 6'!F26+'APPENDIX 7'!F26+'APPENDIX 8'!F26+'APPENDIX 9'!F26+'APPENDIX 10'!F26+'APPENDIX 11'!F26+PENSIONS!F26 -> 0 | G26: ='APPENDIX 6'!G26+'APPENDIX 7'!G26+'APPENDIX 8'!G26+'APPENDIX 9'!G26+'APPENDIX 10'!G26+'APPENDIX 11'!G26+PENSIONS!G26 -> 227635.34 | H26: ='APPENDIX 6'!H26+'APPENDIX 7'!H26+'APPENDIX 8'!H26+'APPENDIX 9'!H26+'APPENDIX 10'!H26+'APPENDIX 11'!H26+PENSIONS!H26 -> 227635.34 | I26: ='APPENDIX 6'!I26+'APPENDIX 7'!I26+'APPENDIX 8'!I26+'APPENDIX 9'!I26+'APPENDIX 10'!I26+'APPENDIX 11'!I26+PENSIONS!I26 -> 0 | J26: ='APPENDIX 6'!J26+'APPENDIX 7'!J26+'APPENDIX 8'!J26+'APPENDIX 9'!J26+'APPENDIX 10'!J26+'APPENDIX 11'!J26+PENSIONS!J26 -> 0 | ... Q26: ='APPENDIX 6'!Q26+'APPENDIX 7'!Q26+'APPENDIX 8'!Q26+'APPENDIX 9'!Q26+'APPENDIX 10'!Q26+'APPENDIX 11'!Q26+PENSIONS!Q26 -> 4706068.5
B27: ='APPENDIX 13'!B27 -> SANLAM LIFE ASSURANCE | C27: ='APPENDIX 6'!C27+'APPENDIX 7'!C27+'APPENDIX 8'!C27+'APPENDIX 9'!C27+'APPENDIX 10'!C27+'APPENDIX 11'!C27+PENSIONS!C27 -> 31424043 | D27: ='APPENDIX 6'!D27+'APPENDIX 7'!D27+'APPENDIX 8'!D27+'APPENDIX 9'!D27+'APPENDIX 10'!D27+'APPENDIX 11'!D27+PENSIONS!D27 -> 1566893.7 | E27: ='APPENDIX 6'!E27+'APPENDIX 7'!E27+'APPENDIX 8'!E27+'APPENDIX 9'!E27+'APPENDIX 10'!E27+'APPENDIX 11'!E27+PENSIONS!E27 -> 1317461.3 | F27: ='APPENDIX 6'!F27+'APPENDIX 7'!F27+'APPENDIX 8'!F27+'APPENDIX 9'!F27+'APPENDIX 10'!F27+'APPENDIX 11'!F27+PENSIONS!F27 -> 0 | G27: ='APPENDIX 6'!G27+'APPENDIX 7'!G27+'APPENDIX 8'!G27+'APPENDIX 9'!G27+'APPENDIX 10'!G27+'APPENDIX 11'!G27+PENSIONS!G27 -> 1410414.3 | H27: ='APPENDIX 6'!H27+'APPENDIX 7'!H27+'APPENDIX 8'!H27+'APPENDIX 9'!H27+'APPENDIX 10'!H27+'APPENDIX 11'!H27+PENSIONS!H27 -> 1410414.3 | I27: ='APPENDIX 6'!I27+'APPENDIX 7'!I27+'APPENDIX 8'!I27+'APPENDIX 9'!I27+'APPENDIX 10'!I27+'APPENDIX 11'!I27+PENSIONS!I27 -> 0 | J27: ='APPENDIX 6'!J27+'APPENDIX 7'!J27+'APPENDIX 8'!J27+'APPENDIX 9'!J27+'APPENDIX 10'!J27+'APPENDIX 11'!J27+PENSIONS!J27 -> 0 | ... Q27: ='APPENDIX 6'!Q27+'APPENDIX 7'!Q27+'APPENDIX 8'!Q27+'APPENDIX 9'!Q27+'APPENDIX 10'!Q27+'APPENDIX 11'!Q27+PENSIONS!Q27 -> 32700494
B28: ='APPENDIX 13'!B28 -> STAR DISCOVER LIFE INSURANCE | C28: ='APPENDIX 6'!C28+'APPENDIX 7'!C28+'APPENDIX 8'!C28+'APPENDIX 9'!C28+'APPENDIX 10'!C28+'APPENDIX 11'!C28+PENSIONS!C28 -> 546648.07 | D28: ='APPENDIX 6'!D28+'APPENDIX 7'!D28+'APPENDIX 8'!D28+'APPENDIX 9'!D28+'APPENDIX 10'!D28+'APPENDIX 11'!D28+PENSIONS!D28 -> 1449.304 | E28: ='APPENDIX 6'!E28+'APPENDIX 7'!E28+'APPENDIX 8'!E28+'APPENDIX 9'!E28+'APPENDIX 10'!E28+'APPENDIX 11'!E28+PENSIONS!E28 -> 256.157 | F28: ='APPENDIX 6'!F28+'APPENDIX 7'!F28+'APPENDIX 8'!F28+'APPENDIX 9'!F28+'APPENDIX 10'!F28+'APPENDIX 11'!F28+PENSIONS!F28 -> 0 | G28: ='APPENDIX 6'!G28+'APPENDIX 7'!G28+'APPENDIX 8'!G28+'APPENDIX 9'!G28+'APPENDIX 10'!G28+'APPENDIX 11'!G28+PENSIONS!G28 -> 17514.184 | H28: ='APPENDIX 6'!H28+'APPENDIX 7'!H28+'APPENDIX 8'!H28+'APPENDIX 9'!H28+'APPENDIX 10'!H28+'APPENDIX 11'!H28+PENSIONS!H28 -> 17514.184 | I28: ='APPENDIX 6'!I28+'APPENDIX 7'!I28+'APPENDIX 8'!I28+'APPENDIX 9'!I28+'APPENDIX 10'!I28+'APPENDIX 11'!I28+PENSIONS!I28 -> 0 | J28: ='APPENDIX 6'!J28+'APPENDIX 7'!J28+'APPENDIX 8'!J28+'APPENDIX 9'!J28+'APPENDIX 10'!J28+'APPENDIX 11'!J28+PENSIONS!J28 -> 0 | ... Q28: ='APPENDIX 6'!Q28+'APPENDIX 7'!Q28+'APPENDIX 8'!Q28+'APPENDIX 9'!Q28+'APPENDIX 10'!Q28+'APPENDIX 11'!Q28+PENSIONS!Q28 -> 522454.22
B29: ='APPENDIX 13'!B29 -> THE KENYAN ALLIANCE INSURANCE | C29: ='APPENDIX 6'!C29+'APPENDIX 7'!C29+'APPENDIX 8'!C29+'APPENDIX 9'!C29+'APPENDIX 10'!C29+'APPENDIX 11'!C29+PENSIONS!C29 -> 5662164 | D29: ='APPENDIX 6'!D29+'APPENDIX 7'!D29+'APPENDIX 8'!D29+'APPENDIX 9'!D29+'APPENDIX 10'!D29+'APPENDIX 11'!D29+PENSIONS!D29 -> 218077.79 | E29: ='APPENDIX 6'!E29+'APPENDIX 7'!E29+'APPENDIX 8'!E29+'APPENDIX 9'!E29+'APPENDIX 10'!E29+'APPENDIX 11'!E29+PENSIONS!E29 -> 209030.52 | F29: ='APPENDIX 6'!F29+'APPENDIX 7'!F29+'APPENDIX 8'!F29+'APPENDIX 9'!F29+'APPENDIX 10'!F29+'APPENDIX 11'!F29+PENSIONS!F29 -> 0 | G29: ='APPENDIX 6'!G29+'APPENDIX 7'!G29+'APPENDIX 8'!G29+'APPENDIX 9'!G29+'APPENDIX 10'!G29+'APPENDIX 11'!G29+PENSIONS!G29 -> 264779.82 | H29: ='APPENDIX 6'!H29+'APPENDIX 7'!H29+'APPENDIX 8'!H29+'APPENDIX 9'!H29+'APPENDIX 10'!H29+'APPENDIX 11'!H29+PENSIONS!H29 -> 152234.17 | I29: ='APPENDIX 6'!I29+'APPENDIX 7'!I29+'APPENDIX 8'!I29+'APPENDIX 9'!I29+'APPENDIX 10'!I29+'APPENDIX 11'!I29+PENSIONS!I29 -> 0 | J29: ='APPENDIX 6'!J29+'APPENDIX 7'!J29+'APPENDIX 8'!J29+'APPENDIX 9'!J29+'APPENDIX 10'!J29+'APPENDIX 11'!J29+PENSIONS!J29 -> 112545.64 | ... Q29: ='APPENDIX 6'!Q29+'APPENDIX 7'!Q29+'APPENDIX 8'!Q29+'APPENDIX 9'!Q29+'APPENDIX 10'!Q29+'APPENDIX 11'!Q29+PENSIONS!Q29 -> 5610906.4
B30: ='APPENDIX 13'!B30 -> THE MONARCH INSURANCE | C30: ='APPENDIX 6'!C30+'APPENDIX 7'!C30+'APPENDIX 8'!C30+'APPENDIX 9'!C30+'APPENDIX 10'!C30+'APPENDIX 11'!C30+PENSIONS!C30 -> 0 | D30: ='APPENDIX 6'!D30+'APPENDIX 7'!D30+'APPENDIX 8'!D30+'APPENDIX 9'!D30+'APPENDIX 10'!D30+'APPENDIX 11'!D30+PENSIONS!D30 -> 0 | E30: ='APPENDIX 6'!E30+'APPENDIX 7'!E30+'APPENDIX 8'!E30+'APPENDIX 9'!E30+'APPENDIX 10'!E30+'APPENDIX 11'!E30+PENSIONS!E30 -> 0 | F30: ='APPENDIX 6'!F30+'APPENDIX 7'!F30+'APPENDIX 8'!F30+'APPENDIX 9'!F30+'APPENDIX 10'!F30+'APPENDIX 11'!F30+PENSIONS!F30 -> 0 | G30: ='APPENDIX 6'!G30+'APPENDIX 7'!G30+'APPENDIX 8'!G30+'APPENDIX 9'!G30+'APPENDIX 10'!G30+'APPENDIX 11'!G30+PENSIONS!G30 -> 0 | H30: ='APPENDIX 6'!H30+'APPENDIX 7'!H30+'APPENDIX 8'!H30+'APPENDIX 9'!H30+'APPENDIX 10'!H30+'APPENDIX 11'!H30+PENSIONS!H30 -> 0 | I30: ='APPENDIX 6'!I30+'APPENDIX 7'!I30+'APPENDIX 8'!I30+'APPENDIX 9'!I30+'APPENDIX 10'!I30+'APPENDIX 11'!I30+PENSIONS!I30 -> 0 | J30: ='APPENDIX 6'!J30+'APPENDIX 7'!J30+'APPENDIX 8'!J30+'APPENDIX 9'!J30+'APPENDIX 10'!J30+'APPENDIX 11'!J30+PENSIONS!J30 -> 0 | ... Q30: ='APPENDIX 6'!Q30+'APPENDIX 7'!Q30+'APPENDIX 8'!Q30+'APPENDIX 9'!Q30+'APPENDIX 10'!Q30+'APPENDIX 11'!Q30+PENSIONS!Q30 -> 0
B31: TOTAL | C31: =SUM(C6:C30) -> 8.0678267e+08 | D31: =SUM(D6:D30) -> 53441206 | E31: =SUM(E6:E30) -> 50785682 | F31: =SUM(F6:F30) -> -263993.97 | G31: =SUM(G6:G30) -> 30915576 | H31: =SUM(H6:H30) -> 29994932 | I31: =SUM(I6:I30) -> 183701.56 | J31: =SUM(J6:J30) -> 112545.64 | ... Q31: =SUM(Q6:Q30) -> 4.4032916e+08
B32: REINSURERS
B33: ='APPENDIX 13'!B33 -> CONTINENTAL REINSURANCE | C33: ='APPENDIX 6'!C33+'APPENDIX 7'!C33+'APPENDIX 8'!C33+'APPENDIX 9'!C33+'APPENDIX 10'!C33+'APPENDIX 11'!C33+PENSIONS!C33 -> 0 | D33: ='APPENDIX 6'!D33+'APPENDIX 7'!D33+'APPENDIX 8'!D33+'APPENDIX 9'!D33+'APPENDIX 10'!D33+'APPENDIX 11'!D33+PENSIONS!D33 -> 22961.78 | E33: ='APPENDIX 6'!E33+'APPENDIX 7'!E33+'APPENDIX 8'!E33+'APPENDIX 9'!E33+'APPENDIX 10'!E33+'APPENDIX 11'!E33+PENSIONS!E33 -> 22961.78 | F33: ='APPENDIX 6'!F33+'APPENDIX 7'!F33+'APPENDIX 8'!F33+'APPENDIX 9'!F33+'APPENDIX 10'!F33+'APPENDIX 11'!F33+PENSIONS!F33 -> 0 | G33: ='APPENDIX 6'!G33+'APPENDIX 7'!G33+'APPENDIX 8'!G33+'APPENDIX 9'!G33+'APPENDIX 10'!G33+'APPENDIX 11'!G33+PENSIONS!G33 -> 16283.717 | H33: ='APPENDIX 6'!H33+'APPENDIX 7'!H33+'APPENDIX 8'!H33+'APPENDIX 9'!H33+'APPENDIX 10'!H33+'APPENDIX 11'!H33+PENSIONS!H33 -> 16283.717 | I33: ='APPENDIX 6'!I33+'APPENDIX 7'!I33+'APPENDIX 8'!I33+'APPENDIX 9'!I33+'APPENDIX 10'!I33+'APPENDIX 11'!I33+PENSIONS!I33 -> 0 | J33: ='APPENDIX 6'!J33+'APPENDIX 7'!J33+'APPENDIX 8'!J33+'APPENDIX 9'!J33+'APPENDIX 10'!J33+'APPENDIX 11'!J33+PENSIONS!J33 -> 0 | ... Q33: ='APPENDIX 6'!Q33+'APPENDIX 7'!Q33+'APPENDIX 8'!Q33+'APPENDIX 9'!Q33+'APPENDIX 10'!Q33+'APPENDIX 11'!Q33+PENSIONS!Q33 -> 14623.39
B34: ='APPENDIX 13'!B34 -> EAST AFRICA REINSURANCE | C34: ='APPENDIX 6'!C34+'APPENDIX 7'!C34+'APPENDIX 8'!C34+'APPENDIX 9'!C34+'APPENDIX 10'!C34+'APPENDIX 11'!C34+PENSIONS!C34 -> 1179335.9 | D34: ='APPENDIX 6'!D34+'APPENDIX 7'!D34+'APPENDIX 8'!D34+'APPENDIX 9'!D34+'APPENDIX 10'!D34+'APPENDIX 11'!D34+PENSIONS!D34 -> 361178.95 | E34: ='APPENDIX 6'!E34+'APPENDIX 7'!E34+'APPENDIX 8'!E34+'APPENDIX 9'!E34+'APPENDIX 10'!E34+'APPENDIX 11'!E34+PENSIONS!E34 -> 301354.61 | F34: ='APPENDIX 6'!F34+'APPENDIX 7'!F34+'APPENDIX 8'!F34+'APPENDIX 9'!F34+'APPENDIX 10'!F34+'APPENDIX 11'!F34+PENSIONS!F34 -> 0 | G34: ='APPENDIX 6'!G34+'APPENDIX 7'!G34+'APPENDIX 8'!G34+'APPENDIX 9'!G34+'APPENDIX 10'!G34+'APPENDIX 11'!G34+PENSIONS!G34 -> 149866.93 | H34: ='APPENDIX 6'!H34+'APPENDIX 7'!H34+'APPENDIX 8'!H34+'APPENDIX 9'!H34+'APPENDIX 10'!H34+'APPENDIX 11'!H34+PENSIONS!H34 -> 149866.93 | I34: ='APPENDIX 6'!I34+'APPENDIX 7'!I34+'APPENDIX 8'!I34+'APPENDIX 9'!I34+'APPENDIX 10'!I34+'APPENDIX 11'!I34+PENSIONS!I34 -> 0 | J34: ='APPENDIX 6'!J34+'APPENDIX 7'!J34+'APPENDIX 8'!J34+'APPENDIX 9'!J34+'APPENDIX 10'!J34+'APPENDIX 11'!J34+PENSIONS!J34 -> 0 | ... Q34: ='APPENDIX 6'!Q34+'APPENDIX 7'!Q34+'APPENDIX 8'!Q34+'APPENDIX 9'!Q34+'APPENDIX 10'!Q34+'APPENDIX 11'!Q34+PENSIONS!Q34 -> 1294875
B35: ='APPENDIX 13'!B35 -> KENYA REINSURANCE CORPORATION | C35: ='APPENDIX 6'!C35+'APPENDIX 7'!C35+'APPENDIX 8'!C35+'APPENDIX 9'!C35+'APPENDIX 10'!C35+'APPENDIX 11'!C35+PENSIONS!C35 -> 8381895 | D35: ='APPENDIX 6'!D35+'APPENDIX 7'!D35+'APPENDIX 8'!D35+'APPENDIX 9'!D35+'APPENDIX 10'!D35+'APPENDIX 11'!D35+PENSIONS!D35 -> 792690.47 | E35: ='APPENDIX 6'!E35+'APPENDIX 7'!E35+'APPENDIX 8'!E35+'APPENDIX 9'!E35+'APPENDIX 10'!E35+'APPENDIX 11'!E35+PENSIONS!E35 -> 792690.47 | F35: ='APPENDIX 6'!F35+'APPENDIX 7'!F35+'APPENDIX 8'!F35+'APPENDIX 9'!F35+'APPENDIX 10'!F35+'APPENDIX 11'!F35+PENSIONS!F35 -> 0 | G35: ='APPENDIX 6'!G35+'APPENDIX 7'!G35+'APPENDIX 8'!G35+'APPENDIX 9'!G35+'APPENDIX 10'!G35+'APPENDIX 11'!G35+PENSIONS!G35 -> 407753.88 | H35: ='APPENDIX 6'!H35+'APPENDIX 7'!H35+'APPENDIX 8'!H35+'APPENDIX 9'!H35+'APPENDIX 10'!H35+'APPENDIX 11'!H35+PENSIONS!H35 -> 407753.88 | I35: ='APPENDIX 6'!I35+'APPENDIX 7'!I35+'APPENDIX 8'!I35+'APPENDIX 9'!I35+'APPENDIX 10'!I35+'APPENDIX 11'!I35+PENSIONS!I35 -> 0 | J35: ='APPENDIX 6'!J35+'APPENDIX 7'!J35+'APPENDIX 8'!J35+'APPENDIX 9'!J35+'APPENDIX 10'!J35+'APPENDIX 11'!J35+PENSIONS!J35 -> 0 | ... Q35: ='APPENDIX 6'!Q35+'APPENDIX 7'!Q35+'APPENDIX 8'!Q35+'APPENDIX 9'!Q35+'APPENDIX 10'!Q35+'APPENDIX 11'!Q35+PENSIONS!Q35 -> 8501640.2
B36: TOTAL | C36: =SUM(C33:C35) -> 9561230.9 | D36: =SUM(D33:D35) -> 1176831.2 | E36: =SUM(E33:E35) -> 1117006.9 | F36: =SUM(F33:F35) -> 0 | G36: =SUM(G33:G35) -> 573904.53 | H36: =SUM(H33:H35) -> 573904.53 | I36: =SUM(I33:I35) -> 0 | J36: =SUM(J33:J35) -> 0 | ... Q36: =SUM(Q33:Q35) -> 9811138.7
B37: Amounts in Thousand Shillings

Sheet APPENDIX 15
B3: =_xlfn.CONCAT('Table of Contents'!B22,": ",'Table of Contents'!C22) -> APPENDIX 15: SUMMARY OF GROSS PREMIUM INCOME UNDER GENERAL INSURANCE BUSINESS FOR THE PERIOD ENDED 31.03.2025
B4: Company | C4: Aviation | D4: Engineering | E4: Fire Domestic | F4: Fire Industrial | G4: Liability | H4: Marine | I4: Motor Private | J4: Motor Commercial | K4: Motor Commercial PSV | L4: Personal Accident | M4: Theft | N4: Workmens' Compensation | O4: Medical | P4: Miscellaneous | Q4: Total_x000D_ | R4: Market Share (%)
B5: INSURERS
B6: =GDP!B6 -> AAR INSURANCE KENYA | C6: =GDP!C6+INWARD!C6 -> 0 | D6: =GDP!D6+INWARD!D6 -> 1119.5712 | E6: =GDP!E6+INWARD!E6 -> 309.63316 | F6: =GDP!F6+INWARD!F6 -> 6656.6433 | G6: =GDP!G6+INWARD!G6 -> 9124.4546 | H6: =GDP!H6+INWARD!H6 -> 48.25 | I6: =GDP!I6+INWARD!I6 -> 0 | J6: =GDP!J6+INWARD!J6 -> 0 | ... P6: =GDP!P6+INWARD!P6 -> 6555.1321 | Q6: =SUM(C6:P6) -> 3291152.1 | R6: =(Q6/$Q$42)*100 -> 4.3565164
B7: =GDP!B7 -> AFRICAN MERCHANT ASSURANCE | C7: =GDP!C7+INWARD!C7 -> 0 | D7: =GDP!D7+INWARD!D7 -> 17139.147 | E7: =GDP!E7+INWARD!E7 -> 123.537 | F7: =GDP!F7+INWARD!F7 -> 925.932 | G7: =GDP!G7+INWARD!G7 -> 6413.55 | H7: =GDP!H7+INWARD!H7 -> 1912.709 | I7: =GDP!I7+INWARD!I7 -> 118667.34 | J7: =GDP!J7+INWARD!J7 -> 170748.09 | ... P7: =GDP!P7+INWARD!P7 -> 7780.29 | Q7: =SUM(C7:P7) -> 1139549.1 | R7: =(Q7/$Q$42)*100 -> 1.5084275
B8: =GDP!B8 -> APA INSURANCE COMPANY | C8: =GDP!C8+INWARD!C8 -> 108049.9 | D8: =GDP!D8+INWARD!D8 -> 121056.13 | E8: =GDP!E8+INWARD!E8 -> 42109.842 | F8: =GDP!F8+INWARD!F8 -> 1033869.8 | G8: =GDP!G8+INWARD!G8 -> 193479.75 | H8: =GDP!H8+INWARD!H8 -> 93265.868 | I8: =GDP!I8+INWARD!I8 -> 885955.22 | J8: =GDP!J8+INWARD!J8 -> 766252.12 | ... P8: =GDP!P8+INWARD!P8 -> 124290.99 | Q8: =SUM(C8:P8) -> 6752530.7 | R8: =(Q8/$Q$42)*100 -> 8.9383624
B9: =GDP!B9 -> BRITAM GENERAL INSURANCE | C9: =GDP!C9+INWARD!C9 -> 36227.085 | D9: =GDP!D9+INWARD!D9 -> 391119.44 | E9: =GDP!E9+INWARD!E9 -> 63255.381 | F9: =GDP!F9+INWARD!F9 -> 630081.59 | G9: =GDP!G9+INWARD!G9 -> 238011.22 | H9: =GDP!H9+INWARD!H9 -> 142006.46 | I9: =GDP!I9+INWARD!I9 -> 429799.27 | J9: =GDP!J9+INWARD!J9 -> 211326.37 | ... P9: =GDP!P9+INWARD!P9 -> 22067.007 | Q9: =SUM(C9:P9) -> 4827677.2 | R9: =(Q9/$Q$42)*100 -> 6.3904232
B10: =GDP!B10 -> CANNON GENERAL INSURANCE (K) LIMITED | C10: =GDP!C10+INWARD!C10 -> 0 | D10: =GDP!D10+INWARD!D10 -> 42627.41 | E10: =GDP!E10+INWARD!E10 -> 5021.126 | F10: =GDP!F10+INWARD!F10 -> 20876.23 | G10: =GDP!G10+INWARD!G10 -> 9073.72 | H10: =GDP!H10+INWARD!H10 -> 14855.732 | I10: =GDP!I10+INWARD!I10 -> 377050.9 | J10: =GDP!J10+INWARD!J10 -> 113456.02 | ... P10: =GDP!P10+INWARD!P10 -> 10559.631 | Q10: =SUM(C10:P10) -> 650621.58 | R10: =(Q10/$Q$42)*100 -> 0.86123141
B11: =GDP!B11 -> CIC GENERAL INSURANCE COMPANY | C11: =GDP!C11+INWARD!C11 -> 0 | D11: =GDP!D11+INWARD!D11 -> 58747.373 | E11: =GDP!E11+INWARD!E11 -> 38529.77 | F11: =GDP!F11+INWARD!F11 -> 188258.39 | G11: =GDP!G11+INWARD!G11 -> 72114.885 | H11: =GDP!H11+INWARD!H11 -> 35120.502 | I11: =GDP!I11+INWARD!I11 -> 872590.45 | J11: =GDP!J11+INWARD!J11 -> 703727.46 | ... P11: =GDP!P11+INWARD!P11 -> 78636.963 | Q11: =SUM(C11:P11) -> 6599113.4 | R11: =(Q11/$Q$42)*100 -> 8.7352832
B12: =GDP!B12 -> CORPORATE INSURANCE COMPANY | C12: =GDP!C12+INWARD!C12 -> 0 | D12: =GDP!D12+INWARD!D12 -> 3199.4292 | E12: =GDP!E12+INWARD!E12 -> 1207.5995 | F12: =GDP!F12+INWARD!F12 -> 6994.3159 | G12: =GDP!G12+INWARD!G12 -> 2051.4668 | H12: =GDP!H12+INWARD!H12 -> 683.15549 | I12: =GDP!I12+INWARD!I12 -> 14116.571 | J12: =GDP!J12+INWARD!J12 -> 6168.2494 | ... P12: =GDP!P12+INWARD!P12 -> 2362.336 | Q12: =SUM(C12:P12) -> 44993.862 | R12: =(Q12/$Q$42)*100 -> 0.059558626
B13: =GDP!B13 -> DEFINITE ASSURANCE COMPANY | C13: =GDP!C13+INWARD!C13 -> 0 | D13: =GDP!D13+INWARD!D13 -> 56.4 | E13: =GDP!E13+INWARD!E13 -> 0 | F13: =GDP!F13+INWARD!F13 -> 239.367 | G13: =GDP!G13+INWARD!G13 -> 0 | H13: =GDP!H13+INWARD!H13 -> 0 | I13: =GDP!I13+INWARD!I13 -> 11605.909 | J13: =GDP!J13+INWARD!J13 -> 5360.2654 | ... P13: =GDP!P13+INWARD!P13 -> 20073.795 | Q13: =SUM(C13:P13) -> 70277.296 | R13: =(Q13/$Q$42)*100 -> 0.093026448
B14: =GDP!B14 -> DIRECTLINE ASSURANCE COMPANY | C14: =GDP!C14+INWARD!C14 -> 0 | D14: =GDP!D14+INWARD!D14 -> 0 | E14: =GDP!E14+INWARD!E14 -> 0 | F14: =GDP!F14+INWARD!F14 -> 0 | G14: =GDP!G14+INWARD!G14 -> 0 | H14: =GDP!H14+INWARD!H14 -> 0 | I14: =GDP!I14+INWARD!I14 -> 70428.599 | J14: =GDP!J14+INWARD!J14 -> 24195.189 | ... P14: =GDP!P14+INWARD!P14 -> 0 | Q14: =SUM(C14:P14) -> 587266.36 | R14: =(Q14/$Q$42)*100 -> 0.77736775
B15: =GDP!B15 -> EQUITY GENERAL INSURANCE LIMITED | C15: =GDP!C15+INWARD!C15 -> 0 | D15: =GDP!D15+INWARD!D15 -> 20436.198 | E15: =GDP!E15+INWARD!E15 -> 0 | F15: =GDP!F15+INWARD!F15 -> 33569.195 | G15: =GDP!G15+INWARD!G15 -> 42088.971 | H15: =GDP!H15+INWARD!H15 -> 0 | I15: =GDP!I15+INWARD!I15 -> 0 | J15: =GDP!J15+INWARD!J15 -> 0 | ... P15: =GDP!P15+INWARD!P15 -> 0 | Q15: =SUM(C15:P15) -> 1358541.5 | R15: =(Q15/$Q$42)*100 -> 1.7983089
B16: =GDP!B16 -> FIDELITY SHIELD INSURANCE | C16: =GDP!C16+INWARD!C16 -> 2366.191 | D16: =GDP!D16+INWARD!D16 -> 28167.014 | E16: =GDP!E16+INWARD!E16 -> 13590.243 | F16: =GDP!F16+INWARD!F16 -> 143092.39 | G16: =GDP!G16+INWARD!G16 -> 26636.739 | H16: =GDP!H16+INWARD!H16 -> 34615.257 | I16: =GDP!I16+INWARD!I16 -> 378001.52 | J16: =GDP!J16+INWARD!J16 -> 464242.79 | ... P16: =GDP!P16+INWARD!P16 -> 81965.32 | Q16: =SUM(C16:P16) -> 1483413.1 | R16: =(Q16/$Q$42)*100 -> 1.9636022
B17: =GDP!B17 -> FIRST ASSURANCE COMPANY | C17: =GDP!C17+INWARD!C17 -> 0 | D17: =GDP!D17+INWARD!D17 -> 56141.827 | E17: =GDP!E17+INWARD!E17 -> 15720.311 | F17: =GDP!F17+INWARD!F17 -> 242252.41 | G17: =GDP!G17+INWARD!G17 -> 34408.928 | H17: =GDP!H17+INWARD!H17 -> 65226.477 | I17: =GDP!I17+INWARD!I17 -> 221356.82 | J17: =GDP!J17+INWARD!J17 -> 208607.3 | ... P17: =GDP!P17+INWARD!P17 -> 35898.384 | Q17: =SUM(C17:P17) -> 2883545.4 | R17: =(Q17/$Q$42)*100 -> 3.8169651
... B41: =GDP!B41 -> TRIDENT INSURANCE COMPANY | C41: =GDP!C41+INWARD!C41 -> 0 | D41: =GDP!D41+INWARD!D41 -> 0 | E41: =GDP!E41+INWARD!E41 -> 0 | F41: =GDP!F41+INWARD!F41 -> 0 | G41: =GDP!G41+INWARD!G41 -> 0 | H41: =GDP!H41+INWARD!H41 -> 0 | I41: =GDP!I41+INWARD!I41 -> 0 | J41: =GDP!J41+INWARD!J41 -> 0 | ... P41: =GDP!P41+INWARD!P41 -> 0 | Q41: =SUM(C41:P41) -> 0 | R41: =(Q41/$Q$42)*100 -> 0
B42: TOTAL | C42: =SUM(C6:C41) -> 1443311.4 | D42: =SUM(D6:D41) -> 2585587.7 | E42: =SUM(E6:E41) -> 693564.52 | F42: =SUM(F6:F41) -> 8701563.3 | G42: =SUM(G6:G41) -> 1955216.7 | H42: =SUM(H6:H41) -> 1449283.1 | I42: =SUM(I6:I41) -> 8768344.6 | J42: =SUM(J6:J41) -> 7626773.5 | ... Q42: =SUM(Q6:Q41) -> 75545501 | R42: =(Q42/$Q$42)*100 -> 100
B43: REINSURERS
B44: CONTINENTAL REINSURANCE | C44: =GDP!C44+INWARD!C44 -> 7095.887 | D44: =GDP!D44+INWARD!D44 -> 167533.04 | E44: =GDP!E44+INWARD!E44 -> 289348.84 | F44: =GDP!F44+INWARD!F44 -> 823531.3 | G44: =GDP!G44+INWARD!G44 -> 57310.221 | H44: =GDP!H44+INWARD!H44 -> 81602.7 | I44: =GDP!I44+INWARD!I44 -> 15009.819 | J44: =GDP!J44+INWARD!J44 -> 64132.867 | ... P44: =GDP!P44+INWARD!P44 -> 395876.75 | Q44: =SUM(C44:P44) -> 2631687.1 | R44: =Q44/$Q$49*100 -> 28.294223
B45: EAST AFRICA REINSURANCE | C45: =GDP!C45+INWARD!C45 -> 585.7519 | D45: =GDP!D45+INWARD!D45 -> 112581.71 | E45: =GDP!E45+INWARD!E45 -> 0 | F45: =GDP!F45+INWARD!F45 -> 577542.96 | G45: =GDP!G45+INWARD!G45 -> 15908.155 | H45: =GDP!H45+INWARD!H45 -> 81905.669 | I45: =GDP!I45+INWARD!I45 -> 0 | J45: =GDP!J45+INWARD!J45 -> 100253.5 | ... P45: =GDP!P45+INWARD!P45 -> 165487.64 | Q45: =SUM(C45:P45) -> 1386158.2 | R45: =Q45/$Q$49*100 -> 14.90309
B46: GHANA REINSURANCE COMPANY | C46: =GDP!C46+INWARD!C46 -> 1126.918 | D46: =GDP!D46+INWARD!D46 -> 78195.399 | E46: =GDP!E46+INWARD!E46 -> 72082.087 | F46: =GDP!F46+INWARD!F46 -> 525071.81 | G46: =GDP!G46+INWARD!G46 -> 20256.177 | H46: =GDP!H46+INWARD!H46 -> 59207.883 | I46: =GDP!I46+INWARD!I46 -> 34981.897 | J46: =GDP!J46+INWARD!J46 -> 37897.057 | ... P46: =GDP!P46+INWARD!P46 -> 51765.325 | Q46: =SUM(C46:P46) -> 919172.43 | R46: =Q46/$Q$49*100 -> 9.8823563
B47: KENYA REINSURANCE CORPORATION | C47: =GDP!C47+INWARD!C47 -> 17710.497 | D47: =GDP!D47+INWARD!D47 -> 311312.57 | E47: =GDP!E47+INWARD!E47 -> 12833.175 | F47: =GDP!F47+INWARD!F47 -> 890714.91 | G47: =GDP!G47+INWARD!G47 -> 35668.27 | H47: =GDP!H47+INWARD!H47 -> 178577.34 | I47: =GDP!I47+INWARD!I47 -> 3771.9159 | J47: =GDP!J47+INWARD!J47 -> 50125.317 | ... P47: =GDP!P47+INWARD!P47 -> 388866.03 | Q47: =SUM(C47:P47) -> 2439927.2 | R47: =Q47/$Q$49*100 -> 26.232543
B48: WAICA REINSURANCE KENYA LIMITED | C48: =GDP!C48+INWARD!C48 -> 16683.521 | D48: =GDP!D48+INWARD!D48 -> 319123.07 | E48: =GDP!E48+INWARD!E48 -> 3257.5374 | F48: =GDP!F48+INWARD!F48 -> 789553.19 | G48: =GDP!G48+INWARD!G48 -> 318217.31 | H48: =GDP!H48+INWARD!H48 -> 82792.605 | I48: =GDP!I48+INWARD!I48 -> 5845.316 | J48: =GDP!J48+INWARD!J48 -> 32787.262 | ... P48: =GDP!P48+INWARD!P48 -> 6605.0987 | Q48: =SUM(C48:P48) -> 1924201.5 | R48: =Q48/$Q$49*100 -> 20.687788
B49: TOTAL | C49: =SUM(C44:C48) -> 43202.575 | D49: =SUM(D44:D48) -> 988745.79 | E49: =SUM(E44:E48) -> 377521.63 | F49: =SUM(F44:F48) -> 3606414.2 | G49: =SUM(G44:G48) -> 447360.13 | H49: =SUM(H44:H48) -> 484086.19 | I49: =SUM(I44:I48) -> 59608.948 | J49: =SUM(J44:J48) -> 285196 | ... R49: =SUM(R44:R48) -> 100
B50: Amounts in Thousand Shillings

Sheet GDP
B3: =_xlfn.CONCAT("GDP: SUMMARY OF GROSS DIRECT PREMIUM UNDER GENERAL INSURANCE BUSINESS FOR THE PERIOD ENDED"," ",Details!F18) -> GDP: SUMMARY OF GROSS DIRECT PREMIUM UNDER GENERAL INSURANCE BUSINESS FOR THE PERIOD ENDED 31.03.2025
B4: Company | C4: Aviation | D4: Engineering | E4: Fire Domestic | F4: Fire Industrial | G4: Liability | H4: Marine | I4: Motor Private | J4: Motor Commercial | K4: Motor Commercial PSV | L4: Personal Accident | M4: Theft | N4: Workmens' Compensation | O4: Medical | P4: Miscellaneous | Q4: Total_x000D_
B5: INSURERS
B6: AAR INSURANCE KENYA | C6: 0 | D6: 1119.5712 | E6: 309.63316 | F6: 6656.6433 | G6: 9124.4546 | H6: 48.25 | I6: 0 | J6: 0 | K6: 0 | L6: 3405.4688 | M6: 6070.6072 | N6: 38019.92 | O6: 3219842.5 | P6: 6555.1321 | Q6: 3291152.1 | R6: 0
B7: AFRICAN MERCHANT ASSURANCE | C7: 0 | D7: 17139.147 | E7: 123.537 | F7: 925.932 | G7: 6413.55 | H7: 1912.709 | I7: 118667.34 | J7: 170748.09 | K7: 755613.81 | L7: 4683.585 | M7: 1420.537 | N7: 54120.591 | O7: 0 | P7: 7608.669 | Q7: 1139377.5 | R7: 0
B8: APA INSURANCE COMPANY | C8: 108049.9 | D8: 121056.13 | E8: 42109.842 | F8: 1028164.7 | G8: 193479.75 | H8: 93040.262 | I8: 885955.22 | J8: 766252.12 | K8: 0 | L8: 64504.316 | M8: 120712.96 | N8: 257497.22 | O8: 2892011.6 | P8: 124290.99 | Q8: 6697124.9 | R8: 0
B9: BRITAM GENERAL INSURANCE | C9: 36227.085 | D9: 389231.43 | E9: 63255.381 | F9: 618336.09 | G9: 237942.16 | H9: 142006.46 | I9: 429799.27 | J9: 211326.37 | K9: 0 | L9: 65403.023 | M9: 399326.43 | N9: 146776.63 | O9: 2047252.3 | P9: 22067.007 | Q9: 4808949.6 | R9: 0
B10: CANNON GENERAL INSURANCE (K) LIMITED | C10: 0 | D10: 42030.258 | E10: 5021.126 | F10: 18573.987 | G10: 8711.35 | H10: 14783.732 | I10: 376766.58 | J10: 111908.71 | K10: 0 | L10: 11173.585 | M10: 7309.964 | N10: 38266.527 | O10: 0 | P10: 10524.631 | Q10: 645070.45 | R10: 0
B11: CIC GENERAL INSURANCE COMPANY | C11: 0 | D11: 37636.273 | E11: 38529.77 | F11: 175426.75 | G11: 71954.885 | H11: 11892.527 | I11: 872590.45 | J11: 703727.46 | K11: 0 | L11: 165872.64 | M11: 400193.89 | N11: 209133.73 | O11: 3775590.3 | P11: 77398.936 | Q11: 6539947.6 | R11: 0
B12: CORPORATE INSURANCE COMPANY | C12: 0 | D12: 1965.792 | E12: 741.97278 | F12: 4297.4447 | G12: 1260.4614 | H12: 419.74412 | I12: 8673.4976 | J12: 3789.8933 | K12: 0 | L12: 1602.7229 | M12: 1136.6465 | N12: 2305.4696 | O12: 0 | P12: 1451.4656 | Q12: 27645.11 | R12: 0
B13: DEFINITE ASSURANCE COMPANY | C13: 0 | D13: 56.4 | E13: 0 | F13: 239.367 | G13: 0 | H13: 0 | I13: 11605.909 | J13: 5360.2654 | K13: 32408.966 | L13: 1.246 | M13: 500.544 | N13: 30.803 | O13: 0 | P13: 20073.795 | Q13: 70277.296 | R13: 0
B14: DIRECTLINE ASSURANCE COMPANY | C14: 0 | D14: 0 | E14: 0 | F14: 0 | G14: 0 | H14: 0 | I14: 70428.599 | J14: 24195.189 | K14: 492642.57 | L14: 0 | M14: 0 | N14: 0 | O14: 0 | P14: 0 | Q14: 587266.36 | R14: 0
B15: EQUITY GENERAL INSURANCE LIMITED | C15: 0 | D15: 20436.198 | E15: 0 | F15: 33569.195 | G15: 42088.971 | H15: 0 | I15: 0 | J15: 0 | K15: 0 | L15: 0 | M15: 97072.728 | N15: 0 | O15: 1165374.4 | P15: 0 | Q15: 1358541.5 | R15: 0
B16: FIDELITY SHIELD INSURANCE | C16: 2366.191 | D16: 28167.014 | E16: 13590.243 | F16: 143092.39 | G16: 26181.739 | H16: 34615.257 | I16: 378001.52 | J16: 464242.79 | K16: 13029.923 | L16: 3377.34 | M16: 35284.327 | N16: 128901.07 | O16: 130142.99 | P16: 81965.32 | Q16: 1482958.1 | R16: 0
B17: FIRST ASSURANCE COMPANY | C17: 0 | D17: 38877.806 | E17: 15720.311 | F17: 222771.36 | G17: 33970.84 | H17: 64915.765 | I17: 221356.82 | J17: 208607.3 | K17: 0 | L17: 61522.848 | M17: 38124.641 | N17: 44003.951 | O17: 1855118.4 | P17: 35101.129 | Q17: 2840091.2 | R17: 0
... B41: TRIDENT INSURANCE COMPANY | C41: 0 | D41: 0 | E41: 0 | F41: 0 | G41: 0 | H41: 0 | I41: 0 | J41: 0 | K41: 0 | L41: 0 | M41: 0 | N41: 0 | O41: 0 | P41: 0 | Q41: 0 | R41: 0
B42: TOTAL | C42: =SUM(C6:C41) -> 1372530.7 | D42: =SUM(D6:D41) -> 2330757.5 | E42: =SUM(E6:E41) -> 692929.34 | F42: =SUM(F6:F41) -> 8470200.7 | G42: =SUM(G6:G41) -> 1946241.4 | H42: =SUM(H6:H41) -> 1411126.5 | I42: =SUM(I6:I41) -> 8757663.2 | J42: =SUM(J6:J41) -> 7620755.1 | ... Q42: =SUM(Q6:Q41) -> 74780805
B43: REINSURERS
B44: CONTINENTAL REINSURANCE | C44: 0 | D44: 0 | E44: 0 | F44: 0 | G44: 0 | H44: 0 | I44: 0 | J44: 0 | K44: 0 | L44: 0 | M44: 0 | N44: 0 | O44: 0 | P44: 0 | Q44: 0 | R44: 0
B45: EAST AFRICA REINSURANCE | C45: 0 | D45: 0 | E45: 0 | F45: 0 | G45: 0 | H45: 0 | I45: 0 | J45: 0 | K45: 0 | L45: 0 | M45: 0 | N45: 0 | O45: 0 | P45: 0 | Q45: 0 | R45: 0
B46: GHANA REINSURANCE COMPANY | C46: 0 | D46: 0 | E46: 0 | F46: 0 | G46: 0 | H46: 0 | I46: 0 | J46: 0 | K46: 0 | L46: 0 | M46: 0 | N46: 0 | O46: 0 | P46: 0 | Q46: 0 | R46: 0
B47: KENYA REINSURANCE CORPORATION | C47: 0 | D47: 0 | E47: 0 | F47: 0 | G47: 0 | H47: 0 | I47: 0 | J47: 0 | K47: 0 | L47: 0 | M47: 0 | N47: 0 | O47: 0 | P47: 0 | Q47: 0 | R47: 0
B48: WAICA REINSURANCE KENYA LIMITED | C48: 0 | D48: 0 | E48: 0 | F48: 0 | G48: 0 | H48: 0 | I48: 0 | J48: 0 | K48: 0 | L48: 0 | M48: 0 | N48: 0 | O48: 0 | P48: 0 | Q48: 0 | R48: 0
B49: TOTAL | C49: =SUM(C44:C48) -> 0 | D49: =SUM(D44:D48) -> 0 | E49: =SUM(E44:E48) -> 0 | F49: =SUM(F44:F48) -> 0 | G49: =SUM(G44:G48) -> 0 | H49: =SUM(H44:H48) -> 0 | I49: =SUM(I44:I48) -> 0 | J49: =SUM(J44:J48) -> 0 | ... Q49: =SUM(Q44:Q48) -> 0
B50: Amounts in Thousand Shillings

Sheet INWARD
B3: =_xlfn.CONCAT("INWARD: SUMMARY OF NET PREMIUM INCOME UNDER GENERAL INSURANCE BUSINESS FOR THE PERIOD ENDED"," ",Details!F18) -> INWARD: SUMMARY OF NET PREMIUM INCOME UNDER GENERAL INSURANCE BUSINESS FOR THE PERIOD ENDED 31.03.2025
B4: Company | C4: Aviation | D4: Engineering | E4: Fire Domestic | F4: Fire Industrial | G4: Liability | H4: Marine | I4: Motor Private | J4: Motor Commercial | K4: Motor Commercial PSV | L4: Personal Accident | M4: Theft | N4: Workmens' Compensation | O4: Medical | P4: Miscellaneous | Q4: Total_x000D_
B5: INSURERS
B6: AAR INSURANCE KENYA | C6: 0 | D6: 0 | E6: 0 | F6: 0 | G6: 0 | H6: 0 | I6: 0 | J6: 0 | K6: 0 | L6: 0 | M6: 0 | N6: 0 | O6: 0 | P6: 0 | Q6: 0 | R6: 0
B7: AFRICAN MERCHANT ASSURANCE | C7: 0 | D7: 0 | E7: 0 | F7: 0 | G7: 0 | H7: 0 | I7: 0 | J7: 0 | K7: 0 | L7: 0 | M7: 0 | N7: 0 | O7: 0 | P7: 171.621 | Q7: 171.621 | R7: 0
B8: APA INSURANCE COMPANY | C8: 0 | D8: 0 | E8: 0 | F8: 5705.124 | G8: 0 | H8: 225.606 | I8: 0 | J8: 0 | K8: 0 | L8: 31496.987 | M8: 0 | N8: 17977.994 | O8: 0 | P8: 0 | Q8: 55405.711 | R8: 0
B9: BRITAM GENERAL INSURANCE | C9: 0 | D9: 1888.0114 | E9: 0 | F9: 11745.499 | G9: 69.06315 | H9: 0 | I9: 0 | J9: 0 | K9: 0 | L9: 5025.0583 | M9: 0 | N9: 0 | O9: 0 | P9: 0 | Q9: 18727.631 | R9: 0
B10: CANNON GENERAL INSURANCE (K) LIMITED | C10: 0 | D10: 597.152 | E10: 0 | F10: 2302.2425 | G10: 362.37 | H10: 72 | I10: 284.317 | J10: 1547.311 | K10: 0 | L10: 0 | M10: 0 | N10: 350.733 | O10: 0 | P10: 35 | Q10: 5551.1255 | R10: 0
B11: CIC GENERAL INSURANCE COMPANY | C11: 0 | D11: 21111.1 | E11: 0 | F11: 12831.643 | G11: 160 | H11: 23227.975 | I11: 0 | J11: 0 | K11: 0 | L11: 0 | M11: 597.0745 | N11: 0 | O11: 0 | P11: 1238.0267 | Q11: 59165.819 | R11: 0
B12: CORPORATE INSURANCE COMPANY | C12: 0 | D12: 1233.6372 | E12: 465.6267 | F12: 2696.8712 | G12: 791.0054 | H12: 263.41137 | I12: 5443.0731 | J12: 2378.3561 | K12: 0 | L12: 1005.7924 | M12: 713.30506 | N12: 1446.8027 | O12: 0 | P12: 910.8705 | Q12: 17348.752 | R12: 0
B13: DEFINITE ASSURANCE COMPANY | C13: 0 | D13: 0 | E13: 0 | F13: 0 | G13: 0 | H13: 0 | I13: 0 | J13: 0 | K13: 0 | L13: 0 | M13: 0 | N13: 0 | O13: 0 | P13: 0 | Q13: 0 | R13: 0
B14: DIRECTLINE ASSURANCE COMPANY | C14: 0 | D14: 0 | E14: 0 | F14: 0 | G14: 0 | H14: 0 | I14: 0 | J14: 0 | K14: 0 | L14: 0 | M14: 0 | N14: 0 | O14: 0 | P14: 0 | Q14: 0 | R14: 0
B15: EQUITY GENERAL INSURANCE LIMITED | C15: 0 | D15: 0 | E15: 0 | F15: 0 | G15: 0 | H15: 0 | I15: 0 | J15: 0 | K15: 0 | L15: 0 | M15: 0 | N15: 0 | O15: 0 | P15: 0 | Q15: 0 | R15: 0
B16: FIDELITY SHIELD INSURANCE | C16: 0 | D16: 0 | E16: 0 | F16: 0 | G16: 455 | H16: 0 | I16: 0 | J16: 0 | K16: 0 | L16: 0 | M16: 0 | N16: 0 | O16: 0 | P16: 0 | Q16: 455 | R16: 0
B17: FIRST ASSURANCE COMPANY | C17: 0 | D17: 17264.021 | E17: 0 | F17: 19481.05 | G17: 438.088 | H17: 310.712 | I17: 0 | J17: 0 | K17: 0 | L17: 5163.092 | M17: 0 | N17: 0 | O17: 0 | P17: 797.255 | Q17: 43454.218 | R17: 0
... B41: TRIDENT INSURANCE COMPANY | C41: 0 | D41: 0 | E41: 0 | F41: 0 | G41: 0 | H41: 0 | I41: 0 | J41: 0 | K41: 0 | L41: 0 | M41: 0 | N41: 0 | O41: 0 | P41: 0 | Q41: 0 | R41: 0
B42: TOTAL | C42: =SUM(C6:C41) -> 70780.749 | D42: =SUM(D6:D41) -> 254830.28 | E42: =SUM(E6:E41) -> 635.1767 | F42: =SUM(F6:F41) -> 231362.57 | G42: =SUM(G6:G41) -> 8975.3163 | H42: =SUM(H6:H41) -> 38156.677 | I42: =SUM(I6:I41) -> 10681.439 | J42: =SUM(J6:J41) -> 6018.4531 | ... Q42: =SUM(Q6:Q41) -> 764695.47
B43: REINSURERS
B44: CONTINENTAL REINSURANCE | C44: 7095.887 | D44: 167533.04 | E44: 289348.84 | F44: 823531.3 | G44: 57310.221 | H44: 81602.7 | I44: 15009.819 | J44: 64132.867 | K44: 0 | L44: 96431.516 | M44: 5075.343 | N44: 10150.686 | O44: 618588.12 | P44: 395876.75 | Q44: 2631687.1 | R44: 0
B45: EAST AFRICA REINSURANCE | C45: 585.7519 | D45: 112581.71 | E45: 0 | F45: 577542.96 | G45: 15908.155 | H45: 81905.669 | I45: 0 | J45: 100253.5 | K45: 0 | L45: 17263.895 | M45: 0 | N45: 0 | O45: 314628.93 | P45: 165487.64 | Q45: 1386158.2 | R45: 0
B46: GHANA REINSURANCE COMPANY | C46: 1126.918 | D46: 78195.399 | E46: 72082.087 | F46: 525071.81 | G46: 20256.177 | H46: 59207.883 | I46: 34981.897 | J46: 37897.057 | K46: 0 | L46: 2561.038 | M46: 7438.067 | N46: -13675.954 | O46: 42264.729 | P46: 51765.325 | Q46: 919172.43 | R46: 0
B47: KENYA REINSURANCE CORPORATION | C47: 17710.497 | D47: 311312.57 | E47: 12833.175 | F47: 890714.91 | G47: 35668.27 | H47: 178577.34 | I47: 3771.9159 | J47: 50125.317 | K47: 0 | L47: 112418.92 | M47: 7755.0912 | N47: -220.39311 | O47: 430393.61 | P47: 388866.03 | Q47: 2439927.2 | R47: 0
B48: WAICA REINSURANCE KENYA LIMITED | C48: 16683.521 | D48: 319123.07 | E48: 3257.5374 | F48: 789553.19 | G48: 318217.31 | H48: 82792.605 | I48: 5845.316 | J48: 32787.262 | K48: 0 | L48: 86490.255 | M48: 17380.149 | N48: 74316.2 | O48: 171149.99 | P48: 6605.0987 | Q48: 1924201.5 | R48: 0
B49: TOTAL | C49: =SUM(C44:C48) -> 43202.575 | D49: =SUM(D44:D48) -> 988745.79 | E49: =SUM(E44:E48) -> 377521.63 | F49: =SUM(F44:F48) -> 3606414.2 | G49: =SUM(G44:G48) -> 447360.13 | H49: =SUM(H44:H48) -> 484086.19 | I49: =SUM(I44:I48) -> 59608.948 | J49: =SUM(J44:J48) -> 285196 | ... Q49: =SUM(Q44:Q48) -> 9301146.5
B50: Amounts in Thousand Shillings

Sheet APPENDIX 16
B3: =_xlfn.CONCAT('Table of Contents'!B23,": ",'Table of Contents'!C23) -> APPENDIX 16: SUMMARY OF GENERAL INSURANCE BUSINESS MARKET SHARE PER CLASS FOR THE PERIOD ENDED 31.03.2025
B4: Company | C4: Aviation | D4: Engineering | E4: Fire Domestic | F4: Fire Industrial | G4: Liability | H4: Marine | I4: Motor Private | J4: Motor Commercial | K4: Motor Commercial PSV | L4: Personal Accident | M4: Theft | N4: Workmens' Compensation | O4: Medical | P4: Miscellaneous | Q4: Total_x000D_
B5: INSURERS
B6: ='APPENDIX 15'!B6 -> AAR INSURANCE KENYA | C6: =IFERROR('APPENDIX 15'!C6/'APPENDIX 15'!C$42*100,"") -> 0 | D6: =IFERROR('APPENDIX 15'!D6/'APPENDIX 15'!D$42*100,"") -> 0.043300453 | E6: =IFERROR('APPENDIX 15'!E6/'APPENDIX 15'!E$42*100,"") -> 0.044643743 | F6: =IFERROR('APPENDIX 15'!F6/'APPENDIX 15'!F$42*100,"") -> 0.076499396 | G6: =IFERROR('APPENDIX 15'!G6/'APPENDIX 15'!G$42*100,"") -> 0.4666723 | H6: =IFERROR('APPENDIX 15'!H6/'APPENDIX 15'!H$42*100,"") -> 0.0033292322 | I6: =IFERROR('APPENDIX 15'!I6/'APPENDIX 15'!I$42*100,"") -> 0 | J6: =IFERROR('APPENDIX 15'!J6/'APPENDIX 15'!J$42*100,"") -> 0 | ... P6: =IFERROR('APPENDIX 15'!P6/'APPENDIX 15'!P$42*100,"") -> 0.47435343 | Q6: =IFERROR('APPENDIX 15'!$Q6/'APPENDIX 15'!Q$42*100,"") -> 4.3565164 | S6: =COUNTIF(Q6:Q41,">5") -> 6
B7: ='APPENDIX 15'!B7 -> AFRICAN MERCHANT ASSURANCE | C7: =IFERROR('APPENDIX 15'!C7/'APPENDIX 15'!C$42*100,"") -> 0 | D7: =IFERROR('APPENDIX 15'!D7/'APPENDIX 15'!D$42*100,"") -> 0.66287238 | E7: =IFERROR('APPENDIX 15'!E7/'APPENDIX 15'!E$42*100,"") -> 0.017811897 | F7: =IFERROR('APPENDIX 15'!F7/'APPENDIX 15'!F$42*100,"") -> 0.010640985 | G7: =IFERROR('APPENDIX 15'!G7/'APPENDIX 15'!G$42*100,"") -> 0.32802247 | H7: =IFERROR('APPENDIX 15'!H7/'APPENDIX 15'!H$42*100,"") -> 0.13197621 | I7: =IFERROR('APPENDIX 15'!I7/'APPENDIX 15'!I$42*100,"") -> 1.3533608 | J7: =IFERROR('APPENDIX 15'!J7/'APPENDIX 15'!J$42*100,"") -> 2.2387985 | ... P7: =IFERROR('APPENDIX 15'!P7/'APPENDIX 15'!P$42*100,"") -> 0.56301035 | Q7: =IFERROR('APPENDIX 15'!$Q7/'APPENDIX 15'!Q$42*100,"") -> 1.5084275
B8: ='APPENDIX 15'!B8 -> APA INSURANCE COMPANY | C8: =IFERROR('APPENDIX 15'!C8/'APPENDIX 15'!C$42*100,"") -> 7.4862501 | D8: =IFERROR('APPENDIX 15'!D8/'APPENDIX 15'!D$42*100,"") -> 4.6819581 | E8: =IFERROR('APPENDIX 15'!E8/'APPENDIX 15'!E$42*100,"") -> 6.0715104 | F8: =IFERROR('APPENDIX 15'!F8/'APPENDIX 15'!F$42*100,"") -> 11.881426 | G8: =IFERROR('APPENDIX 15'!G8/'APPENDIX 15'!G$42*100,"") -> 9.8955654 | H8: =IFERROR('APPENDIX 15'!H8/'APPENDIX 15'!H$42*100,"") -> 6.4353104 | I8: =IFERROR('APPENDIX 15'!I8/'APPENDIX 15'!I$42*100,"") -> 10.104019 | J8: =IFERROR('APPENDIX 15'!J8/'APPENDIX 15'!J$42*100,"") -> 10.046871 | ... P8: =IFERROR('APPENDIX 15'!P8/'APPENDIX 15'!P$42*100,"") -> 8.9941526 | Q8: =IFERROR('APPENDIX 15'!$Q8/'APPENDIX 15'!Q$42*100,"") -> 8.9383624
B9: ='APPENDIX 15'!B9 -> BRITAM GENERAL INSURANCE | C9: =IFERROR('APPENDIX 15'!C9/'APPENDIX 15'!C$42*100,"") -> 2.5099978 | D9: =IFERROR('APPENDIX 15'!D9/'APPENDIX 15'!D$42*100,"") -> 15.126906 | E9: =IFERROR('APPENDIX 15'!E9/'APPENDIX 15'!E$42*100,"") -> 9.1203312 | F9: =IFERROR('APPENDIX 15'!F9/'APPENDIX 15'!F$42*100,"") -> 7.241016 | G9: =IFERROR('APPENDIX 15'!G9/'APPENDIX 15'!G$42*100,"") -> 12.173138 | H9: =IFERROR('APPENDIX 15'!H9/'APPENDIX 15'!H$42*100,"") -> 9.7983932 | I9: =IFERROR('APPENDIX 15'!I9/'APPENDIX 15'!I$42*100,"") -> 4.901715 | J9: =IFERROR('APPENDIX 15'!J9/'APPENDIX 15'!J$42*100,"") -> 2.7708489 | ... P9: =IFERROR('APPENDIX 15'!P9/'APPENDIX 15'!P$42*100,"") -> 1.5968497 | Q9: =IFERROR('APPENDIX 15'!$Q9/'APPENDIX 15'!Q$42*100,"") -> 6.3904232
B10: ='APPENDIX 15'!B10 -> CANNON GENERAL INSURANCE (K) LIMITED | C10: =IFERROR('APPENDIX 15'!C10/'APPENDIX 15'!C$42*100,"") -> 0 | D10: =IFERROR('APPENDIX 15'!D10/'APPENDIX 15'!D$42*100,"") -> 1.6486546 | E10: =IFERROR('APPENDIX 15'!E10/'APPENDIX 15'!E$42*100,"") -> 0.72395947 | F10: =IFERROR('APPENDIX 15'!F10/'APPENDIX 15'!F$42*100,"") -> 0.23991355 | G10: =IFERROR('APPENDIX 15'!G10/'APPENDIX 15'!G$42*100,"") -> 0.46407746 | H10: =IFERROR('APPENDIX 15'!H10/'APPENDIX 15'!H$42*100,"") -> 1.02504 | I10: =IFERROR('APPENDIX 15'!I10/'APPENDIX 15'!I$42*100,"") -> 4.3001378 | J10: =IFERROR('APPENDIX 15'!J10/'APPENDIX 15'!J$42*100,"") -> 1.4876018 | ... P10: =IFERROR('APPENDIX 15'!P10/'APPENDIX 15'!P$42*100,"") -> 0.76413367 | Q10: =IFERROR('APPENDIX 15'!$Q10/'APPENDIX 15'!Q$42*100,"") -> 0.86123141
B11: ='APPENDIX 15'!B11 -> CIC GENERAL INSURANCE COMPANY | C11: =IFERROR('APPENDIX 15'!C11/'APPENDIX 15'!C$42*100,"") -> 0 | D11: =IFERROR('APPENDIX 15'!D11/'APPENDIX 15'!D$42*100,"") -> 2.272109 | E11: =IFERROR('APPENDIX 15'!E11/'APPENDIX 15'!E$42*100,"") -> 5.5553261 | F11: =IFERROR('APPENDIX 15'!F11/'APPENDIX 15'!F$42*100,"") -> 2.1635008 | G11: =IFERROR('APPENDIX 15'!G11/'APPENDIX 15'!G$42*100,"") -> 3.6883321 | H11: =IFERROR('APPENDIX 15'!H11/'APPENDIX 15'!H$42*100,"") -> 2.4233017 | I11: =IFERROR('APPENDIX 15'!I11/'APPENDIX 15'!I$42*100,"") -> 9.9515985 | J11: =IFERROR('APPENDIX 15'!J11/'APPENDIX 15'!J$42*100,"") -> 9.2270664 | ... P11: =IFERROR('APPENDIX 15'!P11/'APPENDIX 15'!P$42*100,"") -> 5.6904594 | Q11: =IFERROR('APPENDIX 15'!$Q11/'APPENDIX 15'!Q$42*100,"") -> 8.7352832
B12: ='APPENDIX 15'!B12 -> CORPORATE INSURANCE COMPANY | C12: =IFERROR('APPENDIX 15'!C12/'APPENDIX 15'!C$42*100,"") -> 0 | D12: =IFERROR('APPENDIX 15'!D12/'APPENDIX 15'!D$42*100,"") -> 0.12374089 | E12: =IFERROR('APPENDIX 15'!E12/'APPENDIX 15'!E$42*100,"") -> 0.17411495 | F12: =IFERROR('APPENDIX 15'!F12/'APPENDIX 15'!F$42*100,"") -> 0.080379992 | G12: =IFERROR('APPENDIX 15'!G12/'APPENDIX 15'!G$42*100,"") -> 0.10492273 | H12: =IFERROR('APPENDIX 15'!H12/'APPENDIX 15'!H$42*100,"") -> 0.047137476 | I12: =IFERROR('APPENDIX 15'!I12/'APPENDIX 15'!I$42*100,"") -> 0.16099471 | J12: =IFERROR('APPENDIX 15'!J12/'APPENDIX 15'!J$42*100,"") -> 0.080876263 | ... P12: =IFERROR('APPENDIX 15'!P12/'APPENDIX 15'!P$42*100,"") -> 0.17094731 | Q12: =IFERROR('APPENDIX 15'!$Q12/'APPENDIX 15'!Q$42*100,"") -> 0.059558626
B13: ='APPENDIX 15'!B13 -> DEFINITE ASSURANCE COMPANY | C13: =IFERROR('APPENDIX 15'!C13/'APPENDIX 15'!C$42*100,"") -> 0 | D13: =IFERROR('APPENDIX 15'!D13/'APPENDIX 15'!D$42*100,"") -> 0.0021813222 | E13: =IFERROR('APPENDIX 15'!E13/'APPENDIX 15'!E$42*100,"") -> 0 | F13: =IFERROR('APPENDIX 15'!F13/'APPENDIX 15'!F$42*100,"") -> 0.0027508505 | G13: =IFERROR('APPENDIX 15'!G13/'APPENDIX 15'!G$42*100,"") -> 0 | H13: =IFERROR('APPENDIX 15'!H13/'APPENDIX 15'!H$42*100,"") -> 0 | I13: =IFERROR('APPENDIX 15'!I13/'APPENDIX 15'!I$42*100,"") -> 0.13236147 | J13: =IFERROR('APPENDIX 15'!J13/'APPENDIX 15'!J$42*100,"") -> 0.070282215 | ... P13: =IFERROR('APPENDIX 15'!P13/'APPENDIX 15'!P$42*100,"") -> 1.4526135 | Q13: =IFERROR('APPENDIX 15'!$Q13/'APPENDIX 15'!Q$42*100,"") -> 0.093026448
B14: ='APPENDIX 15'!B14 -> DIRECTLINE ASSURANCE COMPANY | C14: =IFERROR('APPENDIX 15'!C14/'APPENDIX 15'!C$42*100,"") -> 0 | D14: =IFERROR('APPENDIX 15'!D14/'APPENDIX 15'!D$42*100,"") -> 0 | E14: =IFERROR('APPENDIX 15'!E14/'APPENDIX 15'!E$42*100,"") -> 0 | F14: =IFERROR('APPENDIX 15'!F14/'APPENDIX 15'!F$42*100,"") -> 0 | G14: =IFERROR('APPENDIX 15'!G14/'APPENDIX 15'!G$42*100,"") -> 0 | H14: =IFERROR('APPENDIX 15'!H14/'APPENDIX 15'!H$42*100,"") -> 0 | I14: =IFERROR('APPENDIX 15'!I14/'APPENDIX 15'!I$42*100,"") -> 0.80321432 | J14: =IFERROR('APPENDIX 15'!J14/'APPENDIX 15'!J$42*100,"") -> 0.31724016 | ... P14: =IFERROR('APPENDIX 15'!P14/'APPENDIX 15'!P$42*100,"") -> 0 | Q14: =IFERROR('APPENDIX 15'!$Q14/'APPENDIX 15'!Q$42*100,"") -> 0.77736775
B15: ='APPENDIX 15'!B15 -> EQUITY GENERAL INSURANCE LIMITED | C15: =IFERROR('APPENDIX 15'!C15/'APPENDIX 15'!C$42*100,"") -> 0 | D15: =IFERROR('APPENDIX 15'!D15/'APPENDIX 15'!D$42*100,"") -> 0.79038888 | E15: =IFERROR('APPENDIX 15'!E15/'APPENDIX 15'!E$42*100,"") -> 0 | F15: =IFERROR('APPENDIX 15'!F15/'APPENDIX 15'!F$42*100,"") -> 0.3857835 | G15: =IFERROR('APPENDIX 15'!G15/'APPENDIX 15'!G$42*100,"") -> 2.1526499 | H15: =IFERROR('APPENDIX 15'!H15/'APPENDIX 15'!H$42*100,"") -> 0 | I15: =IFERROR('APPENDIX 15'!I15/'APPENDIX 15'!I$42*100,"") -> 0 | J15: =IFERROR('APPENDIX 15'!J15/'APPENDIX 15'!J$42*100,"") -> 0 | ... P15: =IFERROR('APPENDIX 15'!P15/'APPENDIX 15'!P$42*100,"") -> 0 | Q15: =IFERROR('APPENDIX 15'!$Q15/'APPENDIX 15'!Q$42*100,"") -> 1.7983089
B16: ='APPENDIX 15'!B16 -> FIDELITY SHIELD INSURANCE | C16: =IFERROR('APPENDIX 15'!C16/'APPENDIX 15'!C$42*100,"") -> 0.16394182 | D16: =IFERROR('APPENDIX 15'!D16/'APPENDIX 15'!D$42*100,"") -> 1.0893854 | E16: =IFERROR('APPENDIX 15'!E16/'APPENDIX 15'!E$42*100,"") -> 1.9594778 | F16: =IFERROR('APPENDIX 15'!F16/'APPENDIX 15'!F$42*100,"") -> 1.6444446 | G16: =IFERROR('APPENDIX 15'!G16/'APPENDIX 15'!G$42*100,"") -> 1.362342 | H16: =IFERROR('APPENDIX 15'!H16/'APPENDIX 15'!H$42*100,"") -> 2.3884399 | I16: =IFERROR('APPENDIX 15'!I16/'APPENDIX 15'!I$42*100,"") -> 4.3109793 | J16: =IFERROR('APPENDIX 15'!J16/'APPENDIX 15'!J$42*100,"") -> 6.0870142 | ... P16: =IFERROR('APPENDIX 15'!P16/'APPENDIX 15'!P$42*100,"") -> 5.9313115 | Q16: =IFERROR('APPENDIX 15'!$Q16/'APPENDIX 15'!Q$42*100,"") -> 1.9636022
B17: ='APPENDIX 15'!B17 -> FIRST ASSURANCE COMPANY | C17: =IFERROR('APPENDIX 15'!C17/'APPENDIX 15'!C$42*100,"") -> 0 | D17: =IFERROR('APPENDIX 15'!D17/'APPENDIX 15'!D$42*100,"") -> 2.1713372 | E17: =IFERROR('APPENDIX 15'!E17/'APPENDIX 15'!E$42*100,"") -> 2.2665968 | F17: =IFERROR('APPENDIX 15'!F17/'APPENDIX 15'!F$42*100,"") -> 2.7840102 | G17: =IFERROR('APPENDIX 15'!G17/'APPENDIX 15'!G$42*100,"") -> 1.7598524 | H17: =IFERROR('APPENDIX 15'!H17/'APPENDIX 15'!H$42*100,"") -> 4.5006028 | I17: =IFERROR('APPENDIX 15'!I17/'APPENDIX 15'!I$42*100,"") -> 2.5244996 | J17: =IFERROR('APPENDIX 15'!J17/'APPENDIX 15'!J$42*100,"") -> 2.7351972 | ... P17: =IFERROR('APPENDIX 15'!P17/'APPENDIX 15'!P$42*100,"") -> 2.5977389 | Q17: =IFERROR('APPENDIX 15'!$Q17/'APPENDIX 15'!Q$42*100,"") -> 3.8169651
B18: ='APPENDIX 15'!B18 -> GA INSURANCE COMPANY | C18: =IFERROR('APPENDIX 15'!C18/'APPENDIX 15'!C$42*100,"") -> 23.479595 | D18: =IFERROR('APPENDIX 15'!D18/'APPENDIX 15'!D$42*100,"") -> 15.078145 | E18: =IFERROR('APPENDIX 15'!E18/'APPENDIX 15'!E$42*100,"") -> 10.727687 | F18: =IFERROR('APPENDIX 15'!F18/'APPENDIX 15'!F$42*100,"") -> 18.070191 | G18: =IFERROR('APPENDIX 15'!G18/'APPENDIX 15'!G$42*100,"") -> 5.2538047 | H18: =IFERROR('APPENDIX 15'!H18/'APPENDIX 15'!H$42*100,"") -> 13.532061 | I18: =IFERROR('APPENDIX 15'!I18/'APPENDIX 15'!I$42*100,"") -> 6.6285737 | J18: =IFERROR('APPENDIX 15'!J18/'APPENDIX 15'!J$42*100,"") -> 7.7302316 | ... P18: =IFERROR('APPENDIX 15'!P18/'APPENDIX 15'!P$42*100,"") -> 8.3833243 | Q18: =IFERROR('APPENDIX 15'!$Q18/'APPENDIX 15'!Q$42*100,"") -> 8.8854808
... B41: ='APPENDIX 15'!B41 -> TRIDENT INSURANCE COMPANY | C41: =IFERROR('APPENDIX 15'!C41/'APPENDIX 15'!C$42*100,"") -> 0 | D41: =IFERROR('APPENDIX 15'!D41/'APPENDIX 15'!D$42*100,"") -> 0 | E41: =IFERROR('APPENDIX 15'!E41/'APPENDIX 15'!E$42*100,"") -> 0 | F41: =IFERROR('APPENDIX 15'!F41/'APPENDIX 15'!F$42*100,"") -> 0 | G41: =IFERROR('APPENDIX 15'!G41/'APPENDIX 15'!G$42*100,"") -> 0 | H41: =IFERROR('APPENDIX 15'!H41/'APPENDIX 15'!H$42*100,"") -> 0 | I41: =IFERROR('APPENDIX 15'!I41/'APPENDIX 15'!I$42*100,"") -> 0 | J41: =IFERROR('APPENDIX 15'!J41/'APPENDIX 15'!J$42*100,"") -> 0 | ... P41: =IFERROR('APPENDIX 15'!P41/'APPENDIX 15'!P$42*100,"") -> 0 | Q41: =IFERROR('APPENDIX 15'!$Q41/'APPENDIX 15'!Q$42*100,"") -> 0
B42: TOTAL | C42: =IFERROR('APPENDIX 15'!C42/'APPENDIX 15'!C$42*100,"") -> 100 | D42: =IFERROR('APPENDIX 15'!D42/'APPENDIX 15'!D$42*100,"") -> 100 | E42: =IFERROR('APPENDIX 15'!E42/'APPENDIX 15'!E$42*100,"") -> 100 | F42: =IFERROR('APPENDIX 15'!F42/'APPENDIX 15'!F$42*100,"") -> 100 | G42: =IFERROR('APPENDIX 15'!G42/'APPENDIX 15'!G$42*100,"") -> 100 | H42: =IFERROR('APPENDIX 15'!H42/'APPENDIX 15'!H$42*100,"") -> 100 | I42: =IFERROR('APPENDIX 15'!I42/'APPENDIX 15'!I$42*100,"") -> 100 | J42: =IFERROR('APPENDIX 15'!J42/'APPENDIX 15'!J$42*100,"") -> 100 | ... P42: =IFERROR('APPENDIX 15'!P42/'APPENDIX 15'!P$42*100,"") -> 100 | Q42: =SUM(Q6:Q41) -> 100
B43: REINSURERS
B44: ='APPENDIX 15'!B44 -> CONTINENTAL REINSURANCE | C44: =IFERROR('APPENDIX 15'!C44/'APPENDIX 15'!C$49*100,"") -> 16.424686 | D44: =IFERROR('APPENDIX 15'!D44/'APPENDIX 15'!D$49*100,"") -> 16.943995 | E44: =IFERROR('APPENDIX 15'!E44/'APPENDIX 15'!E$49*100,"") -> 76.644306 | F44: =IFERROR('APPENDIX 15'!F44/'APPENDIX 15'!F$49*100,"") -> 22.835184 | G44: =IFERROR('APPENDIX 15'!G44/'APPENDIX 15'!G$49*100,"") -> 12.810757 | H44: =IFERROR('APPENDIX 15'!H44/'APPENDIX 15'!H$49*100,"") -> 16.85706 | I44: =IFERROR('APPENDIX 15'!I44/'APPENDIX 15'!I$49*100,"") -> 25.18048 | J44: =IFERROR('APPENDIX 15'!J44/'APPENDIX 15'!J$49*100,"") -> 22.487295 | K44: =IFERROR('APPENDIX 15'!K44/'APPENDIX 15'!K$49*100,0) -> 0 | L44: =IFERROR('APPENDIX 15'!L44/'APPENDIX 15'!L$49*100,"") -> 30.597092 | M44: =IFERROR('APPENDIX 15'!M44/'APPENDIX 15'!M$49*100,"") -> 13.48081 | N44: =IFERROR('APPENDIX 15'!N44/'APPENDIX 15'!N$49*100,"") -> 14.383744 | O44: =IFERROR('APPENDIX 15'!O44/'APPENDIX 15'!O$49*100,"") -> 39.224995 | P44: =IFERROR('APPENDIX 15'!P44/'APPENDIX 15'!$P$49*100,"") -> 39.250091 | Q44: =IFERROR('APPENDIX 15'!$Q44/'APPENDIX 15'!$Q$49*100,"") -> 28.294223
B45: ='APPENDIX 15'!B45 -> EAST AFRICA REINSURANCE | C45: =IFERROR('APPENDIX 15'!C45/'APPENDIX 15'!C$49*100,"") -> 1.3558264 | D45: =IFERROR('APPENDIX 15'!D45/'APPENDIX 15'!D$49*100,"") -> 11.386315 | E45: =IFERROR('APPENDIX 15'!E45/'APPENDIX 15'!E$49*100,"") -> 0 | F45: =IFERROR('APPENDIX 15'!F45/'APPENDIX 15'!F$49*100,"") -> 16.014327 | G45: =IFERROR('APPENDIX 15'!G45/'APPENDIX 15'!G$49*100,"") -> 3.5560064 | H45: =IFERROR('APPENDIX 15'!H45/'APPENDIX 15'!H$49*100,"") -> 16.919646 | I45: =IFERROR('APPENDIX 15'!I45/'APPENDIX 15'!I$49*100,"") -> 0 | J45: =IFERROR('APPENDIX 15'!J45/'APPENDIX 15'!J$49*100,"") -> 35.152491 | K45: =IFERROR('APPENDIX 15'!K45/'APPENDIX 15'!K$49*100,0) -> 0 | L45: =IFERROR('APPENDIX 15'!L45/'APPENDIX 15'!L$49*100,"") -> 5.4777215 | M45: =IFERROR('APPENDIX 15'!M45/'APPENDIX 15'!M$49*100,"") -> 0 | N45: =IFERROR('APPENDIX 15'!N45/'APPENDIX 15'!N$49*100,"") -> 0 | O45: =IFERROR('APPENDIX 15'!O45/'APPENDIX 15'!O$49*100,"") -> 19.950784 | P45: =IFERROR('APPENDIX 15'!P45/'APPENDIX 15'!$P$49*100,"") -> 16.407645 | Q45: =IFERROR('APPENDIX 15'!$Q45/'APPENDIX 15'!$Q$49*100,"") -> 14.90309
B46: ='APPENDIX 15'!B46 -> GHANA REINSURANCE COMPANY | C46: =IFERROR('APPENDIX 15'!C46/'APPENDIX 15'!C$49*100,"") -> 2.608451 | D46: =IFERROR('APPENDIX 15'!D46/'APPENDIX 15'!D$49*100,"") -> 7.9085443 | E46: =IFERROR('APPENDIX 15'!E46/'APPENDIX 15'!E$49*100,"") -> 19.093498 | F46: =IFERROR('APPENDIX 15'!F46/'APPENDIX 15'!F$49*100,"") -> 14.559387 | G46: =IFERROR('APPENDIX 15'!G46/'APPENDIX 15'!G$49*100,"") -> 4.5279352 | H46: =IFERROR('APPENDIX 15'!H46/'APPENDIX 15'!H$49*100,"") -> 12.230856 | I46: =IFERROR('APPENDIX 15'!I46/'APPENDIX 15'!I$49*100,"") -> 58.685647 | J46: =IFERROR('APPENDIX 15'!J46/'APPENDIX 15'!J$49*100,"") -> 13.288074 | K46: =IFERROR('APPENDIX 15'!K46/'APPENDIX 15'!K$49*100,0) -> 0 | L46: =IFERROR('APPENDIX 15'!L46/'APPENDIX 15'!L$49*100,"") -> 0.81260068 | M46: =IFERROR('APPENDIX 15'!M46/'APPENDIX 15'!M$49*100,"") -> 19.75653 | N46: =IFERROR('APPENDIX 15'!N46/'APPENDIX 15'!N$49*100,"") -> -19.379126 | O46: =IFERROR('APPENDIX 15'!O46/'APPENDIX 15'!O$49*100,"") -> 2.6800285 | P46: =IFERROR('APPENDIX 15'!P46/'APPENDIX 15'!$P$49*100,"") -> 5.1323897 | Q46: =IFERROR('APPENDIX 15'!$Q46/'APPENDIX 15'!$Q$49*100,"") -> 9.8823563
B47: ='APPENDIX 15'!B47 -> KENYA REINSURANCE CORPORATION | C47: =IFERROR('APPENDIX 15'!C47/'APPENDIX 15'!C$49*100,"") -> 40.994077 | D47: =IFERROR('APPENDIX 15'!D47/'APPENDIX 15'!D$49*100,"") -> 31.485603 | E47: =IFERROR('APPENDIX 15'!E47/'APPENDIX 15'!E$49*100,"") -> 3.3993217 | F47: =IFERROR('APPENDIX 15'!F47/'APPENDIX 15'!F$49*100,"") -> 24.698076 | G47: =IFERROR('APPENDIX 15'!G47/'APPENDIX 15'!G$49*100,"") -> 7.9730551 | H47: =IFERROR('APPENDIX 15'!H47/'APPENDIX 15'!H$49*100,"") -> 36.889574 | I47: =IFERROR('APPENDIX 15'!I47/'APPENDIX 15'!I$49*100,"") -> 6.327768 | J47: =IFERROR('APPENDIX 15'!J47/'APPENDIX 15'!J$49*100,"") -> 17.575743 | K47: =IFERROR('APPENDIX 15'!K47/'APPENDIX 15'!K$49*100,0) -> 0 | L47: =IFERROR('APPENDIX 15'!L47/'APPENDIX 15'!L$49*100,"") -> 35.669791 | M47: =IFERROR('APPENDIX 15'!M47/'APPENDIX 15'!M$49*100,"") -> 20.59859 | N47: =IFERROR('APPENDIX 15'!N47/'APPENDIX 15'!N$49*100,"") -> -0.31230186 | O47: =IFERROR('APPENDIX 15'!O47/'APPENDIX 15'!O$49*100,"") -> 27.291483 | P47: =IFERROR('APPENDIX 15'!P47/'APPENDIX 15'!$P$49*100,"") -> 38.554997 | Q47: =IFERROR('APPENDIX 15'!$Q47/'APPENDIX 15'!$Q$49*100,"") -> 26.232543
B48: ='APPENDIX 15'!B48 -> WAICA REINSURANCE KENYA LIMITED | C48: =IFERROR('APPENDIX 15'!C48/'APPENDIX 15'!C$49*100,"") -> 38.61696 | D48: =IFERROR('APPENDIX 15'!D48/'APPENDIX 15'!D$49*100,"") -> 32.275543 | E48: =IFERROR('APPENDIX 15'!E48/'APPENDIX 15'!E$49*100,"") -> 0.86287436 | F48: =IFERROR('APPENDIX 15'!F48/'APPENDIX 15'!F$49*100,"") -> 21.893026 | G48: =IFERROR('APPENDIX 15'!G48/'APPENDIX 15'!G$49*100,"") -> 71.132246 | H48: =IFERROR('APPENDIX 15'!H48/'APPENDIX 15'!H$49*100,"") -> 17.102864 | I48: =IFERROR('APPENDIX 15'!I48/'APPENDIX 15'!I$49*100,"") -> 9.8061049 | J48: =IFERROR('APPENDIX 15'!J48/'APPENDIX 15'!J$49*100,"") -> 11.496396 | K48: =IFERROR('APPENDIX 15'!K48/'APPENDIX 15'!K$49*100,0) -> 0 | L48: =IFERROR('APPENDIX 15'!L48/'APPENDIX 15'!L$49*100,"") -> 27.442795 | M48: =IFERROR('APPENDIX 15'!M48/'APPENDIX 15'!M$49*100,"") -> 46.164069 | N48: =IFERROR('APPENDIX 15'!N48/'APPENDIX 15'!N$49*100,"") -> 105.30768 | O48: =IFERROR('APPENDIX 15'!O48/'APPENDIX 15'!O$49*100,"") -> 10.85271 | P48: =IFERROR('APPENDIX 15'!P48/'APPENDIX 15'!P$49*100,"") -> 0.65487738 | Q48: =IFERROR('APPENDIX 15'!$Q48/'APPENDIX 15'!$Q$49*100,"") -> 20.687788
B49: TOTAL | C49: =SUM(C44:C48) -> 100 | D49: =SUM(D44:D48) -> 100 | E49: =SUM(E44:E48) -> 100 | F49: =SUM(F44:F48) -> 100 | G49: =SUM(G44:G48) -> 100 | H49: =SUM(H44:H48) -> 100 | I49: =SUM(I44:I48) -> 100 | J49: =SUM(J44:J48) -> 100 | ... Q49: =SUM(Q44:Q48) -> 100
B50: figures in %

Sheet APPENDIX 17
B3: =_xlfn.CONCAT('Table of Contents'!B24,": ",'Table of Contents'!C24) -> APPENDIX 17: SUMMARY OF CLAIMS PAID UNDER GENERAL INSURANCE BUSINESS FOR THE PERIOD ENDED 31.03.2025
B4: Company | C4: Aviation | D4: Engineering | E4: Fire Domestic | F4: Fire Industrial | G4: Liability | H4: Marine | I4: Motor Private | J4: Motor Commercial | K4: Motor Commercial PSV | L4: Personal Accident | M4: Theft | N4: Workmens' Compensation | O4: Medical | P4: Miscellaneous | Q4: Total_x000D_
B5: INSURERS
B6: AAR INSURANCE KENYA | C6: 0 | D6: 173.61165 | E6: 164.6223 | F6: 1660.8327 | G6: 2761.3968 | H6: 57.865415 | I6: 0 | J6: 0 | K6: 0 | L6: 1033.5529 | M6: 1161.4311 | N6: 7944.7535 | O6: 1278680.1 | P6: 1498.0142 | Q6: 1295136.1
B7: AFRICAN MERCHANT ASSURANCE | C7: 0 | D7: 612.34 | E7: 0 | F7: 0 | G7: 0 | H7: 269.912 | I7: 126280.73 | J7: 40402.317 | K7: 140000 | L7: 14921.248 | M7: 0 | N7: 11170.89 | O7: 0 | P7: 6425.538 | Q7: 340082.97
B8: APA INSURANCE COMPANY | C8: 0 | D8: 8002.664 | E8: 10845.883 | F8: 49632.443 | G8: 22902.28 | H8: 35116.345 | I8: 467469.6 | J8: 440957.21 | K8: 0 | L8: 14418.986 | M8: 29165.001 | N8: 45924.534 | O8: 833381.04 | P8: 12225.725 | Q8: 1970041.7
B9: BRITAM GENERAL INSURANCE | C9: 0 | D9: 4721.9026 | E9: 7051.1264 | F9: 94617.471 | G9: 1464.7039 | H9: 7134.1045 | I9: 191337.45 | J9: 151832.23 | K9: 0 | L9: 17433.896 | M9: 16800.822 | N9: 11662.189 | O9: 979255.66 | P9: 286571.59 | Q9: 1769883.1
B10: CANNON GENERAL INSURANCE (K) LIMITED | C10: 0 | D10: 1050.307 | E10: 1508.109 | F10: 4811.059 | G10: 839.515 | H10: -2728.29 | I10: 235047.86 | J10: 57476.636 | K10: 0 | L10: 358.478 | M10: 2095.678 | N10: 12290.962 | O10: 0 | P10: 138.999 | Q10: 312889.31
B11: CIC GENERAL INSURANCE COMPANY | C11: 0 | D11: 9144.778 | E11: 3613.8847 | F11: 37818.342 | G11: 32165.83 | H11: 5457.9872 | I11: 503155.66 | J11: 428125.56 | K11: 0 | L11: 5262.2286 | M11: -31187.219 | N11: 48217.456 | O11: 1560369.5 | P11: 60333.783 | Q11: 2662477.8
B12: CORPORATE INSURANCE COMPANY | C12: 0 | D12: 0 | E12: 483.82684 | F12: 410.775 | G12: 0 | H12: 44.25 | I12: 10737.252 | J12: 982.40206 | K12: 0 | L12: 0 | M12: 173.587 | N12: 492.952 | O12: 0 | P12: 0 | Q12: 13325.045
B13: DEFINITE ASSURANCE COMPANY | C13: 0 | D13: 0 | E13: 0 | F13: 0 | G13: 0 | H13: 0 | I13: 0 | J13: 0 | K13: 0 | L13: 0 | M13: 0 | N13: 0 | O13: 0 | P13: 0 | Q13: 0
B14: DIRECTLINE ASSURANCE COMPANY | C14: 0 | D14: 0 | E14: 0 | F14: 0 | G14: 0 | H14: 0 | I14: 115769.8 | J14: 58958.394 | K14: 914088.21 | L14: 0 | M14: 0 | N14: 0 | O14: 0 | P14: 0 | Q14: 1088816.4
B15: EQUITY GENERAL INSURANCE LIMITED | C15: 0 | D15: 0 | E15: 0 | F15: 0 | G15: 0 | H15: 0 | I15: 0 | J15: 0 | K15: 0 | L15: 0 | M15: 0 | N15: 0 | O15: 37057.403 | P15: 0 | Q15: 37057.403
B16: FIDELITY SHIELD INSURANCE | C16: 0 | D16: 772.186 | E16: 556.787 | F16: 9162.296 | G16: 838.754 | H16: 3225.082 | I16: 217725.87 | J16: 112055.79 | K16: 3366.134 | L16: 4.5 | M16: 4478.753 | N16: 17621.216 | O16: 7867.666 | P16: 4358.832 | Q16: 382033.87
B17: FIRST ASSURANCE COMPANY | C17: 0 | D17: 9308.9882 | E17: 2370.111 | F17: 32916.1 | G17: 6372.791 | H17: 1723.0595 | I17: 130674.59 | J17: 139636.17 | K17: 0 | L17: 7164.1041 | M17: 2934.1023 | N17: 8504.962 | O17: 298507.31 | P17: 196.37968 | Q17: 640308.66
... B41: TRIDENT INSURANCE COMPANY | C41: 0 | D41: 0 | E41: 0 | F41: 0 | G41: 0 | H41: 0 | I41: 0 | J41: 0 | K41: 0 | L41: 0 | M41: 0 | N41: 0 | O41: 0 | P41: 0 | Q41: 0
B42: TOTAL | C42: =SUM(C6:C41) -> 10159.106 | D42: =SUM(D6:D41) -> 158781.99 | E42: =SUM(E6:E41) -> 126820.61 | F42: =SUM(F6:F41) -> 597491.29 | G42: =SUM(G6:G41) -> 164164.07 | H42: =SUM(H6:H41) -> 150298.45 | I42: =SUM(I6:I41) -> 4602877.2 | J42: =SUM(J6:J41) -> 3656068.3 | ... Q42: =SUM(Q6:Q41) -> 23992175
B43: REINSURERS
B44: CONTINENTAL REINSURANCE | C44: 2267.707 | D44: 65233.744 | E44: 56922.834 | F44: 162011.14 | G44: 7389.1038 | H44: 26078.63 | I44: 1935.2415 | J44: 8268.759 | K44: 0 | L44: 8045.2002 | M44: 423.43159 | N44: 846.86318 | O44: 252351.66 | P44: 33027.664 | Q44: 624801.98
B45: EAST AFRICA REINSURANCE | C45: 6.62127 | D45: 50999.188 | E45: -19366.696 | F45: 230953.45 | G45: 456.21551 | H45: 18297.429 | I45: 0 | J45: 28095.077 | K45: 0 | L45: 3333.5247 | M45: 0 | N45: 0 | O45: 185320.88 | P45: 35930.498 | Q45: 534026.19
B46: GHANA REINSURANCE COMPANY | C46: 0 | D46: 10934.781 | E46: 28890.654 | F46: 211864.8 | G46: 422.512 | H46: 9000.532 | I46: 1270.076 | J46: 1375.916 | K46: 0 | L46: 270.389 | M46: 10626.675 | N46: 823.258 | O46: 77269.495 | P46: 626.921 | Q46: 353376.01
B47: KENYA REINSURANCE CORPORATION | C47: -16042.579 | D47: 103273.33 | E47: 80757.974 | F47: 676792.69 | G47: 3602.8672 | H47: 16009.608 | I47: 3029.0576 | J47: 217896.31 | K47: 0 | L47: 67681.074 | M47: 935.60137 | N47: 1687.3298 | O47: 519877.66 | P47: 227253.85 | Q47: 1902754.8
B48: WAICA REINSURANCE KENYA LIMITED | C48: -773.27586 | D48: 80238.632 | E48: 1441.6208 | F48: 343361.44 | G48: 177160.09 | H48: 71544.956 | I48: 9452.6342 | J48: 53021.256 | K48: 0 | L48: 65575.686 | M48: 1266.1219 | N48: 56345.49 | O48: 119812.65 | P48: 169968.47 | Q48: 1148415.8
B49: TOTAL | C49: =SUM(C44:C48) -> -14541.526 | D49: =SUM(D44:D48) -> 310679.68 | E49: =SUM(E44:E48) -> 148646.39 | F49: =SUM(F44:F48) -> 1624983.5 | G49: =SUM(G44:G48) -> 189030.79 | H49: =SUM(H44:H48) -> 140931.15 | I49: =SUM(I44:I48) -> 15687.009 | J49: =SUM(J44:J48) -> 308657.32 | ... Q49: =SUM(Q44:Q48) -> 4563374.7
B50: Amounts in Thousand Shillings

Sheet APPENDIX 18
B3: =_xlfn.CONCAT('Table of Contents'!B25,": ",'Table of Contents'!C25) -> APPENDIX 18: SUMMARY OF CLAIMS INCURRED UNDER GENERAL INSURANCE BUSINESS FOR THE PERIOD ENDED 31.03.2025
B4: Company | C4: Aviation | D4: Engineering | E4: Fire Domestic | F4: Fire Industrial | G4: Liability | H4: Marine | I4: Motor Private | J4: Motor Commercial | K4: Motor Commercial PSV | L4: Personal Accident | M4: Theft | N4: Workmens' Compensation | O4: Medical | P4: Miscellaneous | Q4: Total_x000D_
B5: INSURERS
B6: AAR INSURANCE KENYA | C6: 0 | D6: 254.35605 | E6: 341.95444 | F6: 2556.7828 | G6: 295.3565 | H6: -214.12659 | I6: 0 | J6: 0 | K6: 0 | L6: 3138.3216 | M6: 849.32674 | N6: 6070.3845 | O6: 1521687 | P6: 1546.5451 | Q6: 1536525.9
B7: AFRICAN MERCHANT ASSURANCE | C7: 0 | D7: -8472.1985 | E7: 0 | F7: 0 | G7: 0 | H7: 593.8064 | I7: 285744.99 | J7: -31114.903 | K7: 352000 | L7: 32826.746 | M7: 0 | N7: 24575.958 | O7: 0 | P7: 14136.184 | Q7: 670290.58
B8: APA INSURANCE COMPANY | C8: 0.60445208 | D8: 28442.17 | E8: 4224.9676 | F8: 24522.346 | G8: 62079.61 | H8: 29740.519 | I8: 602263.91 | J8: 432002.53 | K8: 0 | L8: -1062.5612 | M8: 35881.743 | N8: 59459.708 | O8: 797208.97 | P8: 23033.431 | Q8: 2097797.9
B9: BRITAM GENERAL INSURANCE | C9: 0 | D9: 4709.5812 | E9: 2412.4919 | F9: 67812.075 | G9: 12239.852 | H9: 9449.0773 | I9: 205718.64 | J9: 145274.14 | K9: 0 | L9: 36284.283 | M9: 17502.167 | N9: 31053.26 | O9: 937466.04 | P9: 211284.92 | Q9: 1681206.5
B10: CANNON GENERAL INSURANCE (K) LIMITED | C10: 0 | D10: -7912.7061 | E10: 1792.787 | F10: 12230.392 | G10: 3510.23 | H10: -4283.35 | I10: 290624.22 | J10: 60984.197 | K10: 0 | L10: 803.658 | M10: 2914.539 | N10: 10743.943 | O10: 0 | P10: 129.80389 | Q10: 371537.72
B11: CIC GENERAL INSURANCE COMPANY | C11: 0 | D11: 5612.5939 | E11: 3321.8221 | F11: -13865.652 | G11: 18453.45 | H11: -1974.898 | I11: 550221.99 | J11: 484625.53 | K11: 0 | L11: 5869.3065 | M11: -27439.282 | N11: 45972.411 | O11: 1627179.4 | P11: 41658.198 | Q11: 2739634.8
B12: CORPORATE INSURANCE COMPANY | C12: 0 | D12: -136.47587 | E12: -1145.075 | F12: 69.876129 | G12: -3.5279996 | H12: -87.202 | I12: 2198.6942 | J12: -5147.2955 | K12: 0 | L12: -100.46113 | M12: -378.173 | N12: -916.48273 | O12: 0 | P12: 0 | Q12: -5646.1228
B13: DEFINITE ASSURANCE COMPANY | C13: 0 | D13: 0 | E13: 0 | F13: 0 | G13: 0 | H13: 0 | I13: 17.5 | J13: 0 | K13: 16453.6 | L13: 0 | M13: 0 | N13: 0 | O13: 0 | P13: 0 | Q13: 16471.1
B14: DIRECTLINE ASSURANCE COMPANY | C14: 0 | D14: 0 | E14: 0 | F14: 0 | G14: 0 | H14: 0 | I14: 115769.8 | J14: 58958.394 | K14: 914088.21 | L14: 0 | M14: 0 | N14: 0 | O14: 0 | P14: 0 | Q14: 1088816.4
B15: EQUITY GENERAL INSURANCE LIMITED | C15: 0 | D15: 0 | E15: 0 | F15: 0 | G15: 0 | H15: 0 | I15: 0 | J15: 0 | K15: 0 | L15: 0 | M15: 96.6 | N15: 0 | O15: 162699.76 | P15: 0 | Q15: 162796.36
B16: FIDELITY SHIELD INSURANCE | C16: 0 | D16: -6313.892 | E16: 1444.264 | F16: 2254.981 | G16: 7501.948 | H16: 3659.808 | I16: 237355.85 | J16: 221502.99 | K16: 2226.51 | L16: 226.385 | M16: 4018.188 | N16: 35890.764 | O16: 17347.295 | P16: 11835.994 | Q16: 538951.09
B17: FIRST ASSURANCE COMPANY | C17: 0 | D17: -9670.2128 | E17: 1960.543 | F17: -48771.519 | G17: 14366.758 | H17: 9762.3006 | I17: 89779.287 | J17: 78512.258 | K17: 0 | L17: 11133.587 | M17: 8814.7396 | N17: 5532.116 | O17: 376843.17 | P17: 125.70297 | Q17: 538388.73
... B41: TRIDENT INSURANCE COMPANY | C41: 0 | D41: 0 | E41: 0 | F41: 0 | G41: 0 | H41: 0 | I41: 0 | J41: 0 | K41: 0 | L41: 0 | M41: 0 | N41: 0 | O41: 0 | P41: 0 | Q41: 0
B42: TOTAL | C42: =SUM(C6:C41) -> 16985.259 | D42: =SUM(D6:D41) -> 74350.658 | E42: =SUM(E6:E41) -> 117291.93 | F42: =SUM(F6:F41) -> 221003.79 | G42: =SUM(G6:G41) -> 325528.17 | H42: =SUM(H6:H41) -> 170948.07 | I42: =SUM(I6:I41) -> 5488871.8 | J42: =SUM(J6:J41) -> 3726846.1 | ... Q42: =SUM(Q6:Q41) -> 25817210
B43: REINSURERS
B44: CONTINENTAL REINSURANCE | C44: 4762.6788 | D44: -67659.841 | E44: 68822.852 | F44: 195880.42 | G44: 24740.538 | H44: 54770.811 | I44: 6479.6645 | J44: 27685.84 | K44: 0 | L44: -6617.4913 | M44: -348.28928 | N44: -696.57856 | O44: 200431.31 | P44: -27166.546 | Q44: 481085.37
B45: EAST AFRICA REINSURANCE | C45: 181.04297 | D45: 46610.41 | E45: -19366.696 | F45: 346168.69 | G45: -1575.9619 | H45: 44594.092 | I45: 0 | J45: 6729.4553 | K45: 0 | L45: -42.422726 | M45: 0 | N45: 0 | O45: 300864.99 | P45: 29382.394 | Q45: 753546
B46: GHANA REINSURANCE COMPANY | C46: 2878.894 | D46: 43865.816 | E46: 75490.011 | F46: 258464.15 | G46: 1580.1148 | H46: 9492.4427 | I46: 9343.5014 | J46: 9449.3414 | K46: 0 | L46: -2819.2562 | M46: 11166.324 | N46: -2266.3872 | O46: 133985.22 | P46: 1995.6443 | Q46: 552625.82
B47: KENYA REINSURANCE CORPORATION | C47: -16042.579 | D47: 103273.33 | E47: 80757.974 | F47: 676792.69 | G47: 3602.8672 | H47: 16009.608 | I47: 3029.0576 | J47: 217896.31 | K47: 0 | L47: 67681.074 | M47: 935.60137 | N47: 1687.3298 | O47: 519877.66 | P47: 227253.85 | Q47: 1902754.8
B48: WAICA REINSURANCE KENYA LIMITED | C48: 11145.693 | D48: 439356.36 | E48: 7183.051 | F48: -285146.67 | G48: -557093.72 | H48: 170027.68 | I48: -65.11566 | J48: 154303.47 | K48: 0 | L48: 146423 | M48: -901.86851 | N48: 57831.278 | O48: 410562.38 | P48: 108943.36 | Q48: 662568.9
B49: TOTAL | C49: =SUM(C44:C48) -> 2925.7297 | D49: =SUM(D44:D48) -> 565446.08 | E49: =SUM(E44:E48) -> 212887.19 | F49: =SUM(F44:F48) -> 1192159.3 | G49: =SUM(G44:G48) -> -528746.16 | H49: =SUM(H44:H48) -> 294894.63 | I49: =SUM(I44:I48) -> 18787.108 | J49: =SUM(J44:J48) -> 416064.42 | ... Q49: =SUM(Q44:Q48) -> 4352580.9
B50: Amounts in Thousand Shillings

Sheet APPENDIX 19
B3: =_xlfn.CONCAT('Table of Contents'!B26,": ",'Table of Contents'!C26) -> APPENDIX 19: SUMMARY OF INCURRED CLAIMS RATIOS UNDER GENERAL INSURANCE BUSINESS FOR THE PERIOD ENDED 31.03.2025
B4: Company | C4: Aviation | D4: Engineering | E4: Fire Domestic | F4: Fire Industrial | G4: Liability | H4: Marine | I4: Motor Private | J4: Motor Commercial | K4: Motor Commercial PSV | L4: Personal Accident | M4: Theft | N4: Workmens' Compensation | O4: Medical | P4: Miscellaneous | Q4: Total_x000D_
B5: INSURERS
B6: AAR INSURANCE KENYA | C6: =IFERROR('APPENDIX 18'!C6/NEPI!C6*100,"0.00") -> 0.00 | D6: =IFERROR('APPENDIX 18'!D6/NEPI!D6*100,"0.00") -> -70.838113 | E6: =IFERROR('APPENDIX 18'!E6/NEPI!E6*100,"0.00") -> 112.23813 | F6: =IFERROR('APPENDIX 18'!F6/NEPI!F6*100,"0.00") -> -232.94525 | G6: =IFERROR('APPENDIX 18'!G6/NEPI!G6*100,"0.00") -> 4.2614806 | H6: =IFERROR('APPENDIX 18'!H6/NEPI!H6*100,"0.00") -> -136.6256 | I6: =IFERROR('APPENDIX 18'!I6/NEPI!I6*100,"0.00") -> 0.00 | J6: =IFERROR('APPENDIX 18'!J6/NEPI!J6*100,"0.00") -> 0.00 | ... Q6: =IFERROR('APPENDIX 18'!Q6/NEPI!Q6*100,"0.00") -> 77.533616
