Workbook
Name Appendix_1_Range: 'APPENDIX 1'!$B$3:$T$50
Name Appendix_10_Range: 'APPENDIX 10'!$B$3:$Q$34
Name Appendix_11_Range: 'APPENDIX 11'!$B$3:$Q$34
Name Appendix_12_Range: 'APPENDIX 12'!$B$3:$Q$34
Name Appendix_13_Range: 'APPENDIX 13'!$B$3:$Q$34
Name Appendix_14_Range: 'APPENDIX 14'!$B$3:$Q$34
Name Appendix_15_Range: 'APPENDIX 15'!$B$3:$Q$34
Name Appendix_16_Range: 'APPENDIX 16'!$B$3:$Q$34
Name Appendix_17_Range: 'APPENDIX 17'!$B$3:$Q$33
Name Appendix_18_Range: 'APPENDIX 18'!$B$3:$R$49
Name Appendix_19_Range: 'APPENDIX 19'!$B$3:$Q$49
Name Appendix_2_Range: 'APPENDIX 2'!$B$3:$T$35
Name Appendix_20_Range: 'APPENDIX 20'!$B$3:$Q$49
Name Appendix_21_Range: 'APPENDIX 21'!$B$3:$Q$49
Name Appendix_22_Range: 'APPENDIX 22'!$B$3:$Q$49
Name Appendix_23_Range: 'APPENDIX 23'!$B$3:$Q$49
Name Appendix_24_Range: 'APPENDIX 24'!$B$3:$L$35
Name Appendix_25_Range: 'APPENDIX 25'!$B$3:$Q$13
Name Appendix_3_Range: 'APPENDIX 3'!$B$3:$T$13
Name Appendix_4i_Range: 'APPENDIX 4 i'!$B$4:$K$46
Name Appendix_4ii_Range: 'APPENDIX 4 ii'!$B$3:$K$46
Name Appendix_4iii_Range: 'APPENDIX 4 iii'!$B$3:$L$46
Name Appendix_5i_Range: 'APPENDIX 5 i'!$B$4:$L$44
Name Appendix_5ii_Range: 'APPENDIX 5 ii'!$B$3:$L$44
Name Appendix_5iii_Range: 'APPENDIX 5 iii'!$B$3:$M$44
Name Appendix_5iv_Range: 'APPENDIX 5 iv'!$B$3:$N$44
Name Appendix_6i_Range: 'APPENDIX 6'!$B$4:$I$44
Name Appendix_7_Range: 'APPENDIX 7'!$B$3:$L$34
Name Appendix_8_Range: 'APPENDIX 8'!$B$3:$K$34
Name Appendix_9_Range: 'APPENDIX 9'!$B$3:$Q$34
Name Details_Range: Details!$C$2:$J$21
Name Reliances_and_Limitations: 'Reliance & Limitations'!$A$2:$G$8
Name Table_of_Contents: 'Table of Contents'!$A$1:$D$37

Sheet Details
E6: INSURANCE REGULATORY AUTHORITY
E11: TYPE OF INDUSTRY STATISTICS | F11: Quarterly (Unaudited)
E13: QUARTER | F13: 1
E15: YEAR | F15: 2026
E18: PERIOD ENDED | F18: 31.03.2026

Sheet Reliance & Limitations
B3: RELIANCE AND LIMITATIONS
B4: The insurance information contained in this workbook has been extracted from the quarterly unaudited returns submitted to the Authority in line with Section 54 of the Insurance Act. No adjustments have been made to the returns’ data except where necessary in consultation with the affected insurer(s) or reinsurer(s). The publication of any summary of the returns in this report does not necessarily mean that the returns so summarized have satisfied all the requirements of the Insurance Act, or that the Commissioner of Insurance approves the accuracy or the contents of the returns Where necessary, figures have been adjusted to eliminate errors in totals due to rounding off, and are given in thousands Kenya Shillings (‘000’ KES) except where otherwise stated. The report incorporates data from all insurers and reinsurers except for, Definite Assurance Company, The Kenyan Alliance Insurance Company Limited- General, The Monarch Insurance Company Limited- General, The Kenyan Alliance Insurance Company Limited- Life, The Monarch Insurance Company Limited-Life, Star Discover Micro Insurance Limited and Birdview Micro Insurance due to non-compliance with the submission requirements

Sheet Table of Contents
B3: INSURANCE REGULATORY AUTHORITY
B5: =Details!F15&" QUARTER"&" "&Details!F13&" "&"STATISTICS" -> 2026 QUARTER 1 STATISTICS
B6: TABLE OF CONTENTS
B7: Link | C7: Description
B8: APPENDIX 1 | C8: =_xlfn.CONCAT("SUMMARY OF GENERAL INSURANCE BUSINESS PROFIT & LOSS ACCOUNTS FOR THE PERIOD ENDED"," ",Details!F18) -> SUMMARY OF GENERAL INSURANCE BUSINESS PROFIT & LOSS ACCOUNTS FOR THE PERIOD ENDED 31.03.2026
B9: APPENDIX 2 | C9: =_xlfn.CONCAT("SUMMARY OF LONG TERM INSURANCE BUSINESS PROFIT & LOSS ACCOUNTS FOR THE PERIOD ENDED"," ",Details!$F$18) -> SUMMARY OF LONG TERM INSURANCE BUSINESS PROFIT & LOSS ACCOUNTS FOR THE PERIOD ENDED 31.03.2026
B10: APPENDIX 3 | C10: =_xlfn.CONCAT("SUMMARY OF MICRO INSURANCE BUSINESS PROFIT & LOSS ACCOUNTS FOR THE PERIOD ENDED"," ",Details!$F$18) -> SUMMARY OF MICRO INSURANCE BUSINESS PROFIT & LOSS ACCOUNTS FOR THE PERIOD ENDED 31.03.2026
B11: APPENDIX 4 i | C11: =_xlfn.CONCAT("SUMMARY OF LONG TERM INSURANCE BUSINESS BALANCE SHEETS AS AT"," ",Details!F18) -> SUMMARY OF LONG TERM INSURANCE BUSINESS BALANCE SHEETS AS AT 31.03.2026
B12: APPENDIX 4 ii | C12: =_xlfn.CONCAT("SUMMARY OF LONG TERM INSURANCE BUSINESS BALANCE SHEETS AS AT"," ",Details!F18) -> SUMMARY OF LONG TERM INSURANCE BUSINESS BALANCE SHEETS AS AT 31.03.2026
B13: APPENDIX 4 iii | C13: =_xlfn.CONCAT("SUMMARY OF LONG TERM INSURANCE BUSINESS BALANCE SHEETS AS AT"," ",Details!F18) -> SUMMARY OF LONG TERM INSURANCE BUSINESS BALANCE SHEETS AS AT 31.03.2026
B14: APPENDIX 5 i | C14: =_xlfn.CONCAT("SUMMARY OF GENERAL INSURANCE BUSINESS BALANCE SHEETS AS AT"," ",Details!F18) -> SUMMARY OF GENERAL INSURANCE BUSINESS BALANCE SHEETS AS AT 31.03.2026
B15: APPENDIX 5 ii | C15: =_xlfn.CONCAT("SUMMARY OF GENERAL INSURANCE BUSINESS BALANCE SHEETS AS AT"," ",Details!F18) -> SUMMARY OF GENERAL INSURANCE BUSINESS BALANCE SHEETS AS AT 31.03.2026
B16: APPENDIX 5 iii | C16: =_xlfn.CONCAT("SUMMARY OF GENERAL INSURANCE BUSINESS BALANCE SHEETS AS AT"," ",Details!F18) -> SUMMARY OF GENERAL INSURANCE BUSINESS BALANCE SHEETS AS AT 31.03.2026
B17: APPENDIX 5 iv | C17: =_xlfn.CONCAT("SUMMARY OF GENERAL INSURANCE BUSINESS BALANCE SHEETS AS AT"," ",Details!F18) -> SUMMARY OF GENERAL INSURANCE BUSINESS BALANCE SHEETS AS AT 31.03.2026
B18: APPENDIX 6 | C18: =_xlfn.CONCAT("SUMMARY OF MICRO INSURANCE BUSINESS BALANCE SHEETS AS AT"," ",Details!F18) -> SUMMARY OF MICRO INSURANCE BUSINESS BALANCE SHEETS AS AT 31.03.2026
B19: APPENDIX 7 | C19: =_xlfn.CONCAT("SUMMARY OF LONG TERM INSURANCE BUSINESS GROSS PREMIUM INCOME FOR THE PERIOD ENDED"," ",Details!F18) -> SUMMARY OF LONG TERM INSURANCE BUSINESS GROSS PREMIUM INCOME FOR THE PERIOD ENDED 31.03.2026
B20: APPENDIX 8 | C20: =_xlfn.CONCAT("SUMMARY OF LONG TERM INSURANCE BUSINESS MARKET SHARE PER CLASS FOR THE PERIOD ENDED"," ",Details!F18) -> SUMMARY OF LONG TERM INSURANCE BUSINESS MARKET SHARE PER CLASS FOR THE PERIOD ENDED 31.03.2026
B21: APPENDIX 9 | C21: =_xlfn.CONCAT("SUMMARY OF LIFE ASSURANCE BUSINESS REVENUE ACCOUNTS FOR THE PERIOD ENDED"," ",Details!F18) -> SUMMARY OF LIFE ASSURANCE BUSINESS REVENUE ACCOUNTS FOR THE PERIOD ENDED 31.03.2026
B22: APPENDIX 10 | C22: =_xlfn.CONCAT("SUMMARY OF ANNUITIES BUSINESS REVENUE ACCOUNTS FOR THE PERIOD ENDED"," ",Details!F18) -> SUMMARY OF ANNUITIES BUSINESS REVENUE ACCOUNTS FOR THE PERIOD ENDED 31.03.2026
B23: APPENDIX 11 | C23: =_xlfn.CONCAT("SUMMARY OF GROUP LIFE BUSINESS REVENUE ACCOUNTS FOR THE PERIOD ENDED"," ",Details!F18) -> SUMMARY OF GROUP LIFE BUSINESS REVENUE ACCOUNTS FOR THE PERIOD ENDED 31.03.2026
B24: APPENDIX 12 | C24: =_xlfn.CONCAT("SUMMARY OF GROUP CREDIT BUSINESS REVENUE ACCOUNTS FOR THE PERIOD ENDED"," ",Details!F18) -> SUMMARY OF GROUP CREDIT BUSINESS REVENUE ACCOUNTS FOR THE PERIOD ENDED 31.03.2026
B25: APPENDIX 13 | C25: =_xlfn.CONCAT("SUMMARY OF INVESTMENTS BUSINESS REVENUE ACCOUNTS FOR THE PERIOD ENDED"," ",Details!F18) -> SUMMARY OF INVESTMENTS BUSINESS REVENUE ACCOUNTS FOR THE PERIOD ENDED 31.03.2026
B26: APPENDIX 14 | C26: =_xlfn.CONCAT("SUMMARY OF PERMANENT HEALTH BUSINESS REVENUE ACCOUNTS FOR THE PERIOD ENDED"," ",Details!F18) -> SUMMARY OF PERMANENT HEALTH BUSINESS REVENUE ACCOUNTS FOR THE PERIOD ENDED 31.03.2026
B27: APPENDIX 15 | C27: =_xlfn.CONCAT("SUMMARY OF PERSONAL PENSIONS BUSINESS REVENUE ACCOUNTS FOR THE PERIOD ENDED"," ",Details!F18) -> SUMMARY OF PERSONAL PENSIONS BUSINESS REVENUE ACCOUNTS FOR THE PERIOD ENDED 31.03.2026
B28: APPENDIX 16 | C28: =_xlfn.CONCAT("SUMMARY OF DEPOSIT ADMINISTRATION BUSINESS REVENUE ACCOUNTS FOR THE PERIOD ENDED"," ",Details!F18) -> SUMMARY OF DEPOSIT ADMINISTRATION BUSINESS REVENUE ACCOUNTS FOR THE PERIOD ENDED 31.03.2026
B29: APPENDIX 17 | C29: =_xlfn.CONCAT("SUMMARY OF COMBINED LONG TERM BUSINESS REVENUE ACCOUNTS FOR THE PERIOD ENDED"," ",Details!F18) -> SUMMARY OF COMBINED LONG TERM BUSINESS REVENUE ACCOUNTS FOR THE PERIOD ENDED 31.03.2026
B30: APPENDIX 18 | C30: =_xlfn.CONCAT("SUMMARY OF GROSS PREMIUM INCOME UNDER GENERAL INSURANCE BUSINESS FOR THE PERIOD ENDED"," ",Details!$F$18) -> SUMMARY OF GROSS PREMIUM INCOME UNDER GENERAL INSURANCE BUSINESS FOR THE PERIOD ENDED 31.03.2026
B31: APPENDIX 19 | C31: =_xlfn.CONCAT("SUMMARY OF GENERAL INSURANCE BUSINESS MARKET SHARE PER CLASS FOR THE PERIOD ENDED"," ",Details!$F$18) -> SUMMARY OF GENERAL INSURANCE BUSINESS MARKET SHARE PER CLASS FOR THE PERIOD ENDED 31.03.2026
B32: APPENDIX 20 | C32: =_xlfn.CONCAT("SUMMARY OF CLAIMS PAID UNDER GENERAL INSURANCE BUSINESS FOR THE PERIOD ENDED"," ",Details!$F$18) -> SUMMARY OF CLAIMS PAID UNDER GENERAL INSURANCE BUSINESS FOR THE PERIOD ENDED 31.03.2026
B33: APPENDIX 21 | C33: =_xlfn.CONCAT("SUMMARY OF CLAIMS INCURRED UNDER GENERAL INSURANCE BUSINESS FOR THE PERIOD ENDED"," ",Details!$F$18) -> SUMMARY OF CLAIMS INCURRED UNDER GENERAL INSURANCE BUSINESS FOR THE PERIOD ENDED 31.03.2026
B34: APPENDIX 22 | C34: =_xlfn.CONCAT("SUMMARY OF INCURRED CLAIMS RATIOS UNDER GENERAL INSURANCE BUSINESS FOR THE PERIOD ENDED"," ",Details!$F$18) -> SUMMARY OF INCURRED CLAIMS RATIOS UNDER GENERAL INSURANCE BUSINESS FOR THE PERIOD ENDED 31.03.2026
B35: APPENDIX 23 | C35: =_xlfn.CONCAT("SUMMARY OF GENERAL INSURANCE BUSINESS REVENUE ACCOUNTS FOR THE PERIOD ENDED"," ",Details!$F$18) -> SUMMARY OF GENERAL INSURANCE BUSINESS REVENUE ACCOUNTS FOR THE PERIOD ENDED 31.03.2026
B36: APPENDIX 24 | C36: =_xlfn.CONCAT("SUMMARY OF BUSINESS RESULTS UNDER MICRO INSURANCE BUSINESS FOR THE PERIOD ENDED"," ",Details!$F$18) -> SUMMARY OF BUSINESS RESULTS UNDER MICRO INSURANCE BUSINESS FOR THE PERIOD ENDED 31.03.2026
B37: APPENDIX 25 | C37: =_xlfn.CONCAT("SUMMARY OF MICROINSURANCE BUSINESS REVENUE ACCOUNTS FOR THE PERIOD ENDED"," ",Details!$F$18) -> SUMMARY OF MICROINSURANCE BUSINESS REVENUE ACCOUNTS FOR THE PERIOD ENDED 31.03.2026

Sheet APPENDIX 1
B3: =_xlfn.CONCAT('Table of Contents'!B8,": ",'Table of Contents'!C8) -> APPENDIX 1: SUMMARY OF GENERAL INSURANCE BUSINESS PROFIT & LOSS ACCOUNTS FOR THE PERIOD ENDED 31.03.2026
B4: Company | C4: Insurance Revenue | D4: Insurance Service Expense | E4: Expenses from reinsurance contracts held | F4: Income from reinsurance contracts held | G4: Net expenses from reinsurance contracts held | H4: Insurance Service Result | I4: Net Investment Income | J4: Finance expenses from insurance contracts | K4: Finance income from reinsurance contracts | L4: Net Financial Result | M4: Asset management services revenue | N4: Other Income | O4: Other finance costs | P4: Other operating expenses | Q4: Share of profit of associates and joint ventures accounted for using the equity method | R4: Profit before income tax | S4: Income tax expense | T4: Profit for the year
B5: INSURERS
B6: AAR INSURANCE KENYA | C6: 3202261.9 | D6: 3036621.4 | E6: 22124.191 | F6: 0 | G6: 22124.191 | H6: 143516.31 | I6: 208160.32 | J6: 0 | K6: 0 | L6: 208160.32 | M6: 0 | N6: 4445.5469 | O6: 3353.5401 | P6: 167211.99 | Q6: 0 | R6: 185556.65 | S6: 46389.163 | T6: 139167.49
B7: AFRICAN MERCHANT ASSURANCE | C7: 800487.62 | D7: 634518.85 | E7: 49863.665 | F7: 151240.22 | G7: -101376.56 | H7: 267345.33 | I7: 45789.717 | J7: 56125.077 | K7: 4890.452 | L7: -5444.9081 | M7: 0 | N7: 0 | O7: 0 | P7: 249033.18 | Q7: 0 | R7: 12867.24 | S7: 0 | T7: 12867.24
B8: APA INSURANCE LIMITED | C8: 4549400.7 | D8: 5603433.7 | E8: -1209741.1 | F8: -341775.45 | G8: -867965.68 | H8: -186067.34 | I8: 601951.92 | J8: 174821.07 | K8: 66016.795 | L8: 493147.64 | M8: 0 | N8: 0 | O8: 5446.5043 | P8: 107884.24 | Q8: 0 | R8: 193749.55 | S8: -84898.094 | T8: 278647.65
B9: BRITAM GENERAL INSURANCE | C9: 3458627.1 | D9: 2756486.5 | E9: 623981.57 | F9: 133911.1 | G9: 490070.47 | H9: 212070.06 | I9: 630122.89 | J9: 434200.69 | K9: 123941.82 | L9: 319864.02 | M9: 0 | N9: 24648.583 | O9: 8211.5912 | P9: 80187.757 | Q9: 0 | R9: 468183.31 | S9: -53.131 | T9: 468236.44
B10: BUPA GLOBAL INSURANCE | C10: 1696347.5 | D10: 1262355.5 | E10: 1027449.5 | F10: 789973.98 | G10: 237475.49 | H10: 196516.45 | I10: 17855.662 | J10: 7634.503 | K10: 6135.509 | L10: 16356.668 | M10: 0 | N10: 0 | O10: 1065.637 | P10: 0 | Q10: 0 | R10: 211807.48 | S10: -1446.204 | T10: 213253.68
B11: CANNON GENERAL INSURANCE | C11: 660128.23 | D11: 501286.28 | E11: 151778.36 | F11: 0 | G11: 151778.36 | H11: 7063.5919 | I11: 23555.661 | J11: 137409.28 | K11: 74194.313 | L11: -39659.311 | M11: 0 | N11: 0 | O11: 0 | P11: 44798.478 | Q11: 0 | R11: -77394.196 | S11: 0 | T11: -77394.196
B12: CIC GENERAL INSURANCE COMPANY | C12: 5156201.8 | D12: 4291089.8 | E12: 0 | F12: -683136.81 | G12: 683136.81 | H12: 181975.16 | I12: 288836.17 | J12: 159414.61 | K12: 38852.052 | L12: 168273.61 | M12: 0 | N12: 89023.816 | O12: 0 | P12: 204312.95 | Q12: 0 | R12: 234959.64 | S12: 70487.893 | T12: 164471.75
B13: DEFINITE ASSURANCE COMPANY | C13: 0 | D13: 0 | E13: 0 | F13: 0 | G13: 0 | H13: 0 | I13: 0 | J13: 0 | K13: 0 | L13: 0 | M13: 0 | N13: 0 | O13: 0 | P13: 0 | Q13: 0 | R13: 0 | S13: 0 | T13: 0
B14: DIRECTLINE ASSURANCE COMPANY | C14: 763980.07 | D14: 667574.48 | E14: 15464.006 | F14: 0 | G14: 15464.006 | H14: 80941.586 | I14: 62690.069 | J14: 572751.86 | K14: 0 | L14: -510061.79 | M14: 0 | N14: 0 | O14: 0 | P14: 5467.809 | Q14: 0 | R14: -434588.02 | S14: 0 | T14: -434588.02
B15: EQUITY GENERAL INSURANCE LIMITED | C15: 245871.04 | D15: 142223.61 | E15: 163325.55 | F15: 114027.21 | G15: 49298.345 | H15: 54349.09 | I15: 36411.339 | J15: 0 | K15: 0 | L15: 36411.339 | M15: 0 | N15: 0 | O15: 0 | P15: 26360.481 | Q15: 0 | R15: 64399.947 | S15: 19319.984 | T15: 45079.963
B16: EQUITY HEALTH INSURANCE LIMITED | C16: 297359.2 | D16: 288381.46 | E16: 2690.6589 | F16: 0 | G16: 2690.6589 | H16: 6287.0782 | I16: 34895.824 | J16: 0 | K16: 0 | L16: 34895.824 | M16: 0 | N16: 0 | O16: 0 | P16: 24558.183 | Q16: 0 | R16: 16624.72 | S16: 4987.4159 | T16: 11637.304
B17: FIDELITY SHIELD INSURANCE | C17: 1285985.4 | D17: 1126437.5 | E17: 161995.9 | F17: 0 | G17: 161995.9 | H17: -2448.0109 | I17: 141318.66 | J17: 20033.672 | K17: 4549.7516 | L17: 125834.74 | M17: 0 | N17: 25956.051 | O17: 0 | P17: 73968.99 | Q17: 0 | R17: 75373.79 | S17: 0 | T17: 75373.79
... B40: THE MONARCH INSURANCE | C40: 0 | D40: 0 | E40: 0 | F40: 0 | G40: 0 | H40: 0 | I40: 0 | J40: 0 | K40: 0 | L40: 0 | M40: 0 | N40: 0 | O40: 0 | P40: 0 | Q40: 0 | R40: 0 | S40: 0 | T40: 0
B41: TOTAL | C41: =SUM(C6:C40) -> 55312561 | D41: =SUM(D6:D40) -> 55655013 | E41: =SUM(E6:E40) -> 5542954.9 | F41: =SUM(F6:F40) -> 6660814.6 | G41: =SUM(G6:G40) -> -1117859.6 | H41: =SUM(H6:H40) -> 775406.89 | I41: =SUM(I6:I40) -> 5174267.4 | J41: =SUM(J6:J40) -> 2837120.4 | ... T41: =SUM(T6:T40) -> 1269468.6
B42: REINSURERS
B43: CONTINENTAL REINSURANCE | C43: 1609409.6 | D43: 1630625.6 | E43: 229289.21 | F43: 395160.31 | G43: -165871.11 | H43: 144655.18 | I43: 59311.322 | J43: 136532.3 | K43: 61954.964 | L43: -15266.015 | M43: 0 | N43: 138.32 | O43: -12104.573 | P43: 9273.035 | Q43: 0 | R43: 132359.03 | S43: 39707.708 | T43: 92651.318
B44: EAST AFRICA REINSURANCE | C44: 1680189.9 | D44: 1482152.9 | E44: 184270.39 | F44: 49360.343 | G44: 134910.05 | H44: 63127.005 | I44: 180013.09 | J44: 30363.298 | K44: 6433.3212 | L44: 156083.11 | M44: 0 | N44: 9489.1519 | O44: 0 | P44: 0 | Q44: 0 | R44: 228699.27 | S44: 57174.817 | T44: 171524.45
B45: GHANA REINSURANCE COMPANY | C45: 645671.68 | D45: 826825.91 | E45: -327932.36 | F45: 0 | G45: -327932.36 | H45: 146778.13 | I45: 53070.601 | J45: 56920.005 | K45: 12649.018 | L45: 8799.6136 | M45: 0 | N45: 32 | O45: -5871.9968 | P45: 24890.213 | Q45: 0 | R45: 136591.53 | S45: 43656.054 | T45: 92935.474
B46: KENYA REINSURANCE CORPORATION | C46: 3266279.4 | D46: 2563104 | E46: 324183.65 | F46: 68356.203 | G46: 255827.45 | H46: 447347.89 | I46: 1014402.3 | J46: 78130.209 | K46: 4806.0969 | L46: 941078.18 | M46: 0 | N46: 14552.346 | O46: -78884.316 | P46: 283582.87 | Q46: 0 | R46: 1198279.9 | S46: 359459.42 | T46: 838820.44
B47: WAICA REINSURANCE KENYA LIMITED | C47: 992776.51 | D47: 685386.9 | E47: 144903.12 | F47: 161262.72 | G47: -16359.594 | H47: 323749.21 | I47: 82495.79 | J47: 98074.797 | K47: 10957.348 | L47: -4621.6594 | M47: 0 | N47: 46.548 | O47: -27064.498 | P47: 102575.24 | Q47: 0 | R47: 243663.36 | S47: 73099.008 | T47: 170564.35
B48: TOTAL | C48: =SUM(C43:C47) -> 8194327.1 | D48: =SUM(D43:D47) -> 7188095.3 | E48: =SUM(E43:E47) -> 554714.01 | F48: =SUM(F43:F47) -> 674139.58 | G48: =SUM(G43:G47) -> -119425.57 | H48: =SUM(H43:H47) -> 1125657.4 | I48: =SUM(I43:I47) -> 1389293.1 | J48: =SUM(J43:J47) -> 400020.61 | ... T48: =SUM(T43:T47) -> 1366496
B49: GRAND TOTAL | C49: =C41+C48 -> 63506888 | D49: =D41+D48 -> 62843109 | E49: =E41+E48 -> 6097669 | F49: =F41+F48 -> 7334954.1 | G49: =G41+G48 -> -1237285.2 | H49: =H41+H48 -> 1901064.3 | I49: =I41+I48 -> 6563560.5 | J49: =J41+J48 -> 3237141 | ... T49: =T41+T48 -> 2635964.6
B50: Amounts in Thousand Shillings

Sheet APPENDIX 2
B3: =_xlfn.CONCAT('Table of Contents'!B9,": ",'Table of Contents'!C9) -> APPENDIX 2: SUMMARY OF LONG TERM INSURANCE BUSINESS PROFIT & LOSS ACCOUNTS FOR THE PERIOD ENDED 31.03.2026
B4: Company | C4: Insurance Revenue | D4: Insurance Service Expense | E4: Finance expenses from insurance contracts | F4: Finance income from reinsurance contracts | G4: Net expenses from reinsurance contracts held | H4: Insurance Service Result | I4: Net Investment Income | J4: Finance expenses from insurance contracts | K4: Finance income from reinsurance contracts | L4: Net Financial Result | M4: Asset management services revenue | N4: Other Income | O4: Other finance costs | P4: Other operating expenses | Q4: Share of profit of associates and joint ventures accounted for using the equity method | R4: Profit before income tax | S4: Income tax expense | T4: Profit for the year
B5: INSURERS
B6: ABSA LIFE ASSURANCE | C6: 2452929 | D6: 2386849 | E6: 76105.12 | F6: 0 | G6: 76105.12 | H6: -10025.137 | I6: 1061506.7 | J6: 937033.31 | K6: 14233.555 | L6: 138706.94 | M6: 0 | N6: 4139.5 | O6: 0 | P6: 73584.076 | Q6: 0 | R6: 59237.228 | S6: 0 | T6: 59237.228
B7: APA LIFE ASSURANCE COMPANY | C7: 1297258.5 | D7: 1049350 | E7: 138992.1 | F7: 0 | G7: 138992.1 | H7: 108916.44 | I7: 1227885.2 | J7: 1028908.9 | K7: 9246.9951 | L7: 208223.36 | M7: 0 | N7: 0 | O7: 0 | P7: 0 | Q7: 0 | R7: 317139.79 | S7: -3440.4889 | T7: 320580.28
B8: BRITAM LIFE ASSURANCE | C8: 3983747.4 | D8: 3305577.7 | E8: -429143.74 | F8: -805082.21 | G8: 375938.47 | H8: 302231.23 | I8: 8980422.6 | J8: 8387009.2 | K8: 57690.59 | L8: 651103.98 | M8: 0 | N8: 3860.959 | O8: 6994.439 | P8: 176281.15 | Q8: 227237.74 | R8: 1001158.3 | S8: 300347.5 | T8: 700810.83
B9: CANNON LIFE ASSURANCE (K) LIMITED | C9: 116599.69 | D9: 153244.89 | E9: 3001.2428 | F9: 0 | G9: 3001.2428 | H9: -39646.441 | I9: 25550.816 | J9: 18525.173 | K9: 50.498751 | L9: 7076.1416 | M9: 0 | N9: 3608.05 | O9: 0 | P9: 1246.8328 | Q9: 0 | R9: -30209.082 | S9: 1628.8964 | T9: -31837.979
B10: CAPEX LIFE ASSURANCE COMPANY | C10: 498694.04 | D10: 478312.69 | E10: 29157.292 | F10: 46481.674 | G10: -17324.382 | H10: 37705.731 | I10: 1351.796 | J10: 15968.959 | K10: 3303.644 | L10: -11313.519 | M10: 0 | N10: 0 | O10: 0 | P10: 5234.486 | Q10: 0 | R10: 21157.726 | S10: 511.705 | T10: 20646.021
B11: CIC LIFE ASSURANCE COMPANY | C11: 1977934.7 | D11: 2053019.4 | E11: 410996.8 | F11: 372456.1 | G11: 38540.7 | H11: -113625.33 | I11: 1514414.9 | J11: 1259479.1 | K11: 25110.505 | L11: 280046.24 | M11: 0 | N11: 42838.783 | O11: 0 | P11: 85507.804 | Q11: 0 | R11: 123751.88 | S11: 0 | T11: 123751.88
B12: EQUITY LIFE ASSURANCE | C12: 619030.47 | D12: 474505.31 | E12: 189613.11 | F12: 230345.32 | G12: -40732.201 | H12: 185257.37 | I12: 983317.98 | J12: 558203.87 | K12: 592.8039 | L12: 425706.92 | M12: 0 | N12: 42083.237 | O12: 0 | P12: 92535.099 | Q12: 0 | R12: 560512.42 | S12: 168153.73 | T12: 392358.69
B13: GA LIFE ASSURANCE COMPANY | C13: 20607.22 | D13: 12342.797 | E13: 10826.751 | F13: 0 | G13: 10826.751 | H13: -2562.3275 | I13: 2136112.6 | J13: 0 | K13: 0 | L13: 2136112.6 | M13: 0 | N13: 311690.45 | O13: 0 | P13: 86299.013 | Q13: 0 | R13: 2358941.7 | S13: 4665.926 | T13: 2354275.7
B14: GEMINIA LIFE INSURANCE COMPANY | C14: 214047.7 | D14: 27952.135 | E14: 36704.587 | F14: 0 | G14: 36704.587 | H14: 149390.98 | I14: 66708.844 | J14: 26329.25 | K14: 0 | L14: 40379.594 | M14: 0 | N14: 0 | O14: 0 | P14: 92796.78 | Q14: 0 | R14: 96973.794 | S14: 5.8267581 | T14: 96967.967
B15: ICEA LION LIFE ASSURANCE | C15: 2264310.3 | D15: 1541593.3 | E15: 107630.24 | F15: 7810.3228 | G15: 99819.914 | H15: 622897.15 | I15: 8685851 | J15: 8183802.4 | K15: 0 | L15: 502048.64 | M15: 0 | N15: 26092.754 | O15: 0 | P15: 101556.57 | Q15: 0 | R15: 1049482 | S15: 314844.72 | T15: 734637.26
B16: JUBILEE LIFE INSURANCE | C16: 1992524.2 | D16: 941163.24 | E16: 203771.76 | F16: 0 | G16: 203771.76 | H16: 847589.24 | I16: 7007526.5 | J16: 6766128 | K16: 0 | L16: 241398.56 | M16: 0 | N16: 0 | O16: 0 | P16: 259127.64 | Q16: 0 | R16: 829860.16 | S16: 0 | T16: 829860.16
B17: KENINDIA ASSURANCE COMPANY | C17: 524489.98 | D17: 505801.43 | E17: 23148.927 | F17: -2709.6587 | G17: 25858.586 | H17: -7170.0395 | I17: 3854466 | J17: 3269396.2 | K17: 0 | L17: 585069.81 | M17: 0 | N17: 0 | O17: 0 | P17: 0 | Q17: 0 | R17: 577899.77 | S17: 0 | T17: 577899.77
... B27: THE MONARCH INSURANCE | C27: 0 | D27: 0 | E27: 0 | F27: 0 | G27: 0 | H27: 0 | I27: 0 | J27: 0 | K27: 0 | L27: 0 | M27: 0 | N27: 0 | O27: 0 | P27: 0 | Q27: 0 | R27: 0 | S27: 0 | T27: 0
B28: TOTAL | C28: =SUM(C6:C27) -> 20886057 | D28: =SUM(D6:D27) -> 17527998 | E28: =SUM(E6:E27) -> 1138620.4 | F28: =SUM(F6:F27) -> -29075.259 | G28: =SUM(G6:G27) -> 1167695.6 | H28: =SUM(H6:H27) -> 2190362.9 | I28: =SUM(I6:I27) -> 39964430 | J28: =SUM(J6:J27) -> 35464493 | ... T28: =SUM(T6:T27) -> 5745304.1
B29: REINSURERS
B30: CONTINENTAL REINSURANCE | C30: 0 | D30: 0 | E30: 0 | F30: 0 | G30: 0 | H30: 0 | I30: 0 | J30: 0 | K30: 0 | L30: 0 | M30: 0 | N30: 0 | O30: 0 | P30: 0 | Q30: 0 | R30: 0 | S30: 0 | T30: 0
B31: EAST AFRICA REINSURANCE | C31: 256732.76 | D31: 217185.15 | E31: 33019.025 | F31: 35505.969 | G31: -2486.9439 | H31: 42034.55 | I31: 67687.47 | J31: 6005.3906 | K31: 977.10648 | L31: 62659.186 | M31: 0 | N31: 2186.8106 | O31: 0 | P31: 0 | Q31: 0 | R31: 106880.55 | S31: -32465.739 | T31: 74414.807
B32: KENYA REINSURANCE CORPORATION | C32: 631050.78 | D32: 783326.62 | E32: 0 | F32: 0 | G32: 24284.519 | H32: -176560.36 | I32: 243322.29 | J32: -17099.385 | K32: -246.54125 | L32: 260175.13 | M32: 0 | N32: 0 | O32: -0.55550396 | P32: 17511.4 | Q32: 0 | R32: 66103.927 | S32: 19831.178 | T32: 46272.749
B33: TOTAL | C33: =SUM(C30:C32) -> 887783.53 | D33: =SUM(D30:D32) -> 1000511.8 | E33: =SUM(E30:E32) -> 33019.025 | F33: =SUM(F30:F32) -> 35505.969 | G33: =SUM(G30:G32) -> 21797.576 | H33: =SUM(H30:H32) -> -134525.81 | I33: =SUM(I30:I32) -> 311009.76 | J33: =SUM(J30:J32) -> -11093.994 | ... T33: =SUM(T30:T32) -> 120687.56
B34: GRAND TOTAL | C34: =C33+C28 -> 21773840 | D34: =D33+D28 -> 18528510 | E34: =E33+E28 -> 1171639.4 | F34: =F33+F28 -> 6430.71 | G34: =G33+G28 -> 1189493.2 | H34: =H33+H28 -> 2055837.1 | I34: =I33+I28 -> 40275440 | J34: =J33+J28 -> 35453399 | ... T34: =T33+T28 -> 5865991.7
B35: Amounts in Thousand Shillings

Sheet APPENDIX 3
B3: =_xlfn.CONCAT('Table of Contents'!B10,": ",'Table of Contents'!C10) -> APPENDIX 3: SUMMARY OF MICRO INSURANCE BUSINESS PROFIT & LOSS ACCOUNTS FOR THE PERIOD ENDED 31.03.2026
B4: Company | C4: Insurance Revenue | D4: Insurance Service Expense | E4: Finance expenses from insurance contracts | F4: Finance income from reinsurance contracts | G4: Net expenses from reinsurance contracts held | H4: Insurance Service Result | I4: Net Investment Income | J4: Finance expenses from insurance contracts | K4: Finance income from reinsurance contracts | L4: Net Financial Result | M4: Asset management services revenue | N4: Other Income | O4: Other finance costs | P4: Other operating expenses | Q4: Share of profit of associates and joint ventures accounted for using the equity method | R4: Profit before income tax | S4: Income tax expense | T4: Profit for the year
B5: INSURERS
B6: APA MICRO INSURANCE | C6: 0 | D6: 0 | E6: 0 | F6: 0 | G6: 0 | H6: 0 | I6: 2181.524 | J6: 0 | K6: 0 | L6: 2181.524 | M6: 0 | N6: 0 | O6: 0 | P6: 0 | Q6: 0 | R6: 2181.524 | S6: 0 | T6: 2181.524
B7: BIRDVIEW MICRO INSURANCE | C7: 0 | D7: 0 | E7: 0 | F7: 0 | G7: 0 | H7: 0 | I7: 0 | J7: 0 | K7: 0 | L7: 0 | M7: 0 | N7: 0 | O7: 0 | P7: 0 | Q7: 0 | R7: 0 | S7: 0 | T7: 0
B8: BRITAM MICRO INSURANCE | C8: 367803.3 | D8: 341934.26 | E8: 26271.107 | F8: 12466.498 | G8: 13804.609 | H8: 12064.43 | I8: 29295.682 | J8: 11603.812 | K8: -259.75681 | L8: 17432.113 | M8: 0 | N8: 1882.022 | O8: 1244.4324 | P8: 14535.733 | Q8: 0 | R8: 15598.399 | S8: 0 | T8: 15598.399
B9: CIC MICRO INSURANCE | C9: 5704.9331 | D9: 16557.839 | E9: 0 | F9: 0 | G9: 0 | H9: -10852.906 | I9: 935.08493 | J9: 0 | K9: 0 | L9: 935.08493 | M9: 0 | N9: 0 | O9: 0 | P9: 5773.6347 | Q9: 0 | R9: -15691.456 | S9: 0 | T9: -15691.456
B10: STAR DISCOVER MICRO INSURANCE | C10: 0 | D10: 0 | E10: 0 | F10: 0 | G10: 0 | H10: 0 | I10: 0 | J10: 0 | K10: 0 | L10: 0 | M10: 0 | N10: 0 | O10: 0 | P10: 0 | Q10: 0 | R10: 0 | S10: 0 | T10: 0
B11: TURACO MICRO INSURANCE | C11: 132624.78 | D11: 74251.727 | E11: 0 | F11: 0 | G11: 0 | H11: 58373.054 | I11: 3207.863 | J11: 0 | K11: 0 | L11: 3207.863 | M11: 0 | N11: 0 | O11: 0 | P11: 15197.956 | Q11: 0 | R11: 46382.961 | S11: 13644.849 | T11: 32738.111
B12: TOTAL | C12: =SUM(C6:C11) -> 506133.01 | D12: =SUM(D6:D11) -> 432743.82 | E12: =SUM(E6:E11) -> 26271.107 | F12: =SUM(F6:F11) -> 12466.498 | G12: =SUM(G6:G11) -> 13804.609 | H12: =SUM(H6:H11) -> 59584.578 | I12: =SUM(I6:I11) -> 35620.154 | J12: =SUM(J6:J11) -> 11603.812 | ... T12: =SUM(T6:T11) -> 34826.579
B13: Amounts in Thousand Shillings

Sheet APPENDIX 4 i
B4: =_xlfn.CONCAT('Table of Contents'!B11,": ",'Table of Contents'!C11) -> APPENDIX 4 i: SUMMARY OF LONG TERM INSURANCE BUSINESS BALANCE SHEETS AS AT 31.03.2026
B5: Company | C5: ABSA LIFE ASSURANCE | D5: APA LIFE ASSURANCE COMPANY | E5: BRITAM LIFE ASSURANCE | F5: CANNON LIFE ASSURANCE (K) LIMITED | G5: CAPEX LIFE ASSURANCE COMPANY | H5: CIC LIFE ASSURANCE COMPANY | I5: CONTINENTAL REINSURANCE | J5: EAST AFRICA REINSURANCE | K5: EQUITY LIFE ASSURANCE
B6: Share Capital | C6: 699000 | D6: 1100000 | E6: 1200000 | F6: 416725.77 | G6: 400000 | H6: 800000 | I6: 0 | J6: 500000 | K6: 420000
B7: Share Premium_x000D_ | C7: 0 | D7: 0 | E7: 0 | F7: 491067.65 | G7: 0 | H7: 0 | I7: 0 | J7: 0 | K7: 180000
B8: Revaluation Reserves | C8: 0 | D8: 0 | E8: 0 | F8: 2500 | G8: 2072.909 | H8: 0 | I8: 0 | J8: 0 | K8: 0
B9: Statutory Reserves | C9: 1011470.8 | D9: 127630.99 | E9: 18590906 | F9: 0 | G9: 0 | H9: 2255766.2 | I9: 0 | J9: 0 | K9: 0
B10: Other Equity | C10: 1000000 | D10: 0 | E10: 0 | F10: 405066.13 | G10: 0 | H10: 911550.06 | I10: 0 | J10: 0 | K10: 0
B11: Retained Earnings | C11: -940992.74 | D11: 714860.81 | E11: 75000 | F11: -1281726.8 | G11: 309039.36 | H11: 123751.88 | I11: 0 | J11: 1401742.9 | K11: 3835946.4
B12: Other Reserves | C12: 0 | D12: 76549.767 | E12: 1.1920929e-10 | F12: 518154.63 | G12: 1120.164 | H12: 0 | I12: 0 | J12: 0 | K12: 2244635.9
B13: Total Equity_x000D_ | C13: 1769478.1 | D13: 2019041.6 | E13: 19865906 | F13: 551787.36 | G13: 712232.43 | H13: 4091068.1 | I13: 0 | J13: 1901742.9 | K13: 6680582.3
B14: Investment Contract Liabilites | C14: 0 | D14: 292125.61 | E14: 0 | F14: 0 | G14: 68155.135 | H14: 95079.348 | I14: 0 | J14: 0 | K14: 0
B15: Insurance Contract Liabilites | C15: 21599497 | D15: 31326467 | E15: 1.9110872e+08 | F15: 847020.05 | G15: 1409826.4 | H15: 41099195 | I15: 0 | J15: 847712.04 | K15: 26601226
B16: Reinsurance Contract Liabilites | C16: 0 | D16: 17405.565 | E16: 1665.75 | F16: 0 | G16: 26175.576 | H16: 0 | I16: 0 | J16: 80953.52 | K16: 0
B17: Long-Term Liabilites | C17: 0 | D17: 0 | E17: 0 | F17: 0 | G17: 0 | H17: 0 | I17: 0 | J17: 0 | K17: 0
... B45: Total Assets | C45: 24782186 | D45: 34457598 | E45: 2.2074457e+08 | F45: 1808467.2 | G45: 2322706.9 | H45: 47974057 | I45: 0 | J45: 3452233 | K45: 36540717
B46: Amounts in Thousand Shillings | J46: Continued next page

Sheet APPENDIX 4 ii
B3: Continued from previous page
B4: =_xlfn.CONCAT('Table of Contents'!B12,": ",'Table of Contents'!C12) -> APPENDIX 4 ii: SUMMARY OF LONG TERM INSURANCE BUSINESS BALANCE SHEETS AS AT 31.03.2026
B5: Company | C5: GA LIFE ASSURANCE COMPANY | D5: GEMINIA LIFE INSURANCE COMPANY | E5: ICEA LION LIFE ASSURANCE | F5: JUBILEE LIFE INSURANCE | G5: KENINDIA ASSURANCE COMPANY | H5: KENYA ORIENT LIFE ASSURANCE | I5: KENYA REINSURANCE CORPORATION | J5: LIBERTY LIFE ASSURANCE COMPANY | K5: MADISON INSURANCE COMPANY
B6: Share Capital | C6: 400000 | D6: 458093.68 | E6: 1125000 | F6: 500000 | G6: 900000 | H6: 313000 | I6: 500000 | J6: 742340 | K6: 450000
B7: Share Premium_x000D_ | C7: 0 | D7: 0 | E7: 1125000 | F7: 0 | G7: 1000000 | H7: 0 | I7: 0 | J7: 0 | K7: 0
B8: Revaluation Reserves | C8: 0 | D8: 0 | E8: 0 | F8: 0 | G8: 0 | H8: 0 | I8: 0 | J8: 384946.36 | K8: 19341
B9: Statutory Reserves | C9: 5472480.5 | D9: 388371.7 | E9: 18240363 | F9: 0 | G9: 2759237.2 | H9: 264952.49 | I9: 0 | J9: 2094358.5 | K9: -5333877
B10: Other Equity | C10: 0 | D10: 0 | E10: 1470000 | F10: 0 | G10: -514.885 | H10: 0 | I10: 0 | J10: 600000 | K10: 2050000
B11: Retained Earnings | C11: 338109.32 | D11: 277492.59 | E11: 3011861.5 | F11: 6716726.3 | G11: 2764516.8 | H11: 101354.33 | I11: 10808752 | J11: -304169.9 | K11: 62000
B12: Other Reserves | C12: 0 | D12: 0 | E12: 0 | F12: 5312333 | G12: 0 | H12: 0 | I12: 0 | J12: 0 | K12: 0
B13: Total Equity_x000D_ | C13: 6210589.8 | D13: 1123958 | E13: 24972224 | F13: 12529059 | G13: 7423239.2 | H13: 679306.82 | I13: 11308752 | J13: 3517475 | K13: -2752536
B14: Investment Contract Liabilites | C14: 55575689 | D14: 1532928.4 | E14: 0 | F14: 0 | G14: 0 | H14: 2179480.9 | I14: 0 | J14: 13131324 | K14: 0
B15: Insurance Contract Liabilites | C15: 42881.254 | D15: 1383986.9 | E15: 1.9630499e+08 | F15: 1.7637858e+08 | G15: 1.1139575e+08 | H15: 3214395.7 | I15: 2543031.4 | J15: 15234566 | K15: 23286039
B16: Reinsurance Contract Liabilites | C16: 0 | D16: 0 | E16: 0 | F16: 0 | G16: 35903.497 | H16: 0 | I16: 0 | J16: 0 | K16: 0
B17: Long-Term Liabilites | C17: 0 | D17: 0 | E17: 0 | F17: 0 | G17: 0 | H17: 0 | I17: 0 | J17: 0 | K17: 0
... B45: Total Assets | C45: 67259389 | D45: 4151135.3 | E45: 2.2834978e+08 | F45: 1.9351947e+08 | G45: 1.2129353e+08 | H45: 6284243.8 | I45: 13851783 | J45: 33816797 | K45: 21028844
B46: Amounts in Thousand Shillings | J46: Continued next page

Sheet APPENDIX 4 iii
B3: Continued from previous page
B4: =_xlfn.CONCAT('Table of Contents'!B13,": ",'Table of Contents'!C13) -> APPENDIX 4 iii: SUMMARY OF LONG TERM INSURANCE BUSINESS BALANCE SHEETS AS AT 31.03.2026 | Q4: Industry
B5: Company | C5: OLD MUTUAL LIFE ASSURANCE KENYA | D5: PIONEER ASSURANCE COMPANY | E5: PRUDENTIAL LIFE ASSURANCE | F5: SANLAM LIFE ASSURANCE | G5: STAR DISCOVER LIFE INSURANCE | H5: THE KENYAN ALLIANCE INSURANCE | I5: THE MONARCH INSURANCE | J5: TOTAL | N5: Insurers | O5: Reinsurers | Q5: Insurers | R5: Reinsurers | S5: Total
B6: Share Capital | C6: 2946667.4 | D6: 600000 | E6: 425698.08 | F6: 843138.54 | G6: 400000 | H6: 0 | I6: 0 | J6: 16139663 | N6: =SUMIFS('APPENDIX 4 iii'!$B6:$L6,'APPENDIX 4 iii'!$B$5:$L$5,"*total*")-O6 -> 15139663 | O6: =SUMIFS('APPENDIX 4 i'!$B6:$K6,'APPENDIX 4 i'!$B$5:$K$5,"*reinsurance*")+ SUMIFS('APPENDIX 4 ii'!$B6:$K6,'APPENDIX 4 ii'!$B$5:$K$5,"*reinsurance*")+ SUMIFS('APPENDIX 4 iii'!$B6:$K6,'APPENDIX 4 iii'!$B$5:$K$5,"*reinsurance*") -> 1000000 | Q6: =N6+_xlfn.XLOOKUP($B6,'APPENDIX 5 iv'!$B:$B,'APPENDIX 5 iv'!P:P,0,0)+_xlfn.XLOOKUP($B6,'APPENDIX 6'!$B:$B,'APPENDIX 6'!I:I,0,0) -> 50105680 | R6: =O6+_xlfn.XLOOKUP($B6,'APPENDIX 5 iv'!$B:$B,'APPENDIX 5 iv'!Q:Q,0,0)+_xlfn.XLOOKUP($B6,'APPENDIX 6'!$B:$B,'APPENDIX 6'!J:J,0,0) -> 19101531 | S6: =SUM(Q6:R6) -> 69207211
B7: Share Premium_x000D_ | C7: 1160475.7 | D7: 0 | E7: 3768621.6 | F7: 30260 | G7: 0 | H7: 0 | I7: 0 | J7: 7755424.9 | N7: =SUMIFS('APPENDIX 4 iii'!$B7:$L7,'APPENDIX 4 iii'!$B$5:$L$5,"*total*")-O7 -> 7755424.9 | O7: =SUMIFS('APPENDIX 4 i'!$B7:$K7,'APPENDIX 4 i'!$B$5:$K$5,"*reinsurance*")+ SUMIFS('APPENDIX 4 ii'!$B7:$K7,'APPENDIX 4 ii'!$B$5:$K$5,"*reinsurance*")+ SUMIFS('APPENDIX 4 iii'!$B7:$K7,'APPENDIX 4 iii'!$B$5:$K$5,"*reinsurance*") -> 0 | Q7: =N7+_xlfn.XLOOKUP($B7,'APPENDIX 5 iv'!$B:$B,'APPENDIX 5 iv'!P:P,0,0)+_xlfn.XLOOKUP($B7,'APPENDIX 6'!$B:$B,'APPENDIX 6'!I:I,0,0) -> 12016882 | R7: =O7+_xlfn.XLOOKUP($B7,'APPENDIX 5 iv'!$B:$B,'APPENDIX 5 iv'!Q:Q,0,0)+_xlfn.XLOOKUP($B7,'APPENDIX 6'!$B:$B,'APPENDIX 6'!J:J,0,0) -> 10871.242 | S7: =SUM(Q7:R7) -> 12027754
B8: Revaluation Reserves | C8: 0 | D8: 0 | E8: 0 | F8: 0 | G8: 0 | H8: 0 | I8: 0 | J8: 408860.27 | N8: =SUMIFS('APPENDIX 4 iii'!$B8:$L8,'APPENDIX 4 iii'!$B$5:$L$5,"*total*")-O8 -> 408860.27 | O8: =SUMIFS('APPENDIX 4 i'!$B8:$K8,'APPENDIX 4 i'!$B$5:$K$5,"*reinsurance*")+ SUMIFS('APPENDIX 4 ii'!$B8:$K8,'APPENDIX 4 ii'!$B$5:$K$5,"*reinsurance*")+ SUMIFS('APPENDIX 4 iii'!$B8:$K8,'APPENDIX 4 iii'!$B$5:$K$5,"*reinsurance*") -> 0 | Q8: =N8+_xlfn.XLOOKUP($B8,'APPENDIX 5 iv'!$B:$B,'APPENDIX 5 iv'!P:P,0,0)+_xlfn.XLOOKUP($B8,'APPENDIX 6'!$B:$B,'APPENDIX 6'!I:I,0,0) -> 2960333.5 | R8: =O8+_xlfn.XLOOKUP($B8,'APPENDIX 5 iv'!$B:$B,'APPENDIX 5 iv'!Q:Q,0,0)+_xlfn.XLOOKUP($B8,'APPENDIX 6'!$B:$B,'APPENDIX 6'!J:J,0,0) -> 237108.49 | S8: =SUM(Q8:R8) -> 3197442
B9: Statutory Reserves | C9: -298557.7 | D9: 312202.03 | E9: 0 | F9: 3344067.6 | G9: 0 | H9: 0 | I9: 0 | J9: 49229372 | N9: =SUMIFS('APPENDIX 4 iii'!$B9:$L9,'APPENDIX 4 iii'!$B$5:$L$5,"*total*")-O9 -> 49229372 | O9: =SUMIFS('APPENDIX 4 i'!$B9:$K9,'APPENDIX 4 i'!$B$5:$K$5,"*reinsurance*")+ SUMIFS('APPENDIX 4 ii'!$B9:$K9,'APPENDIX 4 ii'!$B$5:$K$5,"*reinsurance*")+ SUMIFS('APPENDIX 4 iii'!$B9:$K9,'APPENDIX 4 iii'!$B$5:$K$5,"*reinsurance*") -> 0 | Q9: =N9+_xlfn.XLOOKUP($B9,'APPENDIX 5 iv'!$B:$B,'APPENDIX 5 iv'!P:P,0,0)+_xlfn.XLOOKUP($B9,'APPENDIX 6'!$B:$B,'APPENDIX 6'!I:I,0,0) -> 49229372 | R9: =O9+_xlfn.XLOOKUP($B9,'APPENDIX 5 iv'!$B:$B,'APPENDIX 5 iv'!Q:Q,0,0)+_xlfn.XLOOKUP($B9,'APPENDIX 6'!$B:$B,'APPENDIX 6'!J:J,0,0) -> 0 | S9: =SUM(Q9:R9) -> 49229372
B10: Other Equity | C10: 0 | D10: 0 | E10: 0 | F10: 0 | G10: 0 | H10: 0 | I10: 0 | J10: 6436101.3 | N10: =SUMIFS('APPENDIX 4 iii'!$B10:$L10,'APPENDIX 4 iii'!$B$5:$L$5,"*total*")-O10 -> 6436101.3 | O10: =SUMIFS('APPENDIX 4 i'!$B10:$K10,'APPENDIX 4 i'!$B$5:$K$5,"*reinsurance*")+ SUMIFS('APPENDIX 4 ii'!$B10:$K10,'APPENDIX 4 ii'!$B$5:$K$5,"*reinsurance*")+ SUMIFS('APPENDIX 4 iii'!$B10:$K10,'APPENDIX 4 iii'!$B$5:$K$5,"*reinsurance*") -> 0 | Q10: =N10+_xlfn.XLOOKUP($B10,'APPENDIX 5 iv'!$B:$B,'APPENDIX 5 iv'!P:P,0,0)+_xlfn.XLOOKUP($B10,'APPENDIX 6'!$B:$B,'APPENDIX 6'!I:I,0,0) -> 11981909 | R10: =O10+_xlfn.XLOOKUP($B10,'APPENDIX 5 iv'!$B:$B,'APPENDIX 5 iv'!Q:Q,0,0)+_xlfn.XLOOKUP($B10,'APPENDIX 6'!$B:$B,'APPENDIX 6'!J:J,0,0) -> 1314112.1 | S10: =SUM(Q10:R10) -> 13296021
B11: Retained Earnings | C11: 118180.75 | D11: 257545.71 | E11: -3516609.7 | F11: 235067.35 | G11: 363638.96 | H11: 0 | I11: 0 | J11: 25472088 | N11: =SUMIFS('APPENDIX 4 iii'!$B11:$L11,'APPENDIX 4 iii'!$B$5:$L$5,"*total*")-O11 -> 13261593 | O11: =SUMIFS('APPENDIX 4 i'!$B11:$K11,'APPENDIX 4 i'!$B$5:$K$5,"*reinsurance*")+ SUMIFS('APPENDIX 4 ii'!$B11:$K11,'APPENDIX 4 ii'!$B$5:$K$5,"*reinsurance*")+ SUMIFS('APPENDIX 4 iii'!$B11:$K11,'APPENDIX 4 iii'!$B$5:$K$5,"*reinsurance*") -> 12210495 | Q11: =N11+_xlfn.XLOOKUP($B11,'APPENDIX 5 iv'!$B:$B,'APPENDIX 5 iv'!P:P,0,0)+_xlfn.XLOOKUP($B11,'APPENDIX 6'!$B:$B,'APPENDIX 6'!I:I,0,0) -> 58827892 | R11: =O11+_xlfn.XLOOKUP($B11,'APPENDIX 5 iv'!$B:$B,'APPENDIX 5 iv'!Q:Q,0,0)+_xlfn.XLOOKUP($B11,'APPENDIX 6'!$B:$B,'APPENDIX 6'!J:J,0,0) -> 49218054 | S11: =SUM(Q11:R11) -> 1.0804595e+08
B12: Other Reserves | C12: 27533.634 | D12: 0 | E12: 0 | F12: 0 | G12: 0 | H12: 0 | I12: 0 | J12: 8180327.1 | N12: =SUMIFS('APPENDIX 4 iii'!$B12:$L12,'APPENDIX 4 iii'!$B$5:$L$5,"*total*")-O12 -> 8180327.1 | O12: =SUMIFS('APPENDIX 4 i'!$B12:$K12,'APPENDIX 4 i'!$B$5:$K$5,"*reinsurance*")+ SUMIFS('APPENDIX 4 ii'!$B12:$K12,'APPENDIX 4 ii'!$B$5:$K$5,"*reinsurance*")+ SUMIFS('APPENDIX 4 iii'!$B12:$K12,'APPENDIX 4 iii'!$B$5:$K$5,"*reinsurance*") -> 0 | Q12: =N12+_xlfn.XLOOKUP($B12,'APPENDIX 5 iv'!$B:$B,'APPENDIX 5 iv'!P:P,0,0)+_xlfn.XLOOKUP($B12,'APPENDIX 6'!$B:$B,'APPENDIX 6'!I:I,0,0) -> 10749663 | R12: =O12+_xlfn.XLOOKUP($B12,'APPENDIX 5 iv'!$B:$B,'APPENDIX 5 iv'!Q:Q,0,0)+_xlfn.XLOOKUP($B12,'APPENDIX 6'!$B:$B,'APPENDIX 6'!J:J,0,0) -> 1593975.7 | S12: =SUM(Q12:R12) -> 12343639
B13: Total Equity_x000D_ | C13: 3954299.7 | D13: 1169747.7 | E13: 677709.98 | F13: 4452533.5 | G13: 763638.96 | H13: 0 | I13: 0 | J13: 1.1362184e+08 | N13: =SUMIFS('APPENDIX 4 iii'!$B13:$L13,'APPENDIX 4 iii'!$B$5:$L$5,"*total*")-O13 -> 1.0041134e+08 | O13: =SUMIFS('APPENDIX 4 i'!$B13:$K13,'APPENDIX 4 i'!$B$5:$K$5,"*reinsurance*")+ SUMIFS('APPENDIX 4 ii'!$B13:$K13,'APPENDIX 4 ii'!$B$5:$K$5,"*reinsurance*")+ SUMIFS('APPENDIX 4 iii'!$B13:$K13,'APPENDIX 4 iii'!$B$5:$K$5,"*reinsurance*") -> 13210495 | Q13: =N13+_xlfn.XLOOKUP($B13,'APPENDIX 5 iv'!$B:$B,'APPENDIX 5 iv'!P:P,0,0)+_xlfn.XLOOKUP($B13,'APPENDIX 6'!$B:$B,'APPENDIX 6'!I:I,0,0) -> 1.9587173e+08 | R13: =O13+_xlfn.XLOOKUP($B13,'APPENDIX 5 iv'!$B:$B,'APPENDIX 5 iv'!Q:Q,0,0)+_xlfn.XLOOKUP($B13,'APPENDIX 6'!$B:$B,'APPENDIX 6'!J:J,0,0) -> 71475653 | S13: =SUM(Q13:R13) -> 2.6734739e+08
B14: Investment Contract Liabilites | C14: 674175.28 | D14: 0 | E14: 0 | F14: 0 | G14: 0 | H14: 0 | I14: 0 | J14: 73548957 | N14: =SUMIFS('APPENDIX 4 iii'!$B14:$L14,'APPENDIX 4 iii'!$B$5:$L$5,"*total*")-O14 -> 73548957 | O14: =SUMIFS('APPENDIX 4 i'!$B14:$K14,'APPENDIX 4 i'!$B$5:$K$5,"*reinsurance*")+ SUMIFS('APPENDIX 4 ii'!$B14:$K14,'APPENDIX 4 ii'!$B$5:$K$5,"*reinsurance*")+ SUMIFS('APPENDIX 4 iii'!$B14:$K14,'APPENDIX 4 iii'!$B$5:$K$5,"*reinsurance*") -> 0 | Q14: =N14+_xlfn.XLOOKUP($B14,'APPENDIX 5 iv'!$B:$B,'APPENDIX 5 iv'!P:P,0,0)+_xlfn.XLOOKUP($B14,'APPENDIX 6'!$B:$B,'APPENDIX 6'!I:I,0,0) -> 73548957 | R14: =O14+_xlfn.XLOOKUP($B14,'APPENDIX 5 iv'!$B:$B,'APPENDIX 5 iv'!Q:Q,0,0)+_xlfn.XLOOKUP($B14,'APPENDIX 6'!$B:$B,'APPENDIX 6'!J:J,0,0) -> 0 | S14: =SUM(Q14:R14) -> 73548957
B15: Insurance Contract Liabilites | C15: 25409747 | D15: 20860906 | E15: 6669080 | F15: 33112743 | G15: 122394.48 | H15: 0 | I15: 0 | J15: 9.3079876e+08 | N15: =SUMIFS('APPENDIX 4 iii'!$B15:$L15,'APPENDIX 4 iii'!$B$5:$L$5,"*total*")-O15 -> 9.2740801e+08 | O15: =SUMIFS('APPENDIX 4 i'!$B15:$K15,'APPENDIX 4 i'!$B$5:$K$5,"*reinsurance*")+ SUMIFS('APPENDIX 4 ii'!$B15:$K15,'APPENDIX 4 ii'!$B$5:$K$5,"*reinsurance*")+ SUMIFS('APPENDIX 4 iii'!$B15:$K15,'APPENDIX 4 iii'!$B$5:$K$5,"*reinsurance*") -> 3390743.4 | Q15: =N15+_xlfn.XLOOKUP($B15,'APPENDIX 5 iv'!$B:$B,'APPENDIX 5 iv'!P:P,0,0)+_xlfn.XLOOKUP($B15,'APPENDIX 6'!$B:$B,'APPENDIX 6'!I:I,0,0) -> 1.144899e+09 | R15: =O15+_xlfn.XLOOKUP($B15,'APPENDIX 5 iv'!$B:$B,'APPENDIX 5 iv'!Q:Q,0,0)+_xlfn.XLOOKUP($B15,'APPENDIX 6'!$B:$B,'APPENDIX 6'!J:J,0,0) -> 35965653 | S15: =SUM(Q15:R15) -> 1.1808647e+09
B16: Reinsurance Contract Liabilites | C16: 0 | D16: 0 | E16: 0 | F16: 0 | G16: 0 | H16: 0 | I16: 0 | J16: 162103.91 | N16: =SUMIFS('APPENDIX 4 iii'!$B16:$L16,'APPENDIX 4 iii'!$B$5:$L$5,"*total*")-O16 -> 81150.389 | O16: =SUMIFS('APPENDIX 4 i'!$B16:$K16,'APPENDIX 4 i'!$B$5:$K$5,"*reinsurance*")+ SUMIFS('APPENDIX 4 ii'!$B16:$K16,'APPENDIX 4 ii'!$B$5:$K$5,"*reinsurance*")+ SUMIFS('APPENDIX 4 iii'!$B16:$K16,'APPENDIX 4 iii'!$B$5:$K$5,"*reinsurance*") -> 80953.52 | Q16: =N16+_xlfn.XLOOKUP($B16,'APPENDIX 5 iv'!$B:$B,'APPENDIX 5 iv'!P:P,0,0)+_xlfn.XLOOKUP($B16,'APPENDIX 6'!$B:$B,'APPENDIX 6'!I:I,0,0) -> 4415482.7 | R16: =O16+_xlfn.XLOOKUP($B16,'APPENDIX 5 iv'!$B:$B,'APPENDIX 5 iv'!Q:Q,0,0)+_xlfn.XLOOKUP($B16,'APPENDIX 6'!$B:$B,'APPENDIX 6'!J:J,0,0) -> 1473334.1 | S16: =SUM(Q16:R16) -> 5888816.7
B17: Long-Term Liabilites | C17: 0 | D17: 0 | E17: 0 | F17: 0 | G17: 0 | H17: 0 | I17: 0 | J17: 0 | N17: =SUMIFS('APPENDIX 4 iii'!$B17:$L17,'APPENDIX 4 iii'!$B$5:$L$5,"*total*")-O17 -> 0 | O17: =SUMIFS('APPENDIX 4 i'!$B17:$K17,'APPENDIX 4 i'!$B$5:$K$5,"*reinsurance*")+ SUMIFS('APPENDIX 4 ii'!$B17:$K17,'APPENDIX 4 ii'!$B$5:$K$5,"*reinsurance*")+ SUMIFS('APPENDIX 4 iii'!$B17:$K17,'APPENDIX 4 iii'!$B$5:$K$5,"*reinsurance*") -> 0 | Q17: =N17+_xlfn.XLOOKUP($B17,'APPENDIX 5 iv'!$B:$B,'APPENDIX 5 iv'!P:P,0,0)+_xlfn.XLOOKUP($B17,'APPENDIX 6'!$B:$B,'APPENDIX 6'!I:I,0,0) -> 438424.9 | R17: =O17+_xlfn.XLOOKUP($B17,'APPENDIX 5 iv'!$B:$B,'APPENDIX 5 iv'!Q:Q,0,0)+_xlfn.XLOOKUP($B17,'APPENDIX 6'!$B:$B,'APPENDIX 6'!J:J,0,0) -> 0 | S17: =SUM(Q17:R17) -> 438424.9
... B45: Total Assets | C45: 31784005 | D45: 22598964 | E45: 7823446.6 | F45: 39969835 | G45: 894716.47 | H45: 0 | I45: 0 | J45: 1.1647085e+09 | N45: =SUMIFS('APPENDIX 4 iii'!$B45:$L45,'APPENDIX 4 iii'!$B$5:$L$5,"*total*")-O45 -> 1.1474045e+09 | O45: =SUMIFS('APPENDIX 4 i'!$B45:$K45,'APPENDIX 4 i'!$B$5:$K$5,"*reinsurance*")+ SUMIFS('APPENDIX 4 ii'!$B45:$K45,'APPENDIX 4 ii'!$B$5:$K$5,"*reinsurance*")+ SUMIFS('APPENDIX 4 iii'!$B45:$K45,'APPENDIX 4 iii'!$B$5:$K$5,"*reinsurance*") -> 17304016 | Q45: =N45+_xlfn.XLOOKUP($B45,'APPENDIX 5 iv'!$B:$B,'APPENDIX 5 iv'!P:P,0,0)+_xlfn.XLOOKUP($B45,'APPENDIX 6'!$B:$B,'APPENDIX 6'!I:I,0,0) -> 1.4926807e+09 | R45: =O45+_xlfn.XLOOKUP($B45,'APPENDIX 5 iv'!$B:$B,'APPENDIX 5 iv'!Q:Q,0,0)+_xlfn.XLOOKUP($B45,'APPENDIX 6'!$B:$B,'APPENDIX 6'!J:J,0,0) -> 1.1500946e+08 | S45: =SUM(Q45:R45) -> 1.6076901e+09
B46: Amounts in Thousand Shillings
N49: =N45-N42-N41-N43-N44-N40-N25-N22-N23 -> 1.0955451e+09 | O49: =O45-O42-O41-O43-O44-O40-O25-O22-O23 -> 15563642 | Q49: =Q45-Q42-Q41-Q43-Q44-Q40-Q25-Q22-Q23 -> 1.2997507e+09 | R49: =R45-R42-R41-R43-R44-R40-R25-R22-R23 -> 87961845 | S49: =S45-S42-S41-S43-S44-S40-S25-S22-S23 -> 1.3877126e+09
N50: Life | P50: General | R50: Micro | S50: Industry
N51: Insurers | O51: Reinsurers | P51: Insurers | Q51: Reinsurers | R51: Microinsurers | S51: Insurers | T51: Reinsurers | U51: Total
M52: Equity | N52: =N13 -> 1.0041134e+08 | O52: =O13 -> 13210495 | P52: ='APPENDIX 5 iv'!P12 -> 94965539 | Q52: ='APPENDIX 5 iv'!Q12 -> 58265158 | R52: ='APPENDIX 6'!I12 -> 494851.35 | S52: =Q13 -> 1.9587173e+08 | T52: =R13 -> 71475653 | U52: =S13 -> 2.6734739e+08 | V52: =IF(AND(SUM(N52:R52)=SUM(S52:T52),SUM(S52:T52)=U52),"Ok","Check") -> Ok
M53: Assets | N53: =N45 -> 1.1474045e+09 | O53: =O45 -> 17304016 | P53: ='APPENDIX 5 iv'!P43 -> 3.436757e+08 | Q53: ='APPENDIX 5 iv'!Q43 -> 97705442 | R53: ='APPENDIX 6'!I43 -> 1600509.8 | S53: =Q45 -> 1.4926807e+09 | T53: =R45 -> 1.1500946e+08 | U53: =S45 -> 1.6076901e+09 | V53: =IF(AND(SUM(N53:R53)=SUM(S53:T53),SUM(S53:T53)=U53),"Ok","Check") -> Ok
M54: Investments | N54: =SUM(N24,N26:N39) -> 1.0955451e+09 | O54: =SUM(O24,O26:O39) -> 15563642 | P54: =SUM('APPENDIX 5 iv'!P22,'APPENDIX 5 iv'!P24:P37) -> 2.0591962e+08 | Q54: =SUM('APPENDIX 5 iv'!Q22,'APPENDIX 5 iv'!Q24:Q37) -> 69650543 | R54: =SUM('APPENDIX 6'!I22,'APPENDIX 6'!I24:I37) -> 1033640.7 | S54: =SUM(Q24,Q26:Q39) -> 1.3024984e+09 | T54: =SUM(R24,R26:R39) -> 85214185 | U54: =SUM(S24,S26:S39) -> 1.3877126e+09 | V54: =IF(AND(SUM(N54:R54)=SUM(S54:T54),SUM(S54:T54)=U54),"Ok","Check") -> Ok

Sheet APPENDIX 5 i
B4: =_xlfn.CONCAT('Table of Contents'!B14,": ",'Table of Contents'!C14) -> APPENDIX 5 i: SUMMARY OF GENERAL INSURANCE BUSINESS BALANCE SHEETS AS AT 31.03.2026
B5: COMPANY | C5: AAR INSURANCE KENYA | D5: AFRICAN MERCHANT ASSURANCE | E5: APA INSURANCE LIMITED | F5: BRITAM GENERAL INSURANCE | G5: BUPA GLOBAL INSURANCE | H5: CANNON GENERAL INSURANCE | I5: CIC GENERAL INSURANCE COMPANY | J5: CONTINENTAL REINSURANCE | K5: DEFINITE ASSURANCE COMPANY | L5: DIRECTLINE ASSURANCE COMPANY
B6: Share Capital | C6: 1017626.6 | D6: 987386 | E6: 1250000 | F6: 2668000 | G6: 1086683.1 | H6: 453960.46 | I6: 1700000 | J6: 1500000 | K6: 0 | L6: 300000
B7: Share Premium | C7: 460523 | D7: 0 | E7: 0 | F7: 0 | G7: 0 | H7: 583039.52 | I7: 0 | J7: 0 | K7: 0 | L7: 0
B8: Revaluation Reserve | C8: 0 | D8: 30240.538 | E8: 0 | F8: 0 | G8: 0 | H8: 74345 | I8: 0 | J8: 0 | K8: 0 | L8: 0
B9: Other Equity | C9: 0 | D9: 0 | E9: 1165168.2 | F9: 0 | G9: 0 | H9: -86582 | I9: 349723.34 | J9: 0 | K9: 0 | L9: 0
B10: Retained Earnings | C10: 1374944.7 | D10: 270683.15 | E10: 5211241 | F10: 5795611.3 | G10: 306.865 | H10: -303595.12 | I10: 4395349.1 | J10: 2237763.7 | K10: 0 | L10: -2787343.5
B11: Other Reserves | C11: 0 | D11: 0 | E11: 0 | F11: 0 | G11: 0 | H11: 0 | I11: 0 | J11: -87345.33 | K11: 0 | L11: 0
B12: Total Equity_x000D_ | C12: 2853094.3 | D12: 1288309.7 | E12: 7626409.2 | F12: 8463611.3 | G12: 1086990 | H12: 721167.86 | I12: 6445072.5 | J12: 3650418.3 | K12: 0 | L12: -2487343.5
B13: Insurance Contract Liabilites | C13: 6301226.5 | D13: 3469223.4 | E13: 17111456 | F13: 15867776 | G13: 4482583 | H13: 2714863.7 | I13: 16195843 | J13: 6444699.4 | K13: 0 | L13: 9172659
B14: Reinsurance Contract Liabilites | C14: 0 | D14: 18.841367 | E14: 0 | F14: 30824.157 | G14: 0 | H14: 0 | I14: 0 | J14: 0 | K14: 0 | L14: 0
B15: Long-Term Liabilites | C15: 0 | D15: 0 | E15: 0 | F15: 0 | G15: 0 | H15: 0 | I15: 0 | J15: 0 | K15: 0 | L15: 0
B16: Deferred tax liability | C16: 0 | D16: 0 | E16: 0 | F16: 0 | G16: 0 | H16: 122344.66 | I16: 0 | J16: 51587.241 | K16: 0 | L16: 0
B17: Short-Term Liabilites | C17: 355113.84 | D17: 229204.96 | E17: 1530094.7 | F17: 1006130.1 | G17: 19235.17 | H17: 517354.41 | I17: 704623.18 | J17: 202872.7 | K17: 0 | L17: 330235.69
... B43: Total Assets | C43: 10003161 | D43: 5044946.9 | E43: 26423610 | F43: 26076585 | G43: 5863041.2 | H43: 4091056.5 | I43: 23430840 | J43: 10566962 | K43: 0 | L43: 7110021.4
B44: Amounts in Thousand Shillings | K44: Continued next page

Sheet APPENDIX 5 ii
B3: Continued from previous page
B4: =_xlfn.CONCAT('Table of Contents'!B15,": ",'Table of Contents'!C15) -> APPENDIX 5 ii: SUMMARY OF GENERAL INSURANCE BUSINESS BALANCE SHEETS AS AT 31.03.2026
B5: COMPANY | C5: EAST AFRICA REINSURANCE | D5: EQUITY GENERAL INSURANCE LIMITED | E5: EQUITY HEALTH INSURANCE LIMITED | F5: FIDELITY SHIELD INSURANCE | G5: FIRST ASSURANCE COMPANY | H5: GA INSURANCE COMPANY | I5: GEMINIA INSURANCE COMPANY | J5: GHANA REINSURANCE COMPANY | K5: ICEA LION GENERAL INSURANCE | L5: INTRA-AFRICA ASSURANCE
B6: Share Capital | C6: 1000000 | D6: 600000 | E6: 600000 | F6: 600000 | G6: 810000 | H6: 1500000 | I6: 1006250 | J6: 1000000 | K6: 1000000 | L6: 800000
B7: Share Premium | C7: 0 | D7: 0 | E7: 0 | F7: 0 | G7: 512138.51 | H7: 0 | I7: 0 | J7: 10871.242 | K7: 0 | L7: 0
B8: Revaluation Reserve | C8: 199204.18 | D8: 0 | E8: 0 | F8: 100140.56 | G8: 339178 | H8: 911178.74 | I8: 68492.66 | J8: 0 | K8: 66982.18 | L8: 342209.34
B9: Other Equity | C9: 0 | D9: 0 | E9: 0 | F9: 0 | G9: 71118.815 | H9: -750000 | I9: 21065.59 | J9: 0 | K9: 600000 | L9: 25000
B10: Retained Earnings | C10: 5106113.5 | D10: 239118.57 | E10: 41657.304 | F10: 738893.11 | G10: 222027.58 | H10: 8154107.4 | I10: 281064.84 | J10: 1390983.3 | K10: 7440347.5 | L10: 249103.63
B11: Other Reserves | C11: 0 | D11: 0 | E11: 0 | F11: 0 | G11: -16454.886 | H11: 950137 | I11: 0 | J11: 0 | K11: 0 | L11: 0
B12: Total Equity_x000D_ | C12: 6305317.6 | D12: 839118.57 | E12: 641657.3 | F12: 1439033.7 | G12: 1938008 | H12: 10765423 | I12: 1376873.1 | J12: 2401854.5 | K12: 9107329.7 | L12: 1416313
B13: Insurance Contract Liabilites | C13: 3385215.3 | D13: 862861.12 | E13: 1063463.3 | F13: 5796497.2 | G13: 5853555.4 | H13: 18634608 | I13: 6168932 | J13: 3316502 | K13: 7942529.7 | L13: 3033919.4
B14: Reinsurance Contract Liabilites | C14: 161180.33 | D14: 0 | E14: 0 | F14: 0 | G14: 0 | H14: 3128598.5 | I14: 0 | J14: 0 | K14: 432249.85 | L14: 8725.0624
B15: Long-Term Liabilites | C15: 0 | D15: 200000 | E15: 200000 | F15: 0 | G15: 0 | H15: 0 | I15: 0 | J15: 0 | K15: 0 | L15: 0
B16: Deferred tax liability | C16: 0 | D16: 0 | E16: 0 | F16: 11133.526 | G16: 0 | H16: 121943.95 | I16: 0 | J16: 0 | K16: 532885.94 | L16: 0
B17: Short-Term Liabilites | C17: 916987.56 | D17: 400523.72 | E17: 179915.67 | F17: 203287.09 | G17: 451158.82 | H17: 495050.39 | I17: 104132.81 | J17: 8570.936 | K17: 957361.02 | L17: 65400.603
... B43: Total Assets | C43: 10865238 | D43: 2364573.7 | E43: 2090023.7 | F43: 7459785.3 | G43: 8472972.7 | H43: 33468273 | I43: 7709620 | J43: 5796263.7 | K43: 19311463 | L43: 4598354.2
B44: Amounts in Thousand Shillings | K44: Continued next page

Sheet APPENDIX 5 iii
B3: Continued from previous page
B4: =_xlfn.CONCAT('Table of Contents'!B16,": ",'Table of Contents'!C16) -> APPENDIX 5 iii: SUMMARY OF GENERAL INSURANCE BUSINESS BALANCE SHEETS AS AT 31.03.2026
B5: COMPANY | C5: JUBILEE HEALTH INSURANCE | D5: KENINDIA ASSURANCE COMPANY | E5: KENYA ORIENT INSURANCE | F5: KENYA REINSURANCE CORPORATION | G5: MADISON INSURANCE COMPANY | H5: MAYFAIR INSURANCE COMPANY | I5: MUA INSURANCE COMPANY | J5: NCBA INSURANCE COMPANY | K5: OCCIDENTAL INSURANCE COMPANY | L5: OLD MUTUAL GENERAL INSURANCE | M5: PACIS INSURANCE COMPANY
B6: Share Capital | C6: 2763720 | D6: 600000 | E6: 810721.06 | F6: 13498981 | G6: 605000 | H6: 1500000 | I6: 600000 | J6: 600000 | K6: 895831 | L6: 1000000 | M6: 688553.91
B7: Share Premium | C7: 0 | D7: 1198.295 | E7: 0 | F7: 0 | G7: 0 | H7: 0 | I7: 0 | J7: 0 | K7: 0 | L7: 0 | M7: 5712
B8: Revaluation Reserve | C8: 54390.06 | D8: 456853 | E8: 10029.498 | F8: 37904.31 | G8: 0 | H8: -152930.36 | I8: 0 | J8: 0 | K8: 0 | L8: 0 | M8: 0
B9: Other Equity | C9: 0 | D9: 592976.33 | E9: 1672217.3 | F9: 1314112.1 | G9: 0 | H9: 244574 | I9: 1220213 | J9: 170013.69 | K9: 100378.9 | L9: 0 | M9: 0
B10: Retained Earnings | C10: 2442585.9 | D10: 2795919.9 | E10: -3949216.7 | F10: 25965243 | G10: 657475.84 | H10: 3851254.1 | I10: -2197953 | J10: 1640591.4 | K10: -437720.33 | L10: 5590792.6 | M10: 318901.32
B11: Other Reserves | C11: 0 | D11: 0 | E11: 0 | F11: 1681321 | G11: 0 | H11: 557046.93 | I11: 17823.603 | J11: 0 | K11: 0 | L11: 0 | M11: 29527.889
B12: Total Equity_x000D_ | C12: 5260696 | D12: 4446947.5 | E12: -1456248.9 | F12: 42497561 | G12: 1262475.8 | H12: 5999944.6 | I12: -359916.43 | J12: 2410605.1 | K12: 558489.57 | L12: 6590792.6 | M12: 1042695.1
B13: Insurance Contract Liabilites | C13: 8308280.6 | D13: 7083695.2 | E13: 2992167.2 | F13: 14468912 | G13: 8062992.9 | H13: 12261133 | I13: 2633864.8 | J13: 3020020.1 | K13: 2238469.5 | L13: 15323176 | M13: 3560958.5
B14: Reinsurance Contract Liabilites | C14: 0 | D14: 0 | E14: 0 | F14: 1231200.2 | G14: 0 | H14: 0 | I14: 0 | J14: 153957.83 | K14: 0 | L14: 0 | M14: 0
B15: Long-Term Liabilites | C15: 0 | D15: 0 | E15: 0 | F15: 0 | G15: 0 | H15: 0 | I15: 0 | J15: 0 | K15: 0 | L15: 0 | M15: 0
B16: Deferred tax liability | C16: 0 | D16: 0 | E16: 0 | F16: 1702582.3 | G16: 0 | H16: 101209.47 | I16: 0 | J16: 0 | K16: 0 | L16: 23488.854 | M16: 48694.997
B17: Short-Term Liabilites | C17: -37660.347 | D17: 181828.88 | E17: 606554.07 | F17: 827628.45 | G17: 58250.546 | H17: 3339313.8 | I17: 508455.82 | J17: 414847.11 | K17: 654118.55 | L17: 2817678.2 | M17: 224035.79
... B43: Total Assets | C43: 14528021 | D43: 11739902 | E43: 2216217.8 | F43: 61090313 | G43: 9605090.1 | H43: 21903271 | I43: 2837945.6 | J43: 6193713 | K43: 3513659.8 | L43: 26166330 | M43: 4951318.4
B44: Amounts in Thousand Shillings | L44: Continued next page

Sheet APPENDIX  5 iv
B3: Continued from previous page
B4: =_xlfn.CONCAT('Table of Contents'!B17,": ",'Table of Contents'!C17) -> APPENDIX 5 iv: SUMMARY OF GENERAL INSURANCE BUSINESS BALANCE SHEETS AS AT 31.03.2026
B5: COMPANY | C5: PIONEER INSURANCE COMPANY | D5: SANLAM ALLIANZ GENERAL INSURANCE | E5: STAR DISCOVER INSURANCE | F5: TAKAFUL INSURANCE OF AFRICA | G5: TAUSI ASSURANCE COMPANY | H5: THE HERITAGE INSURANCE COMPANY | I5: THE KENYAN ALLIANCE INSURANCE | J5: THE MONARCH INSURANCE | K5: WAICA REINSURANCE KENYA LIMITED | L5: TOTAL | P5: Insurers | Q5: Reinsurers
B6: Share Capital | C6: 700000 | D6: 3907103 | E6: 675000 | F6: 1239704.3 | G6: 600000 | H6: 1000000 | I6: 0 | J6: 0 | K6: 1102550 | L6: 52667071 | P6: =SUMIFS('APPENDIX 5 iv'!$B6:$O6,'APPENDIX 5 iv'!$B$5:$O$5,"*total*")-Q6 -> 34565539 | Q6: =SUMIFS('APPENDIX 5 i'!$B6:$O6,'APPENDIX 5 i'!$B$5:$O$5,"*reinsurance*")+ SUMIFS('APPENDIX 5 ii'!$B6:$O6,'APPENDIX 5 ii'!$B$5:$O$5,"*reinsurance*")+ SUMIFS('APPENDIX 5 iii'!$B6:$O6,'APPENDIX 5 iii'!$B$5:$O$5,"*reinsurance*")+ SUMIFS('APPENDIX 5 iv'!$B6:$O6,'APPENDIX 5 iv'!$B$5:$O$5,"*reinsurance*") -> 18101531
B7: Share Premium_x000D_ | C7: 0 | D7: 2552745 | E7: 0 | F7: 146101 | G7: 0 | H7: 0 | I7: 0 | J7: 0 | K7: 0 | L7: 4272328.6 | P7: =SUMIFS('APPENDIX 5 iv'!$B7:$O7,'APPENDIX 5 iv'!$B$5:$O$5,"*total*")-Q7 -> 4261457.3 | Q7: =SUMIFS('APPENDIX 5 i'!$B7:$O7,'APPENDIX 5 i'!$B$5:$O$5,"*reinsurance*")+ SUMIFS('APPENDIX 5 ii'!$B7:$O7,'APPENDIX 5 ii'!$B$5:$O$5,"*reinsurance*")+ SUMIFS('APPENDIX 5 iii'!$B7:$O7,'APPENDIX 5 iii'!$B$5:$O$5,"*reinsurance*")+ SUMIFS('APPENDIX 5 iv'!$B7:$O7,'APPENDIX 5 iv'!$B$5:$O$5,"*reinsurance*") -> 10871.242
B8: Revaluation Reserves | C8: 0 | D8: 0 | E8: 16000 | F8: 25539.216 | G8: 208824.79 | H8: 0 | I8: 0 | J8: 0 | K8: 0 | L8: 2788581.7 | P8: =SUMIFS('APPENDIX 5 iv'!$B8:$O8,'APPENDIX 5 iv'!$B$5:$O$5,"*total*")-Q8 -> 2551473.2 | Q8: =SUMIFS('APPENDIX 5 i'!$B8:$O8,'APPENDIX 5 i'!$B$5:$O$5,"*reinsurance*")+ SUMIFS('APPENDIX 5 ii'!$B8:$O8,'APPENDIX 5 ii'!$B$5:$O$5,"*reinsurance*")+ SUMIFS('APPENDIX 5 iii'!$B8:$O8,'APPENDIX 5 iii'!$B$5:$O$5,"*reinsurance*")+ SUMIFS('APPENDIX 5 iv'!$B8:$O8,'APPENDIX 5 iv'!$B$5:$O$5,"*reinsurance*") -> 237108.49
B9: Other Equity | C9: 60200 | D9: 0 | E9: 0 | F9: 0 | G9: 89740.165 | H9: 0 | I9: 0 | J9: 0 | K9: 0 | L9: 6859919.4 | P9: =SUMIFS('APPENDIX 5 iv'!$B9:$O9,'APPENDIX 5 iv'!$B$5:$O$5,"*total*")-Q9 -> 5545807.3 | Q9: =SUMIFS('APPENDIX 5 i'!$B9:$O9,'APPENDIX 5 i'!$B$5:$O$5,"*reinsurance*")+ SUMIFS('APPENDIX 5 ii'!$B9:$O9,'APPENDIX 5 ii'!$B$5:$O$5,"*reinsurance*")+ SUMIFS('APPENDIX 5 iii'!$B9:$O9,'APPENDIX 5 iii'!$B$5:$O$5,"*reinsurance*")+ SUMIFS('APPENDIX 5 iv'!$B9:$O9,'APPENDIX 5 iv'!$B$5:$O$5,"*reinsurance*") -> 1314112.1
B10: Retained Earnings | C10: 602217.91 | D10: -3227847.6 | E10: -11579.211 | F10: -477725.49 | G10: 2081032.8 | H10: 4469678.2 | I10: 0 | J10: 0 | K10: 2307456.5 | L10: 82479484 | P10: =SUMIFS('APPENDIX 5 iv'!$B10:$O10,'APPENDIX 5 iv'!$B$5:$O$5,"*total*")-Q10 -> 45471925 | Q10: =SUMIFS('APPENDIX 5 i'!$B10:$O10,'APPENDIX 5 i'!$B$5:$O$5,"*reinsurance*")+ SUMIFS('APPENDIX 5 ii'!$B10:$O10,'APPENDIX 5 ii'!$B$5:$O$5,"*reinsurance*")+ SUMIFS('APPENDIX 5 iii'!$B10:$O10,'APPENDIX 5 iii'!$B$5:$O$5,"*reinsurance*")+ SUMIFS('APPENDIX 5 iv'!$B10:$O10,'APPENDIX 5 iv'!$B$5:$O$5,"*reinsurance*") -> 37007559
B11: Other Reserves | C11: 1031184.4 | D11: 71.376174 | E11: 0 | F11: 0 | G11: 0 | H11: 0 | I11: 0 | J11: 0 | K11: 0 | L11: 4163312 | P11: =SUMIFS('APPENDIX 5 iv'!$B11:$O11,'APPENDIX 5 iv'!$B$5:$O$5,"*total*")-Q11 -> 2569336.4 | Q11: =SUMIFS('APPENDIX 5 i'!$B11:$O11,'APPENDIX 5 i'!$B$5:$O$5,"*reinsurance*")+ SUMIFS('APPENDIX 5 ii'!$B11:$O11,'APPENDIX 5 ii'!$B$5:$O$5,"*reinsurance*")+ SUMIFS('APPENDIX 5 iii'!$B11:$O11,'APPENDIX 5 iii'!$B$5:$O$5,"*reinsurance*")+ SUMIFS('APPENDIX 5 iv'!$B11:$O11,'APPENDIX 5 iv'!$B$5:$O$5,"*reinsurance*") -> 1593975.7
B12: Total Equity_x000D_ | C12: 2393602.3 | D12: 3232071.8 | E12: 679420.79 | F12: 933618.99 | G12: 2979597.7 | H12: 5469678.2 | I12: 0 | J12: 0 | K12: 3410006.5 | L12: 1.532307e+08 | P12: =SUMIFS('APPENDIX 5 iv'!$B12:$O12,'APPENDIX 5 iv'!$B$5:$O$5,"*total*")-Q12 -> 94965539 | Q12: =SUMIFS('APPENDIX 5 i'!$B12:$O12,'APPENDIX 5 i'!$B$5:$O$5,"*reinsurance*")+ SUMIFS('APPENDIX 5 ii'!$B12:$O12,'APPENDIX 5 ii'!$B$5:$O$5,"*reinsurance*")+ SUMIFS('APPENDIX 5 iii'!$B12:$O12,'APPENDIX 5 iii'!$B$5:$O$5,"*reinsurance*")+ SUMIFS('APPENDIX 5 iv'!$B12:$O12,'APPENDIX 5 iv'!$B$5:$O$5,"*reinsurance*") -> 58265158
B13: Insurance Contract Liabilites | C13: 2382681.8 | D13: 10832690 | E13: 1332180.6 | F13: 1383080.9 | G13: 2498156.5 | H13: 8083284.6 | I13: 0 | J13: 0 | K13: 4959580.9 | L13: 2.4924374e+08 | P13: =SUMIFS('APPENDIX 5 iv'!$B13:$O13,'APPENDIX 5 iv'!$B$5:$O$5,"*total*")-Q13 -> 2.1666883e+08 | Q13: =SUMIFS('APPENDIX 5 i'!$B13:$O13,'APPENDIX 5 i'!$B$5:$O$5,"*reinsurance*")+ SUMIFS('APPENDIX 5 ii'!$B13:$O13,'APPENDIX 5 ii'!$B$5:$O$5,"*reinsurance*")+ SUMIFS('APPENDIX 5 iii'!$B13:$O13,'APPENDIX 5 iii'!$B$5:$O$5,"*reinsurance*")+ SUMIFS('APPENDIX 5 iv'!$B13:$O13,'APPENDIX 5 iv'!$B$5:$O$5,"*reinsurance*") -> 32574910
B14: Reinsurance Contract Liabilites | C14: 0 | D14: 547078.41 | E14: 0 | F14: 27691.879 | G14: 0 | H14: 0 | I14: 0 | J14: 0 | K14: 0 | L14: 5721525 | P14: =SUMIFS('APPENDIX 5 iv'!$B14:$O14,'APPENDIX 5 iv'!$B$5:$O$5,"*total*")-Q14 -> 4329144.5 | Q14: =SUMIFS('APPENDIX 5 i'!$B14:$O14,'APPENDIX 5 i'!$B$5:$O$5,"*reinsurance*")+ SUMIFS('APPENDIX 5 ii'!$B14:$O14,'APPENDIX 5 ii'!$B$5:$O$5,"*reinsurance*")+ SUMIFS('APPENDIX 5 iii'!$B14:$O14,'APPENDIX 5 iii'!$B$5:$O$5,"*reinsurance*")+ SUMIFS('APPENDIX 5 iv'!$B14:$O14,'APPENDIX 5 iv'!$B$5:$O$5,"*reinsurance*") -> 1392380.5
B15: Long-Term Liabilites | C15: 0 | D15: 0 | E15: 34950.782 | F15: 0 | G15: 0 | H15: 0 | I15: 0 | J15: 0 | K15: 0 | L15: 434950.78 | P15: =SUMIFS('APPENDIX 5 iv'!$B15:$O15,'APPENDIX 5 iv'!$B$5:$O$5,"*total*")-Q15 -> 434950.78 | Q15: =SUMIFS('APPENDIX 5 i'!$B15:$O15,'APPENDIX 5 i'!$B$5:$O$5,"*reinsurance*")+ SUMIFS('APPENDIX 5 ii'!$B15:$O15,'APPENDIX 5 ii'!$B$5:$O$5,"*reinsurance*")+ SUMIFS('APPENDIX 5 iii'!$B15:$O15,'APPENDIX 5 iii'!$B$5:$O$5,"*reinsurance*")+ SUMIFS('APPENDIX 5 iv'!$B15:$O15,'APPENDIX 5 iv'!$B$5:$O$5,"*reinsurance*") -> 0
B16: Deferred tax liability | C16: 0 | D16: 0 | E16: 756.59033 | F16: 16921.2 | G16: 93228.071 | H16: 38586.533 | I16: 0 | J16: 0 | K16: 0 | L16: 2865363.3 | P16: =SUMIFS('APPENDIX 5 iv'!$B16:$O16,'APPENDIX 5 iv'!$B$5:$O$5,"*total*")-Q16 -> 1111193.8 | Q16: =SUMIFS('APPENDIX 5 i'!$B16:$O16,'APPENDIX 5 i'!$B$5:$O$5,"*reinsurance*")+ SUMIFS('APPENDIX 5 ii'!$B16:$O16,'APPENDIX 5 ii'!$B$5:$O$5,"*reinsurance*")+ SUMIFS('APPENDIX 5 iii'!$B16:$O16,'APPENDIX 5 iii'!$B$5:$O$5,"*reinsurance*")+ SUMIFS('APPENDIX 5 iv'!$B16:$O16,'APPENDIX 5 iv'!$B$5:$O$5,"*reinsurance*") -> 1754169.5
B17: Short-Term Liabilites | C17: 641451.46 | D17: 1170188.7 | E17: 104998.56 | F17: 24178.283 | G17: 108806.34 | H17: 705453.83 | I17: 0 | J17: 0 | K17: 998936.41 | L17: 22026318 | P17: =SUMIFS('APPENDIX 5 iv'!$B17:$O17,'APPENDIX 5 iv'!$B$5:$O$5,"*total*")-Q17 -> 19071322 | Q17: =SUMIFS('APPENDIX 5 i'!$B17:$O17,'APPENDIX 5 i'!$B$5:$O$5,"*reinsurance*")+ SUMIFS('APPENDIX 5 ii'!$B17:$O17,'APPENDIX 5 ii'!$B$5:$O$5,"*reinsurance*")+ SUMIFS('APPENDIX 5 iii'!$B17:$O17,'APPENDIX 5 iii'!$B$5:$O$5,"*reinsurance*")+ SUMIFS('APPENDIX 5 iv'!$B17:$O17,'APPENDIX 5 iv'!$B$5:$O$5,"*reinsurance*") -> 2954996.1
... B23: Fixed Assets | C23: 26786.43 | D23: 61303.437 | E23: 11371.666 | F23: 23565.157 | G23: 33340.841 | H23: 85337.985 | I23: 0 | J23: 0 | K23: 26786.54 | L23: 1868006.5 | P23: =SUMIFS('APPENDIX 5 iv'!$B23:$O23,'APPENDIX 5 iv'!$B$5:$O$5,"*total*")-Q23 -> 1734359.1 | Q23: =SUMIFS('APPENDIX 5 i'!$B23:$O23,'APPENDIX 5 i'!$B$5:$O$5,"*reinsurance*")+ SUMIFS('APPENDIX 5 ii'!$B23:$O23,'APPENDIX 5 ii'!$B$5:$O$5,"*reinsurance*")+ SUMIFS('APPENDIX 5 iii'!$B23:$O23,'APPENDIX 5 iii'!$B$5:$O$5,"*reinsurance*")+ SUMIFS('APPENDIX 5 iv'!$B23:$O23,'APPENDIX 5 iv'!$B$5:$O$5,"*reinsurance*") -> 133647.36
B24: Government Securites | C24: 1330242.6 | D24: 7895603.3 | E24: 875928.69 | F24: 20606 | G24: 2791156.8 | H24: 7749375.4 | I24: 0 | J24: 0 | K24: 1606148.3 | L24: 1.4994521e+08 | P24: =SUMIFS('APPENDIX 5 iv'!$B24:$O24,'APPENDIX 5 iv'!$B$5:$O$5,"*total*")-Q24 -> 1.2433392e+08 | Q24: =SUMIFS('APPENDIX 5 i'!$B25:$O25,'APPENDIX 5 i'!$B$5:$O$5,"*reinsurance*")+ SUMIFS('APPENDIX 5 ii'!$B24:$O24,'APPENDIX 5 ii'!$B$5:$O$5,"*reinsurance*")+ SUMIFS('APPENDIX 5 iii'!$B24:$O24,'APPENDIX 5 iii'!$B$5:$O$5,"*reinsurance*")+ SUMIFS('APPENDIX 5 iv'!$B24:$O24,'APPENDIX 5 iv'!$B$5:$O$5,"*reinsurance*") -> 25611288
B25: Investment In Unit Trusts | C25: 0 | D25: 0 | E25: 0 | F25: 0 | G25: 8115.185 | H25: 0 | I25: 0 | J25: 0 | K25: 0 | L25: 1752214.6 | P25: =SUMIFS('APPENDIX 5 iv'!$B25:$O25,'APPENDIX 5 iv'!$B$5:$O$5,"*total*")-Q25 -> 1467348.4 | Q25: =SUMIFS('APPENDIX 5 i'!$B26:$O26,'APPENDIX 5 i'!$B$5:$O$5,"*reinsurance*")+ SUMIFS('APPENDIX 5 ii'!$B25:$O25,'APPENDIX 5 ii'!$B$5:$O$5,"*reinsurance*")+ SUMIFS('APPENDIX 5 iii'!$B25:$O25,'APPENDIX 5 iii'!$B$5:$O$5,"*reinsurance*")+ SUMIFS('APPENDIX 5 iv'!$B25:$O25,'APPENDIX 5 iv'!$B$5:$O$5,"*reinsurance*") -> 284866.19
B26: Other Securites | C26: 0 | D26: 0 | E26: 0 | F26: 0 | G26: 0 | H26: 0 | I26: 0 | J26: 0 | K26: 0 | L26: 249222.79 | P26: =SUMIFS('APPENDIX 5 iv'!$B26:$O26,'APPENDIX 5 iv'!$B$5:$O$5,"*total*")-Q26 -> 51226.818 | Q26: =SUMIFS('APPENDIX 5 i'!$B26:$O26,'APPENDIX 5 i'!$B$5:$O$5,"*reinsurance*")+ SUMIFS('APPENDIX 5 ii'!$B26:$O26,'APPENDIX 5 ii'!$B$5:$O$5,"*reinsurance*")+ SUMIFS('APPENDIX 5 iii'!$B26:$O26,'APPENDIX 5 iii'!$B$5:$O$5,"*reinsurance*")+ SUMIFS('APPENDIX 5 iv'!$B26:$O26,'APPENDIX 5 iv'!$B$5:$O$5,"*reinsurance*") -> 197995.97
B27: Investment in Related Parties | C27: 1642709.5 | D27: 0 | E27: 0 | F27: 0 | G27: 0 | H27: 0 | I27: 0 | J27: 0 | K27: 0 | L27: 21415642 | P27: =SUMIFS('APPENDIX 5 iv'!$B27:$O27,'APPENDIX 5 iv'!$B$5:$O$5,"*total*")-Q27 -> 7749140.2 | Q27: =SUMIFS('APPENDIX 5 i'!$B27:$O27,'APPENDIX 5 i'!$B$5:$O$5,"*reinsurance*")+ SUMIFS('APPENDIX 5 ii'!$B27:$O27,'APPENDIX 5 ii'!$B$5:$O$5,"*reinsurance*")+ SUMIFS('APPENDIX 5 iii'!$B27:$O27,'APPENDIX 5 iii'!$B$5:$O$5,"*reinsurance*")+ SUMIFS('APPENDIX 5 iv'!$B27:$O27,'APPENDIX 5 iv'!$B$5:$O$5,"*reinsurance*") -> 13666502
B28: Corporate Bonds | C28: 20000 | D28: 0 | E28: 0 | F28: 0 | G28: 39902.536 | H28: 0 | I28: 0 | J28: 0 | K28: 294367.19 | L28: 1887921.1 | P28: =SUMIFS('APPENDIX 5 iv'!$B28:$O28,'APPENDIX 5 iv'!$B$5:$O$5,"*total*")-Q28 -> 1195104.1 | Q28: =SUMIFS('APPENDIX 5 i'!$B28:$O28,'APPENDIX 5 i'!$B$5:$O$5,"*reinsurance*")+ SUMIFS('APPENDIX 5 ii'!$B28:$O28,'APPENDIX 5 ii'!$B$5:$O$5,"*reinsurance*")+ SUMIFS('APPENDIX 5 iii'!$B28:$O28,'APPENDIX 5 iii'!$B$5:$O$5,"*reinsurance*")+ SUMIFS('APPENDIX 5 iv'!$B28:$O28,'APPENDIX 5 iv'!$B$5:$O$5,"*reinsurance*") -> 692816.93
B29: Commercial Papers | C29: 0 | D29: 0 | E29: 0 | F29: 0 | G29: 0 | H29: 0 | I29: 0 | J29: 0 | K29: 0 | L29: 212037.35 | P29: =SUMIFS('APPENDIX 5 iv'!$B29:$O29,'APPENDIX 5 iv'!$B$5:$O$5,"*total*")-Q29 -> 212037.35 | Q29: =SUMIFS('APPENDIX 5 i'!$B29:$O29,'APPENDIX 5 i'!$B$5:$O$5,"*reinsurance*")+ SUMIFS('APPENDIX 5 ii'!$B29:$O29,'APPENDIX 5 ii'!$B$5:$O$5,"*reinsurance*")+ SUMIFS('APPENDIX 5 iii'!$B29:$O29,'APPENDIX 5 iii'!$B$5:$O$5,"*reinsurance*")+ SUMIFS('APPENDIX 5 iv'!$B29:$O29,'APPENDIX 5 iv'!$B$5:$O$5,"*reinsurance*") -> 0
B30: Debentures | C30: 0 | D30: 0 | E30: 0 | F30: 0 | G30: 0 | H30: 0 | I30: 0 | J30: 0 | K30: 0 | L30: 0 | P30: =SUMIFS('APPENDIX 5 iv'!$B30:$O30,'APPENDIX 5 iv'!$B$5:$O$5,"*total*")-Q30 -> 0 | Q30: =SUMIFS('APPENDIX 5 i'!$B30:$O30,'APPENDIX 5 i'!$B$5:$O$5,"*reinsurance*")+ SUMIFS('APPENDIX 5 ii'!$B30:$O30,'APPENDIX 5 ii'!$B$5:$O$5,"*reinsurance*")+ SUMIFS('APPENDIX 5 iii'!$B30:$O30,'APPENDIX 5 iii'!$B$5:$O$5,"*reinsurance*")+ SUMIFS('APPENDIX 5 iv'!$B30:$O30,'APPENDIX 5 iv'!$B$5:$O$5,"*reinsurance*") -> 0
B31: Ordinary Shares Quoted | C31: 0 | D31: 0 | E31: 0 | F31: 0 | G31: 316465.44 | H31: 0 | I31: 0 | J31: 0 | K31: 0 | L31: 10774573 | P31: =SUMIFS('APPENDIX 5 iv'!$B31:$O31,'APPENDIX 5 iv'!$B$5:$O$5,"*total*")-Q31 -> 4791215 | Q31: =SUMIFS('APPENDIX 5 i'!$B31:$O31,'APPENDIX 5 i'!$B$5:$O$5,"*reinsurance*")+ SUMIFS('APPENDIX 5 ii'!$B31:$O31,'APPENDIX 5 ii'!$B$5:$O$5,"*reinsurance*")+ SUMIFS('APPENDIX 5 iii'!$B31:$O31,'APPENDIX 5 iii'!$B$5:$O$5,"*reinsurance*")+ SUMIFS('APPENDIX 5 iv'!$B31:$O31,'APPENDIX 5 iv'!$B$5:$O$5,"*reinsurance*") -> 5983358.2
B32: Ordinary Shares Unquoted | C32: 0 | D32: 0 | E32: 0 | F32: 0 | G32: 2928.125 | H32: 0 | I32: 0 | J32: 0 | K32: 0 | L32: 3563950.9 | P32: =SUMIFS('APPENDIX 5 iv'!$B32:$O32,'APPENDIX 5 iv'!$B$5:$O$5,"*total*")-Q32 -> 2629238.8 | Q32: =SUMIFS('APPENDIX 5 i'!$B32:$O32,'APPENDIX 5 i'!$B$5:$O$5,"*reinsurance*")+ SUMIFS('APPENDIX 5 ii'!$B32:$O32,'APPENDIX 5 ii'!$B$5:$O$5,"*reinsurance*")+ SUMIFS('APPENDIX 5 iii'!$B32:$O32,'APPENDIX 5 iii'!$B$5:$O$5,"*reinsurance*")+ SUMIFS('APPENDIX 5 iv'!$B32:$O32,'APPENDIX 5 iv'!$B$5:$O$5,"*reinsurance*") -> 934712.11
B33: Preference Shares Quoted | C33: 0 | D33: 0 | E33: 0 | F33: 0 | G33: 0 | H33: 0 | I33: 0 | J33: 0 | K33: 0 | L33: 482.88 | P33: =SUMIFS('APPENDIX 5 iv'!$B33:$O33,'APPENDIX 5 iv'!$B$5:$O$5,"*total*")-Q33 -> 402.1 | Q33: =SUMIFS('APPENDIX 5 i'!$B33:$O33,'APPENDIX 5 i'!$B$5:$O$5,"*reinsurance*")+ SUMIFS('APPENDIX 5 ii'!$B33:$O33,'APPENDIX 5 ii'!$B$5:$O$5,"*reinsurance*")+ SUMIFS('APPENDIX 5 iii'!$B33:$O33,'APPENDIX 5 iii'!$B$5:$O$5,"*reinsurance*")+ SUMIFS('APPENDIX 5 iv'!$B33:$O33,'APPENDIX 5 iv'!$B$5:$O$5,"*reinsurance*") -> 80.78
B34: Preference Shares Unquoted | C34: 0 | D34: 0 | E34: 0 | F34: 0 | G34: 0 | H34: 0 | I34: 0 | J34: 0 | K34: 0 | L34: 0 | P34: =SUMIFS('APPENDIX 5 iv'!$B34:$O34,'APPENDIX 5 iv'!$B$5:$O$5,"*total*")-Q34 -> 0 | Q34: =SUMIFS('APPENDIX 5 i'!$B34:$O34,'APPENDIX 5 i'!$B$5:$O$5,"*reinsurance*")+ SUMIFS('APPENDIX 5 ii'!$B34:$O34,'APPENDIX 5 ii'!$B$5:$O$5,"*reinsurance*")+ SUMIFS('APPENDIX 5 iii'!$B34:$O34,'APPENDIX 5 iii'!$B$5:$O$5,"*reinsurance*")+ SUMIFS('APPENDIX 5 iv'!$B34:$O34,'APPENDIX 5 iv'!$B$5:$O$5,"*reinsurance*") -> 0
B35: Loans Secured and Unsecured | C35: 108720.52 | D35: 0 | E35: 0 | F35: 0 | G35: 1193.277 | H35: 5908.291 | I35: 0 | J35: 0 | K35: 29579.715 | L35: 3215576 | P35: =SUMIFS('APPENDIX 5 iv'!$B35:$O35,'APPENDIX 5 iv'!$B$5:$O$5,"*total*")-Q35 -> 3165880.2 | Q35: =SUMIFS('APPENDIX 5 i'!$B35:$O35,'APPENDIX 5 i'!$B$5:$O$5,"*reinsurance*")+ SUMIFS('APPENDIX 5 ii'!$B35:$O35,'APPENDIX 5 ii'!$B$5:$O$5,"*reinsurance*")+ SUMIFS('APPENDIX 5 iii'!$B35:$O35,'APPENDIX 5 iii'!$B$5:$O$5,"*reinsurance*")+ SUMIFS('APPENDIX 5 iv'!$B35:$O35,'APPENDIX 5 iv'!$B$5:$O$5,"*reinsurance*") -> 49695.772
B36: Mortgages | C36: 0 | D36: 0 | E36: 0 | F36: 0 | G36: 6222.63 | H36: 91299.447 | I36: 0 | J36: 0 | K36: 0 | L36: 1297466.7 | P36: =SUMIFS('APPENDIX 5 iv'!$B36:$O36,'APPENDIX 5 iv'!$B$5:$O$5,"*total*")-Q36 -> 294171.55 | Q36: =SUMIFS('APPENDIX 5 i'!$B36:$O36,'APPENDIX 5 i'!$B$5:$O$5,"*reinsurance*")+ SUMIFS('APPENDIX 5 ii'!$B36:$O36,'APPENDIX 5 ii'!$B$5:$O$5,"*reinsurance*")+ SUMIFS('APPENDIX 5 iii'!$B36:$O36,'APPENDIX 5 iii'!$B$5:$O$5,"*reinsurance*")+ SUMIFS('APPENDIX 5 iv'!$B36:$O36,'APPENDIX 5 iv'!$B$5:$O$5,"*reinsurance*") -> 1003295.2
B37: Term Deposits | C37: 400385.19 | D37: 1625260.8 | E37: 229940.86 | F37: 989462.42 | G37: 530518.65 | H37: 3877489.1 | I37: 0 | J37: 0 | K37: 3295576.6 | L37: 46441584 | P37: =SUMIFS('APPENDIX 5 iv'!$B37:$O37,'APPENDIX 5 iv'!$B$5:$O$5,"*total*")-Q37 -> 37451727 | Q37: =SUMIFS('APPENDIX 5 i'!$B37:$O37,'APPENDIX 5 i'!$B$5:$O$5,"*reinsurance*")+ SUMIFS('APPENDIX 5 ii'!$B37:$O37,'APPENDIX 5 ii'!$B$5:$O$5,"*reinsurance*")+ SUMIFS('APPENDIX 5 iii'!$B37:$O37,'APPENDIX 5 iii'!$B$5:$O$5,"*reinsurance*")+ SUMIFS('APPENDIX 5 iv'!$B37:$O37,'APPENDIX 5 iv'!$B$5:$O$5,"*reinsurance*") -> 8989857.8
... B43: Total Assets | C43: 5446303.8 | D43: 15961070 | E43: 2306371.6 | F43: 2435079.3 | G43: 5706830.8 | H43: 14646250 | I43: 0 | J43: 0 | K43: 9386665.5 | L43: 4.4138114e+08 | P43: =SUMIFS('APPENDIX 5 iv'!$B43:$O43,'APPENDIX 5 iv'!$B$5:$O$5,"*total*")-Q43 -> 3.436757e+08 | Q43: =SUMIFS('APPENDIX 5 i'!$B43:$O43,'APPENDIX 5 i'!$B$5:$O$5,"*reinsurance*")+ SUMIFS('APPENDIX 5 ii'!$B43:$O43,'APPENDIX 5 ii'!$B$5:$O$5,"*reinsurance*")+ SUMIFS('APPENDIX 5 iii'!$B43:$O43,'APPENDIX 5 iii'!$B$5:$O$5,"*reinsurance*")+ SUMIFS('APPENDIX 5 iv'!$B43:$O43,'APPENDIX 5 iv'!$B$5:$O$5,"*reinsurance*") -> 97705442
B44: Amounts in thousand Shillings

Sheet APPENDIX 6
B4: =_xlfn.CONCAT('Table of Contents'!B18,": ",'Table of Contents'!C18) -> APPENDIX 6: SUMMARY OF MICRO INSURANCE BUSINESS BALANCE SHEETS AS AT 31.03.2026
B5: COMPANY | C5: APA MICRO INSURANCE | D5: BIRDVIEW MICRO INSURANCE | E5: BRITAM MICRO INSURANCE | F5: CIC MICRO INSURANCE | G5: STAR DISCOVER MICRO INSURANCE | H5: TURACO MICRO INSURANCE | I5: TOTAL
B6: Share Capital | C6: 50000 | D6: 0 | E6: 250476.9 | F6: 50000 | G6: 0 | H6: 50000 | I6: 400476.9
B7: Share Premium_x000D_ | C7: 0 | D7: 0 | E7: 0 | F7: 0 | G7: 0 | H7: 0 | I7: 0
B8: Revaluation Reserves | C8: 0 | D8: 0 | E8: 0 | F8: 0 | G8: 0 | H8: 0 | I8: 0
B9: Other Equity | C9: 0 | D9: 0 | E9: 0 | F9: 0 | G9: 0 | H9: 0 | I9: 0
B10: Retained Earnings | C10: 16352.606 | D10: 0 | E10: 22263.242 | F10: -29819.197 | G10: 0 | H10: 85577.804 | I10: 94374.455
B11: Other Reserves | C11: 0 | D11: 0 | E11: 0 | F11: 0 | G11: 0 | H11: 0 | I11: 0
B12: Total Equity_x000D_ | C12: 66352.606 | D12: 0 | E12: 272740.14 | F12: 20180.803 | G12: 0 | H12: 135577.8 | I12: 494851.35
B13: Insurance Contract Liabilites | C13: 0 | D13: 0 | E13: 722943.24 | F13: 20175.14 | G13: 0 | H13: 79065.732 | I13: 822184.12
B14: Reinsurance Contract Liabilites | C14: 0 | D14: 0 | E14: 5187.783 | F14: 0 | G14: 0 | H14: 0 | I14: 5187.783
B15: Long-Term Liabilites | C15: 0 | D15: 0 | E15: 0 | F15: 0 | G15: 0 | H15: 3474.1148 | I15: 3474.1148
B16: Deferred tax liability | C16: 0 | D16: 0 | E16: 0 | F16: 0 | G16: 0 | H16: 0 | I16: 0
B17: Short-Term Liabilites | C17: 544.75 | D17: 0 | E17: 90495.67 | F17: 28148.07 | G17: 0 | H17: 41716.95 | I17: 160905.44
... B43: Total Assets | C43: 66897.356 | D43: 0 | E43: 1185649.5 | F43: 68504.013 | G43: 0 | H43: 279459.02 | I43: 1600509.8
B44: Amounts in thousand Shillings

Sheet APPENDIX 7
B3: =_xlfn.CONCAT('Table of Contents'!B19,": ",'Table of Contents'!C19) -> APPENDIX 7: SUMMARY OF LONG TERM INSURANCE BUSINESS GROSS PREMIUM INCOME FOR THE PERIOD ENDED 31.03.2026
B4: Company | C4: Life Assurances | D4: Annuities | E4: Personal Pensions | F4: Deposit Administration | G4: Group Life | H4: Group Credit | I4: Permanent Health | J4: Investments | K4: Total | L4: Market Share (%)
B5: INSURERS
B6: ='APPENDIX 9'!B6 -> ABSA LIFE ASSURANCE | C6: ='APPENDIX 9'!D6 -> 1718647.9 | D6: ='APPENDIX 10'!D6 -> 0 | E6: ='APPENDIX 15'!D6 -> 0 | F6: ='APPENDIX 16'!D6 -> 0 | G6: ='APPENDIX 11'!D6 -> 1658362.9 | H6: ='APPENDIX 12'!D6 -> 425074.02 | I6: ='APPENDIX 14'!D6 -> 0 | J6: ='APPENDIX 13'!D6 -> 0 | K6: =SUM(C6:J6) -> 3802084.8 | L6: =IFERROR(K6/$K$28,0)*100 -> 5.2179778
B7: ='APPENDIX 9'!B7 -> APA LIFE ASSURANCE COMPANY | C7: ='APPENDIX 9'!D7 -> 445344.23 | D7: ='APPENDIX 10'!D7 -> 5112.158 | E7: ='APPENDIX 15'!D7 -> 50242.991 | F7: ='APPENDIX 16'!D7 -> 493888.6 | G7: ='APPENDIX 11'!D7 -> 618127.89 | H7: ='APPENDIX 12'!D7 -> 371018.23 | I7: ='APPENDIX 14'!D7 -> 0 | J7: ='APPENDIX 13'!D7 -> 3619278.6 | K7: =SUM(C7:J7) -> 5603012.7 | L7: =IFERROR(K7/$K$28,0)*100 -> 7.6895697
B8: ='APPENDIX 9'!B8 -> BRITAM LIFE ASSURANCE | C8: ='APPENDIX 9'!D8 -> 2950229.5 | D8: ='APPENDIX 10'!D8 -> 2387797.2 | E8: ='APPENDIX 15'!D8 -> 1289835.6 | F8: ='APPENDIX 16'!D8 -> 2941220.5 | G8: ='APPENDIX 11'!D8 -> 342902.07 | H8: ='APPENDIX 12'!D8 -> 208986.61 | I8: ='APPENDIX 14'!D8 -> 0 | J8: ='APPENDIX 13'!D8 -> 4527608.8 | K8: =SUM(C8:J8) -> 14648580 | L8: =IFERROR(K8/$K$28,0)*100 -> 20.103699
B9: ='APPENDIX 9'!B9 -> CANNON LIFE ASSURANCE (K) LIMITED | C9: ='APPENDIX 9'!D9 -> 0 | D9: ='APPENDIX 10'!D9 -> 0 | E9: ='APPENDIX 15'!D9 -> 0 | F9: ='APPENDIX 16'!D9 -> 0 | G9: ='APPENDIX 11'!D9 -> 170519.51 | H9: ='APPENDIX 12'!D9 -> 647.2533 | I9: ='APPENDIX 14'!D9 -> 0 | J9: ='APPENDIX 13'!D9 -> 5811.6588 | K9: =SUM(C9:J9) -> 176978.42 | L9: =IFERROR(K9/$K$28,0)*100 -> 0.24288502
B10: ='APPENDIX 9'!B10 -> CAPEX LIFE ASSURANCE COMPANY | C10: ='APPENDIX 9'!D10 -> 1211.99 | D10: ='APPENDIX 10'!D10 -> 238776.36 | E10: ='APPENDIX 15'!D10 -> 0 | F10: ='APPENDIX 16'!D10 -> 7382.0123 | G10: ='APPENDIX 11'!D10 -> 455455.79 | H10: ='APPENDIX 12'!D10 -> 19683.293 | I10: ='APPENDIX 14'!D10 -> 0 | J10: ='APPENDIX 13'!D10 -> 0 | K10: =SUM(C10:J10) -> 722509.44 | L10: =IFERROR(K10/$K$28,0)*100 -> 0.99157131
B11: ='APPENDIX 9'!B11 -> CIC LIFE ASSURANCE COMPANY | C11: ='APPENDIX 9'!D11 -> 359188.68 | D11: ='APPENDIX 10'!D11 -> 883273.85 | E11: ='APPENDIX 15'!D11 -> 0 | F11: ='APPENDIX 16'!D11 -> 933321.99 | G11: ='APPENDIX 11'!D11 -> 439602.9 | H11: ='APPENDIX 12'!D11 -> 2406625.8 | I11: ='APPENDIX 14'!D11 -> 0 | J11: ='APPENDIX 13'!D11 -> 0 | K11: =SUM(C11:J11) -> 5022013.2 | L11: =IFERROR(K11/$K$28,0)*100 -> 6.8922065
B12: ='APPENDIX 9'!B12 -> EQUITY LIFE ASSURANCE | C12: ='APPENDIX 9'!D12 -> 20.532 | D12: ='APPENDIX 10'!D12 -> 0 | E12: ='APPENDIX 15'!D12 -> 157458.4 | F12: ='APPENDIX 16'!D12 -> 571586.93 | G12: ='APPENDIX 11'!D12 -> 802065.89 | H12: ='APPENDIX 12'!D12 -> 299580.37 | I12: ='APPENDIX 14'!D12 -> 0 | J12: ='APPENDIX 13'!D12 -> 137370.67 | K12: =SUM(C12:J12) -> 1968082.8 | L12: =IFERROR(K12/$K$28,0)*100 -> 2.7009951
B13: ='APPENDIX 9'!B13 -> GA LIFE ASSURANCE COMPANY | C13: ='APPENDIX 9'!D13 -> 254366.31 | D13: ='APPENDIX 10'!D13 -> 0 | E13: ='APPENDIX 15'!D13 -> 533514.34 | F13: ='APPENDIX 16'!D13 -> 1575121 | G13: ='APPENDIX 11'!D13 -> 37309.409 | H13: ='APPENDIX 12'!D13 -> 604.017 | I13: ='APPENDIX 14'!D13 -> 0 | J13: ='APPENDIX 13'!D13 -> 0 | K13: =SUM(C13:J13) -> 2400915 | L13: =IFERROR(K13/$K$28,0)*100 -> 3.2950137
B14: ='APPENDIX 9'!B14 -> GEMINIA LIFE INSURANCE COMPANY | C14: ='APPENDIX 9'!D14 -> 19902.858 | D14: ='APPENDIX 10'!D14 -> 0 | E14: ='APPENDIX 15'!D14 -> 40881.616 | F14: ='APPENDIX 16'!D14 -> 679008.9 | G14: ='APPENDIX 11'!D14 -> 162677.36 | H14: ='APPENDIX 12'!D14 -> 145002.75 | I14: ='APPENDIX 14'!D14 -> 0 | J14: ='APPENDIX 13'!D14 -> 218435.74 | K14: =SUM(C14:J14) -> 1265909.2 | L14: =IFERROR(K14/$K$28,0)*100 -> 1.7373327
B15: ='APPENDIX 9'!B15 -> ICEA LION LIFE ASSURANCE | C15: ='APPENDIX 9'!D15 -> 4784466.4 | D15: ='APPENDIX 10'!D15 -> 954829.8 | E15: ='APPENDIX 15'!D15 -> 2222063.5 | F15: ='APPENDIX 16'!D15 -> 3091787.4 | G15: ='APPENDIX 11'!D15 -> 344659.46 | H15: ='APPENDIX 12'!D15 -> 52408.217 | I15: ='APPENDIX 14'!D15 -> 0 | J15: ='APPENDIX 13'!D15 -> 1022.42 | K15: =SUM(C15:J15) -> 11451237 | L15: =IFERROR(K15/$K$28,0)*100 -> 15.715668
B16: ='APPENDIX 9'!B16 -> JUBILEE LIFE INSURANCE | C16: ='APPENDIX 9'!D16 -> 1206031.6 | D16: ='APPENDIX 10'!D16 -> 534487.43 | E16: ='APPENDIX 15'!D16 -> 717634.84 | F16: ='APPENDIX 16'!D16 -> 4317417 | G16: ='APPENDIX 11'!D16 -> 521039.22 | H16: ='APPENDIX 12'!D16 -> 30943.158 | I16: ='APPENDIX 14'!D16 -> 0 | J16: ='APPENDIX 13'!D16 -> 1042386.9 | K16: =SUM(C16:J16) -> 8369940.2 | L16: =IFERROR(K16/$K$28,0)*100 -> 11.486898
B17: ='APPENDIX 9'!B17 -> KENINDIA ASSURANCE COMPANY | C17: ='APPENDIX 9'!D17 -> 201199.69 | D17: ='APPENDIX 10'!D17 -> 153279.18 | E17: ='APPENDIX 15'!D17 -> 14565.909 | F17: ='APPENDIX 16'!D17 -> 3659648.8 | G17: ='APPENDIX 11'!D17 -> 5263.353 | H17: ='APPENDIX 12'!D17 -> 4379.627 | I17: ='APPENDIX 14'!D17 -> 0 | J17: ='APPENDIX 13'!D17 -> 356442.07 | K17: =SUM(C17:J17) -> 4394778.6 | L17: =IFERROR(K17/$K$28,0)*100 -> 6.0313903
... B27: ='APPENDIX 9'!B27 -> THE MONARCH INSURANCE | C27: ='APPENDIX 9'!D27 -> 0 | D27: ='APPENDIX 10'!D27 -> 0 | E27: ='APPENDIX 15'!D27 -> 0 | F27: ='APPENDIX 16'!D27 -> 0 | G27: ='APPENDIX 11'!D27 -> 0 | H27: ='APPENDIX 12'!D27 -> 0 | I27: ='APPENDIX 14'!D27 -> 0 | J27: ='APPENDIX 13'!D27 -> 0 | K27: =SUM(C27:J27) -> 0 | L27: =IFERROR(K27/$K$28,0)*100 -> 0
B28: TOTAL | C28: =SUM(C6:C27) -> 14353581 | D28: =SUM(D6:D27) -> 5331679.3 | E28: =SUM(E6:E27) -> 6505671.2 | F28: =SUM(F6:F27) -> 21676213 | G28: =SUM(G6:G27) -> 8719984.2 | H28: =SUM(H6:H27) -> 5119694.8 | I28: =SUM(I6:I27) -> 0 | J28: =SUM(J6:J27) -> 11158278 | ... L28: =SUM(L6:L27) -> 100
B29: REINSURERS
B30: ='APPENDIX 9'!B30 -> CONTINENTAL REINSURANCE | C30: ='APPENDIX 9'!D30 -> 0 | D30: ='APPENDIX 10'!D30 -> 0 | E30: ='APPENDIX 15'!D30 -> 0 | F30: ='APPENDIX 16'!F30 -> 0 | G30: ='APPENDIX 11'!D30 -> 0 | H30: ='APPENDIX 12'!D30 -> 0 | I30: ='APPENDIX 14'!D30 -> 0 | J30: ='APPENDIX 13'!D30 -> 0 | K30: =SUM(C30:J30) -> 0 | L30: =IFERROR(K30/$K$33,0)*100 -> 0
B31: ='APPENDIX 9'!B31 -> EAST AFRICA REINSURANCE | C31: ='APPENDIX 9'!D31 -> 42625.761 | D31: ='APPENDIX 10'!D31 -> 0 | E31: ='APPENDIX 15'!D31 -> 0 | F31: ='APPENDIX 16'!F31 -> 0 | G31: ='APPENDIX 11'!D31 -> 214106.99 | H31: ='APPENDIX 12'!D31 -> 0 | I31: ='APPENDIX 14'!D31 -> 0 | J31: ='APPENDIX 13'!D31 -> 0 | K31: =SUM(C31:J31) -> 256732.76 | L31: =IFERROR(K31/$K$33,0)*100 -> 26.669977
B32: ='APPENDIX 9'!B32 -> KENYA REINSURANCE CORPORATION | C32: ='APPENDIX 9'!D32 -> 46959.677 | D32: ='APPENDIX 10'!D32 -> 0 | E32: ='APPENDIX 15'!D32 -> 0 | F32: ='APPENDIX 16'!F32 -> 0 | G32: ='APPENDIX 11'!D32 -> 658935.9 | H32: ='APPENDIX 12'!D32 -> 0 | I32: ='APPENDIX 14'!D32 -> 0 | J32: ='APPENDIX 13'!D32 -> 0 | K32: =SUM(C32:J32) -> 705895.58 | L32: =IFERROR(K32/$K$33,0)*100 -> 73.330023
B33: TOTAL | C33: =SUM(C30:C32) -> 89585.438 | D33: =SUM(D30:D32) -> 0 | E33: =SUM(E30:E32) -> 0 | F33: =SUM(F30:F32) -> 0 | G33: =SUM(G30:G32) -> 873042.89 | H33: =SUM(H30:H32) -> 0 | I33: =SUM(I30:I32) -> 0 | J33: =SUM(J30:J32) -> 0 | ... L33: =SUM(L30:L32) -> 100
B34: Amounts in Thousand Shillings

Sheet APPENDIX 8
B3: =_xlfn.CONCAT('Table of Contents'!B20,": ",'Table of Contents'!C20) -> APPENDIX 8: SUMMARY OF LONG TERM INSURANCE BUSINESS MARKET SHARE PER CLASS FOR THE PERIOD ENDED 31.03.2026
B4: Company | C4: Life Assurances | D4: Annuities | E4: Pensions | F4: Deposit Administration | G4: Group Life | H4: Group Credit | I4: Permanent Health | J4: Investments | K4: Total
B5: INSURERS
B6: ='APPENDIX 9'!B6 -> ABSA LIFE ASSURANCE | C6: =IFERROR(('APPENDIX 7'!C6/'APPENDIX 7'!C$28)*100,0) -> 11.973653 | D6: =IFERROR(('APPENDIX 7'!D6/'APPENDIX 7'!D$28)*100,0) -> 0 | E6: =IFERROR(('APPENDIX 7'!E6/'APPENDIX 7'!E$28)*100,0) -> 0 | F6: =IFERROR(('APPENDIX 7'!F6/'APPENDIX 7'!F$28)*100,0) -> 0 | G6: =IFERROR(('APPENDIX 7'!G6/'APPENDIX 7'!G$28)*100,0) -> 19.017957 | H6: =IFERROR(('APPENDIX 7'!H6/'APPENDIX 7'!H$28)*100,0) -> 8.3027218 | I6: =IFERROR(('APPENDIX 7'!I6/'APPENDIX 7'!I$28)*100,0) -> 0 | J6: =IFERROR(('APPENDIX 7'!J6/'APPENDIX 7'!J$28)*100,0) -> 0 | K6: =IFERROR(('APPENDIX 7'!K6/'APPENDIX 7'!K$28)*100,0) -> 5.2179778 | L6: =RANK(K6,$K$6:$K$27) -> 7 | M6: =COUNTIF(K6:K27,">5") -> 7
B7: ='APPENDIX 9'!B7 -> APA LIFE ASSURANCE COMPANY | C7: =IFERROR(('APPENDIX 7'!C7/'APPENDIX 7'!C$28)*100,0) -> 3.1026699 | D7: =IFERROR(('APPENDIX 7'!D7/'APPENDIX 7'!D$28)*100,0) -> 0.095882699 | E7: =IFERROR(('APPENDIX 7'!E7/'APPENDIX 7'!E$28)*100,0) -> 0.77229527 | F7: =IFERROR(('APPENDIX 7'!F7/'APPENDIX 7'!F$28)*100,0) -> 2.278482 | G7: =IFERROR(('APPENDIX 7'!G7/'APPENDIX 7'!G$28)*100,0) -> 7.0886355 | H7: =IFERROR(('APPENDIX 7'!H7/'APPENDIX 7'!H$28)*100,0) -> 7.2468817 | I7: =IFERROR(('APPENDIX 7'!I7/'APPENDIX 7'!I$28)*100,0) -> 0 | J7: =IFERROR(('APPENDIX 7'!J7/'APPENDIX 7'!J$28)*100,0) -> 32.435816 | K7: =IFERROR(('APPENDIX 7'!K7/'APPENDIX 7'!K$28)*100,0) -> 7.6895697 | L7: =RANK(K7,$K$6:$K$27) -> 4
B8: ='APPENDIX 9'!B8 -> BRITAM LIFE ASSURANCE | C8: =IFERROR(('APPENDIX 7'!C8/'APPENDIX 7'!C$28)*100,0) -> 20.553962 | D8: =IFERROR(('APPENDIX 7'!D8/'APPENDIX 7'!D$28)*100,0) -> 44.785088 | E8: =IFERROR(('APPENDIX 7'!E8/'APPENDIX 7'!E$28)*100,0) -> 19.826326 | F8: =IFERROR(('APPENDIX 7'!F8/'APPENDIX 7'!F$28)*100,0) -> 13.568885 | G8: =IFERROR(('APPENDIX 7'!G8/'APPENDIX 7'!G$28)*100,0) -> 3.9323703 | H8: =IFERROR(('APPENDIX 7'!H8/'APPENDIX 7'!H$28)*100,0) -> 4.0820131 | I8: =IFERROR(('APPENDIX 7'!I8/'APPENDIX 7'!I$28)*100,0) -> 0 | J8: =IFERROR(('APPENDIX 7'!J8/'APPENDIX 7'!J$28)*100,0) -> 40.576231 | K8: =IFERROR(('APPENDIX 7'!K8/'APPENDIX 7'!K$28)*100,0) -> 20.103699 | L8: =RANK(K8,$K$6:$K$27) -> 1
B9: ='APPENDIX 9'!B9 -> CANNON LIFE ASSURANCE (K) LIMITED | C9: =IFERROR(('APPENDIX 7'!C9/'APPENDIX 7'!C$28)*100,0) -> 0 | D9: =IFERROR(('APPENDIX 7'!D9/'APPENDIX 7'!D$28)*100,0) -> 0 | E9: =IFERROR(('APPENDIX 7'!E9/'APPENDIX 7'!E$28)*100,0) -> 0 | F9: =IFERROR(('APPENDIX 7'!F9/'APPENDIX 7'!F$28)*100,0) -> 0 | G9: =IFERROR(('APPENDIX 7'!G9/'APPENDIX 7'!G$28)*100,0) -> 1.9555025 | H9: =IFERROR(('APPENDIX 7'!H9/'APPENDIX 7'!H$28)*100,0) -> 0.012642419 | I9: =IFERROR(('APPENDIX 7'!I9/'APPENDIX 7'!I$28)*100,0) -> 0 | J9: =IFERROR(('APPENDIX 7'!J9/'APPENDIX 7'!J$28)*100,0) -> 0.052083831 | K9: =IFERROR(('APPENDIX 7'!K9/'APPENDIX 7'!K$28)*100,0) -> 0.24288502 | L9: =RANK(K9,$K$6:$K$27) -> 19
B10: ='APPENDIX 9'!B10 -> CAPEX LIFE ASSURANCE COMPANY | C10: =IFERROR(('APPENDIX 7'!C10/'APPENDIX 7'!C$28)*100,0) -> 0.0084438164 | D10: =IFERROR(('APPENDIX 7'!D10/'APPENDIX 7'!D$28)*100,0) -> 4.4784456 | E10: =IFERROR(('APPENDIX 7'!E10/'APPENDIX 7'!E$28)*100,0) -> 0 | F10: =IFERROR(('APPENDIX 7'!F10/'APPENDIX 7'!F$28)*100,0) -> 0.034055822 | G10: =IFERROR(('APPENDIX 7'!G10/'APPENDIX 7'!G$28)*100,0) -> 5.2231263 | H10: =IFERROR(('APPENDIX 7'!H10/'APPENDIX 7'!H$28)*100,0) -> 0.38446223 | I10: =IFERROR(('APPENDIX 7'!I10/'APPENDIX 7'!I$28)*100,0) -> 0 | J10: =IFERROR(('APPENDIX 7'!J10/'APPENDIX 7'!J$28)*100,0) -> 0 | K10: =IFERROR(('APPENDIX 7'!K10/'APPENDIX 7'!K$28)*100,0) -> 0.99157131 | L10: =RANK(K10,$K$6:$K$27) -> 17
B11: ='APPENDIX 9'!B11 -> CIC LIFE ASSURANCE COMPANY | C11: =IFERROR(('APPENDIX 7'!C11/'APPENDIX 7'!C$28)*100,0) -> 2.5024326 | D11: =IFERROR(('APPENDIX 7'!D11/'APPENDIX 7'!D$28)*100,0) -> 16.566523 | E11: =IFERROR(('APPENDIX 7'!E11/'APPENDIX 7'!E$28)*100,0) -> 0 | F11: =IFERROR(('APPENDIX 7'!F11/'APPENDIX 7'!F$28)*100,0) -> 4.3057429 | G11: =IFERROR(('APPENDIX 7'!G11/'APPENDIX 7'!G$28)*100,0) -> 5.0413267 | H11: =IFERROR(('APPENDIX 7'!H11/'APPENDIX 7'!H$28)*100,0) -> 47.007212 | I11: =IFERROR(('APPENDIX 7'!I11/'APPENDIX 7'!I$28)*100,0) -> 0 | J11: =IFERROR(('APPENDIX 7'!J11/'APPENDIX 7'!J$28)*100,0) -> 0 | K11: =IFERROR(('APPENDIX 7'!K11/'APPENDIX 7'!K$28)*100,0) -> 6.8922065 | L11: =RANK(K11,$K$6:$K$27) -> 5
B12: ='APPENDIX 9'!B12 -> EQUITY LIFE ASSURANCE | C12: =IFERROR(('APPENDIX 7'!C12/'APPENDIX 7'!C$28)*100,0) -> 0.00014304445 | D12: =IFERROR(('APPENDIX 7'!D12/'APPENDIX 7'!D$28)*100,0) -> 0 | E12: =IFERROR(('APPENDIX 7'!E12/'APPENDIX 7'!E$28)*100,0) -> 2.4203252 | F12: =IFERROR(('APPENDIX 7'!F12/'APPENDIX 7'!F$28)*100,0) -> 2.6369317 | G12: =IFERROR(('APPENDIX 7'!G12/'APPENDIX 7'!G$28)*100,0) -> 9.19802 | H12: =IFERROR(('APPENDIX 7'!H12/'APPENDIX 7'!H$28)*100,0) -> 5.8515279 | I12: =IFERROR(('APPENDIX 7'!I12/'APPENDIX 7'!I$28)*100,0) -> 0 | J12: =IFERROR(('APPENDIX 7'!J12/'APPENDIX 7'!J$28)*100,0) -> 1.2311099 | K12: =IFERROR(('APPENDIX 7'!K12/'APPENDIX 7'!K$28)*100,0) -> 2.7009951 | L12: =RANK(K12,$K$6:$K$27) -> 13
B13: ='APPENDIX 9'!B13 -> GA LIFE ASSURANCE COMPANY | C13: =IFERROR(('APPENDIX 7'!C13/'APPENDIX 7'!C$28)*100,0) -> 1.7721453 | D13: =IFERROR(('APPENDIX 7'!D13/'APPENDIX 7'!D$28)*100,0) -> 0 | E13: =IFERROR(('APPENDIX 7'!E13/'APPENDIX 7'!E$28)*100,0) -> 8.2007578 | F13: =IFERROR(('APPENDIX 7'!F13/'APPENDIX 7'!F$28)*100,0) -> 7.2665876 | G13: =IFERROR(('APPENDIX 7'!G13/'APPENDIX 7'!G$28)*100,0) -> 0.42786097 | H13: =IFERROR(('APPENDIX 7'!H13/'APPENDIX 7'!H$28)*100,0) -> 0.01179791 | I13: =IFERROR(('APPENDIX 7'!I13/'APPENDIX 7'!I$28)*100,0) -> 0 | J13: =IFERROR(('APPENDIX 7'!J13/'APPENDIX 7'!J$28)*100,0) -> 0 | K13: =IFERROR(('APPENDIX 7'!K13/'APPENDIX 7'!K$28)*100,0) -> 3.2950137 | L13: =RANK(K13,$K$6:$K$27) -> 10
B14: ='APPENDIX 9'!B14 -> GEMINIA LIFE INSURANCE COMPANY | C14: =IFERROR(('APPENDIX 7'!C14/'APPENDIX 7'!C$28)*100,0) -> 0.13866127 | D14: =IFERROR(('APPENDIX 7'!D14/'APPENDIX 7'!D$28)*100,0) -> 0 | E14: =IFERROR(('APPENDIX 7'!E14/'APPENDIX 7'!E$28)*100,0) -> 0.62839967 | F14: =IFERROR(('APPENDIX 7'!F14/'APPENDIX 7'!F$28)*100,0) -> 3.1325071 | G14: =IFERROR(('APPENDIX 7'!G14/'APPENDIX 7'!G$28)*100,0) -> 1.8655694 | H14: =IFERROR(('APPENDIX 7'!H14/'APPENDIX 7'!H$28)*100,0) -> 2.8322538 | I14: =IFERROR(('APPENDIX 7'!I14/'APPENDIX 7'!I$28)*100,0) -> 0 | J14: =IFERROR(('APPENDIX 7'!J14/'APPENDIX 7'!J$28)*100,0) -> 1.9576115 | K14: =IFERROR(('APPENDIX 7'!K14/'APPENDIX 7'!K$28)*100,0) -> 1.7373327 | L14: =RANK(K14,$K$6:$K$27) -> 15
B15: ='APPENDIX 9'!B15 -> ICEA LION LIFE ASSURANCE | C15: =IFERROR(('APPENDIX 7'!C15/'APPENDIX 7'!C$28)*100,0) -> 33.332912 | D15: =IFERROR(('APPENDIX 7'!D15/'APPENDIX 7'!D$28)*100,0) -> 17.908613 | E15: =IFERROR(('APPENDIX 7'!E15/'APPENDIX 7'!E$28)*100,0) -> 34.155792 | F15: =IFERROR(('APPENDIX 7'!F15/'APPENDIX 7'!F$28)*100,0) -> 14.263504 | G15: =IFERROR(('APPENDIX 7'!G15/'APPENDIX 7'!G$28)*100,0) -> 3.9525239 | H15: =IFERROR(('APPENDIX 7'!H15/'APPENDIX 7'!H$28)*100,0) -> 1.023659 | I15: =IFERROR(('APPENDIX 7'!I15/'APPENDIX 7'!I$28)*100,0) -> 0 | J15: =IFERROR(('APPENDIX 7'!J15/'APPENDIX 7'!J$28)*100,0) -> 0.0091628831 | K15: =IFERROR(('APPENDIX 7'!K15/'APPENDIX 7'!K$28)*100,0) -> 15.715668 | L15: =RANK(K15,$K$6:$K$27) -> 2
B16: ='APPENDIX 9'!B16 -> JUBILEE LIFE INSURANCE | C16: =IFERROR(('APPENDIX 7'!C16/'APPENDIX 7'!C$28)*100,0) -> 8.4023049 | D16: =IFERROR(('APPENDIX 7'!D16/'APPENDIX 7'!D$28)*100,0) -> 10.024748 | E16: =IFERROR(('APPENDIX 7'!E16/'APPENDIX 7'!E$28)*100,0) -> 11.030912 | F16: =IFERROR(('APPENDIX 7'!F16/'APPENDIX 7'!F$28)*100,0) -> 19.917765 | G16: =IFERROR(('APPENDIX 7'!G16/'APPENDIX 7'!G$28)*100,0) -> 5.9752313 | H16: =IFERROR(('APPENDIX 7'!H16/'APPENDIX 7'!H$28)*100,0) -> 0.60439457 | I16: =IFERROR(('APPENDIX 7'!I16/'APPENDIX 7'!I$28)*100,0) -> 0 | J16: =IFERROR(('APPENDIX 7'!J16/'APPENDIX 7'!J$28)*100,0) -> 9.3418258 | K16: =IFERROR(('APPENDIX 7'!K16/'APPENDIX 7'!K$28)*100,0) -> 11.486898 | L16: =RANK(K16,$K$6:$K$27) -> 3
B17: ='APPENDIX 9'!B17 -> KENINDIA ASSURANCE COMPANY | C17: =IFERROR(('APPENDIX 7'!C17/'APPENDIX 7'!C$28)*100,0) -> 1.4017386 | D17: =IFERROR(('APPENDIX 7'!D17/'APPENDIX 7'!D$28)*100,0) -> 2.8748763 | E17: =IFERROR(('APPENDIX 7'!E17/'APPENDIX 7'!E$28)*100,0) -> 0.22389556 | F17: =IFERROR(('APPENDIX 7'!F17/'APPENDIX 7'!F$28)*100,0) -> 16.883248 | G17: =IFERROR(('APPENDIX 7'!G17/'APPENDIX 7'!G$28)*100,0) -> 0.060359662 | H17: =IFERROR(('APPENDIX 7'!H17/'APPENDIX 7'!H$28)*100,0) -> 0.085544688 | I17: =IFERROR(('APPENDIX 7'!I17/'APPENDIX 7'!I$28)*100,0) -> 0 | J17: =IFERROR(('APPENDIX 7'!J17/'APPENDIX 7'!J$28)*100,0) -> 3.1944182 | K17: =IFERROR(('APPENDIX 7'!K17/'APPENDIX 7'!K$28)*100,0) -> 6.0313903 | L17: =RANK(K17,$K$6:$K$27) -> 6
B18: ='APPENDIX 9'!B18 -> KENYA ORIENT LIFE ASSURANCE | C18: =IFERROR(('APPENDIX 7'!C18/'APPENDIX 7'!C$28)*100,0) -> 0.11577438 | D18: =IFERROR(('APPENDIX 7'!D18/'APPENDIX 7'!D$28)*100,0) -> 1.799658 | E18: =IFERROR(('APPENDIX 7'!E18/'APPENDIX 7'!E$28)*100,0) -> 0.24436918 | F18: =IFERROR(('APPENDIX 7'!F18/'APPENDIX 7'!F$28)*100,0) -> 0.2822813 | G18: =IFERROR(('APPENDIX 7'!G18/'APPENDIX 7'!G$28)*100,0) -> 0.47890899 | H18: =IFERROR(('APPENDIX 7'!H18/'APPENDIX 7'!H$28)*100,0) -> 2.3480613 | I18: =IFERROR(('APPENDIX 7'!I18/'APPENDIX 7'!I$28)*100,0) -> 0 | J18: =IFERROR(('APPENDIX 7'!J18/'APPENDIX 7'!J$28)*100,0) -> 0 | K18: =IFERROR(('APPENDIX 7'!K18/'APPENDIX 7'!K$28)*100,0) -> 0.48257652 | L18: =RANK(K18,$K$6:$K$27) -> 18
... B27: ='APPENDIX 9'!B27 -> THE MONARCH INSURANCE | C27: =IFERROR(('APPENDIX 7'!C27/'APPENDIX 7'!C$28)*100,0) -> 0 | D27: =IFERROR(('APPENDIX 7'!D27/'APPENDIX 7'!D$28)*100,0) -> 0 | E27: =IFERROR(('APPENDIX 7'!E27/'APPENDIX 7'!E$28)*100,0) -> 0 | F27: =IFERROR(('APPENDIX 7'!F27/'APPENDIX 7'!F$28)*100,0) -> 0 | G27: =IFERROR(('APPENDIX 7'!G27/'APPENDIX 7'!G$28)*100,0) -> 0 | H27: =IFERROR(('APPENDIX 7'!H27/'APPENDIX 7'!H$28)*100,0) -> 0 | I27: =IFERROR(('APPENDIX 7'!I27/'APPENDIX 7'!I$28)*100,0) -> 0 | J27: =IFERROR(('APPENDIX 7'!J27/'APPENDIX 7'!J$28)*100,0) -> 0 | K27: =IFERROR(('APPENDIX 7'!K27/'APPENDIX 7'!K$28)*100,0) -> 0 | L27: =RANK(K27,$K$6:$K$27) -> 21
B28: TOTAL | C28: =SUM(C6:C27) -> 100 | D28: =SUM(D6:D27) -> 100 | E28: =SUM(E6:E27) -> 100 | F28: =SUM(F6:F27) -> 100 | G28: =SUM(G6:G27) -> 100 | H28: =SUM(H6:H27) -> 100 | I28: =SUM(I6:I27) -> 0 | J28: =SUM(J6:J27) -> 100 | K28: =SUM(K6:K27) -> 100
B29: REINSURERS
B30: ='APPENDIX 9'!B30 -> CONTINENTAL REINSURANCE | C30: =IFERROR(('APPENDIX 7'!C30/'APPENDIX 7'!C$33)*100,0) -> 0 | D30: =IFERROR(('APPENDIX 7'!D30/'APPENDIX 7'!D$33)*100,0) -> 0 | E30: =IFERROR(('APPENDIX 7'!E30/'APPENDIX 7'!E$33)*100,0) -> 0 | F30: =IFERROR(('APPENDIX 7'!F30/'APPENDIX 7'!F$33)*100,0) -> 0 | G30: =IFERROR(('APPENDIX 7'!G30/'APPENDIX 7'!G$33)*100,0) -> 0 | H30: =IFERROR(('APPENDIX 7'!H30/'APPENDIX 7'!H$33)*100,0) -> 0 | I30: =IFERROR(('APPENDIX 7'!I30/'APPENDIX 7'!I$33)*100,0) -> 0 | J30: =IFERROR(('APPENDIX 7'!J30/'APPENDIX 7'!J$33)*100,0) -> 0 | K30: =IFERROR(('APPENDIX 7'!K30/'APPENDIX 7'!K$33)*100,0) -> 0
B31: ='APPENDIX 9'!B31 -> EAST AFRICA REINSURANCE | C31: =IFERROR(('APPENDIX 7'!C31/'APPENDIX 7'!C$33)*100,0) -> 47.581127 | D31: =IFERROR(('APPENDIX 7'!D31/'APPENDIX 7'!D$33)*100,0) -> 0 | E31: =IFERROR(('APPENDIX 7'!E31/'APPENDIX 7'!E$33)*100,0) -> 0 | F31: =IFERROR(('APPENDIX 7'!F31/'APPENDIX 7'!F$33)*100,0) -> 0 | G31: =IFERROR(('APPENDIX 7'!G31/'APPENDIX 7'!G$33)*100,0) -> 24.524224 | H31: =IFERROR(('APPENDIX 7'!H31/'APPENDIX 7'!H$33)*100,0) -> 0 | I31: =IFERROR(('APPENDIX 7'!I31/'APPENDIX 7'!I$33)*100,0) -> 0 | J31: =IFERROR(('APPENDIX 7'!J31/'APPENDIX 7'!J$33)*100,0) -> 0 | K31: =IFERROR(('APPENDIX 7'!K31/'APPENDIX 7'!K$33)*100,0) -> 26.669977
B32: ='APPENDIX 9'!B32 -> KENYA REINSURANCE CORPORATION | C32: =IFERROR(('APPENDIX 7'!C32/'APPENDIX 7'!C$33)*100,0) -> 52.418873 | D32: =IFERROR(('APPENDIX 7'!D32/'APPENDIX 7'!D$33)*100,0) -> 0 | E32: =IFERROR(('APPENDIX 7'!E32/'APPENDIX 7'!E$33)*100,0) -> 0 | F32: =IFERROR(('APPENDIX 7'!F32/'APPENDIX 7'!F$33)*100,0) -> 0 | G32: =IFERROR(('APPENDIX 7'!G32/'APPENDIX 7'!G$33)*100,0) -> 75.475776 | H32: =IFERROR(('APPENDIX 7'!H32/'APPENDIX 7'!H$33)*100,0) -> 0 | I32: =IFERROR(('APPENDIX 7'!I32/'APPENDIX 7'!I$33)*100,0) -> 0 | J32: =IFERROR(('APPENDIX 7'!J32/'APPENDIX 7'!J$33)*100,0) -> 0 | K32: =IFERROR(('APPENDIX 7'!K32/'APPENDIX 7'!K$33)*100,0) -> 73.330023
B33: TOTAL | C33: =SUM(C30:C32) -> 100 | D33: =SUM(D30:D32) -> 0 | E33: =SUM(E30:E32) -> 0 | F33: =SUM(F30:F32) -> 0 | G33: =SUM(G30:G32) -> 100 | H33: =SUM(H30:H32) -> 0 | I33: =SUM(I30:I32) -> 0 | J33: =SUM(J30:J32) -> 0 | K33: =SUM(K30:K32) -> 100
B34: Figures in %

Sheet APPENDIX 9
B3: =_xlfn.CONCAT('Table of Contents'!B21,": ",'Table of Contents'!C21) -> APPENDIX 9: SUMMARY OF LIFE ASSURANCE BUSINESS REVENUE ACCOUNTS FOR THE PERIOD ENDED 31.03.2026
B4: Company | C4: Life Fund BF | D4: Gross Premium | E4: Net Premium | F4: Other (Fee) Income | G4: Total Benefits | H4: Claims | I4: Surrenders_x000D_ | J4: Bonuses Paid | K4: Annuities Paid | L4: Net Commisions | M4: Expense of Management | N4: Investment Income | O4: Investment Expenses | P4: Transfer To (From) P & L | Q4: Life Fund CF
B5: INSURERS
B6: ABSA LIFE ASSURANCE | C6: 15935686 | D6: 1718647.9 | E6: 1694300.2 | F6: 0 | G6: 495698.8 | H6: 495698.8 | I6: 0 | J6: 0 | K6: 0 | L6: 139210.64 | M6: 143241.68 | N6: 854380.45 | O6: 0 | P6: 0 | Q6: 17706215
B7: APA LIFE ASSURANCE COMPANY | C7: 1289607.9 | D7: 445344.23 | E7: 445344.23 | F7: 0 | G7: 74362.441 | H7: 74362.441 | I7: 0 | J7: 0 | K7: 0 | L7: 55778.137 | M7: 34279.59 | N7: 147628.15 | O7: 2137.6754 | P7: 0 | Q7: 1716022.5
B8: BRITAM LIFE ASSURANCE | C8: 50863133 | D8: 2950229.5 | E8: 2948514.8 | F8: 3860.959 | G8: 2369802.2 | H8: 2369802.2 | I8: 0 | J8: 0 | K8: 0 | L8: 460564.4 | M8: 645333.49 | N8: 2373230.5 | O8: 44613.843 | P8: 0 | Q8: 52668425
B9: CANNON LIFE ASSURANCE (K) LIMITED | C9: 0 | D9: 0 | E9: 0 | F9: 0 | G9: 0 | H9: 0 | I9: 0 | J9: 0 | K9: 0 | L9: 0 | M9: 0 | N9: 0 | O9: 0 | P9: 0 | Q9: 0
B10: CAPEX LIFE ASSURANCE COMPANY | C10: 31691.75 | D10: 1211.99 | E10: 1202.3752 | F10: 0 | G10: 1609.8215 | H10: 1609.8215 | I10: 0 | J10: 0 | K10: 0 | L10: 37.261218 | M10: 206.97127 | N10: 2.6724973 | O10: 0 | P10: 0 | Q10: 31042.744
B11: CIC LIFE ASSURANCE COMPANY | C11: 5251674.5 | D11: 359188.68 | E11: 355863.26 | F11: 0 | G11: 49455.364 | H11: 49455.364 | I11: 0 | J11: 0 | K11: 0 | L11: 50348.518 | M11: 115897.4 | N11: 0 | O11: 0 | P11: 0 | Q11: 5391836.4
B12: EQUITY LIFE ASSURANCE | C12: 0 | D12: 20.532 | E12: 20.532 | F12: 0 | G12: 0 | H12: 0 | I12: 0 | J12: 0 | K12: 0 | L12: 0 | M12: 43.269 | N12: 0 | O12: 0 | P12: 0 | Q12: -22.737
B13: GA LIFE ASSURANCE COMPANY | C13: 5879614.6 | D13: 254366.31 | E13: 254366.31 | F13: 0 | G13: 78603.742 | H13: 78603.742 | I13: 0 | J13: 0 | K13: 0 | L13: 2091.58 | M13: 70.527 | N13: 295872.79 | O13: 0 | P13: 0 | Q13: 6349087.9
B14: GEMINIA LIFE INSURANCE COMPANY | C14: 483491.08 | D14: 19902.858 | E14: 19902.858 | F14: 0 | G14: 8480.9176 | H14: 8480.9176 | I14: 0 | J14: 0 | K14: 0 | L14: 3900.7018 | M14: 4667.9513 | N14: 0 | O14: 0 | P14: 0 | Q14: 486344.36
B15: ICEA LION LIFE ASSURANCE | C15: 29002091 | D15: 4784466.4 | E15: 4761982.4 | F15: 0 | G15: 979048.58 | H15: 783737.66 | I15: 195310.92 | J15: 0 | K15: 0 | L15: 510191.91 | M15: 441276.59 | N15: 1227982.7 | O15: 0 | P15: 83982.894 | Q15: 32977556
B16: JUBILEE LIFE INSURANCE | C16: 14833573 | D16: 1206031.6 | E16: 1202398.2 | F16: 0 | G16: 1378586.9 | H16: 1378586.9 | I16: 0 | J16: 0 | K16: 0 | L16: 245637.62 | M16: 218035.66 | N16: 727044.28 | O16: 3871.4086 | P16: 0 | Q16: 14916884
B17: KENINDIA ASSURANCE COMPANY | C17: 3629622.7 | D17: 201199.69 | E17: 201199.69 | F17: 0 | G17: 222903.82 | H17: 222903.82 | I17: 0 | J17: 0 | K17: 0 | L17: 25625.356 | M17: 88031.97 | N17: 192688.49 | O17: 2862.004 | P17: 80121.93 | Q17: 3603965.8
... B27: THE MONARCH INSURANCE | C27: 0 | D27: 0 | E27: 0 | F27: 0 | G27: 0 | H27: 0 | I27: 0 | J27: 0 | K27: 0 | L27: 0 | M27: 0 | N27: 0 | O27: 0 | P27: 0 | Q27: 0
B28: TOTAL | C28: =SUM(C6:C27) -> 1.5525688e+08 | D28: =SUM(D6:D27) -> 14353581 | E28: =SUM(E6:E27) -> 14184571 | F28: =SUM(F6:F27) -> 6905.4622 | G28: =SUM(G6:G27) -> 7198299 | H28: =SUM(H6:H27) -> 7002988.1 | I28: =SUM(I6:I27) -> 195310.92 | J28: =SUM(J6:J27) -> 0 | ... Q28: =SUM(Q6:Q27) -> 1.6492788e+08
B29: REINSURERS
B30: CONTINENTAL REINSURANCE | C30: 0 | D30: 0 | E30: 0 | F30: 0 | G30: 0 | H30: 0 | I30: 0 | J30: 0 | K30: 0 | L30: 0 | M30: 0 | N30: 0 | O30: 0 | P30: 0 | Q30: 0
B31: EAST AFRICA REINSURANCE | C31: 249027.24 | D31: 42625.761 | E31: 38691.032 | F31: 0 | G31: 5983.5859 | H31: 5983.5859 | I31: 0 | J31: 0 | K31: 0 | L31: 9917.2048 | M31: 2497.2055 | N31: 6768.747 | O31: 320.38751 | P31: 0 | Q31: 275768.63
B32: KENYA REINSURANCE CORPORATION | C32: 521444.69 | D32: 46959.677 | E32: 46959.677 | F32: 0 | G32: 9027.1796 | H32: 9027.1796 | I32: 0 | J32: 0 | K32: 0 | L32: 12480.384 | M32: 1751.1394 | N32: 8034.576 | O32: 0 | P32: 0 | Q32: 553180.24
B33: TOTAL | C33: =SUM(C30:C32) -> 770471.93 | D33: =SUM(D30:D32) -> 89585.438 | E33: =SUM(E30:E32) -> 85650.709 | F33: =SUM(F30:F32) -> 0 | G33: =SUM(G30:G32) -> 15010.766 | H33: =SUM(H30:H32) -> 15010.766 | I33: =SUM(I30:I32) -> 0 | J33: =SUM(J30:J32) -> 0 | ... Q33: =SUM(Q30:Q32) -> 828948.88
B34: Amounts in Thousand Shillings

Sheet APPENDIX 10
B3: =_xlfn.CONCAT('Table of Contents'!B22,": ",'Table of Contents'!C22) -> APPENDIX 10: SUMMARY OF ANNUITIES BUSINESS REVENUE ACCOUNTS FOR THE PERIOD ENDED 31.03.2026
B4: Company | C4: Life Fund BF | D4: Gross Premium | E4: Net Premium | F4: Other (Fee) Income | G4: Total Benefits | H4: Claims | I4: Surrenders_x000D_ | J4: Bonuses Paid | K4: Annuities Paid | L4: Net Commisions | M4: Expense of Management | N4: Investment Income | O4: Investment Expenses | P4: Transfer To (From) P & L | Q4: Life Fund CF
B5: INSURERS
B6: ABSA LIFE ASSURANCE | C6: 0 | D6: 0 | E6: 0 | F6: 0 | G6: 0 | H6: 0 | I6: 0 | J6: 0 | K6: 0 | L6: 0 | M6: 0 | N6: 0 | O6: 0 | P6: 0 | Q6: 0
B7: APA LIFE ASSURANCE COMPANY | C7: 1023473.9 | D7: 5112.158 | E7: 5112.158 | F7: 0 | G7: 28078.109 | H7: 28078.109 | I7: 0 | J7: 0 | K7: 0 | L7: 0 | M7: 2809.692 | N7: 32414.934 | O7: -2807.1353 | P7: 0 | Q7: 1032920.3
B8: BRITAM LIFE ASSURANCE | C8: 33926903 | D8: 2387797.2 | E8: 2387797.2 | F8: 0 | G8: 1039680.5 | H8: 1039680.5 | I8: 0 | J8: 0 | K8: 0 | L8: 51433.348 | M8: 27910.899 | N8: 2517311 | O8: 11185.611 | P8: 0 | Q8: 37701801
B9: CANNON LIFE ASSURANCE (K) LIMITED | C9: 10223.214 | D9: 0 | E9: 0 | F9: 0 | G9: 327.37725 | H9: 327.37725 | I9: 0 | J9: 0 | K9: 0 | L9: 0 | M9: 0 | N9: 0 | O9: 0 | P9: 0 | Q9: 9895.8368
B10: CAPEX LIFE ASSURANCE COMPANY | C10: 872585.05 | D10: 238776.36 | E10: 238776.36 | F10: 0 | G10: 119540.48 | H10: 119540.48 | I10: 0 | J10: 0 | K10: 0 | L10: 10888.551 | M10: 40475.258 | N10: 522.63302 | O10: 0 | P10: 0 | Q10: 940979.75
B11: CIC LIFE ASSURANCE COMPANY | C11: 3176782.8 | D11: 883273.85 | E11: 883273.85 | F11: 0 | G11: 17613.784 | H11: 17613.784 | I11: 0 | J11: 0 | K11: 0 | L11: 17613.784 | M11: 18448.718 | N11: 0 | O11: 0 | P11: 0 | Q11: 4006380.4
B12: EQUITY LIFE ASSURANCE | C12: 0 | D12: 0 | E12: 0 | F12: 0 | G12: 0 | H12: 0 | I12: 0 | J12: 0 | K12: 0 | L12: 0 | M12: 0 | N12: 0 | O12: 0 | P12: 0 | Q12: 0
B13: GA LIFE ASSURANCE COMPANY | C13: 0 | D13: 0 | E13: 0 | F13: 0 | G13: 0 | H13: 0 | I13: 0 | J13: 0 | K13: 0 | L13: 0 | M13: 0 | N13: 0 | O13: 0 | P13: 0 | Q13: 0
B14: GEMINIA LIFE INSURANCE COMPANY | C14: 0 | D14: 0 | E14: 0 | F14: 0 | G14: 0 | H14: 0 | I14: 0 | J14: 0 | K14: 0 | L14: 0 | M14: 0 | N14: 0 | O14: 0 | P14: 0 | Q14: 0
B15: ICEA LION LIFE ASSURANCE | C15: 26623036 | D15: 954829.8 | E15: 954829.8 | F15: 0 | G15: 715256.33 | H15: 15542.353 | I15: 0 | J15: 0 | K15: 699713.98 | L15: 20640.717 | M15: 13741.53 | N15: 1965226.6 | O15: 0 | P15: 105000 | Q15: 28688454
B16: JUBILEE LIFE INSURANCE | C16: 15560174 | D16: 534487.43 | E16: 534487.43 | F16: 0 | G16: 474993.75 | H16: 474993.75 | I16: 0 | J16: 0 | K16: 0 | L16: 10955.292 | M16: 6419.9319 | N16: 1188420.8 | O16: 3421.296 | P16: 0 | Q16: 16787292
B17: KENINDIA ASSURANCE COMPANY | C17: 5697574 | D17: 153279.18 | E17: 153279.18 | F17: 0 | G17: 241319.75 | H17: 241319.75 | I17: 0 | J17: 0 | K17: 0 | L17: 2541.5836 | M17: 3618.0862 | N17: 192266.54 | O17: 0 | P17: 0 | Q17: 5795640.3
... B27: THE MONARCH INSURANCE | C27: 0 | D27: 0 | E27: 0 | F27: 0 | G27: 0 | H27: 0 | I27: 0 | J27: 0 | K27: 0 | L27: 0 | M27: 0 | N27: 0 | O27: 0 | P27: 0 | Q27: 0
B28: TOTAL | C28: =SUM(C6:C27) -> 1.1423434e+08 | D28: =SUM(D6:D27) -> 5331679.3 | E28: =SUM(E6:E27) -> 5331679.3 | F28: =SUM(F6:F27) -> 0 | G28: =SUM(G6:G27) -> 3484112.4 | H28: =SUM(H6:H27) -> 2780087.4 | I28: =SUM(I6:I27) -> 0 | J28: =SUM(J6:J27) -> 0 | ... Q28: =SUM(Q6:Q27) -> 1.2289993e+08
B29: REINSURERS
B30: CONTINENTAL REINSURANCE | C30: 0 | D30: 0 | E30: 0 | F30: 0 | G30: 0 | H30: 0 | I30: 0 | J30: 0 | K30: 0 | L30: 0 | M30: 0 | N30: 0 | O30: 0 | P30: 0 | Q30: 0
B31: EAST AFRICA REINSURANCE | C31: 0 | D31: 0 | E31: 0 | F31: 0 | G31: 0 | H31: 0 | I31: 0 | J31: 0 | K31: 0 | L31: 0 | M31: 0 | N31: 0 | O31: 0 | P31: 0 | Q31: 0
B32: KENYA REINSURANCE CORPORATION | C32: 0 | D32: 0 | E32: 0 | F32: 0 | G32: 0 | H32: 0 | I32: 0 | J32: 0 | K32: 0 | L32: 0 | M32: 0 | N32: 0 | O32: 0 | P32: 0 | Q32: 0
B33: TOTAL | C33: =SUM(C30:C32) -> 0 | D33: =SUM(D30:D32) -> 0 | E33: =SUM(E30:E32) -> 0 | F33: =SUM(F30:F32) -> 0 | G33: =SUM(G30:G32) -> 0 | H33: =SUM(H30:H32) -> 0 | I33: =SUM(I30:I32) -> 0 | J33: =SUM(J30:J32) -> 0 | ... Q33: =SUM(Q30:Q32) -> 0
B34: Amounts in Thousand Shillings

Sheet APPENDIX 11
B3: =_xlfn.CONCAT('Table of Contents'!B23,": ",'Table of Contents'!C23) -> APPENDIX 11: SUMMARY OF GROUP LIFE BUSINESS REVENUE ACCOUNTS FOR THE PERIOD ENDED 31.03.2026
B4: Company | C4: Life Fund BF | D4: Gross Premium | E4: Net Premium | F4: Other (Fee) Income | G4: Total Benefits | H4: Claims | I4: Surrenders_x000D_ | J4: Bonuses Paid | K4: Annuities Paid | L4: Net Commisions | M4: Expense of Management | N4: Investment Income | O4: Investment Expenses | P4: Transfer To (From) P & L | Q4: Life Fund CF
B5: INSURERS
B6: ABSA LIFE ASSURANCE | C6: 752012.9 | D6: 1658362.9 | E6: 844221.32 | F6: 0 | G6: 294109.42 | H6: 294109.42 | I6: 0 | J6: 0 | K6: 0 | L6: 41490.671 | M6: 108304.68 | N6: 18986.232 | O6: 0 | P6: 0 | Q6: 1171315.7
B7: APA LIFE ASSURANCE COMPANY | C7: 1082259 | D7: 618127.89 | E7: 349888.54 | F7: 0 | G7: 34584.837 | H7: 34584.837 | I7: 0 | J7: 0 | K7: 0 | L7: 178046.08 | M7: 37488.168 | N7: 18489.628 | O7: 2301.8041 | P7: 0 | Q7: 1198216.3
B8: BRITAM LIFE ASSURANCE | C8: 3419881.3 | D8: 342902.07 | E8: 355614.55 | F8: 0 | G8: 98900.16 | H8: 98900.16 | I8: 0 | J8: 0 | K8: 0 | L8: 15042.643 | M8: 123165.09 | N8: 172331.82 | O8: -251.478 | P8: 0 | Q8: 3710971.3
B9: CANNON LIFE ASSURANCE (K) LIMITED | C9: 270325.61 | D9: 170519.51 | E9: 93580.762 | F9: 0 | G9: -345.41753 | H9: -345.41753 | I9: 0 | J9: 0 | K9: 0 | L9: -1599.1086 | M9: 27614.515 | N9: 13838.786 | O9: 0 | P9: 0 | Q9: 352075.17
B10: CAPEX LIFE ASSURANCE COMPANY | C10: 108947.61 | D10: 455455.79 | E10: 385481.36 | F10: 0 | G10: 133767.95 | H10: 133767.95 | I10: 0 | J10: 0 | K10: 0 | L10: 69258.834 | M10: 59928.529 | N10: 783.40774 | O10: 0 | P10: 0 | Q10: 232257.06
B11: CIC LIFE ASSURANCE COMPANY | C11: 340340.32 | D11: 439602.9 | E11: 366388.13 | F11: 0 | G11: 224351.48 | H11: 224351.48 | I11: 0 | J11: 0 | K11: 0 | L11: 25584.151 | M11: 36426.456 | N11: 0 | O11: 0 | P11: 0 | Q11: 420366.36
B12: EQUITY LIFE ASSURANCE | C12: 1100244.7 | D12: 802065.89 | E12: 287062.41 | F12: 0 | G12: 8618.6508 | H12: 8618.6508 | I12: 0 | J12: 0 | K12: 0 | L12: -13730.222 | M12: 34871.123 | N12: 118036.12 | O12: 0 | P12: 0 | Q12: 1475583.7
B13: GA LIFE ASSURANCE COMPANY | C13: 49766.627 | D13: 37309.409 | E13: 986.861 | F13: 0 | G13: 1954.727 | H13: 1954.727 | I13: 0 | J13: 0 | K13: 0 | L13: -7319.255 | M13: 8866.942 | N13: 1508.897 | O13: 0 | P13: 0 | Q13: 48759.971
B14: GEMINIA LIFE INSURANCE COMPANY | C14: 734894.5 | D14: 162677.36 | E14: 162677.36 | F14: 0 | G14: 248061.02 | H14: 21267.923 | I14: 226793.1 | J14: 0 | K14: 0 | L14: 18069.036 | M14: 34852.522 | N14: 0 | O14: 0 | P14: 0 | Q14: 596589.27
B15: ICEA LION LIFE ASSURANCE | C15: 447081.27 | D15: 344659.46 | E15: 208243.38 | F15: 0 | G15: 45880.634 | H15: 45880.634 | I15: 0 | J15: 0 | K15: 0 | L15: -22137.967 | M15: 48306.458 | N15: 20644.889 | O15: 0 | P15: 13135.691 | Q15: 590784.72
B16: JUBILEE LIFE INSURANCE | C16: 333545.05 | D16: 521039.22 | E16: 312013.39 | F16: 0 | G16: 31783.981 | H16: 31783.981 | I16: 0 | J16: 0 | K16: 0 | L16: -13021.722 | M16: 37406.402 | N16: 49925.384 | O16: 354.21714 | P16: 0 | Q16: 638960.94
B17: KENINDIA ASSURANCE COMPANY | C17: 102782.14 | D17: 5263.353 | E17: -29575.27 | F17: 0 | G17: -9086.388 | H17: -9086.388 | I17: 0 | J17: 0 | K17: 0 | L17: -8222.2016 | M17: 4937.0786 | N17: 2143.8737 | O17: 0 | P17: 0 | Q17: 87722.259
... B27: THE MONARCH INSURANCE | C27: 0 | D27: 0 | E27: 0 | F27: 0 | G27: 0 | H27: 0 | I27: 0 | J27: 0 | K27: 0 | L27: 0 | M27: 0 | N27: 0 | O27: 0 | P27: 0 | Q27: 0
B28: TOTAL | C28: =SUM(C6:C27) -> 16414532 | D28: =SUM(D6:D27) -> 8719984.2 | E28: =SUM(E6:E27) -> 5605787.4 | F28: =SUM(F6:F27) -> -427505.25 | G28: =SUM(G6:G27) -> 1946947.5 | H28: =SUM(H6:H27) -> 1720154.4 | I28: =SUM(I6:I27) -> 226793.1 | J28: =SUM(J6:J27) -> 0 | ... Q28: =SUM(Q6:Q27) -> 18698772
B29: REINSURERS
B30: CONTINENTAL REINSURANCE | C30: 0 | D30: 0 | E30: 0 | F30: 0 | G30: 0 | H30: 0 | I30: 0 | J30: 0 | K30: 0 | L30: 0 | M30: 0 | N30: 0 | O30: 0 | P30: 0 | Q30: 0
B31: EAST AFRICA REINSURANCE | C31: 1315939.5 | D31: 214106.99 | E31: 161562.35 | F31: 0 | G31: 77356.337 | H31: 77356.337 | I31: 0 | J31: 0 | K31: 0 | L31: 36598.953 | M31: 22474.85 | N31: 60918.723 | O31: 2883.4876 | P31: 0 | Q31: 1399107
B32: KENYA REINSURANCE CORPORATION | C32: 8891836.7 | D32: 658935.9 | E32: 658935.9 | F32: 0 | G32: 466412.93 | H32: 466412.93 | I32: 0 | J32: 0 | K32: 0 | L32: 225726.58 | M32: 15760.258 | N32: 235287.71 | O32: 0 | P32: 0 | Q32: 9078160.5
B33: TOTAL | C33: =SUM(C30:C32) -> 10207776 | D33: =SUM(D30:D32) -> 873042.89 | E33: =SUM(E30:E32) -> 820498.25 | F33: =SUM(F30:F32) -> 0 | G33: =SUM(G30:G32) -> 543769.27 | H33: =SUM(H30:H32) -> 543769.27 | I33: =SUM(I30:I32) -> 0 | J33: =SUM(J30:J32) -> 0 | ... Q33: =SUM(Q30:Q32) -> 10477268
B34: Amounts in Thousand Shillings

Sheet APPENDIX 12
B3: =_xlfn.CONCAT('Table of Contents'!B24,": ",'Table of Contents'!C24) -> APPENDIX 12: SUMMARY OF GROUP CREDIT BUSINESS REVENUE ACCOUNTS FOR THE PERIOD ENDED 31.03.2026
B4: Company | C4: Life Fund BF | D4: Gross Premium | E4: Net Premium | F4: Other (Fee) Income | G4: Total Benefits | H4: Claims | I4: Surrenders_x000D_ | J4: Bonuses Paid | K4: Annuities Paid | L4: Net Commisions | M4: Expense of Management | N4: Investment Income | O4: Investment Expenses | P4: Transfer To (From) P & L | Q4: Life Fund CF
B5: INSURERS
B6: ABSA LIFE ASSURANCE | C6: 1999808.3 | D6: 425074.02 | E6: 328214.88 | F6: 0 | G6: 78578.032 | H6: 78578.032 | I6: 0 | J6: 0 | K6: 0 | L6: 241816.11 | M6: 97823.586 | N6: 75944.929 | O6: 0 | P6: 0 | Q6: 1985750.3
B7: APA LIFE ASSURANCE COMPANY | C7: 741624.36 | D7: 371018.23 | E7: 319402.76 | F7: 0 | G7: 131431.56 | H7: 131431.56 | I7: 0 | J7: 0 | K7: 0 | L7: 87465.527 | M7: 25441.111 | N7: 12507.829 | O7: 0 | P7: 0 | Q7: 829196.75
B8: BRITAM LIFE ASSURANCE | C8: -217453.39 | D8: 208986.61 | E8: 198163.62 | F8: 0 | G8: 63198.753 | H8: 63198.753 | I8: 0 | J8: 0 | K8: 0 | L8: 14078.675 | M8: 84044.855 | N8: 46563.81 | O8: 716.894 | P8: 0 | Q8: -134765.13
B9: CANNON LIFE ASSURANCE (K) LIMITED | C9: -2118.5585 | D9: 647.2533 | E9: 612.1133 | F9: 0 | G9: 2071.617 | H9: 2071.617 | I9: 0 | J9: 0 | K9: 0 | L9: 42.754566 | M9: 4132.709 | N9: 2071.073 | O9: 0 | P9: 0 | Q9: -5682.4527
B10: CAPEX LIFE ASSURANCE COMPANY | C10: 12706.818 | D10: 19683.293 | E10: 12290.533 | F10: 0 | G10: 15294.923 | H10: 15294.923 | I10: 0 | J10: 0 | K10: 0 | L10: 1340.5275 | M10: 3336.5379 | N10: 43.082737 | O10: 0 | P10: 0 | Q10: 5068.4457
B11: CIC LIFE ASSURANCE COMPANY | C11: 9038374.4 | D11: 2406625.8 | E11: 1871233.2 | F11: 0 | G11: 0 | H11: 0 | I11: 0 | J11: 0 | K11: 0 | L11: 408304.75 | M11: 341487.98 | N11: 0 | O11: 0 | P11: 0 | Q11: 10159815
B12: EQUITY LIFE ASSURANCE | C12: 8566374.9 | D12: 299580.37 | E12: 326365.21 | F12: 0 | G12: 69640.58 | H12: 69640.58 | I12: 0 | J12: 0 | K12: 0 | L12: 2629.3746 | M12: 136208.26 | N12: 244484.59 | O12: 0 | P12: 0 | Q12: 8928746.4
B13: GA LIFE ASSURANCE COMPANY | C13: 1820.1959 | D13: 604.017 | E13: 9.465 | F13: 0 | G13: 82.134 | H13: 82.134 | I13: 0 | J13: 0 | K13: 0 | L13: -169.448 | M13: 143.551 | N13: 24.428 | O13: 0 | P13: 0 | Q13: 1797.8519
B14: GEMINIA LIFE INSURANCE COMPANY | C14: 570152.99 | D14: 145002.75 | E14: 108230.4 | F14: 0 | G14: 147845.53 | H14: 17272.634 | I14: 130572.9 | J14: 0 | K14: 0 | L14: 11057.21 | M14: 24072.609 | N14: 0 | O14: 0 | P14: 0 | Q14: 495408.04
B15: ICEA LION LIFE ASSURANCE | C15: 92416.921 | D15: 52408.217 | E15: 41527.131 | F15: 0 | G15: 50781.87 | H15: 50781.87 | I15: 0 | J15: 0 | K15: 0 | L15: 1549.434 | M15: 38362.044 | N15: 9668.191 | O15: 0 | P15: 7881.415 | Q15: 45037.48
B16: JUBILEE LIFE INSURANCE | C16: 361051.35 | D16: 30943.158 | E16: 7081.0532 | F16: 0 | G16: 4204.1562 | H16: 4204.1562 | I16: 0 | J16: 0 | K16: 0 | L16: 416.14887 | M16: 6385.5787 | N16: 10586.872 | O16: 78.239274 | P16: 0 | Q16: 367635.16
B17: KENINDIA ASSURANCE COMPANY | C17: 6147.6034 | D17: 4379.627 | E17: 4020.257 | F17: 0 | G17: 737.088 | H17: 737.088 | I17: 0 | J17: 0 | K17: 0 | L17: 312.895 | M17: 4108.1354 | N17: 128.22932 | O17: 0 | P17: 0 | Q17: 5137.9713
... B27: THE MONARCH INSURANCE | C27: 0 | D27: 0 | E27: 0 | F27: 0 | G27: 0 | H27: 0 | I27: 0 | J27: 0 | K27: 0 | L27: 0 | M27: 0 | N27: 0 | O27: 0 | P27: 0 | Q27: 0
B28: TOTAL | C28: =SUM(C6:C27) -> 25637663 | D28: =SUM(D6:D27) -> 5119694.8 | E28: =SUM(E6:E27) -> 4114575.7 | F28: =SUM(F6:F27) -> 0 | G28: =SUM(G6:G27) -> 884642.41 | H28: =SUM(H6:H27) -> 754069.51 | I28: =SUM(I6:I27) -> 130572.9 | J28: =SUM(J6:J27) -> 0 | ... Q28: =SUM(Q6:Q27) -> 27501710
B29: REINSURERS
B30: CONTINENTAL REINSURANCE | C30: 0 | D30: 0 | E30: 0 | F30: 0 | G30: 0 | H30: 0 | I30: 0 | J30: 0 | K30: 0 | L30: 0 | M30: 0 | N30: 0 | O30: 0 | P30: 0 | Q30: 0
B31: EAST AFRICA REINSURANCE | C31: 0 | D31: 0 | E31: 0 | F31: 0 | G31: 0 | H31: 0 | I31: 0 | J31: 0 | K31: 0 | L31: 0 | M31: 0 | N31: 0 | O31: 0 | P31: 0 | Q31: 0
B32: KENYA REINSURANCE CORPORATION | C32: 0 | D32: 0 | E32: 0 | F32: 0 | G32: 0 | H32: 0 | I32: 0 | J32: 0 | K32: 0 | L32: 0 | M32: 0 | N32: 0 | O32: 0 | P32: 0 | Q32: 0
B33: TOTAL | C33: =SUM(C30:C32) -> 0 | D33: =SUM(D30:D32) -> 0 | E33: =SUM(E30:E32) -> 0 | F33: =SUM(F30:F32) -> 0 | G33: =SUM(G30:G32) -> 0 | H33: =SUM(H30:H32) -> 0 | I33: =SUM(I30:I32) -> 0 | J33: =SUM(J30:J32) -> 0 | ... Q33: =SUM(Q30:Q32) -> 0
B34: Amounts in Thousand Shillings

Sheet APPENDIX 13
B3: =_xlfn.CONCAT('Table of Contents'!B25,": ",'Table of Contents'!C25) -> APPENDIX 13: SUMMARY OF INVESTMENTS BUSINESS REVENUE ACCOUNTS FOR THE PERIOD ENDED 31.03.2026
B4: Company | C4: Life Fund BF | D4: Gross Premium | E4: Net Premium | F4: Other (Fee) Income | G4: Total Benefits | H4: Claims | I4: Surrenders_x000D_ | J4: Bonuses Paid | K4: Annuities Paid | L4: Net Commisions | M4: Expense of Management | N4: Investment Income | O4: Investment Expenses | P4: Transfer To (From) P & L | Q4: Life Fund CF
B5: INSURERS
B6: =LINKED!B6 -> ABSA LIFE ASSURANCE | C6: =+LINKED!C6+'NON-LINKED'!C6 -> 0 | D6: =+LINKED!D6+'NON-LINKED'!D6 -> 0 | E6: =+LINKED!E6+'NON-LINKED'!E6 -> 0 | F6: =+LINKED!F6+'NON-LINKED'!F6 -> 0 | G6: =+LINKED!G6+'NON-LINKED'!G6 -> 0 | H6: =+LINKED!H6+'NON-LINKED'!H6 -> 0 | I6: =+LINKED!I6+'NON-LINKED'!I6 -> 0 | J6: =+LINKED!J6+'NON-LINKED'!J6 -> 0 | ... Q6: =+LINKED!Q6+'NON-LINKED'!Q6 -> 0
B7: =LINKED!B7 -> APA LIFE ASSURANCE COMPANY | C7: =+LINKED!C7+'NON-LINKED'!C7 -> 10690089 | D7: =+LINKED!D7+'NON-LINKED'!D7 -> 3619278.6 | E7: =+LINKED!E7+'NON-LINKED'!E7 -> 3619278.6 | F7: =+LINKED!F7+'NON-LINKED'!F7 -> 0 | G7: =+LINKED!G7+'NON-LINKED'!G7 -> 29416.598 | H7: =+LINKED!H7+'NON-LINKED'!H7 -> 29416.598 | I7: =+LINKED!I7+'NON-LINKED'!I7 -> 0 | J7: =+LINKED!J7+'NON-LINKED'!J7 -> 0 | ... Q7: =+LINKED!Q7+'NON-LINKED'!Q7 -> 14664240
B8: =LINKED!B8 -> BRITAM LIFE ASSURANCE | C8: =+LINKED!C8+'NON-LINKED'!C8 -> 18319650 | D8: =+LINKED!D8+'NON-LINKED'!D8 -> 4527608.8 | E8: =+LINKED!E8+'NON-LINKED'!E8 -> 4527608.8 | F8: =+LINKED!F8+'NON-LINKED'!F8 -> 0 | G8: =+LINKED!G8+'NON-LINKED'!G8 -> 1924103.8 | H8: =+LINKED!H8+'NON-LINKED'!H8 -> 1924103.8 | I8: =+LINKED!I8+'NON-LINKED'!I8 -> 0 | J8: =+LINKED!J8+'NON-LINKED'!J8 -> 0 | ... Q8: =+LINKED!Q8+'NON-LINKED'!Q8 -> 21596179
B9: =LINKED!B9 -> CANNON LIFE ASSURANCE (K) LIMITED | C9: =+LINKED!C9+'NON-LINKED'!C9 -> 538626.19 | D9: =+LINKED!D9+'NON-LINKED'!D9 -> 5811.6588 | E9: =+LINKED!E9+'NON-LINKED'!E9 -> 5577.2198 | F9: =+LINKED!F9+'NON-LINKED'!F9 -> 0 | G9: =+LINKED!G9+'NON-LINKED'!G9 -> 11544.84 | H9: =+LINKED!H9+'NON-LINKED'!H9 -> 11544.84 | I9: =+LINKED!I9+'NON-LINKED'!I9 -> 0 | J9: =+LINKED!J9+'NON-LINKED'!J9 -> 0 | ... Q9: =+LINKED!Q9+'NON-LINKED'!Q9 -> 520956.72
B10: =LINKED!B10 -> CAPEX LIFE ASSURANCE COMPANY | C10: =+LINKED!C10+'NON-LINKED'!C10 -> 0 | D10: =+LINKED!D10+'NON-LINKED'!D10 -> 0 | E10: =+LINKED!E10+'NON-LINKED'!E10 -> 0 | F10: =+LINKED!F10+'NON-LINKED'!F10 -> 0 | G10: =+LINKED!G10+'NON-LINKED'!G10 -> 0 | H10: =+LINKED!H10+'NON-LINKED'!H10 -> 0 | I10: =+LINKED!I10+'NON-LINKED'!I10 -> 0 | J10: =+LINKED!J10+'NON-LINKED'!J10 -> 0 | ... Q10: =+LINKED!Q10+'NON-LINKED'!Q10 -> 0
B11: =LINKED!B11 -> CIC LIFE ASSURANCE COMPANY | C11: =+LINKED!C11+'NON-LINKED'!C11 -> 0 | D11: =+LINKED!D11+'NON-LINKED'!D11 -> 0 | E11: =+LINKED!E11+'NON-LINKED'!E11 -> 0 | F11: =+LINKED!F11+'NON-LINKED'!F11 -> 0 | G11: =+LINKED!G11+'NON-LINKED'!G11 -> 0 | H11: =+LINKED!H11+'NON-LINKED'!H11 -> 0 | I11: =+LINKED!I11+'NON-LINKED'!I11 -> 0 | J11: =+LINKED!J11+'NON-LINKED'!J11 -> 0 | ... Q11: =+LINKED!Q11+'NON-LINKED'!Q11 -> 0
B12: =LINKED!B12 -> EQUITY LIFE ASSURANCE | C12: =+LINKED!C12+'NON-LINKED'!C12 -> 321400.65 | D12: =+LINKED!D12+'NON-LINKED'!D12 -> 137370.67 | E12: =+LINKED!E12+'NON-LINKED'!E12 -> 137370.67 | F12: =+LINKED!F12+'NON-LINKED'!F12 -> 0 | G12: =+LINKED!G12+'NON-LINKED'!G12 -> 0 | H12: =+LINKED!H12+'NON-LINKED'!H12 -> 0 | I12: =+LINKED!I12+'NON-LINKED'!I12 -> 0 | J12: =+LINKED!J12+'NON-LINKED'!J12 -> 0 | ... Q12: =+LINKED!Q12+'NON-LINKED'!Q12 -> 470279.59
B13: =LINKED!B13 -> GA LIFE ASSURANCE COMPANY | C13: =+LINKED!C13+'NON-LINKED'!C13 -> 0 | D13: =+LINKED!D13+'NON-LINKED'!D13 -> 0 | E13: =+LINKED!E13+'NON-LINKED'!E13 -> 0 | F13: =+LINKED!F13+'NON-LINKED'!F13 -> 0 | G13: =+LINKED!G13+'NON-LINKED'!G13 -> 0 | H13: =+LINKED!H13+'NON-LINKED'!H13 -> 0 | I13: =+LINKED!I13+'NON-LINKED'!I13 -> 0 | J13: =+LINKED!J13+'NON-LINKED'!J13 -> 0 | ... Q13: =+LINKED!Q13+'NON-LINKED'!Q13 -> 0
B14: =LINKED!B14 -> GEMINIA LIFE INSURANCE COMPANY | C14: =+LINKED!C14+'NON-LINKED'!C14 -> 534404.75 | D14: =+LINKED!D14+'NON-LINKED'!D14 -> 218435.74 | E14: =+LINKED!E14+'NON-LINKED'!E14 -> 218435.74 | F14: =+LINKED!F14+'NON-LINKED'!F14 -> 0 | G14: =+LINKED!G14+'NON-LINKED'!G14 -> 86060.755 | H14: =+LINKED!H14+'NON-LINKED'!H14 -> 0 | I14: =+LINKED!I14+'NON-LINKED'!I14 -> 86060.755 | J14: =+LINKED!J14+'NON-LINKED'!J14 -> 0 | ... Q14: =+LINKED!Q14+'NON-LINKED'!Q14 -> 660896.16
B15: =LINKED!B15 -> ICEA LION LIFE ASSURANCE | C15: =+LINKED!C15+'NON-LINKED'!C15 -> 592627.12 | D15: =+LINKED!D15+'NON-LINKED'!D15 -> 1022.42 | E15: =+LINKED!E15+'NON-LINKED'!E15 -> 1022.42 | F15: =+LINKED!F15+'NON-LINKED'!F15 -> 0 | G15: =+LINKED!G15+'NON-LINKED'!G15 -> 3679.946 | H15: =+LINKED!H15+'NON-LINKED'!H15 -> 0 | I15: =+LINKED!I15+'NON-LINKED'!I15 -> 3679.946 | J15: =+LINKED!J15+'NON-LINKED'!J15 -> 0 | ... Q15: =+LINKED!Q15+'NON-LINKED'!Q15 -> 533995.78
B16: =LINKED!B16 -> JUBILEE LIFE INSURANCE | C16: =+LINKED!C16+'NON-LINKED'!C16 -> 2775734.8 | D16: =+LINKED!D16+'NON-LINKED'!D16 -> 1042386.9 | E16: =+LINKED!E16+'NON-LINKED'!E16 -> 1042386.9 | F16: =+LINKED!F16+'NON-LINKED'!F16 -> 0 | G16: =+LINKED!G16+'NON-LINKED'!G16 -> 0 | H16: =+LINKED!H16+'NON-LINKED'!H16 -> 0 | I16: =+LINKED!I16+'NON-LINKED'!I16 -> 0 | J16: =+LINKED!J16+'NON-LINKED'!J16 -> 0 | ... Q16: =+LINKED!Q16+'NON-LINKED'!Q16 -> 3794065.4
B17: =LINKED!B17 -> KENINDIA ASSURANCE COMPANY | C17: =+LINKED!C17+'NON-LINKED'!C17 -> 18749372 | D17: =+LINKED!D17+'NON-LINKED'!D17 -> 356442.07 | E17: =+LINKED!E17+'NON-LINKED'!E17 -> 356442.07 | F17: =+LINKED!F17+'NON-LINKED'!F17 -> 0 | G17: =+LINKED!G17+'NON-LINKED'!G17 -> 674501.43 | H17: =+LINKED!H17+'NON-LINKED'!H17 -> 674501.43 | I17: =+LINKED!I17+'NON-LINKED'!I17 -> 0 | J17: =+LINKED!J17+'NON-LINKED'!J17 -> 0 | ... Q17: =+LINKED!Q17+'NON-LINKED'!Q17 -> 19071909
... B27: =LINKED!B27 -> THE MONARCH INSURANCE | C27: =+LINKED!C27+'NON-LINKED'!C27 -> 0 | D27: =+LINKED!D27+'NON-LINKED'!D27 -> 0 | E27: =+LINKED!E27+'NON-LINKED'!E27 -> 0 | F27: =+LINKED!F27+'NON-LINKED'!F27 -> 0 | G27: =+LINKED!G27+'NON-LINKED'!G27 -> 0 | H27: =+LINKED!H27+'NON-LINKED'!H27 -> 0 | I27: =+LINKED!I27+'NON-LINKED'!I27 -> 0 | J27: =+LINKED!J27+'NON-LINKED'!J27 -> 0 | ... Q27: =+LINKED!Q27+'NON-LINKED'!Q27 -> 0
B28: TOTAL | C28: =SUM(C6:C27) -> 68373921 | D28: =SUM(D6:D27) -> 11158278 | E28: =SUM(E6:E27) -> 11153948 | F28: =SUM(F6:F27) -> -2386.9233 | G28: =SUM(G6:G27) -> 3766861.5 | H28: =SUM(H6:H27) -> 3677120.8 | I28: =SUM(I6:I27) -> 89740.701 | J28: =SUM(J6:J27) -> 0 | ... Q28: =SUM(Q6:Q27) -> 77679770
B29: REINSURERS
B30: =LINKED!B30 -> CONTINENTAL REINSURANCE | C30: =+LINKED!C30+'NON-LINKED'!C30 -> 0 | D30: =+LINKED!D30+'NON-LINKED'!D30 -> 0 | E30: =+LINKED!E30+'NON-LINKED'!E30 -> 0 | F30: =+LINKED!F30+'NON-LINKED'!F30 -> 0 | G30: =+LINKED!G30+'NON-LINKED'!G30 -> 0 | H30: =+LINKED!H30+'NON-LINKED'!H30 -> 0 | I30: =+LINKED!I30+'NON-LINKED'!I30 -> 0 | J30: =+LINKED!J30+'NON-LINKED'!J30 -> 0 | ... Q30: =+LINKED!Q30+'NON-LINKED'!Q30 -> 0
B31: =LINKED!B31 -> EAST AFRICA REINSURANCE | C31: =+LINKED!C31+'NON-LINKED'!C31 -> 0 | D31: =+LINKED!D31+'NON-LINKED'!D31 -> 0 | E31: =+LINKED!E31+'NON-LINKED'!E31 -> 0 | F31: =+LINKED!F31+'NON-LINKED'!F31 -> 0 | G31: =+LINKED!G31+'NON-LINKED'!G31 -> 0 | H31: =+LINKED!H31+'NON-LINKED'!H31 -> 0 | I31: =+LINKED!I31+'NON-LINKED'!I31 -> 0 | J31: =+LINKED!J31+'NON-LINKED'!J31 -> 0 | ... Q31: =+LINKED!Q31+'NON-LINKED'!Q31 -> 0
B32: =LINKED!B32 -> KENYA REINSURANCE CORPORATION | C32: =+LINKED!C32+'NON-LINKED'!C32 -> 0 | D32: =+LINKED!D32+'NON-LINKED'!D32 -> 0 | E32: =+LINKED!E32+'NON-LINKED'!E32 -> 0 | F32: =+LINKED!F32+'NON-LINKED'!F32 -> 0 | G32: =+LINKED!G32+'NON-LINKED'!G32 -> 0 | H32: =+LINKED!H32+'NON-LINKED'!H32 -> 0 | I32: =+LINKED!I32+'NON-LINKED'!I32 -> 0 | J32: =+LINKED!J32+'NON-LINKED'!J32 -> 0 | ... Q32: =+LINKED!Q32+'NON-LINKED'!Q32 -> 0
B33: TOTAL | C33: =SUM(C30:C32) -> 0 | D33: =SUM(D30:D32) -> 0 | E33: =SUM(E30:E32) -> 0 | F33: =SUM(F30:F32) -> 0 | G33: =SUM(G30:G32) -> 0 | H33: =SUM(H30:H32) -> 0 | I33: =SUM(I30:I32) -> 0 | J33: =SUM(J30:J32) -> 0 | ... Q33: =SUM(Q30:Q32) -> 0
B34: Amounts in Thousand Shillings

Sheet LINKED
B3: =_xlfn.CONCAT("LINKED INVESTMENTS"," ",Details!F18) -> LINKED INVESTMENTS 31.03.2026
B4: Company | C4: Life Fund BF | D4: Gross Premium | E4: Net Premium | F4: Other (Fee) Income | G4: Total Benefits | H4: Claims | I4: Surrenders_x000D_ | J4: Bonuses Paid | K4: Annuities Paid | L4: Net Commisions | M4: Expense of Management | N4: Investment Income | O4: Investment Expenses | P4: Transfer To (From) P & L | Q4: Life Fund CF
B5: INSURERS
B6: ABSA LIFE ASSURANCE | C6: 0 | D6: 0 | E6: 0 | F6: 0 | G6: 0 | H6: 0 | I6: 0 | J6: 0 | K6: 0 | L6: 0 | M6: 0 | N6: 0 | O6: 0 | P6: 0 | Q6: 0
B7: APA LIFE ASSURANCE COMPANY | C7: 0 | D7: 0 | E7: 0 | F7: 0 | G7: 0 | H7: 0 | I7: 0 | J7: 0 | K7: 0 | L7: 0 | M7: 0 | N7: 0 | O7: 0 | P7: 0 | Q7: 0
B8: BRITAM LIFE ASSURANCE | C8: 18319650 | D8: 4527608.8 | E8: 4527608.8 | F8: 0 | G8: 1924103.8 | H8: 1924103.8 | I8: 0 | J8: 0 | K8: 0 | L8: 11831.134 | M8: 33730.454 | N8: 723340.7 | O8: 4755.06 | P8: 0 | Q8: 21596179
B9: CANNON LIFE ASSURANCE (K) LIMITED | C9: 538626.19 | D9: 5811.6588 | E9: 5577.2198 | F9: 0 | G9: 11544.84 | H9: 11544.84 | I9: 0 | J9: 0 | K9: 0 | L9: -245.62676 | M9: 23949.657 | N9: 12002.174 | O9: 0 | P9: 0 | Q9: 520956.72
B10: CAPEX LIFE ASSURANCE COMPANY | C10: 0 | D10: 0 | E10: 0 | F10: 0 | G10: 0 | H10: 0 | I10: 0 | J10: 0 | K10: 0 | L10: 0 | M10: 0 | N10: 0 | O10: 0 | P10: 0 | Q10: 0
B11: CIC LIFE ASSURANCE COMPANY | C11: 0 | D11: 0 | E11: 0 | F11: 0 | G11: 0 | H11: 0 | I11: 0 | J11: 0 | K11: 0 | L11: 0 | M11: 0 | N11: 0 | O11: 0 | P11: 0 | Q11: 0
B12: EQUITY LIFE ASSURANCE | C12: 0 | D12: 0 | E12: 0 | F12: 0 | G12: 0 | H12: 0 | I12: 0 | J12: 0 | K12: 0 | L12: 0 | M12: 0 | N12: 0 | O12: 0 | P12: 0 | Q12: 0
B13: GA LIFE ASSURANCE COMPANY | C13: 0 | D13: 0 | E13: 0 | F13: 0 | G13: 0 | H13: 0 | I13: 0 | J13: 0 | K13: 0 | L13: 0 | M13: 0 | N13: 0 | O13: 0 | P13: 0 | Q13: 0
B14: GEMINIA LIFE INSURANCE COMPANY | C14: 0 | D14: 0 | E14: 0 | F14: 0 | G14: 0 | H14: 0 | I14: 0 | J14: 0 | K14: 0 | L14: 0 | M14: 0 | N14: 0 | O14: 0 | P14: 0 | Q14: 0
B15: ICEA LION LIFE ASSURANCE | C15: 592627.12 | D15: 1022.42 | E15: 1022.42 | F15: 0 | G15: 0 | H15: 0 | I15: 0 | J15: 0 | K15: 0 | L15: 0 | M15: 0 | N15: 0 | O15: 0 | P15: 0 | Q15: 593649.54
B16: JUBILEE LIFE INSURANCE | C16: 2775734.8 | D16: 1042386.9 | E16: 1042386.9 | F16: 0 | G16: 0 | H16: 0 | I16: 0 | J16: 0 | K16: 0 | L16: 0 | M16: 24056.303 | N16: 0 | O16: 0 | P16: 0 | Q16: 3794065.4
B17: KENINDIA ASSURANCE COMPANY | C17: 0 | D17: 0 | E17: 0 | F17: 0 | G17: 0 | H17: 0 | I17: 0 | J17: 0 | K17: 0 | L17: 0 | M17: 0 | N17: 0 | O17: 0 | P17: 0 | Q17: 0
... B27: THE MONARCH INSURANCE | C27: 0 | D27: 0 | E27: 0 | F27: 0 | G27: 0 | H27: 0 | I27: 0 | J27: 0 | K27: 0 | L27: 0 | M27: 0 | N27: 0 | O27: 0 | P27: 0 | Q27: 0
B28: TOTAL | C28: =SUM(C6:C27) -> 35859457 | D28: =SUM(D6:D27) -> 6204843.7 | E28: =SUM(E6:E27) -> 6204539 | F28: =SUM(F6:F27) -> -577.04632 | G28: =SUM(G6:G27) -> 2845716.3 | H28: =SUM(H6:H27) -> 2845716.3 | I28: =SUM(I6:I27) -> 0 | J28: =SUM(J6:J27) -> 0 | ... Q28: =SUM(Q6:Q27) -> 40175096
B29: REINSURERS
B30: CONTINENTAL REINSURANCE | C30: 0 | D30: 0 | E30: 0 | F30: 0 | G30: 0 | H30: 0 | I30: 0 | J30: 0 | K30: 0 | L30: 0 | M30: 0 | N30: 0 | O30: 0 | P30: 0 | Q30: 0
B31: EAST AFRICA REINSURANCE | C31: 0 | D31: 0 | E31: 0 | F31: 0 | G31: 0 | H31: 0 | I31: 0 | J31: 0 | K31: 0 | L31: 0 | M31: 0 | N31: 0 | O31: 0 | P31: 0 | Q31: 0
B32: KENYA REINSURANCE CORPORATION | C32: 0 | D32: 0 | E32: 0 | F32: 0 | G32: 0 | H32: 0 | I32: 0 | J32: 0 | K32: 0 | L32: 0 | M32: 0 | N32: 0 | O32: 0 | P32: 0 | Q32: 0
B33: TOTAL | C33: 0 | D33: 0 | E33: 0 | F33: 0 | G33: 0 | H33: 0 | I33: 0 | J33: 0 | K33: 0 | L33: 0 | M33: 0 | N33: 0 | O33: 0 | P33: 0 | Q33: 0
B34: Amounts in Thousand Shillings

Sheet NON-LINKED
B3: =_xlfn.CONCAT("NON-LINKED INVESTMENTS"," ",Details!F18) -> NON-LINKED INVESTMENTS 31.03.2026
B4: Company | C4: Life Fund BF | D4: Gross Premium | E4: Net Premium | F4: Other (Fee) Income | G4: Total Benefits | H4: Claims | I4: Surrenders_x000D_ | J4: Bonuses Paid | K4: Annuities Paid | L4: Net Commisions | M4: Expense of Management | N4: Investment Income | O4: Investment Expenses | P4: Transfer To (From) P & L | Q4: Life Fund CF
B5: INSURERS
B6: ABSA LIFE ASSURANCE | C6: 0 | D6: 0 | E6: 0 | F6: 0 | G6: 0 | H6: 0 | I6: 0 | J6: 0 | K6: 0 | L6: 0 | M6: 0 | N6: 0 | O6: 0 | P6: 0 | Q6: 0
B7: APA LIFE ASSURANCE COMPANY | C7: 10690089 | D7: 3619278.6 | E7: 3619278.6 | F7: 0 | G7: 29416.598 | H7: 29416.598 | I7: 0 | J7: 0 | K7: 0 | L7: 188004.54 | M7: 9668.6023 | N7: 586994.85 | O7: 5032.9468 | P7: 0 | Q7: 14664240
B8: BRITAM LIFE ASSURANCE | C8: 0 | D8: 0 | E8: 0 | F8: 0 | G8: 0 | H8: 0 | I8: 0 | J8: 0 | K8: 0 | L8: 0 | M8: 0 | N8: 0 | O8: 0 | P8: 0 | Q8: 0
B9: CANNON LIFE ASSURANCE (K) LIMITED | C9: 0 | D9: 0 | E9: 0 | F9: 0 | G9: 0 | H9: 0 | I9: 0 | J9: 0 | K9: 0 | L9: 0 | M9: 0 | N9: 0 | O9: 0 | P9: 0 | Q9: 0
B10: CAPEX LIFE ASSURANCE COMPANY | C10: 0 | D10: 0 | E10: 0 | F10: 0 | G10: 0 | H10: 0 | I10: 0 | J10: 0 | K10: 0 | L10: 0 | M10: 0 | N10: 0 | O10: 0 | P10: 0 | Q10: 0
B11: CIC LIFE ASSURANCE COMPANY | C11: 0 | D11: 0 | E11: 0 | F11: 0 | G11: 0 | H11: 0 | I11: 0 | J11: 0 | K11: 0 | L11: 0 | M11: 0 | N11: 0 | O11: 0 | P11: 0 | Q11: 0
B12: EQUITY LIFE ASSURANCE | C12: 321400.65 | D12: 137370.67 | E12: 137370.67 | F12: 0 | G12: 0 | H12: 0 | I12: 0 | J12: 0 | K12: 0 | L12: 0 | M12: 0 | N12: 11508.263 | O12: 0 | P12: 0 | Q12: 470279.59
B13: GA LIFE ASSURANCE COMPANY | C13: 0 | D13: 0 | E13: 0 | F13: 0 | G13: 0 | H13: 0 | I13: 0 | J13: 0 | K13: 0 | L13: 0 | M13: 0 | N13: 0 | O13: 0 | P13: 0 | Q13: 0
B14: GEMINIA LIFE INSURANCE COMPANY | C14: 534404.75 | D14: 218435.74 | E14: 218435.74 | F14: 0 | G14: 86060.755 | H14: 0 | I14: 86060.755 | J14: 0 | K14: 0 | L14: 0 | M14: 5883.5756 | N14: 0 | O14: 0 | P14: 0 | Q14: 660896.16
B15: ICEA LION LIFE ASSURANCE | C15: 0 | D15: 0 | E15: 0 | F15: 0 | G15: 3679.946 | H15: 0 | I15: 3679.946 | J15: 0 | K15: 0 | L15: 0 | M15: 0 | N15: -55973.821 | O15: 0 | P15: 0 | Q15: -59653.767
B16: JUBILEE LIFE INSURANCE | C16: 0 | D16: 0 | E16: 0 | F16: 0 | G16: 0 | H16: 0 | I16: 0 | J16: 0 | K16: 0 | L16: 0 | M16: 0 | N16: 0 | O16: 0 | P16: 0 | Q16: 0
B17: KENINDIA ASSURANCE COMPANY | C17: 18749372 | D17: 356442.07 | E17: 356442.07 | F17: 0 | G17: 674501.43 | H17: 674501.43 | I17: 0 | J17: 0 | K17: 0 | L17: 7186.177 | M17: 23648.98 | N17: 671431.5 | O17: 0 | P17: 0 | Q17: 19071909
... B27: THE MONARCH INSURANCE | C27: 0 | D27: 0 | E27: 0 | F27: 0 | G27: 0 | H27: 0 | I27: 0 | J27: 0 | K27: 0 | L27: 0 | M27: 0 | N27: 0 | O27: 0 | P27: 0 | Q27: 0
B28: TOTAL | C28: =SUM(C6:C27) -> 32514463 | D28: =SUM(D6:D27) -> 4953434.7 | E28: =SUM(E6:E27) -> 4949408.6 | F28: =SUM(F6:F27) -> -1809.877 | G28: =SUM(G6:G27) -> 921145.17 | H28: =SUM(H6:H27) -> 831404.47 | I28: =SUM(I6:I27) -> 89740.701 | J28: =SUM(J6:J27) -> 0 | ... Q28: =SUM(Q6:Q27) -> 37504674
B29: REINSURERS
B30: CONTINENTAL REINSURANCE | C30: 0 | D30: 0 | E30: 0 | F30: 0 | G30: 0 | H30: 0 | I30: 0 | J30: 0 | K30: 0 | L30: 0 | M30: 0 | N30: 0 | O30: 0 | P30: 0 | Q30: 0
B31: EAST AFRICA REINSURANCE | C31: 0 | D31: 0 | E31: 0 | F31: 0 | G31: 0 | H31: 0 | I31: 0 | J31: 0 | K31: 0 | L31: 0 | M31: 0 | N31: 0 | O31: 0 | P31: 0 | Q31: 0
B32: KENYA REINSURANCE CORPORATION | C32: 0 | D32: 0 | E32: 0 | F32: 0 | G32: 0 | H32: 0 | I32: 0 | J32: 0 | K32: 0 | L32: 0 | M32: 0 | N32: 0 | O32: 0 | P32: 0 | Q32: 0
B33: TOTAL | C33: =SUM(C30:C32) -> 0 | D33: =SUM(D30:D32) -> 0 | E33: =SUM(E30:E32) -> 0 | F33: =SUM(F30:F32) -> 0 | G33: =SUM(G30:G32) -> 0 | H33: =SUM(H30:H32) -> 0 | I33: =SUM(I30:I32) -> 0 | J33: =SUM(J30:J32) -> 0 | ... Q33: =SUM(Q30:Q32) -> 0
B34: Amounts in Thousand Shillings

Sheet APPENDIX 14
B3: =_xlfn.CONCAT('Table of Contents'!B26,": ",'Table of Contents'!C26) -> APPENDIX 14: SUMMARY OF PERMANENT HEALTH BUSINESS REVENUE ACCOUNTS FOR THE PERIOD ENDED 31.03.2026
B4: Company | C4: Life Fund BF | D4: Gross Premium | E4: Net Premium | F4: Other (Fee) Income | G4: Total Benefits | H4: Claims | I4: Surrenders_x000D_ | J4: Bonuses Paid | K4: Annuities Paid | L4: Net Commisions | M4: Expense of Management | N4: Investment Income | O4: Investment Expenses | P4: Transfer To (From) P & L | Q4: Life Fund CF
B5: INSURERS
B6: ABSA LIFE ASSURANCE | C6: 0 | D6: 0 | E6: 0 | F6: 0 | G6: 0 | H6: 0 | I6: 0 | J6: 0 | K6: 0 | L6: 0 | M6: 0 | N6: 0 | O6: 0 | P6: 0 | Q6: 0
B7: APA LIFE ASSURANCE COMPANY | C7: 0 | D7: 0 | E7: 0 | F7: 0 | G7: 0 | H7: 0 | I7: 0 | J7: 0 | K7: 0 | L7: 0 | M7: 0 | N7: 0 | O7: 0 | P7: 0 | Q7: 0
B8: BRITAM LIFE ASSURANCE | C8: 0 | D8: 0 | E8: 0 | F8: 0 | G8: 0 | H8: 0 | I8: 0 | J8: 0 | K8: 0 | L8: 0 | M8: 0 | N8: 0 | O8: 0 | P8: 0 | Q8: 0
B9: CANNON LIFE ASSURANCE (K) LIMITED | C9: 0 | D9: 0 | E9: 0 | F9: 0 | G9: 0 | H9: 0 | I9: 0 | J9: 0 | K9: 0 | L9: 0 | M9: 0 | N9: 0 | O9: 0 | P9: 0 | Q9: 0
B10: CAPEX LIFE ASSURANCE COMPANY | C10: 0 | D10: 0 | E10: 0 | F10: 0 | G10: 0 | H10: 0 | I10: 0 | J10: 0 | K10: 0 | L10: 0 | M10: 0 | N10: 0 | O10: 0 | P10: 0 | Q10: 0
B11: CIC LIFE ASSURANCE COMPANY | C11: 0 | D11: 0 | E11: 0 | F11: 0 | G11: 0 | H11: 0 | I11: 0 | J11: 0 | K11: 0 | L11: 0 | M11: 0 | N11: 0 | O11: 0 | P11: 0 | Q11: 0
B12: EQUITY LIFE ASSURANCE | C12: 0 | D12: 0 | E12: 0 | F12: 0 | G12: 0 | H12: 0 | I12: 0 | J12: 0 | K12: 0 | L12: 0 | M12: 0 | N12: 0 | O12: 0 | P12: 0 | Q12: 0
B13: GA LIFE ASSURANCE COMPANY | C13: 0 | D13: 0 | E13: 0 | F13: 0 | G13: 0 | H13: 0 | I13: 0 | J13: 0 | K13: 0 | L13: 0 | M13: 0 | N13: 0 | O13: 0 | P13: 0 | Q13: 0
B14: GEMINIA LIFE INSURANCE COMPANY | C14: 0 | D14: 0 | E14: 0 | F14: 0 | G14: 0 | H14: 0 | I14: 0 | J14: 0 | K14: 0 | L14: 0 | M14: 0 | N14: 0 | O14: 0 | P14: 0 | Q14: 0
B15: ICEA LION LIFE ASSURANCE | C15: 0 | D15: 0 | E15: 0 | F15: 0 | G15: 0 | H15: 0 | I15: 0 | J15: 0 | K15: 0 | L15: 0 | M15: 0 | N15: 0 | O15: 0 | P15: 0 | Q15: 0
B16: JUBILEE LIFE INSURANCE | C16: 0 | D16: 0 | E16: 0 | F16: 0 | G16: 0 | H16: 0 | I16: 0 | J16: 0 | K16: 0 | L16: 0 | M16: 0 | N16: 0 | O16: 0 | P16: 0 | Q16: 0
B17: KENINDIA ASSURANCE COMPANY | C17: 0 | D17: 0 | E17: 0 | F17: 0 | G17: 0 | H17: 0 | I17: 0 | J17: 0 | K17: 0 | L17: 0 | M17: 0 | N17: 0 | O17: 0 | P17: 0 | Q17: 0
... B27: THE MONARCH INSURANCE | C27: 0 | D27: 0 | E27: 0 | F27: 0 | G27: 0 | H27: 0 | I27: 0 | J27: 0 | K27: 0 | L27: 0 | M27: 0 | N27: 0 | O27: 0 | P27: 0 | Q27: 0
B28: TOTAL | C28: =SUM(C6:C27) -> 0 | D28: =SUM(D6:D27) -> 0 | E28: =SUM(E6:E27) -> 0 | F28: =SUM(F6:F27) -> 0 | G28: =SUM(G6:G27) -> 0 | H28: =SUM(H6:H27) -> 0 | I28: =SUM(I6:I27) -> 0 | J28: =SUM(J6:J27) -> 0 | ... Q28: =SUM(Q6:Q27) -> 0
B29: REINSURERS
B30: CONTINENTAL REINSURANCE | C30: 0 | D30: 0 | E30: 0 | F30: 0 | G30: 0 | H30: 0 | I30: 0 | J30: 0 | K30: 0 | L30: 0 | M30: 0 | N30: 0 | O30: 0 | P30: 0 | Q30: 0
B31: EAST AFRICA REINSURANCE | C31: 0 | D31: 0 | E31: 0 | F31: 0 | G31: 0 | H31: 0 | I31: 0 | J31: 0 | K31: 0 | L31: 0 | M31: 0 | N31: 0 | O31: 0 | P31: 0 | Q31: 0
B32: KENYA REINSURANCE CORPORATION | C32: 0 | D32: 0 | E32: 0 | F32: 0 | G32: 0 | H32: 0 | I32: 0 | J32: 0 | K32: 0 | L32: 0 | M32: 0 | N32: 0 | O32: 0 | P32: 0 | Q32: 0
B33: TOTAL | C33: =SUM(C30:C32) -> 0 | D33: =SUM(D30:D32) -> 0 | E33: =SUM(E30:E32) -> 0 | F33: =SUM(F30:F32) -> 0 | G33: =SUM(G30:G32) -> 0 | H33: =SUM(H30:H32) -> 0 | I33: =SUM(I30:I32) -> 0 | J33: =SUM(J30:J32) -> 0 | ... Q33: =SUM(Q30:Q32) -> 0
B34: Amounts in Thousand Shillings

Sheet PENSIONS
B3: =_xlfn.CONCAT("SUMMARY OF PENSIONS BUSINESS REVENUE ACCOUNTS FOR THE PERIOD ENDED"," ",Details!F18) -> SUMMARY OF PENSIONS BUSINESS REVENUE ACCOUNTS FOR THE PERIOD ENDED 31.03.2026
B4: Company | C4: Life Fund BF | D4: Gross Premium | E4: Net Premium | F4: Other (Fee) Income | G4: Total Benefits | H4: Claims | I4: Surrenders_x000D_ | J4: Bonuses Paid | K4: Annuities Paid | L4: Net Commisions | M4: Expense of Management | N4: Investment Income | O4: Investment Expenses | P4: Transfer To (From) P & L | Q4: Life Fund CF
B5: INSURERS
B6: =+'APPENDIX 15'!B6 -> ABSA LIFE ASSURANCE | C6: =+'APPENDIX 15'!C6+'APPENDIX 16'!C6 -> 0 | D6: =+'APPENDIX 15'!D6+'APPENDIX 16'!D6 -> 0 | E6: =+'APPENDIX 15'!E6+'APPENDIX 16'!E6 -> 0 | F6: =+'APPENDIX 15'!F6+'APPENDIX 16'!F6 -> 0 | G6: =+'APPENDIX 15'!G6+'APPENDIX 16'!G6 -> 0 | H6: =+'APPENDIX 15'!H6+'APPENDIX 16'!H6 -> 0 | I6: =+'APPENDIX 15'!I6+'APPENDIX 16'!I6 -> 0 | J6: =+'APPENDIX 15'!J6+'APPENDIX 16'!J6 -> 0 | ... Q6: =+'APPENDIX 15'!Q6+'APPENDIX 16'!Q6 -> 0
B7: =+'APPENDIX 15'!B7 -> APA LIFE ASSURANCE COMPANY | C7: =+'APPENDIX 15'!C7+'APPENDIX 16'!C7 -> 11803300 | D7: =+'APPENDIX 15'!D7+'APPENDIX 16'!D7 -> 544131.59 | E7: =+'APPENDIX 15'!E7+'APPENDIX 16'!E7 -> 544131.59 | F7: =+'APPENDIX 15'!F7+'APPENDIX 16'!F7 -> 0 | G7: =+'APPENDIX 15'!G7+'APPENDIX 16'!G7 -> 343232.08 | H7: =+'APPENDIX 15'!H7+'APPENDIX 16'!H7 -> 343232.08 | I7: =+'APPENDIX 15'!I7+'APPENDIX 16'!I7 -> 0 | J7: =+'APPENDIX 15'!J7+'APPENDIX 16'!J7 -> 0 | ... Q7: =+'APPENDIX 15'!Q7+'APPENDIX 16'!Q7 -> 12412843
B8: =+'APPENDIX 15'!B8 -> BRITAM LIFE ASSURANCE | C8: =+'APPENDIX 15'!C8+'APPENDIX 16'!C8 -> 83669194 | D8: =+'APPENDIX 15'!D8+'APPENDIX 16'!D8 -> 4231056 | E8: =+'APPENDIX 15'!E8+'APPENDIX 16'!E8 -> 4231056 | F8: =+'APPENDIX 15'!F8+'APPENDIX 16'!F8 -> 0 | G8: =+'APPENDIX 15'!G8+'APPENDIX 16'!G8 -> 3673215.3 | H8: =+'APPENDIX 15'!H8+'APPENDIX 16'!H8 -> 3673215.3 | I8: =+'APPENDIX 15'!I8+'APPENDIX 16'!I8 -> 0 | J8: =+'APPENDIX 15'!J8+'APPENDIX 16'!J8 -> 0 | ... Q8: =+'APPENDIX 15'!Q8+'APPENDIX 16'!Q8 -> 87356154
B9: =+'APPENDIX 15'!B9 -> CANNON LIFE ASSURANCE (K) LIMITED | C9: =+'APPENDIX 15'!C9+'APPENDIX 16'!C9 -> 0 | D9: =+'APPENDIX 15'!D9+'APPENDIX 16'!D9 -> 0 | E9: =+'APPENDIX 15'!E9+'APPENDIX 16'!E9 -> 0 | F9: =+'APPENDIX 15'!F9+'APPENDIX 16'!F9 -> 0 | G9: =+'APPENDIX 15'!G9+'APPENDIX 16'!G9 -> 0 | H9: =+'APPENDIX 15'!H9+'APPENDIX 16'!H9 -> 0 | I9: =+'APPENDIX 15'!I9+'APPENDIX 16'!I9 -> 0 | J9: =+'APPENDIX 15'!J9+'APPENDIX 16'!J9 -> 0 | ... Q9: =+'APPENDIX 15'!Q9+'APPENDIX 16'!Q9 -> 0
B10: =+'APPENDIX 15'!B10 -> CAPEX LIFE ASSURANCE COMPANY | C10: =+'APPENDIX 15'!C10+'APPENDIX 16'!C10 -> 41545.871 | D10: =+'APPENDIX 15'!D10+'APPENDIX 16'!D10 -> 7382.0123 | E10: =+'APPENDIX 15'!E10+'APPENDIX 16'!E10 -> 7382.0123 | F10: =+'APPENDIX 15'!F10+'APPENDIX 16'!F10 -> 0 | G10: =+'APPENDIX 15'!G10+'APPENDIX 16'!G10 -> 9789.0976 | H10: =+'APPENDIX 15'!H10+'APPENDIX 16'!H10 -> 9789.0976 | I10: =+'APPENDIX 15'!I10+'APPENDIX 16'!I10 -> 0 | J10: =+'APPENDIX 15'!J10+'APPENDIX 16'!J10 -> 0 | ... Q10: =+'APPENDIX 15'!Q10+'APPENDIX 16'!Q10 -> 38396.386
B11: =+'APPENDIX 15'!B11 -> CIC LIFE ASSURANCE COMPANY | C11: =+'APPENDIX 15'!C11+'APPENDIX 16'!C11 -> 20131563 | D11: =+'APPENDIX 15'!D11+'APPENDIX 16'!D11 -> 933321.99 | E11: =+'APPENDIX 15'!E11+'APPENDIX 16'!E11 -> 933321.99 | F11: =+'APPENDIX 15'!F11+'APPENDIX 16'!F11 -> 0 | G11: =+'APPENDIX 15'!G11+'APPENDIX 16'!G11 -> 67977.144 | H11: =+'APPENDIX 15'!H11+'APPENDIX 16'!H11 -> 67977.144 | I11: =+'APPENDIX 15'!I11+'APPENDIX 16'!I11 -> 0 | J11: =+'APPENDIX 15'!J11+'APPENDIX 16'!J11 -> 0 | ... Q11: =+'APPENDIX 15'!Q11+'APPENDIX 16'!Q11 -> 20795847
B12: =+'APPENDIX 15'!B12 -> EQUITY LIFE ASSURANCE | C12: =+'APPENDIX 15'!C12+'APPENDIX 16'!C12 -> 17866379 | D12: =+'APPENDIX 15'!D12+'APPENDIX 16'!D12 -> 729045.33 | E12: =+'APPENDIX 15'!E12+'APPENDIX 16'!E12 -> 729045.33 | F12: =+'APPENDIX 15'!F12+'APPENDIX 16'!F12 -> 42083.237 | G12: =+'APPENDIX 15'!G12+'APPENDIX 16'!G12 -> 385686.3 | H12: =+'APPENDIX 15'!H12+'APPENDIX 16'!H12 -> 385686.3 | I12: =+'APPENDIX 15'!I12+'APPENDIX 16'!I12 -> 0 | J12: =+'APPENDIX 15'!J12+'APPENDIX 16'!J12 -> 0 | ... Q12: =+'APPENDIX 15'!Q12+'APPENDIX 16'!Q12 -> 18814431
B13: =+'APPENDIX 15'!B13 -> GA LIFE ASSURANCE COMPANY | C13: =+'APPENDIX 15'!C13+'APPENDIX 16'!C13 -> 56511369 | D13: =+'APPENDIX 15'!D13+'APPENDIX 16'!D13 -> 2108635.3 | E13: =+'APPENDIX 15'!E13+'APPENDIX 16'!E13 -> 2108635.3 | F13: =+'APPENDIX 15'!F13+'APPENDIX 16'!F13 -> 0 | G13: =+'APPENDIX 15'!G13+'APPENDIX 16'!G13 -> 831593.06 | H13: =+'APPENDIX 15'!H13+'APPENDIX 16'!H13 -> 831593.06 | I13: =+'APPENDIX 15'!I13+'APPENDIX 16'!I13 -> 0 | J13: =+'APPENDIX 15'!J13+'APPENDIX 16'!J13 -> 0 | ... Q13: =+'APPENDIX 15'!Q13+'APPENDIX 16'!Q13 -> 59842544
B14: =+'APPENDIX 15'!B14 -> GEMINIA LIFE INSURANCE COMPANY | C14: =+'APPENDIX 15'!C14+'APPENDIX 16'!C14 -> 870602.66 | D14: =+'APPENDIX 15'!D14+'APPENDIX 16'!D14 -> 719890.52 | E14: =+'APPENDIX 15'!E14+'APPENDIX 16'!E14 -> 719890.52 | F14: =+'APPENDIX 15'!F14+'APPENDIX 16'!F14 -> 0 | G14: =+'APPENDIX 15'!G14+'APPENDIX 16'!G14 -> 362783.27 | H14: =+'APPENDIX 15'!H14+'APPENDIX 16'!H14 -> 0 | I14: =+'APPENDIX 15'!I14+'APPENDIX 16'!I14 -> 362783.27 | J14: =+'APPENDIX 15'!J14+'APPENDIX 16'!J14 -> 0 | ... Q14: =+'APPENDIX 15'!Q14+'APPENDIX 16'!Q14 -> 1224400.6
B15: =+'APPENDIX 15'!B15 -> ICEA LION LIFE ASSURANCE | C15: =+'APPENDIX 15'!C15+'APPENDIX 16'!C15 -> 1.5232041e+08 | D15: =+'APPENDIX 15'!D15+'APPENDIX 16'!D15 -> 5313850.9 | E15: =+'APPENDIX 15'!E15+'APPENDIX 16'!E15 -> 5313850.9 | F15: =+'APPENDIX 15'!F15+'APPENDIX 16'!F15 -> 0 | G15: =+'APPENDIX 15'!G15+'APPENDIX 16'!G15 -> 4028356.1 | H15: =+'APPENDIX 15'!H15+'APPENDIX 16'!H15 -> 4028356.1 | I15: =+'APPENDIX 15'!I15+'APPENDIX 16'!I15 -> 0 | J15: =+'APPENDIX 15'!J15+'APPENDIX 16'!J15 -> 0 | ... Q15: =+'APPENDIX 15'!Q15+'APPENDIX 16'!Q15 -> 1.5849181e+08
B16: =+'APPENDIX 15'!B16 -> JUBILEE LIFE INSURANCE | C16: =+'APPENDIX 15'!C16+'APPENDIX 16'!C16 -> 1.3159901e+08 | D16: =+'APPENDIX 15'!D16+'APPENDIX 16'!D16 -> 5035051.8 | E16: =+'APPENDIX 15'!E16+'APPENDIX 16'!E16 -> 5035051.8 | F16: =+'APPENDIX 15'!F16+'APPENDIX 16'!F16 -> 0 | G16: =+'APPENDIX 15'!G16+'APPENDIX 16'!G16 -> 2438049.2 | H16: =+'APPENDIX 15'!H16+'APPENDIX 16'!H16 -> 2438049.2 | I16: =+'APPENDIX 15'!I16+'APPENDIX 16'!I16 -> 0 | J16: =+'APPENDIX 15'!J16+'APPENDIX 16'!J16 -> 0 | ... Q16: =+'APPENDIX 15'!Q16+'APPENDIX 16'!Q16 -> 1.388443e+08
B17: =+'APPENDIX 15'!B17 -> KENINDIA ASSURANCE COMPANY | C17: =+'APPENDIX 15'!C17+'APPENDIX 16'!C17 -> 82409182 | D17: =+'APPENDIX 15'!D17+'APPENDIX 16'!D17 -> 3674214.7 | E17: =+'APPENDIX 15'!E17+'APPENDIX 16'!E17 -> 3674214.7 | F17: =+'APPENDIX 15'!F17+'APPENDIX 16'!F17 -> 0 | G17: =+'APPENDIX 15'!G17+'APPENDIX 16'!G17 -> 1913060.2 | H17: =+'APPENDIX 15'!H17+'APPENDIX 16'!H17 -> 1913060.2 | I17: =+'APPENDIX 15'!I17+'APPENDIX 16'!I17 -> 0 | J17: =+'APPENDIX 15'!J17+'APPENDIX 16'!J17 -> 0 | ... Q17: =+'APPENDIX 15'!Q17+'APPENDIX 16'!Q17 -> 86600305
... B27: =+'APPENDIX 15'!B27 -> THE MONARCH INSURANCE | C27: =+'APPENDIX 15'!C27+'APPENDIX 16'!C27 -> 0 | D27: =+'APPENDIX 15'!D27+'APPENDIX 16'!D27 -> 0 | E27: =+'APPENDIX 15'!E27+'APPENDIX 16'!E27 -> 0 | F27: =+'APPENDIX 15'!F27+'APPENDIX 16'!F27 -> 0 | G27: =+'APPENDIX 15'!G27+'APPENDIX 16'!G27 -> 0 | H27: =+'APPENDIX 15'!H27+'APPENDIX 16'!H27 -> 0 | I27: =+'APPENDIX 15'!I27+'APPENDIX 16'!I27 -> 0 | J27: =+'APPENDIX 15'!J27+'APPENDIX 16'!J27 -> 0 | ... Q27: =+'APPENDIX 15'!Q27+'APPENDIX 16'!Q27 -> 0
B28: TOTAL | C28: =SUM(C6:C27) -> 6.0805521e+08 | D28: =SUM(D6:D27) -> 28181884 | E28: =SUM(E6:E27) -> 28181884 | F28: =SUM(F6:F27) -> 42083.237 | G28: =SUM(G6:G27) -> 15166754 | H28: =SUM(H6:H27) -> 14803970 | I28: =SUM(I6:I27) -> 362783.27 | J28: =SUM(J6:J27) -> 0 | ... Q28: =SUM(Q6:Q27) -> 6.4062923e+08
B29: REINSURERS
B30: =+'APPENDIX 15'!B30 -> CONTINENTAL REINSURANCE | C30: =+'APPENDIX 15'!C30+'APPENDIX 16'!C30 -> 0 | D30: =+'APPENDIX 15'!D30+'APPENDIX 16'!D30 -> 0 | E30: =+'APPENDIX 15'!E30+'APPENDIX 16'!E30 -> 0 | F30: =+'APPENDIX 15'!F30+'APPENDIX 16'!F30 -> 0 | G30: =+'APPENDIX 15'!G30+'APPENDIX 16'!G30 -> 0 | H30: =+'APPENDIX 15'!H30+'APPENDIX 16'!H30 -> 0 | I30: =+'APPENDIX 15'!I30+'APPENDIX 16'!I30 -> 0 | J30: =+'APPENDIX 15'!J30+'APPENDIX 16'!J30 -> 0 | ... Q30: =+'APPENDIX 15'!Q30+'APPENDIX 16'!Q30 -> 0
B31: =+'APPENDIX 15'!B31 -> EAST AFRICA REINSURANCE | C31: =+'APPENDIX 15'!C31+'APPENDIX 16'!C31 -> 0 | D31: =+'APPENDIX 15'!D31+'APPENDIX 16'!D31 -> 0 | E31: =+'APPENDIX 15'!E31+'APPENDIX 16'!E31 -> 0 | F31: =+'APPENDIX 15'!F31+'APPENDIX 16'!F31 -> 0 | G31: =+'APPENDIX 15'!G31+'APPENDIX 16'!G31 -> 0 | H31: =+'APPENDIX 15'!H31+'APPENDIX 16'!H31 -> 0 | I31: =+'APPENDIX 15'!I31+'APPENDIX 16'!I31 -> 0 | J31: =+'APPENDIX 15'!J31+'APPENDIX 16'!J31 -> 0 | ... Q31: =+'APPENDIX 15'!Q31+'APPENDIX 16'!Q31 -> 0
B32: =+'APPENDIX 15'!B32 -> KENYA REINSURANCE CORPORATION | C32: =+'APPENDIX 15'!C32+'APPENDIX 16'!C32 -> 0 | D32: =+'APPENDIX 15'!D32+'APPENDIX 16'!D32 -> 0 | E32: =+'APPENDIX 15'!E32+'APPENDIX 16'!E32 -> 0 | F32: =+'APPENDIX 15'!F32+'APPENDIX 16'!F32 -> 0 | G32: =+'APPENDIX 15'!G32+'APPENDIX 16'!G32 -> 0 | H32: =+'APPENDIX 15'!H32+'APPENDIX 16'!H32 -> 0 | I32: =+'APPENDIX 15'!I32+'APPENDIX 16'!I32 -> 0 | J32: =+'APPENDIX 15'!J32+'APPENDIX 16'!J32 -> 0 | ... Q32: =+'APPENDIX 15'!Q32+'APPENDIX 16'!Q32 -> 0
B33: TOTAL | C33: =SUM(C30:C32) -> 0 | D33: =SUM(D30:D32) -> 0 | E33: =SUM(E30:E32) -> 0 | F33: =SUM(F30:F32) -> 0 | G33: =SUM(G30:G32) -> 0 | H33: =SUM(H30:H32) -> 0 | I33: =SUM(I30:I32) -> 0 | J33: =SUM(J30:J32) -> 0 | ... Q33: =SUM(Q30:Q32) -> 0
B34: Amounts in Thousand Shillings

Sheet APPENDIX 15
B3: =_xlfn.CONCAT('Table of Contents'!B27,": ",'Table of Contents'!C27) -> APPENDIX 15: SUMMARY OF PERSONAL PENSIONS BUSINESS REVENUE ACCOUNTS FOR THE PERIOD ENDED 31.03.2026
B4: Company | C4: Life Fund BF | D4: Gross Premium | E4: Net Premium | F4: Other (Fee) Income | G4: Total Benefits | H4: Claims | I4: Surrenders_x000D_ | J4: Bonuses Paid | K4: Annuities Paid | L4: Net Commisions | M4: Expense of Management | N4: Investment Income | O4: Investment Expenses | P4: Transfer To (From) P & L | Q4: Life Fund CF
B5: INSURERS
B6: ABSA LIFE ASSURANCE | C6: 0 | D6: 0 | E6: 0 | F6: 0 | G6: 0 | H6: 0 | I6: 0 | J6: 0 | K6: 0 | L6: 0 | M6: 0 | N6: 0 | O6: 0 | P6: 0 | Q6: 0
B7: APA LIFE ASSURANCE COMPANY | C7: 119405.79 | D7: 50242.991 | E7: 50242.991 | F7: 0 | G7: 34338.005 | H7: 34338.005 | I7: 0 | J7: 0 | K7: 0 | L7: 0 | M7: 0 | N7: 40652.003 | O7: 345.89499 | P7: 0 | Q7: 175616.89
B8: BRITAM LIFE ASSURANCE | C8: 39278757 | D8: 1289835.6 | E8: 1289835.6 | F8: 0 | G8: 1055545.9 | H8: 1055545.9 | I8: 0 | J8: 0 | K8: 0 | L8: 12662.282 | M8: 80861.177 | N8: 1049771.6 | O8: 2273.723 | P8: 0 | Q8: 40467021
B9: CANNON LIFE ASSURANCE (K) LIMITED | C9: 0 | D9: 0 | E9: 0 | F9: 0 | G9: 0 | H9: 0 | I9: 0 | J9: 0 | K9: 0 | L9: 0 | M9: 0 | N9: 0 | O9: 0 | P9: 0 | Q9: 0
B10: CAPEX LIFE ASSURANCE COMPANY | C10: 0 | D10: 0 | E10: 0 | F10: 0 | G10: 0 | H10: 0 | I10: 0 | J10: 0 | K10: 0 | L10: 0 | M10: 0 | N10: 0 | O10: 0 | P10: 0 | Q10: 0
B11: CIC LIFE ASSURANCE COMPANY | C11: 0 | D11: 0 | E11: 0 | F11: 0 | G11: 0 | H11: 0 | I11: 0 | J11: 0 | K11: 0 | L11: 0 | M11: 0 | N11: 0 | O11: 0 | P11: 0 | Q11: 0
B12: EQUITY LIFE ASSURANCE | C12: 692701.77 | D12: 157458.4 | E12: 157458.4 | F12: 0 | G12: 10167.836 | H12: 10167.836 | I12: 0 | J12: 0 | K12: 0 | L12: 0 | M12: 0 | N12: 23490.811 | O12: 0 | P12: 0 | Q12: 863483.15
B13: GA LIFE ASSURANCE COMPANY | C13: 8157330.6 | D13: 533514.34 | E13: 533514.34 | F13: 0 | G13: 112715.34 | H13: 112715.34 | I13: 0 | J13: 0 | K13: 0 | L13: 3423.626 | M13: 9732.228 | N13: 308240.53 | O13: 0 | P13: 0 | Q13: 8873214.2
B14: GEMINIA LIFE INSURANCE COMPANY | C14: 215032.23 | D14: 40881.616 | E14: 40881.616 | F14: 0 | G14: 0 | H14: 0 | I14: 0 | J14: 0 | K14: 0 | L14: -1155.008 | M14: 1339.2972 | N14: 0 | O14: 0 | P14: 0 | Q14: 255729.55
B15: ICEA LION LIFE ASSURANCE | C15: 58509830 | D15: 2222063.5 | E15: 2222063.5 | F15: 0 | G15: 1238876.4 | H15: 1238876.4 | I15: 0 | J15: 0 | K15: 0 | L15: 19214.16 | M15: 88699.182 | N15: 2085659.6 | O15: 0 | P15: 105000 | Q15: 61365764
B16: JUBILEE LIFE INSURANCE | C16: 13847576 | D16: 717634.84 | E16: 717634.84 | F16: 0 | G16: 0 | H16: 0 | I16: 0 | J16: 0 | K16: 0 | L16: 0 | M16: 12467.387 | N16: 0 | O16: 0 | P16: 0 | Q16: 14552743
B17: KENINDIA ASSURANCE COMPANY | C17: 612808.76 | D17: 14565.909 | E17: 14565.909 | F17: 0 | G17: 14301.829 | H17: 14301.829 | I17: 0 | J17: 0 | K17: 0 | L17: 351.39913 | M17: 1809.0426 | N17: 20996.074 | O17: 0 | P17: 0 | Q17: 631908.48
... B27: THE MONARCH INSURANCE | C27: 0 | D27: 0 | E27: 0 | F27: 0 | G27: 0 | H27: 0 | I27: 0 | J27: 0 | K27: 0 | L27: 0 | M27: 0 | N27: 0 | O27: 0 | P27: 0 | Q27: 0
B28: TOTAL | C28: =SUM(C6:C27) -> 1.2703078e+08 | D28: =SUM(D6:D27) -> 6505671.2 | E28: =SUM(E6:E27) -> 6505671.2 | F28: =SUM(F6:F27) -> 0 | G28: =SUM(G6:G27) -> 2864075.4 | H28: =SUM(H6:H27) -> 2864075.4 | I28: =SUM(I6:I27) -> 0 | J28: =SUM(J6:J27) -> 0 | ... Q28: =SUM(Q6:Q27) -> 1.3418685e+08
B29: REINSURERS
B30: CONTINENTAL REINSURANCE | C30: 0 | D30: 0 | E30: 0 | F30: 0 | G30: 0 | H30: 0 | I30: 0 | J30: 0 | K30: 0 | L30: 0 | M30: 0 | N30: 0 | O30: 0 | P30: 0 | Q30: 0
B31: EAST AFRICA REINSURANCE | C31: 0 | D31: 0 | E31: 0 | F31: 0 | G31: 0 | H31: 0 | I31: 0 | J31: 0 | K31: 0 | L31: 0 | M31: 0 | N31: 0 | O31: 0 | P31: 0 | Q31: 0
B32: KENYA REINSURANCE CORPORATION | C32: 0 | D32: 0 | E32: 0 | F32: 0 | G32: 0 | H32: 0 | I32: 0 | J32: 0 | K32: 0 | L32: 0 | M32: 0 | N32: 0 | O32: 0 | P32: 0 | Q32: 0
B33: TOTAL | C33: =SUM(C30:C32) -> 0 | D33: =SUM(D30:D32) -> 0 | E33: =SUM(E30:E32) -> 0 | F33: =SUM(F30:F32) -> 0 | G33: =SUM(G30:G32) -> 0 | H33: =SUM(H30:H32) -> 0 | I33: =SUM(I30:I32) -> 0 | J33: =SUM(J30:J32) -> 0 | ... Q33: =SUM(Q30:Q32) -> 0
B34: Amounts in Thousand Shillings

Sheet APPENDIX 16
B3: =_xlfn.CONCAT('Table of Contents'!B28,": ",'Table of Contents'!C28) -> APPENDIX 16: SUMMARY OF DEPOSIT ADMINISTRATION BUSINESS REVENUE ACCOUNTS FOR THE PERIOD ENDED 31.03.2026
B4: Company | C4: Life Fund BF | D4: Gross Premium | E4: Net Premium | F4: Other (Fee) Income | G4: Total Benefits | H4: Claims | I4: Surrenders_x000D_ | J4: Bonuses Paid | K4: Annuities Paid | L4: Net Commisions | M4: Expense of Management | N4: Investment Income | O4: Investment Expenses | P4: Transfer To (From) P & L | Q4: Life Fund CF
B5: INSURERS
B6: ABSA LIFE ASSURANCE | C6: 0 | D6: 0 | E6: 0 | F6: 0 | G6: 0 | H6: 0 | I6: 0 | J6: 0 | K6: 0 | L6: 0 | M6: 0 | N6: 0 | O6: 0 | P6: 0 | Q6: 0
B7: APA LIFE ASSURANCE COMPANY | C7: 11683894 | D7: 493888.6 | E7: 493888.6 | F7: 0 | G7: 308894.07 | H7: 308894.07 | I7: 0 | J7: 0 | K7: 0 | L7: 10951.759 | M7: 16919.706 | N7: 399609.19 | O7: 3400.1477 | P7: 0 | Q7: 12237226
B8: BRITAM LIFE ASSURANCE | C8: 44390437 | D8: 2941220.5 | E8: 2941220.5 | F8: 0 | G8: 2617669.3 | H8: 2617669.3 | I8: 0 | J8: 0 | K8: 0 | L8: 28871.325 | M8: 184388.27 | N8: 2393588.9 | O8: 5184.327 | P8: 0 | Q8: 46889133
B9: CANNON LIFE ASSURANCE (K) LIMITED | C9: 0 | D9: 0 | E9: 0 | F9: 0 | G9: 0 | H9: 0 | I9: 0 | J9: 0 | K9: 0 | L9: 0 | M9: 0 | N9: 0 | O9: 0 | P9: 0 | Q9: 0
B10: CAPEX LIFE ASSURANCE COMPANY | C10: 41545.871 | D10: 7382.0123 | E10: 7382.0123 | F10: 0 | G10: 9789.0976 | H10: 9789.0976 | I10: 0 | J10: 0 | K10: 0 | L10: 0 | M10: 742.4 | N10: 0 | O10: 0 | P10: 0 | Q10: 38396.386
B11: CIC LIFE ASSURANCE COMPANY | C11: 20131563 | D11: 933321.99 | E11: 933321.99 | F11: 0 | G11: 67977.144 | H11: 67977.144 | I11: 0 | J11: 0 | K11: 0 | L11: 67977.144 | M11: 133083.59 | N11: 0 | O11: 0 | P11: 0 | Q11: 20795847
B12: EQUITY LIFE ASSURANCE | C12: 17173677 | D12: 571586.93 | E12: 571586.93 | F12: 42083.237 | G12: 375518.46 | H12: 375518.46 | I12: 0 | J12: 0 | K12: 0 | L12: 0 | M12: 757.39885 | N12: 585798.19 | O12: 45922.214 | P12: 0 | Q12: 17950947
B13: GA LIFE ASSURANCE COMPANY | C13: 48354038 | D13: 1575121 | E13: 1575121 | F13: 0 | G13: 718877.72 | H13: 718877.72 | I13: 0 | J13: 0 | K13: 0 | L13: 9627.113 | M13: 57663.874 | N13: 1826338.7 | O13: 0 | P13: 0 | Q13: 50969329
B14: GEMINIA LIFE INSURANCE COMPANY | C14: 655570.44 | D14: 679008.9 | E14: 679008.9 | F14: 0 | G14: 362783.27 | H14: 0 | I14: 362783.27 | J14: 0 | K14: 0 | L14: 0 | M14: 3125.0267 | N14: 0 | O14: 0 | P14: 0 | Q14: 968671.05
B15: ICEA LION LIFE ASSURANCE | C15: 93810582 | D15: 3091787.4 | E15: 3091787.4 | F15: 0 | G15: 2789479.8 | H15: 2789479.8 | I15: 0 | J15: 0 | K15: 0 | L15: 70898.516 | M15: 138590.27 | N15: 3432642.8 | O15: 0 | P15: 210000 | Q15: 97126044
B16: JUBILEE LIFE INSURANCE | C16: 1.1775143e+08 | D16: 4317417 | E16: 4317417 | F16: 0 | G16: 2438049.2 | H16: 2438049.2 | I16: 0 | J16: 0 | K16: 0 | L16: 81148.623 | M16: 97846.849 | N16: 4867047.3 | O16: 27293.517 | P16: 0 | Q16: 1.2429156e+08
B17: KENINDIA ASSURANCE COMPANY | C17: 81796373 | D17: 3659648.8 | E17: 3659648.8 | F17: 0 | G17: 1898758.3 | H17: 1898758.3 | I17: 0 | J17: 0 | K17: 0 | L17: 65350.177 | M17: 199349.32 | N17: 2785211.1 | O17: 0 | P17: 109378.07 | Q17: 85968397
... B27: THE MONARCH INSURANCE | C27: 0 | D27: 0 | E27: 0 | F27: 0 | G27: 0 | H27: 0 | I27: 0 | J27: 0 | K27: 0 | L27: 0 | M27: 0 | N27: 0 | O27: 0 | P27: 0 | Q27: 0
B28: TOTAL | C28: =SUM(C6:C27) -> 4.8102443e+08 | D28: =SUM(D6:D27) -> 21676213 | E28: =SUM(E6:E27) -> 21676213 | F28: =SUM(F6:F27) -> 42083.237 | G28: =SUM(G6:G27) -> 12302678 | H28: =SUM(H6:H27) -> 11939895 | I28: =SUM(I6:I27) -> 362783.27 | J28: =SUM(J6:J27) -> 0 | ... Q28: =SUM(Q6:Q27) -> 5.0644238e+08
B29: REINSURERS
B30: CONTINENTAL REINSURANCE | C30: 0 | D30: 0 | E30: 0 | F30: 0 | G30: 0 | H30: 0 | I30: 0 | J30: 0 | K30: 0 | L30: 0 | M30: 0 | N30: 0 | O30: 0 | P30: 0 | Q30: 0
B31: EAST AFRICA REINSURANCE | C31: 0 | D31: 0 | E31: 0 | F31: 0 | G31: 0 | H31: 0 | I31: 0 | J31: 0 | K31: 0 | L31: 0 | M31: 0 | N31: 0 | O31: 0 | P31: 0 | Q31: 0
B32: KENYA REINSURANCE CORPORATION | C32: 0 | D32: 0 | E32: 0 | F32: 0 | G32: 0 | H32: 0 | I32: 0 | J32: 0 | K32: 0 | L32: 0 | M32: 0 | N32: 0 | O32: 0 | P32: 0 | Q32: 0
B33: TOTAL | C33: =SUM(C30:C32) -> 0 | D33: =SUM(D30:D32) -> 0 | E33: =SUM(E30:E32) -> 0 | F33: =SUM(F30:F32) -> 0 | G33: =SUM(G30:G32) -> 0 | H33: =SUM(H30:H32) -> 0 | I33: =SUM(I30:I32) -> 0 | J33: =SUM(J30:J32) -> 0 | ... Q33: =SUM(Q30:Q32) -> 0
B34: Amounts in Thousand Shillings

Sheet APPENDIX 17
B3: =_xlfn.CONCAT('Table of Contents'!B29,": ",'Table of Contents'!C29) -> APPENDIX 17: SUMMARY OF COMBINED LONG TERM BUSINESS REVENUE ACCOUNTS FOR THE PERIOD ENDED 31.03.2026
B4: Company | C4: Life Fund BF | D4: Gross Premium | E4: Net Premium | F4: Other (Fee) Income | G4: Total Benefits | H4: Claims | I4: Surrenders_x000D_ | J4: Bonuses Paid | K4: Annuities Paid | L4: Net Commisions | M4: Expense of Management | N4: Investment Income | O4: Investment Expenses | P4: Transfer To (From) P & L | Q4: Life Fund CF
B5: INSURERS
B6: ABSA LIFE ASSURANCE | C6: 18687507 | D6: 3802084.8 | E6: 2866736.4 | F6: 0 | G6: 868386.26 | H6: 868386.26 | I6: 0 | J6: 0 | K6: 0 | L6: 422517.42 | M6: 349369.95 | N6: 949311.62 | O6: 0 | P6: 0 | Q6: 20863281
B7: APA LIFE ASSURANCE COMPANY | C7: 26630354 | D7: 5603012.7 | E7: 5283157.9 | F7: 0 | G7: 641105.63 | H7: 641105.63 | I7: 0 | J7: 0 | K7: 0 | L7: 520246.04 | M7: 126606.87 | N7: 1238296.6 | O7: 10411.334 | P7: 0 | Q7: 31853439
B8: BRITAM LIFE ASSURANCE | C8: 1.8998131e+08 | D8: 14648580 | E8: 14648755 | F8: 3860.959 | G8: 9168900.7 | H8: 9168900.7 | I8: 0 | J8: 0 | K8: 0 | L8: 594483.81 | M8: 1179434.2 | N8: 9276138.3 | O8: 68477.98 | P8: 0 | Q8: 2.0289877e+08
B9: CANNON LIFE ASSURANCE (K) LIMITED | C9: 817056.46 | D9: 176978.42 | E9: 99770.095 | F9: 0 | G9: 13598.417 | H9: 13598.417 | I9: 0 | J9: 0 | K9: 0 | L9: -1801.9807 | M9: 55696.881 | N9: 27912.033 | O9: 0 | P9: 0 | Q9: 877245.27
B10: CAPEX LIFE ASSURANCE COMPANY | C10: 1067477.1 | D10: 722509.44 | E10: 645132.63 | F10: 0 | G10: 280002.27 | H10: 280002.27 | I10: 0 | J10: 0 | K10: 0 | L10: 81525.174 | M10: 104689.7 | N10: 1351.796 | O10: 0 | P10: 0 | Q10: 1247744.4
B11: CIC LIFE ASSURANCE COMPANY | C11: 37938735 | D11: 5022013.2 | E11: 4410080.4 | F11: 0 | G11: 359397.77 | H11: 359397.77 | I11: 0 | J11: 0 | K11: 0 | L11: 569828.35 | M11: 645344.15 | N11: 0 | O11: 0 | P11: 0 | Q11: 40774245
B12: EQUITY LIFE ASSURANCE | C12: 27854399 | D12: 1968082.8 | E12: 1479864.1 | F12: 42083.237 | G12: 463945.53 | H12: 463945.53 | I12: 0 | J12: 0 | K12: 0 | L12: -11100.847 | M12: 171880.05 | N12: 983317.98 | O12: 45922.214 | P12: 0 | Q12: 29689018
B13: GA LIFE ASSURANCE COMPANY | C13: 62442570 | D13: 2400915 | E13: 2363997.9 | F13: 0 | G13: 912233.66 | H13: 912233.66 | I13: 0 | J13: 0 | K13: 0 | L13: 7653.616 | M13: 76477.122 | N13: 2431985.3 | O13: 0 | P13: 0 | Q13: 66242189
B14: GEMINIA LIFE INSURANCE COMPANY | C14: 3193546 | D14: 1265909.2 | E14: 1229136.9 | F14: 0 | G14: 853231.49 | H14: 47021.474 | I14: 806210.02 | J14: 0 | K14: 0 | L14: 31871.94 | M14: 73940.982 | N14: 0 | O14: 0 | P14: 0 | Q14: 3463638.4
B15: ICEA LION LIFE ASSURANCE | C15: 2.0907766e+08 | D15: 11451237 | E15: 11281456 | F15: 0 | G15: 5823003.5 | H15: 4924298.7 | I15: 198990.86 | J15: 0 | K15: 699713.98 | L15: 600356.77 | M15: 768976.07 | N15: 8685851 | O15: 0 | P15: 525000 | Q15: 2.2132763e+08
B16: JUBILEE LIFE INSURANCE | C16: 1.6546309e+08 | D16: 8369940.2 | E16: 8133418.9 | F16: 0 | G16: 4327618 | H16: 4327618 | I16: 0 | J16: 0 | K16: 0 | L16: 325135.96 | M16: 402618.11 | N16: 6843024.7 | O16: 35018.678 | P16: 0 | Q16: 1.7534914e+08
B17: KENINDIA ASSURANCE COMPANY | C17: 1.1059468e+08 | D17: 4394778.6 | E17: 4359580.6 | F17: 0 | G17: 3043435.9 | H17: 3043435.9 | I17: 0 | J17: 0 | K17: 0 | L17: 93145.386 | M17: 325502.61 | N17: 3864865.8 | O17: 2862.004 | P17: 189500 | Q17: 1.1516468e+08
... B27: THE MONARCH INSURANCE | C27: 0 | D27: 0 | E27: 0 | F27: 0 | G27: 0 | H27: 0 | I27: 0 | J27: 0 | K27: 0 | L27: 0 | M27: 0 | N27: 0 | O27: 0 | P27: 0 | Q27: 0
B28: TOTAL | C28: =SUM(C6:C27) -> 9.8797255e+08 | D28: =SUM(D6:D27) -> 72865101 | E28: =SUM(E6:E27) -> 68572445 | F28: =SUM(F6:F27) -> -380903.47 | G28: =SUM(G6:G27) -> 32447617 | H28: =SUM(H6:H27) -> 30738391 | I28: =SUM(I6:I27) -> 1005200.9 | J28: =SUM(J6:J27) -> 0 | ... Q28: =SUM(Q6:Q27) -> 1.0523373e+09
B29: REINSURERS
B30: CONTINENTAL REINSURANCE | C30: 0 | D30: 0 | E30: 0 | F30: 0 | G30: 0 | H30: 0 | I30: 0 | J30: 0 | K30: 0 | L30: 0 | M30: 0 | N30: 0 | O30: 0 | P30: 0 | Q30: 0
B31: EAST AFRICA REINSURANCE | C31: 1564966.8 | D31: 256732.76 | E31: 200253.38 | F31: 0 | G31: 83339.923 | H31: 83339.923 | I31: 0 | J31: 0 | K31: 0 | L31: 46516.158 | M31: 24972.055 | N31: 67687.47 | O31: 3203.8751 | P31: 0 | Q31: 1674875.6
B32: KENYA REINSURANCE CORPORATION | C32: 9413281.4 | D32: 705895.58 | E32: 705895.58 | F32: 0 | G32: 475440.11 | H32: 475440.11 | I32: 0 | J32: 0 | K32: 0 | L32: 238206.96 | M32: 17511.397 | N32: 243322.29 | O32: 0 | P32: 0 | Q32: 9631340.8
B33: TOTAL | C33: =SUM(C30:C32) -> 10978248 | D33: =SUM(D30:D32) -> 962628.33 | E33: =SUM(E30:E32) -> 906148.96 | F33: =SUM(F30:F32) -> 0 | G33: =SUM(G30:G32) -> 558780.04 | H33: =SUM(H30:H32) -> 558780.04 | I33: =SUM(I30:I32) -> 0 | J33: =SUM(J30:J32) -> 0 | ... Q33: =SUM(Q30:Q32) -> 11306216
B34: Amounts in Thousand Shillings

Sheet APPENDIX 18
B3: =_xlfn.CONCAT('Table of Contents'!B30,": ",'Table of Contents'!C30) -> APPENDIX 18: SUMMARY OF GROSS PREMIUM INCOME UNDER GENERAL INSURANCE BUSINESS FOR THE PERIOD ENDED 31.03.2026
B4: Company | C4: Aviation | D4: Engineering | E4: Fire Domestic | F4: Fire Industrial | G4: Liability | H4: Marine | I4: Motor Private | J4: Motor Commercial | K4: Motor Commercial PSV | L4: Personal Accident | M4: Theft | N4: Workmens' Compensation | O4: Medical | P4: Miscellaneous | Q4: Total_x000D_ | R4: Market Share (%)
B5: INSURERS
B6: =GDP!B6 -> AAR INSURANCE KENYA | C6: =GDP!C6+INWARD!C6 -> 0 | D6: =GDP!D6+INWARD!D6 -> 553.15363 | E6: =GDP!E6+INWARD!E6 -> 883.02476 | F6: =GDP!F6+INWARD!F6 -> 6400.3602 | G6: =GDP!G6+INWARD!G6 -> 11013.586 | H6: =GDP!H6+INWARD!H6 -> 1162.8895 | I6: =GDP!I6+INWARD!I6 -> 831.83488 | J6: =GDP!J6+INWARD!J6 -> 991.7484 | ... Q6: =GDP!Q6+INWARD!Q6 -> 3685906.5 | R6: =(Q6/$Q$41)*100 -> 4.5011717
B7: =GDP!B7 -> AFRICAN MERCHANT ASSURANCE | C7: =GDP!C7+INWARD!C7 -> 0 | D7: =GDP!D7+INWARD!D7 -> 9884.9031 | E7: =GDP!E7+INWARD!E7 -> 180.28551 | F7: =GDP!F7+INWARD!F7 -> 999.29943 | G7: =GDP!G7+INWARD!G7 -> 17424.306 | H7: =GDP!H7+INWARD!H7 -> 1460.3095 | I7: =GDP!I7+INWARD!I7 -> 130767.36 | J7: =GDP!J7+INWARD!J7 -> 419049.12 | ... Q7: =GDP!Q7+INWARD!Q7 -> 848299.34 | R7: =(Q7/$Q$41)*100 -> 1.03593
B8: =GDP!B8 -> APA INSURANCE LIMITED | C8: =GDP!C8+INWARD!C8 -> 146143 | D8: =GDP!D8+INWARD!D8 -> 155151.47 | E8: =GDP!E8+INWARD!E8 -> 46757.547 | F8: =GDP!F8+INWARD!F8 -> 1097792.7 | G8: =GDP!G8+INWARD!G8 -> 200769.13 | H8: =GDP!H8+INWARD!H8 -> 108758.31 | I8: =GDP!I8+INWARD!I8 -> 809829.3 | J8: =GDP!J8+INWARD!J8 -> 817147.74 | ... Q8: =GDP!Q8+INWARD!Q8 -> 7150288.1 | R8: =(Q8/$Q$41)*100 -> 8.7318207
B9: =GDP!B9 -> BRITAM GENERAL INSURANCE | C9: =GDP!C9+INWARD!C9 -> 102800.01 | D9: =GDP!D9+INWARD!D9 -> 285845.34 | E9: =GDP!E9+INWARD!E9 -> 64115.727 | F9: =GDP!F9+INWARD!F9 -> 574820.63 | G9: =GDP!G9+INWARD!G9 -> 189911.53 | H9: =GDP!H9+INWARD!H9 -> 161620.02 | I9: =GDP!I9+INWARD!I9 -> 581770.9 | J9: =GDP!J9+INWARD!J9 -> 214933.45 | ... Q9: =GDP!Q9+INWARD!Q9 -> 4893736.8 | R9: =(Q9/$Q$41)*100 -> 5.9761553
B10: =GDP!B10 -> BUPA GLOBAL INSURANCE | C10: =GDP!C10+INWARD!C10 -> 0 | D10: =GDP!D10+INWARD!D10 -> 0 | E10: =GDP!E10+INWARD!E10 -> 0 | F10: =GDP!F10+INWARD!F10 -> 0 | G10: =GDP!G10+INWARD!G10 -> 0 | H10: =GDP!H10+INWARD!H10 -> 0 | I10: =GDP!I10+INWARD!I10 -> 0 | J10: =GDP!J10+INWARD!J10 -> 0 | ... Q10: =GDP!Q10+INWARD!Q10 -> 2503251.7 | R10: =(Q10/$Q$41)*100 -> 3.0569321
B11: =GDP!B11 -> CANNON GENERAL INSURANCE | C11: =GDP!C11+INWARD!C11 -> 0 | D11: =GDP!D11+INWARD!D11 -> 16228.163 | E11: =GDP!E11+INWARD!E11 -> 4462.714 | F11: =GDP!F11+INWARD!F11 -> 32280.757 | G11: =GDP!G11+INWARD!G11 -> 12661.444 | H11: =GDP!H11+INWARD!H11 -> 20926.338 | I11: =GDP!I11+INWARD!I11 -> 304756.36 | J11: =GDP!J11+INWARD!J11 -> 84614.83 | ... Q11: =GDP!Q11+INWARD!Q11 -> 552542.83 | R11: =(Q11/$Q$41)*100 -> 0.67475672
B12: =GDP!B12 -> CIC GENERAL INSURANCE COMPANY | C12: =GDP!C12+INWARD!C12 -> 0 | D12: =GDP!D12+INWARD!D12 -> 101712.51 | E12: =GDP!E12+INWARD!E12 -> 41404.551 | F12: =GDP!F12+INWARD!F12 -> 193628.97 | G12: =GDP!G12+INWARD!G12 -> 81423.065 | H12: =GDP!H12+INWARD!H12 -> 13250.295 | I12: =GDP!I12+INWARD!I12 -> 1093604.6 | J12: =GDP!J12+INWARD!J12 -> 1004615.4 | ... Q12: =GDP!Q12+INWARD!Q12 -> 7498428.8 | R12: =(Q12/$Q$41)*100 -> 9.1569647
B13: =GDP!B13 -> DEFINITE ASSURANCE COMPANY | C13: =GDP!C13+INWARD!C13 -> 0 | D13: =GDP!D13+INWARD!D13 -> 0 | E13: =GDP!E13+INWARD!E13 -> 0 | F13: =GDP!F13+INWARD!F13 -> 0 | G13: =GDP!G13+INWARD!G13 -> 0 | H13: =GDP!H13+INWARD!H13 -> 0 | I13: =GDP!I13+INWARD!I13 -> 0 | J13: =GDP!J13+INWARD!J13 -> 0 | ... Q13: =GDP!Q13+INWARD!Q13 -> 0 | R13: =(Q13/$Q$41)*100 -> 0
B14: =GDP!B14 -> DIRECTLINE ASSURANCE COMPANY | C14: =GDP!C14+INWARD!C14 -> 0 | D14: =GDP!D14+INWARD!D14 -> 0 | E14: =GDP!E14+INWARD!E14 -> 0 | F14: =GDP!F14+INWARD!F14 -> 0 | G14: =GDP!G14+INWARD!G14 -> 0 | H14: =GDP!H14+INWARD!H14 -> 0 | I14: =GDP!I14+INWARD!I14 -> 111370.14 | J14: =GDP!J14+INWARD!J14 -> 36215.914 | ... Q14: =GDP!Q14+INWARD!Q14 -> 757751.16 | R14: =(Q14/$Q$41)*100 -> 0.92535393
B15: =GDP!B15 -> EQUITY GENERAL INSURANCE LIMITED | C15: =GDP!C15+INWARD!C15 -> 0 | D15: =GDP!D15+INWARD!D15 -> 24976.628 | E15: =GDP!E15+INWARD!E15 -> 285.567 | F15: =GDP!F15+INWARD!F15 -> 53862.87 | G15: =GDP!G15+INWARD!G15 -> 81387.634 | H15: =GDP!H15+INWARD!H15 -> 643.459 | I15: =GDP!I15+INWARD!I15 -> 12977.982 | J15: =GDP!J15+INWARD!J15 -> 0 | ... Q15: =GDP!Q15+INWARD!Q15 -> 594767.32 | R15: =(Q15/$Q$41)*100 -> 0.7263206
B16: =GDP!B16 -> EQUITY HEALTH INSURANCE LIMITED | C16: =GDP!C16+INWARD!C16 -> 0 | D16: =GDP!D16+INWARD!D16 -> 0 | E16: =GDP!E16+INWARD!E16 -> 0 | F16: =GDP!F16+INWARD!F16 -> 0 | G16: =GDP!G16+INWARD!G16 -> 0 | H16: =GDP!H16+INWARD!H16 -> 0 | I16: =GDP!I16+INWARD!I16 -> 0 | J16: =GDP!J16+INWARD!J16 -> 0 | ... Q16: =GDP!Q16+INWARD!Q16 -> 1204994.2 | R16: =(Q16/$Q$41)*100 -> 1.4715201
B17: =GDP!B17 -> FIDELITY SHIELD INSURANCE | C17: =GDP!C17+INWARD!C17 -> 119.264 | D17: =GDP!D17+INWARD!D17 -> 32429.582 | E17: =GDP!E17+INWARD!E17 -> 14939.301 | F17: =GDP!F17+INWARD!F17 -> 163102.2 | G17: =GDP!G17+INWARD!G17 -> 40844.639 | H17: =GDP!H17+INWARD!H17 -> 51092.726 | I17: =GDP!I17+INWARD!I17 -> 521508.87 | J17: =GDP!J17+INWARD!J17 -> 337538.83 | ... Q17: =GDP!Q17+INWARD!Q17 -> 1606633.7 | R17: =(Q17/$Q$41)*100 -> 1.9619961
... B40: =GDP!B40 -> THE MONARCH INSURANCE | C40: =GDP!C40+INWARD!C40 -> 0 | D40: =GDP!D40+INWARD!D40 -> 0 | E40: =GDP!E40+INWARD!E40 -> 0 | F40: =GDP!F40+INWARD!F40 -> 0 | G40: =GDP!G40+INWARD!G40 -> 0 | H40: =GDP!H40+INWARD!H40 -> 0 | I40: =GDP!I40+INWARD!I40 -> 0 | J40: =GDP!J40+INWARD!J40 -> 0 | ... Q40: =GDP!Q40+INWARD!Q40 -> 0 | R40: =(Q40/$Q$41)*100 -> 0
B41: TOTAL | C41: =SUM(C6:C40) -> 1150660.8 | D41: =SUM(D6:D40) -> 2543506.1 | E41: =SUM(E6:E40) -> 768668.25 | F41: =SUM(F6:F40) -> 9870190.2 | G41: =SUM(G6:G40) -> 2147973 | H41: =SUM(H6:H40) -> 1626347.3 | I41: =SUM(I6:I40) -> 9552572.1 | J41: =SUM(J6:J40) -> 8457893.6 | ... Q41: =SUM(Q6:Q40) -> 81887711 | R41: =(Q41/$Q$41)*100 -> 100
B42: REINSURERS
B43: =GDP!B43 -> CONTINENTAL REINSURANCE | C43: =GDP!C43+INWARD!C43 -> 5274.378 | D43: =GDP!D43+INWARD!D43 -> 185475.53 | E43: =GDP!E43+INWARD!E43 -> 241354.94 | F43: =GDP!F43+INWARD!F43 -> 686933.3 | G43: =GDP!G43+INWARD!G43 -> 102572.08 | H43: =GDP!H43+INWARD!H43 -> 60655.34 | I43: =GDP!I43+INWARD!I43 -> 26864.115 | J43: =GDP!J43+INWARD!J43 -> 114783.04 | ... Q43: =GDP!Q43+INWARD!Q43 -> 2231613.2 | R43: =Q43/$Q$48*100 -> 24.981463
B44: =GDP!B44 -> EAST AFRICA REINSURANCE | C44: =GDP!C44+INWARD!C44 -> 932.69701 | D44: =GDP!D44+INWARD!D44 -> 115411.59 | E44: =GDP!E44+INWARD!E44 -> 0 | F44: =GDP!F44+INWARD!F44 -> 629079.05 | G44: =GDP!G44+INWARD!G44 -> 22734.493 | H44: =GDP!H44+INWARD!H44 -> 53870.156 | I44: =GDP!I44+INWARD!I44 -> 0 | J44: =GDP!J44+INWARD!J44 -> 124013.49 | ... Q44: =GDP!Q44+INWARD!Q44 -> 1615442.2 | R44: =Q44/$Q$48*100 -> 18.083828
B45: =GDP!B45 -> GHANA REINSURANCE COMPANY | C45: =GDP!C45+INWARD!C45 -> 610.204 | D45: =GDP!D45+INWARD!D45 -> 36223.394 | E45: =GDP!E45+INWARD!E45 -> 51989.559 | F45: =GDP!F45+INWARD!F45 -> 381256.77 | G45: =GDP!G45+INWARD!G45 -> 24008.493 | H45: =GDP!H45+INWARD!H45 -> 26797.863 | I45: =GDP!I45+INWARD!I45 -> 28509.376 | J45: =GDP!J45+INWARD!J45 -> 30885.155 | ... Q45: =GDP!Q45+INWARD!Q45 -> 752831.47 | R45: =Q45/$Q$48*100 -> 8.4274603
B46: =GDP!B46 -> KENYA REINSURANCE CORPORATION | C46: =GDP!C46+INWARD!C46 -> 37117.939 | D46: =GDP!D46+INWARD!D46 -> 429012 | E46: =GDP!E46+INWARD!E46 -> 13385.789 | F46: =GDP!F46+INWARD!F46 -> 893574.23 | G46: =GDP!G46+INWARD!G46 -> 33883.287 | H46: =GDP!H46+INWARD!H46 -> 166192.39 | I46: =GDP!I46+INWARD!I46 -> 3802.0976 | J46: =GDP!J46+INWARD!J46 -> 208668 | ... Q46: =GDP!Q46+INWARD!Q46 -> 2858276.4 | R46: =Q46/$Q$48*100 -> 31.996551
B47: =GDP!B47 -> WAICA REINSURANCE KENYA LIMITED | C47: =GDP!C47+INWARD!C47 -> 14242.402 | D47: =GDP!D47+INWARD!D47 -> 201608.19 | E47: =GDP!E47+INWARD!E47 -> 110970.96 | F47: =GDP!F47+INWARD!F47 -> 525011.53 | G47: =GDP!G47+INWARD!G47 -> 54045.454 | H47: =GDP!H47+INWARD!H47 -> 64960.652 | I47: =GDP!I47+INWARD!I47 -> 22197.511 | J47: =GDP!J47+INWARD!J47 -> 46020.632 | ... Q47: =GDP!Q47+INWARD!Q47 -> 1474913.2 | R47: =Q47/$Q$48*100 -> 16.510697
B48: TOTAL | C48: =SUM(C43:C47) -> 58177.619 | D48: =SUM(D43:D47) -> 967730.7 | E48: =SUM(E43:E47) -> 417701.26 | F48: =SUM(F43:F47) -> 3115854.9 | G48: =SUM(G43:G47) -> 237243.8 | H48: =SUM(H43:H47) -> 372476.4 | I48: =SUM(I43:I47) -> 81373.099 | J48: =SUM(J43:J47) -> 524370.31 | ... R48: =SUM(R43:R47) -> 100
B49: Amounts in Thousand Shillings

Sheet GDP
B3: =_xlfn.CONCAT("GDP: SUMMARY OF GROSS DIRECT PREMIUM UNDER GENERAL INSURANCE BUSINESS FOR THE PERIOD ENDED"," ",Details!F18) -> GDP: SUMMARY OF GROSS DIRECT PREMIUM UNDER GENERAL INSURANCE BUSINESS FOR THE PERIOD ENDED 31.03.2026
B4: Company | C4: Aviation | D4: Engineering | E4: Fire Domestic | F4: Fire Industrial | G4: Liability | H4: Marine | I4: Motor Private | J4: Motor Commercial | K4: Motor Commercial PSV | L4: Personal Accident | M4: Theft | N4: Workmens' Compensation | O4: Medical | P4: Miscellaneous | Q4: Total_x000D_
B5: INSURERS
B6: AAR INSURANCE KENYA | C6: 0 | D6: 553.15363 | E6: 883.02476 | F6: 6400.3602 | G6: 11013.586 | H6: 1162.8895 | I6: 831.83488 | J6: 991.7484 | K6: 0 | L6: 4159.7112 | M6: 4056.6085 | N6: 31265.155 | O6: 3608864.2 | P6: 15724.251 | Q6: 3685906.5
B7: AFRICAN MERCHANT ASSURANCE | C7: 0 | D7: 9884.9031 | E7: 180.28551 | F7: 999.29943 | G7: 17424.306 | H7: 1460.3095 | I7: 130767.36 | J7: 419049.12 | K7: 206347.65 | L7: 6290.4838 | M7: 933.29363 | N7: 39521.213 | O7: 0 | P7: 15441.119 | Q7: 848299.34
B8: APA INSURANCE LIMITED | C8: 146143 | D8: 154835.03 | E8: 46757.547 | F8: 1086799.7 | G8: 200769.13 | H8: 108625.49 | I8: 809829.3 | J8: 817147.74 | K8: 0 | L8: 69113.758 | M8: 138163.36 | N8: 285271.47 | O8: 3086652.8 | P8: 122213.33 | Q8: 7072321.7
B9: BRITAM GENERAL INSURANCE | C9: 102800.01 | D9: 279643.5 | E9: 64115.727 | F9: 541621.09 | G9: 189740.92 | H9: 136447.23 | I9: 581770.9 | J9: 214933.45 | K9: 0 | L9: 99999.67 | M9: 53837.592 | N9: 297539.49 | O9: 2224467 | P9: 28666.335 | Q9: 4815583
B10: BUPA GLOBAL INSURANCE | C10: 0 | D10: 0 | E10: 0 | F10: 0 | G10: 0 | H10: 0 | I10: 0 | J10: 0 | K10: 0 | L10: 0 | M10: 0 | N10: 0 | O10: 2503251.7 | P10: 0 | Q10: 2503251.7
B11: CANNON GENERAL INSURANCE | C11: 0 | D11: 16224.012 | E11: 4462.714 | F11: 30727.725 | G11: 12299.434 | H11: 20559.229 | I11: 304739.51 | J11: 84570.952 | K11: 0 | L11: 5682.62 | M11: 9829.838 | N11: 41139.26 | O11: 0 | P11: 14123.126 | Q11: 544358.42
B12: CIC GENERAL INSURANCE COMPANY | C12: 0 | D12: 50524.063 | E12: 41404.551 | F12: 181827.64 | G12: 81423.065 | H12: 12898.716 | I12: 1093604.6 | J12: 1004615.4 | K12: 0 | L12: 160370.96 | M12: 405935.78 | N12: 231298.32 | O12: 4058650.8 | P12: 90173.185 | Q12: 7412727
B13: DEFINITE ASSURANCE COMPANY | C13: 0 | D13: 0 | E13: 0 | F13: 0 | G13: 0 | H13: 0 | I13: 0 | J13: 0 | K13: 0 | L13: 0 | M13: 0 | N13: 0 | O13: 0 | P13: 0 | Q13: 0
B14: DIRECTLINE ASSURANCE COMPANY | C14: 0 | D14: 0 | E14: 0 | F14: 0 | G14: 0 | H14: 0 | I14: 111370.14 | J14: 36215.914 | K14: 610165.11 | L14: 0 | M14: 0 | N14: 0 | O14: 0 | P14: 0 | Q14: 757751.16
B15: EQUITY GENERAL INSURANCE LIMITED | C15: 0 | D15: 24976.628 | E15: 285.567 | F15: 53862.87 | G15: 81387.634 | H15: 643.459 | I15: 12977.982 | J15: 0 | K15: 0 | L15: 263.398 | M15: 419607.62 | N15: 762.161 | O15: 0 | P15: 0 | Q15: 594767.32
B16: EQUITY HEALTH INSURANCE LIMITED | C16: 0 | D16: 0 | E16: 0 | F16: 0 | G16: 0 | H16: 0 | I16: 0 | J16: 0 | K16: 0 | L16: 0 | M16: 0 | N16: 0 | O16: 1204994.2 | P16: 0 | Q16: 1204994.2
B17: FIDELITY SHIELD INSURANCE | C17: 119.264 | D17: 32429.582 | E17: 14939.301 | F17: 163102.2 | G17: 39739.639 | H17: 51092.726 | I17: 521508.87 | J17: 337538.83 | K17: 7480.934 | L17: 3852.109 | M17: 36140.312 | N17: 133419.2 | O17: 199207.06 | P17: 64958.665 | Q17: 1605528.7
... B40: THE MONARCH INSURANCE | C40: 0 | D40: 0 | E40: 0 | F40: 0 | G40: 0 | H40: 0 | I40: 0 | J40: 0 | K40: 0 | L40: 0 | M40: 0 | N40: 0 | O40: 0 | P40: 0 | Q40: 0
B41: TOTAL | C41: =SUM(C6:C40) -> 1072126.4 | D41: =SUM(D6:D40) -> 2381187.5 | E41: =SUM(E6:E40) -> 768668.25 | F41: =SUM(F6:F40) -> 9578455 | G41: =SUM(G6:G40) -> 2081082.6 | H41: =SUM(H6:H40) -> 1547682.3 | I41: =SUM(I6:I40) -> 9549674.4 | J41: =SUM(J6:J40) -> 8457196.4 | ... Q41: =SUM(Q6:Q40) -> 80872202
B42: CONTINENTAL REINSURANCE
B43: CONTINENTAL REINSURANCE | C43: 0 | D43: 0 | E43: 0 | F43: 0 | G43: 0 | H43: 0 | I43: 0 | J43: 0 | K43: 0 | L43: 0 | M43: 0 | N43: 0 | O43: 0 | P43: 0 | Q43: 0
B44: EAST AFRICA REINSURANCE | C44: 0 | D44: 0 | E44: 0 | F44: 0 | G44: 0 | H44: 0 | I44: 0 | J44: 0 | K44: 0 | L44: 0 | M44: 0 | N44: 0 | O44: 0 | P44: 0 | Q44: 0
B45: GHANA REINSURANCE COMPANY | C45: 0 | D45: 0 | E45: 0 | F45: 0 | G45: 0 | H45: 0 | I45: 0 | J45: 0 | K45: 0 | L45: 0 | M45: 0 | N45: 0 | O45: 0 | P45: 0 | Q45: 0
B46: KENYA REINSURANCE CORPORATION | C46: 37117.939 | D46: 429012 | E46: 13385.789 | F46: 893574.23 | G46: 33883.287 | H46: 166192.39 | I46: 3802.0976 | J46: 208668 | K46: 0 | L46: 155819.05 | M46: 12906.042 | N46: 23664.948 | O46: 378275.93 | P46: 501974.67 | Q46: 2858276.4
B47: WAICA REINSURANCE KENYA LIMITED | C47: 0 | D47: 0 | E47: 0 | F47: 0 | G47: 0 | H47: 0 | I47: 0 | J47: 0 | K47: 0 | L47: 0 | M47: 0 | N47: 0 | O47: 0 | P47: 0 | Q47: 0
B48: TOTAL | C48: =SUM(C43:C47) -> 37117.939 | D48: =SUM(D43:D47) -> 429012 | E48: =SUM(E43:E47) -> 13385.789 | F48: =SUM(F43:F47) -> 893574.23 | G48: =SUM(G43:G47) -> 33883.287 | H48: =SUM(H43:H47) -> 166192.39 | I48: =SUM(I43:I47) -> 3802.0976 | J48: =SUM(J43:J47) -> 208668 | ... Q48: =SUM(Q43:Q47) -> 2858276.4
B49: Amounts in Thousand Shillings

Sheet INWARD
B3: =_xlfn.CONCAT("INWARD: SUMMARY OF NET PREMIUM INCOME UNDER GENERAL INSURANCE BUSINESS FOR THE PERIOD ENDED"," ",Details!F18) -> INWARD: SUMMARY OF NET PREMIUM INCOME UNDER GENERAL INSURANCE BUSINESS FOR THE PERIOD ENDED 31.03.2026
B4: Company | C4: Aviation | D4: Engineering | E4: Fire Domestic | F4: Fire Industrial | G4: Liability | H4: Marine | I4: Motor Private | J4: Motor Commercial | K4: Motor Commercial PSV | L4: Personal Accident | M4: Theft | N4: Workmens' Compensation | O4: Medical | P4: Miscellaneous | Q4: Total_x000D_
B5: INSURERS
B6: AAR INSURANCE KENYA | C6: 0 | D6: 0 | E6: 0 | F6: 0 | G6: 0 | H6: 0 | I6: 0 | J6: 0 | K6: 0 | L6: 0 | M6: 0 | N6: 0 | O6: 0 | P6: 0 | Q6: 0
B7: AFRICAN MERCHANT ASSURANCE | C7: 0 | D7: 0 | E7: 0 | F7: 0 | G7: 0 | H7: 0 | I7: 0 | J7: 0 | K7: 0 | L7: 0 | M7: 0 | N7: 0 | O7: 0 | P7: 0 | Q7: 0
B8: APA INSURANCE LIMITED | C8: 0 | D8: 316.436 | E8: 0 | F8: 10992.954 | G8: 0 | H8: 132.82 | I8: 0 | J8: 0 | K8: 0 | L8: 40047.623 | M8: 0 | N8: 26476.564 | O8: 0 | P8: 0 | Q8: 77966.397
B9: BRITAM GENERAL INSURANCE | C9: 0 | D9: 6201.8411 | E9: 0 | F9: 33199.542 | G9: 170.604 | H9: 25172.79 | I9: 0 | J9: 0 | K9: 0 | L9: 5457.2738 | M9: 6809.9423 | N9: 1141.8255 | O9: 0 | P9: 0 | Q9: 78153.819
B10: BUPA GLOBAL INSURANCE | C10: 0 | D10: 0 | E10: 0 | F10: 0 | G10: 0 | H10: 0 | I10: 0 | J10: 0 | K10: 0 | L10: 0 | M10: 0 | N10: 0 | O10: 0 | P10: 0 | Q10: 0
B11: CANNON GENERAL INSURANCE | C11: 0 | D11: 4.151 | E11: 0 | F11: 1553.032 | G11: 362.01 | H11: 367.109 | I11: 16.85 | J11: 43.878 | K11: 0 | L11: 0 | M11: 0 | N11: 5554.355 | O11: 0 | P11: 283.03 | Q11: 8184.415
B12: CIC GENERAL INSURANCE COMPANY | C12: 0 | D12: 51188.451 | E12: 0 | F12: 11801.331 | G12: 0 | H12: 351.57871 | I12: 0 | J12: 0 | K12: 0 | L12: 0 | M12: 0 | N12: 22360.438 | O12: 0 | P12: 0 | Q12: 85701.798
B13: DEFINITE ASSURANCE COMPANY | C13: 0 | D13: 0 | E13: 0 | F13: 0 | G13: 0 | H13: 0 | I13: 0 | J13: 0 | K13: 0 | L13: 0 | M13: 0 | N13: 0 | O13: 0 | P13: 0 | Q13: 0
B14: DIRECTLINE ASSURANCE COMPANY | C14: 0 | D14: 0 | E14: 0 | F14: 0 | G14: 0 | H14: 0 | I14: 0 | J14: 0 | K14: 0 | L14: 0 | M14: 0 | N14: 0 | O14: 0 | P14: 0 | Q14: 0
B15: EQUITY GENERAL INSURANCE LIMITED | C15: 0 | D15: 0 | E15: 0 | F15: 0 | G15: 0 | H15: 0 | I15: 0 | J15: 0 | K15: 0 | L15: 0 | M15: 0 | N15: 0 | O15: 0 | P15: 0 | Q15: 0
B16: EQUITY HEALTH INSURANCE LIMITED | C16: 0 | D16: 0 | E16: 0 | F16: 0 | G16: 0 | H16: 0 | I16: 0 | J16: 0 | K16: 0 | L16: 0 | M16: 0 | N16: 0 | O16: 0 | P16: 0 | Q16: 0
B17: FIDELITY SHIELD INSURANCE | C17: 0 | D17: 0 | E17: 0 | F17: 0 | G17: 1105 | H17: 0 | I17: 0 | J17: 0 | K17: 0 | L17: 0 | M17: 0 | N17: 0 | O17: 0 | P17: 0 | Q17: 1105
... B40: THE MONARCH INSURANCE | C40: 0 | D40: 0 | E40: 0 | F40: 0 | G40: 0 | H40: 0 | I40: 0 | J40: 0 | K40: 0 | L40: 0 | M40: 0 | N40: 0 | O40: 0 | P40: 0 | Q40: 0
B41: TOTAL | C41: =SUM(C6:C40) -> 78534.43 | D41: =SUM(D6:D40) -> 162318.6 | E41: =SUM(E6:E40) -> 0 | F41: =SUM(F6:F40) -> 291735.16 | G41: =SUM(G6:G40) -> 66890.41 | H41: =SUM(H6:H40) -> 78664.925 | I41: =SUM(I6:I40) -> 2897.715 | J41: =SUM(J6:J40) -> 697.241 | ... Q41: =SUM(Q6:Q40) -> 1015509.8
B42: CONTINENTAL REINSURANCE
B43: CONTINENTAL REINSURANCE | C43: 5274.378 | D43: 185475.53 | E43: 241354.94 | F43: 686933.3 | G43: 102572.08 | H43: 60655.34 | I43: 26864.115 | J43: 114783.04 | K43: 0 | L43: 72189.141 | M43: 3799.429 | N43: 7598.857 | O43: 427757.66 | P43: 296355.42 | Q43: 2231613.2
B44: EAST AFRICA REINSURANCE | C44: 932.69701 | D44: 115411.59 | E44: 0 | F44: 629079.05 | G44: 22734.493 | H44: 53870.156 | I44: 0 | J44: 124013.49 | K44: 0 | L44: 47657.196 | M44: 0 | N44: 0 | O44: 357483.57 | P44: 264259.94 | Q44: 1615442.2
B45: GHANA REINSURANCE COMPANY | C45: 610.204 | D45: 36223.394 | E45: 51989.559 | F45: 381256.77 | G45: 24008.493 | H45: 26797.863 | I45: 28509.376 | J45: 30885.155 | K45: 0 | L45: 1975.815 | M45: 4670.389 | N45: 13103.54 | O45: 96179.642 | P45: 56621.273 | Q45: 752831.47
B46: KENYA REINSURANCE CORPORATION | C46: 0 | D46: 0 | E46: 0 | F46: 0 | G46: 0 | H46: 0 | I46: 0 | J46: 0 | K46: 0 | L46: 0 | M46: 0 | N46: 0 | O46: 0 | P46: 0 | Q46: 0
B47: WAICA REINSURANCE KENYA LIMITED | C47: 14242.402 | D47: 201608.19 | E47: 110970.96 | F47: 525011.53 | G47: 54045.454 | H47: 64960.652 | I47: 22197.511 | J47: 46020.632 | K47: 0 | L47: 342270.47 | M47: 14420.258 | N47: 0 | O47: 7906.069 | P47: 71259.108 | Q47: 1474913.2
B48: TOTAL | C48: =SUM(C43:C47) -> 21059.681 | D48: =SUM(D43:D47) -> 538718.7 | E48: =SUM(E43:E47) -> 404315.47 | F48: =SUM(F43:F47) -> 2222280.6 | G48: =SUM(G43:G47) -> 203360.52 | H48: =SUM(H43:H47) -> 206284.01 | I48: =SUM(I43:I47) -> 77571.002 | J48: =SUM(J43:J47) -> 315702.31 | ... Q48: =SUM(Q43:Q47) -> 6074800.1
B49: Amounts in Thousand Shillings

Sheet APPENDIX 19
B3: =_xlfn.CONCAT('Table of Contents'!B31,": ",'Table of Contents'!C31) -> APPENDIX 19: SUMMARY OF GENERAL INSURANCE BUSINESS MARKET SHARE PER CLASS FOR THE PERIOD ENDED 31.03.2026
B4: Company | C4: Aviation | D4: Engineering | E4: Fire Domestic | F4: Fire Industrial | G4: Liability | H4: Marine | I4: Motor Private | J4: Motor Commercial | K4: Motor Commercial PSV | L4: Personal Accident | M4: Theft | N4: Workmens' Compensation | O4: Medical | P4: Miscellaneous | Q4: Total
B5: INSURERS
B6: ='APPENDIX 18'!B6 -> AAR INSURANCE KENYA | C6: =IFERROR('APPENDIX 18'!C6/'APPENDIX 18'!C$41*100,"") -> 0 | D6: =IFERROR('APPENDIX 18'!D6/'APPENDIX 18'!D$41*100,"") -> 0.021747682 | E6: =IFERROR('APPENDIX 18'!E6/'APPENDIX 18'!E$41*100,"") -> 0.11487723 | F6: =IFERROR('APPENDIX 18'!F6/'APPENDIX 18'!F$41*100,"") -> 0.064845358 | G6: =IFERROR('APPENDIX 18'!G6/'APPENDIX 18'!G$41*100,"") -> 0.5127432 | H6: =IFERROR('APPENDIX 18'!H6/'APPENDIX 18'!H$41*100,"") -> 0.071503147 | I6: =IFERROR('APPENDIX 18'!I6/'APPENDIX 18'!I$41*100,"") -> 0.0087079676 | J6: =IFERROR('APPENDIX 18'!J6/'APPENDIX 18'!J$41*100,"") -> 0.011725714 | ... P6: =IFERROR('APPENDIX 18'!P6/'APPENDIX 18'!P$41*100,"") -> 0.85643015 | Q6: =IFERROR('APPENDIX 18'!$Q6/'APPENDIX 18'!Q$41*100,"") -> 4.5011717 | S6: =COUNTIF(Q6:Q40,">5") -> 7
B7: ='APPENDIX 18'!B7 -> AFRICAN MERCHANT ASSURANCE | C7: =IFERROR('APPENDIX 18'!C7/'APPENDIX 18'!C$41*100,"") -> 0 | D7: =IFERROR('APPENDIX 18'!D7/'APPENDIX 18'!D$41*100,"") -> 0.38863296 | E7: =IFERROR('APPENDIX 18'!E7/'APPENDIX 18'!E$41*100,"") -> 0.023454268 | F7: =IFERROR('APPENDIX 18'!F7/'APPENDIX 18'!F$41*100,"") -> 0.010124419 | G7: =IFERROR('APPENDIX 18'!G7/'APPENDIX 18'!G$41*100,"") -> 0.8111976 | H7: =IFERROR('APPENDIX 18'!H7/'APPENDIX 18'!H$41*100,"") -> 0.089790756 | I7: =IFERROR('APPENDIX 18'!I7/'APPENDIX 18'!I$41*100,"") -> 1.368923 | J7: =IFERROR('APPENDIX 18'!J7/'APPENDIX 18'!J$41*100,"") -> 4.9545329 | ... P7: =IFERROR('APPENDIX 18'!P7/'APPENDIX 18'!P$41*100,"") -> 0.84100924 | Q7: =IFERROR('APPENDIX 18'!$Q7/'APPENDIX 18'!Q$41*100,"") -> 1.03593
B8: ='APPENDIX 18'!B8 -> APA INSURANCE LIMITED | C8: =IFERROR('APPENDIX 18'!C8/'APPENDIX 18'!C$41*100,"") -> 12.700789 | D8: =IFERROR('APPENDIX 18'!D8/'APPENDIX 18'!D$41*100,"") -> 6.0999055 | E8: =IFERROR('APPENDIX 18'!E8/'APPENDIX 18'!E$41*100,"") -> 6.0829294 | F8: =IFERROR('APPENDIX 18'!F8/'APPENDIX 18'!F$41*100,"") -> 11.122305 | G8: =IFERROR('APPENDIX 18'!G8/'APPENDIX 18'!G$41*100,"") -> 9.346911 | H8: =IFERROR('APPENDIX 18'!H8/'APPENDIX 18'!H$41*100,"") -> 6.687275 | I8: =IFERROR('APPENDIX 18'!I8/'APPENDIX 18'!I$41*100,"") -> 8.4776047 | J8: =IFERROR('APPENDIX 18'!J8/'APPENDIX 18'!J$41*100,"") -> 9.6613623 | ... P8: =IFERROR('APPENDIX 18'!P8/'APPENDIX 18'!P$41*100,"") -> 6.6564174 | Q8: =IFERROR('APPENDIX 18'!$Q8/'APPENDIX 18'!Q$41*100,"") -> 8.7318207
B9: ='APPENDIX 18'!B9 -> BRITAM GENERAL INSURANCE | C9: =IFERROR('APPENDIX 18'!C9/'APPENDIX 18'!C$41*100,"") -> 8.9339975 | D9: =IFERROR('APPENDIX 18'!D9/'APPENDIX 18'!D$41*100,"") -> 11.238241 | E9: =IFERROR('APPENDIX 18'!E9/'APPENDIX 18'!E$41*100,"") -> 8.3411442 | F9: =IFERROR('APPENDIX 18'!F9/'APPENDIX 18'!F$41*100,"") -> 5.823805 | G9: =IFERROR('APPENDIX 18'!G9/'APPENDIX 18'!G$41*100,"") -> 8.8414297 | H9: =IFERROR('APPENDIX 18'!H9/'APPENDIX 18'!H$41*100,"") -> 9.9376085 | I9: =IFERROR('APPENDIX 18'!I9/'APPENDIX 18'!I$41*100,"") -> 6.0902016 | J9: =IFERROR('APPENDIX 18'!J9/'APPENDIX 18'!J$41*100,"") -> 2.5412173 | ... P9: =IFERROR('APPENDIX 18'!P9/'APPENDIX 18'!P$41*100,"") -> 1.5613281 | Q9: =IFERROR('APPENDIX 18'!$Q9/'APPENDIX 18'!Q$41*100,"") -> 5.9761553
B10: ='APPENDIX 18'!B10 -> BUPA GLOBAL INSURANCE | C10: =IFERROR('APPENDIX 18'!C10/'APPENDIX 18'!C$41*100,"") -> 0 | D10: =IFERROR('APPENDIX 18'!D10/'APPENDIX 18'!D$41*100,"") -> 0 | E10: =IFERROR('APPENDIX 18'!E10/'APPENDIX 18'!E$41*100,"") -> 0 | F10: =IFERROR('APPENDIX 18'!F10/'APPENDIX 18'!F$41*100,"") -> 0 | G10: =IFERROR('APPENDIX 18'!G10/'APPENDIX 18'!G$41*100,"") -> 0 | H10: =IFERROR('APPENDIX 18'!H10/'APPENDIX 18'!H$41*100,"") -> 0 | I10: =IFERROR('APPENDIX 18'!I10/'APPENDIX 18'!I$41*100,"") -> 0 | J10: =IFERROR('APPENDIX 18'!J10/'APPENDIX 18'!J$41*100,"") -> 0 | ... P10: =IFERROR('APPENDIX 18'!P10/'APPENDIX 18'!P$41*100,"") -> 0 | Q10: =IFERROR('APPENDIX 18'!$Q10/'APPENDIX 18'!Q$41*100,"") -> 3.0569321
B11: ='APPENDIX 18'!B11 -> CANNON GENERAL INSURANCE | C11: =IFERROR('APPENDIX 18'!C11/'APPENDIX 18'!C$41*100,"") -> 0 | D11: =IFERROR('APPENDIX 18'!D11/'APPENDIX 18'!D$41*100,"") -> 0.63802335 | E11: =IFERROR('APPENDIX 18'!E11/'APPENDIX 18'!E$41*100,"") -> 0.58057738 | F11: =IFERROR('APPENDIX 18'!F11/'APPENDIX 18'!F$41*100,"") -> 0.32705304 | G11: =IFERROR('APPENDIX 18'!G11/'APPENDIX 18'!G$41*100,"") -> 0.5894601 | H11: =IFERROR('APPENDIX 18'!H11/'APPENDIX 18'!H$41*100,"") -> 1.2867079 | I11: =IFERROR('APPENDIX 18'!I11/'APPENDIX 18'!I$41*100,"") -> 3.1903068 | J11: =IFERROR('APPENDIX 18'!J11/'APPENDIX 18'!J$41*100,"") -> 1.0004244 | ... P11: =IFERROR('APPENDIX 18'!P11/'APPENDIX 18'!P$41*100,"") -> 0.78463938 | Q11: =IFERROR('APPENDIX 18'!$Q11/'APPENDIX 18'!Q$41*100,"") -> 0.67475672
B12: ='APPENDIX 18'!B12 -> CIC GENERAL INSURANCE COMPANY | C12: =IFERROR('APPENDIX 18'!C12/'APPENDIX 18'!C$41*100,"") -> 0 | D12: =IFERROR('APPENDIX 18'!D12/'APPENDIX 18'!D$41*100,"") -> 3.9989098 | E12: =IFERROR('APPENDIX 18'!E12/'APPENDIX 18'!E$41*100,"") -> 5.3865306 | F12: =IFERROR('APPENDIX 18'!F12/'APPENDIX 18'!F$41*100,"") -> 1.9617552 | G12: =IFERROR('APPENDIX 18'!G12/'APPENDIX 18'!G$41*100,"") -> 3.7906931 | H12: =IFERROR('APPENDIX 18'!H12/'APPENDIX 18'!H$41*100,"") -> 0.81472729 | I12: =IFERROR('APPENDIX 18'!I12/'APPENDIX 18'!I$41*100,"") -> 11.448274 | J12: =IFERROR('APPENDIX 18'!J12/'APPENDIX 18'!J$41*100,"") -> 11.877844 | ... P12: =IFERROR('APPENDIX 18'!P12/'APPENDIX 18'!P$41*100,"") -> 4.9113332 | Q12: =IFERROR('APPENDIX 18'!$Q12/'APPENDIX 18'!Q$41*100,"") -> 9.1569647
B13: ='APPENDIX 18'!B13 -> DEFINITE ASSURANCE COMPANY | C13: =IFERROR('APPENDIX 18'!C13/'APPENDIX 18'!C$41*100,"") -> 0 | D13: =IFERROR('APPENDIX 18'!D13/'APPENDIX 18'!D$41*100,"") -> 0 | E13: =IFERROR('APPENDIX 18'!E13/'APPENDIX 18'!E$41*100,"") -> 0 | F13: =IFERROR('APPENDIX 18'!F13/'APPENDIX 18'!F$41*100,"") -> 0 | G13: =IFERROR('APPENDIX 18'!G13/'APPENDIX 18'!G$41*100,"") -> 0 | H13: =IFERROR('APPENDIX 18'!H13/'APPENDIX 18'!H$41*100,"") -> 0 | I13: =IFERROR('APPENDIX 18'!I13/'APPENDIX 18'!I$41*100,"") -> 0 | J13: =IFERROR('APPENDIX 18'!J13/'APPENDIX 18'!J$41*100,"") -> 0 | ... P13: =IFERROR('APPENDIX 18'!P13/'APPENDIX 18'!P$41*100,"") -> 0 | Q13: =IFERROR('APPENDIX 18'!$Q13/'APPENDIX 18'!Q$41*100,"") -> 0
B14: ='APPENDIX 18'!B14 -> DIRECTLINE ASSURANCE COMPANY | C14: =IFERROR('APPENDIX 18'!C14/'APPENDIX 18'!C$41*100,"") -> 0 | D14: =IFERROR('APPENDIX 18'!D14/'APPENDIX 18'!D$41*100,"") -> 0 | E14: =IFERROR('APPENDIX 18'!E14/'APPENDIX 18'!E$41*100,"") -> 0 | F14: =IFERROR('APPENDIX 18'!F14/'APPENDIX 18'!F$41*100,"") -> 0 | G14: =IFERROR('APPENDIX 18'!G14/'APPENDIX 18'!G$41*100,"") -> 0 | H14: =IFERROR('APPENDIX 18'!H14/'APPENDIX 18'!H$41*100,"") -> 0 | I14: =IFERROR('APPENDIX 18'!I14/'APPENDIX 18'!I$41*100,"") -> 1.1658654 | J14: =IFERROR('APPENDIX 18'!J14/'APPENDIX 18'!J$41*100,"") -> 0.42819071 | ... P14: =IFERROR('APPENDIX 18'!P14/'APPENDIX 18'!P$41*100,"") -> 0 | Q14: =IFERROR('APPENDIX 18'!$Q14/'APPENDIX 18'!Q$41*100,"") -> 0.92535393
B15: ='APPENDIX 18'!B15 -> EQUITY GENERAL INSURANCE LIMITED | C15: =IFERROR('APPENDIX 18'!C15/'APPENDIX 18'!C$41*100,"") -> 0 | D15: =IFERROR('APPENDIX 18'!D15/'APPENDIX 18'!D$41*100,"") -> 0.98197633 | E15: =IFERROR('APPENDIX 18'!E15/'APPENDIX 18'!E$41*100,"") -> 0.037150877 | F15: =IFERROR('APPENDIX 18'!F15/'APPENDIX 18'!F$41*100,"") -> 0.54571258 | G15: =IFERROR('APPENDIX 18'!G15/'APPENDIX 18'!G$41*100,"") -> 3.7890436 | H15: =IFERROR('APPENDIX 18'!H15/'APPENDIX 18'!H$41*100,"") -> 0.039564674 | I15: =IFERROR('APPENDIX 18'!I15/'APPENDIX 18'!I$41*100,"") -> 0.13585851 | J15: =IFERROR('APPENDIX 18'!J15/'APPENDIX 18'!J$41*100,"") -> 0 | ... P15: =IFERROR('APPENDIX 18'!P15/'APPENDIX 18'!P$41*100,"") -> 0 | Q15: =IFERROR('APPENDIX 18'!$Q15/'APPENDIX 18'!Q$41*100,"") -> 0.7263206
B16: ='APPENDIX 18'!B16 -> EQUITY HEALTH INSURANCE LIMITED | C16: =IFERROR('APPENDIX 18'!C16/'APPENDIX 18'!C$41*100,"") -> 0 | D16: =IFERROR('APPENDIX 18'!D16/'APPENDIX 18'!D$41*100,"") -> 0 | E16: =IFERROR('APPENDIX 18'!E16/'APPENDIX 18'!E$41*100,"") -> 0 | F16: =IFERROR('APPENDIX 18'!F16/'APPENDIX 18'!F$41*100,"") -> 0 | G16: =IFERROR('APPENDIX 18'!G16/'APPENDIX 18'!G$41*100,"") -> 0 | H16: =IFERROR('APPENDIX 18'!H16/'APPENDIX 18'!H$41*100,"") -> 0 | I16: =IFERROR('APPENDIX 18'!I16/'APPENDIX 18'!I$41*100,"") -> 0 | J16: =IFERROR('APPENDIX 18'!J16/'APPENDIX 18'!J$41*100,"") -> 0 | ... P16: =IFERROR('APPENDIX 18'!P16/'APPENDIX 18'!P$41*100,"") -> 0 | Q16: =IFERROR('APPENDIX 18'!$Q16/'APPENDIX 18'!Q$41*100,"") -> 1.4715201
B17: ='APPENDIX 18'!B17 -> FIDELITY SHIELD INSURANCE | C17: =IFERROR('APPENDIX 18'!C17/'APPENDIX 18'!C$41*100,"") -> 0.010364827 | D17: =IFERROR('APPENDIX 18'!D17/'APPENDIX 18'!D$41*100,"") -> 1.2749952 | E17: =IFERROR('APPENDIX 18'!E17/'APPENDIX 18'!E$41*100,"") -> 1.9435304 | F17: =IFERROR('APPENDIX 18'!F17/'APPENDIX 18'!F$41*100,"") -> 1.6524727 | G17: =IFERROR('APPENDIX 18'!G17/'APPENDIX 18'!G$41*100,"") -> 1.9015434 | H17: =IFERROR('APPENDIX 18'!H17/'APPENDIX 18'!H$41*100,"") -> 3.1415631 | I17: =IFERROR('APPENDIX 18'!I17/'APPENDIX 18'!I$41*100,"") -> 5.4593555 | J17: =IFERROR('APPENDIX 18'!J17/'APPENDIX 18'!J$41*100,"") -> 3.9908143 | ... P17: =IFERROR('APPENDIX 18'!P17/'APPENDIX 18'!P$41*100,"") -> 3.5380102 | Q17: =IFERROR('APPENDIX 18'!$Q17/'APPENDIX 18'!Q$41*100,"") -> 1.9619961
B18: ='APPENDIX 18'!B18 -> FIRST ASSURANCE COMPANY | C18: =IFERROR('APPENDIX 18'!C18/'APPENDIX 18'!C$41*100,"") -> 0 | D18: =IFERROR('APPENDIX 18'!D18/'APPENDIX 18'!D$41*100,"") -> 3.6418159 | E18: =IFERROR('APPENDIX 18'!E18/'APPENDIX 18'!E$41*100,"") -> 2.5828983 | F18: =IFERROR('APPENDIX 18'!F18/'APPENDIX 18'!F$41*100,"") -> 2.8581179 | G18: =IFERROR('APPENDIX 18'!G18/'APPENDIX 18'!G$41*100,"") -> 1.8615966 | H18: =IFERROR('APPENDIX 18'!H18/'APPENDIX 18'!H$41*100,"") -> 2.7710714 | I18: =IFERROR('APPENDIX 18'!I18/'APPENDIX 18'!I$41*100,"") -> 2.5885488 | J18: =IFERROR('APPENDIX 18'!J18/'APPENDIX 18'!J$41*100,"") -> 2.2008709 | ... P18: =IFERROR('APPENDIX 18'!P18/'APPENDIX 18'!P$41*100,"") -> 2.6042602 | Q18: =IFERROR('APPENDIX 18'!$Q18/'APPENDIX 18'!Q$41*100,"") -> 2.8625952
... B40: ='APPENDIX 18'!B40 -> THE MONARCH INSURANCE | C40: =IFERROR('APPENDIX 18'!C40/'APPENDIX 18'!C$41*100,"") -> 0 | D40: =IFERROR('APPENDIX 18'!D40/'APPENDIX 18'!D$41*100,"") -> 0 | E40: =IFERROR('APPENDIX 18'!E40/'APPENDIX 18'!E$41*100,"") -> 0 | F40: =IFERROR('APPENDIX 18'!F40/'APPENDIX 18'!F$41*100,"") -> 0 | G40: =IFERROR('APPENDIX 18'!G40/'APPENDIX 18'!G$41*100,"") -> 0 | H40: =IFERROR('APPENDIX 18'!H40/'APPENDIX 18'!H$41*100,"") -> 0 | I40: =IFERROR('APPENDIX 18'!I40/'APPENDIX 18'!I$41*100,"") -> 0 | J40: =IFERROR('APPENDIX 18'!J40/'APPENDIX 18'!J$41*100,"") -> 0 | ... P40: =IFERROR('APPENDIX 18'!P40/'APPENDIX 18'!P$41*100,"") -> 0 | Q40: =IFERROR('APPENDIX 18'!$Q40/'APPENDIX 18'!Q$41*100,"") -> 0
B41: TOTAL | C41: =IFERROR('APPENDIX 18'!C41/'APPENDIX 18'!C$41*100,"") -> 100 | D41: =IFERROR('APPENDIX 18'!D41/'APPENDIX 18'!D$41*100,"") -> 100 | E41: =IFERROR('APPENDIX 18'!E41/'APPENDIX 18'!E$41*100,"") -> 100 | F41: =IFERROR('APPENDIX 18'!F41/'APPENDIX 18'!F$41*100,"") -> 100 | G41: =IFERROR('APPENDIX 18'!G41/'APPENDIX 18'!G$41*100,"") -> 100 | H41: =IFERROR('APPENDIX 18'!H41/'APPENDIX 18'!H$41*100,"") -> 100 | I41: =IFERROR('APPENDIX 18'!I41/'APPENDIX 18'!I$41*100,"") -> 100 | J41: =IFERROR('APPENDIX 18'!J41/'APPENDIX 18'!J$41*100,"") -> 100 | ... P41: =IFERROR('APPENDIX 18'!P41/'APPENDIX 18'!P$41*100,"") -> 100 | Q41: =IFERROR('APPENDIX 18'!$Q41/'APPENDIX 18'!Q$41*100,"") -> 100
B42: REINSURERS
B43: ='APPENDIX 18'!B43 -> CONTINENTAL REINSURANCE | C43: =IFERROR('APPENDIX 18'!C43/'APPENDIX 18'!C$48*100,"") -> 9.0659915 | D43: =IFERROR('APPENDIX 18'!D43/'APPENDIX 18'!D$48*100,"") -> 19.166027 | E43: =IFERROR('APPENDIX 18'!E43/'APPENDIX 18'!E$48*100,"") -> 57.781714 | F43: =IFERROR('APPENDIX 18'!F43/'APPENDIX 18'!F$48*100,"") -> 22.046383 | G43: =IFERROR('APPENDIX 18'!G43/'APPENDIX 18'!G$48*100,"") -> 43.234881 | H43: =IFERROR('APPENDIX 18'!H43/'APPENDIX 18'!H$48*100,"") -> 16.284344 | I43: =IFERROR('APPENDIX 18'!I43/'APPENDIX 18'!I$48*100,"") -> 33.013508 | J43: =IFERROR('APPENDIX 18'!J43/'APPENDIX 18'!J$48*100,"") -> 21.88969 | K43: =IFERROR('APPENDIX 18'!K43/'APPENDIX 18'!K$48*100,0) -> 0 | L43: =IFERROR('APPENDIX 18'!L43/'APPENDIX 18'!L$48*100,"") -> 11.645069 | M43: =IFERROR('APPENDIX 18'!M43/'APPENDIX 18'!M$48*100,"") -> 10.614081 | N43: =IFERROR('APPENDIX 18'!N43/'APPENDIX 18'!N$48*100,"") -> 17.127139 | O43: =IFERROR('APPENDIX 18'!O43/'APPENDIX 18'!O$48*100,"") -> 33.7454 | P43: =IFERROR('APPENDIX 18'!P43/'APPENDIX 18'!$P$48*100,"") -> 24.893976 | Q43: =IFERROR('APPENDIX 18'!$Q43/'APPENDIX 18'!$Q$48*100,"") -> 24.981463
B44: ='APPENDIX 18'!B44 -> EAST AFRICA REINSURANCE | C44: =IFERROR('APPENDIX 18'!C44/'APPENDIX 18'!C$48*100,"") -> 1.6031887 | D44: =IFERROR('APPENDIX 18'!D44/'APPENDIX 18'!D$48*100,"") -> 11.926003 | E44: =IFERROR('APPENDIX 18'!E44/'APPENDIX 18'!E$48*100,"") -> 0 | F44: =IFERROR('APPENDIX 18'!F44/'APPENDIX 18'!F$48*100,"") -> 20.189613 | G44: =IFERROR('APPENDIX 18'!G44/'APPENDIX 18'!G$48*100,"") -> 9.5827553 | H44: =IFERROR('APPENDIX 18'!H44/'APPENDIX 18'!H$48*100,"") -> 14.462703 | I44: =IFERROR('APPENDIX 18'!I44/'APPENDIX 18'!I$48*100,"") -> 0 | J44: =IFERROR('APPENDIX 18'!J44/'APPENDIX 18'!J$48*100,"") -> 23.649982 | K44: =IFERROR('APPENDIX 18'!K44/'APPENDIX 18'!K$48*100,0) -> 0 | L44: =IFERROR('APPENDIX 18'!L44/'APPENDIX 18'!L$48*100,"") -> 7.6877397 | M44: =IFERROR('APPENDIX 18'!M44/'APPENDIX 18'!M$48*100,"") -> 0 | N44: =IFERROR('APPENDIX 18'!N44/'APPENDIX 18'!N$48*100,"") -> 0 | O44: =IFERROR('APPENDIX 18'!O44/'APPENDIX 18'!O$48*100,"") -> 28.201543 | P44: =IFERROR('APPENDIX 18'!P44/'APPENDIX 18'!$P$48*100,"") -> 22.197943 | Q44: =IFERROR('APPENDIX 18'!$Q44/'APPENDIX 18'!$Q$48*100,"") -> 18.083828
B45: ='APPENDIX 18'!B45 -> GHANA REINSURANCE COMPANY | C45: =IFERROR('APPENDIX 18'!C45/'APPENDIX 18'!C$48*100,"") -> 1.0488638 | D45: =IFERROR('APPENDIX 18'!D45/'APPENDIX 18'!D$48*100,"") -> 3.7431275 | E45: =IFERROR('APPENDIX 18'!E45/'APPENDIX 18'!E$48*100,"") -> 12.446589 | F45: =IFERROR('APPENDIX 18'!F45/'APPENDIX 18'!F$48*100,"") -> 12.236025 | G45: =IFERROR('APPENDIX 18'!G45/'APPENDIX 18'!G$48*100,"") -> 10.119756 | H45: =IFERROR('APPENDIX 18'!H45/'APPENDIX 18'!H$48*100,"") -> 7.1945129 | I45: =IFERROR('APPENDIX 18'!I45/'APPENDIX 18'!I$48*100,"") -> 35.035382 | J45: =IFERROR('APPENDIX 18'!J45/'APPENDIX 18'!J$48*100,"") -> 5.8899511 | K45: =IFERROR('APPENDIX 18'!K45/'APPENDIX 18'!K$48*100,0) -> 0 | L45: =IFERROR('APPENDIX 18'!L45/'APPENDIX 18'!L$48*100,"") -> 0.31872525 | M45: =IFERROR('APPENDIX 18'!M45/'APPENDIX 18'!M$48*100,"") -> 13.047194 | N45: =IFERROR('APPENDIX 18'!N45/'APPENDIX 18'!N$48*100,"") -> 29.534199 | O45: =IFERROR('APPENDIX 18'!O45/'APPENDIX 18'!O$48*100,"") -> 7.5875216 | P45: =IFERROR('APPENDIX 18'!P45/'APPENDIX 18'!$P$48*100,"") -> 4.75621 | Q45: =IFERROR('APPENDIX 18'!$Q45/'APPENDIX 18'!$Q$48*100,"") -> 8.4274603
B46: ='APPENDIX 18'!B46 -> KENYA REINSURANCE CORPORATION | C46: =IFERROR('APPENDIX 18'!C46/'APPENDIX 18'!C$48*100,"") -> 63.801061 | D46: =IFERROR('APPENDIX 18'!D46/'APPENDIX 18'!D$48*100,"") -> 44.331755 | E46: =IFERROR('APPENDIX 18'!E46/'APPENDIX 18'!E$48*100,"") -> 3.2046322 | F46: =IFERROR('APPENDIX 18'!F46/'APPENDIX 18'!F$48*100,"") -> 28.678301 | G46: =IFERROR('APPENDIX 18'!G46/'APPENDIX 18'!G$48*100,"") -> 14.282054 | H46: =IFERROR('APPENDIX 18'!H46/'APPENDIX 18'!H$48*100,"") -> 44.618234 | I46: =IFERROR('APPENDIX 18'!I46/'APPENDIX 18'!I$48*100,"") -> 4.6724257 | J46: =IFERROR('APPENDIX 18'!J46/'APPENDIX 18'!J$48*100,"") -> 39.794015 | K46: =IFERROR('APPENDIX 18'!K46/'APPENDIX 18'!K$48*100,0) -> 0 | L46: =IFERROR('APPENDIX 18'!L46/'APPENDIX 18'!L$48*100,"") -> 25.135686 | M46: =IFERROR('APPENDIX 18'!M46/'APPENDIX 18'!M$48*100,"") -> 36.054307 | N46: =IFERROR('APPENDIX 18'!N46/'APPENDIX 18'!N$48*100,"") -> 53.338662 | O46: =IFERROR('APPENDIX 18'!O46/'APPENDIX 18'!O$48*100,"") -> 29.841833 | P46: =IFERROR('APPENDIX 18'!P46/'APPENDIX 18'!$P$48*100,"") -> 42.166077 | Q46: =IFERROR('APPENDIX 18'!$Q46/'APPENDIX 18'!$Q$48*100,"") -> 31.996551
B47: ='APPENDIX 18'!B47 -> WAICA REINSURANCE KENYA LIMITED | C47: =IFERROR('APPENDIX 18'!C47/'APPENDIX 18'!C$48*100,"") -> 24.480895 | D47: =IFERROR('APPENDIX 18'!D47/'APPENDIX 18'!D$48*100,"") -> 20.833088 | E47: =IFERROR('APPENDIX 18'!E47/'APPENDIX 18'!E$48*100,"") -> 26.567065 | F47: =IFERROR('APPENDIX 18'!F47/'APPENDIX 18'!F$48*100,"") -> 16.849678 | G47: =IFERROR('APPENDIX 18'!G47/'APPENDIX 18'!G$48*100,"") -> 22.780555 | H47: =IFERROR('APPENDIX 18'!H47/'APPENDIX 18'!H$48*100,"") -> 17.440206 | I47: =IFERROR('APPENDIX 18'!I47/'APPENDIX 18'!I$48*100,"") -> 27.278684 | J47: =IFERROR('APPENDIX 18'!J47/'APPENDIX 18'!J$48*100,"") -> 8.7763612 | K47: =IFERROR('APPENDIX 18'!K47/'APPENDIX 18'!K$48*100,0) -> 0 | L47: =IFERROR('APPENDIX 18'!L47/'APPENDIX 18'!L$48*100,"") -> 55.21278 | M47: =IFERROR('APPENDIX 18'!M47/'APPENDIX 18'!M$48*100,"") -> 40.284418 | N47: =IFERROR('APPENDIX 18'!N47/'APPENDIX 18'!N$48*100,"") -> 0 | O47: =IFERROR('APPENDIX 18'!O47/'APPENDIX 18'!O$48*100,"") -> 0.62370236 | P47: =IFERROR('APPENDIX 18'!P47/'APPENDIX 18'!$P$48*100,"") -> 5.9857941 | Q47: =IFERROR('APPENDIX 18'!$Q47/'APPENDIX 18'!$Q$48*100,"") -> 16.510697
B48: TOTAL | C48: =SUM(C43:C47) -> 100 | D48: =SUM(D43:D47) -> 100 | E48: =SUM(E43:E47) -> 100 | F48: =SUM(F43:F47) -> 100 | G48: =SUM(G43:G47) -> 100 | H48: =SUM(H43:H47) -> 100 | I48: =SUM(I43:I47) -> 100 | J48: =SUM(J43:J47) -> 100 | ... Q48: =SUM(Q43:Q47) -> 100
B49: figures in %

Sheet APPENDIX 20
B3: =_xlfn.CONCAT('Table of Contents'!B32,": ",'Table of Contents'!C32) -> APPENDIX 20: SUMMARY OF CLAIMS PAID UNDER GENERAL INSURANCE BUSINESS FOR THE PERIOD ENDED 31.03.2026
B4: Company | C4: Aviation | D4: Engineering | E4: Fire Domestic | F4: Fire Industrial | G4: Liability | H4: Marine | I4: Motor Private | J4: Motor Commercial | K4: Motor Commercial PSV | L4: Personal Accident | M4: Theft | N4: Workmens' Compensation | O4: Medical | P4: Miscellaneous | Q4: Total_x000D_
B5: INSURERS
B6: AAR INSURANCE KENYA | C6: 0 | D6: 938.76955 | E6: 75.351271 | F6: 108.44328 | G6: 1699.8878 | H6: 0 | I6: 130.97969 | J6: 21.409671 | K6: 0 | L6: 503.42486 | M6: 2228.3528 | N6: 6181.5033 | O6: 1594195.4 | P6: 41.257309 | Q6: 1606124.8
B7: AFRICAN MERCHANT ASSURANCE | C7: 0 | D7: 1899.5908 | E7: 65.042637 | F7: 360.52298 | G7: 4064.3953 | H7: 526.84423 | I7: 140541.9 | J7: 6600.6632 | K7: 50835.611 | L7: 180.37811 | M7: 14778.382 | N7: 33.394989 | O7: 0 | P7: 176.71282 | Q7: 220063.43
B8: APA INSURANCE LIMITED | C8: 0 | D8: 9383.113 | E8: 26791.278 | F8: 36922.999 | G8: 20790.847 | H8: 24180.626 | I8: 526980.32 | J8: 451934.05 | K8: 0 | L8: 13721.99 | M8: 12272.971 | N8: 69563.241 | O8: 737776.07 | P8: -1240.222 | Q8: 1929077.3
B9: BRITAM GENERAL INSURANCE | C9: 0 | D9: 8968.2606 | E9: 5480.1731 | F9: 12220.039 | G9: 196.731 | H9: 2057.6472 | I9: 225265.1 | J9: 116904.19 | K9: 0 | L9: 15117.923 | M9: 5055.2258 | N9: 13722.781 | O9: 1241418.4 | P9: 46763.868 | Q9: 1693170.3
B10: BUPA GLOBAL INSURANCE | C10: 0 | D10: 0 | E10: 0 | F10: 0 | G10: 0 | H10: 0 | I10: 0 | J10: 0 | K10: 0 | L10: 0 | M10: 0 | N10: 0 | O10: 50211.254 | P10: 0 | Q10: 50211.254
B11: CANNON GENERAL INSURANCE | C11: 0 | D11: 2079.68 | E11: 214.38 | F11: 87.816 | G11: 1076.864 | H11: 1506.576 | I11: 221062.95 | J11: 53427.646 | K11: 0 | L11: 6.284 | M11: 3191.253 | N11: 9202.447 | O11: 0 | P11: 0 | Q11: 291855.9
B12: CIC GENERAL INSURANCE COMPANY | C12: 0 | D12: 32340.987 | E12: 1031.213 | F12: 25434.685 | G12: 17205.823 | H12: 2975.8326 | I12: 645566.83 | J12: 494626.1 | K12: 0 | L12: 18527.673 | M12: 31437.28 | N12: 167683.09 | O12: 1868211.2 | P12: 281289.41 | Q12: 3586330.1
B13: DEFINITE ASSURANCE COMPANY | C13: 0 | D13: 0 | E13: 0 | F13: 0 | G13: 0 | H13: 0 | I13: 0 | J13: 0 | K13: 0 | L13: 0 | M13: 0 | N13: 0 | O13: 0 | P13: 0 | Q13: 0
B14: DIRECTLINE ASSURANCE COMPANY | C14: 0 | D14: 0 | E14: 0 | F14: 0 | G14: 0 | H14: 0 | I14: 53052.862 | J14: 243105.9 | K14: 0 | L14: 0 | M14: 0 | N14: 0 | O14: 0 | P14: 0 | Q14: 296158.76
B15: EQUITY GENERAL INSURANCE LIMITED | C15: 0 | D15: 0 | E15: 0 | F15: 0 | G15: 0 | H15: 0 | I15: 226.072 | J15: 0 | K15: 0 | L15: 0 | M15: 257.621 | N15: 0 | O15: 63547.467 | P15: 0 | Q15: 64031.16
B16: EQUITY HEALTH INSURANCE LIMITED | C16: 0 | D16: 0 | E16: 0 | F16: 0 | G16: 0 | H16: 0 | I16: 0 | J16: 0 | K16: 0 | L16: 0 | M16: 0 | N16: 0 | O16: -82045.749 | P16: 0 | Q16: -82045.749
B17: FIDELITY SHIELD INSURANCE | C17: 0 | D17: 1641.47 | E17: 1818.29 | F17: 3667.6429 | G17: 5347.017 | H17: 2621.45 | I17: 269218.04 | J17: 164617.3 | K17: 1363.45 | L17: 465.428 | M17: 1589.058 | N17: 23380.513 | O17: 35279.626 | P17: 3647.213 | Q17: 514656.5
... B40: THE MONARCH INSURANCE | C40: 0 | D40: 0 | E40: 0 | F40: 0 | G40: 0 | H40: 0 | I40: 0 | J40: 0 | K40: 0 | L40: 0 | M40: 0 | N40: 0 | O40: 0 | P40: 0 | Q40: 0
B41: TOTAL | C41: =SUM(C6:C40) -> 4146.4876 | D41: =SUM(D6:D40) -> 168116.41 | E41: =SUM(E6:E40) -> 107051.42 | F41: =SUM(F6:F40) -> 291890.62 | G41: =SUM(G6:G40) -> 173337 | H41: =SUM(H6:H40) -> 63108.367 | I41: =SUM(I6:I40) -> 5215159.1 | J41: =SUM(J6:J40) -> 3963225.7 | ... Q41: =SUM(Q6:Q40) -> 24915664
B42: REINSURERS
B43: CONTINENTAL REINSURANCE | C43: 4304.754 | D43: -1215.313 | E43: 41233.464 | F43: 117356.78 | G43: 19518.701 | H43: 49504.663 | I43: 5112.041 | J43: 21842.356 | K43: 0 | L43: 19199.435 | M43: 1010.497 | N43: 2020.993 | O43: 181598.27 | P43: 78818.731 | Q43: 540305.38
B44: EAST AFRICA REINSURANCE | C44: 11 | D44: 36132.333 | E44: 0 | F44: 171969.36 | G44: 2088.9397 | H44: 11234.077 | I44: 0 | J44: 46225.978 | K44: 0 | L44: 5508.1112 | M44: 0 | N44: 0 | O44: 225869.71 | P44: 40519.478 | Q44: 539558.99
B45: GHANA REINSURANCE COMPANY | C45: 463.344 | D45: 27221.748 | E45: -5483.7475 | F45: 64933.982 | G45: 343.877 | H45: 79617.191 | I45: 5787.097 | J45: 6269.355 | K45: 0 | L45: 0 | M45: 6425.861 | N45: 84.54 | O45: 98132.811 | P45: 609.1 | Q45: 284405.16
B46: KENYA REINSURANCE CORPORATION | C46: 32489.434 | D46: 118482.95 | E46: 4794.2978 | F46: 302570.21 | G46: 3019.1703 | H46: 79142.1 | I46: 2136.8518 | J46: 129532.5 | K46: 0 | L46: 120793.29 | M46: 34.06487 | N46: 6214.1518 | O46: 397239.62 | P46: 286348.29 | Q46: 1482796.9
B47: WAICA REINSURANCE KENYA LIMITED | C47: -19398.248 | D47: 90830.826 | E47: -110186.9 | F47: 197779.93 | G47: 20153.308 | H47: 19925.832 | I47: 1224.1384 | J47: 6866.3777 | K47: -824.28448 | L47: 8830.733 | M47: 884.19301 | N47: 7587.751 | O47: -9360.8239 | P47: 1593.2306 | Q47: 215906.07
B48: TOTAL | C48: =SUM(C43:C47) -> 17870.284 | D48: =SUM(D43:D47) -> 271452.54 | E48: =SUM(E43:E47) -> -69642.882 | F48: =SUM(F43:F47) -> 854610.27 | G48: =SUM(G43:G47) -> 45123.996 | H48: =SUM(H43:H47) -> 239423.86 | I48: =SUM(I43:I47) -> 14260.128 | J48: =SUM(J43:J47) -> 210736.56 | ... Q48: =SUM(Q43:Q47) -> 3062972.5
B49: Amounts in Thousand Shillings

Sheet APPENDIX 21
B3: =_xlfn.CONCAT('Table of Contents'!B33,": ",'Table of Contents'!C33) -> APPENDIX 21: SUMMARY OF CLAIMS INCURRED UNDER GENERAL INSURANCE BUSINESS FOR THE PERIOD ENDED 31.03.2026
B4: Company | C4: Aviation | D4: Engineering | E4: Fire Domestic | F4: Fire Industrial | G4: Liability | H4: Marine | I4: Motor Private | J4: Motor Commercial | K4: Motor Commercial PSV | L4: Personal Accident | M4: Theft | N4: Workmens' Compensation | O4: Medical | P4: Miscellaneous | Q4: Total_x000D_
B5: INSURERS
B6: AAR INSURANCE KENYA | C6: 0 | D6: 953.88632 | E6: 102.74069 | F6: 396.74193 | G6: 5862.2941 | H6: 64.796593 | I6: -273.22001 | J6: 72.038427 | K6: 0 | L6: 1896.7617 | M6: 3747.7797 | N6: 13169.984 | O6: 1644208.7 | P6: 322.33832 | Q6: 1670524.8
B7: AFRICAN MERCHANT ASSURANCE | C7: 0 | D7: 3343.0511 | E7: -4871.1442 | F7: -7248.0637 | G7: 57384.004 | H7: 2519.9372 | I7: 22622.565 | J7: -76837.668 | K7: 316128.56 | L7: 134193.99 | M7: -56512.25 | N7: 100942.93 | O7: 0 | P7: 4019.2064 | Q7: 495685.12
B8: APA INSURANCE LIMITED | C8: -167.287 | D8: 47756.187 | E8: 3857.958 | F8: 109398.87 | G8: 12392.284 | H8: 49500.71 | I8: 610178.97 | J8: 605335.26 | K8: 0 | L8: 221.969 | M8: 45034.249 | N8: 112186.34 | O8: 716895.14 | P8: 3888.761 | Q8: 2316479.4
B9: BRITAM GENERAL INSURANCE | C9: 2.36 | D9: 12489.075 | E9: 5824.6567 | F9: 29362.509 | G9: 24263.389 | H9: 11203.872 | I9: 278678.32 | J9: 133161.42 | K9: 0 | L9: 27565.92 | M9: 8254.5974 | N9: 33812.317 | O9: 1247759.2 | P9: 22712.062 | Q9: 1835089.7
B10: BUPA GLOBAL INSURANCE | C10: 0 | D10: 0 | E10: 0 | F10: 0 | G10: 0 | H10: 0 | I10: 0 | J10: 0 | K10: 0 | L10: 0 | M10: 0 | N10: 0 | O10: 16658.974 | P10: 0 | Q10: 16658.974
B11: CANNON GENERAL INSURANCE | C11: 0 | D11: 182.626 | E11: -48.47 | F11: 4552.588 | G11: 4602.747 | H11: 2777.68 | I11: 318845.51 | J11: 61414.885 | K11: 0 | L11: 572.555 | M11: 4595.453 | N11: 8163.382 | O11: 0 | P11: 35.665 | Q11: 405694.62
B12: CIC GENERAL INSURANCE COMPANY | C12: 0 | D12: 11075.017 | E12: -7941.829 | F12: -22173.437 | G12: 8335.1902 | H12: 6569.7216 | I12: 678221.44 | J12: 559611.5 | K12: 0 | L12: -4159.9591 | M12: 4144.9743 | N12: 138623.95 | O12: 1738188.5 | P12: 134835.57 | Q12: 3245330.6
B13: DEFINITE ASSURANCE COMPANY | C13: 0 | D13: 0 | E13: 0 | F13: 0 | G13: 0 | H13: 0 | I13: 0 | J13: 0 | K13: 0 | L13: 0 | M13: 0 | N13: 0 | O13: 0 | P13: 0 | Q13: 0
B14: DIRECTLINE ASSURANCE COMPANY | C14: 0 | D14: 0 | E14: 0 | F14: 0 | G14: 0 | H14: 0 | I14: 130716.97 | J14: 276266.86 | K14: 497384.45 | L14: 0 | M14: 0 | N14: 0 | O14: 0 | P14: 0 | Q14: 904368.28
B15: EQUITY GENERAL INSURANCE LIMITED | C15: 0 | D15: 300 | E15: 0 | F15: 0 | G15: 20 | H15: 620.5 | I15: 4481.495 | J15: 0 | K15: 0 | L15: 0 | M15: 32066.539 | N15: 100 | O15: 25499.725 | P15: 0 | Q15: 63088.259
B16: EQUITY HEALTH INSURANCE LIMITED | C16: 0 | D16: 0 | E16: 0 | F16: 0 | G16: 0 | H16: 0 | I16: 0 | J16: 0 | K16: 0 | L16: 0 | M16: 0 | N16: 0 | O16: 13540.429 | P16: 0 | Q16: 13540.429
B17: FIDELITY SHIELD INSURANCE | C17: 0 | D17: 2826.299 | E17: 2572.086 | F17: 32844.59 | G17: 3344.07 | H17: 637.147 | I17: 335040.43 | J17: 159732.15 | K17: 4089.813 | L17: 339.492 | M17: -5994.704 | N17: 30548.913 | O17: 49082.696 | P17: 3141.196 | Q17: 618204.18
... B40: THE MONARCH INSURANCE | C40: 0 | D40: 0 | E40: 0 | F40: 0 | G40: 0 | H40: 0 | I40: 0 | J40: 0 | K40: 0 | L40: 0 | M40: 0 | N40: 0 | O40: 0 | P40: 0 | Q40: 0
B41: TOTAL | C41: =SUM(C6:C40) -> -2989.8045 | D41: =SUM(D6:D40) -> 264518.49 | E41: =SUM(E6:E40) -> 141735.97 | F41: =SUM(F6:F40) -> 994019.85 | G41: =SUM(G6:G40) -> 231366.2 | H41: =SUM(H6:H40) -> 26066.052 | I41: =SUM(I6:I40) -> 6042593.3 | J41: =SUM(J6:J40) -> 4409974.2 | ... Q41: =SUM(Q6:Q40) -> 28258569
B42: REINSURERS
B43: CONTINENTAL REINSURANCE | C43: -10751.919 | D43: 154774.04 | E43: 150647.75 | F43: 428766.69 | G43: -3324.9563 | H43: -123647.08 | I43: -870.82162 | J43: -3720.7843 | K43: 0 | L43: -1551.2247 | M43: -81.643142 | N43: -163.28728 | O43: -149652.45 | P43: -58367.998 | Q43: 382056.32
B44: EAST AFRICA REINSURANCE | C44: 65.504487 | D44: 46932.497 | E44: 0 | F44: 320773.67 | G44: 3236.3082 | H44: 34358.567 | I44: 0 | J44: 40905.988 | K44: 0 | L44: 9030.3401 | M44: 0 | N44: 0 | O44: 319304.61 | P44: 53455.963 | Q44: 828063.45
B45: GHANA REINSURANCE COMPANY | C45: 960.64244 | D45: 37589.016 | E45: 60447.388 | F45: 130865.12 | G45: -541.61284 | H45: 38965.249 | I45: 8778.4495 | J45: 9260.7075 | K45: 0 | L45: 679.89466 | M45: 12499.913 | N45: 764.43466 | O45: 109553.95 | P45: 2208.4755 | Q45: 412031.63
B46: KENYA REINSURANCE CORPORATION | C46: 32489.434 | D46: 118482.95 | E46: 4794.2978 | F46: 302570.21 | G46: 3019.1703 | H46: 79142.1 | I46: 2136.8518 | J46: 129532.5 | K46: 0 | L46: 120793.29 | M46: 34.06487 | N46: 6214.1518 | O46: 397239.62 | P46: 286348.29 | Q46: 1482796.9
B47: WAICA REINSURANCE KENYA LIMITED | C47: -24177.958 | D47: 53181.853 | E47: -110180.99 | F47: 194949.08 | G47: 25612.504 | H47: 6856.7626 | I47: 2515.7561 | J47: 14111.257 | K47: -824.28448 | L47: 10911.645 | M47: 2394.0944 | N47: 9375.7615 | O47: -8829.839 | P47: 75742.937 | Q47: 251638.58
B48: TOTAL | C48: =SUM(C43:C47) -> -1414.2958 | D48: =SUM(D43:D47) -> 410960.35 | E48: =SUM(E43:E47) -> 105708.45 | F48: =SUM(F43:F47) -> 1377924.8 | G48: =SUM(G43:G47) -> 28001.413 | H48: =SUM(H43:H47) -> 35675.601 | I48: =SUM(I43:I47) -> 12560.236 | J48: =SUM(J43:J47) -> 190089.66 | ... Q48: =SUM(Q43:Q47) -> 3356586.9
B49: Amounts in Thousand Shillings

Sheet APPENDIX 22
B3: =_xlfn.CONCAT('Table of Contents'!B34,": ",'Table of Contents'!C34) -> APPENDIX 22: SUMMARY OF INCURRED CLAIMS RATIOS UNDER GENERAL INSURANCE BUSINESS FOR THE PERIOD ENDED 31.03.2026
B4: Company | C4: Aviation | D4: Engineering | E4: Fire Domestic | F4: Fire Industrial | G4: Liability | H4: Marine | I4: Motor Private | J4: Motor Commercial | K4: Motor Commercial PSV | L4: Personal Accident | M4: Theft | N4: Workmens' Compensation | O4: Medical | P4: Miscellaneous | Q4: Total_x000D_
B5: INSURERS
B6: ='APPENDIX 21'!B6 -> AAR INSURANCE KENYA | C6: =IFERROR('APPENDIX 21'!C6/NEPI!C6*100,"0.0") -> 0.0 | D6: =IFERROR('APPENDIX 21'!D6/NEPI!D6*100,"0.0") -> 190.32946 | E6: =IFERROR('APPENDIX 21'!E6/NEPI!E6*100,"0.0") -> 57.631215 | F6: =IFERROR('APPENDIX 21'!F6/NEPI!F6*100,"0.0") -> -230.2872 | G6: =IFERROR('APPENDIX 21'!G6/NEPI!G6*100,"0.0") -> 44.713074 | H6: =IFERROR('APPENDIX 21'!H6/NEPI!H6*100,"0.0") -> 5.2401391 | I6: =IFERROR('APPENDIX 21'!I6/NEPI!I6*100,"0.0") -> -21.676578 | J6: =IFERROR('APPENDIX 21'!J6/NEPI!J6*100,"0.0") -> 22.260137 | ... P6: =IFERROR('APPENDIX 21'!P6/NEPI!P6*100,"0.0") -> 6.856333 | Q6: =IFERROR('APPENDIX 21'!Q6/NEPI!Q6*100,"0.00") -> 78.182309
