Workbook
Name Appendix_1_Range: 'APPENDIX 1'!$B$3:$R$52
Name Appendix_10_Range: 'APPENDIX 10'!$B$3:$Q$36
Name Appendix_11_Range: 'APPENDIX 11'!$B$3:$Q$36
Name Appendix_12_Range: 'APPENDIX 12'!$B$3:$Q$36
Name Appendix_13_Range: 'APPENDIX 13'!$B$3:$Q$36
Name Appendix_14_Range: 'APPENDIX 14'!$B$3:$Q$36
Name Appendix_15_Range: 'APPENDIX 15'!$B$3:$Q$36
Name Appendix_16_Range: 'APPENDIX 16'!$B$3:$Q$36
Name Appendix_17_Range: 'APPENDIX 17'!$B$3:$Q$35
Name Appendix_18_Range: 'APPENDIX 18'!$B$3:$R$51
Name Appendix_19_Range: 'APPENDIX 19'!$B$3:$Q$51
Name Appendix_2_Range: 'APPENDIX 2'!$B$3:$R$37
Name Appendix_20_Range: 'APPENDIX 20'!$B$3:$Q$51
Name Appendix_21_Range: 'APPENDIX 21'!$B$3:$Q$51
Name Appendix_22_Range: 'APPENDIX 22'!$B$3:$Q$51
Name Appendix_23_Range: 'APPENDIX 23'!$B$3:$Q$51
Name Appendix_24_Range: 'APPENDIX 25'!$B$3:$L$35
Name Appendix_25_Range: 'APPENDIX 24'!$B$3:$Q$13
Name Appendix_3_Range: 'APPENDIX 3'!$B$3:$R$13
Name Appendix_4i_Range: 'APPENDIX 4 i'!$B$4:$K$44
Name Appendix_4ii_Range: 'APPENDIX 4 ii'!$B$3:$K$44
Name Appendix_4iii_Range: 'APPENDIX 4 iii'!$B$3:$L$44
Name Appendix_5i_Range: 'APPENDIX 5 i'!$B$4:$L$42
Name Appendix_5ii_Range: 'APPENDIX 5 ii'!$B$3:$L$42
Name Appendix_5iii_Range: 'APPENDIX 5 iii'!$B$3:$M$42
Name Appendix_5iv_Range: 'APPENDIX 5 iv'!$B$3:$N$42
Name Appendix_6i_Range: 'APPENDIX 6'!$B$4:$I$42
Name Appendix_7_Range: 'APPENDIX 7'!$B$3:$L$36
Name Appendix_8_Range: 'APPENDIX 8'!$B$3:$K$36
Name Appendix_9_Range: 'APPENDIX 9'!$B$3:$Q$36
Name Details_Range: Details!$C$2:$J$21
Name Reliances_and_Limitations: 'Reliance & Limitations'!$A$2:$G$8
Name Table_of_Contents: 'Table of Contents'!$A$1:$D$37

Sheet Details
E6: INSURANCE REGULATORY AUTHORITY
E11: TYPE OF INDUSTRY STATISTICS | F11: Quarterly (Unaudited)
E13: QUARTER | F13: 4
E15: YEAR | F15: 2025
E18: PERIOD ENDED | F18: 31.12.2025

Sheet Reliance & Limitations
B3: RELIANCE AND LIMITATIONS
B4: The insurance information contained in this workbook has been extracted from the quarterly unaudited returns submitted to the Authority in line with Section 54 of the Insurance Act. No adjustments have been made to the returns’ data except where necessary in consultation with the affected insurer(s) or reinsurer(s). The publication of any summary of the returns in this report does not necessarily mean that the returns so summarized have satisfied all the requirements of the Insurance Act, or that the Commissioner of Insurance approves the accuracy or the contents of the returns Where necessary, figures have been adjusted to eliminate errors in totals due to rounding off, and are given in thousands Kenya Shillings (‘000’ KES) except where otherwise stated. The report incorporates data from all insurers and reinsurers except for, KUSCCO Mutual Assurance Limited, The Monarch Insurance Company Limited-Life, Corporate Insurance Company- General, The Monarch Insurance Company Limited-General and Trident Insurance Company Limited due to non-compliance with the submission requirements

Sheet Table of Contents
B3: INSURANCE REGULATORY AUTHORITY
B5: =Details!F15&" QUARTER"&" "&Details!F13&" "&"STATISTICS" -> 2025 QUARTER 4 STATISTICS
B6: TABLE OF CONTENTS
B7: Link | C7: Description
B8: APPENDIX 1 | C8: =_xlfn.CONCAT("SUMMARY OF GENERAL INSURANCE BUSINESS PROFIT & LOSS ACCOUNTS FOR THE PERIOD ENDED"," ",Details!F18) -> SUMMARY OF GENERAL INSURANCE BUSINESS PROFIT & LOSS ACCOUNTS FOR THE PERIOD ENDED 31.12.2025
B9: APPENDIX 2 | C9: =_xlfn.CONCAT("SUMMARY OF LONG TERM INSURANCE BUSINESS PROFIT & LOSS ACCOUNTS FOR THE PERIOD ENDED"," ",Details!$F$18) -> SUMMARY OF LONG TERM INSURANCE BUSINESS PROFIT & LOSS ACCOUNTS FOR THE PERIOD ENDED 31.12.2025
B10: APPENDIX 3 | C10: =_xlfn.CONCAT("SUMMARY OF MICRO INSURANCE BUSINESS PROFIT & LOSS ACCOUNTS FOR THE PERIOD ENDED"," ",Details!$F$18) -> SUMMARY OF MICRO INSURANCE BUSINESS PROFIT & LOSS ACCOUNTS FOR THE PERIOD ENDED 31.12.2025
B11: APPENDIX 4 i | C11: =_xlfn.CONCAT("SUMMARY OF LONG TERM INSURANCE BUSINESS BALANCE SHEETS AS AT"," ",Details!F18) -> SUMMARY OF LONG TERM INSURANCE BUSINESS BALANCE SHEETS AS AT 31.12.2025
B12: APPENDIX 4 ii | C12: =_xlfn.CONCAT("SUMMARY OF LONG TERM INSURANCE BUSINESS BALANCE SHEETS AS AT"," ",Details!F18) -> SUMMARY OF LONG TERM INSURANCE BUSINESS BALANCE SHEETS AS AT 31.12.2025
B13: APPENDIX 4 iii | C13: =_xlfn.CONCAT("SUMMARY OF LONG TERM INSURANCE BUSINESS BALANCE SHEETS AS AT"," ",Details!F18) -> SUMMARY OF LONG TERM INSURANCE BUSINESS BALANCE SHEETS AS AT 31.12.2025
B14: APPENDIX 5 i | C14: =_xlfn.CONCAT("SUMMARY OF GENERAL INSURANCE BUSINESS BALANCE SHEETS AS AT"," ",Details!F18) -> SUMMARY OF GENERAL INSURANCE BUSINESS BALANCE SHEETS AS AT 31.12.2025
B15: APPENDIX 5 ii | C15: =_xlfn.CONCAT("SUMMARY OF GENERAL INSURANCE BUSINESS BALANCE SHEETS AS AT"," ",Details!F18) -> SUMMARY OF GENERAL INSURANCE BUSINESS BALANCE SHEETS AS AT 31.12.2025
B16: APPENDIX 5 iii | C16: =_xlfn.CONCAT("SUMMARY OF GENERAL INSURANCE BUSINESS BALANCE SHEETS AS AT"," ",Details!F18) -> SUMMARY OF GENERAL INSURANCE BUSINESS BALANCE SHEETS AS AT 31.12.2025
B17: APPENDIX 5 iv | C17: =_xlfn.CONCAT("SUMMARY OF GENERAL INSURANCE BUSINESS BALANCE SHEETS AS AT"," ",Details!F18) -> SUMMARY OF GENERAL INSURANCE BUSINESS BALANCE SHEETS AS AT 31.12.2025
B18: APPENDIX 6 | C18: =_xlfn.CONCAT("SUMMARY OF MICRO INSURANCE BUSINESS BALANCE SHEETS AS AT"," ",Details!F18) -> SUMMARY OF MICRO INSURANCE BUSINESS BALANCE SHEETS AS AT 31.12.2025
B19: APPENDIX 7 | C19: =_xlfn.CONCAT("SUMMARY OF LONG TERM INSURANCE BUSINESS GROSS PREMIUM INCOME FOR THE PERIOD ENDED"," ",Details!F18) -> SUMMARY OF LONG TERM INSURANCE BUSINESS GROSS PREMIUM INCOME FOR THE PERIOD ENDED 31.12.2025
B20: APPENDIX 8 | C20: =_xlfn.CONCAT("SUMMARY OF LONG TERM INSURANCE BUSINESS MARKET SHARE PER CLASS FOR THE PERIOD ENDED"," ",Details!F18) -> SUMMARY OF LONG TERM INSURANCE BUSINESS MARKET SHARE PER CLASS FOR THE PERIOD ENDED 31.12.2025
B21: APPENDIX 9 | C21: =_xlfn.CONCAT("SUMMARY OF LIFE ASSURANCE BUSINESS REVENUE ACCOUNTS FOR THE PERIOD ENDED"," ",Details!F18) -> SUMMARY OF LIFE ASSURANCE BUSINESS REVENUE ACCOUNTS FOR THE PERIOD ENDED 31.12.2025
B22: APPENDIX 10 | C22: =_xlfn.CONCAT("SUMMARY OF ANNUITIES BUSINESS REVENUE ACCOUNTS FOR THE PERIOD ENDED"," ",Details!F18) -> SUMMARY OF ANNUITIES BUSINESS REVENUE ACCOUNTS FOR THE PERIOD ENDED 31.12.2025
B23: APPENDIX 11 | C23: =_xlfn.CONCAT("SUMMARY OF GROUP LIFE BUSINESS REVENUE ACCOUNTS FOR THE PERIOD ENDED"," ",Details!F18) -> SUMMARY OF GROUP LIFE BUSINESS REVENUE ACCOUNTS FOR THE PERIOD ENDED 31.12.2025
B24: APPENDIX 12 | C24: =_xlfn.CONCAT("SUMMARY OF GROUP CREDIT BUSINESS REVENUE ACCOUNTS FOR THE PERIOD ENDED"," ",Details!F18) -> SUMMARY OF GROUP CREDIT BUSINESS REVENUE ACCOUNTS FOR THE PERIOD ENDED 31.12.2025
B25: APPENDIX 13 | C25: =_xlfn.CONCAT("SUMMARY OF INVESTMENTS BUSINESS REVENUE ACCOUNTS FOR THE PERIOD ENDED"," ",Details!F18) -> SUMMARY OF INVESTMENTS BUSINESS REVENUE ACCOUNTS FOR THE PERIOD ENDED 31.12.2025
B26: APPENDIX 14 | C26: =_xlfn.CONCAT("SUMMARY OF PERMANENT HEALTH BUSINESS REVENUE ACCOUNTS FOR THE PERIOD ENDED"," ",Details!F18) -> SUMMARY OF PERMANENT HEALTH BUSINESS REVENUE ACCOUNTS FOR THE PERIOD ENDED 31.12.2025
B27: APPENDIX 15 | C27: =_xlfn.CONCAT("SUMMARY OF PERSONAL PENSIONS BUSINESS REVENUE ACCOUNTS FOR THE PERIOD ENDED"," ",Details!F18) -> SUMMARY OF PERSONAL PENSIONS BUSINESS REVENUE ACCOUNTS FOR THE PERIOD ENDED 31.12.2025
B28: APPENDIX 16 | C28: =_xlfn.CONCAT("SUMMARY OF DEPOSIT ADMINISTRATION BUSINESS REVENUE ACCOUNTS FOR THE PERIOD ENDED"," ",Details!F18) -> SUMMARY OF DEPOSIT ADMINISTRATION BUSINESS REVENUE ACCOUNTS FOR THE PERIOD ENDED 31.12.2025
B29: APPENDIX 17 | C29: =_xlfn.CONCAT("SUMMARY OF COMBINED LONG TERM BUSINESS REVENUE ACCOUNTS FOR THE PERIOD ENDED"," ",Details!F18) -> SUMMARY OF COMBINED LONG TERM BUSINESS REVENUE ACCOUNTS FOR THE PERIOD ENDED 31.12.2025
B30: APPENDIX 18 | C30: =_xlfn.CONCAT("SUMMARY OF GROSS PREMIUM INCOME UNDER GENERAL INSURANCE BUSINESS FOR THE PERIOD ENDED"," ",Details!$F$18) -> SUMMARY OF GROSS PREMIUM INCOME UNDER GENERAL INSURANCE BUSINESS FOR THE PERIOD ENDED 31.12.2025
B31: APPENDIX 19 | C31: =_xlfn.CONCAT("SUMMARY OF GENERAL INSURANCE BUSINESS MARKET SHARE PER CLASS FOR THE PERIOD ENDED"," ",Details!$F$18) -> SUMMARY OF GENERAL INSURANCE BUSINESS MARKET SHARE PER CLASS FOR THE PERIOD ENDED 31.12.2025
B32: APPENDIX 20 | C32: =_xlfn.CONCAT("SUMMARY OF CLAIMS PAID UNDER GENERAL INSURANCE BUSINESS FOR THE PERIOD ENDED"," ",Details!$F$18) -> SUMMARY OF CLAIMS PAID UNDER GENERAL INSURANCE BUSINESS FOR THE PERIOD ENDED 31.12.2025
B33: APPENDIX 21 | C33: =_xlfn.CONCAT("SUMMARY OF CLAIMS INCURRED UNDER GENERAL INSURANCE BUSINESS FOR THE PERIOD ENDED"," ",Details!$F$18) -> SUMMARY OF CLAIMS INCURRED UNDER GENERAL INSURANCE BUSINESS FOR THE PERIOD ENDED 31.12.2025
B34: APPENDIX 22 | C34: =_xlfn.CONCAT("SUMMARY OF INCURRED CLAIMS RATIOS UNDER GENERAL INSURANCE BUSINESS FOR THE PERIOD ENDED"," ",Details!$F$18) -> SUMMARY OF INCURRED CLAIMS RATIOS UNDER GENERAL INSURANCE BUSINESS FOR THE PERIOD ENDED 31.12.2025
B35: APPENDIX 23 | C35: =_xlfn.CONCAT("SUMMARY OF GENERAL INSURANCE BUSINESS REVENUE ACCOUNTS FOR THE PERIOD ENDED"," ",Details!$F$18) -> SUMMARY OF GENERAL INSURANCE BUSINESS REVENUE ACCOUNTS FOR THE PERIOD ENDED 31.12.2025
B36: APPENDIX 24 | C36: =_xlfn.CONCAT("SUMMARY OF MICROINSURANCE BUSINESS REVENUE ACCOUNTS FOR THE PERIOD ENDED"," ",Details!$F$18) -> SUMMARY OF MICROINSURANCE BUSINESS REVENUE ACCOUNTS FOR THE PERIOD ENDED 31.12.2025
B37: APPENDIX 25 | C37: =_xlfn.CONCAT("SUMMARY OF BUSINESS RESULTS UNDER MICRO INSURANCE BUSINESS FOR THE PERIOD ENDED"," ",Details!$F$18) -> SUMMARY OF BUSINESS RESULTS UNDER MICRO INSURANCE BUSINESS FOR THE PERIOD ENDED 31.12.2025

Sheet APPENDIX 1
B3: =_xlfn.CONCAT('Table of Contents'!B8,": ",'Table of Contents'!C8) -> APPENDIX 1: SUMMARY OF GENERAL INSURANCE BUSINESS PROFIT & LOSS ACCOUNTS FOR THE PERIOD ENDED 31.12.2025
B4: Company | C4: Insurance Revenue | D4: Insurance Service Expense | E4: Net expenses from reinsurance contracts held | F4: Insurance Service Result | G4: Net Investment Income | H4: Finance expenses from insurance contracts | I4: Finance income from reinsurance contracts | J4: Net Financial Result | K4: Asset management services revenue | L4: Other Income | M4: Other finance costs | N4: Other operating expenses | O4: Share of profit of associates and joint ventures accounted for using the equity method | P4: Profit before income tax | Q4: Income tax expense | R4: Profit for the year
B5: INSURERS
B6: AAR INSURANCE KENYA | C6: 12309693 | D6: 11767626 | E6: -32687.526 | F6: 574754.53 | G6: 738160.64 | H6: 0 | I6: 0 | J6: 738160.64 | K6: 0 | L6: 11818.483 | M6: 13476.897 | N6: 593240.67 | O6: 0 | P6: 718016.08 | Q6: 157747.4 | R6: 560268.68
B7: AFRICAN MERCHANT ASSURANCE | C7: 3764707.9 | D7: 2694540.6 | E7: 161575.88 | F7: 908591.4 | G7: 194549.02 | H7: 396376.16 | I7: 43488.455 | J7: -158338.69 | K7: 0 | L7: 0 | M7: 0 | N7: 487085.99 | O7: 0 | P7: 263166.72 | Q7: 37349.674 | R7: 225817.05
B8: APA INSURANCE LIMITED | C8: 19029084 | D8: 15588884 | E8: 2803547.4 | F8: 636652.89 | G8: 2056160.7 | H8: 1264285.1 | I8: 489592.52 | J8: 1281468.1 | K8: 0 | L8: 0 | M8: 22413.707 | N8: 459302.86 | O8: 0 | P8: 1436404.5 | Q8: -70485.353 | R8: 1506889.8
B9: BRITAM GENERAL INSURANCE | C9: 15255849 | D9: 11545994 | E9: 2779323.6 | F9: 930531.84 | G9: 1960381.6 | H9: 1205126.3 | I9: 511517.36 | J9: 1266772.7 | K9: 0 | L9: 35438.195 | M9: 33032.757 | N9: 398128.38 | O9: 0 | P9: 1801581.6 | Q9: 48.647 | R9: 1801532.9
B10: BUPA GLOBAL INSURANCE | C10: 2145748.9 | D10: 1981140.4 | E10: 453438.61 | F10: -288830.12 | G10: 81144.823 | H10: 0 | I10: 0 | J10: 81144.823 | K10: 0 | L10: 0 | M10: 0 | N10: 0 | O10: 0 | P10: -207685.29 | Q10: -16715.591 | R10: -190969.7
B11: CANNON GENERAL INSURANCE | C11: 2295386.6 | D11: 2487102.4 | E11: 120052.75 | F11: -311768.47 | G11: 498788.08 | H11: 120835.34 | I11: 71370.871 | J11: 449323.62 | K11: 0 | L11: 0 | M11: 0 | N11: 214762.87 | O11: 0 | P11: -77207.726 | Q11: 0 | R11: -77207.726
B12: CIC GENERAL INSURANCE COMPANY | C12: 18891677 | D12: 17351225 | E12: 1047035.5 | F12: 493415.81 | G12: 1301522.6 | H12: 455941.38 | I12: 110305.72 | J12: 955886.96 | K12: 0 | L12: 440375.68 | M12: 0 | N12: 460782.67 | O12: 0 | P12: 1428895.8 | Q12: 428668.74 | R12: 1000227
B13: CORPORATE INSURANCE COMPANY | C13: 0 | D13: 0 | E13: 0 | F13: 0 | G13: 0 | H13: 0 | I13: 0 | J13: 0 | K13: 0 | L13: 0 | M13: 0 | N13: 0 | O13: 0 | P13: 0 | Q13: 0 | R13: 0
B14: DEFINITE ASSURANCE COMPANY | C14: 711439.43 | D14: 515701.64 | E14: 1493.169 | F14: 194244.61 | G14: 0 | H14: 0 | I14: 0 | J14: 0 | K14: 0 | L14: 0 | M14: 0 | N14: 540741.68 | O14: 0 | P14: -346497.07 | Q14: 0 | R14: -346497.07
B15: DIRECTLINE ASSURANCE COMPANY | C15: 2891099.7 | D15: 3220443.1 | E15: 61924.504 | F15: -391267.92 | G15: 239822.88 | H15: 749755.13 | I15: 0 | J15: -509932.25 | K15: 0 | L15: 0 | M15: 0 | N15: 28625.34 | O15: 0 | P15: -929825.51 | Q15: 0 | R15: -929825.51
B16: EQUITY GENERAL INSURANCE LIMITED | C16: 1487881.8 | D16: 1238677.4 | E16: 64053.309 | F16: 185151.04 | G16: 140156.95 | H16: 0 | I16: 0 | J16: 140156.95 | K16: 0 | L16: 0 | M16: 0 | N16: 125167.14 | O16: 0 | P16: 200140.84 | Q16: 60042.253 | R16: 140098.59
B17: EQUITY HEALTH INSURANCE LIMITED | C17: 3734.7279 | D17: 7905.4547 | E17: -240.83358 | F17: -3929.8932 | G17: 53098.03 | H17: 0 | I17: 0 | J17: 53098.03 | K17: 0 | L17: 0 | M17: 0 | N17: 8960.9472 | O17: 0 | P17: 40207.19 | Q17: 12062.157 | R17: 28145.033
... B42: TRIDENT INSURANCE COMPANY | C42: 0 | D42: 0 | E42: 0 | F42: 0 | G42: 0 | H42: 0 | I42: 0 | J42: 0 | K42: 0 | L42: 0 | M42: 0 | N42: 0 | O42: 0 | P42: 0 | Q42: 0 | R42: 0
B43: TOTAL | C43: =SUM(C6:C42) -> 2.1941225e+08 | D43: =SUM(D6:D42) -> 1.8333493e+08 | E43: =SUM(E6:E42) -> 27360817 | F43: =SUM(F6:F42) -> 8716498.3 | G43: =SUM(G6:G42) -> 20518348 | H43: =SUM(H6:H42) -> 7600534.7 | I43: =SUM(I6:I42) -> 2149047 | J43: =SUM(J6:J42) -> 15066860 | ... R43: =SUM(R6:R42) -> 10706898
B44: REINSURERS
B45: CONTINENTAL REINSURANCE | C45: 5696642 | D45: 4668264.4 | E45: 526853.58 | F45: 501523.95 | G45: 240678.7 | H45: 642292.7 | I45: 266149.19 | J45: -135464.82 | K45: 0 | L45: 16912.396 | M45: 9683.745 | N45: 37924.267 | O45: 0 | P45: 335363.52 | Q45: 100609.05 | R45: 234754.46
B46: EAST AFRICA REINSURANCE | C46: 4478184.4 | D46: 3810500.9 | E46: 519512.66 | F46: 148170.85 | G46: 672574.01 | H46: 122909.46 | I46: 23325.911 | J46: 572990.46 | K46: 0 | L46: 0 | M46: 0 | N46: 91065.755 | O46: 0 | P46: 630095.55 | Q46: 157151.54 | R46: 472944.01
B47: GHANA REINSURANCE COMPANY | C47: 3800134.5 | D47: 3086636.3 | E47: 178539.36 | F47: 534958.82 | G47: 231792.13 | H47: 209159.29 | I47: 46888.859 | J47: 69521.698 | K47: 0 | L47: -36.91703 | M47: -29072.824 | N47: 150410.76 | O47: 0 | P47: 483105.66 | Q47: 144931.7 | R47: 338173.96
B48: KENYA REINSURANCE CORPORATION | C48: 11663307 | D48: 10660833 | E48: 1562451.2 | F48: -559977.73 | G48: 4101738.9 | H48: 413898.52 | I48: 53882.553 | J48: 3741723 | K48: 0 | L48: 315265.37 | M48: 102272.73 | N48: 1874687.2 | O48: 0 | P48: 1520050.6 | Q48: 455937.71 | R48: 1064112.9
B49: WAICA REINSURANCE KENYA LIMITED | C49: 5306780.5 | D49: 4030911.2 | E49: 34979.277 | F49: 1240890 | G49: 349963.1 | H49: 377865.48 | I49: 38057.66 | J49: 10155.282 | K49: 0 | L49: 4.545 | M49: 82988.744 | N49: 337861.47 | O49: 0 | P49: 830199.64 | Q49: 228560.83 | R49: 601638.81
B50: TOTAL | C50: =SUM(C45:C49) -> 30945048 | D50: =SUM(D45:D49) -> 26257146 | E50: =SUM(E45:E49) -> 2822336 | F50: =SUM(F45:F49) -> 1865565.9 | G50: =SUM(G45:G49) -> 5596746.9 | H50: =SUM(H45:H49) -> 1766125.5 | I50: =SUM(I45:I49) -> 428304.17 | J50: =SUM(J45:J49) -> 4258925.6 | ... R50: =SUM(R45:R49) -> 2711624.2
B51: GRAND TOTAL | C51: =C43+C50 -> 2.503573e+08 | D51: =D43+D50 -> 2.0959208e+08 | E51: =E43+E50 -> 30183153 | F51: =F43+F50 -> 10582064 | G51: =G43+G50 -> 26115095 | H51: =H43+H50 -> 9366660.2 | I51: =I43+I50 -> 2577351.2 | J51: =J43+J50 -> 19325786 | ... R51: =R43+R50 -> 13418523
B52: Amounts in Thousand Shillings

Sheet APPENDIX 2
B3: =_xlfn.CONCAT('Table of Contents'!B9,": ",'Table of Contents'!C9) -> APPENDIX 2: SUMMARY OF LONG TERM INSURANCE BUSINESS PROFIT & LOSS ACCOUNTS FOR THE PERIOD ENDED 31.12.2025
B4: Company | C4: Insurance Revenue | D4: Insurance Service Expense | E4: Net expenses from reinsurance contracts held | F4: Insurance Service Result | G4: Net Investment Income | H4: Finance expenses from insurance contracts | I4: Finance income from reinsurance contracts | J4: Net Financial Result | K4: Asset management services revenue | L4: Other Income | M4: Other finance costs | N4: Other operating expenses | O4: Share of profit of associates and joint ventures accounted for using the equity method | P4: Profit before income tax | Q4: Income tax expense | R4: Profit for the year
B5: INSURERS
B6: ABSA LIFE ASSURANCE | C6: 7999022.1 | D6: 7415893.1 | E6: 444977.49 | F6: 138151.51 | G6: 2358873.5 | H6: 3911424.2 | I6: 52486.125 | J6: -1500064.6 | K6: 0 | L6: 0 | M6: -32221.011 | N6: 194147.2 | O6: 0 | P6: -1523839.2 | Q6: -523609.27 | R6: -1000230
B7: APA LIFE ASSURANCE COMPANY | C7: 4495527.7 | D7: 3500961.7 | E7: 581574.79 | F7: 412991.21 | G7: 3050262 | H7: 2773464.7 | I7: 74054.436 | J7: 350851.74 | K7: 0 | L7: 0 | M7: 29770.145 | N7: 152360.42 | O7: 0 | P7: 581712.39 | Q7: 36154.957 | R7: 545557.43
B8: BRITAM LIFE ASSURANCE | C8: 14878232 | D8: 10799996 | E8: 1401923.4 | F8: 2676312.9 | G8: 27294855 | H8: 26425566 | I8: 146531.35 | J8: 1015820.2 | K8: 0 | L8: -2600.692 | M8: 42466.494 | N8: 698027.64 | O8: 727319.68 | P8: 3676358 | Q8: 1102907.4 | R8: 2573450.6
B9: CANNON LIFE ASSURANCE (K) LIMITED | C9: 481760.75 | D9: 487063.3 | E9: 88837.333 | F9: -94139.886 | G9: 139798.73 | H9: 71376.537 | I9: 2177.5877 | J9: 70599.781 | K9: 0 | L9: 15747.5 | M9: 0 | N9: 9819.1657 | O9: 0 | P9: -17611.77 | Q9: 9316.562 | R9: -26928.332
B10: CAPEX LIFE ASSURANCE COMPANY | C10: 1598705.5 | D10: 1461270.4 | E10: 63833.714 | F10: 73601.47 | G10: 36741.364 | H10: 15177.119 | I10: 3105.436 | J10: 24669.681 | K10: 0 | L10: -1319.752 | M10: 0 | N10: 19884.956 | O10: 0 | P10: 77066.443 | Q10: 19981.511 | R10: 57084.932
B11: CIC LIFE ASSURANCE COMPANY | C11: 7129652.9 | D11: 7126604.5 | E11: -76645.722 | F11: 79694.152 | G11: 2027539.1 | H11: 4024946.1 | I11: 65029.994 | J11: -1932377 | K11: 1965632 | L11: 388686.02 | M11: 0 | N11: 270315.73 | O11: 0 | P11: 231319.44 | Q11: 61751.348 | R11: 169568.09
B12: CORPORATE INSURANCE COMPANY | C12: 54932.119 | D12: 147081.05 | E12: 10265.994 | F12: -102414.93 | G12: 8082.879 | H12: 32132.494 | I12: 0 | J12: -24049.615 | K12: 0 | L12: 0 | M12: 0 | N12: 3446.0658 | O12: 0 | P12: -129910.61 | Q12: 0 | R12: -129910.61
B13: EQUITY LIFE ASSURANCE | C13: 2078131.1 | D13: 1604240.2 | E13: 97004.823 | F13: 376886 | G13: 4225723 | H13: 2676924.8 | I13: 39139.573 | J13: 1587937.7 | K13: 0 | L13: 144232.69 | M13: 0 | N13: 331848.28 | O13: 0 | P13: 1777208.1 | Q13: 533162.44 | R13: 1244045.7
B14: GA LIFE ASSURANCE COMPANY | C14: 85531.404 | D14: 52896.341 | E14: 9336.632 | F14: 23298.431 | G14: 7138437.2 | H14: 0 | I14: 0 | J14: 7138437.2 | K14: 0 | L14: 1082667.6 | M14: 771.453 | N14: 227854.6 | O14: 0 | P14: 8015777.2 | Q14: 84.755 | R14: 8015692.4
B15: GEMINIA LIFE INSURANCE COMPANY | C15: 398161.3 | D15: 168922.82 | E15: 10843.237 | F15: 218395.24 | G15: 6146.895 | H15: -13653.857 | I15: 0 | J15: 19800.752 | K15: 0 | L15: 0 | M15: 0 | N15: 97584.115 | O15: 0 | P15: 140611.88 | Q15: 0 | R15: 140611.88
B16: ICEA LION LIFE ASSURANCE | C16: 7845134.9 | D16: 5629572.9 | E16: 106287.18 | F16: 2109274.8 | G16: 28730284 | H16: 23630715 | I16: 0 | J16: 5099569 | K16: 0 | L16: 26819.761 | M16: 0 | N16: 683576.32 | O16: 0 | P16: 6552087.3 | Q16: 1965613 | R16: 4586474.3
B17: JUBILEE LIFE INSURANCE | C17: 4273477.1 | D17: 3901981 | E17: 325043.29 | F17: 46452.806 | G17: 26997518 | H17: 23281143 | I17: 0 | J17: 3716375 | K17: 0 | L17: 0 | M17: 0 | N17: 1297578 | O17: 28321.349 | P17: 2493571.2 | Q17: 419937.39 | R17: 2073633.8
... B29: THE MONARCH INSURANCE | C29: 0 | D29: 0 | E29: 0 | F29: 0 | G29: 0 | H29: 0 | I29: 0 | J29: 0 | K29: 0 | L29: 0 | M29: 0 | N29: 0 | O29: 0 | P29: 0 | Q29: 0 | R29: 0
B30: TOTAL | C30: =SUM(C6:C29) -> 74377062 | D30: =SUM(D6:D29) -> 64111089 | E30: =SUM(E6:E29) -> 3640408.3 | F30: =SUM(F6:F29) -> 6625565.3 | G30: =SUM(G6:G29) -> 1.31083e+08 | H30: =SUM(H6:H29) -> 1.1389757e+08 | I30: =SUM(I6:I29) -> 444302.57 | J30: =SUM(J6:J29) -> 17629730 | ... R30: =SUM(R6:R29) -> 19004432
B31: REINSURERS
B32: CONTINENTAL REINSURANCE | C32: 36272.799 | D32: 103392.75 | E32: -3476.847 | F32: -63643.105 | G32: 68066.016 | H32: 5608.024 | I32: 626.984 | J32: 63084.976 | K32: 0 | L32: 0.012 | M32: 2016.506 | N32: 940.401 | O32: 0 | P32: -3515.024 | Q32: 1054.507 | R32: -2460.517
B33: EAST AFRICA REINSURANCE | C33: 1334886.2 | D33: 1085660.3 | E33: 91040.993 | F33: 158184.87 | G33: 267767.59 | H33: 22343.517 | I33: 5362.2192 | J33: 250786.29 | K33: 0 | L33: 0 | M33: 0 | N33: 14366.242 | O33: 0 | P33: 394604.92 | Q33: -127899.56 | R33: 266705.37
B34: KENYA REINSURANCE CORPORATION | C34: 2918918.1 | D34: 3197289.1 | E34: -65951.856 | F34: -212419.16 | G34: 1020339.1 | H34: 109322.35 | I34: -1280.8807 | J34: 909735.91 | K34: 0 | L34: 0 | M34: -2.993 | N34: 102691.13 | O34: 0 | P34: 594628.61 | Q34: -178388.7 | R34: 416239.91
B35: TOTAL | C35: =SUM(C32:C34) -> 4290077.1 | D35: =SUM(D32:D34) -> 4386342.2 | E35: =SUM(E32:E34) -> 21612.29 | F35: =SUM(F32:F34) -> -117877.39 | G35: =SUM(G32:G34) -> 1356172.7 | H35: =SUM(H32:H34) -> 137273.89 | I35: =SUM(I32:I34) -> 4708.3225 | J35: =SUM(J32:J34) -> 1223607.2 | ... R35: =SUM(R32:R34) -> 680484.76
B36: GRAND TOTAL | C36: =C35+C30 -> 78667139 | D36: =D35+D30 -> 68497431 | E36: =E35+E30 -> 3662020.6 | F36: =F35+F30 -> 6507687.9 | G36: =G35+G30 -> 1.3243917e+08 | H36: =H35+H30 -> 1.1403484e+08 | I36: =I35+I30 -> 449010.89 | J36: =J35+J30 -> 18853337 | ... R36: =R35+R30 -> 19684916
B37: Amounts in Thousand Shillings

Sheet APPENDIX 3
B3: =_xlfn.CONCAT('Table of Contents'!B10,": ",'Table of Contents'!C10) -> APPENDIX 3: SUMMARY OF MICRO INSURANCE BUSINESS PROFIT & LOSS ACCOUNTS FOR THE PERIOD ENDED 31.12.2025
B4: Company | C4: Insurance Revenue | D4: Insurance Service Expense | E4: Net expenses from reinsurance contracts held | F4: Insurance Service Result | G4: Net Investment Income | H4: Finance expenses from insurance contracts | I4: Finance income from reinsurance contracts | J4: Net Financial Result | K4: Asset management services revenue | L4: Other Income | M4: Other finance costs | N4: Other operating expenses | O4: Share of profit of associates and joint ventures accounted for using the equity method | P4: Profit before income tax | Q4: Income tax expense | R4: Profit for the year
B5: INSURERS
B6: APA MICRO INSURANCE | C6: 0 | D6: 0 | E6: 0 | F6: 0 | G6: 0 | H6: 0 | I6: 0 | J6: 0 | K6: 0 | L6: 0 | M6: 0 | N6: 0 | O6: 0 | P6: 0 | Q6: 0 | R6: 0
B7: BIRDVIEW MICRO INSURANCE | C7: 5620.9536 | D7: 39396.988 | E7: 345.44319 | F7: -34121.477 | G7: 0 | H7: 0 | I7: 0 | J7: 0 | K7: 0 | L7: 0 | M7: 0 | N7: 0 | O7: 0 | P7: -34121.477 | Q7: 0 | R7: -34121.477
B8: BRITAM MICRO INSURANCE | C8: 1090229.5 | D8: 1010963.6 | E8: 39922.421 | F8: 39343.462 | G8: 47074.091 | H8: 43598.521 | I8: 92.07156 | J8: 3567.6414 | K8: 0 | L8: 7093.2743 | M8: 5284.9804 | N8: 67954.175 | O8: 0 | P8: -23234.778 | Q8: 0 | R8: -23234.778
B9: CIC MICRO INSURANCE | C9: 2447.5647 | D9: 12589.965 | E9: 118.14515 | F9: -10260.545 | G9: 2383.7418 | H9: 0 | I9: 0 | J9: 2383.7418 | K9: 0 | L9: 55.0619 | M9: 0 | N9: 9754.658 | O9: 0 | P9: -17576.4 | Q9: 0 | R9: -17576.4
B10: STAR DISCOVER MICRO INSURANCE
B11: TURACO MICRO INSURANCE | C11: 466714.82 | D11: 374676.64 | E11: 47250.138 | F11: 44788.047 | G11: 11045.685 | H11: 0 | I11: 0 | J11: 11045.685 | K11: 0 | L11: 0 | M11: 0 | N11: 0 | O11: 0 | P11: 55833.732 | Q11: 0 | R11: 55833.732
B12: TOTAL | C12: =SUM(C6:C11) -> 1565012.8 | D12: =SUM(D6:D11) -> 1437627.2 | E12: =SUM(E6:E11) -> 87636.147 | F12: =SUM(F6:F11) -> 39749.486 | G12: =SUM(G6:G11) -> 60503.518 | H12: =SUM(H6:H11) -> 43598.521 | I12: =SUM(I6:I11) -> 92.07156 | J12: =SUM(J6:J11) -> 16997.068 | ... R12: =SUM(R6:R11) -> -19098.923
B13: Amounts in Thousand Shillings

Sheet APPENDIX 4 i
B4: =_xlfn.CONCAT('Table of Contents'!B11,": ",'Table of Contents'!C11) -> APPENDIX 4 i: SUMMARY OF LONG TERM INSURANCE BUSINESS BALANCE SHEETS AS AT 31.12.2025
B5: Company | C5: ABSA LIFE ASSURANCE | D5: APA LIFE ASSURANCE COMPANY | E5: BRITAM LIFE ASSURANCE | F5: CANNON LIFE ASSURANCE (K) LIMITED | G5: CAPEX LIFE ASSURANCE COMPANY | H5: CIC LIFE ASSURANCE COMPANY | I5: CONTINENTAL REINSURANCE | J5: CORPORATE INSURANCE COMPANY | K5: EAST AFRICA REINSURANCE
B6: Share Capital | C6: 699000 | D6: 1100000 | E6: 1200000 | F6: 416725.77 | G6: 400000 | H6: 800000 | I6: 500000 | J6: 200000 | K6: 500000
B7: Share Premium_x000D_ | C7: 0 | D7: 0 | E7: 0 | F7: 491067.65 | G7: 0 | H7: 0 | I7: 0 | J7: 0 | K7: 0
B8: Revaluation Reserves | C8: 0 | D8: 0 | E8: 0 | F8: 2500 | G8: 2072.909 | H8: 0 | I8: 0 | J8: -8100 | K8: 0
B9: Statutory Reserves | C9: 778220.1 | D9: -113765.05 | E9: 16650414 | F9: 0 | G9: 1120.164 | H9: 2248532 | I9: 0 | J9: 0 | K9: 0
B10: Other Equity | C10: 1000000 | D10: 0 | E10: 0 | F10: 404206.58 | G10: 0 | H10: 588924.67 | I10: -0.001 | J10: 0 | K10: 0
B11: Retained Earnings | C11: -1000230.2 | D11: 790348.24 | E11: 75000 | F11: -1248907.1 | G11: 284659.29 | H11: 4.7946692e-05 | I11: -2461.1683 | J11: -295693.98 | K11: 1322979.5
B12: Other Reserves | C12: 0 | D12: 122330.97 | E12: 0 | F12: 518154.63 | G12: 0 | H12: 0 | I12: 0 | J12: -205203 | K12: 0
B13: Total Equity_x000D_ | C13: 1476989.9 | D13: 1898914.2 | E13: 17925414 | F13: 583747.49 | G13: 687852.36 | H13: 3637456.7 | I13: 497538.83 | J13: -308996.98 | K13: 1822979.5
B14: Investment Contract Liabilites | C14: 0 | D14: 290376.27 | E14: 0 | F14: 0 | G14: 17360.134 | H14: 98924.319 | I14: 0 | J14: 0 | K14: 0
B15: Insurance Contract Liabilites | C15: 19163545 | D15: 25685137 | E15: 1.7426825e+08 | F15: 804549.28 | G15: 1316385.2 | H15: 37157330 | I15: 83563.37 | J15: 947009.01 | K15: 750944.86
B16: Reinsurance Contract Liabilites | C16: 0 | D16: 0 | E16: 3217.346 | F16: 0 | G16: 60826.293 | H16: 0 | I16: 5985.719 | J16: 0 | K16: 99143.935
B17: Long-Term Liabilites | C17: 0 | D17: 0 | E17: 7135891.8 | F17: 0 | G17: 0 | H17: 1034704.6 | I17: 70315.084 | J17: 0 | K17: 566991.12
... B43: Total Assets | C43: 21422690 | D43: 28346986 | E43: 2.020984e+08 | F43: 1745432.2 | G43: 2149111.3 | H43: 43001821 | I43: 729779.93 | J43: 781095.72 | K43: 3247556.7
B44: Amounts in Thousand Shillings | J44: Continued next page

Sheet APPENDIX 4 ii
B3: Continued from previous page
B4: =_xlfn.CONCAT('Table of Contents'!B12,": ",'Table of Contents'!C12) -> APPENDIX 4 ii: SUMMARY OF LONG TERM INSURANCE BUSINESS BALANCE SHEETS AS AT 31.12.2025
B5: Company | C5: EQUITY LIFE ASSURANCE | D5: GA LIFE ASSURANCE COMPANY | E5: GEMINIA LIFE INSURANCE COMPANY | F5: ICEA LION LIFE ASSURANCE | G5: JUBILEE LIFE INSURANCE | H5: KENINDIA ASSURANCE COMPANY | I5: KENYA ORIENT LIFE ASSURANCE | J5: KENYA REINSURANCE CORPORATION | K5: KUSCCO MUTUAL ASSURANCE LIMITED
B6: Share Capital | C6: 420000 | D6: 400000 | E6: 458093.68 | F6: 1125000 | G6: 500000 | H6: 900000 | I6: 313000 | J6: 500000 | K6: 0
B7: Share Premium_x000D_ | C7: 180000 | D7: 0 | E7: 0 | F7: 1125000 | G7: 0 | H7: 1000000 | I7: 0 | J7: 0 | K7: 0
B8: Revaluation Reserves | C8: 0 | D8: 0 | E8: 0 | F8: 0 | G8: 0 | H8: -536.59 | I8: 0 | J8: 0 | K8: 0
B9: Statutory Reserves | C9: 0 | D9: 9749606.2 | E9: 316903 | F9: 18510139 | G9: 0 | H9: 0 | I9: 228861.75 | J9: 0 | K9: 0
B10: Other Equity | C10: 0 | D10: 0 | E10: 0 | F10: 1015000 | G10: 0 | H10: 0 | I10: 0 | J10: 0 | K10: 0
B11: Retained Earnings | C11: 3445095.5 | D11: 70798.782 | E11: 404024.89 | F11: 5232443.2 | G11: 8190483.3 | H11: 2450187.5 | I11: 87724.449 | J11: 10773758 | K11: 0
B12: Other Reserves | C12: 4020853.2 | D12: 0 | E12: 0 | F12: 0 | G12: 3067746.2 | H12: 2384092.7 | I12: 0 | J12: 0 | K12: 0
B13: Total Equity_x000D_ | C13: 8065948.7 | D13: 10220405 | E13: 1179021.6 | F13: 27007582 | G13: 11758229 | H13: 6733743.6 | I13: 629586.2 | J13: 11273758 | K13: 0
B14: Investment Contract Liabilites | C14: 0 | D14: 48577386 | E14: 1257322.5 | F14: 0 | G14: 0 | H14: 0 | I14: 2081460.1 | J14: 0 | K14: 0
B15: Insurance Contract Liabilites | C15: 25000416 | D15: 41755.416 | E15: 1546154.3 | F15: 1.820023e+08 | G15: 1.6624529e+08 | H15: 1.0779783e+08 | I15: 3098899.8 | J15: 2133750.8 | K15: 0
B16: Reinsurance Contract Liabilites | C16: 0 | D16: 0 | E16: 0 | F16: 0 | G16: 0 | H16: 23126.829 | I16: 0 | J16: 0 | K16: 0
B17: Long-Term Liabilites | C17: 1328750.4 | D17: 0 | E17: 58439.677 | F17: 5520156 | G17: 1378255 | H17: 1021648.4 | I17: 131859.1 | J17: 0 | K17: 0
... B43: Total Assets | C43: 35949764 | D43: 63409248 | E43: 4151589.1 | F43: 2.1593023e+08 | G43: 1.8131079e+08 | H43: 1.1621327e+08 | I43: 5964701.1 | J43: 13604371 | K43: 0
B44: Amounts in Thousand Shillings | J44: Continued next page

Sheet APPENDIX 4 iii
B3: Continued from previous page
B4: =_xlfn.CONCAT('Table of Contents'!B13,": ",'Table of Contents'!C13) -> APPENDIX 4 iii: SUMMARY OF LONG TERM INSURANCE BUSINESS BALANCE SHEETS AS AT 31.12.2025 | Q4: Industry
B5: Company | C5: LIBERTY LIFE ASSURANCE COMPANY | D5: MADISON INSURANCE COMPANY | E5: OLD MUTUAL LIFE ASSURANCE KENYA | F5: PIONEER ASSURANCE COMPANY | G5: PRUDENTIAL LIFE ASSURANCE | H5: SANLAM LIFE ASSURANCE | I5: STAR DISCOVER LIFE INSURANCE | J5: THE KENYAN ALLIANCE INSURANCE | K5: THE MONARCH INSURANCE | L5: TOTAL | N5: Insurers | O5: Reinsurers | Q5: Insurers | R5: Reinsurers | S5: Total
B6: Share Capital | C6: 742340 | D6: 450000 | E6: 2946667.4 | F6: 400000 | G6: 425698.08 | H6: 843138.54 | I6: 400000 | J6: 510000 | K6: 0 | L6: 17149663 | N6: =SUMIFS('APPENDIX 4 iii'!$B6:$L6,'APPENDIX 4 iii'!$B$5:$L$5,"*total*")-O6 -> 15649663 | O6: =SUMIFS('APPENDIX 4 i'!$B6:$K6,'APPENDIX 4 i'!$B$5:$K$5,"*reinsurance*")+ SUMIFS('APPENDIX 4 ii'!$B6:$K6,'APPENDIX 4 ii'!$B$5:$K$5,"*reinsurance*")+ SUMIFS('APPENDIX 4 iii'!$B6:$K6,'APPENDIX 4 iii'!$B$5:$K$5,"*reinsurance*") -> 1500000 | Q6: =N6+_xlfn.XLOOKUP($B6,'APPENDIX 5 iv'!$B:$B,'APPENDIX 5 iv'!P:P,0,0)+_xlfn.XLOOKUP($B6,'APPENDIX 6'!$B:$B,'APPENDIX 6'!I:I,0,0) -> 54329466 | R6: =O6+_xlfn.XLOOKUP($B6,'APPENDIX 5 iv'!$B:$B,'APPENDIX 5 iv'!Q:Q,0,0)+_xlfn.XLOOKUP($B6,'APPENDIX 6'!$B:$B,'APPENDIX 6'!J:J,0,0) -> 19101531 | S6: =SUM(Q6:R6) -> 73430998
B7: Share Premium_x000D_ | C7: 0 | D7: 0 | E7: 1160475.7 | F7: 0 | G7: 3768621.6 | H7: 30260 | I7: 0 | J7: 0 | K7: 0 | L7: 7755424.9 | N7: =SUMIFS('APPENDIX 4 iii'!$B7:$L7,'APPENDIX 4 iii'!$B$5:$L$5,"*total*")-O7 -> 7755424.9 | O7: =SUMIFS('APPENDIX 4 i'!$B7:$K7,'APPENDIX 4 i'!$B$5:$K$5,"*reinsurance*")+ SUMIFS('APPENDIX 4 ii'!$B7:$K7,'APPENDIX 4 ii'!$B$5:$K$5,"*reinsurance*")+ SUMIFS('APPENDIX 4 iii'!$B7:$K7,'APPENDIX 4 iii'!$B$5:$K$5,"*reinsurance*") -> 0 | Q7: =N7+_xlfn.XLOOKUP($B7,'APPENDIX 5 iv'!$B:$B,'APPENDIX 5 iv'!P:P,0,0)+_xlfn.XLOOKUP($B7,'APPENDIX 6'!$B:$B,'APPENDIX 6'!I:I,0,0) -> 9564516.2 | R7: =O7+_xlfn.XLOOKUP($B7,'APPENDIX 5 iv'!$B:$B,'APPENDIX 5 iv'!Q:Q,0,0)+_xlfn.XLOOKUP($B7,'APPENDIX 6'!$B:$B,'APPENDIX 6'!J:J,0,0) -> 10871.242 | S7: =SUM(Q7:R7) -> 9575387.4
B8: Revaluation Reserves | C8: 384946.36 | D8: 19341 | E8: 0 | F8: 0 | G8: 0 | H8: 0 | I8: 0 | J8: 0 | K8: 0 | L8: 400223.68 | N8: =SUMIFS('APPENDIX 4 iii'!$B8:$L8,'APPENDIX 4 iii'!$B$5:$L$5,"*total*")-O8 -> 400223.68 | O8: =SUMIFS('APPENDIX 4 i'!$B8:$K8,'APPENDIX 4 i'!$B$5:$K$5,"*reinsurance*")+ SUMIFS('APPENDIX 4 ii'!$B8:$K8,'APPENDIX 4 ii'!$B$5:$K$5,"*reinsurance*")+ SUMIFS('APPENDIX 4 iii'!$B8:$K8,'APPENDIX 4 iii'!$B$5:$K$5,"*reinsurance*") -> 0 | Q8: =N8+_xlfn.XLOOKUP($B8,'APPENDIX 5 iv'!$B:$B,'APPENDIX 5 iv'!P:P,0,0)+_xlfn.XLOOKUP($B8,'APPENDIX 6'!$B:$B,'APPENDIX 6'!I:I,0,0) -> 3241322.4 | R8: =O8+_xlfn.XLOOKUP($B8,'APPENDIX 5 iv'!$B:$B,'APPENDIX 5 iv'!Q:Q,0,0)+_xlfn.XLOOKUP($B8,'APPENDIX 6'!$B:$B,'APPENDIX 6'!J:J,0,0) -> 258456.3 | S8: =SUM(Q8:R8) -> 3499778.7
B9: Statutory Reserves | C9: 2071905.5 | D9: 0 | E9: 131486.3 | F9: 232406.33 | G9: 0 | H9: 3288226.9 | I9: 0 | J9: 0 | K9: 0 | L9: 54094056 | N9: =SUMIFS('APPENDIX 4 iii'!$B9:$L9,'APPENDIX 4 iii'!$B$5:$L$5,"*total*")-O9 -> 54094056 | O9: =SUMIFS('APPENDIX 4 i'!$B9:$K9,'APPENDIX 4 i'!$B$5:$K$5,"*reinsurance*")+ SUMIFS('APPENDIX 4 ii'!$B9:$K9,'APPENDIX 4 ii'!$B$5:$K$5,"*reinsurance*")+ SUMIFS('APPENDIX 4 iii'!$B9:$K9,'APPENDIX 4 iii'!$B$5:$K$5,"*reinsurance*") -> 0 | Q9: =N9+_xlfn.XLOOKUP($B9,'APPENDIX 5 iv'!$B:$B,'APPENDIX 5 iv'!P:P,0,0)+_xlfn.XLOOKUP($B9,'APPENDIX 6'!$B:$B,'APPENDIX 6'!I:I,0,0) -> 54094056 | R9: =O9+_xlfn.XLOOKUP($B9,'APPENDIX 5 iv'!$B:$B,'APPENDIX 5 iv'!Q:Q,0,0)+_xlfn.XLOOKUP($B9,'APPENDIX 6'!$B:$B,'APPENDIX 6'!J:J,0,0) -> 0 | S9: =SUM(Q9:R9) -> 54094056
B10: Other Equity | C10: 600000 | D10: 2050000 | E10: 0 | F10: 0 | G10: 0 | H10: 0 | I10: 0 | J10: 0 | K10: 0 | L10: 5658131.2 | N10: =SUMIFS('APPENDIX 4 iii'!$B10:$L10,'APPENDIX 4 iii'!$B$5:$L$5,"*total*")-O10 -> 5658131.3 | O10: =SUMIFS('APPENDIX 4 i'!$B10:$K10,'APPENDIX 4 i'!$B$5:$K$5,"*reinsurance*")+ SUMIFS('APPENDIX 4 ii'!$B10:$K10,'APPENDIX 4 ii'!$B$5:$K$5,"*reinsurance*")+ SUMIFS('APPENDIX 4 iii'!$B10:$K10,'APPENDIX 4 iii'!$B$5:$K$5,"*reinsurance*") -> -0.001 | Q10: =N10+_xlfn.XLOOKUP($B10,'APPENDIX 5 iv'!$B:$B,'APPENDIX 5 iv'!P:P,0,0)+_xlfn.XLOOKUP($B10,'APPENDIX 6'!$B:$B,'APPENDIX 6'!I:I,0,0) -> 9294304.1 | R10: =O10+_xlfn.XLOOKUP($B10,'APPENDIX 5 iv'!$B:$B,'APPENDIX 5 iv'!Q:Q,0,0)+_xlfn.XLOOKUP($B10,'APPENDIX 6'!$B:$B,'APPENDIX 6'!J:J,0,0) -> 627494.57 | S10: =SUM(Q10:R10) -> 9921798.7
B11: Retained Earnings | C11: -304169.9 | D11: 62000 | E11: -413300.98 | F11: 371258.93 | G11: -3475210.8 | H11: 235067.35 | I11: 305693.34 | J11: -630249.63 | K11: 0 | L11: 26731299 | N11: =SUMIFS('APPENDIX 4 iii'!$B11:$L11,'APPENDIX 4 iii'!$B$5:$L$5,"*total*")-O11 -> 14637022 | O11: =SUMIFS('APPENDIX 4 i'!$B11:$K11,'APPENDIX 4 i'!$B$5:$K$5,"*reinsurance*")+ SUMIFS('APPENDIX 4 ii'!$B11:$K11,'APPENDIX 4 ii'!$B$5:$K$5,"*reinsurance*")+ SUMIFS('APPENDIX 4 iii'!$B11:$K11,'APPENDIX 4 iii'!$B$5:$K$5,"*reinsurance*") -> 12094277 | Q11: =N11+_xlfn.XLOOKUP($B11,'APPENDIX 5 iv'!$B:$B,'APPENDIX 5 iv'!P:P,0,0)+_xlfn.XLOOKUP($B11,'APPENDIX 6'!$B:$B,'APPENDIX 6'!I:I,0,0) -> 60479169 | R11: =O11+_xlfn.XLOOKUP($B11,'APPENDIX 5 iv'!$B:$B,'APPENDIX 5 iv'!Q:Q,0,0)+_xlfn.XLOOKUP($B11,'APPENDIX 6'!$B:$B,'APPENDIX 6'!J:J,0,0) -> 45743195 | S11: =SUM(Q11:R11) -> 1.0622236e+08
B12: Other Reserves | C12: 0 | D12: -4263247 | E12: 27533.634 | F12: 0 | G12: 0 | H12: 0 | I12: 0 | J12: 0 | K12: 0 | L12: 5672261.3 | N12: =SUMIFS('APPENDIX 4 iii'!$B12:$L12,'APPENDIX 4 iii'!$B$5:$L$5,"*total*")-O12 -> 5672261.3 | O12: =SUMIFS('APPENDIX 4 i'!$B12:$K12,'APPENDIX 4 i'!$B$5:$K$5,"*reinsurance*")+ SUMIFS('APPENDIX 4 ii'!$B12:$K12,'APPENDIX 4 ii'!$B$5:$K$5,"*reinsurance*")+ SUMIFS('APPENDIX 4 iii'!$B12:$K12,'APPENDIX 4 iii'!$B$5:$K$5,"*reinsurance*") -> 0 | Q12: =N12+_xlfn.XLOOKUP($B12,'APPENDIX 5 iv'!$B:$B,'APPENDIX 5 iv'!P:P,0,0)+_xlfn.XLOOKUP($B12,'APPENDIX 6'!$B:$B,'APPENDIX 6'!I:I,0,0) -> 8286005.2 | R12: =O12+_xlfn.XLOOKUP($B12,'APPENDIX 5 iv'!$B:$B,'APPENDIX 5 iv'!Q:Q,0,0)+_xlfn.XLOOKUP($B12,'APPENDIX 6'!$B:$B,'APPENDIX 6'!J:J,0,0) -> 1421695.6 | S12: =SUM(Q12:R12) -> 9707700.7
B13: Total Equity_x000D_ | C13: 3495022 | D13: -1681906 | E13: 3852862 | F13: 1003665.3 | G13: 719108.84 | H13: 4396692.8 | I13: 705693.34 | J13: -120249.63 | K13: 0 | L13: 1.1746106e+08 | N13: =SUMIFS('APPENDIX 4 iii'!$B13:$L13,'APPENDIX 4 iii'!$B$5:$L$5,"*total*")-O13 -> 1.0386678e+08 | O13: =SUMIFS('APPENDIX 4 i'!$B13:$K13,'APPENDIX 4 i'!$B$5:$K$5,"*reinsurance*")+ SUMIFS('APPENDIX 4 ii'!$B13:$K13,'APPENDIX 4 ii'!$B$5:$K$5,"*reinsurance*")+ SUMIFS('APPENDIX 4 iii'!$B13:$K13,'APPENDIX 4 iii'!$B$5:$K$5,"*reinsurance*") -> 13594277 | Q13: =N13+_xlfn.XLOOKUP($B13,'APPENDIX 5 iv'!$B:$B,'APPENDIX 5 iv'!P:P,0,0)+_xlfn.XLOOKUP($B13,'APPENDIX 6'!$B:$B,'APPENDIX 6'!I:I,0,0) -> 1.9890684e+08 | R13: =O13+_xlfn.XLOOKUP($B13,'APPENDIX 5 iv'!$B:$B,'APPENDIX 5 iv'!Q:Q,0,0)+_xlfn.XLOOKUP($B13,'APPENDIX 6'!$B:$B,'APPENDIX 6'!J:J,0,0) -> 67163244 | S13: =SUM(Q13:R13) -> 2.6607009e+08
B14: Investment Contract Liabilites | C14: 12442208 | D14: 0 | E14: 707847.45 | F14: 0 | G14: 0 | H14: 0 | I14: 0 | J14: 4775158 | K14: 0 | L14: 70248042 | N14: =SUMIFS('APPENDIX 4 iii'!$B14:$L14,'APPENDIX 4 iii'!$B$5:$L$5,"*total*")-O14 -> 70248042 | O14: =SUMIFS('APPENDIX 4 i'!$B14:$K14,'APPENDIX 4 i'!$B$5:$K$5,"*reinsurance*")+ SUMIFS('APPENDIX 4 ii'!$B14:$K14,'APPENDIX 4 ii'!$B$5:$K$5,"*reinsurance*")+ SUMIFS('APPENDIX 4 iii'!$B14:$K14,'APPENDIX 4 iii'!$B$5:$K$5,"*reinsurance*") -> 0 | Q14: =N14+_xlfn.XLOOKUP($B14,'APPENDIX 5 iv'!$B:$B,'APPENDIX 5 iv'!P:P,0,0)+_xlfn.XLOOKUP($B14,'APPENDIX 6'!$B:$B,'APPENDIX 6'!I:I,0,0) -> 70248042 | R14: =O14+_xlfn.XLOOKUP($B14,'APPENDIX 5 iv'!$B:$B,'APPENDIX 5 iv'!Q:Q,0,0)+_xlfn.XLOOKUP($B14,'APPENDIX 6'!$B:$B,'APPENDIX 6'!J:J,0,0) -> 0 | S14: =SUM(Q14:R14) -> 70248042
B15: Insurance Contract Liabilites | C15: 14605242 | D15: 21460800 | E15: 23719671 | F15: 18032422 | G15: 6137082.7 | H15: 30420933 | I15: 174105.22 | J15: 911842.75 | K15: 0 | L15: 8.6350521e+08 | N15: =SUMIFS('APPENDIX 4 iii'!$B15:$L15,'APPENDIX 4 iii'!$B$5:$L$5,"*total*")-O15 -> 8.6053695e+08 | O15: =SUMIFS('APPENDIX 4 i'!$B15:$K15,'APPENDIX 4 i'!$B$5:$K$5,"*reinsurance*")+ SUMIFS('APPENDIX 4 ii'!$B15:$K15,'APPENDIX 4 ii'!$B$5:$K$5,"*reinsurance*")+ SUMIFS('APPENDIX 4 iii'!$B15:$K15,'APPENDIX 4 iii'!$B$5:$K$5,"*reinsurance*") -> 2968259 | Q15: =N15+_xlfn.XLOOKUP($B15,'APPENDIX 5 iv'!$B:$B,'APPENDIX 5 iv'!P:P,0,0)+_xlfn.XLOOKUP($B15,'APPENDIX 6'!$B:$B,'APPENDIX 6'!I:I,0,0) -> 1.0291078e+09 | R15: =O15+_xlfn.XLOOKUP($B15,'APPENDIX 5 iv'!$B:$B,'APPENDIX 5 iv'!Q:Q,0,0)+_xlfn.XLOOKUP($B15,'APPENDIX 6'!$B:$B,'APPENDIX 6'!J:J,0,0) -> 26080713 | S15: =SUM(Q15:R15) -> 1.0551886e+09
B16: Reinsurance Contract Liabilites | C16: 0 | D16: 228776 | E16: 0 | F16: 0 | G16: 0 | H16: 0 | I16: 0 | J16: 0 | K16: 0 | L16: 421076.12 | N16: =SUMIFS('APPENDIX 4 iii'!$B16:$L16,'APPENDIX 4 iii'!$B$5:$L$5,"*total*")-O16 -> 315946.47 | O16: =SUMIFS('APPENDIX 4 i'!$B16:$K16,'APPENDIX 4 i'!$B$5:$K$5,"*reinsurance*")+ SUMIFS('APPENDIX 4 ii'!$B16:$K16,'APPENDIX 4 ii'!$B$5:$K$5,"*reinsurance*")+ SUMIFS('APPENDIX 4 iii'!$B16:$K16,'APPENDIX 4 iii'!$B$5:$K$5,"*reinsurance*") -> 105129.65 | Q16: =N16+_xlfn.XLOOKUP($B16,'APPENDIX 5 iv'!$B:$B,'APPENDIX 5 iv'!P:P,0,0)+_xlfn.XLOOKUP($B16,'APPENDIX 6'!$B:$B,'APPENDIX 6'!I:I,0,0) -> 3806417.8 | R16: =O16+_xlfn.XLOOKUP($B16,'APPENDIX 5 iv'!$B:$B,'APPENDIX 5 iv'!Q:Q,0,0)+_xlfn.XLOOKUP($B16,'APPENDIX 6'!$B:$B,'APPENDIX 6'!J:J,0,0) -> 1754720 | S16: =SUM(Q16:R16) -> 5561137.8
B17: Long-Term Liabilites | C17: 1052931.6 | D17: 0 | E17: 0 | F17: 103666.28 | G17: 0 | H17: 1409654.3 | I17: 0 | J17: 0 | K17: 0 | L17: 20813263 | N17: =SUMIFS('APPENDIX 4 iii'!$B17:$L17,'APPENDIX 4 iii'!$B$5:$L$5,"*total*")-O17 -> 20175957 | O17: =SUMIFS('APPENDIX 4 i'!$B17:$K17,'APPENDIX 4 i'!$B$5:$K$5,"*reinsurance*")+ SUMIFS('APPENDIX 4 ii'!$B17:$K17,'APPENDIX 4 ii'!$B$5:$K$5,"*reinsurance*")+ SUMIFS('APPENDIX 4 iii'!$B17:$K17,'APPENDIX 4 iii'!$B$5:$K$5,"*reinsurance*") -> 637306.2 | Q17: =N17+_xlfn.XLOOKUP($B17,'APPENDIX 5 iv'!$B:$B,'APPENDIX 5 iv'!P:P,0,0)+_xlfn.XLOOKUP($B17,'APPENDIX 6'!$B:$B,'APPENDIX 6'!I:I,0,0) -> 21720981 | R17: =O17+_xlfn.XLOOKUP($B17,'APPENDIX 5 iv'!$B:$B,'APPENDIX 5 iv'!Q:Q,0,0)+_xlfn.XLOOKUP($B17,'APPENDIX 6'!$B:$B,'APPENDIX 6'!J:J,0,0) -> 2056840.6 | S17: =SUM(Q17:R17) -> 23777822
... B43: Total Assets | C43: 32389142 | D43: 20550769 | E43: 29904983 | F43: 19511797 | G43: 7326873 | H43: 37240489 | I43: 893565.17 | J43: 5610059.5 | K43: 0 | L43: 1.0934845e+09 | N43: =SUMIFS('APPENDIX 4 iii'!$B43:$L43,'APPENDIX 4 iii'!$B$5:$L$5,"*total*")-O43 -> 1.0759028e+09 | O43: =SUMIFS('APPENDIX 4 i'!$B43:$K43,'APPENDIX 4 i'!$B$5:$K$5,"*reinsurance*")+ SUMIFS('APPENDIX 4 ii'!$B43:$K43,'APPENDIX 4 ii'!$B$5:$K$5,"*reinsurance*")+ SUMIFS('APPENDIX 4 iii'!$B43:$K43,'APPENDIX 4 iii'!$B$5:$K$5,"*reinsurance*") -> 17581708 | Q43: =N43+_xlfn.XLOOKUP($B43,'APPENDIX 5 iv'!$B:$B,'APPENDIX 5 iv'!P:P,0,0)+_xlfn.XLOOKUP($B43,'APPENDIX 6'!$B:$B,'APPENDIX 6'!I:I,0,0) -> 1.3676787e+09 | R43: =O43+_xlfn.XLOOKUP($B43,'APPENDIX 5 iv'!$B:$B,'APPENDIX 5 iv'!Q:Q,0,0)+_xlfn.XLOOKUP($B43,'APPENDIX 6'!$B:$B,'APPENDIX 6'!J:J,0,0) -> 99402604 | S43: =SUM(Q43:R43) -> 1.4670813e+09
B44: Amounts in Thousand Shillings
N47: =N43-N40-N39-N41-N42-N38-N24-N21-N22 -> 1.0283786e+09 | O47: =O43-O40-O39-O41-O42-O38-O24-O21-O22 -> 16721934 | Q47: =Q43-Q40-Q39-Q41-Q42-Q38-Q24-Q21-Q22 -> 1.2200674e+09 | R47: =R43-R40-R39-R41-R42-R38-R24-R21-R22 -> 85200245 | S47: =S43-S40-S39-S41-S42-S38-S24-S21-S22 -> 1.3052676e+09
N48: Life | P48: General | R48: Micro | S48: Industry
N49: Insurers | O49: Reinsurers | P49: Insurers | Q49: Reinsurers | R49: Microinsurers | S49: Insurers | T49: Reinsurers | U49: Total
M50: Equity | N50: =N13 -> 1.0386678e+08 | O50: =O13 -> 13594277 | P50: ='[1]APPENDIX 5 iv'!P12 -> 90922729 | Q50: ='[1]APPENDIX 5 iv'!Q12 -> 53446421 | R50: ='[1]APPENDIX 6 i'!I12 -> 305551.66 | S50: =Q13 -> 1.9890684e+08 | T50: =R13 -> 67163244 | U50: =S13 -> 2.6607009e+08 | V50: =IF(AND(SUM(N50:R50)=SUM(S50:T50),SUM(S50:T50)=U50),"Ok","Check") -> Check
M51: Assets | N51: =N43 -> 1.0759028e+09 | O51: =O43 -> 17581708 | P51: ='[1]APPENDIX 5 iv'!P41 -> 3.0299732e+08 | Q51: ='[1]APPENDIX 5 iv'!Q41 -> 80549341 | R51: ='[1]APPENDIX 6 i'!I41 -> 995719.77 | S51: =Q43 -> 1.3676787e+09 | T51: =R43 -> 99402604 | U51: =S43 -> 1.4670813e+09 | V51: =IF(AND(SUM(N51:R51)=SUM(S51:T51),SUM(S51:T51)=U51),"Ok","Check") -> Check
M52: Investments | N52: =SUM(N23,N25:N37) -> 1.0283786e+09 | O52: =SUM(O23,O25:O37) -> 16721934 | P52: =SUM('[1]APPENDIX 5 iv'!P21,'[1]APPENDIX 5 iv'!P23:P35) -> 1.9170523e+08 | Q52: =SUM('[1]APPENDIX 5 iv'!Q21,'[1]APPENDIX 5 iv'!Q23:Q35) -> 67454378 | R52: =SUM('[1]APPENDIX 6 i'!I21,'[1]APPENDIX 6 i'!I23:I35) -> 600634.44 | S52: =SUM(Q23,Q25:Q37) -> 1.2200674e+09 | T52: =SUM(R23,R25:R37) -> 85200245 | U52: =SUM(S23,S25:S37) -> 1.3052676e+09 | V52: =IF(AND(SUM(N52:R52)=SUM(S52:T52),SUM(S52:T52)=U52),"Ok","Check") -> Check

Sheet APPENDIX 5 i
B4: =_xlfn.CONCAT('Table of Contents'!B14,": ",'Table of Contents'!C14) -> APPENDIX 5 i: SUMMARY OF GENERAL INSURANCE BUSINESS BALANCE SHEETS AS AT 31.12.2025
B5: COMPANY | C5: AAR INSURANCE KENYA | D5: AFRICAN MERCHANT ASSURANCE | E5: APA INSURANCE LIMITED | F5: BRITAM GENERAL INSURANCE | G5: BUPA GLOBAL INSURANCE | H5: CANNON GENERAL INSURANCE | I5: CIC GENERAL INSURANCE COMPANY | J5: CONTINENTAL REINSURANCE | K5: CORPORATE INSURANCE COMPANY | L5: DEFINITE ASSURANCE COMPANY
B6: Share Capital | C6: 1017626.6 | D6: 987386 | E6: 1250000 | F6: 2668000 | G6: 1086683.1 | H6: 453960.46 | I6: 1700000 | J6: 1000000 | K6: 0 | L6: 711518.66
B7: Share Premium | C7: 460523 | D7: 0 | E7: 0 | F7: 0 | G7: 0 | H7: 583039.52 | I7: 0 | J7: 0 | K7: 0 | L7: 0
B8: Revaluation Reserve | C8: 0 | D8: 0 | E8: 234618.57 | F8: 0 | G8: 0 | H8: 74345 | I8: 0 | J8: 0 | K8: 0 | L8: 0
B9: Other Equity | C9: 0 | D9: 26469.279 | E9: 0 | F9: 0 | G9: 0 | H9: -86582 | I9: 261491.19 | J9: 705.556 | K9: 0 | L9: 0
B10: Retained Earnings | C10: 1220426.3 | D10: 397365.52 | E10: 5902178.3 | F10: 5744747.7 | G10: -213218.59 | H10: -229587.65 | I10: 4458007.7 | J10: 2067774.5 | K10: 0 | L10: -346497.07
B11: Other Reserves | C11: 0 | D11: 0 | E11: 0 | F11: 0 | G11: 0 | H11: 0 | I11: 0 | J11: -92125.444 | K11: 0 | L11: 0
B12: Total Equity_x000D_ | C12: 2698575.9 | D12: 1411220.8 | E12: 7386796.9 | F12: 8412747.7 | G12: 873464.55 | H12: 795175.33 | I12: 6419498.9 | J12: 2976354.6 | K12: 0 | L12: 365021.59
B13: Insurance Contract Liabilites | C13: 4967299.8 | D13: 2468260.8 | E13: 11099375 | F13: 11546882 | G13: 1870579.1 | H13: 2668764.1 | I13: 12135575 | J13: 5160618.4 | K13: 0 | L13: 812680.6
B14: Reinsurance Contract Liabilites | C14: 0 | D14: 0 | E14: 0 | F14: 22449.235 | G14: 0 | H14: 0 | I14: 0 | J14: 24374.617 | K14: 0 | L14: 0
B15: Long-Term Liabilites | C15: 0 | D15: 0 | E15: 0 | F15: 0 | G15: 0 | H15: 84201.965 | I15: 0 | J15: 0 | K15: 0 | L15: 0
B16: Short-Term Liabilites | C16: 283965.24 | D16: 246833.47 | E16: 921953.03 | F16: 561630.12 | G16: 39113.9 | H16: 479149.38 | I16: 602357.58 | J16: 0 | K16: 0 | L16: 22810.555
B17: Other Liabilites | C17: 370865.22 | D17: 101052.91 | E17: 171376.46 | F17: 714347.33 | G17: 855354.92 | H17: 30741.775 | I17: 63774.41 | J17: 178786.6 | K17: 0 | L17: 111870.01
... B41: Total Assets | C41: 8320706.1 | D41: 4227367.9 | E41: 19579502 | F41: 21258056 | G41: 3638512.5 | H41: 4058032.6 | I41: 19221206 | J41: 8340134.2 | K41: 0 | L41: 1312382.8
B42: Amounts in Thousand Shillings | K42: Continued next page

Sheet APPENDIX 5 ii
B3: Continued from previous page
B4: =_xlfn.CONCAT('Table of Contents'!B15,": ",'Table of Contents'!C15) -> APPENDIX 5 ii: SUMMARY OF GENERAL INSURANCE BUSINESS BALANCE SHEETS AS AT 31.12.2025
B5: COMPANY | C5: DIRECTLINE ASSURANCE COMPANY | D5: EAST AFRICA REINSURANCE | E5: EQUITY GENERAL INSURANCE LIMITED | F5: EQUITY HEALTH INSURANCE LIMITED | G5: FIDELITY SHIELD INSURANCE | H5: FIRST ASSURANCE COMPANY | I5: GA INSURANCE COMPANY | J5: GEMINIA INSURANCE COMPANY | K5: GHANA REINSURANCE COMPANY | L5: ICEA LION GENERAL INSURANCE
B6: Share Capital | C6: 300000 | D6: 1000000 | E6: 600000 | F6: 600000 | G6: 600000 | H6: 810000 | I6: 1500000 | J6: 1006250 | K6: 1000000 | L6: 1000000
B7: Share Premium | C7: 0 | D7: 0 | E7: 0 | F7: 0 | G7: 0 | H7: 512138.51 | I7: 0 | J7: 0 | K7: 10871.242 | L7: 0
B8: Revaluation Reserve | C8: 15447.29 | D8: 221544.99 | E8: 0 | F8: 0 | G8: 100140.56 | H8: 339179.19 | I8: 904878.74 | J8: 0 | K8: 0 | L8: 22567.995
B9: Other Equity | C9: 0 | D9: 0 | E9: 0 | F9: 0 | G9: 0 | H9: 0 | I9: -750000 | J9: -11810.996 | K9: 0 | L9: 400000
B10: Retained Earnings | C10: -2739567.5 | D10: 4913251.4 | E10: 196224.68 | F10: 28145.033 | G10: 678092.83 | H10: 296670.55 | I10: 7597100.7 | J10: 165833.06 | K10: 1300553.3 | L10: 7341621.4
B11: Other Reserves | C11: 0 | D11: 0 | E11: 0 | F11: 0 | G11: 0 | H11: 0 | I11: 873227.88 | J11: 47953.118 | K11: 0 | L11: 0
B12: Total Equity_x000D_ | C12: -2424120.2 | D12: 6134796.3 | E12: 796224.68 | F12: 628145.03 | G12: 1378233.4 | H12: 1957988.2 | I12: 10125207 | J12: 1208225.2 | K12: 2311424.5 | L12: 8764189.4
B13: Insurance Contract Liabilites | C13: 9520265.7 | D13: 3115873.7 | E13: 540350.38 | F13: 18559.363 | G13: 5296684.5 | H13: 5180952.1 | I13: 13603087 | J13: 5132874.1 | K13: 1202000.5 | L13: 7175065.9
B14: Reinsurance Contract Liabilites | C14: 0 | D14: 111006.35 | E14: 0 | F14: 0 | G14: 0 | H14: 0 | I14: 2056755.7 | J14: 0 | K14: 0 | L14: 239516.29
B15: Long-Term Liabilites | C15: 0 | D15: 0 | E15: 200000 | F15: 200000 | G15: 0 | H15: 0 | I15: 137686.41 | J15: 0 | K15: 0 | L15: 449102.85
B16: Short-Term Liabilites | C16: 260706.15 | D16: 522662.39 | E16: 397928.64 | F16: 10550.603 | G16: 182328.9 | H16: 103765.34 | I16: 489615.82 | J16: 0 | K16: 78527.515 | L16: 962934.05
B17: Other Liabilites | C17: 112804.27 | D17: 32244.74 | E17: 45789.816 | F17: 12062.157 | G17: 7573.6145 | H17: 522017.52 | I17: 417561.57 | J17: 41391.059 | K17: -0.00015000001 | L17: 88888.494
... B41: Total Assets | C41: 7469655.9 | D41: 9916583.5 | E41: 1980293.5 | F41: 869317.16 | G41: 6864820.4 | H41: 7764723.2 | I41: 26829914 | J41: 6382490.4 | K41: 3592026.4 | L41: 17679697
B42: Amounts in Thousand Shillings | K42: Continued next page

Sheet APPENDIX 5 iii
B3: Continued from previous page
B4: =_xlfn.CONCAT('Table of Contents'!B16,": ",'Table of Contents'!C16) -> APPENDIX 5 iii: SUMMARY OF GENERAL INSURANCE BUSINESS BALANCE SHEETS AS AT 31.12.2025
B5: COMPANY | C5: INTRA-AFRICA ASSURANCE | D5: JUBILEE HEALTH INSURANCE | E5: KENINDIA ASSURANCE COMPANY | F5: KENYA ORIENT INSURANCE | G5: KENYA REINSURANCE CORPORATION | H5: MADISON INSURANCE COMPANY | I5: MAYFAIR INSURANCE COMPANY | J5: MUA INSURANCE COMPANY | K5: NCBA INSURANCE COMPANY | L5: OCCIDENTAL INSURANCE COMPANY | M5: OLD MUTUAL GENERAL INSURANCE
B6: Share Capital | C6: 800000 | D6: 2763720 | E6: 600000 | F6: 810721.06 | G6: 13498981 | H6: 605000 | I6: 1500000 | J6: 600000 | K6: 600000 | L6: 745831 | M6: 1000000
B7: Share Premium | C7: 0 | D7: 0 | E7: 1198.295 | F7: 0 | G7: 0 | H7: 0 | I7: 0 | J7: 0 | K7: 0 | L7: 100378.9 | M7: 0
B8: Revaluation Reserve | C8: 342209.34 | D8: 33523.352 | E8: 456053 | F8: 356.34275 | G8: 36911.31 | H8: 0 | I8: -51662.879 | J8: 0 | K8: 9514.7905 | L8: 0 | M8: 0
B9: Other Equity | C9: 30000 | D9: 0 | E9: 441589.77 | F9: 1644217.3 | G9: 626789.01 | H9: 0 | I9: 213735.07 | J9: 1233590.3 | K9: 0 | L9: 150000 | M9: 0
B10: Retained Earnings | C10: 241971.25 | D10: 2982704.4 | E10: 3304913.3 | F10: -3576928.1 | G10: 23201255 | H10: 584023.1 | I10: 3939650.5 | J10: -2122401.1 | K10: 1702361.3 | L10: -348062.29 | M10: 6158123.9
B11: Other Reserves | C11: 0 | D11: 0 | E11: 0 | F11: 0 | G11: 1513821 | H11: 0 | I11: 631146.7 | J11: 20990.634 | K11: 0 | L11: 0 | M11: 0
B12: Total Equity_x000D_ | C12: 1414180.6 | D12: 5779947.8 | E12: 4803754.4 | F12: -1121633.5 | G12: 38877758 | H12: 1189023.1 | I12: 6232869.4 | J12: -267820.12 | K12: 2311876.1 | L12: 648147.61 | M12: 7158123.9
B13: Insurance Contract Liabilites | C13: 1999942.9 | D13: 5108929.8 | E13: 6197381.5 | F13: 2754118.5 | G13: 11462688 | H13: 6715553.5 | I13: 7421699.9 | J13: 2465268.3 | K13: 2603727.3 | L13: 2154329.6 | M13: 11171668
B14: Reinsurance Contract Liabilites | C14: 10754.805 | D14: 0 | E14: 0 | F14: 0 | G14: 1161513.9 | H14: 0 | I14: 0 | J14: 0 | K14: 675836.33 | L14: 0 | M14: 329572.9
B15: Long-Term Liabilites | C15: 0 | D15: 0 | E15: 54306.604 | F15: 0 | G15: 1419534.4 | H15: 0 | I15: 126893.38 | J15: 0 | K15: 0 | L15: 0 | M15: 0
B16: Short-Term Liabilites | C16: 37375.949 | D16: 165113.46 | E16: 268039.32 | F16: 735918.76 | G16: 764449.3 | H16: 52973.053 | I16: 2009412.4 | J16: 580503.9 | K16: 471434.17 | L16: 479054.8 | M16: 473316.52
B17: Other Liabilites | C17: 66587.708 | D17: 486457.56 | E17: 70595.667 | F17: 83957.799 | G17: 324427.39 | H17: 3314.5374 | I17: 206353.72 | J17: 33940.353 | K17: 203345.74 | L17: 71038.118 | M17: 1425297.3
... B41: Total Assets | C41: 3528841.9 | D41: 11540449 | E41: 11394077 | F41: 2452361.6 | G41: 54010371 | H41: 7960864.2 | I41: 15997229 | J41: 2811892.4 | K41: 6266219.7 | L41: 3352570.2 | M41: 20557978
B42: Amounts in Thousand Shillings | L42: Continued next page

Sheet APPENDIX  5 iv
B3: Continued from previous page
B4: =_xlfn.CONCAT('Table of Contents'!B17,": ",'Table of Contents'!C17) -> APPENDIX 5 iv: SUMMARY OF GENERAL INSURANCE BUSINESS BALANCE SHEETS AS AT 31.12.2025
B5: COMPANY | C5: PACIS INSURANCE COMPANY | D5: PIONEER INSURANCE COMPANY | E5: SANLAM ALLIANZ GENERAL INSURANCE | F5: STAR DISCOVER INSURANCE | G5: TAKAFUL INSURANCE OF AFRICA | H5: TAUSI ASSURANCE COMPANY | I5: THE HERITAGE INSURANCE COMPANY | J5: THE KENYAN ALLIANCE INSURANCE | K5: THE MONARCH INSURANCE | L5: TRIDENT INSURANCE COMPANY | M5: WAICA REINSURANCE KENYA LIMITED | N5: TOTAL | P5: Insurers | Q5: Reinsurers
B6: Share Capital | C6: 688553.91 | D6: 700000 | E6: 6459848 | F6: 675000 | G6: 1239704.3 | H6: 600000 | I6: 1000000 | J6: 600000 | K6: 0 | L6: 0 | M6: 1102550 | N6: 55881334 | P6: =SUMIFS('APPENDIX 5 iv'!$B6:$O6,'APPENDIX 5 iv'!$B$5:$O$5,"*total*")-Q6 -> 38279803 | Q6: =SUMIFS('APPENDIX 5 i'!$B6:$O6,'APPENDIX 5 i'!$B$5:$O$5,"*reinsurance*")+ SUMIFS('APPENDIX 5 ii'!$B6:$O6,'APPENDIX 5 ii'!$B$5:$O$5,"*reinsurance*")+ SUMIFS('APPENDIX 5 iii'!$B6:$O6,'APPENDIX 5 iii'!$B$5:$O$5,"*reinsurance*")+ SUMIFS('APPENDIX 5 iv'!$B6:$O6,'APPENDIX 5 iv'!$B$5:$O$5,"*reinsurance*") -> 17601531
B7: Share Premium_x000D_ | C7: 5712 | D7: 0 | E7: 0 | F7: 0 | G7: 146101 | H7: 0 | I7: 0 | J7: 0 | K7: 0 | L7: 0 | M7: 0 | N7: 1819962.5 | P7: =SUMIFS('APPENDIX 5 iv'!$B7:$O7,'APPENDIX 5 iv'!$B$5:$O$5,"*total*")-Q7 -> 1809091.2 | Q7: =SUMIFS('APPENDIX 5 i'!$B7:$O7,'APPENDIX 5 i'!$B$5:$O$5,"*reinsurance*")+ SUMIFS('APPENDIX 5 ii'!$B7:$O7,'APPENDIX 5 ii'!$B$5:$O$5,"*reinsurance*")+ SUMIFS('APPENDIX 5 iii'!$B7:$O7,'APPENDIX 5 iii'!$B$5:$O$5,"*reinsurance*")+ SUMIFS('APPENDIX 5 iv'!$B7:$O7,'APPENDIX 5 iv'!$B$5:$O$5,"*reinsurance*") -> 10871.242
B8: Revaluation Reserves | C8: 0 | D8: 0 | E8: 0 | F8: 0 | G8: 25539.216 | H8: 206006.19 | I8: 0 | J8: 128382 | K8: 0 | L8: 0 | M8: 0 | N8: 3099555 | P8: =SUMIFS('APPENDIX 5 iv'!$B8:$O8,'APPENDIX 5 iv'!$B$5:$O$5,"*total*")-Q8 -> 2841098.7 | Q8: =SUMIFS('APPENDIX 5 i'!$B8:$O8,'APPENDIX 5 i'!$B$5:$O$5,"*reinsurance*")+ SUMIFS('APPENDIX 5 ii'!$B8:$O8,'APPENDIX 5 ii'!$B$5:$O$5,"*reinsurance*")+ SUMIFS('APPENDIX 5 iii'!$B8:$O8,'APPENDIX 5 iii'!$B$5:$O$5,"*reinsurance*")+ SUMIFS('APPENDIX 5 iv'!$B8:$O8,'APPENDIX 5 iv'!$B$5:$O$5,"*reinsurance*") -> 258456.3
B9: Other Equity | C9: 0 | D9: 0 | E9: 0 | F9: 0 | G9: 0 | H9: 53472.984 | I9: 0 | J9: 0 | K9: 0 | L9: 0 | M9: 0 | N9: 4233667.4 | P9: =SUMIFS('APPENDIX 5 iv'!$B9:$O9,'APPENDIX 5 iv'!$B$5:$O$5,"*total*")-Q9 -> 3606172.9 | Q9: =SUMIFS('APPENDIX 5 i'!$B9:$O9,'APPENDIX 5 i'!$B$5:$O$5,"*reinsurance*")+ SUMIFS('APPENDIX 5 ii'!$B9:$O9,'APPENDIX 5 ii'!$B$5:$O$5,"*reinsurance*")+ SUMIFS('APPENDIX 5 iii'!$B9:$O9,'APPENDIX 5 iii'!$B$5:$O$5,"*reinsurance*")+ SUMIFS('APPENDIX 5 iv'!$B9:$O9,'APPENDIX 5 iv'!$B$5:$O$5,"*reinsurance*") -> 627494.57
B10: Retained Earnings | C10: 348914.81 | D10: 213711.94 | E10: -2850363.1 | F10: 30896.77 | G10: -507346.63 | H10: 2291382 | I10: 4336725.4 | J10: -1337669.2 | K10: 0 | L10: 0 | M10: 2166084.2 | N10: 79539070 | P10: =SUMIFS('APPENDIX 5 iv'!$B10:$O10,'APPENDIX 5 iv'!$B$5:$O$5,"*total*")-Q10 -> 45890151 | Q10: =SUMIFS('APPENDIX 5 i'!$B10:$O10,'APPENDIX 5 i'!$B$5:$O$5,"*reinsurance*")+ SUMIFS('APPENDIX 5 ii'!$B10:$O10,'APPENDIX 5 ii'!$B$5:$O$5,"*reinsurance*")+ SUMIFS('APPENDIX 5 iii'!$B10:$O10,'APPENDIX 5 iii'!$B$5:$O$5,"*reinsurance*")+ SUMIFS('APPENDIX 5 iv'!$B10:$O10,'APPENDIX 5 iv'!$B$5:$O$5,"*reinsurance*") -> 33648918
B11: Other Reserves | C11: 24798.639 | D11: 1031184.4 | E11: 0 | F11: 0 | G11: 0 | H11: 0 | I11: 0 | J11: -15557.495 | K11: 0 | L11: 0 | M11: 0 | N11: 4035439.5 | P11: =SUMIFS('APPENDIX 5 iv'!$B11:$O11,'APPENDIX 5 iv'!$B$5:$O$5,"*total*")-Q11 -> 2613743.9 | Q11: =SUMIFS('APPENDIX 5 i'!$B11:$O11,'APPENDIX 5 i'!$B$5:$O$5,"*reinsurance*")+ SUMIFS('APPENDIX 5 ii'!$B11:$O11,'APPENDIX 5 ii'!$B$5:$O$5,"*reinsurance*")+ SUMIFS('APPENDIX 5 iii'!$B11:$O11,'APPENDIX 5 iii'!$B$5:$O$5,"*reinsurance*")+ SUMIFS('APPENDIX 5 iv'!$B11:$O11,'APPENDIX 5 iv'!$B$5:$O$5,"*reinsurance*") -> 1421695.6
B12: Total Equity_x000D_ | C12: 1067979.4 | D12: 1944896.4 | E12: 3609484.9 | F12: 705896.77 | G12: 903997.86 | H12: 3150861.2 | I12: 5336725.4 | J12: -624844.74 | K12: 0 | L12: 0 | M12: 3268634.2 | N12: 1.4860903e+08 | P12: =SUMIFS('APPENDIX 5 iv'!$B12:$O12,'APPENDIX 5 iv'!$B$5:$O$5,"*total*")-Q12 -> 95040061 | Q12: =SUMIFS('APPENDIX 5 i'!$B12:$O12,'APPENDIX 5 i'!$B$5:$O$5,"*reinsurance*")+ SUMIFS('APPENDIX 5 ii'!$B12:$O12,'APPENDIX 5 ii'!$B$5:$O$5,"*reinsurance*")+ SUMIFS('APPENDIX 5 iii'!$B12:$O12,'APPENDIX 5 iii'!$B$5:$O$5,"*reinsurance*")+ SUMIFS('APPENDIX 5 iv'!$B12:$O12,'APPENDIX 5 iv'!$B$5:$O$5,"*reinsurance*") -> 53568968
B13: Insurance Contract Liabilites | C13: 2923192.1 | D13: 2181593.5 | E13: 10322094 | F13: 345901.35 | G13: 1022158.3 | H13: 1176654.7 | I13: 6184587.2 | J13: 1175089.8 | K13: 0 | L13: 0 | M13: 2171274.1 | N13: 1.910736e+08 | P13: =SUMIFS('APPENDIX 5 iv'!$B13:$O13,'APPENDIX 5 iv'!$B$5:$O$5,"*total*")-Q13 -> 1.6796115e+08 | Q13: =SUMIFS('APPENDIX 5 i'!$B13:$O13,'APPENDIX 5 i'!$B$5:$O$5,"*reinsurance*")+ SUMIFS('APPENDIX 5 ii'!$B13:$O13,'APPENDIX 5 ii'!$B$5:$O$5,"*reinsurance*")+ SUMIFS('APPENDIX 5 iii'!$B13:$O13,'APPENDIX 5 iii'!$B$5:$O$5,"*reinsurance*")+ SUMIFS('APPENDIX 5 iv'!$B13:$O13,'APPENDIX 5 iv'!$B$5:$O$5,"*reinsurance*") -> 23112454
B14: Reinsurance Contract Liabilites | C14: 0 | D14: 0 | E14: 123395.9 | F14: 0 | G14: 77.224395 | H14: 0 | I14: 0 | J14: 23191.565 | K14: 0 | L14: 0 | M14: 352695.53 | N14: 5131140.3 | P14: =SUMIFS('APPENDIX 5 iv'!$B14:$O14,'APPENDIX 5 iv'!$B$5:$O$5,"*total*")-Q14 -> 3481549.9 | Q14: =SUMIFS('APPENDIX 5 i'!$B14:$O14,'APPENDIX 5 i'!$B$5:$O$5,"*reinsurance*")+ SUMIFS('APPENDIX 5 ii'!$B14:$O14,'APPENDIX 5 ii'!$B$5:$O$5,"*reinsurance*")+ SUMIFS('APPENDIX 5 iii'!$B14:$O14,'APPENDIX 5 iii'!$B$5:$O$5,"*reinsurance*")+ SUMIFS('APPENDIX 5 iv'!$B14:$O14,'APPENDIX 5 iv'!$B$5:$O$5,"*reinsurance*") -> 1649590.4
B15: Long-Term Liabilites | C15: 37385.016 | D15: 0 | E15: 0 | F15: 6698.482 | G15: 11988 | H15: 75328.124 | I15: 38586.533 | J15: 119413.41 | K15: 0 | L15: 0 | M15: 0 | N15: 2961125.2 | P15: =SUMIFS('APPENDIX 5 iv'!$B15:$O15,'APPENDIX 5 iv'!$B$5:$O$5,"*total*")-Q15 -> 1541590.8 | Q15: =SUMIFS('APPENDIX 5 i'!$B15:$O15,'APPENDIX 5 i'!$B$5:$O$5,"*reinsurance*")+ SUMIFS('APPENDIX 5 ii'!$B15:$O15,'APPENDIX 5 ii'!$B$5:$O$5,"*reinsurance*")+ SUMIFS('APPENDIX 5 iii'!$B15:$O15,'APPENDIX 5 iii'!$B$5:$O$5,"*reinsurance*")+ SUMIFS('APPENDIX 5 iv'!$B15:$O15,'APPENDIX 5 iv'!$B$5:$O$5,"*reinsurance*") -> 1419534.4
B16: Short-Term Liabilites | C16: 293944.99 | D16: 33239.479 | E16: 769886.48 | F16: 281631.94 | G16: 9032.383 | H16: 87501.419 | I16: 1006630.9 | J16: 1536950.7 | K16: 0 | L16: 0 | M16: 146147.38 | N16: 16369390 | P16: =SUMIFS('APPENDIX 5 iv'!$B16:$O16,'APPENDIX 5 iv'!$B$5:$O$5,"*total*")-Q16 -> 14857603 | Q16: =SUMIFS('APPENDIX 5 i'!$B16:$O16,'APPENDIX 5 i'!$B$5:$O$5,"*reinsurance*")+ SUMIFS('APPENDIX 5 ii'!$B16:$O16,'APPENDIX 5 ii'!$B$5:$O$5,"*reinsurance*")+ SUMIFS('APPENDIX 5 iii'!$B16:$O16,'APPENDIX 5 iii'!$B$5:$O$5,"*reinsurance*")+ SUMIFS('APPENDIX 5 iv'!$B16:$O16,'APPENDIX 5 iv'!$B$5:$O$5,"*reinsurance*") -> 1511786.6
B17: Other Liabilites | C17: 78702.861 | D17: 132981.77 | E17: 182069.33 | F17: 212250.35 | G17: 64265 | H17: 27477.418 | I17: 414356.06 | J17: 56147.649 | K17: 0 | L17: 0 | M17: 23030.269 | N17: 8045099.5 | P17: =SUMIFS('APPENDIX 5 iv'!$B17:$O17,'APPENDIX 5 iv'!$B$5:$O$5,"*total*")-Q17 -> 7486610.5 | Q17: =SUMIFS('APPENDIX 5 i'!$B17:$O17,'APPENDIX 5 i'!$B$5:$O$5,"*reinsurance*")+ SUMIFS('APPENDIX 5 ii'!$B17:$O17,'APPENDIX 5 ii'!$B$5:$O$5,"*reinsurance*")+ SUMIFS('APPENDIX 5 iii'!$B17:$O17,'APPENDIX 5 iii'!$B$5:$O$5,"*reinsurance*")+ SUMIFS('APPENDIX 5 iv'!$B17:$O17,'APPENDIX 5 iv'!$B$5:$O$5,"*reinsurance*") -> 558489
... B41: Total Assets | C41: 4401204.4 | D41: 4292711.2 | E41: 15006930 | F41: 1552378.9 | G41: 2011518.7 | H41: 4517822.8 | I41: 12980886 | J41: 2285948.5 | K41: 0 | L41: 0 | M41: 5961781.5 | N41: 3.7218946e+08 | P41: =SUMIFS('APPENDIX 5 iv'!$B41:$O41,'APPENDIX 5 iv'!$B$5:$O$5,"*total*")-Q41 -> 2.9036856e+08 | Q41: =SUMIFS('APPENDIX 5 i'!$B41:$O41,'APPENDIX 5 i'!$B$5:$O$5,"*reinsurance*")+ SUMIFS('APPENDIX 5 ii'!$B41:$O41,'APPENDIX 5 ii'!$B$5:$O$5,"*reinsurance*")+ SUMIFS('APPENDIX 5 iii'!$B41:$O41,'APPENDIX 5 iii'!$B$5:$O$5,"*reinsurance*")+ SUMIFS('APPENDIX 5 iv'!$B41:$O41,'APPENDIX 5 iv'!$B$5:$O$5,"*reinsurance*") -> 81820896
B42: Amounts in thousand Shillings

Sheet APPENDIX 6
B4: =_xlfn.CONCAT('Table of Contents'!B18,": ",'Table of Contents'!C18) -> APPENDIX 6: SUMMARY OF MICRO INSURANCE BUSINESS BALANCE SHEETS AS AT 31.12.2025
B5: COMPANY | C5: APA MICRO INSURANCE | D5: BIRDVIEW MICRO INSURANCE | E5: BRITAM MICRO INSURANCE | F5: CIC MICRO INSURANCE | G5: STAR DISCOVER MICRO INSURANCE | H5: TURACO MICRO INSURANCE | I5: TOTAL
B6: Share Capital | C6: 0 | D6: 50000 | E6: 150000 | F6: 50000 | G6: 100000 | H6: 50000 | I6: 400000
B7: Share Premium_x000D_ | C7: 0 | D7: 0 | E7: 0 | F7: 0 | G7: 0 | H7: 0 | I7: 0
B8: Revaluation Reserves | C8: 0 | D8: 0 | E8: 0 | F8: 0 | G8: 0 | H8: 0 | I8: 0
B9: Other Equity | C9: 0 | D9: 30000 | E9: 0 | F9: 0 | G9: 0 | H9: 0 | I9: 30000
B10: Retained Earnings | C10: 0 | D10: -34121.477 | E10: -2441.7778 | F10: -19450.436 | G10: -53556.462 | H10: 61566.036 | I10: -48004.117
B11: Other Reserves | C11: 0 | D11: 0 | E11: 0 | F11: 0 | G11: 0 | H11: 0 | I11: 0
B12: Total Equity | C12: 0 | D12: 45878.523 | E12: 147558.22 | F12: 30549.564 | G12: 46443.538 | H12: 111566.04 | I12: 381995.88
B13: Insurance Contract Liabilites | C13: 0 | D13: 14078.794 | E13: 514591.75 | F13: 6512.7901 | G13: 0 | H13: 74572.838 | I13: 609756.17
B14: Reinsurance Contract Liabilites | C14: 0 | D14: 0 | E14: 8921.3717 | F14: 0 | G14: 0 | H14: 0 | I14: 8921.3717
B15: Long-Term Liabilites | C15: 0 | D15: 0 | E15: 0 | F15: 0 | G15: 0 | H15: 3433.0628 | I15: 3433.0628
B16: Short-Term Liabilites | C16: 0 | D16: 0 | E16: 183957.85 | F16: 16442.719 | G16: 0 | H16: 61870.002 | I16: 262270.57
B17: Other Liabilites | C17: 0 | D17: 15420.014 | E17: 68841.907 | F17: 0 | G17: 48223.355 | H17: 8485.5904 | I17: 140970.87
... B41: Total Assets | C41: 0 | D41: 75377.331 | E41: 923871.1 | F41: 53505.074 | G41: 94666.892 | H41: 259927.53 | I41: 1407347.9
B42: Amounts in thousand Shillings

Sheet APPENDIX 7
B3: =_xlfn.CONCAT('Table of Contents'!B19,": ",'Table of Contents'!C19) -> APPENDIX 7: SUMMARY OF LONG TERM INSURANCE BUSINESS GROSS PREMIUM INCOME FOR THE PERIOD ENDED 31.12.2025
B4: Company | C4: Life Assurances | D4: Annuities | E4: Personal Pensions | F4: Deposit Administration | G4: Group Life | H4: Group Credit | I4: Permanent Health | J4: Investments | K4: Total | L4: Market Share (%)
B5: INSURERS
B6: ='APPENDIX 9'!B6 -> ABSA LIFE ASSURANCE | C6: ='APPENDIX 9'!D6 -> 6316275.5 | D6: ='APPENDIX 10'!D6 -> 0 | E6: ='APPENDIX 15'!D6 -> 0 | F6: ='APPENDIX 16'!D6 -> 0 | G6: ='APPENDIX 11'!D6 -> 2567980.5 | H6: ='APPENDIX 12'!D6 -> 1143702.6 | I6: ='APPENDIX 14'!D6 -> 0 | J6: ='APPENDIX 13'!D6 -> 0 | K6: =SUM(C6:J6) -> 10027959 | L6: =IFERROR(K6/$K$30,0)*100 -> 4.2601491
B7: ='APPENDIX 9'!B7 -> APA LIFE ASSURANCE COMPANY | C7: ='APPENDIX 9'!D7 -> 610629.03 | D7: ='APPENDIX 10'!D7 -> 23589.961 | E7: ='APPENDIX 15'!D7 -> 130267.85 | F7: ='APPENDIX 16'!D7 -> 1949836.4 | G7: ='APPENDIX 11'!D7 -> 1831004.8 | H7: ='APPENDIX 12'!D7 -> 1315454.1 | I7: ='APPENDIX 14'!D7 -> 0 | J7: ='APPENDIX 13'!D7 -> 8662218 | K7: =SUM(C7:J7) -> 14523000 | L7: =IFERROR(K7/$K$30,0)*100 -> 6.1697648
B8: ='APPENDIX 9'!B8 -> BRITAM LIFE ASSURANCE | C8: ='APPENDIX 9'!D8 -> 11532887 | D8: ='APPENDIX 10'!D8 -> 7464031 | E8: ='APPENDIX 15'!D8 -> 6139589.5 | F8: ='APPENDIX 16'!D8 -> 8836842.7 | G8: ='APPENDIX 11'!D8 -> 5227073 | H8: ='APPENDIX 12'!D8 -> 432715.57 | I8: ='APPENDIX 14'!D8 -> 0 | J8: ='APPENDIX 13'!D8 -> 13503522 | K8: =SUM(C8:J8) -> 53136661 | L8: =IFERROR(K8/$K$30,0)*100 -> 22.573896
B9: ='APPENDIX 9'!B9 -> CANNON LIFE ASSURANCE (K) LIMITED | C9: ='APPENDIX 9'!D9 -> 21594.655 | D9: ='APPENDIX 10'!D9 -> 0 | E9: ='APPENDIX 15'!D9 -> 0 | F9: ='APPENDIX 16'!D9 -> 0 | G9: ='APPENDIX 11'!D9 -> 504610.99 | H9: ='APPENDIX 12'!D9 -> 14341.352 | I9: ='APPENDIX 14'!D9 -> 0 | J9: ='APPENDIX 13'!D9 -> 0 | K9: =SUM(C9:J9) -> 540547 | L9: =IFERROR(K9/$K$30,0)*100 -> 0.22963905
B10: ='APPENDIX 9'!B10 -> CAPEX LIFE ASSURANCE COMPANY | C10: ='APPENDIX 9'!D10 -> 6056.3897 | D10: ='APPENDIX 10'!D10 -> 249593.05 | E10: ='APPENDIX 15'!D10 -> 41254.695 | F10: ='APPENDIX 16'!D10 -> 0 | G10: ='APPENDIX 11'!D10 -> 948991.07 | H10: ='APPENDIX 12'!D10 -> 111804.07 | I10: ='APPENDIX 14'!D10 -> 0 | J10: ='APPENDIX 13'!D10 -> 0 | K10: =SUM(C10:J10) -> 1357699.3 | L10: =IFERROR(K10/$K$30,0)*100 -> 0.57678752
B11: ='APPENDIX 9'!B11 -> CIC LIFE ASSURANCE COMPANY | C11: ='APPENDIX 9'!D11 -> 1409614.1 | D11: ='APPENDIX 10'!D11 -> 1214105.3 | E11: ='APPENDIX 15'!D11 -> 0 | F11: ='APPENDIX 16'!D11 -> 3353751.3 | G11: ='APPENDIX 11'!D11 -> 824232.39 | H11: ='APPENDIX 12'!D11 -> 6467982.3 | I11: ='APPENDIX 14'!D11 -> 0 | J11: ='APPENDIX 13'!D11 -> 0 | K11: =SUM(C11:J11) -> 13269685 | L11: =IFERROR(K11/$K$30,0)*100 -> 5.6373227
B12: ='APPENDIX 9'!B12 -> CORPORATE INSURANCE COMPANY | C12: ='APPENDIX 9'!D12 -> 34017.644 | D12: ='APPENDIX 10'!D12 -> 0 | E12: ='APPENDIX 15'!D12 -> 0 | F12: ='APPENDIX 16'!D12 -> 0 | G12: ='APPENDIX 11'!D12 -> 0 | H12: ='APPENDIX 12'!D12 -> 0 | I12: ='APPENDIX 14'!D12 -> 0 | J12: ='APPENDIX 13'!D12 -> 0 | K12: =SUM(C12:J12) -> 34017.644 | L12: =IFERROR(K12/$K$30,0)*100 -> 0.014451619
B13: ='APPENDIX 9'!B13 -> EQUITY LIFE ASSURANCE | C13: ='APPENDIX 9'!D13 -> 0 | D13: ='APPENDIX 10'!D13 -> 0 | E13: ='APPENDIX 15'!D13 -> 332020.42 | F13: ='APPENDIX 16'!D13 -> 2461209.1 | G13: ='APPENDIX 11'!D13 -> 646193.82 | H13: ='APPENDIX 12'!D13 -> 2338846.6 | I13: ='APPENDIX 14'!D13 -> 0 | J13: ='APPENDIX 13'!D13 -> 321400.65 | K13: =SUM(C13:J13) -> 6099670.6 | L13: =IFERROR(K13/$K$30,0)*100 -> 2.5913057
B14: ='APPENDIX 9'!B14 -> GA LIFE ASSURANCE COMPANY | C14: ='APPENDIX 9'!D14 -> 1053351.9 | D14: ='APPENDIX 10'!D14 -> 0 | E14: ='APPENDIX 15'!D14 -> 1903228.5 | F14: ='APPENDIX 16'!D14 -> 9973803.1 | G14: ='APPENDIX 11'!D14 -> 81952.477 | H14: ='APPENDIX 12'!D14 -> 3027.538 | I14: ='APPENDIX 14'!D14 -> 0 | J14: ='APPENDIX 13'!D14 -> 0 | K14: =SUM(C14:J14) -> 13015363 | L14: =IFERROR(K14/$K$30,0)*100 -> 5.5292798
B15: ='APPENDIX 9'!B15 -> GEMINIA LIFE INSURANCE COMPANY | C15: ='APPENDIX 9'!D15 -> 90055.417 | D15: ='APPENDIX 10'!D15 -> 0 | E15: ='APPENDIX 15'!D15 -> 106143.11 | F15: ='APPENDIX 16'!D15 -> 653982.21 | G15: ='APPENDIX 11'!D15 -> 213260.89 | H15: ='APPENDIX 12'!D15 -> 511593.44 | I15: ='APPENDIX 14'!D15 -> 0 | J15: ='APPENDIX 13'!D15 -> 574003.62 | K15: =SUM(C15:J15) -> 2149038.7 | L15: =IFERROR(K15/$K$30,0)*100 -> 0.91296999
B16: ='APPENDIX 9'!B16 -> ICEA LION LIFE ASSURANCE | C16: ='APPENDIX 9'!D16 -> 9823389.5 | D16: ='APPENDIX 10'!D16 -> 2481013.5 | E16: ='APPENDIX 15'!D16 -> 8823772.1 | F16: ='APPENDIX 16'!D16 -> 10776285 | G16: ='APPENDIX 11'!D16 -> 549692.75 | H16: ='APPENDIX 12'!D16 -> 355779.25 | I16: ='APPENDIX 14'!D16 -> 0 | J16: ='APPENDIX 13'!D16 -> 5030.2792 | K16: =SUM(C16:J16) -> 32814963 | L16: =IFERROR(K16/$K$30,0)*100 -> 13.940687
B17: ='APPENDIX 9'!B17 -> JUBILEE LIFE INSURANCE | C17: ='APPENDIX 9'!D17 -> 4621119 | D17: ='APPENDIX 10'!D17 -> 1763324.3 | E17: ='APPENDIX 15'!D17 -> 3497687.6 | F17: ='APPENDIX 16'!D17 -> 16677893 | G17: ='APPENDIX 11'!D17 -> 1132529.3 | H17: ='APPENDIX 12'!D17 -> 251953.05 | I17: ='APPENDIX 14'!D17 -> 0 | J17: ='APPENDIX 13'!D17 -> 2710479.1 | K17: =SUM(C17:J17) -> 30654986 | L17: =IFERROR(K17/$K$30,0)*100 -> 13.02307
... B29: ='APPENDIX 9'!B29 -> THE MONARCH INSURANCE | C29: ='APPENDIX 9'!D29 -> 0 | D29: ='APPENDIX 10'!D29 -> 0 | E29: ='APPENDIX 15'!D29 -> 0 | F29: ='APPENDIX 16'!D29 -> 0 | G29: ='APPENDIX 11'!D29 -> 0 | H29: ='APPENDIX 12'!D29 -> 0 | I29: ='APPENDIX 14'!D29 -> 0 | J29: ='APPENDIX 13'!D29 -> 0 | K29: =SUM(C29:J29) -> 0 | L29: =IFERROR(K29/$K$30,0)*100 -> 0
B30: TOTAL | C30: =SUM(C6:C29) -> 46301279 | D30: =SUM(D6:D29) -> 14498772 | E30: =SUM(E6:E29) -> 24976102 | F30: =SUM(F6:F29) -> 79746501 | G30: =SUM(G6:G29) -> 21540254 | H30: =SUM(H6:H29) -> 18029811 | I30: =SUM(I6:I29) -> 0 | J30: =SUM(J6:J29) -> 30297131 | ... L30: =SUM(L6:L29) -> 100
B31: REINSURERS
B32: ='APPENDIX 9'!B32 -> CONTINENTAL REINSURANCE | C32: ='APPENDIX 9'!D32 -> 0 | D32: ='APPENDIX 10'!D32 -> 0 | E32: ='APPENDIX 15'!D32 -> 0 | F32: ='APPENDIX 16'!F32 -> 0 | G32: ='APPENDIX 11'!D32 -> 36252.815 | H32: ='APPENDIX 12'!D32 -> 0 | I32: ='APPENDIX 14'!D32 -> 0 | J32: ='APPENDIX 13'!D32 -> 0 | K32: =SUM(C32:J32) -> 36252.815 | L32: =IFERROR(K32/$K$35,0)*100 -> 0.85050544
B33: ='APPENDIX 9'!B33 -> EAST AFRICA REINSURANCE | C33: ='APPENDIX 9'!D33 -> 142636.88 | D33: ='APPENDIX 10'!D33 -> 0 | E33: ='APPENDIX 15'!D33 -> 0 | F33: ='APPENDIX 16'!F33 -> 0 | G33: ='APPENDIX 11'!D33 -> 1192249.3 | H33: ='APPENDIX 12'!D33 -> 0 | I33: ='APPENDIX 14'!D33 -> 0 | J33: ='APPENDIX 13'!D33 -> 0 | K33: =SUM(C33:J33) -> 1334886.2 | L33: =IFERROR(K33/$K$35,0)*100 -> 31.31696
B34: ='APPENDIX 9'!B34 -> KENYA REINSURANCE CORPORATION | C34: ='APPENDIX 9'!D34 -> 112126.23 | D34: ='APPENDIX 10'!D34 -> 0 | E34: ='APPENDIX 15'!D34 -> 0 | F34: ='APPENDIX 16'!F34 -> 0 | G34: ='APPENDIX 11'!D34 -> 2779237.2 | H34: ='APPENDIX 12'!D34 -> 0 | I34: ='APPENDIX 14'!D34 -> 0 | J34: ='APPENDIX 13'!D34 -> 0 | K34: =SUM(C34:J34) -> 2891363.4 | L34: =IFERROR(K34/$K$35,0)*100 -> 67.832535
B35: TOTAL | C35: =SUM(C32:C34) -> 254763.1 | D35: =SUM(D32:D34) -> 0 | E35: =SUM(E32:E34) -> 0 | F35: =SUM(F32:F34) -> 0 | G35: =SUM(G32:G34) -> 4007739.3 | H35: =SUM(H32:H34) -> 0 | I35: =SUM(I32:I34) -> 0 | J35: =SUM(J32:J34) -> 0 | ... L35: =SUM(L32:L34) -> 100
B36: Amounts in Thousand Shillings

Sheet APPENDIX 8
B3: =_xlfn.CONCAT('Table of Contents'!B20,": ",'Table of Contents'!C20) -> APPENDIX 8: SUMMARY OF LONG TERM INSURANCE BUSINESS MARKET SHARE PER CLASS FOR THE PERIOD ENDED 31.12.2025
B4: Company | C4: Life Assurances | D4: Annuities | E4: Pensions | F4: Deposit Administration | G4: Group Life | H4: Group Credit | I4: Permanent Health | J4: Investments | K4: Total
B5: INSURERS
B6: ='APPENDIX 9'!B6 -> ABSA LIFE ASSURANCE | C6: =IFERROR(('APPENDIX 7'!C6/'APPENDIX 7'!C$30)*100,0) -> 13.641687 | D6: =IFERROR(('APPENDIX 7'!D6/'APPENDIX 7'!D$30)*100,0) -> 0 | E6: =IFERROR(('APPENDIX 7'!E6/'APPENDIX 7'!E$30)*100,0) -> 0 | F6: =IFERROR(('APPENDIX 7'!F6/'APPENDIX 7'!F$30)*100,0) -> 0 | G6: =IFERROR(('APPENDIX 7'!G6/'APPENDIX 7'!G$30)*100,0) -> 11.921775 | H6: =IFERROR(('APPENDIX 7'!H6/'APPENDIX 7'!H$30)*100,0) -> 6.3433978 | I6: =IFERROR(('APPENDIX 7'!I6/'APPENDIX 7'!I$30)*100,0) -> 0 | J6: =IFERROR(('APPENDIX 7'!J6/'APPENDIX 7'!J$30)*100,0) -> 0 | K6: =IFERROR(('APPENDIX 7'!K6/'APPENDIX 7'!K$30)*100,0) -> 4.2601491 | L6: =RANK(K6,$K$6:$K$29) -> 8 | M6: =COUNTIF(K6:K29,">5") -> 7
B7: ='APPENDIX 9'!B7 -> APA LIFE ASSURANCE COMPANY | C7: =IFERROR(('APPENDIX 7'!C7/'APPENDIX 7'!C$30)*100,0) -> 1.3188168 | D7: =IFERROR(('APPENDIX 7'!D7/'APPENDIX 7'!D$30)*100,0) -> 0.16270316 | E7: =IFERROR(('APPENDIX 7'!E7/'APPENDIX 7'!E$30)*100,0) -> 0.52156998 | F7: =IFERROR(('APPENDIX 7'!F7/'APPENDIX 7'!F$30)*100,0) -> 2.4450432 | G7: =IFERROR(('APPENDIX 7'!G7/'APPENDIX 7'!G$30)*100,0) -> 8.5003864 | H7: =IFERROR(('APPENDIX 7'!H7/'APPENDIX 7'!H$30)*100,0) -> 7.2959952 | I7: =IFERROR(('APPENDIX 7'!I7/'APPENDIX 7'!I$30)*100,0) -> 0 | J7: =IFERROR(('APPENDIX 7'!J7/'APPENDIX 7'!J$30)*100,0) -> 28.590885 | K7: =IFERROR(('APPENDIX 7'!K7/'APPENDIX 7'!K$30)*100,0) -> 6.1697648 | L7: =RANK(K7,$K$6:$K$29) -> 5
B8: ='APPENDIX 9'!B8 -> BRITAM LIFE ASSURANCE | C8: =IFERROR(('APPENDIX 7'!C8/'APPENDIX 7'!C$30)*100,0) -> 24.908355 | D8: =IFERROR(('APPENDIX 7'!D8/'APPENDIX 7'!D$30)*100,0) -> 51.480436 | E8: =IFERROR(('APPENDIX 7'!E8/'APPENDIX 7'!E$30)*100,0) -> 24.581856 | F8: =IFERROR(('APPENDIX 7'!F8/'APPENDIX 7'!F$30)*100,0) -> 11.081167 | G8: =IFERROR(('APPENDIX 7'!G8/'APPENDIX 7'!G$30)*100,0) -> 24.266534 | H8: =IFERROR(('APPENDIX 7'!H8/'APPENDIX 7'!H$30)*100,0) -> 2.4000007 | I8: =IFERROR(('APPENDIX 7'!I8/'APPENDIX 7'!I$30)*100,0) -> 0 | J8: =IFERROR(('APPENDIX 7'!J8/'APPENDIX 7'!J$30)*100,0) -> 44.570299 | K8: =IFERROR(('APPENDIX 7'!K8/'APPENDIX 7'!K$30)*100,0) -> 22.573896 | L8: =RANK(K8,$K$6:$K$29) -> 1
B9: ='APPENDIX 9'!B9 -> CANNON LIFE ASSURANCE (K) LIMITED | C9: =IFERROR(('APPENDIX 7'!C9/'APPENDIX 7'!C$30)*100,0) -> 0.046639436 | D9: =IFERROR(('APPENDIX 7'!D9/'APPENDIX 7'!D$30)*100,0) -> 0 | E9: =IFERROR(('APPENDIX 7'!E9/'APPENDIX 7'!E$30)*100,0) -> 0 | F9: =IFERROR(('APPENDIX 7'!F9/'APPENDIX 7'!F$30)*100,0) -> 0 | G9: =IFERROR(('APPENDIX 7'!G9/'APPENDIX 7'!G$30)*100,0) -> 2.3426418 | H9: =IFERROR(('APPENDIX 7'!H9/'APPENDIX 7'!H$30)*100,0) -> 0.079542446 | I9: =IFERROR(('APPENDIX 7'!I9/'APPENDIX 7'!I$30)*100,0) -> 0 | J9: =IFERROR(('APPENDIX 7'!J9/'APPENDIX 7'!J$30)*100,0) -> 0 | K9: =IFERROR(('APPENDIX 7'!K9/'APPENDIX 7'!K$30)*100,0) -> 0.22963905 | L9: =RANK(K9,$K$6:$K$29) -> 20
B10: ='APPENDIX 9'!B10 -> CAPEX LIFE ASSURANCE COMPANY | C10: =IFERROR(('APPENDIX 7'!C10/'APPENDIX 7'!C$30)*100,0) -> 0.013080394 | D10: =IFERROR(('APPENDIX 7'!D10/'APPENDIX 7'!D$30)*100,0) -> 1.7214771 | E10: =IFERROR(('APPENDIX 7'!E10/'APPENDIX 7'!E$30)*100,0) -> 0.16517668 | F10: =IFERROR(('APPENDIX 7'!F10/'APPENDIX 7'!F$30)*100,0) -> 0 | G10: =IFERROR(('APPENDIX 7'!G10/'APPENDIX 7'!G$30)*100,0) -> 4.4056634 | H10: =IFERROR(('APPENDIX 7'!H10/'APPENDIX 7'!H$30)*100,0) -> 0.62010674 | I10: =IFERROR(('APPENDIX 7'!I10/'APPENDIX 7'!I$30)*100,0) -> 0 | J10: =IFERROR(('APPENDIX 7'!J10/'APPENDIX 7'!J$30)*100,0) -> 0 | K10: =IFERROR(('APPENDIX 7'!K10/'APPENDIX 7'!K$30)*100,0) -> 0.57678752 | L10: =RANK(K10,$K$6:$K$29) -> 18
B11: ='APPENDIX 9'!B11 -> CIC LIFE ASSURANCE COMPANY | C11: =IFERROR(('APPENDIX 7'!C11/'APPENDIX 7'!C$30)*100,0) -> 3.0444388 | D11: =IFERROR(('APPENDIX 7'!D11/'APPENDIX 7'!D$30)*100,0) -> 8.3738494 | E11: =IFERROR(('APPENDIX 7'!E11/'APPENDIX 7'!E$30)*100,0) -> 0 | F11: =IFERROR(('APPENDIX 7'!F11/'APPENDIX 7'!F$30)*100,0) -> 4.2055153 | G11: =IFERROR(('APPENDIX 7'!G11/'APPENDIX 7'!G$30)*100,0) -> 3.8264749 | H11: =IFERROR(('APPENDIX 7'!H11/'APPENDIX 7'!H$30)*100,0) -> 35.873823 | I11: =IFERROR(('APPENDIX 7'!I11/'APPENDIX 7'!I$30)*100,0) -> 0 | J11: =IFERROR(('APPENDIX 7'!J11/'APPENDIX 7'!J$30)*100,0) -> 0 | K11: =IFERROR(('APPENDIX 7'!K11/'APPENDIX 7'!K$30)*100,0) -> 5.6373227 | L11: =RANK(K11,$K$6:$K$29) -> 6
B12: ='APPENDIX 9'!B12 -> CORPORATE INSURANCE COMPANY | C12: =IFERROR(('APPENDIX 7'!C12/'APPENDIX 7'!C$30)*100,0) -> 0.073470204 | D12: =IFERROR(('APPENDIX 7'!D12/'APPENDIX 7'!D$30)*100,0) -> 0 | E12: =IFERROR(('APPENDIX 7'!E12/'APPENDIX 7'!E$30)*100,0) -> 0 | F12: =IFERROR(('APPENDIX 7'!F12/'APPENDIX 7'!F$30)*100,0) -> 0 | G12: =IFERROR(('APPENDIX 7'!G12/'APPENDIX 7'!G$30)*100,0) -> 0 | H12: =IFERROR(('APPENDIX 7'!H12/'APPENDIX 7'!H$30)*100,0) -> 0 | I12: =IFERROR(('APPENDIX 7'!I12/'APPENDIX 7'!I$30)*100,0) -> 0 | J12: =IFERROR(('APPENDIX 7'!J12/'APPENDIX 7'!J$30)*100,0) -> 0 | K12: =IFERROR(('APPENDIX 7'!K12/'APPENDIX 7'!K$30)*100,0) -> 0.014451619 | L12: =RANK(K12,$K$6:$K$29) -> 22
B13: ='APPENDIX 9'!B13 -> EQUITY LIFE ASSURANCE | C13: =IFERROR(('APPENDIX 7'!C13/'APPENDIX 7'!C$30)*100,0) -> 0 | D13: =IFERROR(('APPENDIX 7'!D13/'APPENDIX 7'!D$30)*100,0) -> 0 | E13: =IFERROR(('APPENDIX 7'!E13/'APPENDIX 7'!E$30)*100,0) -> 1.3293524 | F13: =IFERROR(('APPENDIX 7'!F13/'APPENDIX 7'!F$30)*100,0) -> 3.086291 | G13: =IFERROR(('APPENDIX 7'!G13/'APPENDIX 7'!G$30)*100,0) -> 2.999936 | H13: =IFERROR(('APPENDIX 7'!H13/'APPENDIX 7'!H$30)*100,0) -> 12.972108 | I13: =IFERROR(('APPENDIX 7'!I13/'APPENDIX 7'!I$30)*100,0) -> 0 | J13: =IFERROR(('APPENDIX 7'!J13/'APPENDIX 7'!J$30)*100,0) -> 1.0608287 | K13: =IFERROR(('APPENDIX 7'!K13/'APPENDIX 7'!K$30)*100,0) -> 2.5913057 | L13: =RANK(K13,$K$6:$K$29) -> 12
B14: ='APPENDIX 9'!B14 -> GA LIFE ASSURANCE COMPANY | C14: =IFERROR(('APPENDIX 7'!C14/'APPENDIX 7'!C$30)*100,0) -> 2.2749952 | D14: =IFERROR(('APPENDIX 7'!D14/'APPENDIX 7'!D$30)*100,0) -> 0 | E14: =IFERROR(('APPENDIX 7'!E14/'APPENDIX 7'!E$30)*100,0) -> 7.6201984 | F14: =IFERROR(('APPENDIX 7'!F14/'APPENDIX 7'!F$30)*100,0) -> 12.506885 | G14: =IFERROR(('APPENDIX 7'!G14/'APPENDIX 7'!G$30)*100,0) -> 0.38046198 | H14: =IFERROR(('APPENDIX 7'!H14/'APPENDIX 7'!H$30)*100,0) -> 0.016791846 | I14: =IFERROR(('APPENDIX 7'!I14/'APPENDIX 7'!I$30)*100,0) -> 0 | J14: =IFERROR(('APPENDIX 7'!J14/'APPENDIX 7'!J$30)*100,0) -> 0 | K14: =IFERROR(('APPENDIX 7'!K14/'APPENDIX 7'!K$30)*100,0) -> 5.5292798 | L14: =RANK(K14,$K$6:$K$29) -> 7
B15: ='APPENDIX 9'!B15 -> GEMINIA LIFE INSURANCE COMPANY | C15: =IFERROR(('APPENDIX 7'!C15/'APPENDIX 7'!C$30)*100,0) -> 0.19449877 | D15: =IFERROR(('APPENDIX 7'!D15/'APPENDIX 7'!D$30)*100,0) -> 0 | E15: =IFERROR(('APPENDIX 7'!E15/'APPENDIX 7'!E$30)*100,0) -> 0.4249787 | F15: =IFERROR(('APPENDIX 7'!F15/'APPENDIX 7'!F$30)*100,0) -> 0.82007637 | G15: =IFERROR(('APPENDIX 7'!G15/'APPENDIX 7'!G$30)*100,0) -> 0.99005748 | H15: =IFERROR(('APPENDIX 7'!H15/'APPENDIX 7'!H$30)*100,0) -> 2.8374865 | I15: =IFERROR(('APPENDIX 7'!I15/'APPENDIX 7'!I$30)*100,0) -> 0 | J15: =IFERROR(('APPENDIX 7'!J15/'APPENDIX 7'!J$30)*100,0) -> 1.8945808 | K15: =IFERROR(('APPENDIX 7'!K15/'APPENDIX 7'!K$30)*100,0) -> 0.91296999 | L15: =RANK(K15,$K$6:$K$29) -> 16
B16: ='APPENDIX 9'!B16 -> ICEA LION LIFE ASSURANCE | C16: =IFERROR(('APPENDIX 7'!C16/'APPENDIX 7'!C$30)*100,0) -> 21.216238 | D16: =IFERROR(('APPENDIX 7'!D16/'APPENDIX 7'!D$30)*100,0) -> 17.111887 | E16: =IFERROR(('APPENDIX 7'!E16/'APPENDIX 7'!E$30)*100,0) -> 35.32886 | F16: =IFERROR(('APPENDIX 7'!F16/'APPENDIX 7'!F$30)*100,0) -> 13.513176 | G16: =IFERROR(('APPENDIX 7'!G16/'APPENDIX 7'!G$30)*100,0) -> 2.5519326 | H16: =IFERROR(('APPENDIX 7'!H16/'APPENDIX 7'!H$30)*100,0) -> 1.9732834 | I16: =IFERROR(('APPENDIX 7'!I16/'APPENDIX 7'!I$30)*100,0) -> 0 | J16: =IFERROR(('APPENDIX 7'!J16/'APPENDIX 7'!J$30)*100,0) -> 0.016603154 | K16: =IFERROR(('APPENDIX 7'!K16/'APPENDIX 7'!K$30)*100,0) -> 13.940687 | L16: =RANK(K16,$K$6:$K$29) -> 2
B17: ='APPENDIX 9'!B17 -> JUBILEE LIFE INSURANCE | C17: =IFERROR(('APPENDIX 7'!C17/'APPENDIX 7'!C$30)*100,0) -> 9.980543 | D17: =IFERROR(('APPENDIX 7'!D17/'APPENDIX 7'!D$30)*100,0) -> 12.161887 | E17: =IFERROR(('APPENDIX 7'!E17/'APPENDIX 7'!E$30)*100,0) -> 14.004137 | F17: =IFERROR(('APPENDIX 7'!F17/'APPENDIX 7'!F$30)*100,0) -> 20.913637 | G17: =IFERROR(('APPENDIX 7'!G17/'APPENDIX 7'!G$30)*100,0) -> 5.2577344 | H17: =IFERROR(('APPENDIX 7'!H17/'APPENDIX 7'!H$30)*100,0) -> 1.3974249 | I17: =IFERROR(('APPENDIX 7'!I17/'APPENDIX 7'!I$30)*100,0) -> 0 | J17: =IFERROR(('APPENDIX 7'!J17/'APPENDIX 7'!J$30)*100,0) -> 8.9463226 | K17: =IFERROR(('APPENDIX 7'!K17/'APPENDIX 7'!K$30)*100,0) -> 13.02307 | L17: =RANK(K17,$K$6:$K$29) -> 3
B18: ='APPENDIX 9'!B18 -> KENINDIA ASSURANCE COMPANY | C18: =IFERROR(('APPENDIX 7'!C18/'APPENDIX 7'!C$30)*100,0) -> 4.8079408 | D18: =IFERROR(('APPENDIX 7'!D18/'APPENDIX 7'!D$30)*100,0) -> 3.4057505 | E18: =IFERROR(('APPENDIX 7'!E18/'APPENDIX 7'!E$30)*100,0) -> 5.5220606 | F18: =IFERROR(('APPENDIX 7'!F18/'APPENDIX 7'!F$30)*100,0) -> 17.516568 | G18: =IFERROR(('APPENDIX 7'!G18/'APPENDIX 7'!G$30)*100,0) -> 0.45074682 | H18: =IFERROR(('APPENDIX 7'!H18/'APPENDIX 7'!H$30)*100,0) -> 0.026816982 | I18: =IFERROR(('APPENDIX 7'!I18/'APPENDIX 7'!I$30)*100,0) -> 0 | J18: =IFERROR(('APPENDIX 7'!J18/'APPENDIX 7'!J$30)*100,0) -> 0 | K18: =IFERROR(('APPENDIX 7'!K18/'APPENDIX 7'!K$30)*100,0) -> 7.7190681 | L18: =RANK(K18,$K$6:$K$29) -> 4
... B29: ='APPENDIX 9'!B29 -> THE MONARCH INSURANCE | C29: =IFERROR(('APPENDIX 7'!C29/'APPENDIX 7'!C$30)*100,0) -> 0 | D29: =IFERROR(('APPENDIX 7'!D29/'APPENDIX 7'!D$30)*100,0) -> 0 | E29: =IFERROR(('APPENDIX 7'!E29/'APPENDIX 7'!E$30)*100,0) -> 0 | F29: =IFERROR(('APPENDIX 7'!F29/'APPENDIX 7'!F$30)*100,0) -> 0 | G29: =IFERROR(('APPENDIX 7'!G29/'APPENDIX 7'!G$30)*100,0) -> 0 | H29: =IFERROR(('APPENDIX 7'!H29/'APPENDIX 7'!H$30)*100,0) -> 0 | I29: =IFERROR(('APPENDIX 7'!I29/'APPENDIX 7'!I$30)*100,0) -> 0 | J29: =IFERROR(('APPENDIX 7'!J29/'APPENDIX 7'!J$30)*100,0) -> 0 | K29: =IFERROR(('APPENDIX 7'!K29/'APPENDIX 7'!K$30)*100,0) -> 0 | L29: =RANK(K29,$K$6:$K$29) -> 23
B30: TOTAL | C30: =SUM(C6:C29) -> 100 | D30: =SUM(D6:D29) -> 100 | E30: =SUM(E6:E29) -> 100 | F30: =SUM(F6:F29) -> 100 | G30: =SUM(G6:G29) -> 100 | H30: =SUM(H6:H29) -> 100 | I30: =SUM(I6:I29) -> 0 | J30: =SUM(J6:J29) -> 100 | K30: =SUM(K6:K29) -> 100
B31: REINSURERS
B32: ='APPENDIX 9'!B32 -> CONTINENTAL REINSURANCE | C32: =IFERROR(('APPENDIX 7'!C32/'APPENDIX 7'!C$35)*100,0) -> 0 | D32: =IFERROR(('APPENDIX 7'!D32/'APPENDIX 7'!D$35)*100,0) -> 0 | E32: =IFERROR(('APPENDIX 7'!E32/'APPENDIX 7'!E$35)*100,0) -> 0 | F32: =IFERROR(('APPENDIX 7'!F32/'APPENDIX 7'!F$35)*100,0) -> 0 | G32: =IFERROR(('APPENDIX 7'!G32/'APPENDIX 7'!G$35)*100,0) -> 0.90457019 | H32: =IFERROR(('APPENDIX 7'!H32/'APPENDIX 7'!H$35)*100,0) -> 0 | I32: =IFERROR(('APPENDIX 7'!I32/'APPENDIX 7'!I$35)*100,0) -> 0 | J32: =IFERROR(('APPENDIX 7'!J32/'APPENDIX 7'!J$35)*100,0) -> 0 | K32: =IFERROR(('APPENDIX 7'!K32/'APPENDIX 7'!K$35)*100,0) -> 0.85050544
B33: ='APPENDIX 9'!B33 -> EAST AFRICA REINSURANCE | C33: =IFERROR(('APPENDIX 7'!C33/'APPENDIX 7'!C$35)*100,0) -> 55.988043 | D33: =IFERROR(('APPENDIX 7'!D33/'APPENDIX 7'!D$35)*100,0) -> 0 | E33: =IFERROR(('APPENDIX 7'!E33/'APPENDIX 7'!E$35)*100,0) -> 0 | F33: =IFERROR(('APPENDIX 7'!F33/'APPENDIX 7'!F$35)*100,0) -> 0 | G33: =IFERROR(('APPENDIX 7'!G33/'APPENDIX 7'!G$35)*100,0) -> 29.748674 | H33: =IFERROR(('APPENDIX 7'!H33/'APPENDIX 7'!H$35)*100,0) -> 0 | I33: =IFERROR(('APPENDIX 7'!I33/'APPENDIX 7'!I$35)*100,0) -> 0 | J33: =IFERROR(('APPENDIX 7'!J33/'APPENDIX 7'!J$35)*100,0) -> 0 | K33: =IFERROR(('APPENDIX 7'!K33/'APPENDIX 7'!K$35)*100,0) -> 31.31696
B34: ='APPENDIX 9'!B34 -> KENYA REINSURANCE CORPORATION | C34: =IFERROR(('APPENDIX 7'!C34/'APPENDIX 7'!C$35)*100,0) -> 44.011957 | D34: =IFERROR(('APPENDIX 7'!D34/'APPENDIX 7'!D$35)*100,0) -> 0 | E34: =IFERROR(('APPENDIX 7'!E34/'APPENDIX 7'!E$35)*100,0) -> 0 | F34: =IFERROR(('APPENDIX 7'!F34/'APPENDIX 7'!F$35)*100,0) -> 0 | G34: =IFERROR(('APPENDIX 7'!G34/'APPENDIX 7'!G$35)*100,0) -> 69.346756 | H34: =IFERROR(('APPENDIX 7'!H34/'APPENDIX 7'!H$35)*100,0) -> 0 | I34: =IFERROR(('APPENDIX 7'!I34/'APPENDIX 7'!I$35)*100,0) -> 0 | J34: =IFERROR(('APPENDIX 7'!J34/'APPENDIX 7'!J$35)*100,0) -> 0 | K34: =IFERROR(('APPENDIX 7'!K34/'APPENDIX 7'!K$35)*100,0) -> 67.832535
B35: TOTAL | C35: =SUM(C32:C34) -> 100 | D35: =SUM(D32:D34) -> 0 | E35: =SUM(E32:E34) -> 0 | F35: =SUM(F32:F34) -> 0 | G35: =SUM(G32:G34) -> 100 | H35: =SUM(H32:H34) -> 0 | I35: =SUM(I32:I34) -> 0 | J35: =SUM(J32:J34) -> 0 | K35: =SUM(K32:K34) -> 100
B36: Figures in %

Sheet APPENDIX 9
B3: =_xlfn.CONCAT('Table of Contents'!B21,": ",'Table of Contents'!C21) -> APPENDIX 9: SUMMARY OF LIFE ASSURANCE BUSINESS REVENUE ACCOUNTS FOR THE PERIOD ENDED 31.12.2025
B4: Company | C4: Life Fund BF | D4: Gross Premium | E4: Net Premium | F4: Other (Fee) Income | G4: Total Benefits | H4: Claims | I4: Surrenders_x000D_ | J4: Bonuses Paid | K4: Annuities Paid | L4: Net Commisions | M4: Expense of Management | N4: Investment Income | O4: Investment Expenses | P4: Transfer To (From) P & L | Q4: Life Fund CF
B5: INSURERS
B6: ABSA LIFE ASSURANCE | C6: 10636609 | D6: 6316275.5 | E6: 6238099.6 | F6: 0 | G6: 2290872.2 | H6: 2290872.2 | I6: 0 | J6: 0 | K6: 0 | L6: 784984.08 | M6: 521940.12 | N6: 2102631.4 | O6: 0 | P6: 0 | Q6: 15379544
B7: APA LIFE ASSURANCE COMPANY | C7: 995078.63 | D7: 610629.03 | E7: 599484.74 | F7: 0 | G7: 175246.71 | H7: 175246.71 | I7: 0 | J7: 0 | K7: 0 | L7: 288715.23 | M7: 184006.1 | N7: 277742.28 | O7: 4488.5889 | P7: 0 | Q7: 1219849
B8: BRITAM LIFE ASSURANCE | C8: 43886184 | D8: 11532887 | E8: 11526531 | F8: -2600.6927 | G8: 7672047.8 | H8: 7672047.8 | I8: 0 | J8: 0 | K8: 0 | L8: 1628360.4 | M8: 2580260.6 | N8: 6950383.1 | O8: 259045.85 | P8: 0 | Q8: 50220782
B9: CANNON LIFE ASSURANCE (K) LIMITED | C9: 527806.79 | D9: 21594.655 | E9: 21594.655 | F9: 0 | G9: 99360.285 | H9: 99360.285 | I9: 0 | J9: 0 | K9: 0 | L9: -3381.1424 | M9: 58476.157 | N9: 28366.919 | O9: 0 | P9: 0 | Q9: 423313.06
B10: CAPEX LIFE ASSURANCE COMPANY | C10: 33226.715 | D10: 6056.3897 | E10: 6056.3897 | F10: 0 | G10: 6202.9194 | H10: 6202.9194 | I10: 0 | J10: 0 | K10: 0 | L10: 417.9822 | M10: 1775.1315 | N10: 163.99522 | O10: 0 | P10: 0 | Q10: 31051.067
B11: CIC LIFE ASSURANCE COMPANY | C11: 5139412.2 | D11: 1409614.1 | E11: 1405875.8 | F11: 0 | G11: 413420.54 | H11: 413420.54 | I11: 0 | J11: 0 | K11: 0 | L11: 186747.82 | M11: 449649.45 | N11: 541136.39 | O11: 0 | P11: 0 | Q11: 6036606.6
B12: CORPORATE INSURANCE COMPANY | C12: 63014.581 | D12: 34017.644 | E12: 34017.644 | F12: 0 | G12: 141310.88 | H12: 141310.88 | I12: 0 | J12: 0 | K12: 0 | L12: 0 | M12: 6585.4459 | N12: 8082.879 | O12: 0 | P12: 0 | Q12: -42781.22
B13: EQUITY LIFE ASSURANCE | C13: 0 | D13: 0 | E13: 0 | F13: 0 | G13: 0 | H13: 0 | I13: 0 | J13: 0 | K13: 0 | L13: 0 | M13: 0 | N13: 0 | O13: 0 | P13: 0 | Q13: 0
B14: GA LIFE ASSURANCE COMPANY | C14: 4094574 | D14: 1053351.9 | E14: 1053351.9 | F14: 0 | G14: 159315.02 | H14: 159315.02 | I14: 0 | J14: 0 | K14: 0 | L14: 19607.077 | M14: 405.029 | N14: 1012255 | O14: 0 | P14: 0 | Q14: 5980853.7
B15: GEMINIA LIFE INSURANCE COMPANY | C15: 423624.61 | D15: 90055.417 | E15: 90055.417 | F15: 0 | G15: 27136.296 | H15: 27136.296 | I15: 0 | J15: 0 | K15: 0 | L15: 12898.216 | M15: 31073.642 | N15: 6146.895 | O15: 0 | P15: 0 | Q15: 448718.77
B16: ICEA LION LIFE ASSURANCE | C16: 22398339 | D16: 9823389.5 | E16: 9783009.4 | F16: 0 | G16: 3626211.8 | H16: 2859859.5 | I16: 766352.24 | J16: 0 | K16: 0 | L16: 1514102 | M16: 1487257 | N16: 3740671.1 | O16: 0 | P16: 277853.72 | Q16: 29016595
B17: JUBILEE LIFE INSURANCE | C17: 13470539 | D17: 4621119 | E17: 4603359.5 | F17: 0 | G17: 4669755.6 | H17: 4669755.6 | I17: 0 | J17: 0 | K17: 0 | L17: 871861.73 | M17: 889158.39 | N17: 2193365 | O17: 15617.62 | P17: 0 | Q17: 13820871
... B29: THE MONARCH INSURANCE | C29: 0 | D29: 0 | E29: 0 | F29: 0 | G29: 0 | H29: 0 | I29: 0 | J29: 0 | K29: 0 | L29: 0 | M29: 0 | N29: 0 | O29: 0 | P29: 0 | Q29: 0
B30: TOTAL | C30: =SUM(C6:C29) -> 1.4732514e+08 | D30: =SUM(D6:D29) -> 46301279 | E30: =SUM(E6:E29) -> 45776089 | F30: =SUM(F6:F29) -> 54654.967 | G30: =SUM(G6:G29) -> 26792427 | H30: =SUM(H6:H29) -> 25558248 | I30: =SUM(I6:I29) -> 1234178.5 | J30: =SUM(J6:J29) -> 0 | ... Q30: =SUM(Q6:Q29) -> 1.7054623e+08
B31: REINSURERS
B32: CONTINENTAL REINSURANCE | C32: 0 | D32: 0 | E32: 0 | F32: 0 | G32: 0 | H32: 0 | I32: 0 | J32: 0 | K32: 0 | L32: 0 | M32: 0 | N32: 0 | O32: 0 | P32: 0 | Q32: 0
B33: EAST AFRICA REINSURANCE | C33: 139860.33 | D33: 142636.88 | E33: 126991.55 | F33: 0 | G33: -2871.8562 | H33: -2871.8562 | I33: 0 | J33: 0 | K33: 0 | L33: 27678.137 | M33: 19147.605 | N33: 27301.744 | O33: 1172.5072 | P33: 0 | Q33: 249027.24
B34: KENYA REINSURANCE CORPORATION | C34: 430383.33 | D34: 112126.23 | E34: 115048.51 | F34: 0 | G34: 5624.5643 | H34: 5624.5643 | I34: 0 | J34: 0 | K34: 0 | L34: 47484.245 | M34: 10269.113 | N34: 10269.113 | O34: 0 | P34: 0 | Q34: 492323.03
B35: TOTAL | C35: =SUM(C32:C34) -> 570243.66 | D35: =SUM(D32:D34) -> 254763.1 | E35: =SUM(E32:E34) -> 242040.06 | F35: =SUM(F32:F34) -> 0 | G35: =SUM(G32:G34) -> 2752.7081 | H35: =SUM(H32:H34) -> 2752.7081 | I35: =SUM(I32:I34) -> 0 | J35: =SUM(J32:J34) -> 0 | ... Q35: =SUM(Q32:Q34) -> 741350.26
B36: Amounts in Thousand Shillings

Sheet APPENDIX 10
B3: =_xlfn.CONCAT('Table of Contents'!B22,": ",'Table of Contents'!C22) -> APPENDIX 10: SUMMARY OF ANNUITIES BUSINESS REVENUE ACCOUNTS FOR THE PERIOD ENDED 31.12.2025
B4: Company | C4: Life Fund BF | D4: Gross Premium | E4: Net Premium | F4: Other (Fee) Income | G4: Total Benefits | H4: Claims | I4: Surrenders_x000D_ | J4: Bonuses Paid | K4: Annuities Paid | L4: Net Commisions | M4: Expense of Management | N4: Investment Income | O4: Investment Expenses | P4: Transfer To (From) P & L | Q4: Life Fund CF
B5: INSURERS
B6: ABSA LIFE ASSURANCE | C6: 0 | D6: 0 | E6: 0 | F6: 0 | G6: 0 | H6: 0 | I6: 0 | J6: 0 | K6: 0 | L6: 0 | M6: 0 | N6: 0 | O6: 0 | P6: 0 | Q6: 0
B7: APA LIFE ASSURANCE COMPANY | C7: 1015040.1 | D7: 23589.961 | E7: 23589.961 | F7: 0 | G7: 123098.82 | H7: 123098.82 | I7: 0 | J7: 0 | K7: 0 | L7: 0 | M7: 10184.819 | N7: 141073.04 | O7: 6370.3468 | P7: 0 | Q7: 1040049.1
B8: BRITAM LIFE ASSURANCE | C8: 24059616 | D8: 7464031 | E8: 7464031 | F8: 0 | G8: 3491782.9 | H8: 3491782.9 | I8: 0 | J8: 0 | K8: 0 | L8: 145992.17 | M8: 111398.51 | N8: 6045212.5 | O8: 62040.51 | P8: 0 | Q8: 33757646
B9: CANNON LIFE ASSURANCE (K) LIMITED | C9: 11532.723 | D9: 0 | E9: -193.954 | F9: 0 | G9: 1309.509 | H9: 1309.509 | I9: 0 | J9: 0 | K9: 0 | L9: 0 | M9: 0 | N9: 0 | O9: 0 | P9: 0 | Q9: 10029.26
B10: CAPEX LIFE ASSURANCE COMPANY | C10: 862965.63 | D10: 249593.05 | E10: 249593.05 | F10: 0 | G10: 447169.72 | H10: 447169.72 | I10: 0 | J10: 0 | K10: 0 | L10: 11513.784 | M10: 39769.913 | N10: 6758.4957 | O10: 0 | P10: 0 | Q10: 620863.75
B11: CIC LIFE ASSURANCE COMPANY | C11: 1829277.5 | D11: 1214105.3 | E11: 1214105.3 | F11: 0 | G11: 0 | H11: 0 | I11: 0 | J11: 0 | K11: 0 | L11: 23946.171 | M11: 42216.703 | N11: 305187.8 | O11: 0 | P11: 0 | Q11: 3282407.8
B12: CORPORATE INSURANCE COMPANY | C12: 0 | D12: 0 | E12: 0 | F12: 0 | G12: 0 | H12: 0 | I12: 0 | J12: 0 | K12: 0 | L12: 0 | M12: 0 | N12: 0 | O12: 0 | P12: 0 | Q12: 0
B13: EQUITY LIFE ASSURANCE | C13: 0 | D13: 0 | E13: 0 | F13: 0 | G13: 0 | H13: 0 | I13: 0 | J13: 0 | K13: 0 | L13: 0 | M13: 0 | N13: 0 | O13: 0 | P13: 0 | Q13: 0
B14: GA LIFE ASSURANCE COMPANY | C14: 0 | D14: 0 | E14: 0 | F14: 0 | G14: 0 | H14: 0 | I14: 0 | J14: 0 | K14: 0 | L14: 0 | M14: 0 | N14: 0 | O14: 0 | P14: 0 | Q14: 0
B15: GEMINIA LIFE INSURANCE COMPANY | C15: 0 | D15: 0 | E15: 0 | F15: 0 | G15: 0 | H15: 0 | I15: 0 | J15: 0 | K15: 0 | L15: 0 | M15: 0 | N15: 0 | O15: 0 | P15: 0 | Q15: 0
B16: ICEA LION LIFE ASSURANCE | C16: 22651302 | D16: 2481013.5 | E16: 2481013.5 | F16: 0 | G16: 2660721.1 | H16: 65296.204 | I16: 0 | J16: 0 | K16: 2595424.9 | L16: 54094.668 | M16: 48868.46 | N16: 4977961.2 | O16: 0 | P16: 522000 | Q16: 26824592
B17: JUBILEE LIFE INSURANCE | C17: 12854457 | D17: 1763324.3 | E17: 1763324.3 | F17: 0 | G17: 1751628.7 | H17: 1751628.7 | I17: 0 | J17: 0 | K17: 0 | L17: 32594.654 | M17: 28066.869 | N17: 2099905.7 | O17: 13684.433 | P17: 0 | Q17: 14891712
... B29: THE MONARCH INSURANCE | C29: 0 | D29: 0 | E29: 0 | F29: 0 | G29: 0 | H29: 0 | I29: 0 | J29: 0 | K29: 0 | L29: 0 | M29: 0 | N29: 0 | O29: 0 | P29: 0 | Q29: 0
B30: TOTAL | C30: =SUM(C6:C29) -> 95611112 | D30: =SUM(D6:D29) -> 14498772 | E30: =SUM(E6:E29) -> 14498578 | F30: =SUM(F6:F29) -> 0 | G30: =SUM(G6:G29) -> 12609989 | H30: =SUM(H6:H29) -> 9989291.1 | I30: =SUM(I6:I29) -> 0 | J30: =SUM(J6:J29) -> 0 | ... Q30: =SUM(Q6:Q29) -> 1.1487285e+08
B31: REINSURERS
B32: CONTINENTAL REINSURANCE | C32: 0 | D32: 0 | E32: 0 | F32: 0 | G32: 0 | H32: 0 | I32: 0 | J32: 0 | K32: 0 | L32: 0 | M32: 0 | N32: 0 | O32: 0 | P32: 0 | Q32: 0
B33: EAST AFRICA REINSURANCE | C33: 0 | D33: 0 | E33: 0 | F33: 0 | G33: 0 | H33: 0 | I33: 0 | J33: 0 | K33: 0 | L33: 0 | M33: 0 | N33: 0 | O33: 0 | P33: 0 | Q33: 0
B34: KENYA REINSURANCE CORPORATION | C34: 0 | D34: 0 | E34: 0 | F34: 0 | G34: 0 | H34: 0 | I34: 0 | J34: 0 | K34: 0 | L34: 0 | M34: 0 | N34: 0 | O34: 0 | P34: 0 | Q34: 0
B35: TOTAL | C35: =SUM(C32:C34) -> 0 | D35: =SUM(D32:D34) -> 0 | E35: =SUM(E32:E34) -> 0 | F35: =SUM(F32:F34) -> 0 | G35: =SUM(G32:G34) -> 0 | H35: =SUM(H32:H34) -> 0 | I35: =SUM(I32:I34) -> 0 | J35: =SUM(J32:J34) -> 0 | ... Q35: =SUM(Q32:Q34) -> 0
B36: Amounts in Thousand Shillings

Sheet APPENDIX 11
B3: =_xlfn.CONCAT('Table of Contents'!B23,": ",'Table of Contents'!C23) -> APPENDIX 11: SUMMARY OF GROUP LIFE BUSINESS REVENUE ACCOUNTS FOR THE PERIOD ENDED 31.12.2025
B4: Company | C4: Life Fund BF | D4: Gross Premium | E4: Net Premium | F4: Other (Fee) Income | G4: Total Benefits | H4: Claims | I4: Surrenders_x000D_ | J4: Bonuses Paid | K4: Annuities Paid | L4: Net Commisions | M4: Expense of Management | N4: Investment Income | O4: Investment Expenses | P4: Transfer To (From) P & L | Q4: Life Fund CF
B5: INSURERS
B6: ABSA LIFE ASSURANCE | C6: 454028.71 | D6: 2567980.5 | E6: 1300924 | F6: 0 | G6: 976714.07 | H6: 976714.07 | I6: 0 | J6: 0 | K6: 0 | L6: 101705.52 | M6: 361370.96 | N6: 47817.389 | O6: 0 | P6: 0 | Q6: 362979.59
B7: APA LIFE ASSURANCE COMPANY | C7: 639163.48 | D7: 1831004.8 | E7: 515434.93 | F7: 0 | G7: 463202.84 | H7: 463202.84 | I7: 0 | J7: 0 | K7: 0 | L7: -69127.941 | M7: 257303.62 | N7: 112762.15 | O7: 5290.3331 | P7: 0 | Q7: 610691.71
B8: BRITAM LIFE ASSURANCE | C8: 2772767 | D8: 5227073 | E8: 846407.13 | F8: 0 | G8: 455688.17 | H8: 455688.17 | I8: 0 | J8: 0 | K8: 0 | L8: -200405.03 | M8: 444404.18 | N8: 502571.2 | O8: -1416.816 | P8: 0 | Q8: 3423474.8
B9: CANNON LIFE ASSURANCE (K) LIMITED | C9: 168205.61 | D9: 504610.99 | E9: 336443.91 | F9: 0 | G9: 170670 | H9: 170670 | I9: 0 | J9: 0 | K9: 0 | L9: 27060.511 | M9: 16416.688 | N9: 7963.774 | O9: 0 | P9: 0 | Q9: 298466.1
B10: CAPEX LIFE ASSURANCE COMPANY | C10: 335333.11 | D10: 948991.07 | E10: 812626.48 | F10: 0 | G10: 353780.57 | H10: 353780.57 | I10: 0 | J10: 0 | K10: 0 | L10: 134425.63 | M10: 311292.44 | N10: 25674.339 | O10: 0 | P10: 0 | Q10: 374135.29
B11: CIC LIFE ASSURANCE COMPANY | C11: 1654152.2 | D11: 824232.39 | E11: 668255.47 | F11: 0 | G11: 256476.01 | H11: 256476.01 | I11: 0 | J11: 0 | K11: 0 | L11: -45830.557 | M11: 181285.2 | N11: 2067352.5 | O11: 0 | P11: 0 | Q11: 3997829.5
B12: CORPORATE INSURANCE COMPANY | C12: 0 | D12: 0 | E12: 0 | F12: 0 | G12: 0.00048 | H12: 0.00048 | I12: 0 | J12: 0 | K12: 0 | L12: 0 | M12: 0 | N12: 0 | O12: 0 | P12: 0 | Q12: -0.00048
B13: EQUITY LIFE ASSURANCE | C13: 587628.71 | D13: 646193.82 | E13: 254659.51 | F13: 0 | G13: 135106.14 | H13: 135106.14 | I13: 0 | J13: 0 | K13: 0 | L13: -68002.649 | M13: 60617.082 | N13: 370113.4 | O13: 0 | P13: 0 | Q13: 1084681
B14: GA LIFE ASSURANCE COMPANY | C14: 27060.958 | D14: 81952.477 | E14: 4702.087 | F14: 0 | G14: 1433.171 | H14: 1433.171 | I14: 0 | J14: 0 | K14: 0 | L14: -39176.131 | M14: 19379.787 | N14: 5506.83 | O14: 0 | P14: 0 | Q14: 55633.048
B15: GEMINIA LIFE INSURANCE COMPANY | C15: 1007272.1 | D15: 213260.89 | E15: 118554.6 | F15: 0 | G15: 381240.48 | H15: 381240.48 | I15: 0 | J15: 0 | K15: 0 | L15: 6365.7415 | M15: 45142.381 | N15: 0 | O15: 0 | P15: 0 | Q15: 693078.14
B16: ICEA LION LIFE ASSURANCE | C16: 433367.02 | D16: 549692.75 | E16: 331465.98 | F16: 0 | G16: 231533.5 | H16: 231533.5 | I16: 0 | J16: 0 | K16: 0 | L16: -25577.849 | M16: 165653.25 | N16: 59848.925 | O16: 0 | P16: 43500 | Q16: 409573.01
B17: JUBILEE LIFE INSURANCE | C17: 474616.36 | D17: 1132529.3 | E17: 587072.77 | F17: 0 | G17: 374335.95 | H17: 374335.95 | I17: 0 | J17: 0 | K17: 0 | L17: -27931.036 | M17: 202591.44 | N17: 173978.64 | O17: 1316.0629 | P17: 0 | Q17: 685355.34
... B29: THE MONARCH INSURANCE | C29: 0 | D29: 0 | E29: 0 | F29: 0 | G29: 0 | H29: 0 | I29: 0 | J29: 0 | K29: 0 | L29: 0 | M29: 0 | N29: 0 | O29: 0 | P29: 0 | Q29: 0
B30: TOTAL | C30: =SUM(C6:C29) -> 15104037 | D30: =SUM(D6:D29) -> 21540254 | E30: =SUM(E6:E29) -> 10883801 | F30: =SUM(F6:F29) -> -153728.45 | G30: =SUM(G6:G29) -> 7129353 | H30: =SUM(H6:H29) -> 7129353 | I30: =SUM(I6:I29) -> 0 | J30: =SUM(J6:J29) -> 0 | ... Q30: =SUM(Q6:Q29) -> 18303030
B31: REINSURERS
B32: CONTINENTAL REINSURANCE | C32: 0 | D32: 36252.815 | E32: 30895.605 | F32: 0 | G32: 85203.153 | H32: 85203.153 | I32: 0 | J32: 0 | K32: 0 | L32: 8823.21 | M32: 4183.395 | N32: 68066.016 | O32: 0 | P32: 0 | Q32: 751.863
B33: EAST AFRICA REINSURANCE | C33: 1039475.6 | D33: 1192249.3 | E33: 930399.6 | F33: 0 | G33: 479382.19 | H33: 479382.19 | I33: 0 | J33: 0 | K33: 0 | L33: 236045.66 | M33: 168646.55 | N33: 240465.85 | O33: 10327.103 | P33: 0 | Q33: 1315939.5
B34: KENYA REINSURANCE CORPORATION | C34: 7951511.7 | D34: 2779237.2 | E34: 2646652.5 | F34: 0 | G34: 1701404.7 | H34: 1701404.7 | I34: 0 | J34: 0 | K34: 0 | L34: 941916.27 | M34: 92422.014 | N34: 92422.013 | O34: 0 | P34: 0 | Q34: 7954843.2
B35: TOTAL | C35: =SUM(C32:C34) -> 8990987.3 | D35: =SUM(D32:D34) -> 4007739.3 | E35: =SUM(E32:E34) -> 3607947.7 | F35: =SUM(F32:F34) -> 0 | G35: =SUM(G32:G34) -> 2265990.1 | H35: =SUM(H32:H34) -> 2265990.1 | I35: =SUM(I32:I34) -> 0 | J35: =SUM(J32:J34) -> 0 | ... Q35: =SUM(Q32:Q34) -> 9271534.6
B36: Amounts in Thousand Shillings

Sheet APPENDIX 12
B3: =_xlfn.CONCAT('Table of Contents'!B24,": ",'Table of Contents'!C24) -> APPENDIX 12: SUMMARY OF GROUP CREDIT BUSINESS REVENUE ACCOUNTS FOR THE PERIOD ENDED 31.12.2025
B4: Company | C4: Life Fund BF | D4: Gross Premium | E4: Net Premium | F4: Other (Fee) Income | G4: Total Benefits | H4: Claims | I4: Surrenders_x000D_ | J4: Bonuses Paid | K4: Annuities Paid | L4: Net Commisions | M4: Expense of Management | N4: Investment Income | O4: Investment Expenses | P4: Transfer To (From) P & L | Q4: Life Fund CF
B5: INSURERS
B6: ABSA LIFE ASSURANCE | C6: 1902798.6 | D6: 1143702.6 | E6: 1003148.7 | F6: 0 | G6: 340541.25 | H6: 340541.25 | I6: 0 | J6: 0 | K6: 0 | L6: 429096.74 | M6: 321258.78 | N6: 208424.68 | O6: 0 | P6: 0 | Q6: 2023475.2
B7: APA LIFE ASSURANCE COMPANY | C7: 1019232.3 | D7: 1315454.1 | E7: 900070.89 | F7: 0 | G7: 650279.69 | H7: 650279.69 | I7: 0 | J7: 0 | K7: 0 | L7: 350756.44 | M7: 11073.691 | N7: 52503.258 | O7: 2463.2355 | P7: 0 | Q7: 957233.39
B8: BRITAM LIFE ASSURANCE | C8: -415879.34 | D8: 432715.57 | E8: 406522.77 | F8: 0 | G8: 163687.05 | H8: 163687.05 | I8: 0 | J8: 0 | K8: 0 | L8: 33747.773 | M8: 246882.5 | N8: 244456.49 | O8: 3976.222 | P8: 0 | Q8: -213193.61
B9: CANNON LIFE ASSURANCE (K) LIMITED | C9: -4966.8409 | D9: 14341.352 | E9: 13515.665 | F9: 0 | G9: 2700.357 | H9: 2700.357 | I9: 0 | J9: 0 | K9: 0 | L9: 987.95746 | M9: 0 | N9: 0 | O9: 0 | P9: 0 | Q9: 4860.5099
B10: CAPEX LIFE ASSURANCE COMPANY | C10: 28980.046 | D10: 111804.07 | E10: 101263.99 | F10: 0 | G10: 37875.389 | H10: 37875.389 | I10: 0 | J10: 0 | K10: 0 | L10: 17500.262 | M10: 32769.856 | N10: 3027.4374 | O10: 0 | P10: 0 | Q10: 45125.967
B11: CIC LIFE ASSURANCE COMPANY | C11: 6623757.7 | D11: 6467982.3 | E11: 6414520.7 | F11: 0 | G11: 1566580.3 | H11: 1566580.3 | I11: 0 | J11: 0 | K11: 0 | L11: 567045.57 | M11: 1392299.7 | N11: 0 | O11: 0 | P11: 0 | Q11: 9512352.8
B12: CORPORATE INSURANCE COMPANY | C12: 0 | D12: 0 | E12: 0 | F12: 0 | G12: 0 | H12: 0 | I12: 0 | J12: 0 | K12: 0 | L12: 0 | M12: 0 | N12: 0 | O12: 0 | P12: 0 | Q12: 0
B13: EQUITY LIFE ASSURANCE | C13: 6283361 | D13: 2338846.6 | E13: 2422334.6 | F13: 0 | G13: 281660.49 | H13: 281660.49 | I13: 0 | J13: 0 | K13: 0 | L13: 240988.38 | M13: 605946.98 | N13: 837097.3 | O13: 0 | P13: 0 | Q13: 8414197.1
B14: GA LIFE ASSURANCE COMPANY | C14: 1843.319 | D14: 3027.538 | E14: 169.59797 | F14: 0 | G14: 175.35 | H14: 175.35 | I14: 0 | J14: 0 | K14: 0 | L14: -663.574 | M14: 709.86761 | N14: 201.711 | O14: 0 | P14: 0 | Q14: 1992.9844
B15: GEMINIA LIFE INSURANCE COMPANY | C15: 384576.65 | D15: 511593.44 | E15: 474821.08 | F15: 0 | G15: 48705.588 | H15: 48705.588 | I15: 0 | J15: 0 | K15: 0 | L15: 48131.71 | M15: 147295.56 | N15: 0 | O15: 0 | P15: 0 | Q15: 615264.88
B16: ICEA LION LIFE ASSURANCE | C16: 125908.65 | D16: 355779.25 | E16: 280287.41 | F16: 0 | G16: 162453.52 | H16: 162453.52 | I16: 0 | J16: 0 | K16: 0 | L16: 10450.202 | M16: 138268.96 | N16: 28027.801 | O16: 0 | P16: 26100 | Q16: 96951.186
B17: JUBILEE LIFE INSURANCE | C17: 304867.38 | D17: 251953.05 | E17: 228090.95 | F17: 0 | G17: 50820.536 | H17: 50820.536 | I17: 0 | J17: 0 | K17: 0 | L17: 38922.595 | M17: 45598.782 | N17: 40478.395 | O17: 290.6912 | P17: 0 | Q17: 437804.12
... B29: THE MONARCH INSURANCE | C29: 0 | D29: 0 | E29: 0 | F29: 0 | G29: 0 | H29: 0 | I29: 0 | J29: 0 | K29: 0 | L29: 0 | M29: 0 | N29: 0 | O29: 0 | P29: 0 | Q29: 0
B30: TOTAL | C30: =SUM(C6:C29) -> 21212193 | D30: =SUM(D6:D29) -> 18029811 | E30: =SUM(E6:E29) -> 15788414 | F30: =SUM(F6:F29) -> -125777.57 | G30: =SUM(G6:G29) -> 5419958.3 | H30: =SUM(H6:H29) -> 5419958.3 | I30: =SUM(I6:I29) -> 0 | J30: =SUM(J6:J29) -> 0 | ... Q30: =SUM(Q6:Q29) -> 26693703
B31: REINSURERS
B32: CONTINENTAL REINSURANCE | C32: 0 | D32: 0 | E32: 0 | F32: 0 | G32: 0 | H32: 0 | I32: 0 | J32: 0 | K32: 0 | L32: 0 | M32: 0 | N32: 0 | O32: 0 | P32: 0 | Q32: 0
B33: EAST AFRICA REINSURANCE | C33: 0 | D33: 0 | E33: 0 | F33: 0 | G33: 0 | H33: 0 | I33: 0 | J33: 0 | K33: 0 | L33: 0 | M33: 0 | N33: 0 | O33: 0 | P33: 0 | Q33: 0
B34: KENYA REINSURANCE CORPORATION | C34: 0 | D34: 0 | E34: 0 | F34: 0 | G34: 0 | H34: 0 | I34: 0 | J34: 0 | K34: 0 | L34: 0 | M34: 0 | N34: 0 | O34: 0 | P34: 0 | Q34: 0
B35: TOTAL | C35: =SUM(C32:C34) -> 0 | D35: =SUM(D32:D34) -> 0 | E35: =SUM(E32:E34) -> 0 | F35: =SUM(F32:F34) -> 0 | G35: =SUM(G32:G34) -> 0 | H35: =SUM(H32:H34) -> 0 | I35: =SUM(I32:I34) -> 0 | J35: =SUM(J32:J34) -> 0 | ... Q35: =SUM(Q32:Q34) -> 0
B36: Amounts in Thousand Shillings

Sheet APPENDIX 13
B3: =_xlfn.CONCAT('Table of Contents'!B25,": ",'Table of Contents'!C25) -> APPENDIX 13: SUMMARY OF INVESTMENTS BUSINESS REVENUE ACCOUNTS FOR THE PERIOD ENDED 31.12.2025
B4: Company | C4: Life Fund BF | D4: Gross Premium | E4: Net Premium | F4: Other (Fee) Income | G4: Total Benefits | H4: Claims | I4: Surrenders_x000D_ | J4: Bonuses Paid | K4: Annuities Paid | L4: Net Commisions | M4: Expense of Management | N4: Investment Income | O4: Investment Expenses | P4: Transfer To (From) P & L | Q4: Life Fund CF
B5: INSURERS
B6: =LINKED!B6 -> ABSA LIFE ASSURANCE | C6: =+LINKED!C6+'NON-LINKED'!C6 -> 0 | D6: =+LINKED!D6+'NON-LINKED'!D6 -> 0 | E6: =+LINKED!E6+'NON-LINKED'!E6 -> 0 | F6: =+LINKED!F6+'NON-LINKED'!F6 -> 0 | G6: =+LINKED!G6+'NON-LINKED'!G6 -> 0 | H6: =+LINKED!H6+'NON-LINKED'!H6 -> 0 | I6: =+LINKED!I6+'NON-LINKED'!I6 -> 0 | J6: =+LINKED!J6+'NON-LINKED'!J6 -> 0 | ... Q6: =+LINKED!Q6+'NON-LINKED'!Q6 -> 0
B7: =LINKED!B7 -> APA LIFE ASSURANCE COMPANY | C7: =+LINKED!C7+'NON-LINKED'!C7 -> 1808290.5 | D7: =+LINKED!D7+'NON-LINKED'!D7 -> 8662218 | E7: =+LINKED!E7+'NON-LINKED'!E7 -> 8662218 | F7: =+LINKED!F7+'NON-LINKED'!F7 -> 0 | G7: =+LINKED!G7+'NON-LINKED'!G7 -> 184289.56 | H7: =+LINKED!H7+'NON-LINKED'!H7 -> 184289.56 | I7: =+LINKED!I7+'NON-LINKED'!I7 -> 0 | J7: =+LINKED!J7+'NON-LINKED'!J7 -> 0 | ... Q7: =+LINKED!Q7+'NON-LINKED'!Q7 -> 10649542
B8: =LINKED!B8 -> BRITAM LIFE ASSURANCE | C8: =+LINKED!C8+'NON-LINKED'!C8 -> 7519675.8 | D8: =+LINKED!D8+'NON-LINKED'!D8 -> 13503522 | E8: =+LINKED!E8+'NON-LINKED'!E8 -> 13503522 | F8: =+LINKED!F8+'NON-LINKED'!F8 -> 0 | G8: =+LINKED!G8+'NON-LINKED'!G8 -> 4674019.5 | H8: =+LINKED!H8+'NON-LINKED'!H8 -> 4674019.5 | I8: =+LINKED!I8+'NON-LINKED'!I8 -> 0 | J8: =+LINKED!J8+'NON-LINKED'!J8 -> 0 | ... Q8: =+LINKED!Q8+'NON-LINKED'!Q8 -> 18167104
B9: =LINKED!B9 -> CANNON LIFE ASSURANCE (K) LIMITED | C9: =+LINKED!C9+'NON-LINKED'!C9 -> 118268.31 | D9: =+LINKED!D9+'NON-LINKED'!D9 -> 0 | E9: =+LINKED!E9+'NON-LINKED'!E9 -> 0 | F9: =+LINKED!F9+'NON-LINKED'!F9 -> 0 | G9: =+LINKED!G9+'NON-LINKED'!G9 -> 0 | H9: =+LINKED!H9+'NON-LINKED'!H9 -> 0 | I9: =+LINKED!I9+'NON-LINKED'!I9 -> 0 | J9: =+LINKED!J9+'NON-LINKED'!J9 -> 0 | ... Q9: =+LINKED!Q9+'NON-LINKED'!Q9 -> 118268.31
B10: =LINKED!B10 -> CAPEX LIFE ASSURANCE COMPANY | C10: =+LINKED!C10+'NON-LINKED'!C10 -> 0 | D10: =+LINKED!D10+'NON-LINKED'!D10 -> 0 | E10: =+LINKED!E10+'NON-LINKED'!E10 -> 0 | F10: =+LINKED!F10+'NON-LINKED'!F10 -> 0 | G10: =+LINKED!G10+'NON-LINKED'!G10 -> 0 | H10: =+LINKED!H10+'NON-LINKED'!H10 -> 0 | I10: =+LINKED!I10+'NON-LINKED'!I10 -> 0 | J10: =+LINKED!J10+'NON-LINKED'!J10 -> 0 | ... Q10: =+LINKED!Q10+'NON-LINKED'!Q10 -> 0
B11: =LINKED!B11 -> CIC LIFE ASSURANCE COMPANY | C11: =+LINKED!C11+'NON-LINKED'!C11 -> 0 | D11: =+LINKED!D11+'NON-LINKED'!D11 -> 0 | E11: =+LINKED!E11+'NON-LINKED'!E11 -> 0 | F11: =+LINKED!F11+'NON-LINKED'!F11 -> 0 | G11: =+LINKED!G11+'NON-LINKED'!G11 -> 0 | H11: =+LINKED!H11+'NON-LINKED'!H11 -> 0 | I11: =+LINKED!I11+'NON-LINKED'!I11 -> 0 | J11: =+LINKED!J11+'NON-LINKED'!J11 -> 0 | ... Q11: =+LINKED!Q11+'NON-LINKED'!Q11 -> 0
B12: =LINKED!B12 -> CORPORATE INSURANCE COMPANY | C12: =+LINKED!C12+'NON-LINKED'!C12 -> 0 | D12: =+LINKED!D12+'NON-LINKED'!D12 -> 0 | E12: =+LINKED!E12+'NON-LINKED'!E12 -> 0 | F12: =+LINKED!F12+'NON-LINKED'!F12 -> 0 | G12: =+LINKED!G12+'NON-LINKED'!G12 -> 0 | H12: =+LINKED!H12+'NON-LINKED'!H12 -> 0 | I12: =+LINKED!I12+'NON-LINKED'!I12 -> 0 | J12: =+LINKED!J12+'NON-LINKED'!J12 -> 0 | ... Q12: =+LINKED!Q12+'NON-LINKED'!Q12 -> 0
B13: =LINKED!B13 -> EQUITY LIFE ASSURANCE | C13: =+LINKED!C13+'NON-LINKED'!C13 -> 317288.83 | D13: =+LINKED!D13+'NON-LINKED'!D13 -> 321400.65 | E13: =+LINKED!E13+'NON-LINKED'!E13 -> 321400.65 | F13: =+LINKED!F13+'NON-LINKED'!F13 -> 0 | G13: =+LINKED!G13+'NON-LINKED'!G13 -> 317288.83 | H13: =+LINKED!H13+'NON-LINKED'!H13 -> 317288.83 | I13: =+LINKED!I13+'NON-LINKED'!I13 -> 0 | J13: =+LINKED!J13+'NON-LINKED'!J13 -> 0 | ... Q13: =+LINKED!Q13+'NON-LINKED'!Q13 -> 321400.65
B14: =LINKED!B14 -> GA LIFE ASSURANCE COMPANY | C14: =+LINKED!C14+'NON-LINKED'!C14 -> 0 | D14: =+LINKED!D14+'NON-LINKED'!D14 -> 0 | E14: =+LINKED!E14+'NON-LINKED'!E14 -> 0 | F14: =+LINKED!F14+'NON-LINKED'!F14 -> 0 | G14: =+LINKED!G14+'NON-LINKED'!G14 -> 0 | H14: =+LINKED!H14+'NON-LINKED'!H14 -> 0 | I14: =+LINKED!I14+'NON-LINKED'!I14 -> 0 | J14: =+LINKED!J14+'NON-LINKED'!J14 -> 0 | ... Q14: =+LINKED!Q14+'NON-LINKED'!Q14 -> 0
B15: =LINKED!B15 -> GEMINIA LIFE INSURANCE COMPANY | C15: =+LINKED!C15+'NON-LINKED'!C15 -> 90519.786 | D15: =+LINKED!D15+'NON-LINKED'!D15 -> 574003.62 | E15: =+LINKED!E15+'NON-LINKED'!E15 -> 574003.62 | F15: =+LINKED!F15+'NON-LINKED'!F15 -> 0 | G15: =+LINKED!G15+'NON-LINKED'!G15 -> 0 | H15: =+LINKED!H15+'NON-LINKED'!H15 -> 0 | I15: =+LINKED!I15+'NON-LINKED'!I15 -> 0 | J15: =+LINKED!J15+'NON-LINKED'!J15 -> 0 | ... Q15: =+LINKED!Q15+'NON-LINKED'!Q15 -> 630031.13
B16: =LINKED!B16 -> ICEA LION LIFE ASSURANCE | C16: =+LINKED!C16+'NON-LINKED'!C16 -> 440263.48 | D16: =+LINKED!D16+'NON-LINKED'!D16 -> 5030.2792 | E16: =+LINKED!E16+'NON-LINKED'!E16 -> 5030.2792 | F16: =+LINKED!F16+'NON-LINKED'!F16 -> 0 | G16: =+LINKED!G16+'NON-LINKED'!G16 -> 32905.701 | H16: =+LINKED!H16+'NON-LINKED'!H16 -> 28134.596 | I16: =+LINKED!I16+'NON-LINKED'!I16 -> 4771.1043 | J16: =+LINKED!J16+'NON-LINKED'!J16 -> 0 | ... Q16: =+LINKED!Q16+'NON-LINKED'!Q16 -> 411841.78
B17: =LINKED!B17 -> JUBILEE LIFE INSURANCE | C17: =+LINKED!C17+'NON-LINKED'!C17 -> 70346.668 | D17: =+LINKED!D17+'NON-LINKED'!D17 -> 2710479.1 | E17: =+LINKED!E17+'NON-LINKED'!E17 -> 2710479.1 | F17: =+LINKED!F17+'NON-LINKED'!F17 -> 0 | G17: =+LINKED!G17+'NON-LINKED'!G17 -> 0 | H17: =+LINKED!H17+'NON-LINKED'!H17 -> 0 | I17: =+LINKED!I17+'NON-LINKED'!I17 -> 0 | J17: =+LINKED!J17+'NON-LINKED'!J17 -> 0 | ... Q17: =+LINKED!Q17+'NON-LINKED'!Q17 -> 2775543.6
... B29: =LINKED!B29 -> THE MONARCH INSURANCE | C29: =+LINKED!C29+'NON-LINKED'!C29 -> 0 | D29: =+LINKED!D29+'NON-LINKED'!D29 -> 0 | E29: =+LINKED!E29+'NON-LINKED'!E29 -> 0 | F29: =+LINKED!F29+'NON-LINKED'!F29 -> 0 | G29: =+LINKED!G29+'NON-LINKED'!G29 -> 0 | H29: =+LINKED!H29+'NON-LINKED'!H29 -> 0 | I29: =+LINKED!I29+'NON-LINKED'!I29 -> 0 | J29: =+LINKED!J29+'NON-LINKED'!J29 -> 0 | ... Q29: =+LINKED!Q29+'NON-LINKED'!Q29 -> 0
B30: TOTAL | C30: =SUM(C6:C29) -> 26358749 | D30: =SUM(D6:D29) -> 30297131 | E30: =SUM(E6:E29) -> 30272158 | F30: =SUM(F6:F29) -> 7480.4863 | G30: =SUM(G6:G29) -> 10851043 | H30: =SUM(H6:H29) -> 10338587 | I30: =SUM(I6:I29) -> 512456.13 | J30: =SUM(J6:J29) -> 0 | ... Q30: =SUM(Q6:Q29) -> 49960639
B31: REINSURERS
B32: =LINKED!B32 -> CONTINENTAL REINSURANCE | C32: =+LINKED!C32+'NON-LINKED'!C32 -> 0 | D32: =+LINKED!D32+'NON-LINKED'!D32 -> 0 | E32: =+LINKED!E32+'NON-LINKED'!E32 -> 0 | F32: =+LINKED!F32+'NON-LINKED'!F32 -> 0 | G32: =+LINKED!G32+'NON-LINKED'!G32 -> 0 | H32: =+LINKED!H32+'NON-LINKED'!H32 -> 0 | I32: =+LINKED!I32+'NON-LINKED'!I32 -> 0 | J32: =+LINKED!J32+'NON-LINKED'!J32 -> 0 | ... Q32: =+LINKED!Q32+'NON-LINKED'!Q32 -> 0
B33: =LINKED!B33 -> EAST AFRICA REINSURANCE | C33: =+LINKED!C33+'NON-LINKED'!C33 -> 0 | D33: =+LINKED!D33+'NON-LINKED'!D33 -> 0 | E33: =+LINKED!E33+'NON-LINKED'!E33 -> 0 | F33: =+LINKED!F33+'NON-LINKED'!F33 -> 0 | G33: =+LINKED!G33+'NON-LINKED'!G33 -> 0 | H33: =+LINKED!H33+'NON-LINKED'!H33 -> 0 | I33: =+LINKED!I33+'NON-LINKED'!I33 -> 0 | J33: =+LINKED!J33+'NON-LINKED'!J33 -> 0 | ... Q33: =+LINKED!Q33+'NON-LINKED'!Q33 -> 0
B34: =LINKED!B34 -> KENYA REINSURANCE CORPORATION | C34: =+LINKED!C34+'NON-LINKED'!C34 -> 0 | D34: =+LINKED!D34+'NON-LINKED'!D34 -> 0 | E34: =+LINKED!E34+'NON-LINKED'!E34 -> 0 | F34: =+LINKED!F34+'NON-LINKED'!F34 -> 0 | G34: =+LINKED!G34+'NON-LINKED'!G34 -> 0 | H34: =+LINKED!H34+'NON-LINKED'!H34 -> 0 | I34: =+LINKED!I34+'NON-LINKED'!I34 -> 0 | J34: =+LINKED!J34+'NON-LINKED'!J34 -> 0 | ... Q34: =+LINKED!Q34+'NON-LINKED'!Q34 -> 0
B35: TOTAL | C35: =SUM(C32:C34) -> 0 | D35: =SUM(D32:D34) -> 0 | E35: =SUM(E32:E34) -> 0 | F35: =SUM(F32:F34) -> 0 | G35: =SUM(G32:G34) -> 0 | H35: =SUM(H32:H34) -> 0 | I35: =SUM(I32:I34) -> 0 | J35: =SUM(J32:J34) -> 0 | ... Q35: =SUM(Q32:Q34) -> 0
B36: Amounts in Thousand Shillings

Sheet LINKED
B3: =_xlfn.CONCAT("LINKED INVESTMENTS"," ",Details!F18) -> LINKED INVESTMENTS 31.12.2025
B4: Company | C4: Life Fund BF | D4: Gross Premium | E4: Net Premium | F4: Other (Fee) Income | G4: Total Benefits | H4: Claims | I4: Surrenders_x000D_ | J4: Bonuses Paid | K4: Annuities Paid | L4: Net Commisions | M4: Expense of Management | N4: Investment Income | O4: Investment Expenses | P4: Transfer To (From) P & L | Q4: Life Fund CF
B5: INSURERS
B6: ABSA LIFE ASSURANCE | C6: 0 | D6: 0 | E6: 0 | F6: 0 | G6: 0 | H6: 0 | I6: 0 | J6: 0 | K6: 0 | L6: 0 | M6: 0 | N6: 0 | O6: 0 | P6: 0 | Q6: 0
B7: APA LIFE ASSURANCE COMPANY | C7: 0 | D7: 9925.981 | E7: 9925.981 | F7: 0 | G7: 0 | H7: 0 | I7: 0 | J7: 0 | K7: 0 | L7: 0 | M7: 0 | N7: 0 | O7: 0 | P7: 0 | Q7: 9925.981
B8: BRITAM LIFE ASSURANCE | C8: 7519675.8 | D8: 13503522 | E8: 13503522 | F8: 0 | G8: 4674019.5 | H8: 4674019.5 | I8: 0 | J8: 0 | K8: 0 | L8: 45214.18 | M8: 134986.51 | N8: 2024500.3 | O8: 26373.734 | P8: 0 | Q8: 18167104
B9: CANNON LIFE ASSURANCE (K) LIMITED | C9: 118268.31 | D9: 0 | E9: 0 | F9: 0 | G9: 0 | H9: 0 | I9: 0 | J9: 0 | K9: 0 | L9: 0 | M9: 0 | N9: 0 | O9: 0 | P9: 0 | Q9: 118268.31
B10: CAPEX LIFE ASSURANCE COMPANY | C10: 0 | D10: 0 | E10: 0 | F10: 0 | G10: 0 | H10: 0 | I10: 0 | J10: 0 | K10: 0 | L10: 0 | M10: 0 | N10: 0 | O10: 0 | P10: 0 | Q10: 0
B11: CIC LIFE ASSURANCE COMPANY | C11: 0 | D11: 0 | E11: 0 | F11: 0 | G11: 0 | H11: 0 | I11: 0 | J11: 0 | K11: 0 | L11: 0 | M11: 0 | N11: 0 | O11: 0 | P11: 0 | Q11: 0
B12: CORPORATE INSURANCE COMPANY | C12: 0 | D12: 0 | E12: 0 | F12: 0 | G12: 0 | H12: 0 | I12: 0 | J12: 0 | K12: 0 | L12: 0 | M12: 0 | N12: 0 | O12: 0 | P12: 0 | Q12: 0
B13: EQUITY LIFE ASSURANCE | C13: 0 | D13: 0 | E13: 0 | F13: 0 | G13: 0 | H13: 0 | I13: 0 | J13: 0 | K13: 0 | L13: 0 | M13: 0 | N13: 0 | O13: 0 | P13: 0 | Q13: 0
B14: GA LIFE ASSURANCE COMPANY | C14: 0 | D14: 0 | E14: 0 | F14: 0 | G14: 0 | H14: 0 | I14: 0 | J14: 0 | K14: 0 | L14: 0 | M14: 0 | N14: 0 | O14: 0 | P14: 0 | Q14: 0
B15: GEMINIA LIFE INSURANCE COMPANY | C15: 0 | D15: 0 | E15: 0 | F15: 0 | G15: 0 | H15: 0 | I15: 0 | J15: 0 | K15: 0 | L15: 0 | M15: 0 | N15: 0 | O15: 0 | P15: 0 | Q15: 0
B16: ICEA LION LIFE ASSURANCE | C16: 440263.48 | D16: 5030.2792 | E16: 5030.2792 | F16: 0 | G16: 32905.701 | H16: 28134.596 | I16: 4771.1043 | J16: 0 | K16: 0 | L16: 0 | M16: 0 | N16: 0 | O16: 0 | P16: 546.28129 | Q16: 411841.78
B17: JUBILEE LIFE INSURANCE | C17: 70346.668 | D17: 2710479.1 | E17: 2710479.1 | F17: 0 | G17: 0 | H17: 0 | I17: 0 | J17: 0 | K17: 0 | L17: 0 | M17: 5282.1477 | N17: 0 | O17: 0 | P17: 0 | Q17: 2775543.6
... B29: THE MONARCH INSURANCE | C29: 0 | D29: 0 | E29: 0 | F29: 0 | G29: 0 | H29: 0 | I29: 0 | J29: 0 | K29: 0 | L29: 0 | M29: 0 | N29: 0 | O29: 0 | P29: 0 | Q29: 0
B30: TOTAL | C30: =SUM(C6:C29) -> 21940643 | D30: =SUM(D6:D29) -> 18614015 | E30: =SUM(E6:E29) -> 18611459 | F30: =SUM(F6:F29) -> 624.17451 | G30: =SUM(G6:G29) -> 8964204.7 | H30: =SUM(H6:H29) -> 8451748.6 | I30: =SUM(I6:I29) -> 512456.13 | J30: =SUM(J6:J29) -> 0 | ... Q30: =SUM(Q6:Q29) -> 35125378
B31: REINSURERS
B32: CONTINENTAL REINSURANCE | C32: 0 | D32: 0 | E32: 0 | F32: 0 | G32: 0 | H32: 0 | I32: 0 | J32: 0 | K32: 0 | L32: 0 | M32: 0 | N32: 0 | O32: 0 | P32: 0 | Q32: 0
B33: EAST AFRICA REINSURANCE | C33: 0 | D33: 0 | E33: 0 | F33: 0 | G33: 0 | H33: 0 | I33: 0 | J33: 0 | K33: 0 | L33: 0 | M33: 0 | N33: 0 | O33: 0 | P33: 0 | Q33: 0
B34: KENYA REINSURANCE CORPORATION | C34: 0 | D34: 0 | E34: 0 | F34: 0 | G34: 0 | H34: 0 | I34: 0 | J34: 0 | K34: 0 | L34: 0 | M34: 0 | N34: 0 | O34: 0 | P34: 0 | Q34: 0
B35: TOTAL | C35: 0 | D35: 0 | E35: 0 | F35: 0 | G35: 0 | H35: 0 | I35: 0 | J35: 0 | K35: 0 | L35: 0 | M35: 0 | N35: 0 | O35: 0 | P35: 0 | Q35: 0
B36: Amounts in Thousand Shillings

Sheet NON-LINKED
B3: =_xlfn.CONCAT("NON-LINKED INVESTMENTS"," ",Details!F18) -> NON-LINKED INVESTMENTS 31.12.2025
B4: Company | C4: Life Fund BF | D4: Gross Premium | E4: Net Premium | F4: Other (Fee) Income | G4: Total Benefits | H4: Claims | I4: Surrenders_x000D_ | J4: Bonuses Paid | K4: Annuities Paid | L4: Net Commisions | M4: Expense of Management | N4: Investment Income | O4: Investment Expenses | P4: Transfer To (From) P & L | Q4: Life Fund CF
B5: INSURERS
B6: ABSA LIFE ASSURANCE | C6: 0 | D6: 0 | E6: 0 | F6: 0 | G6: 0 | H6: 0 | I6: 0 | J6: 0 | K6: 0 | L6: 0 | M6: 0 | N6: 0 | O6: 0 | P6: 0 | Q6: 0
B7: APA LIFE ASSURANCE COMPANY | C7: 1808290.5 | D7: 8652292 | E7: 8652292 | F7: 0 | G7: 184289.56 | H7: 184289.56 | I7: 0 | J7: 0 | K7: 0 | L7: 441169.36 | M7: 0 | N7: 816886.54 | O7: 12394.207 | P7: 0 | Q7: 10639616
B8: BRITAM LIFE ASSURANCE | C8: 0 | D8: 0 | E8: 0 | F8: 0 | G8: 0 | H8: 0 | I8: 0 | J8: 0 | K8: 0 | L8: 0 | M8: 0 | N8: 0 | O8: 0 | P8: 0 | Q8: 0
B9: CANNON LIFE ASSURANCE (K) LIMITED | C9: 0 | D9: 0 | E9: 0 | F9: 0 | G9: 0 | H9: 0 | I9: 0 | J9: 0 | K9: 0 | L9: 0 | M9: 0 | N9: 0 | O9: 0 | P9: 0 | Q9: 0
B10: CAPEX LIFE ASSURANCE COMPANY | C10: 0 | D10: 0 | E10: 0 | F10: 0 | G10: 0 | H10: 0 | I10: 0 | J10: 0 | K10: 0 | L10: 0 | M10: 0 | N10: 0 | O10: 0 | P10: 0 | Q10: 0
B11: CIC LIFE ASSURANCE COMPANY | C11: 0 | D11: 0 | E11: 0 | F11: 0 | G11: 0 | H11: 0 | I11: 0 | J11: 0 | K11: 0 | L11: 0 | M11: 0 | N11: 0 | O11: 0 | P11: 0 | Q11: 0
B12: CORPORATE INSURANCE COMPANY | C12: 0 | D12: 0 | E12: 0 | F12: 0 | G12: 0 | H12: 0 | I12: 0 | J12: 0 | K12: 0 | L12: 0 | M12: 0 | N12: 0 | O12: 0 | P12: 0 | Q12: 0
B13: EQUITY LIFE ASSURANCE | C13: 317288.83 | D13: 321400.65 | E13: 321400.65 | F13: 0 | G13: 317288.83 | H13: 317288.83 | I13: 0 | J13: 0 | K13: 0 | L13: 0 | M13: 0 | N13: 0 | O13: 0 | P13: 0 | Q13: 321400.65
B14: GA LIFE ASSURANCE COMPANY | C14: 0 | D14: 0 | E14: 0 | F14: 0 | G14: 0 | H14: 0 | I14: 0 | J14: 0 | K14: 0 | L14: 0 | M14: 0 | N14: 0 | O14: 0 | P14: 0 | Q14: 0
B15: GEMINIA LIFE INSURANCE COMPANY | C15: 90519.786 | D15: 574003.62 | E15: 574003.62 | F15: 0 | G15: 0 | H15: 0 | I15: 0 | J15: 0 | K15: 0 | L15: 0 | M15: 34492.28 | N15: 0 | O15: 0 | P15: 0 | Q15: 630031.13
B16: ICEA LION LIFE ASSURANCE | C16: 0 | D16: 0 | E16: 0 | F16: 0 | G16: 0 | H16: 0 | I16: 0 | J16: 0 | K16: 0 | L16: 0 | M16: 0 | N16: 0 | O16: 0 | P16: 0 | Q16: 0
B17: JUBILEE LIFE INSURANCE | C17: 0 | D17: 0 | E17: 0 | F17: 0 | G17: 0 | H17: 0 | I17: 0 | J17: 0 | K17: 0 | L17: 0 | M17: 0 | N17: 0 | O17: 0 | P17: 0 | Q17: 0
... B29: THE MONARCH INSURANCE | C29: 0 | D29: 0 | E29: 0 | F29: 0 | G29: 0 | H29: 0 | I29: 0 | J29: 0 | K29: 0 | L29: 0 | M29: 0 | N29: 0 | O29: 0 | P29: 0 | Q29: 0
B30: TOTAL | C30: =SUM(C6:C29) -> 4418106.1 | D30: =SUM(D6:D29) -> 11683116 | E30: =SUM(E6:E29) -> 11660699 | F30: =SUM(F6:F29) -> 6856.3118 | G30: =SUM(G6:G29) -> 1886838.1 | H30: =SUM(H6:H29) -> 1886838.1 | I30: =SUM(I6:I29) -> 0 | J30: =SUM(J6:J29) -> 0 | ... Q30: =SUM(Q6:Q29) -> 14835261
B31: REINSURERS
B32: CONTINENTAL REINSURANCE | C32: 0 | D32: 0 | E32: 0 | F32: 0 | G32: 0 | H32: 0 | I32: 0 | J32: 0 | K32: 0 | L32: 0 | M32: 0 | N32: 0 | O32: 0 | P32: 0 | Q32: 0
B33: EAST AFRICA REINSURANCE | C33: 0 | D33: 0 | E33: 0 | F33: 0 | G33: 0 | H33: 0 | I33: 0 | J33: 0 | K33: 0 | L33: 0 | M33: 0 | N33: 0 | O33: 0 | P33: 0 | Q33: 0
B34: KENYA REINSURANCE CORPORATION | C34: 0 | D34: 0 | E34: 0 | F34: 0 | G34: 0 | H34: 0 | I34: 0 | J34: 0 | K34: 0 | L34: 0 | M34: 0 | N34: 0 | O34: 0 | P34: 0 | Q34: 0
B35: TOTAL | C35: =SUM(C32:C34) -> 0 | D35: =SUM(D32:D34) -> 0 | E35: =SUM(E32:E34) -> 0 | F35: =SUM(F32:F34) -> 0 | G35: =SUM(G32:G34) -> 0 | H35: =SUM(H32:H34) -> 0 | I35: =SUM(I32:I34) -> 0 | J35: =SUM(J32:J34) -> 0 | ... Q35: =SUM(Q32:Q34) -> 0
B36: Amounts in Thousand Shillings

Sheet APPENDIX 14
B3: =_xlfn.CONCAT('Table of Contents'!B26,": ",'Table of Contents'!C26) -> APPENDIX 14: SUMMARY OF PERMANENT HEALTH BUSINESS REVENUE ACCOUNTS FOR THE PERIOD ENDED 31.12.2025
B4: Company | C4: Life Fund BF | D4: Gross Premium | E4: Net Premium | F4: Other (Fee) Income | G4: Total Benefits | H4: Claims | I4: Surrenders_x000D_ | J4: Bonuses Paid | K4: Annuities Paid | L4: Net Commisions | M4: Expense of Management | N4: Investment Income | O4: Investment Expenses | P4: Transfer To (From) P & L | Q4: Life Fund CF
B5: INSURERS
B6: ABSA LIFE ASSURANCE | C6: 0 | D6: 0 | E6: 0 | F6: 0 | G6: 0 | H6: 0 | I6: 0 | J6: 0 | K6: 0 | L6: 0 | M6: 0 | N6: 0 | O6: 0 | P6: 0 | Q6: 0
B7: APA LIFE ASSURANCE COMPANY | C7: 0 | D7: 0 | E7: 0 | F7: 0 | G7: 0 | H7: 0 | I7: 0 | J7: 0 | K7: 0 | L7: 0 | M7: 0 | N7: 0 | O7: 0 | P7: 0 | Q7: 0
B8: BRITAM LIFE ASSURANCE | C8: 0 | D8: 0 | E8: 0 | F8: 0 | G8: 0 | H8: 0 | I8: 0 | J8: 0 | K8: 0 | L8: 0 | M8: 0 | N8: 0 | O8: 0 | P8: 0 | Q8: 0
B9: CANNON LIFE ASSURANCE (K) LIMITED | C9: 0 | D9: 0 | E9: 0 | F9: 0 | G9: 0 | H9: 0 | I9: 0 | J9: 0 | K9: 0 | L9: 0 | M9: 146356.33 | N9: 70997.793 | O9: 0 | P9: 0 | Q9: -75358.534
B10: CAPEX LIFE ASSURANCE COMPANY | C10: 0 | D10: 0 | E10: 0 | F10: 0 | G10: 0 | H10: 0 | I10: 0 | J10: 0 | K10: 0 | L10: 0 | M10: 0 | N10: 0 | O10: 0 | P10: 0 | Q10: 0
B11: CIC LIFE ASSURANCE COMPANY | C11: 0 | D11: 0 | E11: 0 | F11: 0 | G11: 0 | H11: 0 | I11: 0 | J11: 0 | K11: 0 | L11: 0 | M11: 0 | N11: 0 | O11: 0 | P11: 0 | Q11: 0
B12: CORPORATE INSURANCE COMPANY | C12: 0 | D12: 0 | E12: 0 | F12: 0 | G12: 0 | H12: 0 | I12: 0 | J12: 0 | K12: 0 | L12: 0 | M12: 0 | N12: 0 | O12: 0 | P12: 0 | Q12: 0
B13: EQUITY LIFE ASSURANCE | C13: 0 | D13: 0 | E13: 0 | F13: 0 | G13: 0 | H13: 0 | I13: 0 | J13: 0 | K13: 0 | L13: 0 | M13: 0 | N13: 0 | O13: 0 | P13: 0 | Q13: 0
B14: GA LIFE ASSURANCE COMPANY | C14: 0 | D14: 0 | E14: 0 | F14: 0 | G14: 0 | H14: 0 | I14: 0 | J14: 0 | K14: 0 | L14: 0 | M14: 0 | N14: 0 | O14: 0 | P14: 0 | Q14: 0
B15: GEMINIA LIFE INSURANCE COMPANY | C15: 0 | D15: 0 | E15: 0 | F15: 0 | G15: 0 | H15: 0 | I15: 0 | J15: 0 | K15: 0 | L15: 0 | M15: 0 | N15: 0 | O15: 0 | P15: 0 | Q15: 0
B16: ICEA LION LIFE ASSURANCE | C16: 0 | D16: 0 | E16: 0 | F16: 0 | G16: 0 | H16: 0 | I16: 0 | J16: 0 | K16: 0 | L16: 0 | M16: 0 | N16: 0 | O16: 0 | P16: 0 | Q16: 0
B17: JUBILEE LIFE INSURANCE | C17: 0 | D17: 0 | E17: 0 | F17: 0 | G17: 0 | H17: 0 | I17: 0 | J17: 0 | K17: 0 | L17: 0 | M17: 0 | N17: 0 | O17: 0 | P17: 0 | Q17: 0
... B29: THE MONARCH INSURANCE | C29: 0 | D29: 0 | E29: 0 | F29: 0 | G29: 0 | H29: 0 | I29: 0 | J29: 0 | K29: 0 | L29: 0 | M29: 0 | N29: 0 | O29: 0 | P29: 0 | Q29: 0
B30: TOTAL | C30: =SUM(C6:C29) -> 0 | D30: =SUM(D6:D29) -> 0 | E30: =SUM(E6:E29) -> 0 | F30: =SUM(F6:F29) -> 0 | G30: =SUM(G6:G29) -> 0 | H30: =SUM(H6:H29) -> 0 | I30: =SUM(I6:I29) -> 0 | J30: =SUM(J6:J29) -> 0 | ... Q30: =SUM(Q6:Q29) -> -75358.534
B31: REINSURERS
B32: CONTINENTAL REINSURANCE | C32: 0 | D32: 0 | E32: 0 | F32: 0 | G32: 0 | H32: 0 | I32: 0 | J32: 0 | K32: 0 | L32: 0 | M32: 0 | N32: 0 | O32: 0 | P32: 0 | Q32: 0
B33: EAST AFRICA REINSURANCE | C33: 0 | D33: 0 | E33: 0 | F33: 0 | G33: 0 | H33: 0 | I33: 0 | J33: 0 | K33: 0 | L33: 0 | M33: 0 | N33: 0 | O33: 0 | P33: 0 | Q33: 0
B34: KENYA REINSURANCE CORPORATION | C34: 0 | D34: 0 | E34: 0 | F34: 0 | G34: 0 | H34: 0 | I34: 0 | J34: 0 | K34: 0 | L34: 0 | M34: 0 | N34: 0 | O34: 0 | P34: 0 | Q34: 0
B35: TOTAL | C35: =SUM(C32:C34) -> 0 | D35: =SUM(D32:D34) -> 0 | E35: =SUM(E32:E34) -> 0 | F35: =SUM(F32:F34) -> 0 | G35: =SUM(G32:G34) -> 0 | H35: =SUM(H32:H34) -> 0 | I35: =SUM(I32:I34) -> 0 | J35: =SUM(J32:J34) -> 0 | ... Q35: =SUM(Q32:Q34) -> 0
B36: Amounts in Thousand Shillings

Sheet PENSIONS
B3: =_xlfn.CONCAT("SUMMARY OF PENSIONS BUSINESS REVENUE ACCOUNTS FOR THE PERIOD ENDED"," ",Details!F18) -> SUMMARY OF PENSIONS BUSINESS REVENUE ACCOUNTS FOR THE PERIOD ENDED 31.12.2025
B4: Company | C4: Life Fund BF | D4: Gross Premium | E4: Net Premium | F4: Other (Fee) Income | G4: Total Benefits | H4: Claims | I4: Surrenders_x000D_ | J4: Bonuses Paid | K4: Annuities Paid | L4: Net Commisions | M4: Expense of Management | N4: Investment Income | O4: Investment Expenses | P4: Transfer To (From) P & L | Q4: Life Fund CF
B5: INSURERS
B6: =+'APPENDIX 15'!B6 -> ABSA LIFE ASSURANCE | C6: =+'APPENDIX 15'!C6+'APPENDIX 16'!C6 -> 0 | D6: =+'APPENDIX 15'!D6+'APPENDIX 16'!D6 -> 0 | E6: =+'APPENDIX 15'!E6+'APPENDIX 16'!E6 -> 0 | F6: =+'APPENDIX 15'!F6+'APPENDIX 16'!F6 -> 0 | G6: =+'APPENDIX 15'!G6+'APPENDIX 16'!G6 -> 0 | H6: =+'APPENDIX 15'!H6+'APPENDIX 16'!H6 -> 0 | I6: =+'APPENDIX 15'!I6+'APPENDIX 16'!I6 -> 0 | J6: =+'APPENDIX 15'!J6+'APPENDIX 16'!J6 -> 0 | ... Q6: =+'APPENDIX 15'!Q6+'APPENDIX 16'!Q6 -> 0
B7: =+'APPENDIX 15'!B7 -> APA LIFE ASSURANCE COMPANY | C7: =+'APPENDIX 15'!C7+'APPENDIX 16'!C7 -> 9733226.8 | D7: =+'APPENDIX 15'!D7+'APPENDIX 16'!D7 -> 2080104.3 | E7: =+'APPENDIX 15'!E7+'APPENDIX 16'!E7 -> 2080104.3 | F7: =+'APPENDIX 15'!F7+'APPENDIX 16'!F7 -> 0 | G7: =+'APPENDIX 15'!G7+'APPENDIX 16'!G7 -> 1473357.8 | H7: =+'APPENDIX 15'!H7+'APPENDIX 16'!H7 -> 1473357.8 | I7: =+'APPENDIX 15'!I7+'APPENDIX 16'!I7 -> 0 | J7: =+'APPENDIX 15'!J7+'APPENDIX 16'!J7 -> 0 | ... Q7: =+'APPENDIX 15'!Q7+'APPENDIX 16'!Q7 -> 11767805
B8: =+'APPENDIX 15'!B8 -> BRITAM LIFE ASSURANCE | C8: =+'APPENDIX 15'!C8+'APPENDIX 16'!C8 -> 77630272 | D8: =+'APPENDIX 15'!D8+'APPENDIX 16'!D8 -> 14976432 | E8: =+'APPENDIX 15'!E8+'APPENDIX 16'!E8 -> 14976432 | F8: =+'APPENDIX 15'!F8+'APPENDIX 16'!F8 -> 0 | G8: =+'APPENDIX 15'!G8+'APPENDIX 16'!G8 -> 20277977 | H8: =+'APPENDIX 15'!H8+'APPENDIX 16'!H8 -> 20277977 | I8: =+'APPENDIX 15'!I8+'APPENDIX 16'!I8 -> 0 | J8: =+'APPENDIX 15'!J8+'APPENDIX 16'!J8 -> 0 | ... Q8: =+'APPENDIX 15'!Q8+'APPENDIX 16'!Q8 -> 83669298
B9: =+'APPENDIX 15'!B9 -> CANNON LIFE ASSURANCE (K) LIMITED | C9: =+'APPENDIX 15'!C9+'APPENDIX 16'!C9 -> 0 | D9: =+'APPENDIX 15'!D9+'APPENDIX 16'!D9 -> 0 | E9: =+'APPENDIX 15'!E9+'APPENDIX 16'!E9 -> 0 | F9: =+'APPENDIX 15'!F9+'APPENDIX 16'!F9 -> 0 | G9: =+'APPENDIX 15'!G9+'APPENDIX 16'!G9 -> 0 | H9: =+'APPENDIX 15'!H9+'APPENDIX 16'!H9 -> 0 | I9: =+'APPENDIX 15'!I9+'APPENDIX 16'!I9 -> 0 | J9: =+'APPENDIX 15'!J9+'APPENDIX 16'!J9 -> 0 | ... Q9: =+'APPENDIX 15'!Q9+'APPENDIX 16'!Q9 -> 0
B10: =+'APPENDIX 15'!B10 -> CAPEX LIFE ASSURANCE COMPANY | C10: =+'APPENDIX 15'!C10+'APPENDIX 16'!C10 -> 0 | D10: =+'APPENDIX 15'!D10+'APPENDIX 16'!D10 -> 41254.695 | E10: =+'APPENDIX 15'!E10+'APPENDIX 16'!E10 -> 41254.695 | F10: =+'APPENDIX 15'!F10+'APPENDIX 16'!F10 -> 0 | G10: =+'APPENDIX 15'!G10+'APPENDIX 16'!G10 -> 7815.967 | H10: =+'APPENDIX 15'!H10+'APPENDIX 16'!H10 -> 7815.967 | I10: =+'APPENDIX 15'!I10+'APPENDIX 16'!I10 -> 0 | J10: =+'APPENDIX 15'!J10+'APPENDIX 16'!J10 -> 0 | ... Q10: =+'APPENDIX 15'!Q10+'APPENDIX 16'!Q10 -> 22464.043
B11: =+'APPENDIX 15'!B11 -> CIC LIFE ASSURANCE COMPANY | C11: =+'APPENDIX 15'!C11+'APPENDIX 16'!C11 -> 13492770 | D11: =+'APPENDIX 15'!D11+'APPENDIX 16'!D11 -> 3353751.3 | E11: =+'APPENDIX 15'!E11+'APPENDIX 16'!E11 -> 3353751.3 | F11: =+'APPENDIX 15'!F11+'APPENDIX 16'!F11 -> 0 | G11: =+'APPENDIX 15'!G11+'APPENDIX 16'!G11 -> 0 | H11: =+'APPENDIX 15'!H11+'APPENDIX 16'!H11 -> 0 | I11: =+'APPENDIX 15'!I11+'APPENDIX 16'!I11 -> 0 | J11: =+'APPENDIX 15'!J11+'APPENDIX 16'!J11 -> 0 | ... Q11: =+'APPENDIX 15'!Q11+'APPENDIX 16'!Q11 -> 16917502
B12: =+'APPENDIX 15'!B12 -> CORPORATE INSURANCE COMPANY | C12: =+'APPENDIX 15'!C12+'APPENDIX 16'!C12 -> 0 | D12: =+'APPENDIX 15'!D12+'APPENDIX 16'!D12 -> 0 | E12: =+'APPENDIX 15'!E12+'APPENDIX 16'!E12 -> 0 | F12: =+'APPENDIX 15'!F12+'APPENDIX 16'!F12 -> 0 | G12: =+'APPENDIX 15'!G12+'APPENDIX 16'!G12 -> 0 | H12: =+'APPENDIX 15'!H12+'APPENDIX 16'!H12 -> 0 | I12: =+'APPENDIX 15'!I12+'APPENDIX 16'!I12 -> 0 | J12: =+'APPENDIX 15'!J12+'APPENDIX 16'!J12 -> 0 | ... Q12: =+'APPENDIX 15'!Q12+'APPENDIX 16'!Q12 -> 0
B13: =+'APPENDIX 15'!B13 -> EQUITY LIFE ASSURANCE | C13: =+'APPENDIX 15'!C13+'APPENDIX 16'!C13 -> 13828977 | D13: =+'APPENDIX 15'!D13+'APPENDIX 16'!D13 -> 2793229.5 | E13: =+'APPENDIX 15'!E13+'APPENDIX 16'!E13 -> 2793229.5 | F13: =+'APPENDIX 15'!F13+'APPENDIX 16'!F13 -> 0 | G13: =+'APPENDIX 15'!G13+'APPENDIX 16'!G13 -> 1645836.6 | H13: =+'APPENDIX 15'!H13+'APPENDIX 16'!H13 -> 1645836.6 | I13: =+'APPENDIX 15'!I13+'APPENDIX 16'!I13 -> 0 | J13: =+'APPENDIX 15'!J13+'APPENDIX 16'!J13 -> 0 | ... Q13: =+'APPENDIX 15'!Q13+'APPENDIX 16'!Q13 -> 17309907
B14: =+'APPENDIX 15'!B14 -> GA LIFE ASSURANCE COMPANY | C14: =+'APPENDIX 15'!C14+'APPENDIX 16'!C14 -> 41439749 | D14: =+'APPENDIX 15'!D14+'APPENDIX 16'!D14 -> 11877032 | E14: =+'APPENDIX 15'!E14+'APPENDIX 16'!E14 -> 11877032 | F14: =+'APPENDIX 15'!F14+'APPENDIX 16'!F14 -> 0 | G14: =+'APPENDIX 15'!G14+'APPENDIX 16'!G14 -> 3479171.7 | H14: =+'APPENDIX 15'!H14+'APPENDIX 16'!H14 -> 3479171.7 | I14: =+'APPENDIX 15'!I14+'APPENDIX 16'!I14 -> 0 | J14: =+'APPENDIX 15'!J14+'APPENDIX 16'!J14 -> 0 | ... Q14: =+'APPENDIX 15'!Q14+'APPENDIX 16'!Q14 -> 56770410
B15: =+'APPENDIX 15'!B15 -> GEMINIA LIFE INSURANCE COMPANY | C15: =+'APPENDIX 15'!C15+'APPENDIX 16'!C15 -> 872653.45 | D15: =+'APPENDIX 15'!D15+'APPENDIX 16'!D15 -> 760125.32 | E15: =+'APPENDIX 15'!E15+'APPENDIX 16'!E15 -> 760125.32 | F15: =+'APPENDIX 15'!F15+'APPENDIX 16'!F15 -> 0 | G15: =+'APPENDIX 15'!G15+'APPENDIX 16'!G15 -> 0 | H15: =+'APPENDIX 15'!H15+'APPENDIX 16'!H15 -> 0 | I15: =+'APPENDIX 15'!I15+'APPENDIX 16'!I15 -> 0 | J15: =+'APPENDIX 15'!J15+'APPENDIX 16'!J15 -> 0 | ... Q15: =+'APPENDIX 15'!Q15+'APPENDIX 16'!Q15 -> 721727.81
B16: =+'APPENDIX 15'!B16 -> ICEA LION LIFE ASSURANCE | C16: =+'APPENDIX 15'!C16+'APPENDIX 16'!C16 -> 1.2949237e+08 | D16: =+'APPENDIX 15'!D16+'APPENDIX 16'!D16 -> 19600057 | E16: =+'APPENDIX 15'!E16+'APPENDIX 16'!E16 -> 19600057 | F16: =+'APPENDIX 15'!F16+'APPENDIX 16'!F16 -> 0 | G16: =+'APPENDIX 15'!G16+'APPENDIX 16'!G16 -> 14878975 | H16: =+'APPENDIX 15'!H16+'APPENDIX 16'!H16 -> 14878975 | I16: =+'APPENDIX 15'!I16+'APPENDIX 16'!I16 -> 0 | J16: =+'APPENDIX 15'!J16+'APPENDIX 16'!J16 -> 0 | ... Q16: =+'APPENDIX 15'!Q16+'APPENDIX 16'!Q16 -> 1.523258e+08
B17: =+'APPENDIX 15'!B17 -> JUBILEE LIFE INSURANCE | C17: =+'APPENDIX 15'!C17+'APPENDIX 16'!C17 -> 1.0755333e+08 | D17: =+'APPENDIX 15'!D17+'APPENDIX 16'!D17 -> 20175581 | E17: =+'APPENDIX 15'!E17+'APPENDIX 16'!E17 -> 20175581 | F17: =+'APPENDIX 15'!F17+'APPENDIX 16'!F17 -> 0 | G17: =+'APPENDIX 15'!G17+'APPENDIX 16'!G17 -> 11310008 | H17: =+'APPENDIX 15'!H17+'APPENDIX 16'!H17 -> 11310008 | I17: =+'APPENDIX 15'!I17+'APPENDIX 16'!I17 -> 0 | J17: =+'APPENDIX 15'!J17+'APPENDIX 16'!J17 -> 0 | ... Q17: =+'APPENDIX 15'!Q17+'APPENDIX 16'!Q17 -> 1.3100509e+08
... B29: =+'APPENDIX 15'!B29 -> THE MONARCH INSURANCE | C29: =+'APPENDIX 15'!C29+'APPENDIX 16'!C29 -> 0 | D29: =+'APPENDIX 15'!D29+'APPENDIX 16'!D29 -> 0 | E29: =+'APPENDIX 15'!E29+'APPENDIX 16'!E29 -> 0 | F29: =+'APPENDIX 15'!F29+'APPENDIX 16'!F29 -> 0 | G29: =+'APPENDIX 15'!G29+'APPENDIX 16'!G29 -> 0 | H29: =+'APPENDIX 15'!H29+'APPENDIX 16'!H29 -> 0 | I29: =+'APPENDIX 15'!I29+'APPENDIX 16'!I29 -> 0 | J29: =+'APPENDIX 15'!J29+'APPENDIX 16'!J29 -> 0 | ... Q29: =+'APPENDIX 15'!Q29+'APPENDIX 16'!Q29 -> 0
B30: TOTAL | C30: =SUM(C6:C29) -> 4.9991205e+08 | D30: =SUM(D6:D29) -> 1.047226e+08 | E30: =SUM(E6:E29) -> 1.047226e+08 | F30: =SUM(F6:F29) -> 0 | G30: =SUM(G6:G29) -> 65233865 | H30: =SUM(H6:H29) -> 65233865 | I30: =SUM(I6:I29) -> 0 | J30: =SUM(J6:J29) -> 0 | ... Q30: =SUM(Q6:Q29) -> 6.066706e+08
B31: REINSURERS
B32: =+'APPENDIX 15'!B32 -> CONTINENTAL REINSURANCE | C32: =+'APPENDIX 15'!C32+'APPENDIX 16'!C32 -> 0 | D32: =+'APPENDIX 15'!D32+'APPENDIX 16'!D32 -> 0 | E32: =+'APPENDIX 15'!E32+'APPENDIX 16'!E32 -> 0 | F32: =+'APPENDIX 15'!F32+'APPENDIX 16'!F32 -> 0 | G32: =+'APPENDIX 15'!G32+'APPENDIX 16'!G32 -> 0 | H32: =+'APPENDIX 15'!H32+'APPENDIX 16'!H32 -> 0 | I32: =+'APPENDIX 15'!I32+'APPENDIX 16'!I32 -> 0 | J32: =+'APPENDIX 15'!J32+'APPENDIX 16'!J32 -> 0 | ... Q32: =+'APPENDIX 15'!Q32+'APPENDIX 16'!Q32 -> 0
B33: =+'APPENDIX 15'!B33 -> EAST AFRICA REINSURANCE | C33: =+'APPENDIX 15'!C33+'APPENDIX 16'!C33 -> 0 | D33: =+'APPENDIX 15'!D33+'APPENDIX 16'!D33 -> 0 | E33: =+'APPENDIX 15'!E33+'APPENDIX 16'!E33 -> 0 | F33: =+'APPENDIX 15'!F33+'APPENDIX 16'!F33 -> 0 | G33: =+'APPENDIX 15'!G33+'APPENDIX 16'!G33 -> 0 | H33: =+'APPENDIX 15'!H33+'APPENDIX 16'!H33 -> 0 | I33: =+'APPENDIX 15'!I33+'APPENDIX 16'!I33 -> 0 | J33: =+'APPENDIX 15'!J33+'APPENDIX 16'!J33 -> 0 | ... Q33: =+'APPENDIX 15'!Q33+'APPENDIX 16'!Q33 -> 0
B34: =+'APPENDIX 15'!B34 -> KENYA REINSURANCE CORPORATION | C34: =+'APPENDIX 15'!C34+'APPENDIX 16'!C34 -> 0 | D34: =+'APPENDIX 15'!D34+'APPENDIX 16'!D34 -> 0 | E34: =+'APPENDIX 15'!E34+'APPENDIX 16'!E34 -> 0 | F34: =+'APPENDIX 15'!F34+'APPENDIX 16'!F34 -> 0 | G34: =+'APPENDIX 15'!G34+'APPENDIX 16'!G34 -> 0 | H34: =+'APPENDIX 15'!H34+'APPENDIX 16'!H34 -> 0 | I34: =+'APPENDIX 15'!I34+'APPENDIX 16'!I34 -> 0 | J34: =+'APPENDIX 15'!J34+'APPENDIX 16'!J34 -> 0 | ... Q34: =+'APPENDIX 15'!Q34+'APPENDIX 16'!Q34 -> 0
B35: TOTAL | C35: =SUM(C32:C34) -> 0 | D35: =SUM(D32:D34) -> 0 | E35: =SUM(E32:E34) -> 0 | F35: =SUM(F32:F34) -> 0 | G35: =SUM(G32:G34) -> 0 | H35: =SUM(H32:H34) -> 0 | I35: =SUM(I32:I34) -> 0 | J35: =SUM(J32:J34) -> 0 | ... Q35: =SUM(Q32:Q34) -> 0
B36: Amounts in Thousand Shillings

Sheet APPENDIX 15
B3: =_xlfn.CONCAT('Table of Contents'!B27,": ",'Table of Contents'!C27) -> APPENDIX 15: SUMMARY OF PERSONAL PENSIONS BUSINESS REVENUE ACCOUNTS FOR THE PERIOD ENDED 31.12.2025
B4: Company | C4: Life Fund BF | D4: Gross Premium | E4: Net Premium | F4: Other (Fee) Income | G4: Total Benefits | H4: Claims | I4: Surrenders_x000D_ | J4: Bonuses Paid | K4: Annuities Paid | L4: Net Commisions | M4: Expense of Management | N4: Investment Income | O4: Investment Expenses | P4: Transfer To (From) P & L | Q4: Life Fund CF
B5: INSURERS
B6: ABSA LIFE ASSURANCE | C6: 0 | D6: 0 | E6: 0 | F6: 0 | G6: 0 | H6: 0 | I6: 0 | J6: 0 | K6: 0 | L6: 0 | M6: 0 | N6: 0 | O6: 0 | P6: 0 | Q6: 0
B7: APA LIFE ASSURANCE COMPANY | C7: 0 | D7: 130267.85 | E7: 130267.85 | F7: 0 | G7: 109816.94 | H7: 109816.94 | I7: 0 | J7: 0 | K7: 0 | L7: 4635.313 | M7: 6440.596 | N7: 102449.04 | O7: 1892.294 | P7: 0 | Q7: 109931.75
B8: BRITAM LIFE ASSURANCE | C8: 33293702 | D8: 6139589.5 | E8: 6139589.5 | F8: 0 | G8: 4803545.2 | H8: 4803545.2 | I8: 0 | J8: 0 | K8: 0 | L8: 46799.041 | M8: 471582.52 | N8: 5157554.8 | O8: 12212.688 | P8: 0 | Q8: 39256706
B9: CANNON LIFE ASSURANCE (K) LIMITED | C9: 0 | D9: 0 | E9: 0 | F9: 0 | G9: 0 | H9: 0 | I9: 0 | J9: 0 | K9: 0 | L9: 0 | M9: 0 | N9: 0 | O9: 0 | P9: 0 | Q9: 0
B10: CAPEX LIFE ASSURANCE COMPANY | C10: 0 | D10: 41254.695 | E10: 41254.695 | F10: 0 | G10: 7815.967 | H10: 7815.967 | I10: 0 | J10: 0 | K10: 0 | L10: 0 | M10: 12091.782 | N10: 1117.0971 | O10: 0 | P10: 0 | Q10: 22464.043
B11: CIC LIFE ASSURANCE COMPANY | C11: 0 | D11: 0 | E11: 0 | F11: 0 | G11: 0 | H11: 0 | I11: 0 | J11: 0 | K11: 0 | L11: 0 | M11: 0 | N11: 0 | O11: 0 | P11: 0 | Q11: 0
B12: CORPORATE INSURANCE COMPANY | C12: 0 | D12: 0 | E12: 0 | F12: 0 | G12: 0 | H12: 0 | I12: 0 | J12: 0 | K12: 0 | L12: 0 | M12: 0 | N12: 0 | O12: 0 | P12: 0 | Q12: 0
B13: EQUITY LIFE ASSURANCE | C13: 374887.39 | D13: 332020.42 | E13: 332020.42 | F13: 0 | G13: 48756.319 | H13: 48756.319 | I13: 0 | J13: 0 | K13: 0 | L13: 0 | M13: 0 | N13: 0 | O13: 0 | P13: 0 | Q13: 658151.49
B14: GA LIFE ASSURANCE COMPANY | C14: 5859870.8 | D14: 1903228.5 | E14: 1903228.5 | F14: 0 | G14: 546825.87 | H14: 546825.87 | I14: 0 | J14: 0 | K14: 0 | L14: 12319.953 | M14: 19742.045 | N14: 1013629.6 | O14: 0 | P14: 0 | Q14: 8197841
B15: GEMINIA LIFE INSURANCE COMPANY | C15: 129029.75 | D15: 106143.11 | E15: 106143.11 | F15: 0 | G15: 0 | H15: 0 | I15: 0 | J15: 0 | K15: 0 | L15: -2534.524 | M15: 0 | N15: 0 | O15: 0 | P15: 129989.93 | Q15: 107717.46
B16: ICEA LION LIFE ASSURANCE | C16: 48450961 | D16: 8823772.1 | E16: 8823772.1 | F16: 0 | G16: 5674559.2 | H16: 5674559.2 | I16: 0 | J16: 0 | K16: 0 | L16: 106289.75 | M16: 315540.76 | N16: 7283268.6 | O16: 0 | P16: 0 | Q16: 58461612
B17: JUBILEE LIFE INSURANCE | C17: 10414912 | D17: 3497687.6 | E17: 3497687.6 | F17: 0 | G17: 0 | H17: 0 | I17: 0 | J17: 0 | K17: 0 | L17: 0 | M17: 67061.477 | N17: 0 | O17: 0 | P17: 0 | Q17: 13845538
... B29: THE MONARCH INSURANCE | C29: 0 | D29: 0 | E29: 0 | F29: 0 | G29: 0 | H29: 0 | I29: 0 | J29: 0 | K29: 0 | L29: 0 | M29: 0 | N29: 0 | O29: 0 | P29: 0 | Q29: 0
B30: TOTAL | C30: =SUM(C6:C29) -> 1.0393052e+08 | D30: =SUM(D6:D29) -> 24976102 | E30: =SUM(E6:E29) -> 24976102 | F30: =SUM(F6:F29) -> 0 | G30: =SUM(G6:G29) -> 13907592 | H30: =SUM(H6:H29) -> 13907592 | I30: =SUM(I6:I29) -> 0 | J30: =SUM(J6:J29) -> 0 | ... Q30: =SUM(Q6:Q29) -> 1.2851938e+08
B31: REINSURERS
B32: CONTINENTAL REINSURANCE | C32: 0 | D32: 0 | E32: 0 | F32: 0 | G32: 0 | H32: 0 | I32: 0 | J32: 0 | K32: 0 | L32: 0 | M32: 0 | N32: 0 | O32: 0 | P32: 0 | Q32: 0
B33: EAST AFRICA REINSURANCE | C33: 0 | D33: 0 | E33: 0 | F33: 0 | G33: 0 | H33: 0 | I33: 0 | J33: 0 | K33: 0 | L33: 0 | M33: 0 | N33: 0 | O33: 0 | P33: 0 | Q33: 0
B34: KENYA REINSURANCE CORPORATION | C34: 0 | D34: 0 | E34: 0 | F34: 0 | G34: 0 | H34: 0 | I34: 0 | J34: 0 | K34: 0 | L34: 0 | M34: 0 | N34: 0 | O34: 0 | P34: 0 | Q34: 0
B35: TOTAL | C35: =SUM(C32:C34) -> 0 | D35: =SUM(D32:D34) -> 0 | E35: =SUM(E32:E34) -> 0 | F35: =SUM(F32:F34) -> 0 | G35: =SUM(G32:G34) -> 0 | H35: =SUM(H32:H34) -> 0 | I35: =SUM(I32:I34) -> 0 | J35: =SUM(J32:J34) -> 0 | ... Q35: =SUM(Q32:Q34) -> 0
B36: Amounts in Thousand Shillings

Sheet APPENDIX 16
B3: =_xlfn.CONCAT('Table of Contents'!B28,": ",'Table of Contents'!C28) -> APPENDIX 16: SUMMARY OF DEPOSIT ADMINISTRATION BUSINESS REVENUE ACCOUNTS FOR THE PERIOD ENDED 31.12.2025
B4: Company | C4: Life Fund BF | D4: Gross Premium | E4: Net Premium | F4: Other (Fee) Income | G4: Total Benefits | H4: Claims | I4: Surrenders_x000D_ | J4: Bonuses Paid | K4: Annuities Paid | L4: Net Commisions | M4: Expense of Management | N4: Investment Income | O4: Investment Expenses | P4: Transfer To (From) P & L | Q4: Life Fund CF
B5: INSURERS
B6: ABSA LIFE ASSURANCE | C6: 0 | D6: 0 | E6: 0 | F6: 0 | G6: 0 | H6: 0 | I6: 0 | J6: 0 | K6: 0 | L6: 0 | M6: 0 | N6: 0 | O6: 0 | P6: 0 | Q6: 0
B7: APA LIFE ASSURANCE COMPANY | C7: 9733226.8 | D7: 1949836.4 | E7: 1949836.4 | F7: 0 | G7: 1363540.8 | H7: 1363540.8 | I7: 0 | J7: 0 | K7: 0 | L7: 69380.924 | M7: 97525.636 | N7: 1533583.4 | O7: 28326.179 | P7: 0 | Q7: 11657873
B8: BRITAM LIFE ASSURANCE | C8: 44336570 | D8: 8836842.7 | E8: 8836842.7 | F8: 0 | G8: 15474431 | H8: 15474431 | I8: 0 | J8: 0 | K8: 0 | L8: 67358.88 | M8: 678759.01 | N8: 7477306.4 | O8: 17577.988 | P8: 0 | Q8: 44412592
B9: CANNON LIFE ASSURANCE (K) LIMITED | C9: 0 | D9: 0 | E9: 0 | F9: 0 | G9: 0 | H9: 0 | I9: 0 | J9: 0 | K9: 0 | L9: 0 | M9: 0 | N9: 0 | O9: 0 | P9: 0 | Q9: 0
B10: CAPEX LIFE ASSURANCE COMPANY | C10: 0 | D10: 0 | E10: 0 | F10: 0 | G10: 0 | H10: 0 | I10: 0 | J10: 0 | K10: 0 | L10: 0 | M10: 0 | N10: 0 | O10: 0 | P10: 0 | Q10: 0
B11: CIC LIFE ASSURANCE COMPANY | C11: 13492770 | D11: 3353751.3 | E11: 3353751.3 | F11: 0 | G11: 0 | H11: 0 | I11: 0 | J11: 0 | K11: 0 | L11: 67977.144 | M11: 133083.59 | N11: 272041.57 | O11: 0 | P11: 0 | Q11: 16917502
B12: CORPORATE INSURANCE COMPANY | C12: 0 | D12: 0 | E12: 0 | F12: 0 | G12: 0 | H12: 0 | I12: 0 | J12: 0 | K12: 0 | L12: 0 | M12: 0 | N12: 0 | O12: 0 | P12: 0 | Q12: 0
B13: EQUITY LIFE ASSURANCE | C13: 13454089 | D13: 2461209.1 | E13: 2461209.1 | F13: 0 | G13: 1597080.2 | H13: 1597080.2 | I13: 0 | J13: 0 | K13: 0 | L13: 0 | M13: 6732.9703 | N13: 2606485.4 | O13: 266214.97 | P13: 0 | Q13: 16651756
B14: GA LIFE ASSURANCE COMPANY | C14: 35579878 | D14: 9973803.1 | E14: 9973803.1 | F14: 0 | G14: 2932345.8 | H14: 2932345.8 | I14: 0 | J14: 0 | K14: 0 | L14: 48686.568 | M14: 119179.16 | N14: 6119098.8 | O14: 0 | P14: 0 | Q14: 48572569
B15: GEMINIA LIFE INSURANCE COMPANY | C15: 743623.7 | D15: 653982.21 | E15: 653982.21 | F15: 0 | G15: 0 | H15: 0 | I15: 0 | J15: 0 | K15: 0 | L15: 0 | M15: 40027.95 | N15: 0 | O15: 0 | P15: 743567.6 | Q15: 614010.36
B16: ICEA LION LIFE ASSURANCE | C16: 81041405 | D16: 10776285 | E16: 10776285 | F16: 0 | G16: 9204415.4 | H16: 9204415.4 | I16: 0 | J16: 0 | K16: 0 | L16: 262924.65 | M16: 546665.23 | N16: 12640506 | O16: 0 | P16: 580000 | Q16: 93864192
B17: JUBILEE LIFE INSURANCE | C17: 97138413 | D17: 16677893 | E17: 16677893 | F17: 0 | G17: 11310008 | H17: 11310008 | I17: 0 | J17: 0 | K17: 0 | L17: 284612.89 | M17: 518679.03 | N17: 15567674 | O17: 111131.88 | P17: 0 | Q17: 1.1715955e+08
... B29: THE MONARCH INSURANCE | C29: 0 | D29: 0 | E29: 0 | F29: 0 | G29: 0 | H29: 0 | I29: 0 | J29: 0 | K29: 0 | L29: 0 | M29: 0 | N29: 0 | O29: 0 | P29: 0 | Q29: 0
B30: TOTAL | C30: =SUM(C6:C29) -> 3.9598152e+08 | D30: =SUM(D6:D29) -> 79746501 | E30: =SUM(E6:E29) -> 79746501 | F30: =SUM(F6:F29) -> 0 | G30: =SUM(G6:G29) -> 51326273 | H30: =SUM(H6:H29) -> 51326273 | I30: =SUM(I6:I29) -> 0 | J30: =SUM(J6:J29) -> 0 | ... Q30: =SUM(Q6:Q29) -> 4.7815122e+08
B31: REINSURERS
B32: CONTINENTAL REINSURANCE | C32: 0 | D32: 0 | E32: 0 | F32: 0 | G32: 0 | H32: 0 | I32: 0 | J32: 0 | K32: 0 | L32: 0 | M32: 0 | N32: 0 | O32: 0 | P32: 0 | Q32: 0
B33: EAST AFRICA REINSURANCE | C33: 0 | D33: 0 | E33: 0 | F33: 0 | G33: 0 | H33: 0 | I33: 0 | J33: 0 | K33: 0 | L33: 0 | M33: 0 | N33: 0 | O33: 0 | P33: 0 | Q33: 0
B34: KENYA REINSURANCE CORPORATION | C34: 0 | D34: 0 | E34: 0 | F34: 0 | G34: 0 | H34: 0 | I34: 0 | J34: 0 | K34: 0 | L34: 0 | M34: 0 | N34: 0 | O34: 0 | P34: 0 | Q34: 0
B35: TOTAL | C35: =SUM(C32:C34) -> 0 | D35: =SUM(D32:D34) -> 0 | E35: =SUM(E32:E34) -> 0 | F35: =SUM(F32:F34) -> 0 | G35: =SUM(G32:G34) -> 0 | H35: =SUM(H32:H34) -> 0 | I35: =SUM(I32:I34) -> 0 | J35: =SUM(J32:J34) -> 0 | ... Q35: =SUM(Q32:Q34) -> 0
B36: Amounts in Thousand Shillings

Sheet APPENDIX 17
B3: =_xlfn.CONCAT('Table of Contents'!B29,": ",'Table of Contents'!C29) -> APPENDIX 17: SUMMARY OF COMBINED LONG TERM BUSINESS REVENUE ACCOUNTS FOR THE PERIOD ENDED 31.12.2025
B4: Company | C4: Life Fund BF | D4: Gross Premium | E4: Net Premium | F4: Other (Fee) Income | G4: Total Benefits | H4: Claims | I4: Surrenders_x000D_ | J4: Bonuses Paid | K4: Annuities Paid | L4: Net Commisions | M4: Expense of Management | N4: Investment Income | O4: Investment Expenses | P4: Transfer To (From) P & L | Q4: Life Fund CF
B5: INSURERS
B6: ABSA LIFE ASSURANCE | C6: 12993436 | D6: 10027959 | E6: 8542172.3 | F6: 0 | G6: 3608127.5 | H6: 3608127.5 | I6: 0 | J6: 0 | K6: 0 | L6: 1315786.3 | M6: 1204569.9 | N6: 2358873.5 | O6: 0 | P6: 0 | Q6: 17765999
B7: APA LIFE ASSURANCE COMPANY | C7: 15210032 | D7: 14523000 | E7: 12780903 | F7: 0 | G7: 3069475.4 | H7: 3069475.4 | I7: 0 | J7: 0 | K7: 0 | L7: 1085529.3 | M7: 566534.46 | N7: 3036999.7 | O7: 61225.185 | P7: 0 | Q7: 26245170
B8: BRITAM LIFE ASSURANCE | C8: 1.5545264e+08 | D8: 53136661 | E8: 48723446 | F8: -2600.6927 | G8: 36735202 | H8: 36735202 | I8: 0 | J8: 0 | K8: 0 | L8: 1767067.4 | M8: 4668273.9 | N8: 28401985 | O8: 379810.17 | P8: 0 | Q8: 1.8902511e+08
B9: CANNON LIFE ASSURANCE (K) LIMITED | C9: 820846.59 | D9: 540547 | E9: 371360.28 | F9: 0 | G9: 274040.15 | H9: 274040.15 | I9: 0 | J9: 0 | K9: 0 | L9: 24667.326 | M9: 221249.17 | N9: 107328.49 | O9: 0 | P9: 0 | Q9: 779578.71
B10: CAPEX LIFE ASSURANCE COMPANY | C10: 1260505.5 | D10: 1357699.3 | E10: 1210794.6 | F10: 0 | G10: 852844.56 | H10: 852844.56 | I10: 0 | J10: 0 | K10: 0 | L10: 163857.66 | M10: 397699.13 | N10: 36741.364 | O10: 0 | P10: 0 | Q10: 1093640.1
B11: CIC LIFE ASSURANCE COMPANY | C11: 28739369 | D11: 13269685 | E11: 13056509 | F11: 0 | G11: 2236476.8 | H11: 2236476.8 | I11: 0 | J11: 0 | K11: 0 | L11: 799886.15 | M11: 2198534.6 | N11: 3185718.3 | O11: 0 | P11: 0 | Q11: 39746698
B12: CORPORATE INSURANCE COMPANY | C12: 63014.581 | D12: 34017.644 | E12: 34017.644 | F12: 0 | G12: 141310.88 | H12: 141310.88 | I12: 0 | J12: 0 | K12: 0 | L12: 0 | M12: 6585.4459 | N12: 8082.879 | O12: 0 | P12: 0 | Q12: -42781.22
B13: EQUITY LIFE ASSURANCE | C13: 21017255 | D13: 6099670.6 | E13: 5791624.3 | F13: 0 | G13: 2379892 | H13: 2379892 | I13: 0 | J13: 0 | K13: 0 | L13: 172985.73 | M13: 673297.03 | N13: 3813696.1 | O13: 266214.97 | P13: 0 | Q13: 27130186
B14: GA LIFE ASSURANCE COMPANY | C14: 45563227 | D14: 13015363 | E14: 12935255 | F14: 0 | G14: 3640095.2 | H14: 3640095.2 | I14: 0 | J14: 0 | K14: 0 | L14: 40773.893 | M14: 159415.89 | N14: 8150692 | O14: 0 | P14: 0 | Q14: 62808889
B15: GEMINIA LIFE INSURANCE COMPANY | C15: 2778646.6 | D15: 2149038.7 | E15: 2017560 | F15: 0 | G15: 457082.37 | H15: 457082.37 | I15: 0 | J15: 0 | K15: 0 | L15: 64861.144 | M15: 298031.81 | N15: 6146.895 | O15: 0 | P15: 873557.53 | Q15: 3108820.7
B16: ICEA LION LIFE ASSURANCE | C16: 1.7554155e+08 | D16: 32814963 | E16: 32480864 | F16: 0 | G16: 21592800 | H16: 18226252 | I16: 771123.34 | J16: 0 | K16: 2595424.9 | L16: 1922283.4 | M16: 2702253.6 | N16: 28730284 | O16: 0 | P16: 1450000 | Q16: 2.0908536e+08
B17: JUBILEE LIFE INSURANCE | C17: 1.3472815e+08 | D17: 30654986 | E17: 30067908 | F17: 0 | G17: 18156549 | H17: 18156549 | I17: 0 | J17: 0 | K17: 0 | L17: 1200060.8 | M17: 1756438.1 | N17: 20075402 | O17: 142040.69 | P17: 0 | Q17: 1.6361637e+08
... B29: THE MONARCH INSURANCE | C29: 0 | D29: 0 | E29: 0 | F29: 0 | G29: 0 | H29: 0 | I29: 0 | J29: 0 | K29: 0 | L29: 0 | M29: 0 | N29: 0 | O29: 0 | P29: 0 | Q29: 0
B30: TOTAL | C30: =SUM(C6:C29) -> 8.0552328e+08 | D30: =SUM(D6:D29) -> 2.3538985e+08 | E30: =SUM(E6:E29) -> 2.2194164e+08 | F30: =SUM(F6:F29) -> -217370.56 | G30: =SUM(G6:G29) -> 1.2803663e+08 | H30: =SUM(H6:H29) -> 1.236693e+08 | I30: =SUM(I6:I29) -> 1746634.6 | J30: =SUM(J6:J29) -> 0 | ... Q30: =SUM(Q6:Q29) -> 9.8697169e+08
B31: REINSURERS
B32: CONTINENTAL REINSURANCE | C32: 0 | D32: 36252.815 | E32: 30895.605 | F32: 0 | G32: 85203.153 | H32: 85203.153 | I32: 0 | J32: 0 | K32: 0 | L32: 8823.21 | M32: 4183.395 | N32: 68066.016 | O32: 0 | P32: 0 | Q32: 751.863
B33: EAST AFRICA REINSURANCE | C33: 1179335.9 | D33: 1334886.2 | E33: 1057391.2 | F33: 0 | G33: 476510.33 | H33: 476510.33 | I33: 0 | J33: 0 | K33: 0 | L33: 263723.8 | M33: 187794.16 | N33: 267767.59 | O33: 11499.611 | P33: 0 | Q33: 1564966.8
B34: KENYA REINSURANCE CORPORATION | C34: 8381895 | D34: 2891363.4 | E34: 2761701 | F34: 0 | G34: 1707029.3 | H34: 1707029.3 | I34: 0 | J34: 0 | K34: 0 | L34: 989400.51 | M34: 102691.13 | N34: 102691.13 | O34: 0 | P34: 0 | Q34: 8447166.2
B35: TOTAL | C35: =SUM(C32:C34) -> 9561230.9 | D35: =SUM(D32:D34) -> 4262502.4 | E35: =SUM(E32:E34) -> 3849987.8 | F35: =SUM(F32:F34) -> 0 | G35: =SUM(G32:G34) -> 2268742.8 | H35: =SUM(H32:H34) -> 2268742.8 | I35: =SUM(I32:I34) -> 0 | J35: =SUM(J32:J34) -> 0 | ... Q35: =SUM(Q32:Q34) -> 10012885
B36: Amounts in Thousand Shillings

Sheet APPENDIX 18
B3: =_xlfn.CONCAT('Table of Contents'!B30,": ",'Table of Contents'!C30) -> APPENDIX 18: SUMMARY OF GROSS PREMIUM INCOME UNDER GENERAL INSURANCE BUSINESS FOR THE PERIOD ENDED 31.12.2025
B4: Company | C4: Aviation | D4: Engineering | E4: Fire Domestic | F4: Fire Industrial | G4: Liability | H4: Marine | I4: Motor Private | J4: Motor Commercial | K4: Motor Commercial PSV | L4: Personal Accident | M4: Theft | N4: Workmens' Compensation | O4: Medical | P4: Miscellaneous | Q4: Total_x000D_ | R4: Market Share (%)
B5: INSURERS
B6: =GDP!B6 -> AAR INSURANCE KENYA | C6: =GDP!C6+INWARD!C6 -> 0 | D6: =GDP!D6+INWARD!D6 -> 4919.0489 | E6: =GDP!E6+INWARD!E6 -> 2218.0253 | F6: =GDP!F6+INWARD!F6 -> 16028.406 | G6: =GDP!G6+INWARD!G6 -> 33955.925 | H6: =GDP!H6+INWARD!H6 -> 3504.7488 | I6: =GDP!I6+INWARD!I6 -> 3995.7346 | J6: =GDP!J6+INWARD!J6 -> 0 | ... Q6: =GDP!Q6+INWARD!Q6 -> 12772095 | R6: =(Q6/$Q$43)*100 -> 5.6223217
B7: =GDP!B7 -> AFRICAN MERCHANT ASSURANCE | C7: =GDP!C7+INWARD!C7 -> 0 | D7: =GDP!D7+INWARD!D7 -> 83212.567 | E7: =GDP!E7+INWARD!E7 -> 1054.0713 | F7: =GDP!F7+INWARD!F7 -> 110584.03 | G7: =GDP!G7+INWARD!G7 -> 22966.404 | H7: =GDP!H7+INWARD!H7 -> 5569.8685 | I7: =GDP!I7+INWARD!I7 -> 464420.19 | J7: =GDP!J7+INWARD!J7 -> 451194.66 | ... Q7: =GDP!Q7+INWARD!Q7 -> 3850884.7 | R7: =(Q7/$Q$43)*100 -> 1.6951732
B8: =GDP!B8 -> APA INSURANCE LIMITED | C8: =GDP!C8+INWARD!C8 -> 459879.14 | D8: =GDP!D8+INWARD!D8 -> 343501.02 | E8: =GDP!E8+INWARD!E8 -> 135709.81 | F8: =GDP!F8+INWARD!F8 -> 2327052.2 | G8: =GDP!G8+INWARD!G8 -> 323706.8 | H8: =GDP!H8+INWARD!H8 -> 324080.24 | I8: =GDP!I8+INWARD!I8 -> 3077319.1 | J8: =GDP!J8+INWARD!J8 -> 2393125.3 | ... Q8: =GDP!Q8+INWARD!Q8 -> 19381234 | R8: =(Q8/$Q$43)*100 -> 8.5316884
B9: =GDP!B9 -> BRITAM GENERAL INSURANCE | C9: =GDP!C9+INWARD!C9 -> 140103.25 | D9: =GDP!D9+INWARD!D9 -> 540870.13 | E9: =GDP!E9+INWARD!E9 -> 134901.87 | F9: =GDP!F9+INWARD!F9 -> 1668427.7 | G9: =GDP!G9+INWARD!G9 -> 533660.03 | H9: =GDP!H9+INWARD!H9 -> 485920.37 | I9: =GDP!I9+INWARD!I9 -> 1609579.7 | J9: =GDP!J9+INWARD!J9 -> 710048.58 | ... Q9: =GDP!Q9+INWARD!Q9 -> 14944763 | R9: =(Q9/$Q$43)*100 -> 6.5787381
B10: =GDP!B10 -> BUPA GLOBAL INSURANCE | C10: =GDP!C10+INWARD!C10 -> 0 | D10: =GDP!D10+INWARD!D10 -> 0 | E10: =GDP!E10+INWARD!E10 -> 0 | F10: =GDP!F10+INWARD!F10 -> 0 | G10: =GDP!G10+INWARD!G10 -> 0 | H10: =GDP!H10+INWARD!H10 -> 0 | I10: =GDP!I10+INWARD!I10 -> 0 | J10: =GDP!J10+INWARD!J10 -> 0 | ... Q10: =GDP!Q10+INWARD!Q10 -> 5329053.5 | R10: =(Q10/$Q$43)*100 -> 2.3458684
B11: =GDP!B11 -> CANNON GENERAL INSURANCE | C11: =GDP!C11+INWARD!C11 -> 0 | D11: =GDP!D11+INWARD!D11 -> 112145.09 | E11: =GDP!E11+INWARD!E11 -> 15647.183 | F11: =GDP!F11+INWARD!F11 -> 157150.84 | G11: =GDP!G11+INWARD!G11 -> 31489.334 | H11: =GDP!H11+INWARD!H11 -> 59081.441 | I11: =GDP!I11+INWARD!I11 -> 1409622.8 | J11: =GDP!J11+INWARD!J11 -> 454316 | ... Q11: =GDP!Q11+INWARD!Q11 -> 2417007.2 | R11: =(Q11/$Q$43)*100 -> 1.0639752
B12: =GDP!B12 -> CIC GENERAL INSURANCE COMPANY | C12: =GDP!C12+INWARD!C12 -> 0 | D12: =GDP!D12+INWARD!D12 -> 344614.89 | E12: =GDP!E12+INWARD!E12 -> 119099.21 | F12: =GDP!F12+INWARD!F12 -> 770420.23 | G12: =GDP!G12+INWARD!G12 -> 163174.92 | H12: =GDP!H12+INWARD!H12 -> 124826.01 | I12: =GDP!I12+INWARD!I12 -> 3694704.9 | J12: =GDP!J12+INWARD!J12 -> 2919606.4 | ... Q12: =GDP!Q12+INWARD!Q12 -> 20641499 | R12: =(Q12/$Q$43)*100 -> 9.0864614
B13: =GDP!B13 -> CORPORATE INSURANCE COMPANY | C13: =GDP!C13+INWARD!C13 -> 0 | D13: =GDP!D13+INWARD!D13 -> 0 | E13: =GDP!E13+INWARD!E13 -> 0 | F13: =GDP!F13+INWARD!F13 -> 0 | G13: =GDP!G13+INWARD!G13 -> 0 | H13: =GDP!H13+INWARD!H13 -> 0 | I13: =GDP!I13+INWARD!I13 -> 0 | J13: =GDP!J13+INWARD!J13 -> 0 | ... Q13: =GDP!Q13+INWARD!Q13 -> 0 | R13: =(Q13/$Q$43)*100 -> 0
B14: =GDP!B14 -> DEFINITE ASSURANCE COMPANY | C14: =GDP!C14+INWARD!C14 -> 0 | D14: =GDP!D14+INWARD!D14 -> 1044.213 | E14: =GDP!E14+INWARD!E14 -> 546.365 | F14: =GDP!F14+INWARD!F14 -> 2162.55 | G14: =GDP!G14+INWARD!G14 -> 1342.623 | H14: =GDP!H14+INWARD!H14 -> 520.766 | I14: =GDP!I14+INWARD!I14 -> 245975.82 | J14: =GDP!J14+INWARD!J14 -> 190979.95 | ... Q14: =GDP!Q14+INWARD!Q14 -> 1148723.8 | R14: =(Q14/$Q$43)*100 -> 0.50567231
B15: =GDP!B15 -> DIRECTLINE ASSURANCE COMPANY | C15: =GDP!C15+INWARD!C15 -> 0 | D15: =GDP!D15+INWARD!D15 -> 0 | E15: =GDP!E15+INWARD!E15 -> 0 | F15: =GDP!F15+INWARD!F15 -> 0 | G15: =GDP!G15+INWARD!G15 -> 0 | H15: =GDP!H15+INWARD!H15 -> 0 | I15: =GDP!I15+INWARD!I15 -> 318486.41 | J15: =GDP!J15+INWARD!J15 -> 97887.567 | ... Q15: =GDP!Q15+INWARD!Q15 -> 2734058.5 | R15: =(Q15/$Q$43)*100 -> 1.2035423
B16: =GDP!B16 -> EQUITY GENERAL INSURANCE LIMITED | C16: =GDP!C16+INWARD!C16 -> 0 | D16: =GDP!D16+INWARD!D16 -> 29307.97 | E16: =GDP!E16+INWARD!E16 -> 1038.95 | F16: =GDP!F16+INWARD!F16 -> 58055.903 | G16: =GDP!G16+INWARD!G16 -> 46200.206 | H16: =GDP!H16+INWARD!H16 -> 245.297 | I16: =GDP!I16+INWARD!I16 -> 0 | J16: =GDP!J16+INWARD!J16 -> 0 | ... Q16: =GDP!Q16+INWARD!Q16 -> 1789049.5 | R16: =(Q16/$Q$43)*100 -> 0.78754599
B17: =GDP!B17 -> EQUITY HEALTH INSURANCE LIMITED | C17: =GDP!C17+INWARD!C17 -> 0 | D17: =GDP!D17+INWARD!D17 -> 0 | E17: =GDP!E17+INWARD!E17 -> 0 | F17: =GDP!F17+INWARD!F17 -> 0 | G17: =GDP!G17+INWARD!G17 -> 0 | H17: =GDP!H17+INWARD!H17 -> 0 | I17: =GDP!I17+INWARD!I17 -> 0 | J17: =GDP!J17+INWARD!J17 -> 0 | ... Q17: =GDP!Q17+INWARD!Q17 -> 19165.86 | R17: =(Q17/$Q$43)*100 -> 0.0084368798
... B42: =GDP!B42 -> TRIDENT INSURANCE COMPANY | C42: =GDP!C42+INWARD!C42 -> 0 | D42: =GDP!D42+INWARD!D42 -> 0 | E42: =GDP!E42+INWARD!E42 -> 0 | F42: =GDP!F42+INWARD!F42 -> 0 | G42: =GDP!G42+INWARD!G42 -> 0 | H42: =GDP!H42+INWARD!H42 -> 0 | I42: =GDP!I42+INWARD!I42 -> 0 | J42: =GDP!J42+INWARD!J42 -> 0 | ... Q42: =GDP!Q42+INWARD!Q42 -> 0 | R42: =(Q42/$Q$43)*100 -> 0
B43: TOTAL | C43: =SUM(C6:C42) -> 4674783.8 | D43: =SUM(D6:D42) -> 6469115 | E43: =SUM(E6:E42) -> 2097289.8 | F43: =SUM(F6:F42) -> 23216643 | G43: =SUM(G6:G42) -> 5475795.1 | H43: =SUM(H6:H42) -> 4801295.5 | I43: =SUM(I6:I42) -> 31764948 | J43: =SUM(J6:J42) -> 24022216 | ... Q43: =SUM(Q6:Q42) -> 2.2716763e+08 | R43: =(Q43/$Q$43)*100 -> 100
B44: REINSURERS
B45: =GDP!B45 -> CONTINENTAL REINSURANCE | C45: =GDP!C45+INWARD!C45 -> 28913.726 | D45: =GDP!D45+INWARD!D45 -> 548236.38 | E45: =GDP!E45+INWARD!E45 -> 491674.52 | F45: =GDP!F45+INWARD!F45 -> 1399381.3 | G45: =GDP!G45+INWARD!G45 -> 203538.26 | H45: =GDP!H45+INWARD!H45 -> 332507.85 | I45: =GDP!I45+INWARD!I45 -> 53307.64 | J45: =GDP!J45+INWARD!J45 -> 227769.01 | ... Q45: =GDP!Q45+INWARD!Q45 -> 5085076.1 | R45: =Q45/$Q$50*100 -> 15.673236
B46: =GDP!B46 -> EAST AFRICA REINSURANCE | C46: =GDP!C46+INWARD!C46 -> 6168.4786 | D46: =GDP!D46+INWARD!D46 -> 375480.58 | E46: =GDP!E46+INWARD!E46 -> 0 | F46: =GDP!F46+INWARD!F46 -> 1820870.4 | G46: =GDP!G46+INWARD!G46 -> 44230.077 | H46: =GDP!H46+INWARD!H46 -> 166325.1 | I46: =GDP!I46+INWARD!I46 -> 0 | J46: =GDP!J46+INWARD!J46 -> 250920.85 | ... Q46: =GDP!Q46+INWARD!Q46 -> 4558138.4 | R46: =Q46/$Q$50*100 -> 14.049107
B47: =GDP!B47 -> GHANA REINSURANCE COMPANY | C47: =GDP!C47+INWARD!C47 -> 5792.264 | D47: =GDP!D47+INWARD!D47 -> 273328.01 | E47: =GDP!E47+INWARD!E47 -> 274336.29 | F47: =GDP!F47+INWARD!F47 -> 2011799.4 | G47: =GDP!G47+INWARD!G47 -> 89533.519 | H47: =GDP!H47+INWARD!H47 -> 171271.14 | I47: =GDP!I47+INWARD!I47 -> 160510.32 | J47: =GDP!J47+INWARD!J47 -> 173886.18 | ... Q47: =GDP!Q47+INWARD!Q47 -> 4010943.9 | R47: =Q47/$Q$50*100 -> 12.362542
B48: =GDP!B48 -> KENYA REINSURANCE CORPORATION | C48: =GDP!C48+INWARD!C48 -> 108799.45 | D48: =GDP!D48+INWARD!D48 -> 1589695.7 | E48: =GDP!E48+INWARD!E48 -> 116497.29 | F48: =GDP!F48+INWARD!F48 -> 4631068 | G48: =GDP!G48+INWARD!G48 -> 153812.49 | H48: =GDP!H48+INWARD!H48 -> 761806.18 | I48: =GDP!I48+INWARD!I48 -> 13368.515 | J48: =GDP!J48+INWARD!J48 -> 437423.78 | ... Q48: =GDP!Q48+INWARD!Q48 -> 12837331 | R48: =Q48/$Q$50*100 -> 39.567257
B49: =GDP!B49 -> WAICA REINSURANCE KENYA LIMITED | C49: =GDP!C49+INWARD!C49 -> 56900.344 | D49: =GDP!D49+INWARD!D49 -> 928111.24 | E49: =GDP!E49+INWARD!E49 -> 0 | F49: =GDP!F49+INWARD!F49 -> 2837588.7 | G49: =GDP!G49+INWARD!G49 -> 172194.38 | H49: =GDP!H49+INWARD!H49 -> 231889.28 | I49: =GDP!I49+INWARD!I49 -> 89875.234 | J49: =GDP!J49+INWARD!J49 -> 110970.84 | ... Q49: =GDP!Q49+INWARD!Q49 -> 5952839.2 | R49: =Q49/$Q$50*100 -> 18.347858
B50: TOTAL | C50: =SUM(C45:C49) -> 206574.26 | D50: =SUM(D45:D49) -> 3714851.9 | E50: =SUM(E45:E49) -> 882508.1 | F50: =SUM(F45:F49) -> 12700708 | G50: =SUM(G45:G49) -> 663308.72 | H50: =SUM(H45:H49) -> 1663799.5 | I50: =SUM(I45:I49) -> 317061.71 | J50: =SUM(J45:J49) -> 1200970.6 | ... R50: =SUM(R45:R49) -> 100
B51: Amounts in Thousand Shillings

Sheet GDP
B3: =_xlfn.CONCAT("GDP: SUMMARY OF GROSS DIRECT PREMIUM UNDER GENERAL INSURANCE BUSINESS FOR THE PERIOD ENDED"," ",Details!F18) -> GDP: SUMMARY OF GROSS DIRECT PREMIUM UNDER GENERAL INSURANCE BUSINESS FOR THE PERIOD ENDED 31.12.2025
B4: Company | C4: Aviation | D4: Engineering | E4: Fire Domestic | F4: Fire Industrial | G4: Liability | H4: Marine | I4: Motor Private | J4: Motor Commercial | K4: Motor Commercial PSV | L4: Personal Accident | M4: Theft | N4: Workmens' Compensation | O4: Medical | P4: Miscellaneous | Q4: Total_x000D_
B5: INSURERS
B6: AAR INSURANCE KENYA | C6: 0 | D6: 4919.0489 | E6: 2218.0253 | F6: 16028.406 | G6: 33955.925 | H6: 3504.7488 | I6: 3995.7346 | J6: 0 | K6: 0 | L6: 25155.476 | M6: 11683.575 | N6: 110830.08 | O6: 12538971 | P6: 20832.531 | Q6: 12772095
B7: AFRICAN MERCHANT ASSURANCE | C7: 0 | D7: 83212.567 | E7: 1054.0713 | F7: 110584.03 | G7: 22966.404 | H7: 5569.8685 | I7: 464420.19 | J7: 451194.66 | K7: 2556769.7 | L7: 23359.313 | M7: 5965.0381 | N7: 89986.882 | O7: 0 | P7: 35801.911 | Q7: 3850884.7
B8: APA INSURANCE LIMITED | C8: 459879.14 | D8: 339166.93 | E8: 135709.81 | F8: 2293287.2 | G8: 323181.8 | H8: 320544.6 | I8: 3077319.1 | J8: 2393125.3 | K8: 0 | L8: 143785.86 | M8: 282201.18 | N8: 610280.73 | O8: 7901106.5 | P8: 561886.56 | Q8: 18841475
B9: BRITAM GENERAL INSURANCE | C9: 140103.25 | D9: 533330.75 | E9: 133389.66 | F9: 1617096.2 | G9: 533295.82 | H9: 485920.37 | I9: 1609579.7 | J9: 710048.58 | K9: 0 | L9: 206469.81 | M9: 594918.88 | N9: 568920.28 | O9: 7102393.3 | P9: 55369.444 | Q9: 14290836
B10: BUPA GLOBAL INSURANCE | C10: 0 | D10: 0 | E10: 0 | F10: 0 | G10: 0 | H10: 0 | I10: 0 | J10: 0 | K10: 0 | L10: 0 | M10: 0 | N10: 0 | O10: 5329053.5 | P10: 0 | Q10: 5329053.5
B11: CANNON GENERAL INSURANCE | C11: 0 | D11: 109322.86 | E11: 15647.183 | F11: 152024.66 | G11: 30357.858 | H11: 58558.106 | I11: 1408656.1 | J11: 452535.75 | K11: 0 | L11: 18215.454 | M11: 17584.676 | N11: 96358.957 | O11: 0 | P11: 44376.018 | Q11: 2403637.6
B12: CIC GENERAL INSURANCE COMPANY | C12: 0 | D12: 311836.74 | E12: 119099.21 | F12: 704291.12 | G12: 163012.93 | H12: 50673.622 | I12: 3694704.9 | J12: 2919606.4 | K12: 0 | L12: 249940.39 | M12: 709051.34 | N12: 683597.9 | O12: 10175094 | P12: 308636.65 | Q12: 20089546
B13: CORPORATE INSURANCE COMPANY | C13: 0 | D13: 0 | E13: 0 | F13: 0 | G13: 0 | H13: 0 | I13: 0 | J13: 0 | K13: 0 | L13: 0 | M13: 0 | N13: 0 | O13: 0 | P13: 0 | Q13: 0
B14: DEFINITE ASSURANCE COMPANY | C14: 0 | D14: 1044.213 | E14: 546.365 | F14: 2162.55 | G14: 1342.623 | H14: 520.766 | I14: 245975.82 | J14: 190979.95 | K14: 589306.33 | L14: 415.159 | M14: 3665.793 | N14: 904.639 | O14: 0 | P14: 111859.57 | Q14: 1148723.8
B15: DIRECTLINE ASSURANCE COMPANY | C15: 0 | D15: 0 | E15: 0 | F15: 0 | G15: 0 | H15: 0 | I15: 318486.41 | J15: 97887.567 | K15: 2317684.5 | L15: 0 | M15: 0 | N15: 0 | O15: 0 | P15: 0 | Q15: 2734058.5
B16: EQUITY GENERAL INSURANCE LIMITED | C16: 0 | D16: 29307.97 | E16: 1038.95 | F16: 58055.903 | G16: 46200.206 | H16: 245.297 | I16: 0 | J16: 0 | K16: 0 | L16: 1039.505 | M16: 449205.8 | N16: 6948.733 | O16: 1196907.2 | P16: 100 | Q16: 1789049.5
B17: EQUITY HEALTH INSURANCE LIMITED | C17: 0 | D17: 0 | E17: 0 | F17: 0 | G17: 0 | H17: 0 | I17: 0 | J17: 0 | K17: 0 | L17: 0 | M17: 0 | N17: 0 | O17: 19165.86 | P17: 0 | Q17: 19165.86
... B42: TRIDENT INSURANCE COMPANY | C42: 0 | D42: 0 | E42: 0 | F42: 0 | G42: 0 | H42: 0 | I42: 0 | J42: 0 | K42: 0 | L42: 0 | M42: 0 | N42: 0 | O42: 0 | P42: 0 | Q42: 0
B43: TOTAL | C43: =SUM(C6:C42) -> 4602892.9 | D43: =SUM(D6:D42) -> 6198870 | E43: =SUM(E6:E42) -> 2094987.5 | F43: =SUM(F6:F42) -> 22502546 | G43: =SUM(G6:G42) -> 5359959.8 | H43: =SUM(H6:H42) -> 4680628.2 | I43: =SUM(I6:I42) -> 31756233 | J43: =SUM(J6:J42) -> 24015176 | ... Q43: =SUM(Q6:Q42) -> 2.2323499e+08
B44: CONTINENTAL REINSURANCE
B45: CONTINENTAL REINSURANCE | C45: 0 | D45: 0 | E45: 0 | F45: 0 | G45: 0 | H45: 0 | I45: 0 | J45: 0 | K45: 0 | L45: 0 | M45: 0 | N45: 0 | O45: 0 | P45: 0 | Q45: 0
B46: EAST AFRICA REINSURANCE | C46: 0 | D46: 0 | E46: 0 | F46: 0 | G46: 0 | H46: 0 | I46: 0 | J46: 0 | K46: 0 | L46: 0 | M46: 0 | N46: 0 | O46: 0 | P46: 0 | Q46: 0
B47: GHANA REINSURANCE COMPANY | C47: 0 | D47: 0 | E47: 0 | F47: 0 | G47: 0 | H47: 0 | I47: 0 | J47: 0 | K47: 0 | L47: 0 | M47: 0 | N47: 0 | O47: 0 | P47: 0 | Q47: 0
B48: KENYA REINSURANCE CORPORATION | C48: 108799.45 | D48: 1589695.7 | E48: 116497.29 | F48: 4631068 | G48: 153812.49 | H48: 761806.18 | I48: 13368.515 | J48: 437423.78 | K48: 0 | L48: 350440.7 | M48: 31763.131 | N48: 20319.93 | O48: 2955437 | P48: 1666898.8 | Q48: 12837331
B49: WAICA REINSURANCE KENYA LIMITED | C49: 0 | D49: 0 | E49: 0 | F49: 0 | G49: 0 | H49: 0 | I49: 0 | J49: 0 | K49: 0 | L49: 0 | M49: 0 | N49: 0 | O49: 0 | P49: 0 | Q49: 0
B50: TOTAL | C50: =SUM(C45:C49) -> 108799.45 | D50: =SUM(D45:D49) -> 1589695.7 | E50: =SUM(E45:E49) -> 116497.29 | F50: =SUM(F45:F49) -> 4631068 | G50: =SUM(G45:G49) -> 153812.49 | H50: =SUM(H45:H49) -> 761806.18 | I50: =SUM(I45:I49) -> 13368.515 | J50: =SUM(J45:J49) -> 437423.78 | ... Q50: =SUM(Q45:Q49) -> 12837331
B51: Amounts in Thousand Shillings

Sheet INWARD
B3: =_xlfn.CONCAT("INWARD: SUMMARY OF NET PREMIUM INCOME UNDER GENERAL INSURANCE BUSINESS FOR THE PERIOD ENDED"," ",Details!F18) -> INWARD: SUMMARY OF NET PREMIUM INCOME UNDER GENERAL INSURANCE BUSINESS FOR THE PERIOD ENDED 31.12.2025
B4: Company | C4: Aviation | D4: Engineering | E4: Fire Domestic | F4: Fire Industrial | G4: Liability | H4: Marine | I4: Motor Private | J4: Motor Commercial | K4: Motor Commercial PSV | L4: Personal Accident | M4: Theft | N4: Workmens' Compensation | O4: Medical | P4: Miscellaneous | Q4: Total_x000D_
B5: INSURERS
B6: AAR INSURANCE KENYA | C6: 0 | D6: 0 | E6: 0 | F6: 0 | G6: 0 | H6: 0 | I6: 0 | J6: 0 | K6: 0 | L6: 0 | M6: 0 | N6: 0 | O6: 0 | P6: 0 | Q6: 0
B7: AFRICAN MERCHANT ASSURANCE | C7: 0 | D7: 0 | E7: 0 | F7: 0 | G7: 0 | H7: 0 | I7: 0 | J7: 0 | K7: 0 | L7: 0 | M7: 0 | N7: 0 | O7: 0 | P7: 0 | Q7: 0
B8: APA INSURANCE LIMITED | C8: 0 | D8: 4334.097 | E8: 0 | F8: 33764.959 | G8: 525 | H8: 3535.644 | I8: 0 | J8: 0 | K8: 0 | L8: 152017.93 | M8: 1493.996 | N8: 344087.63 | O8: 0 | P8: 0 | Q8: 539759.26
B9: BRITAM GENERAL INSURANCE | C9: 0 | D9: 7539.3781 | E9: 1512.2051 | F9: 51331.523 | G9: 364.20983 | H9: 0 | I9: 0 | J9: 0 | K9: 0 | L9: 120157.9 | M9: 0 | N9: 473021.94 | O9: 0 | P9: 0 | Q9: 653927.16
B10: BUPA GLOBAL INSURANCE | C10: 0 | D10: 0 | E10: 0 | F10: 0 | G10: 0 | H10: 0 | I10: 0 | J10: 0 | K10: 0 | L10: 0 | M10: 0 | N10: 0 | O10: 0 | P10: 0 | Q10: 0
B11: CANNON GENERAL INSURANCE | C11: 0 | D11: 2822.232 | E11: 0 | F11: 5126.186 | G11: 1131.476 | H11: 523.335 | I11: 966.74 | J11: 1780.245 | K11: 0 | L11: 44.245 | M11: 84.94 | N11: 0 | O11: 0 | P11: 890.217 | Q11: 13369.616
B12: CIC GENERAL INSURANCE COMPANY | C12: 0 | D12: 32778.147 | E12: 0 | F12: 66129.106 | G12: 161.9885 | H12: 74152.383 | I12: 0 | J12: 0 | K12: 0 | L12: 0 | M12: 743.35519 | N12: 364345.67 | O12: 0 | P12: 13642.471 | Q12: 551953.12
B13: CORPORATE INSURANCE COMPANY | C13: 0 | D13: 0 | E13: 0 | F13: 0 | G13: 0 | H13: 0 | I13: 0 | J13: 0 | K13: 0 | L13: 0 | M13: 0 | N13: 0 | O13: 0 | P13: 0 | Q13: 0
B14: DEFINITE ASSURANCE COMPANY | C14: 0 | D14: 0 | E14: 0 | F14: 0 | G14: 0 | H14: 0 | I14: 0 | J14: 0 | K14: 0 | L14: 0 | M14: 0 | N14: 0 | O14: 0 | P14: 0 | Q14: 0
B15: DIRECTLINE ASSURANCE COMPANY | C15: 0 | D15: 0 | E15: 0 | F15: 0 | G15: 0 | H15: 0 | I15: 0 | J15: 0 | K15: 0 | L15: 0 | M15: 0 | N15: 0 | O15: 0 | P15: 0 | Q15: 0
B16: EQUITY GENERAL INSURANCE LIMITED | C16: 0 | D16: 0 | E16: 0 | F16: 0 | G16: 0 | H16: 0 | I16: 0 | J16: 0 | K16: 0 | L16: 0 | M16: 0 | N16: 0 | O16: 0 | P16: 0 | Q16: 0
B17: EQUITY HEALTH INSURANCE LIMITED | C17: 0 | D17: 0 | E17: 0 | F17: 0 | G17: 0 | H17: 0 | I17: 0 | J17: 0 | K17: 0 | L17: 0 | M17: 0 | N17: 0 | O17: 0 | P17: 0 | Q17: 0
... B42: TRIDENT INSURANCE COMPANY | C42: 0 | D42: 0 | E42: 0 | F42: 0 | G42: 0 | H42: 0 | I42: 0 | J42: 0 | K42: 0 | L42: 0 | M42: 0 | N42: 0 | O42: 0 | P42: 0 | Q42: 0
B43: TOTAL | C43: =SUM(C6:C42) -> 71890.873 | D43: =SUM(D6:D42) -> 270245.05 | E43: =SUM(E6:E42) -> 2302.3041 | F43: =SUM(F6:F42) -> 714097 | G43: =SUM(G6:G42) -> 115835.3 | H43: =SUM(H6:H42) -> 120667.33 | I43: =SUM(I6:I42) -> 8715.868 | J43: =SUM(J6:J42) -> 7039.938 | ... Q43: =SUM(Q6:Q42) -> 3932631.8
B44: CONTINENTAL REINSURANCE
B45: CONTINENTAL REINSURANCE | C45: 28913.726 | D45: 548236.38 | E45: 491674.52 | F45: 1399381.3 | G45: 203538.26 | H45: 332507.85 | I45: 53307.64 | J45: 227769.01 | K45: 0 | L45: 208247.29 | M45: 10960.384 | N45: 21920.768 | O45: 703708.99 | P45: 854909.93 | Q45: 5085076.1
B46: EAST AFRICA REINSURANCE | C46: 6168.4786 | D46: 375480.58 | E46: 0 | F46: 1820870.4 | G46: 44230.077 | H46: 166325.1 | I46: 0 | J46: 250920.85 | K46: 0 | L46: 61710.809 | M46: 0 | N46: 0 | O46: 1112249 | P46: 720183.18 | Q46: 4558138.4
B47: GHANA REINSURANCE COMPANY | C47: 5792.264 | D47: 273328.01 | E47: 274336.29 | F47: 2011799.4 | G47: 89533.519 | H47: 171271.14 | I47: 160510.32 | J47: 173886.18 | K47: 0 | L47: 2759.662 | M47: 79261.581 | N47: -5046.95 | O47: 580526.31 | P47: 192986.16 | Q47: 4010943.9
B48: KENYA REINSURANCE CORPORATION | C48: 0 | D48: 0 | E48: 0 | F48: 0 | G48: 0 | H48: 0 | I48: 0 | J48: 0 | K48: 0 | L48: 0 | M48: 0 | N48: 0 | O48: 0 | P48: 0 | Q48: 0
B49: WAICA REINSURANCE KENYA LIMITED | C49: 56900.344 | D49: 928111.24 | E49: 0 | F49: 2837588.7 | G49: 172194.38 | H49: 231889.28 | I49: 89875.234 | J49: 110970.84 | K49: 0 | L49: 1324637.9 | M49: 53779.723 | N49: 0 | O49: 31652.09 | P49: 115239.58 | Q49: 5952839.2
B50: TOTAL | C50: =SUM(C45:C49) -> 97774.813 | D50: =SUM(D45:D49) -> 2125156.2 | E50: =SUM(E45:E49) -> 766010.81 | F50: =SUM(F45:F49) -> 8069639.8 | G50: =SUM(G45:G49) -> 509496.24 | H50: =SUM(H45:H49) -> 901993.36 | I50: =SUM(I45:I49) -> 303693.19 | J50: =SUM(J45:J49) -> 763546.87 | ... Q50: =SUM(Q45:Q49) -> 19606998
B51: Amounts in Thousand Shillings

Sheet APPENDIX 19
B3: =_xlfn.CONCAT('Table of Contents'!B31,": ",'Table of Contents'!C31) -> APPENDIX 19: SUMMARY OF GENERAL INSURANCE BUSINESS MARKET SHARE PER CLASS FOR THE PERIOD ENDED 31.12.2025
B4: Company | C4: Aviation | D4: Engineering | E4: Fire Domestic | F4: Fire Industrial | G4: Liability | H4: Marine | I4: Motor Private | J4: Motor Commercial | K4: Motor Commercial PSV | L4: Personal Accident | M4: Theft | N4: Workmens' Compensation | O4: Medical | P4: Miscellaneous | Q4: Total
B5: INSURERS
B6: ='APPENDIX 18'!B6 -> AAR INSURANCE KENYA | C6: =IFERROR('APPENDIX 18'!C6/'APPENDIX 18'!C$43*100,"") -> 0 | D6: =IFERROR('APPENDIX 18'!D6/'APPENDIX 18'!D$43*100,"") -> 0.076038977 | E6: =IFERROR('APPENDIX 18'!E6/'APPENDIX 18'!E$43*100,"") -> 0.10575674 | F6: =IFERROR('APPENDIX 18'!F6/'APPENDIX 18'!F$43*100,"") -> 0.06903843 | G6: =IFERROR('APPENDIX 18'!G6/'APPENDIX 18'!G$43*100,"") -> 0.62010948 | H6: =IFERROR('APPENDIX 18'!H6/'APPENDIX 18'!H$43*100,"") -> 0.072995899 | I6: =IFERROR('APPENDIX 18'!I6/'APPENDIX 18'!I$43*100,"") -> 0.012579069 | J6: =IFERROR('APPENDIX 18'!J6/'APPENDIX 18'!J$43*100,"") -> 0 | ... P6: =IFERROR('APPENDIX 18'!P6/'APPENDIX 18'!P$43*100,"") -> 0.35217039 | Q6: =IFERROR('APPENDIX 18'!$Q6/'APPENDIX 18'!Q$43*100,"") -> 5.6223217 | S6: =COUNTIF(Q6:Q42,">5") -> 7
B7: ='APPENDIX 18'!B7 -> AFRICAN MERCHANT ASSURANCE | C7: =IFERROR('APPENDIX 18'!C7/'APPENDIX 18'!C$43*100,"") -> 0 | D7: =IFERROR('APPENDIX 18'!D7/'APPENDIX 18'!D$43*100,"") -> 1.2863053 | E7: =IFERROR('APPENDIX 18'!E7/'APPENDIX 18'!E$43*100,"") -> 0.050258736 | F7: =IFERROR('APPENDIX 18'!F7/'APPENDIX 18'!F$43*100,"") -> 0.47631361 | G7: =IFERROR('APPENDIX 18'!G7/'APPENDIX 18'!G$43*100,"") -> 0.41941679 | H7: =IFERROR('APPENDIX 18'!H7/'APPENDIX 18'!H$43*100,"") -> 0.11600762 | I7: =IFERROR('APPENDIX 18'!I7/'APPENDIX 18'!I$43*100,"") -> 1.4620524 | J7: =IFERROR('APPENDIX 18'!J7/'APPENDIX 18'!J$43*100,"") -> 1.8782392 | ... P7: =IFERROR('APPENDIX 18'!P7/'APPENDIX 18'!P$43*100,"") -> 0.60522523 | Q7: =IFERROR('APPENDIX 18'!$Q7/'APPENDIX 18'!Q$43*100,"") -> 1.6951732
B8: ='APPENDIX 18'!B8 -> APA INSURANCE LIMITED | C8: =IFERROR('APPENDIX 18'!C8/'APPENDIX 18'!C$43*100,"") -> 9.8374419 | D8: =IFERROR('APPENDIX 18'!D8/'APPENDIX 18'!D$43*100,"") -> 5.3098611 | E8: =IFERROR('APPENDIX 18'!E8/'APPENDIX 18'!E$43*100,"") -> 6.4707229 | F8: =IFERROR('APPENDIX 18'!F8/'APPENDIX 18'!F$43*100,"") -> 10.023207 | G8: =IFERROR('APPENDIX 18'!G8/'APPENDIX 18'!G$43*100,"") -> 5.9115945 | H8: =IFERROR('APPENDIX 18'!H8/'APPENDIX 18'!H$43*100,"") -> 6.7498499 | I8: =IFERROR('APPENDIX 18'!I8/'APPENDIX 18'!I$43*100,"") -> 9.6877824 | J8: =IFERROR('APPENDIX 18'!J8/'APPENDIX 18'!J$43*100,"") -> 9.9621339 | ... P8: =IFERROR('APPENDIX 18'!P8/'APPENDIX 18'!P$43*100,"") -> 9.4985968 | Q8: =IFERROR('APPENDIX 18'!$Q8/'APPENDIX 18'!Q$43*100,"") -> 8.5316884
B9: ='APPENDIX 18'!B9 -> BRITAM GENERAL INSURANCE | C9: =IFERROR('APPENDIX 18'!C9/'APPENDIX 18'!C$43*100,"") -> 2.9969995 | D9: =IFERROR('APPENDIX 18'!D9/'APPENDIX 18'!D$43*100,"") -> 8.3608056 | E9: =IFERROR('APPENDIX 18'!E9/'APPENDIX 18'!E$43*100,"") -> 6.4321997 | F9: =IFERROR('APPENDIX 18'!F9/'APPENDIX 18'!F$43*100,"") -> 7.1863438 | G9: =IFERROR('APPENDIX 18'!G9/'APPENDIX 18'!G$43*100,"") -> 9.7457999 | H9: =IFERROR('APPENDIX 18'!H9/'APPENDIX 18'!H$43*100,"") -> 10.120609 | I9: =IFERROR('APPENDIX 18'!I9/'APPENDIX 18'!I$43*100,"") -> 5.0671567 | J9: =IFERROR('APPENDIX 18'!J9/'APPENDIX 18'!J$43*100,"") -> 2.9557997 | ... P9: =IFERROR('APPENDIX 18'!P9/'APPENDIX 18'!P$43*100,"") -> 0.93601103 | Q9: =IFERROR('APPENDIX 18'!$Q9/'APPENDIX 18'!Q$43*100,"") -> 6.5787381
B10: ='APPENDIX 18'!B10 -> BUPA GLOBAL INSURANCE | C10: =IFERROR('APPENDIX 18'!C10/'APPENDIX 18'!C$43*100,"") -> 0 | D10: =IFERROR('APPENDIX 18'!D10/'APPENDIX 18'!D$43*100,"") -> 0 | E10: =IFERROR('APPENDIX 18'!E10/'APPENDIX 18'!E$43*100,"") -> 0 | F10: =IFERROR('APPENDIX 18'!F10/'APPENDIX 18'!F$43*100,"") -> 0 | G10: =IFERROR('APPENDIX 18'!G10/'APPENDIX 18'!G$43*100,"") -> 0 | H10: =IFERROR('APPENDIX 18'!H10/'APPENDIX 18'!H$43*100,"") -> 0 | I10: =IFERROR('APPENDIX 18'!I10/'APPENDIX 18'!I$43*100,"") -> 0 | J10: =IFERROR('APPENDIX 18'!J10/'APPENDIX 18'!J$43*100,"") -> 0 | ... P10: =IFERROR('APPENDIX 18'!P10/'APPENDIX 18'!P$43*100,"") -> 0 | Q10: =IFERROR('APPENDIX 18'!$Q10/'APPENDIX 18'!Q$43*100,"") -> 2.3458684
B11: ='APPENDIX 18'!B11 -> CANNON GENERAL INSURANCE | C11: =IFERROR('APPENDIX 18'!C11/'APPENDIX 18'!C$43*100,"") -> 0 | D11: =IFERROR('APPENDIX 18'!D11/'APPENDIX 18'!D$43*100,"") -> 1.7335461 | E11: =IFERROR('APPENDIX 18'!E11/'APPENDIX 18'!E$43*100,"") -> 0.74606681 | F11: =IFERROR('APPENDIX 18'!F11/'APPENDIX 18'!F$43*100,"") -> 0.67688875 | G11: =IFERROR('APPENDIX 18'!G11/'APPENDIX 18'!G$43*100,"") -> 0.57506414 | H11: =IFERROR('APPENDIX 18'!H11/'APPENDIX 18'!H$43*100,"") -> 1.2305312 | I11: =IFERROR('APPENDIX 18'!I11/'APPENDIX 18'!I$43*100,"") -> 4.4376676 | J11: =IFERROR('APPENDIX 18'!J11/'APPENDIX 18'!J$43*100,"") -> 1.8912327 | ... P11: =IFERROR('APPENDIX 18'!P11/'APPENDIX 18'!P$43*100,"") -> 0.76521801 | Q11: =IFERROR('APPENDIX 18'!$Q11/'APPENDIX 18'!Q$43*100,"") -> 1.0639752
B12: ='APPENDIX 18'!B12 -> CIC GENERAL INSURANCE COMPANY | C12: =IFERROR('APPENDIX 18'!C12/'APPENDIX 18'!C$43*100,"") -> 0 | D12: =IFERROR('APPENDIX 18'!D12/'APPENDIX 18'!D$43*100,"") -> 5.3270793 | E12: =IFERROR('APPENDIX 18'!E12/'APPENDIX 18'!E$43*100,"") -> 5.6787198 | F12: =IFERROR('APPENDIX 18'!F12/'APPENDIX 18'!F$43*100,"") -> 3.3183964 | G12: =IFERROR('APPENDIX 18'!G12/'APPENDIX 18'!G$43*100,"") -> 2.9799311 | H12: =IFERROR('APPENDIX 18'!H12/'APPENDIX 18'!H$43*100,"") -> 2.5998401 | I12: =IFERROR('APPENDIX 18'!I12/'APPENDIX 18'!I$43*100,"") -> 11.631389 | J12: =IFERROR('APPENDIX 18'!J12/'APPENDIX 18'!J$43*100,"") -> 12.153777 | ... P12: =IFERROR('APPENDIX 18'!P12/'APPENDIX 18'!P$43*100,"") -> 5.4480738 | Q12: =IFERROR('APPENDIX 18'!$Q12/'APPENDIX 18'!Q$43*100,"") -> 9.0864614
B13: ='APPENDIX 18'!B13 -> CORPORATE INSURANCE COMPANY | C13: =IFERROR('APPENDIX 18'!C13/'APPENDIX 18'!C$43*100,"") -> 0 | D13: =IFERROR('APPENDIX 18'!D13/'APPENDIX 18'!D$43*100,"") -> 0 | E13: =IFERROR('APPENDIX 18'!E13/'APPENDIX 18'!E$43*100,"") -> 0 | F13: =IFERROR('APPENDIX 18'!F13/'APPENDIX 18'!F$43*100,"") -> 0 | G13: =IFERROR('APPENDIX 18'!G13/'APPENDIX 18'!G$43*100,"") -> 0 | H13: =IFERROR('APPENDIX 18'!H13/'APPENDIX 18'!H$43*100,"") -> 0 | I13: =IFERROR('APPENDIX 18'!I13/'APPENDIX 18'!I$43*100,"") -> 0 | J13: =IFERROR('APPENDIX 18'!J13/'APPENDIX 18'!J$43*100,"") -> 0 | ... P13: =IFERROR('APPENDIX 18'!P13/'APPENDIX 18'!P$43*100,"") -> 0 | Q13: =IFERROR('APPENDIX 18'!$Q13/'APPENDIX 18'!Q$43*100,"") -> 0
B14: ='APPENDIX 18'!B14 -> DEFINITE ASSURANCE COMPANY | C14: =IFERROR('APPENDIX 18'!C14/'APPENDIX 18'!C$43*100,"") -> 0 | D14: =IFERROR('APPENDIX 18'!D14/'APPENDIX 18'!D$43*100,"") -> 0.016141512 | E14: =IFERROR('APPENDIX 18'!E14/'APPENDIX 18'!E$43*100,"") -> 0.026051002 | F14: =IFERROR('APPENDIX 18'!F14/'APPENDIX 18'!F$43*100,"") -> 0.0093146543 | G14: =IFERROR('APPENDIX 18'!G14/'APPENDIX 18'!G$43*100,"") -> 0.024519234 | H14: =IFERROR('APPENDIX 18'!H14/'APPENDIX 18'!H$43*100,"") -> 0.010846364 | I14: =IFERROR('APPENDIX 18'!I14/'APPENDIX 18'!I$43*100,"") -> 0.77436241 | J14: =IFERROR('APPENDIX 18'!J14/'APPENDIX 18'!J$43*100,"") -> 0.79501387 | ... P14: =IFERROR('APPENDIX 18'!P14/'APPENDIX 18'!P$43*100,"") -> 1.890967 | Q14: =IFERROR('APPENDIX 18'!$Q14/'APPENDIX 18'!Q$43*100,"") -> 0.50567231
B15: ='APPENDIX 18'!B15 -> DIRECTLINE ASSURANCE COMPANY | C15: =IFERROR('APPENDIX 18'!C15/'APPENDIX 18'!C$43*100,"") -> 0 | D15: =IFERROR('APPENDIX 18'!D15/'APPENDIX 18'!D$43*100,"") -> 0 | E15: =IFERROR('APPENDIX 18'!E15/'APPENDIX 18'!E$43*100,"") -> 0 | F15: =IFERROR('APPENDIX 18'!F15/'APPENDIX 18'!F$43*100,"") -> 0 | G15: =IFERROR('APPENDIX 18'!G15/'APPENDIX 18'!G$43*100,"") -> 0 | H15: =IFERROR('APPENDIX 18'!H15/'APPENDIX 18'!H$43*100,"") -> 0 | I15: =IFERROR('APPENDIX 18'!I15/'APPENDIX 18'!I$43*100,"") -> 1.0026348 | J15: =IFERROR('APPENDIX 18'!J15/'APPENDIX 18'!J$43*100,"") -> 0.40748767 | ... P15: =IFERROR('APPENDIX 18'!P15/'APPENDIX 18'!P$43*100,"") -> 0 | Q15: =IFERROR('APPENDIX 18'!$Q15/'APPENDIX 18'!Q$43*100,"") -> 1.2035423
B16: ='APPENDIX 18'!B16 -> EQUITY GENERAL INSURANCE LIMITED | C16: =IFERROR('APPENDIX 18'!C16/'APPENDIX 18'!C$43*100,"") -> 0 | D16: =IFERROR('APPENDIX 18'!D16/'APPENDIX 18'!D$43*100,"") -> 0.4530445 | E16: =IFERROR('APPENDIX 18'!E16/'APPENDIX 18'!E$43*100,"") -> 0.049537742 | F16: =IFERROR('APPENDIX 18'!F16/'APPENDIX 18'!F$43*100,"") -> 0.25006158 | G16: =IFERROR('APPENDIX 18'!G16/'APPENDIX 18'!G$43*100,"") -> 0.84371685 | H16: =IFERROR('APPENDIX 18'!H16/'APPENDIX 18'!H$43*100,"") -> 0.0051089752 | I16: =IFERROR('APPENDIX 18'!I16/'APPENDIX 18'!I$43*100,"") -> 0 | J16: =IFERROR('APPENDIX 18'!J16/'APPENDIX 18'!J$43*100,"") -> 0 | ... P16: =IFERROR('APPENDIX 18'!P16/'APPENDIX 18'!P$43*100,"") -> 0.001690483 | Q16: =IFERROR('APPENDIX 18'!$Q16/'APPENDIX 18'!Q$43*100,"") -> 0.78754599
B17: ='APPENDIX 18'!B17 -> EQUITY HEALTH INSURANCE LIMITED | C17: =IFERROR('APPENDIX 18'!C17/'APPENDIX 18'!C$43*100,"") -> 0 | D17: =IFERROR('APPENDIX 18'!D17/'APPENDIX 18'!D$43*100,"") -> 0 | E17: =IFERROR('APPENDIX 18'!E17/'APPENDIX 18'!E$43*100,"") -> 0 | F17: =IFERROR('APPENDIX 18'!F17/'APPENDIX 18'!F$43*100,"") -> 0 | G17: =IFERROR('APPENDIX 18'!G17/'APPENDIX 18'!G$43*100,"") -> 0 | H17: =IFERROR('APPENDIX 18'!H17/'APPENDIX 18'!H$43*100,"") -> 0 | I17: =IFERROR('APPENDIX 18'!I17/'APPENDIX 18'!I$43*100,"") -> 0 | J17: =IFERROR('APPENDIX 18'!J17/'APPENDIX 18'!J$43*100,"") -> 0 | ... P17: =IFERROR('APPENDIX 18'!P17/'APPENDIX 18'!P$43*100,"") -> 0 | Q17: =IFERROR('APPENDIX 18'!$Q17/'APPENDIX 18'!Q$43*100,"") -> 0.0084368798
B18: ='APPENDIX 18'!B18 -> FIDELITY SHIELD INSURANCE | C18: =IFERROR('APPENDIX 18'!C18/'APPENDIX 18'!C$43*100,"") -> 15.05874 | D18: =IFERROR('APPENDIX 18'!D18/'APPENDIX 18'!D$43*100,"") -> 1.2858624 | E18: =IFERROR('APPENDIX 18'!E18/'APPENDIX 18'!E$43*100,"") -> 1.8106754 | F18: =IFERROR('APPENDIX 18'!F18/'APPENDIX 18'!F$43*100,"") -> 1.3758152 | G18: =IFERROR('APPENDIX 18'!G18/'APPENDIX 18'!G$43*100,"") -> 1.5135348 | H18: =IFERROR('APPENDIX 18'!H18/'APPENDIX 18'!H$43*100,"") -> 2.6058655 | I18: =IFERROR('APPENDIX 18'!I18/'APPENDIX 18'!I$43*100,"") -> 4.7191728 | J18: =IFERROR('APPENDIX 18'!J18/'APPENDIX 18'!J$43*100,"") -> 4.8452236 | ... P18: =IFERROR('APPENDIX 18'!P18/'APPENDIX 18'!P$43*100,"") -> 3.9323165 | Q18: =IFERROR('APPENDIX 18'!$Q18/'APPENDIX 18'!Q$43*100,"") -> 2.2070987
... B42: ='APPENDIX 18'!B42 -> TRIDENT INSURANCE COMPANY | C42: =IFERROR('APPENDIX 18'!C42/'APPENDIX 18'!C$43*100,"") -> 0 | D42: =IFERROR('APPENDIX 18'!D42/'APPENDIX 18'!D$43*100,"") -> 0 | E42: =IFERROR('APPENDIX 18'!E42/'APPENDIX 18'!E$43*100,"") -> 0 | F42: =IFERROR('APPENDIX 18'!F42/'APPENDIX 18'!F$43*100,"") -> 0 | G42: =IFERROR('APPENDIX 18'!G42/'APPENDIX 18'!G$43*100,"") -> 0 | H42: =IFERROR('APPENDIX 18'!H42/'APPENDIX 18'!H$43*100,"") -> 0 | I42: =IFERROR('APPENDIX 18'!I42/'APPENDIX 18'!I$43*100,"") -> 0 | J42: =IFERROR('APPENDIX 18'!J42/'APPENDIX 18'!J$43*100,"") -> 0 | ... P42: =IFERROR('APPENDIX 18'!P42/'APPENDIX 18'!P$43*100,"") -> 0 | Q42: =IFERROR('APPENDIX 18'!$Q42/'APPENDIX 18'!Q$43*100,"") -> 0
B43: TOTAL | C43: =IFERROR('APPENDIX 18'!C43/'APPENDIX 18'!C$43*100,"") -> 100 | D43: =IFERROR('APPENDIX 18'!D43/'APPENDIX 18'!D$43*100,"") -> 100 | E43: =IFERROR('APPENDIX 18'!E43/'APPENDIX 18'!E$43*100,"") -> 100 | F43: =IFERROR('APPENDIX 18'!F43/'APPENDIX 18'!F$43*100,"") -> 100 | G43: =IFERROR('APPENDIX 18'!G43/'APPENDIX 18'!G$43*100,"") -> 100 | H43: =IFERROR('APPENDIX 18'!H43/'APPENDIX 18'!H$43*100,"") -> 100 | I43: =IFERROR('APPENDIX 18'!I43/'APPENDIX 18'!I$43*100,"") -> 100 | J43: =IFERROR('APPENDIX 18'!J43/'APPENDIX 18'!J$43*100,"") -> 100 | ... P43: =IFERROR('APPENDIX 18'!P43/'APPENDIX 18'!P$43*100,"") -> 100 | Q43: =SUM(Q6:Q42) -> 100
B44: REINSURERS
B45: ='APPENDIX 18'!B45 -> CONTINENTAL REINSURANCE | C45: =IFERROR('APPENDIX 18'!C45/'APPENDIX 18'!C$50*100,"") -> 13.996771 | D45: =IFERROR('APPENDIX 18'!D45/'APPENDIX 18'!D$50*100,"") -> 14.757961 | E45: =IFERROR('APPENDIX 18'!E45/'APPENDIX 18'!E$50*100,"") -> 55.713316 | F45: =IFERROR('APPENDIX 18'!F45/'APPENDIX 18'!F$50*100,"") -> 11.018137 | G45: =IFERROR('APPENDIX 18'!G45/'APPENDIX 18'!G$50*100,"") -> 30.685298 | H45: =IFERROR('APPENDIX 18'!H45/'APPENDIX 18'!H$50*100,"") -> 19.98485 | I45: =IFERROR('APPENDIX 18'!I45/'APPENDIX 18'!I$50*100,"") -> 16.813017 | J45: =IFERROR('APPENDIX 18'!J45/'APPENDIX 18'!J$50*100,"") -> 18.96541 | K45: =IFERROR('APPENDIX 18'!K45/'APPENDIX 18'!K$50*100,0) -> 0 | L45: =IFERROR('APPENDIX 18'!L45/'APPENDIX 18'!L$50*100,"") -> 10.691431 | M45: =IFERROR('APPENDIX 18'!M45/'APPENDIX 18'!M$50*100,"") -> 6.2358235 | N45: =IFERROR('APPENDIX 18'!N45/'APPENDIX 18'!N$50*100,"") -> 58.936701 | O45: =IFERROR('APPENDIX 18'!O45/'APPENDIX 18'!O$50*100,"") -> 13.071411 | P45: =IFERROR('APPENDIX 18'!P45/'APPENDIX 18'!$P$50*100,"") -> 24.080494 | Q45: =IFERROR('APPENDIX 18'!$Q45/'APPENDIX 18'!$Q$50*100,"") -> 15.673236
B46: ='APPENDIX 18'!B46 -> EAST AFRICA REINSURANCE | C46: =IFERROR('APPENDIX 18'!C46/'APPENDIX 18'!C$50*100,"") -> 2.9860829 | D46: =IFERROR('APPENDIX 18'!D46/'APPENDIX 18'!D$50*100,"") -> 10.107552 | E46: =IFERROR('APPENDIX 18'!E46/'APPENDIX 18'!E$50*100,"") -> 0 | F46: =IFERROR('APPENDIX 18'!F46/'APPENDIX 18'!F$50*100,"") -> 14.336763 | G46: =IFERROR('APPENDIX 18'!G46/'APPENDIX 18'!G$50*100,"") -> 6.6680982 | H46: =IFERROR('APPENDIX 18'!H46/'APPENDIX 18'!H$50*100,"") -> 9.996703 | I46: =IFERROR('APPENDIX 18'!I46/'APPENDIX 18'!I$50*100,"") -> 0 | J46: =IFERROR('APPENDIX 18'!J46/'APPENDIX 18'!J$50*100,"") -> 20.89317 | K46: =IFERROR('APPENDIX 18'!K46/'APPENDIX 18'!K$50*100,0) -> 0 | L46: =IFERROR('APPENDIX 18'!L46/'APPENDIX 18'!L$50*100,"") -> 3.1682373 | M46: =IFERROR('APPENDIX 18'!M46/'APPENDIX 18'!M$50*100,"") -> 0 | N46: =IFERROR('APPENDIX 18'!N46/'APPENDIX 18'!N$50*100,"") -> 0 | O46: =IFERROR('APPENDIX 18'!O46/'APPENDIX 18'!O$50*100,"") -> 20.660051 | P46: =IFERROR('APPENDIX 18'!P46/'APPENDIX 18'!$P$50*100,"") -> 20.285607 | Q46: =IFERROR('APPENDIX 18'!$Q46/'APPENDIX 18'!$Q$50*100,"") -> 14.049107
B47: ='APPENDIX 18'!B47 -> GHANA REINSURANCE COMPANY | C47: =IFERROR('APPENDIX 18'!C47/'APPENDIX 18'!C$50*100,"") -> 2.8039621 | D47: =IFERROR('APPENDIX 18'!D47/'APPENDIX 18'!D$50*100,"") -> 7.3577093 | E47: =IFERROR('APPENDIX 18'!E47/'APPENDIX 18'!E$50*100,"") -> 31.085979 | F47: =IFERROR('APPENDIX 18'!F47/'APPENDIX 18'!F$50*100,"") -> 15.840058 | G47: =IFERROR('APPENDIX 18'!G47/'APPENDIX 18'!G$50*100,"") -> 13.498016 | H47: =IFERROR('APPENDIX 18'!H47/'APPENDIX 18'!H$50*100,"") -> 10.293977 | I47: =IFERROR('APPENDIX 18'!I47/'APPENDIX 18'!I$50*100,"") -> 50.624315 | J47: =IFERROR('APPENDIX 18'!J47/'APPENDIX 18'!J$50*100,"") -> 14.478803 | K47: =IFERROR('APPENDIX 18'!K47/'APPENDIX 18'!K$50*100,0) -> 0 | L47: =IFERROR('APPENDIX 18'!L47/'APPENDIX 18'!L$50*100,"") -> 0.14168124 | M47: =IFERROR('APPENDIX 18'!M47/'APPENDIX 18'!M$50*100,"") -> 45.095248 | N47: =IFERROR('APPENDIX 18'!N47/'APPENDIX 18'!N$50*100,"") -> -13.56935 | O47: =IFERROR('APPENDIX 18'!O47/'APPENDIX 18'!O$50*100,"") -> 10.78329 | P47: =IFERROR('APPENDIX 18'!P47/'APPENDIX 18'!$P$50*100,"") -> 5.4358965 | Q47: =IFERROR('APPENDIX 18'!$Q47/'APPENDIX 18'!$Q$50*100,"") -> 12.362542
B48: ='APPENDIX 18'!B48 -> KENYA REINSURANCE CORPORATION | C48: =IFERROR('APPENDIX 18'!C48/'APPENDIX 18'!C$50*100,"") -> 52.668443 | D48: =IFERROR('APPENDIX 18'!D48/'APPENDIX 18'!D$50*100,"") -> 42.792976 | E48: =IFERROR('APPENDIX 18'!E48/'APPENDIX 18'!E$50*100,"") -> 13.200705 | F48: =IFERROR('APPENDIX 18'!F48/'APPENDIX 18'!F$50*100,"") -> 36.46307 | G48: =IFERROR('APPENDIX 18'!G48/'APPENDIX 18'!G$50*100,"") -> 23.188673 | H48: =IFERROR('APPENDIX 18'!H48/'APPENDIX 18'!H$50*100,"") -> 45.787137 | I48: =IFERROR('APPENDIX 18'!I48/'APPENDIX 18'!I$50*100,"") -> 4.2163763 | J48: =IFERROR('APPENDIX 18'!J48/'APPENDIX 18'!J$50*100,"") -> 36.42252 | K48: =IFERROR('APPENDIX 18'!K48/'APPENDIX 18'!K$50*100,0) -> 0 | L48: =IFERROR('APPENDIX 18'!L48/'APPENDIX 18'!L$50*100,"") -> 17.99165 | M48: =IFERROR('APPENDIX 18'!M48/'APPENDIX 18'!M$50*100,"") -> 18.071381 | N48: =IFERROR('APPENDIX 18'!N48/'APPENDIX 18'!N$50*100,"") -> 54.63265 | O48: =IFERROR('APPENDIX 18'!O48/'APPENDIX 18'!O$50*100,"") -> 54.897311 | P48: =IFERROR('APPENDIX 18'!P48/'APPENDIX 18'!$P$50*100,"") -> 46.952017 | Q48: =IFERROR('APPENDIX 18'!$Q48/'APPENDIX 18'!$Q$50*100,"") -> 39.567257
B49: ='APPENDIX 18'!B49 -> WAICA REINSURANCE KENYA LIMITED | C49: =IFERROR('APPENDIX 18'!C49/'APPENDIX 18'!C$50*100,"") -> 27.544741 | D49: =IFERROR('APPENDIX 18'!D49/'APPENDIX 18'!D$50*100,"") -> 24.983802 | E49: =IFERROR('APPENDIX 18'!E49/'APPENDIX 18'!E$50*100,"") -> 0 | F49: =IFERROR('APPENDIX 18'!F49/'APPENDIX 18'!F$50*100,"") -> 22.341973 | G49: =IFERROR('APPENDIX 18'!G49/'APPENDIX 18'!G$50*100,"") -> 25.959915 | H49: =IFERROR('APPENDIX 18'!H49/'APPENDIX 18'!H$50*100,"") -> 13.937333 | I49: =IFERROR('APPENDIX 18'!I49/'APPENDIX 18'!I$50*100,"") -> 28.346291 | J49: =IFERROR('APPENDIX 18'!J49/'APPENDIX 18'!J$50*100,"") -> 9.2400959 | K49: =IFERROR('APPENDIX 18'!K49/'APPENDIX 18'!K$50*100,0) -> 0 | L49: =IFERROR('APPENDIX 18'!L49/'APPENDIX 18'!L$50*100,"") -> 68.007001 | M49: =IFERROR('APPENDIX 18'!M49/'APPENDIX 18'!M$50*100,"") -> 30.597547 | N49: =IFERROR('APPENDIX 18'!N49/'APPENDIX 18'!N$50*100,"") -> 0 | O49: =IFERROR('APPENDIX 18'!O49/'APPENDIX 18'!O$50*100,"") -> 0.58793829 | P49: =IFERROR('APPENDIX 18'!P49/'APPENDIX 18'!$P$50*100,"") -> 3.2459863 | Q49: =IFERROR('APPENDIX 18'!$Q49/'APPENDIX 18'!$Q$50*100,"") -> 18.347858
B50: TOTAL | C50: =SUM(C45:C49) -> 100 | D50: =SUM(D45:D49) -> 100 | E50: =SUM(E45:E49) -> 100 | F50: =SUM(F45:F49) -> 100 | G50: =SUM(G45:G49) -> 100 | H50: =SUM(H45:H49) -> 100 | I50: =SUM(I45:I49) -> 100 | J50: =SUM(J45:J49) -> 100 | ... Q50: =SUM(Q45:Q49) -> 100
B51: figures in %

Sheet APPENDIX 20
B3: =_xlfn.CONCAT('Table of Contents'!B32,": ",'Table of Contents'!C32) -> APPENDIX 20: SUMMARY OF CLAIMS PAID UNDER GENERAL INSURANCE BUSINESS FOR THE PERIOD ENDED 31.12.2025
B4: Company | C4: Aviation | D4: Engineering | E4: Fire Domestic | F4: Fire Industrial | G4: Liability | H4: Marine | I4: Motor Private | J4: Motor Commercial | K4: Motor Commercial PSV | L4: Personal Accident | M4: Theft | N4: Workmens' Compensation | O4: Medical | P4: Miscellaneous | Q4: Total_x000D_
B5: INSURERS
B6: AAR INSURANCE KENYA | C6: 0 | D6: 3356.8055 | E6: 269.43733 | F6: 387.76608 | G6: 6078.3744 | H6: 0 | I6: 468.35065 | J6: 0 | K6: 0 | L6: 1800.1216 | M6: 7968.0331 | N6: 22103.513 | O6: 6089350.9 | P6: 147.52584 | Q6: 6131930.8
B7: AFRICAN MERCHANT ASSURANCE | C7: 0 | D7: 49448.764 | E7: 187.73811 | F7: 6334.436 | G7: 324.778 | H7: 1605.471 | I7: 554693.71 | J7: 0 | K7: 1229947.8 | L7: 20810.831 | M7: 1290.027 | N7: 24830.655 | O7: 0 | P7: 19063.279 | Q7: 1908537.5
B8: APA INSURANCE LIMITED | C8: 0 | D8: 47350.668 | E8: 58294.63 | F8: 176756.5 | G8: 124297.96 | H8: 118156.18 | I8: 2217652.8 | J8: 1959755.9 | K8: 0 | L8: 41347.922 | M8: 86565.706 | N8: 245077.53 | O8: 3286303.7 | P8: 77264.147 | Q8: 8438823.6
B9: BRITAM GENERAL INSURANCE | C9: 0 | D9: 12414.391 | E9: 20658.898 | F9: 209868.36 | G9: 13519.99 | H9: 29576.857 | I9: 956077.32 | J9: 624178.04 | K9: 0 | L9: 86316.817 | M9: 49752.25 | N9: 68457.349 | O9: 4421950.7 | P9: 758726.47 | Q9: 7251497.4
B10: BUPA GLOBAL INSURANCE | C10: 0 | D10: 0 | E10: 0 | F10: 0 | G10: 0 | H10: 0 | I10: 0 | J10: 0 | K10: 0 | L10: 0 | M10: 0 | N10: 0 | O10: 83167.598 | P10: 0 | Q10: 83167.598
B11: CANNON GENERAL INSURANCE | C11: 0 | D11: 8816.003 | E11: 24613.937 | F11: 10495.525 | G11: 11205.822 | H11: 6767.083 | I11: 1054826.8 | J11: 252143.9 | K11: 0 | L11: 1522.419 | M11: 6627.78 | N11: 33694.472 | O11: 0 | P11: 601.798 | Q11: 1411315.5
B12: CIC GENERAL INSURANCE COMPANY | C12: 0 | D12: 128186.28 | E12: 18617.185 | F12: 160002.59 | G12: 91597.388 | H12: -3261.001 | I12: 2462412.9 | J12: 1886367.7 | K12: 0 | L12: 17299.468 | M12: 58353.8 | N12: 70121.264 | O12: 6613141.7 | P12: -148493.84 | Q12: 11354345
B13: CORPORATE INSURANCE COMPANY | C13: 0 | D13: 0 | E13: 0 | F13: 0 | G13: 0 | H13: 0 | I13: 0 | J13: 0 | K13: 0 | L13: 0 | M13: 0 | N13: 0 | O13: 0 | P13: 0 | Q13: 0
B14: DEFINITE ASSURANCE COMPANY | C14: 0 | D14: 0 | E14: 0 | F14: 0 | G14: 0 | H14: 0 | I14: 14747 | J14: 1962.602 | K14: 16420.912 | L14: 0 | M14: 0 | N14: 0 | O14: 0 | P14: 88 | Q14: 33218.514
B15: DIRECTLINE ASSURANCE COMPANY | C15: 0 | D15: 0 | E15: 3054.7064 | F15: 0 | G15: 0 | H15: 0 | I15: 261714.44 | J15: 111746.63 | K15: 1676098.5 | L15: 0 | M15: 0 | N15: 0 | O15: 0 | P15: 0 | Q15: 2052614.3
B16: EQUITY GENERAL INSURANCE LIMITED | C16: 0 | D16: 0 | E16: 0 | F16: 0 | G16: 0 | H16: 0 | I16: 0 | J16: 0 | K16: 0 | L16: 0 | M16: 11101.392 | N16: 0 | O16: 613974.22 | P16: 0 | Q16: 625075.61
B17: EQUITY HEALTH INSURANCE LIMITED | C17: 0 | D17: 0 | E17: 0 | F17: 0 | G17: 0 | H17: 0 | I17: 0 | J17: 0 | K17: 0 | L17: 0 | M17: 0 | N17: 0 | O17: 1372.068 | P17: 0 | Q17: 1372.068
... B42: TRIDENT INSURANCE COMPANY | C42: 0 | D42: 0 | E42: 0 | F42: 0 | G42: 0 | H42: 0 | I42: 0 | J42: 0 | K42: 0 | L42: 0 | M42: 0 | N42: 0 | O42: 0 | P42: 0 | Q42: 0
B43: TOTAL | C43: =SUM(C6:C42) -> 17945.859 | D43: =SUM(D6:D42) -> 900722.44 | E43: =SUM(E6:E42) -> 533662.79 | F43: =SUM(F6:F42) -> 1758978 | G43: =SUM(G6:G42) -> 652684.3 | H43: =SUM(H6:H42) -> 629366.3 | I43: =SUM(I6:I42) -> 20688148 | J43: =SUM(J6:J42) -> 15919303 | ... Q43: =SUM(Q6:Q42) -> 1.0276992e+08
B44: REINSURERS
B45: CONTINENTAL REINSURANCE | C45: 6961.5777 | D45: 204602.19 | E45: 167115.81 | F45: 475637.32 | G45: 78832.524 | H45: 80058.143 | I45: 20646.613 | J45: 88217.348 | K45: 0 | L45: 91415.23 | M45: 4811.3279 | N45: 9622.6558 | O45: 764571.3 | P45: 375283.58 | Q45: 2367775.6
B46: EAST AFRICA REINSURANCE | C46: 284.47518 | D46: 97229.735 | E46: 0 | F46: 799118.18 | G46: 3926.3692 | H46: 98515.836 | I46: 0 | J46: 167069.51 | K46: 0 | L46: 28630.838 | M46: 0 | N46: 0 | O46: 784442.71 | P46: 190819.12 | Q46: 2170036.8
B47: GHANA REINSURANCE COMPANY | C47: -4656.052 | D47: 69455.616 | E47: 79078.963 | F47: 579912.39 | G47: 1539.042 | H47: 36084.171 | I47: 73522.285 | J47: 79649.142 | K47: 0 | L47: 598.972 | M47: 79290.077 | N47: 4635.223 | O47: 483019.93 | P47: 9553.749 | Q47: 1491683.5
B48: KENYA REINSURANCE CORPORATION | C48: 23399.417 | D48: 377106.3 | E48: 98306.11 | F48: 2466721.4 | G48: 12301.569 | H48: 362245.17 | I48: 4836.6521 | J48: 494183.8 | K48: 0 | L48: 313625.76 | M48: 6464.0651 | N48: 1610.1041 | O48: 2441161.9 | P48: 746278.19 | Q48: 7348240.5
B49: WAICA REINSURANCE KENYA LIMITED | C49: 1051.5648 | D49: 391969.42 | E49: 3702.5398 | F49: 809693.47 | G49: 5628.2502 | H49: 122679.81 | I49: 27402.193 | J49: 95037.862 | K49: 0 | L49: 599873.1 | M49: 10833.197 | N49: 123360.18 | O49: 36229.436 | P49: 197336.45 | Q49: 2424797.5
B50: TOTAL | C50: =SUM(C45:C49) -> 27040.983 | D50: =SUM(D45:D49) -> 1140363.3 | E50: =SUM(E45:E49) -> 348203.43 | F50: =SUM(F45:F49) -> 5131082.8 | G50: =SUM(G45:G49) -> 102227.75 | H50: =SUM(H45:H49) -> 699583.13 | I50: =SUM(I45:I49) -> 126407.74 | J50: =SUM(J45:J49) -> 924157.67 | ... Q50: =SUM(Q45:Q49) -> 15802534
B51: Amounts in Thousand Shillings

Sheet APPENDIX 21
B3: =_xlfn.CONCAT('Table of Contents'!B33,": ",'Table of Contents'!C33) -> APPENDIX 21: SUMMARY OF CLAIMS INCURRED UNDER GENERAL INSURANCE BUSINESS FOR THE PERIOD ENDED 31.12.2025
B4: Company | C4: Aviation | D4: Engineering | E4: Fire Domestic | F4: Fire Industrial | G4: Liability | H4: Marine | I4: Motor Private | J4: Motor Commercial | K4: Motor Commercial PSV | L4: Personal Accident | M4: Theft | N4: Workmens' Compensation | O4: Medical | P4: Miscellaneous | Q4: Total_x000D_
B5: INSURERS
B6: AAR INSURANCE KENYA | C6: 0 | D6: 3325.9075 | E6: 417.85733 | F6: 711.43808 | G6: 12181.315 | H6: -787.011 | I6: 1537.4697 | J6: 0 | K6: 0 | L6: -783.58137 | M6: 11830.976 | N6: 23221.217 | O6: 6422406.7 | P6: 7400.0128 | Q6: 6481462.3
B7: AFRICAN MERCHANT ASSURANCE | C7: 0 | D7: 56158.896 | E7: 4741.6538 | F7: 31043.328 | G7: 10538.899 | H7: 3843.2237 | I7: 559694.51 | J7: -587359.68 | K7: 2378445.9 | L7: 31759.06 | M7: 27735.299 | N7: 25915.036 | O7: 0 | P7: 84176.041 | Q7: 2626692.2
B8: APA INSURANCE LIMITED | C8: -4.0767371 | D8: 80642.795 | E8: 76962.995 | F8: 104792.74 | G8: 158766.26 | H8: 133773.81 | I8: 2437957.4 | J8: 2257990.5 | K8: 0 | L8: 44756.238 | M8: 112436.76 | N8: 233290.86 | O8: 3254111.1 | P8: 76754.938 | Q8: 8972232.3
B9: BRITAM GENERAL INSURANCE | C9: -267.292 | D9: 15486.466 | E9: 22142.676 | F9: 178974.01 | G9: 53530.863 | H9: 25406.952 | I9: 937559.17 | J9: 549677.66 | K9: 0 | L9: 86295.475 | M9: 33044.511 | N9: 135550.78 | O9: 4588833.3 | P9: 572155.11 | Q9: 7198389.7
B10: BUPA GLOBAL INSURANCE | C10: 0 | D10: 0 | E10: 0 | F10: 0 | G10: 0 | H10: 0 | I10: 0 | J10: 0 | K10: 0 | L10: 0 | M10: 0 | N10: 0 | O10: 108469.76 | P10: 0 | Q10: 108469.76
B11: CANNON GENERAL INSURANCE | C11: 0 | D11: 1697.1767 | E11: 13140.589 | F11: 7922.2057 | G11: 18985.507 | H11: 8075.2761 | I11: 1243279.9 | J11: 277779.99 | K11: 0 | L11: 1476.1661 | M11: 9251.7591 | N11: 38312.394 | O11: 0 | P11: 403.92419 | Q11: 1620324.9
B12: CIC GENERAL INSURANCE COMPANY | C12: 0 | D12: 19049.084 | E12: 34329.316 | F12: 103609.82 | G12: 79656.622 | H12: -26333.349 | I12: 2595873.4 | J12: 2112554.5 | K12: 0 | L12: 46595.572 | M12: 17975.082 | N12: 67997.988 | O12: 7067258.6 | P12: 43399.965 | Q12: 12161967
B13: CORPORATE INSURANCE COMPANY | C13: 0 | D13: 0 | E13: 0 | F13: 0 | G13: 0 | H13: 0 | I13: 0 | J13: 0 | K13: 0 | L13: 0 | M13: 0 | N13: 0 | O13: 0 | P13: 0 | Q13: 0
B14: DEFINITE ASSURANCE COMPANY | C14: 0 | D14: 0 | E14: 0 | F14: 0 | G14: 0 | H14: 0 | I14: 55532.413 | J14: 9899.667 | K14: 165427.22 | L14: 0 | M14: 0 | N14: 0 | O14: 0 | P14: 88 | Q14: 230947.3
B15: DIRECTLINE ASSURANCE COMPANY | C15: 0 | D15: 0 | E15: 3245.6914 | F15: 287.508 | G15: -8500 | H15: 0 | I15: 471183.21 | J15: 126403.24 | K15: 1662291.8 | L15: 0 | M15: 0 | N15: -200 | O15: 0 | P15: -478.4931 | Q15: 2254232.9
B16: EQUITY GENERAL INSURANCE LIMITED | C16: 0 | D16: 0 | E16: 0 | F16: 0 | G16: 10 | H16: 0 | I16: 0 | J16: 0 | K16: 0 | L16: 0 | M16: 22268.289 | N16: 250 | O16: 710592.5 | P16: 0 | Q16: 733120.79
B17: EQUITY HEALTH INSURANCE LIMITED | C17: 0 | D17: 0 | E17: 0 | F17: 0 | G17: 0 | H17: 0 | I17: 0 | J17: 0 | K17: 0 | L17: 0 | M17: 0 | N17: 0 | O17: 2999.73 | P17: 0 | Q17: 2999.73
... B42: TRIDENT INSURANCE COMPANY | C42: 0 | D42: 0 | E42: 0 | F42: 0 | G42: 0 | H42: 0 | I42: 0 | J42: 0 | K42: 0 | L42: 0 | M42: 0 | N42: 0 | O42: 0 | P42: 0 | Q42: 0
B43: TOTAL | C43: =SUM(C6:C42) -> 18466.79 | D43: =SUM(D6:D42) -> 637883.19 | E43: =SUM(E6:E42) -> 520130.36 | F43: =SUM(F6:F42) -> 1217568.8 | G43: =SUM(G6:G42) -> 1056826.8 | H43: =SUM(H6:H42) -> 729867.95 | I43: =SUM(I6:I42) -> 21882115 | J43: =SUM(J6:J42) -> 16415389 | ... Q43: =SUM(Q6:Q42) -> 1.0797021e+08
B44: REINSURERS
B45: CONTINENTAL REINSURANCE | C45: 10303.628 | D45: 147854.91 | E45: 173342.04 | F45: 493358.1 | G45: 89534.612 | H45: 118491.73 | I45: 23449.541 | J45: 100193.49 | K45: 0 | L45: 71216.661 | M45: 3748.2451 | N45: 7496.4901 | O45: 388096.46 | P45: 292363.13 | Q45: 1919449
B46: EAST AFRICA REINSURANCE | C46: 388.98376 | D46: 98489.673 | E46: 0 | F46: 711590.53 | G46: 4206.9215 | H46: 79750.728 | I46: 0 | J46: 145614.86 | K46: 0 | L46: 24283.593 | M46: 0 | N46: 0 | O46: 814268.67 | P46: 186787.14 | Q46: 2065381.1
B47: GHANA REINSURANCE COMPANY | C47: -17384.859 | D47: 115966.15 | E47: 165721.51 | F47: 666554.93 | G47: -4113.4171 | H47: 90298.008 | I47: 89832.074 | J47: 95958.931 | K47: 0 | L47: -4400.2357 | M47: 52315.571 | N47: -363.98474 | O47: 516255.58 | P47: 13251.195 | Q47: 1779891.5
B48: KENYA REINSURANCE CORPORATION | C48: 23399.417 | D48: 377106.3 | E48: 98306.11 | F48: 2466721.4 | G48: 12301.569 | H48: 362245.17 | I48: 4836.6521 | J48: 494183.8 | K48: 0 | L48: 313625.76 | M48: 6464.0651 | N48: 1610.1041 | O48: 2441161.9 | P48: 746278.19 | Q48: 7348240.5
B49: WAICA REINSURANCE KENYA LIMITED | C49: 36664.897 | D49: 841734.17 | E49: 12089.267 | F49: 813441.82 | G49: -718861.59 | H49: 148100.18 | I49: 19639.316 | J49: 206163.42 | K49: 0 | L49: 698263.22 | M49: 21024.829 | N49: 139858.11 | O49: 347446.06 | P49: 113447.63 | Q49: 2679011.3
B50: TOTAL | C50: =SUM(C45:C49) -> 53372.067 | D50: =SUM(D45:D49) -> 1581151.2 | E50: =SUM(E45:E49) -> 449458.92 | F50: =SUM(F45:F49) -> 5151666.8 | G50: =SUM(G45:G49) -> -616931.9 | H50: =SUM(H45:H49) -> 798885.82 | I50: =SUM(I45:I49) -> 137757.58 | J50: =SUM(J45:J49) -> 1042114.5 | ... Q50: =SUM(Q45:Q49) -> 15791973
B51: Amounts in Thousand Shillings

Sheet APPENDIX 22
B3: =_xlfn.CONCAT('Table of Contents'!B34,": ",'Table of Contents'!C34) -> APPENDIX 22: SUMMARY OF INCURRED CLAIMS RATIOS UNDER GENERAL INSURANCE BUSINESS FOR THE PERIOD ENDED 31.12.2025
B4: Company | C4: Aviation | D4: Engineering | E4: Fire Domestic | F4: Fire Industrial | G4: Liability | H4: Marine | I4: Motor Private | J4: Motor Commercial | K4: Motor Commercial PSV | L4: Personal Accident | M4: Theft | N4: Workmens' Compensation | O4: Medical | P4: Miscellaneous | Q4: Total_x000D_
B5: INSURERS
B6: ='APPENDIX 21'!B6 -> AAR INSURANCE KENYA | C6: =IFERROR('APPENDIX 21'!C6/NEPI!C6*100,"0.0") -> 0.0 | D6: =IFERROR('APPENDIX 21'!D6/NEPI!D6*100,"0.0") -> -1386.2431 | E6: =IFERROR('APPENDIX 21'!E6/NEPI!E6*100,"0.0") -> 66.845498 | F6: =IFERROR('APPENDIX 21'!F6/NEPI!F6*100,"0.0") -> 15.512623 | G6: =IFERROR('APPENDIX 21'!G6/NEPI!G6*100,"0.0") -> 51.196239 | H6: =IFERROR('APPENDIX 21'!H6/NEPI!H6*100,"0.0") -> 58.5996 | I6: =IFERROR('APPENDIX 21'!I6/NEPI!I6*100,"0.0") -> 81.534974 | J6: =IFERROR('APPENDIX 21'!J6/NEPI!J6*100,"0.0") -> 0.0 | ... P6: =IFERROR('APPENDIX 21'!P6/NEPI!P6*100,"0.0") -> 80.546646 | Q6: =IFERROR('APPENDIX 21'!Q6/NEPI!Q6*100,"0.00") -> 74.044415
B7: ='APPENDIX 21'!B7 -> AFRICAN MERCHANT ASSURANCE | C7: =IFERROR('APPENDIX 21'!C7/NEPI!C7*100,"0.0") -> 0.0 | D7: =IFERROR('APPENDIX 21'!D7/NEPI!D7*100,"0.0") -> 118.34695 | E7: =IFERROR('APPENDIX 21'!E7/NEPI!E7*100,"0.0") -> 687.23691 | F7: =IFERROR('APPENDIX 21'!F7/NEPI!F7*100,"0.0") -> 145.85648 | G7: =IFERROR('APPENDIX 21'!G7/NEPI!G7*100,"0.0") -> 50.264687 | H7: =IFERROR('APPENDIX 21'!H7/NEPI!H7*100,"0.0") -> 176.35207 | I7: =IFERROR('APPENDIX 21'!I7/NEPI!I7*100,"0.0") -> 94.285568 | J7: =IFERROR('APPENDIX 21'!J7/NEPI!J7*100,"0.0") -> -281.02995 | ... P7: =IFERROR('APPENDIX 21'!P7/NEPI!P7*100,"0.0") -> 322.24056 | Q7: =IFERROR('APPENDIX 21'!Q7/NEPI!Q7*100,"0.00") -> 73.154832
B8: ='APPENDIX 21'!B8 -> APA INSURANCE LIMITED | C8: =IFERROR('APPENDIX 21'!C8/NEPI!C8*100,"0.0") -> -0.56929706 | D8: =IFERROR('APPENDIX 21'!D8/NEPI!D8*100,"0.0") -> 75.473121 | E8: =IFERROR('APPENDIX 21'!E8/NEPI!E8*100,"0.0") -> 79.915637 | F8: =IFERROR('APPENDIX 21'!F8/NEPI!F8*100,"0.0") -> 16.99919 | G8: =IFERROR('APPENDIX 21'!G8/NEPI!G8*100,"0.0") -> 140.42261 | H8: =IFERROR('APPENDIX 21'!H8/NEPI!H8*100,"0.0") -> 73.833879 | I8: =IFERROR('APPENDIX 21'!I8/NEPI!I8*100,"0.0") -> 79.996308 | J8: =IFERROR('APPENDIX 21'!J8/NEPI!J8*100,"0.0") -> 100.40219 | ... P8: =IFERROR('APPENDIX 21'!P8/NEPI!P8*100,"0.0") -> 25.970449 | Q8: =IFERROR('APPENDIX 21'!Q8/NEPI!Q8*100,"0.00") -> 72.78154
B9: ='APPENDIX 21'!B9 -> BRITAM GENERAL INSURANCE | C9: =IFERROR('APPENDIX 21'!C9/NEPI!C9*100,"0.0") -> 6.6058174 | D9: =IFERROR('APPENDIX 21'!D9/NEPI!D9*100,"0.0") -> 27.862903 | E9: =IFERROR('APPENDIX 21'!E9/NEPI!E9*100,"0.0") -> 19.714743 | F9: =IFERROR('APPENDIX 21'!F9/NEPI!F9*100,"0.0") -> 56.023634 | G9: =IFERROR('APPENDIX 21'!G9/NEPI!G9*100,"0.0") -> 32.357557 | H9: =IFERROR('APPENDIX 21'!H9/NEPI!H9*100,"0.0") -> 30.022918 | I9: =IFERROR('APPENDIX 21'!I9/NEPI!I9*100,"0.0") -> 66.834642 | J9: =IFERROR('APPENDIX 21'!J9/NEPI!J9*100,"0.0") -> 80.463748 | ... P9: =IFERROR('APPENDIX 21'!P9/NEPI!P9*100,"0.0") -> 109.02839 | Q9: =IFERROR('APPENDIX 21'!Q9/NEPI!Q9*100,"0.00") -> 67.487178
B10: ='APPENDIX 21'!B10 -> BUPA GLOBAL INSURANCE | C10: =IFERROR('APPENDIX 21'!C10/NEPI!C10*100,"0.0") -> 0.0 | D10: =IFERROR('APPENDIX 21'!D10/NEPI!D10*100,"0.0") -> 0.0 | E10: =IFERROR('APPENDIX 21'!E10/NEPI!E10*100,"0.0") -> 0.0 | F10: =IFERROR('APPENDIX 21'!F10/NEPI!F10*100,"0.0") -> 0.0 | G10: =IFERROR('APPENDIX 21'!G10/NEPI!G10*100,"0.0") -> 0.0 | H10: =IFERROR('APPENDIX 21'!H10/NEPI!H10*100,"0.0") -> 0.0 | I10: =IFERROR('APPENDIX 21'!I10/NEPI!I10*100,"0.0") -> 0.0 | J10: =IFERROR('APPENDIX 21'!J10/NEPI!J10*100,"0.0") -> 0.0 | ... P10: =IFERROR('APPENDIX 21'!P10/NEPI!P10*100,"0.0") -> 0.0 | Q10: =IFERROR('APPENDIX 21'!Q10/NEPI!Q10*100,"0.00") -> 71.528743
B11: ='APPENDIX 21'!B11 -> CANNON GENERAL INSURANCE | C11: =IFERROR('APPENDIX 21'!C11/NEPI!C11*100,"0.0") -> 0.0 | D11: =IFERROR('APPENDIX 21'!D11/NEPI!D11*100,"0.0") -> 17.646527 | E11: =IFERROR('APPENDIX 21'!E11/NEPI!E11*100,"0.0") -> 104.52472 | F11: =IFERROR('APPENDIX 21'!F11/NEPI!F11*100,"0.0") -> 23.303933 | G11: =IFERROR('APPENDIX 21'!G11/NEPI!G11*100,"0.0") -> 139.04179 | H11: =IFERROR('APPENDIX 21'!H11/NEPI!H11*100,"0.0") -> 41.335457 | I11: =IFERROR('APPENDIX 21'!I11/NEPI!I11*100,"0.0") -> 96.728862 | J11: =IFERROR('APPENDIX 21'!J11/NEPI!J11*100,"0.0") -> 73.113616 | ... P11: =IFERROR('APPENDIX 21'!P11/NEPI!P11*100,"0.0") -> -0.79216504 | Q11: =IFERROR('APPENDIX 21'!Q11/NEPI!Q11*100,"0.00") -> 90.248723
B12: ='APPENDIX 21'!B12 -> CIC GENERAL INSURANCE COMPANY | C12: =IFERROR('APPENDIX 21'!C12/NEPI!C12*100,"0.0") -> 0.0 | D12: =IFERROR('APPENDIX 21'!D12/NEPI!D12*100,"0.0") -> 25.864495 | E12: =IFERROR('APPENDIX 21'!E12/NEPI!E12*100,"0.0") -> 38.588762 | F12: =IFERROR('APPENDIX 21'!F12/NEPI!F12*100,"0.0") -> 45.569672 | G12: =IFERROR('APPENDIX 21'!G12/NEPI!G12*100,"0.0") -> 91.379096 | H12: =IFERROR('APPENDIX 21'!H12/NEPI!H12*100,"0.0") -> -50.676816 | I12: =IFERROR('APPENDIX 21'!I12/NEPI!I12*100,"0.0") -> 77.202108 | J12: =IFERROR('APPENDIX 21'!J12/NEPI!J12*100,"0.0") -> 83.124366 | ... P12: =IFERROR('APPENDIX 21'!P12/NEPI!P12*100,"0.0") -> 82.862006 | Q12: =IFERROR('APPENDIX 21'!Q12/NEPI!Q12*100,"0.00") -> 72.463069
B13: ='APPENDIX 21'!B13 -> CORPORATE INSURANCE COMPANY | C13: =IFERROR('APPENDIX 21'!C13/NEPI!C13*100,"0.0") -> 0.0 | D13: =IFERROR('APPENDIX 21'!D13/NEPI!D13*100,"0.0") -> 0.0 | E13: =IFERROR('APPENDIX 21'!E13/NEPI!E13*100,"0.0") -> 0.0 | F13: =IFERROR('APPENDIX 21'!F13/NEPI!F13*100,"0.0") -> 0.0 | G13: =IFERROR('APPENDIX 21'!G13/NEPI!G13*100,"0.0") -> 0.0 | H13: =IFERROR('APPENDIX 21'!H13/NEPI!H13*100,"0.0") -> 0.0 | I13: =IFERROR('APPENDIX 21'!I13/NEPI!I13*100,"0.0") -> 0.0 | J13: =IFERROR('APPENDIX 21'!J13/NEPI!J13*100,"0.0") -> 0.0 | ... P13: =IFERROR('APPENDIX 21'!P13/NEPI!P13*100,"0.0") -> 0.0 | Q13: =IFERROR('APPENDIX 21'!Q13/NEPI!Q13*100,"0.00") -> 0.00
B14: ='APPENDIX 21'!B14 -> DEFINITE ASSURANCE COMPANY | C14: =IFERROR('APPENDIX 21'!C14/NEPI!C14*100,"0.0") -> 0.0 | D14: =IFERROR('APPENDIX 21'!D14/NEPI!D14*100,"0.0") -> 0 | E14: =IFERROR('APPENDIX 21'!E14/NEPI!E14*100,"0.0") -> 0 | F14: =IFERROR('APPENDIX 21'!F14/NEPI!F14*100,"0.0") -> 0 | G14: =IFERROR('APPENDIX 21'!G14/NEPI!G14*100,"0.0") -> 0 | H14: =IFERROR('APPENDIX 21'!H14/NEPI!H14*100,"0.0") -> 0 | I14: =IFERROR('APPENDIX 21'!I14/NEPI!I14*100,"0.0") -> 44.312936 | J14: =IFERROR('APPENDIX 21'!J14/NEPI!J14*100,"0.0") -> 10.866873 | ... P14: =IFERROR('APPENDIX 21'!P14/NEPI!P14*100,"0.0") -> -0.23763879 | Q14: =IFERROR('APPENDIX 21'!Q14/NEPI!Q14*100,"0.00") -> 39.216384
B15: ='APPENDIX 21'!B15 -> DIRECTLINE ASSURANCE COMPANY | C15: =IFERROR('APPENDIX 21'!C15/NEPI!C15*100,"0.0") -> 0.0 | D15: =IFERROR('APPENDIX 21'!D15/NEPI!D15*100,"0.0") -> 0.0 | E15: =IFERROR('APPENDIX 21'!E15/NEPI!E15*100,"0.0") -> 4907.9748 | F15: =IFERROR('APPENDIX 21'!F15/NEPI!F15*100,"0.0") -> 2.7056169 | G15: =IFERROR('APPENDIX 21'!G15/NEPI!G15*100,"0.0") -> -1434.3784 | H15: =IFERROR('APPENDIX 21'!H15/NEPI!H15*100,"0.0") -> 0 | I15: =IFERROR('APPENDIX 21'!I15/NEPI!I15*100,"0.0") -> 125.75772 | J15: =IFERROR('APPENDIX 21'!J15/NEPI!J15*100,"0.0") -> 102.5943 | ... P15: =IFERROR('APPENDIX 21'!P15/NEPI!P15*100,"0.0") -> -4.4253193 | Q15: =IFERROR('APPENDIX 21'!Q15/NEPI!Q15*100,"0.00") -> 88.30721
B16: ='APPENDIX 21'!B16 -> EQUITY GENERAL INSURANCE LIMITED | C16: =IFERROR('APPENDIX 21'!C16/NEPI!C16*100,"0.0") -> 0.0 | D16: =IFERROR('APPENDIX 21'!D16/NEPI!D16*100,"0.0") -> 0 | E16: =IFERROR('APPENDIX 21'!E16/NEPI!E16*100,"0.0") -> 0 | F16: =IFERROR('APPENDIX 21'!F16/NEPI!F16*100,"0.0") -> 0 | G16: =IFERROR('APPENDIX 21'!G16/NEPI!G16*100,"0.0") -> 0.25310997 | H16: =IFERROR('APPENDIX 21'!H16/NEPI!H16*100,"0.0") -> 0 | I16: =IFERROR('APPENDIX 21'!I16/NEPI!I16*100,"0.0") -> 0.0 | J16: =IFERROR('APPENDIX 21'!J16/NEPI!J16*100,"0.0") -> 0.0 | ... P16: =IFERROR('APPENDIX 21'!P16/NEPI!P16*100,"0.0") -> 0 | Q16: =IFERROR('APPENDIX 21'!Q16/NEPI!Q16*100,"0.00") -> 64.58946
B17: ='APPENDIX 21'!B17 -> EQUITY HEALTH INSURANCE LIMITED | C17: =IFERROR('APPENDIX 21'!C17/NEPI!C17*100,"0.0") -> 0.0 | D17: =IFERROR('APPENDIX 21'!D17/NEPI!D17*100,"0.0") -> 0.0 | E17: =IFERROR('APPENDIX 21'!E17/NEPI!E17*100,"0.0") -> 0.0 | F17: =IFERROR('APPENDIX 21'!F17/NEPI!F17*100,"0.0") -> 0.0 | G17: =IFERROR('APPENDIX 21'!G17/NEPI!G17*100,"0.0") -> 0.0 | H17: =IFERROR('APPENDIX 21'!H17/NEPI!H17*100,"0.0") -> 0.0 | I17: =IFERROR('APPENDIX 21'!I17/NEPI!I17*100,"0.0") -> 0.0 | J17: =IFERROR('APPENDIX 21'!J17/NEPI!J17*100,"0.0") -> 0.0 | ... P17: =IFERROR('APPENDIX 21'!P17/NEPI!P17*100,"0.0") -> 0.0 | Q17: =IFERROR('APPENDIX 21'!Q17/NEPI!Q17*100,"0.00") -> 164.98868
... B42: ='APPENDIX 21'!B42 -> TRIDENT INSURANCE COMPANY | C42: =IFERROR('APPENDIX 21'!C42/NEPI!C42*100,"0.0") -> 0.0 | D42: =IFERROR('APPENDIX 21'!D42/NEPI!D42*100,"0.0") -> 0.0 | E42: =IFERROR('APPENDIX 21'!E42/NEPI!E42*100,"0.0") -> 0.0 | F42: =IFERROR('APPENDIX 21'!F42/NEPI!F42*100,"0.0") -> 0.0 | G42: =IFERROR('APPENDIX 21'!G42/NEPI!G42*100,"0.0") -> 0.0 | H42: =IFERROR('APPENDIX 21'!H42/NEPI!H42*100,"0.0") -> 0.0 | I42: =IFERROR('APPENDIX 21'!I42/NEPI!I42*100,"0.0") -> 0.0 | J42: =IFERROR('APPENDIX 21'!J42/NEPI!J42*100,"0.0") -> 0.0 | ... P42: =IFERROR('APPENDIX 21'!P42/NEPI!P42*100,"0.0") -> 0.0 | Q42: =IFERROR('APPENDIX 21'!Q42/NEPI!Q42*100,"0.00") -> 0.00
B43: TOTAL | C43: =IFERROR('APPENDIX 21'!C43/NEPI!C43*100,"0.0") -> 62.014314 | D43: =IFERROR('APPENDIX 21'!D43/NEPI!D43*100,"0.0") -> 44.609918 | E43: =IFERROR('APPENDIX 21'!E43/NEPI!E43*100,"0.0") -> 33.82569 | F43: =IFERROR('APPENDIX 21'!F43/NEPI!F43*100,"0.0") -> 25.317625 | G43: =IFERROR('APPENDIX 21'!G43/NEPI!G43*100,"0.0") -> 49.858662 | H43: =IFERROR('APPENDIX 21'!H43/NEPI!H43*100,"0.0") -> 32.777438 | I43: =IFERROR('APPENDIX 21'!I43/NEPI!I43*100,"0.0") -> 73.573379 | J43: =IFERROR('APPENDIX 21'!J43/NEPI!J43*100,"0.0") -> 69.709299 | ... Q43: =IFERROR('APPENDIX 21'!Q43/NEPI!Q43*100,"0.0") -> 69.753144
B44: ='APPENDIX 21'!B44 -> REINSURERS
